{
  "type": "Feature",
  "properties": {
    "gn:admin1_code":"17",
    "gn:asciiname":"Nazlat al `Adrah",
    "gn:country_code":"EG",
    "gn:dem":47,
    "gn:feature_class":"P",
    "gn:feature_code":"PPL",
    "gn:name":"Nazlat al \u2018Adrah",
    "gn:population":0,
    "gn:timezone":"Africa/Cairo",
    "iso:country":"EG",
    "name:und_x_variant":[
        "Nazlet el \u2018Adra",
        "Nazlat al \u2018Adrah"
    ],
    "wof:name":"Nazlat al `Adrah",
    "wof:placetype":"locality"
},
  "geometry": {"coordinates":[31.03333,27.33333],"type":"Point"}
}