{
  "type": "Feature",
  "properties": {
    "gn:admin1_code":"04",
    "gn:asciiname":"`Izbat al Qasr",
    "gn:country_code":"EG",
    "gn:dem":-26,
    "gn:feature_class":"P",
    "gn:feature_code":"PPL",
    "gn:name":"\u2018Izbat al Qa\u015fr",
    "gn:population":0,
    "gn:timezone":"Africa/Cairo",
    "iso:country":"EG",
    "wof:name":"`Izbat al Qasr",
    "wof:placetype":"locality"
},
  "geometry": {"coordinates":[30.90799,29.50164],"type":"Point"}
}