{
  "type": "Feature",
  "properties": {
    "gn:admin1_code":"27",
    "gn:asciiname":"Al Wifaq",
    "gn:country_code":"EG",
    "gn:dem":62,
    "gn:feature_class":"P",
    "gn:feature_code":"PPL",
    "gn:name":"Al Wif\u0101q",
    "gn:population":0,
    "gn:timezone":"Africa/Cairo",
    "iso:country":"EG",
    "name:ara_x_preferred":[
        "Al Wif\u0101q"
    ],
    "name:ara_x_variant":[
        "\u0627\u0644\u0648\u0641\u0627\u0642"
    ],
    "name:und_x_variant":[
        "Wofag"
    ],
    "wof:name":"Al Wifaq",
    "wof:placetype":"locality"
},
  "geometry": {"coordinates":[34.16088,31.21802000000001],"type":"Point"}
}