{
  "type": "Feature",
  "properties": {
    "gn:admin1_code":"14",
    "gn:asciiname":"Al `Awamirah",
    "gn:country_code":"EG",
    "gn:dem":13,
    "gn:feature_class":"P",
    "gn:feature_code":"PPL",
    "gn:name":"Al \u2018Aw\u0101mirah",
    "gn:population":0,
    "gn:timezone":"Africa/Cairo",
    "iso:country":"EG",
    "name:ara_x_preferred":[
        "\u0627\u0644\u0639\u0648\u0627\u0645\u0631\u0629"
    ],
    "name:und_x_variant":[
        "Al \u2018Aw\u0101mirah",
        "Al \u2018Aw\u0101mrah"
    ],
    "wof:name":"Al `Awamirah",
    "wof:placetype":"locality"
},
  "geometry": {"coordinates":[31.70707,30.68126],"type":"Point"}
}