{
  "type": "Feature",
  "properties": {
    "gn:admin1_code":"10",
    "gn:asciiname":"Ash Shaykh Timay",
    "gn:country_code":"EG",
    "gn:dem":49,
    "gn:feature_class":"P",
    "gn:feature_code":"PPL",
    "gn:name":"Ash Shaykh Timay",
    "gn:population":0,
    "gn:timezone":"Africa/Cairo",
    "iso:country":"EG",
    "name:und_x_variant":[
        "Esh Sheikh Timai",
        "El Sheikh Timai",
        "Ash Shaykh Timay"
    ],
    "wof:name":"Ash Shaykh Timay",
    "wof:placetype":"locality"
},
  "geometry": {"coordinates":[30.84217,27.86708],"type":"Point"}
}