{
  "type": "Feature",
  "properties": {
    "gn:admin1_code":"04",
    "gn:asciiname":"`Izbat Salam",
    "gn:country_code":"EG",
    "gn:dem":14,
    "gn:feature_class":"P",
    "gn:feature_code":"PPL",
    "gn:name":"\u2018Izbat Sal\u0101m",
    "gn:population":0,
    "gn:timezone":"Africa/Cairo",
    "iso:country":"EG",
    "wof:name":"`Izbat Salam",
    "wof:placetype":"locality"
},
  "geometry": {"coordinates":[30.7775,29.12902],"type":"Point"}
}