{
  "type": "Feature",
  "properties": {
    "gn:admin1_code":"21",
    "gn:asciiname":"Burayd",
    "gn:country_code":"EG",
    "gn:dem":8,
    "gn:feature_class":"P",
    "gn:feature_code":"PPL",
    "gn:name":"Burayd",
    "gn:population":0,
    "gn:timezone":"Africa/Cairo",
    "iso:country":"EG",
    "name:ara_x_preferred":[
        "\u0628\u0631\u064a\u062f"
    ],
    "name:und_x_variant":[
        "Bureid",
        "Burayd"
    ],
    "wof:name":"Burayd",
    "wof:placetype":"locality"
},
  "geometry": {"coordinates":[30.85761,31.21408],"type":"Point"}
}