{
  "type": "Feature",
  "properties": {
    "gn:admin1_code":"04",
    "gn:asciiname":"Al Hadiqah",
    "gn:country_code":"EG",
    "gn:dem":24,
    "gn:feature_class":"P",
    "gn:feature_code":"PPL",
    "gn:name":"Al \u1e28\u0101diqah",
    "gn:population":0,
    "gn:timezone":"Africa/Cairo",
    "iso:country":"EG",
    "name:und_x_variant":[
        "El H\u00e2dqa",
        "Al \u1e28\u0101diqah"
    ],
    "wof:name":"Al Hadiqah",
    "wof:placetype":"locality"
},
  "geometry": {"coordinates":[30.84093,29.27255],"type":"Point"}
}