{
  "type": "Feature",
  "properties": {
    "gn:admin1_code":"24",
    "gn:asciiname":"Al Khazandariyah",
    "gn:country_code":"EG",
    "gn:dem":63,
    "gn:feature_class":"P",
    "gn:feature_code":"PPL",
    "gn:name":"Al Khazand\u0101r\u012byah",
    "gn:population":0,
    "gn:timezone":"Africa/Cairo",
    "iso:country":"EG",
    "name:und_x_variant":[
        "El Khizind\u0101r\u012bya",
        "El Khazind\u00e2r\u00eeya",
        "Al Khazand\u0101r\u012byah"
    ],
    "wof:name":"Al Khazandariyah",
    "wof:placetype":"locality"
},
  "geometry": {"coordinates":[31.54269,26.78458],"type":"Point"}
}