{
  "type": "Feature",
  "properties": {
    "gn:admin1_code":"09",
    "gn:asciiname":"Kamshush",
    "gn:country_code":"EG",
    "gn:dem":18,
    "gn:feature_class":"P",
    "gn:feature_code":"PPL",
    "gn:name":"Kamsh\u016bsh",
    "gn:population":0,
    "gn:timezone":"Africa/Cairo",
    "iso:country":"EG",
    "name:ara_x_preferred":[
        "\u0643\u0645\u0634\u0648\u0634"
    ],
    "name:und_x_variant":[
        "Kemshish",
        "Kamsh\u016bsh"
    ],
    "wof:name":"Kamshush",
    "wof:placetype":"locality"
},
  "geometry": {"coordinates":[30.93166,30.41638],"type":"Point"}
}