{
  "type": "Feature",
  "properties": {
    "gn:admin1_code":"03",
    "gn:asciiname":"Al Ghaffarah",
    "gn:country_code":"EG",
    "gn:dem":4,
    "gn:feature_class":"P",
    "gn:feature_code":"PPL",
    "gn:name":"Al Ghaff\u0101rah",
    "gn:population":0,
    "gn:timezone":"Africa/Cairo",
    "iso:country":"EG",
    "name:ara_x_preferred":[
        "\u0627\u0644\u063a\u0641\u0627\u0631\u0629"
    ],
    "name:und_x_variant":[
        "Al Ghaff\u0101rah",
        "Al-Ghaff\u0101rah"
    ],
    "wof:name":"Al Ghaffarah",
    "wof:placetype":"locality"
},
  "geometry": {"coordinates":[30.51482,31.0288],"type":"Point"}
}