{
  "type": "Feature",
  "properties": {
    "gn:admin1_code":"03",
    "gn:asciiname":"`Izbat Hulayyil",
    "gn:country_code":"EG",
    "gn:dem":2,
    "gn:feature_class":"P",
    "gn:feature_code":"PPL",
    "gn:name":"\u2018Izbat Hulayyil",
    "gn:population":0,
    "gn:timezone":"Africa/Cairo",
    "iso:country":"EG",
    "name:ara_x_preferred":[
        "\u0639\u0632\u0628\u0629 \u0647\u0644\u064a\u0644"
    ],
    "name:und_x_variant":[
        "\u2018Ezbet Yunis Mu\u1e25ammad",
        "\u2018Ezbet Kuraiyim Hil\u00e2iyil",
        "\u2018Izbat Kurayyim Hulayyil",
        "\u2018Izbat Hulayyil",
        "\u2018Izbat Hulayl"
    ],
    "wof:name":"`Izbat Hulayyil",
    "wof:placetype":"locality"
},
  "geometry": {"coordinates":[30.4864,31.09317],"type":"Point"}
}