{
  "type": "Feature",
  "properties": {
    "gn:admin1_code":"13",
    "gn:asciiname":"`Ezbet el-Sha`abna",
    "gn:country_code":"EG",
    "gn:dem":63,
    "gn:feature_class":"P",
    "gn:feature_code":"PPL",
    "gn:name":"\u2018Ezbet el-Sha\u2018\u00e2bna",
    "gn:population":0,
    "gn:timezone":"Africa/Cairo",
    "iso:country":"EG",
    "wof:name":"`Ezbet el-Sha`abna",
    "wof:placetype":"locality"
},
  "geometry": {"coordinates":[30.60487,25.57825],"type":"Point"}
}