{
  "type": "Feature",
  "properties": {
    "gn:admin1_code":"08",
    "gn:asciiname":"`Ezbet el-Khassa",
    "gn:country_code":"EG",
    "gn:dem":21,
    "gn:feature_class":"P",
    "gn:feature_code":"PPL",
    "gn:name":"\u2018Ezbet el-Kh\u00e2\u1e63\u1e63a",
    "gn:population":0,
    "gn:timezone":"Africa/Cairo",
    "iso:country":"EG",
    "wof:name":"`Ezbet el-Khassa",
    "wof:placetype":"locality"
},
  "geometry": {"coordinates":[31.23333,29.76667],"type":"Point"}
}