{
  "type": "Feature",
  "properties": {
    "gn:admin1_code":"03",
    "gn:asciiname":"`Izbat Muhammad Salamah",
    "gn:country_code":"EG",
    "gn:dem":-2,
    "gn:feature_class":"P",
    "gn:feature_code":"PPL",
    "gn:name":"\u2018Izbat Mu\u1e29ammad Sal\u0101mah",
    "gn:population":0,
    "gn:timezone":"Africa/Cairo",
    "iso:country":"EG",
    "name:ara_x_preferred":[
        "\u0639\u0632\u0628\u0629 \u0645\u062d\u0645\u062f \u0633\u0644\u0627\u0645\u0629"
    ],
    "name:und_x_variant":[
        "\u2018Izbat Mu\u1e29ammad Sal\u0101mah",
        "\u2018Izbat Mu\u1e25ammad Sal\u0101mah"
    ],
    "wof:name":"`Izbat Muhammad Salamah",
    "wof:placetype":"locality"
},
  "geometry": {"coordinates":[30.44324000000001,31.23524],"type":"Point"}
}