{
  "type": "Feature",
  "properties": {
    "gn:admin1_code":"21",
    "gn:asciiname":"Al Ab`adiyah",
    "gn:country_code":"EG",
    "gn:dem":6,
    "gn:feature_class":"P",
    "gn:feature_code":"PPL",
    "gn:name":"Al Ab\u2018\u0101d\u012byah",
    "gn:population":0,
    "gn:timezone":"Africa/Cairo",
    "iso:country":"EG",
    "name:ara_x_preferred":[
        "\u0627\u0644\u0627\u0628\u0639\u0627\u062f\u064a\u0629"
    ],
    "name:ara_x_variant":[
        "\u0627\u0644\u0627\u0628\u0639\u0627\u062f\u064a\u0629 \u0627\u0644\u0628\u062d\u0631\u064a\u0629"
    ],
    "name:und_x_variant":[
        "El-Ab\u2018\u00e2d\u00eeya",
        "Al Ab\u2018\u0101d\u012byah",
        "Al Ab\u2018\u0101d\u012byah Al Bahariyah"
    ],
    "wof:name":"Al Ab`adiyah",
    "wof:placetype":"locality"
},
  "geometry": {"coordinates":[31.11823,31.37448],"type":"Point"}
}