{
  "type": "Feature",
  "properties": {
    "gn:admin1_code":"03",
    "gn:asciiname":"Kawm Dilinjat",
    "gn:country_code":"EG",
    "gn:dem":7,
    "gn:feature_class":"P",
    "gn:feature_code":"PPL",
    "gn:name":"Kawm Dilinj\u0101t",
    "gn:population":0,
    "gn:timezone":"Africa/Cairo",
    "iso:country":"EG",
    "wof:name":"Kawm Dilinjat",
    "wof:placetype":"locality"
},
  "geometry": {"coordinates":[30.51988,30.82531],"type":"Point"}
}