{
  "type": "Feature",
  "properties": {
    "iso:country":"EG",
    "name:eng_x_preferred":[
        "Ad-darb Al-ahmar"
    ],
    "qs:gn_adm0_cc":"EG",
    "qs:gn_local":360630,
    "qs:gn_nam_loc":"\u0627\u0644\u0642\u0627\u0647\u0631\u0629, \u0627\u0644\u0642\u0627\u0647\u0631\u0629, EG",
    "qs:gn_namadm1":"11",
    "qs:local_max":6277,
    "qs:local_sum":54808,
    "qs:localhoods":36,
    "qs:name":"Ad-darb Al-ahmar",
    "qs:name_adm0":"\u0645\u0635\u0631",
    "qs:name_adm1":"\u0627\u0644\u0642\u0627\u0647\u0631\u0629",
    "qs:name_local":"\u0627\u0644\u0642\u0627\u0647\u0631\u0629",
    "qs:photo_max":397,
    "qs:photo_sum":2500,
    "qs:placetype":"Suburb",
    "qs:quad_count":47,
    "qs:woe_adm0":23424802,
    "qs:woe_adm1":2345233,
    "qs:woe_adm2":0,
    "qs:woe_lau":0,
    "qs:woe_local":1521894,
    "qs:woe_ver":"7.10.0",
    "wof:lang":[
        "eng"
    ],
    "wof:name":"Ad-darb Al-ahmar",
    "wof:placetype":"neighbourhood"
},
  "geometry": {"coordinates":[31.260185,30.042119],"type":"Point"}
}