{
  "type": "Feature",
  "properties": {
    "gn:admin1_code":"01",
    "gn:asciiname":"As Sabriyah",
    "gn:country_code":"EG",
    "gn:dem":5,
    "gn:feature_class":"P",
    "gn:feature_code":"PPL",
    "gn:name":"A\u015f \u015eabr\u012byah",
    "gn:population":0,
    "gn:timezone":"Africa/Cairo",
    "iso:country":"EG",
    "name:ara_x_preferred":[
        "\u0639\u0632\u0628\u0629 \u0627\u0644\u0635\u0628\u0631\u064a\u0629"
    ],
    "name:und_x_variant":[
        "El-\u1e62abr\u00eeya",
        "A\u015f \u015eabr\u012byah",
        "\u2018Iz. a\u1e63-\u1e62abriyyah"
    ],
    "wof:name":"As Sabriyah",
    "wof:placetype":"locality"
},
  "geometry": {"coordinates":[31.57751,31.222],"type":"Point"}
}