{
  "type": "Feature",
  "properties": {
    "gn:admin1_code":"3.0",
    "gn:asciiname":"Zumran an Nakhl",
    "gn:cc2":"EG",
    "gn:country_code":"EG",
    "gn:dem":8,
    "gn:feature_class":"P",
    "gn:feature_code":"PPL",
    "gn:name":"Zumr\u0101n an Nakhl",
    "gn:population":0,
    "gn:timezone":"Africa/Cairo",
    "iso:country":"EG",
    "name:ara_x_preferred":[
        "\u0632\u0645\u0631\u0627\u0646 \u0627\u0644\u0646\u062e\u0644"
    ],
    "name:und_x_variant":[
        "Zimr\u00e2n en-Nakhl",
        "Zumr\u00e2n el-Nakhl",
        "Zumr\u0101n an Nakhl"
    ],
    "wof:name":"Zumran an Nakhl",
    "wof:placetype":"locality"
},
  "geometry": {"coordinates":[30.55917,30.82472000000001],"type":"Point"}
}