{
  "type": "Feature",
  "properties": {
    "gn:country":"EG",
    "gn:fcode":"PPL",
    "gn:population":15000,
    "iso:country":"EG",
    "name:ara_x_preferred":[
        "\u0627\u0644\u062c\u0648\u0646\u0629"
    ],
    "name:arz_x_preferred":[
        "\u0627\u0644\u062c\u0648\u0646\u0647"
    ],
    "name:bul_x_preferred":[
        "\u0415\u043b \u0413\u0443\u043d\u0430"
    ],
    "name:cat_x_preferred":[
        "El Gouna"
    ],
    "name:ceb_x_preferred":[
        "El Gouna"
    ],
    "name:deu_x_preferred":[
        "El Gouna"
    ],
    "name:eng_x_preferred":[
        "El Gouna"
    ],
    "name:epo_x_preferred":[
        "El Gouna"
    ],
    "name:fas_x_preferred":[
        "\u0627\u0644\u062c\u0648\u0646\u0647"
    ],
    "name:fin_x_preferred":[
        "El Gouna"
    ],
    "name:fra_x_preferred":[
        "El Gouna"
    ],
    "name:hye_x_preferred":[
        "\u0537\u056c \u0533\u0578\u0582\u0576\u0561"
    ],
    "name:ita_x_preferred":[
        "El Gouna"
    ],
    "name:jpn_x_preferred":[
        "\u30a8\u30eb\u30fb\u30b0\u30a6\u30ca"
    ],
    "name:nld_x_preferred":[
        "El Gouna"
    ],
    "name:nob_x_preferred":[
        "El Gouna"
    ],
    "name:pol_x_preferred":[
        "Al-D\u017cuna"
    ],
    "name:ron_x_preferred":[
        "El Gouna"
    ],
    "name:rus_x_preferred":[
        "\u042d\u043b\u044c-\u0413\u0443\u043d\u0430"
    ],
    "name:spa_x_preferred":[
        "El Gouna"
    ],
    "name:swe_x_preferred":[
        "El Gouna"
    ],
    "name:tur_x_preferred":[
        "El-C\u00fbna"
    ],
    "name:ukr_x_preferred":[
        "\u0415\u043b\u044c-\u0413\u0443\u043d\u0430"
    ],
    "name:urd_x_preferred":[
        "\u0627\u0644\u062c\u0648\u0646\u06c1"
    ],
    "name:uzb_x_preferred":[
        "El-Guna"
    ],
    "name:zho_x_preferred":[
        "\u827e\u723e\u53e4\u7d0d"
    ],
    "qs_pg:aaroncc":"EG",
    "qs_pg:gn_country":"EG",
    "qs_pg:gn_fcode":"PPL",
    "qs_pg:gn_pop":15000,
    "qs_pg:name":"El Gouna",
    "qs_pg:photos_9r":0,
    "qs_pg:photos_sr":0,
    "qs_pg:pop_sr":6,
    "qs_pg:qs_pg_placetype":"locality",
    "wof:name":"El Gouna",
    "wof:placetype":"locality",
    "wof:population":15000
},
  "geometry": {"coordinates":[33.67825,27.39417],"type":"Point"}
}