{
  "type": "Feature",
  "properties": {
    "gn:admin1_code":"03",
    "gn:asciiname":"`Ezbet el-Sharika `elwel-Biljikiya",
    "gn:country_code":"EG",
    "gn:dem":0,
    "gn:feature_class":"P",
    "gn:feature_code":"PPL",
    "gn:name":"\u2018Ezbet el-Sharika \u2018elwel-Bilj\u00eek\u00eeya",
    "gn:population":0,
    "gn:timezone":"Africa/Cairo",
    "iso:country":"EG",
    "wof:name":"`Ezbet el-Sharika `elwel-Biljikiya",
    "wof:placetype":"locality"
},
  "geometry": {"coordinates":[30.23028,30.91833],"type":"Point"}
}