{
  "type": "Feature",
  "properties": {
    "gn:admin1_code":"12",
    "gn:asciiname":"Shubra Shihab",
    "gn:country_code":"EG",
    "gn:dem":17,
    "gn:feature_class":"P",
    "gn:feature_code":"PPL",
    "gn:name":"Shubr\u0101 Shih\u0101b",
    "gn:population":0,
    "gn:timezone":"Africa/Cairo",
    "iso:country":"EG",
    "name:ara_x_preferred":[
        "Shubr\u0101 Shih\u0101b"
    ],
    "name:ara_x_variant":[
        "\u0634\u0628\u0631\u0627 \u0634\u0628\u0647\u0627\u0628"
    ],
    "wof:name":"Shubra Shihab",
    "wof:placetype":"locality"
},
  "geometry": {"coordinates":[31.10946,30.27868],"type":"Point"}
}