{
  "type": "Feature",
  "properties": {
    "gn:admin1_code":"03",
    "gn:asciiname":"`Izbat Salim `Abbud",
    "gn:country_code":"EG",
    "gn:dem":10,
    "gn:feature_class":"P",
    "gn:feature_code":"PPL",
    "gn:name":"\u2018Izbat Sal\u012bm \u2018Abb\u016bd",
    "gn:population":0,
    "gn:timezone":"Africa/Cairo",
    "iso:country":"EG",
    "name:ara_x_preferred":[
        "\u0639\u0632\u0628\u0629 \u0633\u0644\u064a\u0645 \u0639\u0628\u0648\u062f"
    ],
    "name:und_x_variant":[
        "\u2018Izbat Sal\u012bm \u2018Abb\u016bd",
        "\u2018Izbat Sil\u012bm \u2018Abb\u016bd"
    ],
    "wof:name":"`Izbat Salim `Abbud",
    "wof:placetype":"locality"
},
  "geometry": {"coordinates":[30.81433,30.48131],"type":"Point"}
}