{
  "type": "Feature",
  "properties": {
    "gn:admin1_code":"21",
    "gn:asciiname":"Bani Bakkar",
    "gn:country_code":"EG",
    "gn:dem":1,
    "gn:feature_class":"P",
    "gn:feature_code":"PPL",
    "gn:name":"Ban\u012b Bakk\u0101r",
    "gn:population":0,
    "gn:timezone":"Africa/Cairo",
    "iso:country":"EG",
    "name:ara_x_preferred":[
        "\u0628\u0646\u064a \u0628\u0643\u0627\u0631"
    ],
    "name:und_x_variant":[
        "Beni Bakk\u00e2r el-Ba\u1e25ar\u00eeya",
        "Ban\u012b Bakk\u0101r al Ba\u1e29r\u012byah",
        "Ban\u012b Bakk\u0101r",
        "Beni Bakk\u00e2r el-Qibl\u00eeya",
        "Beni Bakk\u00e2i el-Qibl\u00eeya",
        "Ban\u012b Bakk\u0101r al Qibl\u012byah"
    ],
    "wof:name":"Bani Bakkar",
    "wof:placetype":"locality"
},
  "geometry": {"coordinates":[30.58547,31.32909],"type":"Point"}
}