{
  "type": "Feature",
  "properties": {
    "gn:admin1_code":"20",
    "gn:asciiname":"Al Birashiyah",
    "gn:country_code":"EG",
    "gn:dem":5,
    "gn:feature_class":"P",
    "gn:feature_code":"PPL",
    "gn:name":"Al Bir\u0101sh\u012byah",
    "gn:population":0,
    "gn:timezone":"Africa/Cairo",
    "iso:country":"EG",
    "name:ara_x_preferred":[
        "\u0627\u0644\u0628\u0631\u0627\u0634\u064a\u0629"
    ],
    "name:und_x_variant":[
        "El-Bir\u00e2shiya",
        "Al Brashieh",
        "El-Bir\u00fbsh\u00eeya",
        "El Brashieh",
        "Al Bir\u0101sh\u012byah"
    ],
    "wof:name":"Al Birashiyah",
    "wof:placetype":"locality"
},
  "geometry": {"coordinates":[31.68302000000001,31.26451],"type":"Point"}
}