{
  "type": "Feature",
  "properties": {
    "gn:admin1_code":"9.0",
    "gn:asciiname":"Tanbisha",
    "gn:country_code":"EG",
    "gn:dem":15,
    "gn:feature_class":"P",
    "gn:feature_code":"PPL",
    "gn:name":"\u0162anbish\u0101",
    "gn:population":0,
    "gn:timezone":"Africa/Cairo",
    "iso:country":"EG",
    "name:ara_x_preferred":[
        "\u0637\u0646\u0628\u0634\u0627"
    ],
    "name:und_x_variant":[
        "Tanbesha",
        "\u1e6cambisha",
        "\u0162anbish\u0101"
    ],
    "wof:name":"Tanbisha",
    "wof:placetype":"locality"
},
  "geometry": {"coordinates":[31.08733,30.60296],"type":"Point"}
}