{
  "type": "Feature",
  "properties": {
    "gn:admin1_code":"03",
    "gn:asciiname":"`Izbat `Asharah",
    "gn:country_code":"EG",
    "gn:dem":-1,
    "gn:feature_class":"P",
    "gn:feature_code":"PPL",
    "gn:name":"\u2018Izbat \u2018Asharah",
    "gn:population":0,
    "gn:timezone":"Africa/Cairo",
    "iso:country":"EG",
    "name:ara_x_preferred":[
        "\u0639\u0632\u0628\u0629 \u06f1\u06f0"
    ],
    "name:und_x_variant":[
        "\u2018Izbat \u2018Asharah",
        "\u2018Izbat 10",
        "\u2018Izbat Ten"
    ],
    "wof:name":"`Izbat `Asharah",
    "wof:placetype":"locality"
},
  "geometry": {"coordinates":[30.41262,31.2121],"type":"Point"}
}