{
  "type": "Feature",
  "properties": {
    "gn:admin1_code":"12",
    "gn:asciiname":"Nisf Atrib",
    "gn:country_code":"EG",
    "gn:dem":15,
    "gn:feature_class":"P",
    "gn:feature_code":"PPL",
    "gn:name":"Ni\u015ff Atr\u012bb",
    "gn:population":0,
    "gn:timezone":"Africa/Cairo",
    "iso:country":"EG",
    "wof:name":"Nisf Atrib",
    "wof:placetype":"locality"
},
  "geometry": {"coordinates":[31.18333,30.46667],"type":"Point"}
}