{
  "type": "Feature",
  "properties": {
    "gn:admin1_code":"10",
    "gn:asciiname":"Qufadah",
    "gn:country_code":"EG",
    "gn:dem":155,
    "gn:feature_class":"P",
    "gn:feature_code":"PPL",
    "gn:name":"Quf\u0101dah",
    "gn:population":0,
    "gn:timezone":"Africa/Cairo",
    "iso:country":"EG",
    "wof:name":"Qufadah",
    "wof:placetype":"locality"
},
  "geometry": {"coordinates":[30.25139,28.58056],"type":"Point"}
}