{
  "type": "Feature",
  "properties": {
    "gn:admin1_code":"03",
    "gn:asciiname":"`Izbat Amin `Allubah",
    "gn:country_code":"EG",
    "gn:dem":-1,
    "gn:feature_class":"P",
    "gn:feature_code":"PPL",
    "gn:name":"\u2018Izbat Am\u012bn \u2018All\u016bbah",
    "gn:population":0,
    "gn:timezone":"Africa/Cairo",
    "iso:country":"EG",
    "wof:name":"`Izbat Amin `Allubah",
    "wof:placetype":"locality"
},
  "geometry": {"coordinates":[30.13813,30.9338],"type":"Point"}
}