{
  "type": "Feature",
  "properties": {
    "gn:admin1_code":"21",
    "gn:asciiname":"`Izbat Mahmud",
    "gn:country_code":"EG",
    "gn:dem":3,
    "gn:feature_class":"P",
    "gn:feature_code":"PPL",
    "gn:name":"\u2018Izbat Ma\u1e29m\u016bd",
    "gn:population":0,
    "gn:timezone":"Africa/Cairo",
    "iso:country":"EG",
    "name:ara_x_preferred":[
        "\u0639\u0632\u0628\u0629 \u0645\u062d\u0645\u0648\u062f"
    ],
    "name:und_x_variant":[
        "\u2018Izbat Ma\u1e29m\u016bd"
    ],
    "wof:name":"`Izbat Mahmud",
    "wof:placetype":"locality"
},
  "geometry": {"coordinates":[30.67493,31.28098],"type":"Point"}
}