{
  "type": "Feature",
  "properties": {
    "gn:admin1_code":"03",
    "gn:asciiname":"`Izbat as Sayyid Sulayman Makram",
    "gn:country_code":"EG",
    "gn:dem":5,
    "gn:feature_class":"P",
    "gn:feature_code":"PPL",
    "gn:name":"\u2018Izbat as Sayyid Sulaym\u0101n Makram",
    "gn:population":0,
    "gn:timezone":"Africa/Cairo",
    "iso:country":"EG",
    "name:ara_x_preferred":[
        "\u0639\u0632\u0628\u0629 \u0627\u0644\u0633\u064a\u062f \u0633\u0644\u064a\u0645\u0627\u0646 \u0645\u0643\u0631\u0645"
    ],
    "name:und_x_variant":[
        "\u2018Izbat as Sayyid Sulaym\u0101n Makram",
        "\u2018Izbat as- Sayyid Sulaym\u0101n Makram"
    ],
    "wof:name":"`Izbat as Sayyid Sulayman Makram",
    "wof:placetype":"locality"
},
  "geometry": {"coordinates":[30.50959000000001,31.03559000000001],"type":"Point"}
}