{
  "type": "Feature",
  "properties": {
    "gn:admin1_code":"14",
    "gn:asciiname":"`Izbat Abu `Ashur",
    "gn:country_code":"EG",
    "gn:dem":7,
    "gn:feature_class":"P",
    "gn:feature_code":"PPL",
    "gn:name":"\u2018Izbat Ab\u016b \u2018\u0100sh\u016br",
    "gn:population":0,
    "gn:timezone":"Africa/Cairo",
    "iso:country":"EG",
    "name:ara_x_preferred":[
        "\u0639\u0632\u0628\u0629 \u0623\u0628\u0648 \u0639\u0627\u0634\u0648\u0631"
    ],
    "name:und_x_variant":[
        "\u2018Izbat Ab\u016b \u2018\u0100sh\u016br"
    ],
    "wof:name":"`Izbat Abu `Ashur",
    "wof:placetype":"locality"
},
  "geometry": {"coordinates":[31.44112,30.67662],"type":"Point"}
}