{
  "type": "Feature",
  "properties": {
    "gn:admin1_code":"9.0",
    "gn:asciiname":"Zawiyat Razin",
    "gn:country_code":"EG",
    "gn:dem":15,
    "gn:feature_class":"P",
    "gn:feature_code":"PPL",
    "gn:name":"Z\u0101wiyat Raz\u012bn",
    "gn:population":0,
    "gn:timezone":"Africa/Cairo",
    "iso:country":"EG",
    "name:ara_x_preferred":[
        "\u0632\u0627\u0648\u064a\u0629 \u0631\u0632\u064a\u0646"
    ],
    "name:und_x_variant":[
        "Z\u00e2wyet Raz\u00een",
        "Z\u0101wiyat Raz\u012bn",
        "Z\u0101wyat Raz\u012bn"
    ],
    "wof:name":"Zawiyat Razin",
    "wof:placetype":"locality"
},
  "geometry": {"coordinates":[30.85316,30.41248],"type":"Point"}
}