{
  "type": "Feature",
  "properties": {
    "gn:admin1_code":"01",
    "gn:asciiname":"Mit al `Amil",
    "gn:country_code":"EG",
    "gn:dem":13,
    "gn:feature_class":"P",
    "gn:feature_code":"PPL",
    "gn:name":"M\u012bt al \u2018\u0100mil",
    "gn:population":0,
    "gn:timezone":"Africa/Cairo",
    "iso:country":"EG",
    "name:ara_x_preferred":[
        "\u0645\u064a\u062a \u0627\u0644\u0639\u0627\u0645\u0644"
    ],
    "name:und_x_variant":[
        "M\u00eet el-\u2018\u00c2mil",
        "M\u012bt al \u2018\u0100mil",
        "M\u012bt al-\u2018\u0100mil"
    ],
    "wof:name":"Mit al `Amil",
    "wof:placetype":"locality"
},
  "geometry": {"coordinates":[31.34725,30.89572],"type":"Point"}
}