{
  "type": "Feature",
  "properties": {
    "gn:admin1_code":"03",
    "gn:asciiname":"Saqr al Kubra",
    "gn:country_code":"EG",
    "gn:dem":2,
    "gn:feature_class":"P",
    "gn:feature_code":"PPL",
    "gn:name":"\u015eaqr al Kubr\u00e1",
    "gn:population":0,
    "gn:timezone":"Africa/Cairo",
    "iso:country":"EG",
    "name:ara_x_preferred":[
        "\u0635\u0642\u0631 \u0627\u0644\u0643\u0628\u0631\u0649"
    ],
    "name:und_x_variant":[
        "\u2018Ezbet Safar",
        "\u2018Ezbet \u1e62aqr",
        "\u2018Izbat \u015eaqr",
        "\u015eaqr al Kubr\u00e1",
        "\u1e62aqr al-Kubr\u0101"
    ],
    "wof:name":"Saqr al Kubra",
    "wof:placetype":"locality"
},
  "geometry": {"coordinates":[30.23568,31.11801],"type":"Point"}
}