{
  "type": "Feature",
  "properties": {
    "gn:admin1_code":"21",
    "gn:asciiname":"`Izbat Abu Yusuf",
    "gn:country_code":"EG",
    "gn:dem":2,
    "gn:feature_class":"P",
    "gn:feature_code":"PPL",
    "gn:name":"\u2018Izbat Ab\u016b Y\u016bsuf",
    "gn:population":0,
    "gn:timezone":"Africa/Cairo",
    "iso:country":"EG",
    "name:ara_x_preferred":[
        "\u0639\u0632\u0628\u0629 \u0623\u0628\u0648 \u064a\u0648\u0633\u0641"
    ],
    "name:und_x_variant":[
        "\u2018Izbat Ab\u016b Y\u016bsuf"
    ],
    "wof:name":"`Izbat Abu Yusuf",
    "wof:placetype":"locality"
},
  "geometry": {"coordinates":[30.55243,31.33744],"type":"Point"}
}