{
  "type": "Feature",
  "properties": {
    "gn:admin1_code":"1.0",
    "gn:asciiname":"Tukh al Aqlam",
    "gn:country_code":"EG",
    "gn:dem":10,
    "gn:feature_class":"P",
    "gn:feature_code":"PPL",
    "gn:name":"\u0162\u016bkh al Aql\u0101m",
    "gn:population":0,
    "gn:timezone":"Africa/Cairo",
    "iso:country":"EG",
    "name:ara_x_preferred":[
        "\u0637\u0648\u062e \u0627\u0644\u0623\u0642\u0627\u0644\u0645"
    ],
    "name:und_x_variant":[
        "\u1e6c\u00fbkh el-Aql\u00e2m",
        "\u0162\u016bkh al Aql\u0101m",
        "\u1e6c\u016bkh al-Aql\u0101m"
    ],
    "wof:name":"Tukh al Aqlam",
    "wof:placetype":"locality"
},
  "geometry": {"coordinates":[31.43398,30.8707],"type":"Point"}
}