{
  "type": "Feature",
  "properties": {
    "gn:admin1_code":"01",
    "gn:asciiname":"Kafr al Jawhari",
    "gn:cc2":"EG",
    "gn:country_code":"EG",
    "gn:dem":12,
    "gn:feature_class":"P",
    "gn:feature_code":"PPL",
    "gn:name":"Kafr al Jawhar\u012b",
    "gn:population":0,
    "gn:timezone":"Africa/Cairo",
    "iso:country":"EG",
    "name:und_x_variant":[
        "Kafr el-Gauhari",
        "Kafr al Jawhar\u012b"
    ],
    "wof:name":"Kafr al Jawhari",
    "wof:placetype":"locality"
},
  "geometry": {"coordinates":[31.31667,30.66667],"type":"Point"}
}