{
  "type": "Feature",
  "properties": {
    "gn:admin1_code":"03",
    "gn:asciiname":"`Izbat Fadil",
    "gn:country_code":"EG",
    "gn:dem":3,
    "gn:feature_class":"P",
    "gn:feature_code":"PPL",
    "gn:name":"\u2018Izbat F\u0101\u1e11il",
    "gn:population":0,
    "gn:timezone":"Africa/Cairo",
    "iso:country":"EG",
    "name:ara_x_preferred":[
        "\u0639\u0632\u0628\u0629 \u0641\u0627\u0636\u0644"
    ],
    "name:und_x_variant":[
        "\u2018Izbat F\u0101\u1e11il",
        "\u2018Izbat F\u0101\u1e0dil"
    ],
    "wof:name":"`Izbat Fadil",
    "wof:placetype":"locality"
},
  "geometry": {"coordinates":[30.40681,31.00994],"type":"Point"}
}