{
  "type": "Feature",
  "properties": {
    "gn:admin1_code":"01",
    "gn:asciiname":"As Samahah al Kubra",
    "gn:country_code":"EG",
    "gn:dem":9,
    "gn:feature_class":"P",
    "gn:feature_code":"PPL",
    "gn:name":"As Sam\u0101\u1e29ah al Kubr\u00e1",
    "gn:population":0,
    "gn:timezone":"Africa/Cairo",
    "iso:country":"EG",
    "name:ara_x_preferred":[
        "\u0627\u0644\u0633\u0645\u0627\u062d\u0629 \u0627\u0644\u0643\u0628\u0631\u0649"
    ],
    "name:und_x_variant":[
        "El-Sam\u00e2\u1e25iya el-Kubra",
        "El-Samahiga el-Kubra",
        "As Sam\u0101\u1e29\u012byah al Kubr\u00e1",
        "As Sam\u0101\u1e29ah al Kubr\u00e1",
        "As-Sam\u0101\u1e25ah al-Kubr\u00e1"
    ],
    "wof:name":"As Samahah al Kubra",
    "wof:placetype":"locality"
},
  "geometry": {"coordinates":[31.37406,31.2382],"type":"Point"}
}