{
  "type": "Feature",
  "properties": {
    "gn:admin1_code":"09",
    "gn:asciiname":"`Izbat Mirhim",
    "gn:country_code":"EG",
    "gn:dem":15,
    "gn:feature_class":"P",
    "gn:feature_code":"PPL",
    "gn:name":"\u2018Izbat M\u012brhim",
    "gn:population":0,
    "gn:timezone":"Africa/Cairo",
    "iso:country":"EG",
    "name:ara_x_preferred":[
        "\u0639\u0632\u0628\u0629 \u0645\u064a\u0631\u0647\u0645"
    ],
    "name:und_x_variant":[
        "\u2018Izbat M\u012brhim"
    ],
    "wof:name":"`Izbat Mirhim",
    "wof:placetype":"locality"
},
  "geometry": {"coordinates":[31.10535,30.47799],"type":"Point"}
}