{
  "type": "Feature",
  "properties": {
    "gn:admin1_code":"03",
    "gn:asciiname":"`Izbat al Hamamiyah",
    "gn:country_code":"EG",
    "gn:dem":6,
    "gn:feature_class":"P",
    "gn:feature_code":"PPL",
    "gn:name":"\u2018Izbat al \u1e28am\u0101m\u012byah",
    "gn:population":0,
    "gn:timezone":"Africa/Cairo",
    "iso:country":"EG",
    "name:ara_x_preferred":[
        "\u0639\u0632\u0628\u0629 \u0627\u0644\u062d\u0645\u0627\u0645\u064a\u0629"
    ],
    "name:und_x_variant":[
        "\u2018Izbat al \u1e28am\u0101m\u012byah",
        "\u2018Izbat al-\u1e24am\u0101miyyah"
    ],
    "wof:name":"`Izbat al Hamamiyah",
    "wof:placetype":"locality"
},
  "geometry": {"coordinates":[30.48842,31.01367],"type":"Point"}
}