{
  "type": "Feature",
  "properties": {
    "gn:admin1_code":"03",
    "gn:asciiname":"`Izbat ad Dawwar",
    "gn:country_code":"EG",
    "gn:dem":-3,
    "gn:feature_class":"P",
    "gn:feature_code":"PPL",
    "gn:name":"\u2018Izbat ad Daww\u0101r",
    "gn:population":0,
    "gn:timezone":"Africa/Cairo",
    "iso:country":"EG",
    "name:und_x_variant":[
        "\u2018Ezbet ed Dauw\u0101r",
        "\u2018Ezbet el-Dauw\u00e2r",
        "Ezbet el Dawar",
        "El Dauwer",
        "\u2018Izbat ad Daww\u0101r"
    ],
    "wof:name":"`Izbat ad Dawwar",
    "wof:placetype":"locality"
},
  "geometry": {"coordinates":[30.08667,31.06861],"type":"Point"}
}