{
  "type": "Feature",
  "properties": {
    "gn:admin1_code":"14",
    "gn:asciiname":"Munsha'at Sahbarah",
    "gn:country_code":"EG",
    "gn:dem":9,
    "gn:feature_class":"P",
    "gn:feature_code":"PPL",
    "gn:name":"Munsha\u2019at \u015eahbarah",
    "gn:population":0,
    "gn:timezone":"Africa/Cairo",
    "iso:country":"EG",
    "name:ara_x_preferred":[
        "\u0645\u0646\u0634\u0623\u0629 \u0635\u0647\u0628\u0631\u0629"
    ],
    "name:und_x_variant":[
        "Minsh\u00e2t \u1e62ahbara",
        "Minsh\u0101t \u015eahbarah",
        "Munsha\u2019at \u015eahbarah",
        "Minsh\u0101t \u1e62ahbarah"
    ],
    "wof:name":"Munsha'at Sahbarah",
    "wof:placetype":"locality"
},
  "geometry": {"coordinates":[31.40363,30.76208],"type":"Point"}
}