{
  "type": "Feature",
  "properties": {
    "gn:admin1_code":"07",
    "gn:asciiname":"`Izbat Abu Husayn",
    "gn:country_code":"EG",
    "gn:dem":14,
    "gn:feature_class":"P",
    "gn:feature_code":"PPL",
    "gn:name":"\u2018Izbat Ab\u016b \u1e28usayn",
    "gn:population":0,
    "gn:timezone":"Africa/Cairo",
    "iso:country":"EG",
    "name:und_x_variant":[
        "Ezbet Abu Husein",
        "\u2018Izbat Ab\u016b \u1e28usayn"
    ],
    "wof:name":"`Izbat Abu Husayn",
    "wof:placetype":"locality"
},
  "geometry": {"coordinates":[32.25,30.56667],"type":"Point"}
}