{
  "type": "Feature",
  "properties": {
    "gn:admin1_code":"03",
    "gn:asciiname":"`Izbat Tawfiq",
    "gn:country_code":"EG",
    "gn:dem":1,
    "gn:feature_class":"P",
    "gn:feature_code":"PPL",
    "gn:name":"\u2018Izbat Tawf\u012bq",
    "gn:population":0,
    "gn:timezone":"Africa/Cairo",
    "iso:country":"EG",
    "name:ara_x_preferred":[
        "\u0639\u0632\u0628\u0629 \u062a\u0648\u0641\u064a\u0642"
    ],
    "name:und_x_variant":[
        "\u2018Izbat Tawf\u012bq"
    ],
    "wof:name":"`Izbat Tawfiq",
    "wof:placetype":"locality"
},
  "geometry": {"coordinates":[30.38573,31.00283],"type":"Point"}
}