{
  "type": "Feature",
  "properties": {
    "gn:admin1_code":"18",
    "gn:asciiname":"Al Qasabah",
    "gn:country_code":"EG",
    "gn:dem":34,
    "gn:feature_class":"P",
    "gn:feature_code":"PPL",
    "gn:name":"Al Qa\u015fabah",
    "gn:population":0,
    "gn:timezone":"Africa/Cairo",
    "iso:country":"EG",
    "name:und_x_variant":[
        "El Qa\u1e63ba",
        "Al Qa\u015fabah"
    ],
    "wof:name":"Al Qasabah",
    "wof:placetype":"locality"
},
  "geometry": {"coordinates":[30.865,28.94718],"type":"Point"}
}