{
  "type": "Feature",
  "properties": {
    "gn:admin1_code":"01",
    "gn:asciiname":"Buhut",
    "gn:country_code":"EG",
    "gn:dem":13,
    "gn:feature_class":"P",
    "gn:feature_code":"PPL",
    "gn:name":"Buh\u016bt",
    "gn:population":0,
    "gn:timezone":"Africa/Cairo",
    "iso:country":"EG",
    "name:ara_x_preferred":[
        "Buh\u016bt"
    ],
    "name:ara_x_variant":[
        "\u0628\u0647\u0648\u062a"
    ],
    "name:und_x_variant":[
        "Buh\u00fbt"
    ],
    "wof:name":"Buhut",
    "wof:placetype":"locality"
},
  "geometry": {"coordinates":[31.32726,31.17058],"type":"Point"}
}