{
  "type": "Feature",
  "properties": {
    "gn:admin1_code":"01",
    "gn:asciiname":"`Izbat `Umar",
    "gn:country_code":"EG",
    "gn:dem":3,
    "gn:feature_class":"P",
    "gn:feature_code":"PPL",
    "gn:name":"\u2018Izbat \u2018Umar",
    "gn:population":0,
    "gn:timezone":"Africa/Cairo",
    "iso:country":"EG",
    "name:ara_x_preferred":[
        "\u0639\u0632\u0628\u0629 \u0639\u0645\u0631"
    ],
    "name:und_x_variant":[
        "\u2018Izbat \u2018Umar"
    ],
    "wof:name":"`Izbat `Umar",
    "wof:placetype":"locality"
},
  "geometry": {"coordinates":[31.85396,31.19208],"type":"Point"}
}