{
  "type": "Feature",
  "properties": {
    "gn:admin1_code":"06",
    "gn:asciiname":"`Izbat al `Amrawi al Kubra",
    "gn:country_code":"EG",
    "gn:dem":5,
    "gn:feature_class":"P",
    "gn:feature_code":"PPL",
    "gn:name":"\u2018Izbat al \u2018Amr\u0101w\u012b al Kubr\u00e1",
    "gn:population":0,
    "gn:timezone":"Africa/Cairo",
    "iso:country":"EG",
    "name:ara_x_preferred":[
        "\u0639\u0632\u0628\u0629 \u0627\u0644\u0639\u0645\u0631\u0627\u0648\u064a \u0627\u0644\u0643\u0628\u0631\u0649"
    ],
    "name:und_x_variant":[
        "\u2018Ezbet el-\u2018Am\u00e2rwa",
        "\u2018Izbat al \u2018Amr\u0101w\u012b al Kubr\u00e1",
        "\u2018Azbat al \u2018Am\u0101rwah al Qibl\u012byah",
        "\u2018Ezbet el-\u2018Amarwa",
        "\u2018Izbat al \u2018Am\u0101riwah",
        "\u2018Azbat al \u2018Am\u0101riwah al Qibl\u012byah"
    ],
    "wof:name":"`Izbat al `Amrawi al Kubra",
    "wof:placetype":"locality"
},
  "geometry": {"coordinates":[30.02358,31.26414],"type":"Point"}
}