{
  "type": "Feature",
  "properties": {
    "gn:admin1_code":"03",
    "gn:asciiname":"Saft Khalid",
    "gn:country_code":"EG",
    "gn:dem":6,
    "gn:feature_class":"P",
    "gn:feature_code":"PPL",
    "gn:name":"\u015eaf\u0163 Kh\u0101lid",
    "gn:population":0,
    "gn:timezone":"Africa/Cairo",
    "iso:country":"EG",
    "wof:name":"Saft Khalid",
    "wof:placetype":"locality"
},
  "geometry": {"coordinates":[30.65881,30.93903],"type":"Point"}
}