{
  "type": "Feature",
  "properties": {
    "gn:admin1_code":"04",
    "gn:asciiname":"`Izbat `Ali ad Dali",
    "gn:country_code":"EG",
    "gn:dem":4,
    "gn:feature_class":"P",
    "gn:feature_code":"PPL",
    "gn:name":"\u2018Izbat \u2018Al\u012b ad D\u0101l\u012b",
    "gn:population":0,
    "gn:timezone":"Africa/Cairo",
    "iso:country":"EG",
    "wof:name":"`Izbat `Ali ad Dali",
    "wof:placetype":"locality"
},
  "geometry": {"coordinates":[30.99698,29.38915],"type":"Point"}
}