{
  "type": "Feature",
  "properties": {
    "gn:admin1_code":"03",
    "gn:asciiname":"`Izbat al Basha as Sughra",
    "gn:country_code":"EG",
    "gn:dem":-3,
    "gn:feature_class":"P",
    "gn:feature_code":"PPL",
    "gn:name":"\u2018Izbat al B\u0101sh\u0101 a\u015f \u015eughr\u00e1",
    "gn:population":0,
    "gn:timezone":"Africa/Cairo",
    "iso:country":"EG",
    "name:ara_x_preferred":[
        "\u0639\u0632\u0628\u0629 \u0627\u0644\u0628\u0627\u0634\u0627 \u0627\u0644\u0635\u063a\u0631\u0649"
    ],
    "name:und_x_variant":[
        "\u2018Izbat al B\u0101sh\u0101 a\u015f \u015eughr\u00e1"
    ],
    "wof:name":"`Izbat al Basha as Sughra",
    "wof:placetype":"locality"
},
  "geometry": {"coordinates":[30.14858,31.00455],"type":"Point"}
}