{
  "type": "Feature",
  "properties": {
    "gn:admin1_code":"14",
    "gn:asciiname":"Kafr as Safatiwah",
    "gn:cc2":"EG",
    "gn:country_code":"EG",
    "gn:dem":13,
    "gn:feature_class":"P",
    "gn:feature_code":"PPL",
    "gn:name":"Kafr a\u015f \u015eaf\u0101\u0163iwah",
    "gn:population":0,
    "gn:timezone":"Africa/Cairo",
    "iso:country":"EG",
    "name:und_x_variant":[
        "Kafr el \u1e62af\u00e2\u1e6dwa",
        "Kafr a\u015f \u015eaf\u0101\u0163iwah"
    ],
    "wof:name":"Kafr as Safatiwah",
    "wof:placetype":"locality"
},
  "geometry": {"coordinates":[31.75,30.61667000000001],"type":"Point"}
}