{
  "type": "Feature",
  "properties": {
    "gn:admin1_code":"04",
    "gn:asciiname":"Minsha'at Futayh",
    "gn:country_code":"EG",
    "gn:dem":22,
    "gn:feature_class":"P",
    "gn:feature_code":"PPL",
    "gn:name":"Minsha\u2019at Futay\u1e29",
    "gn:population":0,
    "gn:timezone":"Africa/Cairo",
    "iso:country":"EG",
    "wof:name":"Minsha'at Futayh",
    "wof:placetype":"locality"
},
  "geometry": {"coordinates":[30.80701,29.31736],"type":"Point"}
}