{
  "type": "Feature",
  "properties": {
    "gn:admin1_code":"14",
    "gn:asciiname":"`Izbat Abu Hammudah",
    "gn:country_code":"EG",
    "gn:dem":8,
    "gn:feature_class":"P",
    "gn:feature_code":"PPL",
    "gn:name":"\u2018Izbat Ab\u016b \u1e28amm\u016bdah",
    "gn:population":0,
    "gn:timezone":"Africa/Cairo",
    "iso:country":"EG",
    "name:ara_x_preferred":[
        "\u0639\u0632\u0628\u0629 \u0623\u0628\u0648 \u062d\u0645\u0648\u062f\u0629"
    ],
    "name:und_x_variant":[
        "\u2018Izbat Ab\u016b \u1e28amm\u016bdah"
    ],
    "wof:name":"`Izbat Abu Hammudah",
    "wof:placetype":"locality"
},
  "geometry": {"coordinates":[31.62824,30.84585],"type":"Point"}
}