{
  "type": "Feature",
  "properties": {
    "gn:admin1_code":"10",
    "gn:asciiname":"`Ezbet el-Hagg Yusef",
    "gn:country_code":"EG",
    "gn:dem":46,
    "gn:feature_class":"P",
    "gn:feature_code":"PPL",
    "gn:name":"\u2018Ezbet el-Hagg Y\u00fbsef",
    "gn:population":0,
    "gn:timezone":"Africa/Cairo",
    "iso:country":"EG",
    "wof:name":"`Ezbet el-Hagg Yusef",
    "wof:placetype":"locality"
},
  "geometry": {"coordinates":[30.81667,27.66667],"type":"Point"}
}