{
  "type": "Feature",
  "properties": {
    "gn:admin1_code":"03",
    "gn:asciiname":"`Izbat al Fartitah",
    "gn:country_code":"EG",
    "gn:dem":-4,
    "gn:feature_class":"P",
    "gn:feature_code":"PPL",
    "gn:name":"\u2018Izbat al Far\u0163\u012b\u0163ah",
    "gn:population":0,
    "gn:timezone":"Africa/Cairo",
    "iso:country":"EG",
    "name:ara_x_preferred":[
        "\u0639\u0632\u0628\u0629 \u0627\u0644\u0641\u0631\u0637\u064a\u0637\u0629"
    ],
    "name:und_x_variant":[
        "\u2018Izbat al Far\u0163\u012b\u0163ah"
    ],
    "wof:name":"`Izbat al Fartitah",
    "wof:placetype":"locality"
},
  "geometry": {"coordinates":[30.09579,31.07215],"type":"Point"}
}