{
  "type": "Feature",
  "properties": {
    "gn:admin1_code":"01",
    "gn:asciiname":"Nawasa al Ghayt",
    "gn:country_code":"EG",
    "gn:dem":15,
    "gn:feature_class":"P",
    "gn:feature_code":"PPL",
    "gn:name":"Nawas\u0101 al Ghay\u0163",
    "gn:population":0,
    "gn:timezone":"Africa/Cairo",
    "iso:country":"EG",
    "name:ara_x_preferred":[
        "\u0646\u0648\u0633\u0627 \u0627\u0644\u063a\u064a\u0637"
    ],
    "name:und_x_variant":[
        "Nawasa el-Ghei\u1e6d",
        "Nawas\u0101 al Ghay\u0163",
        "Nawas\u0101 al-Ghay\u1e6d"
    ],
    "wof:name":"Nawasa al Ghayt",
    "wof:placetype":"locality"
},
  "geometry": {"coordinates":[31.32219000000001,30.97557],"type":"Point"}
}