{
  "type": "Feature",
  "properties": {
    "gn:admin1_code":"03",
    "gn:asciiname":"`Izbat Abu Bakr Hasan",
    "gn:country_code":"EG",
    "gn:dem":2,
    "gn:feature_class":"P",
    "gn:feature_code":"PPL",
    "gn:name":"\u2018Izbat Ab\u016b Bakr \u1e28asan",
    "gn:population":0,
    "gn:timezone":"Africa/Cairo",
    "iso:country":"EG",
    "name:ara_x_preferred":[
        "\u0639\u0632\u0628\u0629 \u0623\u0628\u0648 \u0628\u0643\u0631 \u062d\u0633\u0646"
    ],
    "name:und_x_variant":[
        "\u2018Ezbet Abu Bakr \u1e24asan",
        "\u2018Izbat Ab\u016b Bakr \u1e28asan",
        "\u2018Izbat Ab\u016b Bakr \u1e24asan"
    ],
    "wof:name":"`Izbat Abu Bakr Hasan",
    "wof:placetype":"locality"
},
  "geometry": {"coordinates":[30.26847,31.15339],"type":"Point"}
}