{
  "type": "Feature",
  "properties": {
    "gn:admin1_code":"14",
    "gn:asciiname":"Kafr an Nakhkhal",
    "gn:country_code":"EG",
    "gn:dem":13,
    "gn:feature_class":"P",
    "gn:feature_code":"PPL",
    "gn:name":"Kafr an Nakhkh\u0101l",
    "gn:population":0,
    "gn:timezone":"Africa/Cairo",
    "iso:country":"EG",
    "name:ara_x_preferred":[
        "\u0643\u0641\u0631 \u0627\u0644\u0646\u062e\u0627\u0644"
    ],
    "name:und_x_variant":[
        "Kafr el-Nakhkh\u00e2l",
        "Kafr an Nakhkh\u0101l"
    ],
    "wof:name":"Kafr an Nakhkhal",
    "wof:placetype":"locality"
},
  "geometry": {"coordinates":[31.71315,30.61751],"type":"Point"}
}