{
  "type": "Feature",
  "properties": {
    "gn:admin1_code":"03",
    "gn:asciiname":"Al Faransawiyah",
    "gn:country_code":"EG",
    "gn:dem":-1,
    "gn:feature_class":"P",
    "gn:feature_code":"PPL",
    "gn:name":"Al Farans\u0101w\u012byah",
    "gn:population":0,
    "gn:timezone":"Africa/Cairo",
    "iso:country":"EG",
    "wof:name":"Al Faransawiyah",
    "wof:placetype":"locality"
},
  "geometry": {"coordinates":[30.29354,30.96804],"type":"Point"}
}