{
  "type": "Feature",
  "properties": {
    "gn:admin1_code":"08",
    "gn:asciiname":"Ar Riqqah",
    "gn:cc2":"EG",
    "gn:country_code":"EG",
    "gn:dem":28,
    "gn:feature_class":"P",
    "gn:feature_code":"PPL",
    "gn:name":"Ar Riqqah",
    "gn:population":0,
    "gn:timezone":"Africa/Cairo",
    "iso:country":"EG",
    "name:und_x_variant":[
        "Er Riqa",
        "El Riqqa",
        "Ar Riqqah"
    ],
    "wof:name":"Ar Riqqah",
    "wof:placetype":"locality"
},
  "geometry": {"coordinates":[31.1925,29.41722],"type":"Point"}
}