{
  "type": "Feature",
  "properties": {
    "gn:admin1_code":"21",
    "gn:asciiname":"`Izbah Raqm `Ishrun",
    "gn:country_code":"EG",
    "gn:dem":7,
    "gn:feature_class":"P",
    "gn:feature_code":"PPL",
    "gn:name":"\u2018Izbah Raqm \u2018Ishr\u016bn",
    "gn:population":0,
    "gn:timezone":"Africa/Cairo",
    "iso:country":"EG",
    "name:ara_x_preferred":[
        "\u0639\u0632\u0628\u0629 \u0631\u0642\u0645 \u0662\u0660"
    ],
    "name:ara_x_variant":[
        "\u0639\u0632\u0628\u0629 \u0631\u0642\u0645 20"
    ],
    "name:und_x_variant":[
        "\u2018Izbah Raqm \u2018Ishr\u016bn",
        "\u2018Izbah Raqm 20"
    ],
    "wof:name":"`Izbah Raqm `Ishrun",
    "wof:placetype":"locality"
},
  "geometry": {"coordinates":[31.08632,31.35],"type":"Point"}
}