{
  "type": "Feature",
  "properties": {
    "gn:admin1_code":"08",
    "gn:asciiname":"Al Burumbul",
    "gn:cc2":"EG",
    "gn:country_code":"EG",
    "gn:dem":33,
    "gn:feature_class":"P",
    "gn:feature_code":"PPL",
    "gn:name":"Al Burumbul",
    "gn:population":0,
    "gn:timezone":"Africa/Cairo",
    "iso:country":"EG",
    "name:und_x_variant":[
        "El Burumbul",
        "Al Burumbul"
    ],
    "wof:name":"Al Burumbul",
    "wof:placetype":"locality"
},
  "geometry": {"coordinates":[31.24,29.30917],"type":"Point"}
}