{
  "type": "Feature",
  "properties": {
    "gn:admin1_code":"12",
    "gn:asciiname":"`Izbat Qasim Murad",
    "gn:country_code":"EG",
    "gn:dem":16,
    "gn:feature_class":"P",
    "gn:feature_code":"PPL",
    "gn:name":"\u2018Izbat Q\u0101sim Mur\u0101d",
    "gn:population":0,
    "gn:timezone":"Africa/Cairo",
    "iso:country":"EG",
    "name:ara_x_preferred":[
        "\u0639\u0632\u0628\u0629 \u0642\u0627\u0633\u0645 \u0645\u0631\u0627\u062f"
    ],
    "name:und_x_variant":[
        "\u2018Izbat Q\u0101sim Mur\u0101d"
    ],
    "wof:name":"`Izbat Qasim Murad",
    "wof:placetype":"locality"
},
  "geometry": {"coordinates":[31.22107,30.34023],"type":"Point"}
}