{
  "type": "Feature",
  "properties": {
    "gn:admin1_code":"09",
    "gn:asciiname":"Kafr al Khadrah",
    "gn:country_code":"EG",
    "gn:dem":15,
    "gn:feature_class":"P",
    "gn:feature_code":"PPL",
    "gn:name":"Kafr al Kha\u1e11rah",
    "gn:population":0,
    "gn:timezone":"Africa/Cairo",
    "iso:country":"EG",
    "name:ara_x_preferred":[
        "\u0643\u0641\u0631 \u0627\u0644\u062e\u0636\u0631\u0629"
    ],
    "name:und_x_variant":[
        "Kafr al Kha\u1e11rah"
    ],
    "wof:name":"Kafr al Khadrah",
    "wof:placetype":"locality"
},
  "geometry": {"coordinates":[31.0198,30.37478],"type":"Point"}
}