{
  "type": "Feature",
  "properties": {
    "gn:admin1_code":"03",
    "gn:asciiname":"`Ezbet `Omar Fadil Bey",
    "gn:country_code":"EG",
    "gn:dem":0,
    "gn:feature_class":"P",
    "gn:feature_code":"PPL",
    "gn:name":"\u2018Ezbet \u2018Omar Fadil Bey",
    "gn:population":0,
    "gn:timezone":"Africa/Cairo",
    "iso:country":"EG",
    "wof:name":"`Ezbet `Omar Fadil Bey",
    "wof:placetype":"locality"
},
  "geometry": {"coordinates":[30.41667,31.08333],"type":"Point"}
}