{
  "type": "Feature",
  "properties": {
    "gn:admin1_code":"01",
    "gn:asciiname":"`Izbat Saniyah",
    "gn:country_code":"EG",
    "gn:dem":11,
    "gn:feature_class":"P",
    "gn:feature_code":"PPL",
    "gn:name":"\u2018Izbat San\u012byah",
    "gn:population":0,
    "gn:timezone":"Africa/Cairo",
    "iso:country":"EG",
    "name:ara_x_preferred":[
        "\u0639\u0632\u0628\u0629 \u0633\u0646\u064a\u0629"
    ],
    "name:und_x_variant":[
        "\u2018Izbat San\u012byah",
        "\u2018Iz. Saniyyah"
    ],
    "wof:name":"`Izbat Saniyah",
    "wof:placetype":"locality"
},
  "geometry": {"coordinates":[31.30261,30.90273],"type":"Point"}
}