{
  "type": "Feature",
  "properties": {
    "gn:admin1_code":"1.0",
    "gn:asciiname":"Tunnamil",
    "gn:country_code":"EG",
    "gn:dem":13,
    "gn:feature_class":"P",
    "gn:feature_code":"PPL",
    "gn:name":"\u0162unn\u0101mil",
    "gn:population":0,
    "gn:timezone":"Africa/Cairo",
    "iso:country":"EG",
    "name:ara_x_preferred":[
        "\u0162unn\u0101mil"
    ],
    "name:ara_x_variant":[
        "\u0637\u0646\u0627\u0645\u0644"
    ],
    "name:und_x_variant":[
        "\u1e6cunn\u00e2mil el-Gharbi",
        "\u0162unn\u0101mil al Gharb\u012b",
        "\u1e6cunn\u00e2mil",
        "\u1e6cunn\u0101mil"
    ],
    "wof:name":"Tunnamil",
    "wof:placetype":"locality"
},
  "geometry": {"coordinates":[31.26172,30.83602],"type":"Point"}
}