{
  "type": "Feature",
  "properties": {
    "gn:admin1_code":"07",
    "gn:asciiname":"Fanarah",
    "gn:country_code":"EG",
    "gn:dem":14,
    "gn:feature_class":"P",
    "gn:feature_code":"PPL",
    "gn:name":"Fan\u0101rah",
    "gn:population":0,
    "gn:timezone":"Africa/Cairo",
    "iso:country":"EG",
    "name:und_x_variant":[
        "Fanara",
        "Fan\u0101rah"
    ],
    "wof:name":"Fanarah",
    "wof:placetype":"locality"
},
  "geometry": {"coordinates":[32.33974,30.27671],"type":"Point"}
}