{
  "type": "Feature",
  "properties": {
    "gn:admin1_code":"03",
    "gn:asciiname":"`Izbat Saqr",
    "gn:country_code":"EG",
    "gn:dem":2,
    "gn:feature_class":"P",
    "gn:feature_code":"PPL",
    "gn:name":"\u2018Izbat \u015eaqr",
    "gn:population":0,
    "gn:timezone":"Africa/Cairo",
    "iso:country":"EG",
    "name:ara_x_preferred":[
        "\u0639\u0632\u0628\u0629 \u0635\u0642\u0631"
    ],
    "name:und_x_variant":[
        "\u2018Izbat \u015eaqr"
    ],
    "wof:name":"`Izbat Saqr",
    "wof:placetype":"locality"
},
  "geometry": {"coordinates":[30.58041,31.07163],"type":"Point"}
}