{
  "type": "Feature",
  "properties": {
    "gn:admin1_code":"09",
    "gn:asciiname":"Ad Dabayibah",
    "gn:country_code":"EG",
    "gn:dem":13,
    "gn:feature_class":"P",
    "gn:feature_code":"PPL",
    "gn:name":"Ad Dab\u0101yibah",
    "gn:population":0,
    "gn:timezone":"Africa/Cairo",
    "iso:country":"EG",
    "name:ara_x_preferred":[
        "\u0627\u0644\u062f\u0628\u0627\u064a\u0628\u0647"
    ],
    "name:und_x_variant":[
        "El-Dab\u00e2yba",
        "Ad Dab\u0101\u2019ibah",
        "Ad Dab\u0101yibah"
    ],
    "wof:name":"Ad Dabayibah",
    "wof:placetype":"locality"
},
  "geometry": {"coordinates":[31.07105,30.59685],"type":"Point"}
}