{
  "type": "Feature",
  "properties": {
    "gn:admin1_code":"14",
    "gn:asciiname":"Shaybat Qashsh",
    "gn:cc2":"EG",
    "gn:country_code":"EG",
    "gn:dem":13,
    "gn:feature_class":"P",
    "gn:feature_code":"PPL",
    "gn:name":"Shaybat Qashsh",
    "gn:population":0,
    "gn:timezone":"Africa/Cairo",
    "iso:country":"EG",
    "name:und_x_variant":[
        "Sheibet Qash",
        "Shaybat Qashsh"
    ],
    "wof:name":"Shaybat Qashsh",
    "wof:placetype":"locality"
},
  "geometry": {"coordinates":[31.30278,30.55389000000001],"type":"Point"}
}