{
  "type": "Feature",
  "properties": {
    "gn:admin1_code":"17",
    "gn:asciiname":"Al Akrad wa Bani Zayd",
    "gn:country_code":"EG",
    "gn:dem":57,
    "gn:feature_class":"P",
    "gn:feature_code":"PPL",
    "gn:name":"Al Akr\u0101d wa Ban\u012b Zayd",
    "gn:population":0,
    "gn:timezone":"Africa/Cairo",
    "iso:country":"EG",
    "name:und_x_variant":[
        "El Akr\u00e2d",
        "Al Akr\u0101d",
        "Al Akr\u0101d wa Ban\u012b Zayd"
    ],
    "wof:name":"Al Akrad wa Bani Zayd",
    "wof:placetype":"locality"
},
  "geometry": {"coordinates":[31.15034,27.22233],"type":"Point"}
}