{
  "type": "Feature",
  "properties": {
    "gn:admin1_code":"01",
    "gn:asciiname":"`Izbat as Sayyid Abu Jalal",
    "gn:country_code":"EG",
    "gn:dem":4,
    "gn:feature_class":"P",
    "gn:feature_code":"PPL",
    "gn:name":"\u2018Izbat as Sayyid Ab\u016b Jal\u0101l",
    "gn:population":0,
    "gn:timezone":"Africa/Cairo",
    "iso:country":"EG",
    "name:ara_x_preferred":[
        "\u0639\u0632\u0628\u0629 \u0627\u0644\u0633\u064a\u062f \u0623\u0628\u0648 \u062c\u0644\u0627\u0644"
    ],
    "name:und_x_variant":[
        "\u2018Izbat as Sayyid Ab\u016b Jal\u0101l"
    ],
    "wof:name":"`Izbat as Sayyid Abu Jalal",
    "wof:placetype":"locality"
},
  "geometry": {"coordinates":[31.56386,31.26669],"type":"Point"}
}