{
  "type": "Feature",
  "properties": {
    "gn:admin1_code":"21",
    "gn:asciiname":"`Izbat al Waqf",
    "gn:country_code":"EG",
    "gn:dem":4,
    "gn:feature_class":"P",
    "gn:feature_code":"PPL",
    "gn:name":"\u2018Izbat al Waqf",
    "gn:population":0,
    "gn:timezone":"Africa/Cairo",
    "iso:country":"EG",
    "name:ara_x_preferred":[
        "\u0639\u0632\u0628\u0629 \u0627\u0644\u0648\u0642\u0641"
    ],
    "name:und_x_variant":[
        "\u2018Izbat al Waqf"
    ],
    "wof:name":"`Izbat al Waqf",
    "wof:placetype":"locality"
},
  "geometry": {"coordinates":[30.82419,31.18657],"type":"Point"}
}