{
  "type": "Feature",
  "properties": {
    "gn:admin1_code":"14",
    "gn:asciiname":"Kafr al Mashhad",
    "gn:country_code":"EG",
    "gn:dem":14,
    "gn:feature_class":"P",
    "gn:feature_code":"PPL",
    "gn:name":"Kafr al Mashhad",
    "gn:population":0,
    "gn:timezone":"Africa/Cairo",
    "iso:country":"EG",
    "name:ara_x_preferred":[
        "\u0643\u0641\u0631 \u0627\u0644\u0645\u0634\u0647\u062f"
    ],
    "name:und_x_variant":[
        "Kafr el-Mashhad",
        "Kafr al Mashhad"
    ],
    "wof:name":"Kafr al Mashhad",
    "wof:placetype":"locality"
},
  "geometry": {"coordinates":[31.60375,30.44383],"type":"Point"}
}