{
  "type": "Feature",
  "properties": {
    "gn:admin1_code":"09",
    "gn:asciiname":"Kafr ash Shaykh Tu`ayma",
    "gn:country_code":"EG",
    "gn:dem":14,
    "gn:feature_class":"P",
    "gn:feature_code":"PPL",
    "gn:name":"Kafr ash Shaykh \u0162u\u2018aym\u00e1",
    "gn:population":0,
    "gn:timezone":"Africa/Cairo",
    "iso:country":"EG",
    "name:ara_x_preferred":[
        "\u0643\u0641\u0631 \u0627\u0644\u0634\u064a\u062e \u0637\u0639\u064a\u0645\u0649"
    ],
    "name:und_x_variant":[
        "Kafr el-Sheikh \u1e6ci\u2018eima",
        "Kafr ash Shaykh \u0162u\u2018aymah",
        "Kafr ash Shaykh \u0162u\u2018aym\u00e1"
    ],
    "wof:name":"Kafr ash Shaykh Tu`ayma",
    "wof:placetype":"locality"
},
  "geometry": {"coordinates":[31.16653,30.63609000000001],"type":"Point"}
}