{
  "type": "Feature",
  "properties": {
    "gn:admin1_code":"14",
    "gn:asciiname":"`Izbat `Udah",
    "gn:country_code":"EG",
    "gn:dem":6,
    "gn:feature_class":"P",
    "gn:feature_code":"PPL",
    "gn:name":"\u2018Izbat \u2018Udah",
    "gn:population":0,
    "gn:timezone":"Africa/Cairo",
    "iso:country":"EG",
    "name:ara_x_preferred":[
        "\u0639\u0632\u0628\u0629 \u0639\u0648\u062f\u0629"
    ],
    "name:und_x_variant":[
        "\u2018Izbat \u2018Udah"
    ],
    "wof:name":"`Izbat `Udah",
    "wof:placetype":"locality"
},
  "geometry": {"coordinates":[31.7279,30.85276],"type":"Point"}
}