{
  "type": "Feature",
  "properties": {
    "gn:admin1_code":"14",
    "gn:asciiname":"`Izbat Ibrahim Sa`d",
    "gn:country_code":"EG",
    "gn:dem":3,
    "gn:feature_class":"P",
    "gn:feature_code":"PPL",
    "gn:name":"\u2018Izbat Ibr\u0101h\u012bm Sa\u2018d",
    "gn:population":0,
    "gn:timezone":"Africa/Cairo",
    "iso:country":"EG",
    "name:ara_x_preferred":[
        "\u0639\u0632\u0628\u0629 \u0625\u0628\u0631\u0627\u0647\u064a\u0645 \u0633\u0639\u062f"
    ],
    "name:und_x_variant":[
        "\u2018Izbat Ibr\u0101h\u012bm Sa\u2018d",
        "\u2018Ezbet Ibr\u00e2h\u00eem Sa\u2018d"
    ],
    "wof:name":"`Izbat Ibrahim Sa`d",
    "wof:placetype":"locality"
},
  "geometry": {"coordinates":[31.81621,31.03372],"type":"Point"}
}