{
  "type": "Feature",
  "properties": {
    "gn:admin1_code":"03",
    "gn:asciiname":"`Izbat Barquqah",
    "gn:country_code":"EG",
    "gn:dem":1,
    "gn:feature_class":"P",
    "gn:feature_code":"PPL",
    "gn:name":"\u2018Izbat Barq\u016bqah",
    "gn:population":0,
    "gn:timezone":"Africa/Cairo",
    "iso:country":"EG",
    "name:ara_x_preferred":[
        "\u0639\u0632\u0628\u0629 \u0628\u0631\u0642\u0648\u0642\u0629"
    ],
    "name:und_x_variant":[
        "\u2018Izbat Barq\u016bqah"
    ],
    "wof:name":"`Izbat Barquqah",
    "wof:placetype":"locality"
},
  "geometry": {"coordinates":[30.49222,31.08659],"type":"Point"}
}