{
  "type": "Feature",
  "properties": {
    "iso:country":"EG",
    "qs:gn_pop":0,
    "qs:name":"Badrashen",
    "qs:name_adm0":"\u0645\u0635\u0631",
    "qs:name_adm1":"\u0627\u0644\u0633\u0627\u062f\u0633 \u0645\u0646 \u0627\u0643\u062a\u0648\u0628\u0631",
    "qs:photos":857,
    "qs:photos_1k":174,
    "qs:photos_9k":4,
    "qs:photos_9r":6,
    "qs:photos_all":857,
    "qs:photos_sr":10,
    "qs:placetype":"Town",
    "qs:pop_sr":"0",
    "qs:woe_adm0":23424802,
    "wof:name":"Badrashen",
    "wof:placetype":"locality"
},
  "geometry": {"coordinates":[31.219711,29.869079],"type":"Point"}
}