{
  "type": "Feature",
  "properties": {
    "gn:admin1_code":"21",
    "gn:asciiname":"`Izbat Siraywah al Kubra",
    "gn:country_code":"EG",
    "gn:dem":3,
    "gn:feature_class":"P",
    "gn:feature_code":"PPL",
    "gn:name":"\u2018Izbat Siraywah al Kubr\u00e1",
    "gn:population":0,
    "gn:timezone":"Africa/Cairo",
    "iso:country":"EG",
    "name:ara_x_preferred":[
        "\u0639\u0632\u0628\u0629 \u0633\u0631\u064a\u0648\u0629 \u0627\u0644\u0643\u0628\u0631\u0649"
    ],
    "name:und_x_variant":[
        "\u2018Izbat Siraywah al Kubr\u00e1",
        "\u2018Izbat Suraywah al Kubr\u00e1"
    ],
    "wof:name":"`Izbat Siraywah al Kubra",
    "wof:placetype":"locality"
},
  "geometry": {"coordinates":[31.24097,31.27548],"type":"Point"}
}