{
  "type": "Feature",
  "properties": {
    "gn:admin1_code":"17",
    "gn:asciiname":"Naj` `Arab Salim Sulayman",
    "gn:country_code":"EG",
    "gn:dem":45,
    "gn:feature_class":"P",
    "gn:feature_code":"PPL",
    "gn:name":"Naj\u2018 \u2018Arab S\u0101lim Sulaym\u0101n",
    "gn:population":0,
    "gn:timezone":"Africa/Cairo",
    "iso:country":"EG",
    "name:und_x_variant":[
        "Qab\u012blat al Jahm\u0101\u2019",
        "Nag\u2018 \u2018Arab S\u00e2lim Sulim\u00e2n",
        "Qab\u00eelet el Gahma",
        "Naj\u2018 \u2018Arab S\u0101lim Sulaym\u0101n"
    ],
    "wof:name":"Naj` `Arab Salim Sulayman",
    "wof:placetype":"locality"
},
  "geometry": {"coordinates":[30.81667,27.46667],"type":"Point"}
}