{
  "type": "Feature",
  "properties": {
    "gn:admin1_code":"03",
    "gn:asciiname":"Al Haddayn",
    "gn:country_code":"EG",
    "gn:dem":3,
    "gn:feature_class":"P",
    "gn:feature_code":"PPL",
    "gn:name":"Al \u1e28addayn",
    "gn:population":0,
    "gn:timezone":"Africa/Cairo",
    "iso:country":"EG",
    "name:und_x_variant":[
        "El-\u1e24addein",
        "Al \u1e28addayn"
    ],
    "wof:name":"Al Haddayn",
    "wof:placetype":"locality"
},
  "geometry": {"coordinates":[30.63052,30.73565],"type":"Point"}
}