{
  "type": "Feature",
  "properties": {
    "gn:admin1_code":"14",
    "gn:asciiname":"`Izbat Abu ad Dahab",
    "gn:country_code":"EG",
    "gn:dem":9,
    "gn:feature_class":"P",
    "gn:feature_code":"PPL",
    "gn:name":"\u2018Izbat Ab\u016b ad Dahab",
    "gn:population":0,
    "gn:timezone":"Africa/Cairo",
    "iso:country":"EG",
    "name:ara_x_preferred":[
        "\u0639\u0632\u0628\u0629 \u0623\u0628\u0648 \u0627\u0644\u062f\u0647\u0628"
    ],
    "name:und_x_variant":[
        "\u2018Izbat Ab\u016b ad Dahab"
    ],
    "wof:name":"`Izbat Abu ad Dahab",
    "wof:placetype":"locality"
},
  "geometry": {"coordinates":[31.63706,30.58988],"type":"Point"}
}