{
  "type": "Feature",
  "properties": {
    "gn:admin1_code":"17",
    "gn:asciiname":"Al Bayyadiyah",
    "gn:cc2":"EG",
    "gn:country_code":"EG",
    "gn:dem":52,
    "gn:feature_class":"P",
    "gn:feature_code":"PPL",
    "gn:name":"Al Bayy\u0101\u1e11\u012byah",
    "gn:population":0,
    "gn:timezone":"Africa/Cairo",
    "iso:country":"EG",
    "name:und_x_variant":[
        "El Baiy\u00e2d\u00eeya",
        "Al Bayy\u0101\u1e11\u012byah"
    ],
    "wof:name":"Al Bayyadiyah",
    "wof:placetype":"locality"
},
  "geometry": {"coordinates":[31.45,26.95],"type":"Point"}
}