{
  "type": "Feature",
  "properties": {
    "gn:admin1_code":"14",
    "gn:asciiname":"Nubah",
    "gn:country_code":"EG",
    "gn:dem":12,
    "gn:feature_class":"P",
    "gn:feature_code":"PPL",
    "gn:name":"N\u016bbah",
    "gn:population":0,
    "gn:timezone":"Africa/Cairo",
    "iso:country":"EG",
    "name:ara_x_preferred":[
        "\u0646\u0648\u0628\u0629"
    ],
    "name:und_x_variant":[
        "N\u00fbba",
        "N\u016bbah"
    ],
    "wof:name":"Nubah",
    "wof:placetype":"locality"
},
  "geometry": {"coordinates":[31.55653,30.48256],"type":"Point"}
}