{
  "type": "Feature",
  "properties": {
    "gn:admin1_code":"01",
    "gn:asciiname":"`Izbat al Baghdadi",
    "gn:country_code":"EG",
    "gn:dem":4,
    "gn:feature_class":"P",
    "gn:feature_code":"PPL",
    "gn:name":"\u2018Izbat al Baghd\u0101d\u012b",
    "gn:population":0,
    "gn:timezone":"Africa/Cairo",
    "iso:country":"EG",
    "name:ara_x_preferred":[
        "\u0639\u0632\u0628\u0629 \u0627\u0644\u0628\u063a\u062f\u0627\u062f\u064a"
    ],
    "name:und_x_variant":[
        "\u2018Izbat al Baghd\u0101d\u012b"
    ],
    "wof:name":"`Izbat al Baghdadi",
    "wof:placetype":"locality"
},
  "geometry": {"coordinates":[31.43911,31.29478],"type":"Point"}
}