{
  "type": "Feature",
  "properties": {
    "gn:admin1_code":"14",
    "gn:asciiname":"Kafr Qabtan",
    "gn:country_code":"EG",
    "gn:dem":7,
    "gn:feature_class":"P",
    "gn:feature_code":"PPL",
    "gn:name":"Kafr Qab\u0163\u0101n",
    "gn:population":0,
    "gn:timezone":"Africa/Cairo",
    "iso:country":"EG",
    "name:ara_x_preferred":[
        "\u0643\u0641\u0631 \u0642\u0628\u0637\u0627\u0646"
    ],
    "name:und_x_variant":[
        "Kafr Qab\u0163\u0101n"
    ],
    "wof:name":"Kafr Qabtan",
    "wof:placetype":"locality"
},
  "geometry": {"coordinates":[31.69458,30.77631],"type":"Point"}
}