{
  "type": "Feature",
  "properties": {
    "gn:admin1_code":"14",
    "gn:asciiname":"`Izbat Anjah",
    "gn:country_code":"EG",
    "gn:dem":7,
    "gn:feature_class":"P",
    "gn:feature_code":"PPL",
    "gn:name":"\u2018Izbat Anjah",
    "gn:population":0,
    "gn:timezone":"Africa/Cairo",
    "iso:country":"EG",
    "name:ara_x_preferred":[
        "\u0639\u0632\u0628\u0629 \u0623\u0646\u062c\u0629"
    ],
    "name:und_x_variant":[
        "\u2018Izbat Anjah"
    ],
    "wof:name":"`Izbat Anjah",
    "wof:placetype":"locality"
},
  "geometry": {"coordinates":[31.56793,30.77075],"type":"Point"}
}