{
  "type": "Feature",
  "properties": {
    "gn:admin1_code":"04",
    "gn:asciiname":"`Ezbet Butrus Sa`d",
    "gn:country_code":"EG",
    "gn:dem":4,
    "gn:feature_class":"P",
    "gn:feature_code":"PPL",
    "gn:name":"\u2018Ezbet Bu\u1e6drus Sa\u2018d",
    "gn:population":0,
    "gn:timezone":"Africa/Cairo",
    "iso:country":"EG",
    "wof:name":"`Ezbet Butrus Sa`d",
    "wof:placetype":"locality"
},
  "geometry": {"coordinates":[30.58333,29.35],"type":"Point"}
}