{
  "type": "Feature",
  "properties": {
    "gn:admin1_code":"21",
    "gn:asciiname":"Kafr al Lubaydi",
    "gn:country_code":"EG",
    "gn:dem":7,
    "gn:feature_class":"P",
    "gn:feature_code":"PPL",
    "gn:name":"Kafr al Lubayd\u012b",
    "gn:population":0,
    "gn:timezone":"Africa/Cairo",
    "iso:country":"EG",
    "name:ara_x_preferred":[
        "\u0643\u0641\u0631 \u0627\u0644\u0644\u0628\u064a\u062f\u064a"
    ],
    "name:und_x_variant":[
        "Kafr al Lubayd\u012b"
    ],
    "wof:name":"Kafr al Lubaydi",
    "wof:placetype":"locality"
},
  "geometry": {"coordinates":[30.76269000000001,31.04387],"type":"Point"}
}