{
  "type": "Feature",
  "properties": {
    "gn:admin1_code":"05",
    "gn:asciiname":"Difrah",
    "gn:country_code":"EG",
    "gn:dem":16,
    "gn:feature_class":"P",
    "gn:feature_code":"PPL",
    "gn:name":"Difrah",
    "gn:population":0,
    "gn:timezone":"Africa/Cairo",
    "iso:country":"EG",
    "name:ara_x_preferred":[
        "\u062f\u0641\u0631\u0629"
    ],
    "name:und_x_variant":[
        "Difra",
        "Difrah"
    ],
    "wof:name":"Difrah",
    "wof:placetype":"locality"
},
  "geometry": {"coordinates":[31.02501,30.72593],"type":"Point"}
}