{
  "type": "Feature",
  "properties": {
    "gn:admin1_code":"05",
    "gn:asciiname":"Shinraq",
    "gn:country_code":"EG",
    "gn:dem":14,
    "gn:feature_class":"P",
    "gn:feature_code":"PPL",
    "gn:name":"Shinr\u0101q",
    "gn:population":0,
    "gn:timezone":"Africa/Cairo",
    "iso:country":"EG",
    "name:ara_x_preferred":[
        "Shinr\u0101q"
    ],
    "name:ara_x_variant":[
        "\u0634\u0646\u0631\u0627\u0642"
    ],
    "name:und_x_variant":[
        "Shinr\u00e2q"
    ],
    "wof:name":"Shinraq",
    "wof:placetype":"locality"
},
  "geometry": {"coordinates":[31.15713,30.81189],"type":"Point"}
}