{
  "type": "Feature",
  "properties": {
    "gn:admin1_code":"10",
    "gn:asciiname":"Kafr al Mansurah al Qibli",
    "gn:cc2":"EG",
    "gn:country_code":"EG",
    "gn:dem":41,
    "gn:feature_class":"P",
    "gn:feature_code":"PPL",
    "gn:name":"Kafr al Man\u015f\u016brah al Qibl\u012b",
    "gn:population":0,
    "gn:timezone":"Africa/Cairo",
    "iso:country":"EG",
    "name:und_x_variant":[
        "Kafr al Mans\u00fbra el Qibli",
        "Kafr al Man\u015f\u016brah al Qibl\u012b"
    ],
    "wof:name":"Kafr al Mansurah al Qibli",
    "wof:placetype":"locality"
},
  "geometry": {"coordinates":[30.75,28.08333],"type":"Point"}
}