{
  "type": "Feature",
  "properties": {
    "gn:admin1_code":"03",
    "gn:asciiname":"`Izbat `Uthman as Sa`idi",
    "gn:country_code":"EG",
    "gn:dem":10,
    "gn:feature_class":"P",
    "gn:feature_code":"PPL",
    "gn:name":"\u2018Izbat \u2018Uthm\u0101n a\u015f \u015ea\u2018\u012bd\u012b",
    "gn:population":0,
    "gn:timezone":"Africa/Cairo",
    "iso:country":"EG",
    "name:ara_x_preferred":[
        "\u0639\u0632\u0628\u0629 \u0639\u062b\u0645\u0627\u0646 \u0627\u0644\u0635\u0639\u064a\u062f\u064a"
    ],
    "name:und_x_variant":[
        "\u2018Izbat \u2018Uthm\u0101n a\u015f \u015ea\u2018\u012bd\u012b",
        "\u2018Izbat \u2018Uthm\u0101n a\u1e63-\u1e62a\u2018\u012bd\u012b"
    ],
    "wof:name":"`Izbat `Uthman as Sa`idi",
    "wof:placetype":"locality"
},
  "geometry": {"coordinates":[30.80742,30.48601],"type":"Point"}
}