{
  "type": "Feature",
  "properties": {
    "gn:admin1_code":"12",
    "gn:asciiname":"Sanafir",
    "gn:country_code":"EG",
    "gn:dem":18,
    "gn:feature_class":"P",
    "gn:feature_code":"PPL",
    "gn:name":"\u015ean\u0101f\u012br",
    "gn:population":0,
    "gn:timezone":"Africa/Cairo",
    "iso:country":"EG",
    "name:ara_x_preferred":[
        "\u0635\u0646\u0627\u0641\u064a\u0631"
    ],
    "name:und_x_variant":[
        "\u015ean\u0101f\u012br"
    ],
    "wof:name":"Sanafir",
    "wof:placetype":"locality"
},
  "geometry": {"coordinates":[31.17022,30.2203],"type":"Point"}
}