{
  "type": "Feature",
  "properties": {
    "gn:admin1_code":"03",
    "gn:asciiname":"`Izbat al Faransawiyah",
    "gn:country_code":"EG",
    "gn:dem":0,
    "gn:feature_class":"P",
    "gn:feature_code":"PPL",
    "gn:name":"\u2018Izbat al Farans\u0101w\u012byah",
    "gn:population":0,
    "gn:timezone":"Africa/Cairo",
    "iso:country":"EG",
    "name:ara_x_preferred":[
        "\u0639\u0632\u0628\u0629 \u0627\u0644\u0641\u0631\u0646\u0633\u0627\u0648\u064a\u0629"
    ],
    "name:und_x_variant":[
        "\u2018Izbat al Farans\u0101w\u012byah"
    ],
    "wof:name":"`Izbat al Faransawiyah",
    "wof:placetype":"locality"
},
  "geometry": {"coordinates":[30.43584,31.18685],"type":"Point"}
}