{
  "type": "Feature",
  "properties": {
    "gn:admin1_code":"09",
    "gn:asciiname":"`Izbat `Ali `Abd ar Rahman",
    "gn:country_code":"EG",
    "gn:dem":11,
    "gn:feature_class":"P",
    "gn:feature_code":"PPL",
    "gn:name":"\u2018Izbat \u2018Al\u012b \u2018Abd ar Ra\u1e29m\u0101n",
    "gn:population":0,
    "gn:timezone":"Africa/Cairo",
    "iso:country":"EG",
    "name:ara_x_preferred":[
        "\u0639\u0632\u0628\u0629 \u0639\u0644\u064a \u0639\u0628\u062f \u0627\u0644\u0631\u062d\u0645\u0646"
    ],
    "name:und_x_variant":[
        "\u2018Izbat \u2018Al\u012b \u2018Abd ar Ra\u1e29m\u0101n",
        "\u2018Izbat \u2018Al\u012b \u2018Abd ar-Ra\u1e25m\u0101n"
    ],
    "wof:name":"`Izbat `Ali `Abd ar Rahman",
    "wof:placetype":"locality"
},
  "geometry": {"coordinates":[30.97258,30.45545],"type":"Point"}
}