{
  "type": "Feature",
  "properties": {
    "gn:admin1_code":"11",
    "gn:asciiname":"Al Ma`sarah",
    "gn:country_code":"EG",
    "gn:dem":26,
    "gn:feature_class":"P",
    "gn:feature_code":"PPL",
    "gn:name":"Al Ma\u2018\u015farah",
    "gn:population":0,
    "gn:timezone":"Africa/Cairo",
    "iso:country":"EG",
    "name:und_x_variant":[
        "El Ma\u2018\u1e63ara",
        "El-Maasara",
        "Al Ma\u2018\u015farah"
    ],
    "wof:name":"Al Ma`sarah",
    "wof:placetype":"locality"
},
  "geometry": {"coordinates":[31.2894,29.9022],"type":"Point"}
}