{
  "type": "Feature",
  "properties": {
    "gn:admin1_code":"01",
    "gn:asciiname":"Kafr ar Ruk",
    "gn:country_code":"EG",
    "gn:dem":10,
    "gn:feature_class":"P",
    "gn:feature_code":"PPL",
    "gn:name":"Kafr ar R\u016bk",
    "gn:population":0,
    "gn:timezone":"Africa/Cairo",
    "iso:country":"EG",
    "name:ara_x_preferred":[
        "\u0643\u0641\u0631 \u0627\u0644\u0631\u0648\u0643"
    ],
    "name:und_x_variant":[
        "Kafr el-R\u00f4k",
        "Kafr ar Rawk",
        "Kafr ar R\u016bk",
        "Kafr ar-R\u016bk"
    ],
    "wof:name":"Kafr ar Ruk",
    "wof:placetype":"locality"
},
  "geometry": {"coordinates":[31.40436,30.82924],"type":"Point"}
}