{
  "type": "Feature",
  "properties": {
    "gn:admin1_code":"09",
    "gn:asciiname":"`Amrus",
    "gn:country_code":"EG",
    "gn:dem":10,
    "gn:feature_class":"P",
    "gn:feature_code":"PPL",
    "gn:name":"\u2018Amr\u016bs",
    "gn:population":0,
    "gn:timezone":"Africa/Cairo",
    "iso:country":"EG",
    "name:und_x_variant":[
        "\u2018Amr\u00fbs",
        "\u2018Amr\u016bs"
    ],
    "wof:name":"`Amrus",
    "wof:placetype":"locality"
},
  "geometry": {"coordinates":[30.80477,30.66457],"type":"Point"}
}