{
  "type": "Feature",
  "properties": {
    "gn:admin1_code":"03",
    "gn:asciiname":"Al Mu`aysirah",
    "gn:country_code":"EG",
    "gn:dem":8,
    "gn:feature_class":"P",
    "gn:feature_code":"PPL",
    "gn:name":"Al Mu\u2018ay\u015firah",
    "gn:population":0,
    "gn:timezone":"Africa/Cairo",
    "iso:country":"EG",
    "name:ara_x_preferred":[
        "\u0627\u0644\u0645\u0639\u064a\u0635\u0631\u0629"
    ],
    "name:und_x_variant":[
        "El-Mi\u2018eisra",
        "Al Mu\u2018ay\u015firah",
        "Al-Mi\u2018ay\u1e63rah"
    ],
    "wof:name":"Al Mu`aysirah",
    "wof:placetype":"locality"
},
  "geometry": {"coordinates":[30.71133,31.02508],"type":"Point"}
}