{
  "type": "Feature",
  "properties": {
    "gn:admin1_code":"21",
    "gn:asciiname":"`Izbat al Quni",
    "gn:country_code":"EG",
    "gn:dem":4,
    "gn:feature_class":"P",
    "gn:feature_code":"PPL",
    "gn:name":"\u2018Izbat al Qun\u012b",
    "gn:population":0,
    "gn:timezone":"Africa/Cairo",
    "iso:country":"EG",
    "name:ara_x_preferred":[
        "\u0639\u0632\u0628\u0629 \u0627\u0644\u0642\u0646\u064a"
    ],
    "name:und_x_variant":[
        "El-Quni",
        "Al Qun\u012b",
        "\u2018Izbat al Qun\u012b"
    ],
    "wof:name":"`Izbat al Quni",
    "wof:placetype":"locality"
},
  "geometry": {"coordinates":[30.5578,31.30714],"type":"Point"}
}