{
  "type": "Feature",
  "properties": {
    "gn:admin1_code":"14",
    "gn:asciiname":"`Izbat Musa Thabit",
    "gn:country_code":"EG",
    "gn:dem":10,
    "gn:feature_class":"P",
    "gn:feature_code":"PPL",
    "gn:name":"\u2018Izbat M\u016bs\u00e1 Th\u0101bit",
    "gn:population":0,
    "gn:timezone":"Africa/Cairo",
    "iso:country":"EG",
    "name:ara_x_preferred":[
        "\u0639\u0632\u0628\u0629 \u0645\u0648\u0633\u0649 \u062b\u0627\u0628\u062a"
    ],
    "name:und_x_variant":[
        "\u2018Izbat M\u016bs\u00e1 Th\u0101bit"
    ],
    "wof:name":"`Izbat Musa Thabit",
    "wof:placetype":"locality"
},
  "geometry": {"coordinates":[31.64968,30.58792],"type":"Point"}
}