{
  "type": "Feature",
  "properties": {
    "gn:admin1_code":"03",
    "gn:asciiname":"`Izbat al Azhari",
    "gn:country_code":"EG",
    "gn:dem":6,
    "gn:feature_class":"P",
    "gn:feature_code":"PPL",
    "gn:name":"\u2018Izbat al Azhar\u012b",
    "gn:population":0,
    "gn:timezone":"Africa/Cairo",
    "iso:country":"EG",
    "name:ara_x_preferred":[
        "\u0639\u0632\u0628\u0629 \u0627\u0644\u0623\u0632\u0647\u0631\u064a"
    ],
    "name:und_x_variant":[
        "\u2018Izbat al Azhar\u012b"
    ],
    "wof:name":"`Izbat al Azhari",
    "wof:placetype":"locality"
},
  "geometry": {"coordinates":[30.68245,31.0682],"type":"Point"}
}