{
  "type": "Feature",
  "properties": {
    "gn:admin1_code":"10",
    "gn:asciiname":"Awlad ash Shaykh `Ali",
    "gn:country_code":"EG",
    "gn:dem":36,
    "gn:feature_class":"P",
    "gn:feature_code":"PPL",
    "gn:name":"Awl\u0101d ash Shaykh \u2018Al\u012b",
    "gn:population":0,
    "gn:timezone":"Africa/Cairo",
    "iso:country":"EG",
    "name:und_x_variant":[
        "Nazlat Awl\u0101d ash Shaykh",
        "Aul\u00e2d el Sheikh \u2018Ali",
        "Awl\u0101d ash Shaykh \u2018Al\u012b"
    ],
    "wof:name":"Awlad ash Shaykh `Ali",
    "wof:placetype":"locality"
},
  "geometry": {"coordinates":[30.75,28.41667],"type":"Point"}
}