{
  "type": "Feature",
  "properties": {
    "gn:admin1_code":"14",
    "gn:asciiname":"`Izbat Muhammad Tahah",
    "gn:country_code":"EG",
    "gn:dem":12,
    "gn:feature_class":"P",
    "gn:feature_code":"PPL",
    "gn:name":"\u2018Izbat Mu\u1e29ammad \u0162\u0101hah",
    "gn:population":0,
    "gn:timezone":"Africa/Cairo",
    "iso:country":"EG",
    "name:ara_x_preferred":[
        "\u0639\u0632\u0628\u0629 \u0645\u062d\u0645\u062f \u0637\u0647"
    ],
    "name:und_x_variant":[
        "\u2018Izbat Mu\u1e29ammad \u0162\u0101hah",
        "\u2018Izbat Mu\u1e25ammad \u1e6c\u0101ha"
    ],
    "wof:name":"`Izbat Muhammad Tahah",
    "wof:placetype":"locality"
},
  "geometry": {"coordinates":[31.80615,30.6094],"type":"Point"}
}