{
  "type": "Feature",
  "properties": {
    "gn:admin1_code":"14",
    "gn:asciiname":"`Izbat al Lakhmiyin",
    "gn:country_code":"EG",
    "gn:dem":8,
    "gn:feature_class":"P",
    "gn:feature_code":"PPL",
    "gn:name":"\u2018Izbat al Lakhm\u012by\u012bn",
    "gn:population":0,
    "gn:timezone":"Africa/Cairo",
    "iso:country":"EG",
    "name:ara_x_preferred":[
        "\u0639\u0632\u0628\u0629 \u0627\u0644\u0644\u062e\u0645\u064a\u064a\u0646"
    ],
    "name:und_x_variant":[
        "\u2018Izbat al Lakhm\u012by\u012bn",
        "\u2018Izbat al-Lakhmiyy\u012bn"
    ],
    "wof:name":"`Izbat al Lakhmiyin",
    "wof:placetype":"locality"
},
  "geometry": {"coordinates":[31.80666,30.69275],"type":"Point"}
}