{
  "type": "Feature",
  "properties": {
    "gn:admin1_code":"14",
    "gn:asciiname":"Bahnaya",
    "gn:country_code":"EG",
    "gn:dem":13,
    "gn:feature_class":"P",
    "gn:feature_code":"PPL",
    "gn:name":"Bahnay\u0101",
    "gn:population":0,
    "gn:timezone":"Africa/Cairo",
    "iso:country":"EG",
    "name:ara_x_preferred":[
        "\u0628\u0647\u0646\u064a\u0627"
    ],
    "name:und_x_variant":[
        "Bahnay\u0101"
    ],
    "wof:name":"Bahnaya",
    "wof:placetype":"locality"
},
  "geometry": {"coordinates":[31.38341,30.68964],"type":"Point"}
}