{
  "type": "Feature",
  "properties": {
    "gn:admin1_code":"09",
    "gn:asciiname":"`Izbat an Nashwah",
    "gn:country_code":"EG",
    "gn:dem":16,
    "gn:feature_class":"P",
    "gn:feature_code":"PPLF",
    "gn:name":"\u2018Izbat an Nashwah",
    "gn:population":0,
    "gn:timezone":"Africa/Cairo",
    "iso:country":"EG",
    "name:ara_x_preferred":[
        "\u0639\u0632\u0628\u0629 \u0627\u0644\u0646\u0634\u0648\u0629"
    ],
    "name:und_x_variant":[
        "\u2018Izbat an Nashwah",
        "\u2018Ezbet el-Nashwa"
    ],
    "wof:name":"`Izbat an Nashwah",
    "wof:placetype":"locality"
},
  "geometry": {"coordinates":[30.87772,30.37906],"type":"Point"}
}