{
  "type": "Feature",
  "properties": {
    "gn:admin1_code":"13",
    "gn:asciiname":"`Izbat Tulaytilah",
    "gn:country_code":"EG",
    "gn:dem":129,
    "gn:feature_class":"P",
    "gn:feature_code":"PPL",
    "gn:name":"\u2018Izbat \u0162ulay\u0163ilah",
    "gn:population":0,
    "gn:timezone":"Africa/Cairo",
    "iso:country":"EG",
    "name:und_x_variant":[
        "\u2018Azbet Tulaytlah",
        "\u2018Ezbet Tileitla",
        "\u2018Izbat \u0162ulay\u0163ilah"
    ],
    "wof:name":"`Izbat Tulaytilah",
    "wof:placetype":"locality"
},
  "geometry": {"coordinates":[29.23753,25.4833],"type":"Point"}
}