{
  "type": "Feature",
  "properties": {
    "gn:admin1_code":"10",
    "gn:asciiname":"Dahmaru",
    "gn:country_code":"EG",
    "gn:dem":36,
    "gn:feature_class":"P",
    "gn:feature_code":"PPL",
    "gn:name":"Dahmar\u016b",
    "gn:population":0,
    "gn:timezone":"Africa/Cairo",
    "iso:country":"EG",
    "wof:name":"Dahmaru",
    "wof:placetype":"locality"
},
  "geometry": {"coordinates":[30.81333,28.69062000000001],"type":"Point"}
}