{
  "type": "Feature",
  "properties": {
    "gn:admin1_code":"03",
    "gn:asciiname":"`Izbat al Minufi",
    "gn:country_code":"EG",
    "gn:dem":2,
    "gn:feature_class":"P",
    "gn:feature_code":"PPL",
    "gn:name":"\u2018Izbat al Min\u016bf\u012b",
    "gn:population":0,
    "gn:timezone":"Africa/Cairo",
    "iso:country":"EG",
    "name:ara_x_preferred":[
        "\u0639\u0632\u0628\u0629 \u0627\u0644\u0645\u0646\u0648\u0641\u064a"
    ],
    "name:und_x_variant":[
        "\u2018Izbat al Min\u016bf\u012b"
    ],
    "wof:name":"`Izbat al Minufi",
    "wof:placetype":"locality"
},
  "geometry": {"coordinates":[30.38865,31.10894],"type":"Point"}
}