{
  "type": "Feature",
  "properties": {
    "gn:admin1_code":"01",
    "gn:asciiname":"`Izbat Biljay as Sughra",
    "gn:country_code":"EG",
    "gn:dem":10,
    "gn:feature_class":"P",
    "gn:feature_code":"PPL",
    "gn:name":"\u2018Izbat Bilj\u0101y as \u015eughr\u00e1",
    "gn:population":0,
    "gn:timezone":"Africa/Cairo",
    "iso:country":"EG",
    "name:und_x_variant":[
        "\u2018Izbat Bilj\u0101y as \u015eughr\u00e1",
        "\u0639\u0632\u0628\u0629 \u0628\u0644\u062c\u0627\u064a \u0627\u0644\u0635\u063a\u0631\u064a",
        "\u2018Iz. Bilj\u0101y a\u1e63-\u1e62ughra"
    ],
    "wof:name":"`Izbat Biljay as Sughra",
    "wof:placetype":"locality"
},
  "geometry": {"coordinates":[31.39543,30.98346],"type":"Point"}
}