{
  "type": "Feature",
  "properties": {
    "gn:admin1_code":"02",
    "gn:asciiname":"Barramiya",
    "gn:country_code":"EG",
    "gn:dem":421,
    "gn:feature_class":"P",
    "gn:feature_code":"PPL",
    "gn:name":"Barr\u00e2m\u00eeya",
    "gn:population":0,
    "gn:timezone":"Africa/Cairo",
    "iso:country":"EG",
    "wof:name":"Barramiya",
    "wof:placetype":"locality"
},
  "geometry": {"coordinates":[33.78333,25.06667],"type":"Point"}
}