{
  "type": "Feature",
  "properties": {
    "gn:admin1_code":"14",
    "gn:asciiname":"Ad Didamun",
    "gn:country_code":"EG",
    "gn:dem":9,
    "gn:feature_class":"P",
    "gn:feature_code":"PPL",
    "gn:name":"Ad D\u012bd\u0101m\u016bn",
    "gn:population":0,
    "gn:timezone":"Africa/Cairo",
    "iso:country":"EG",
    "name:ara_x_preferred":[
        "\u0627\u0644\u062f\u064a\u062f\u0627\u0645\u0648\u0646"
    ],
    "name:und_x_variant":[
        "El-D\u00eed\u00e2m\u00fbn",
        "Ad D\u012bd\u0101m\u016bn"
    ],
    "wof:name":"Ad Didamun",
    "wof:placetype":"locality"
},
  "geometry": {"coordinates":[31.8029,30.7522],"type":"Point"}
}