{
  "type": "Feature",
  "properties": {
    "gn:admin1_code":"14",
    "gn:asciiname":"Kafr Faraj Jirjis",
    "gn:country_code":"EG",
    "gn:dem":16,
    "gn:feature_class":"P",
    "gn:feature_code":"PPL",
    "gn:name":"Kafr Faraj Jirjis",
    "gn:population":0,
    "gn:timezone":"Africa/Cairo",
    "iso:country":"EG",
    "name:ara_x_preferred":[
        "\u0643\u0641\u0631 \u0641\u0631\u062c \u062c\u0631\u062c\u0633"
    ],
    "name:und_x_variant":[
        "Kafr Farag Girgis",
        "Kafr Faraj Jirjis"
    ],
    "wof:name":"Kafr Faraj Jirjis",
    "wof:placetype":"locality"
},
  "geometry": {"coordinates":[31.33452,30.51436],"type":"Point"}
}