{
  "type": "Feature",
  "properties": {
    "gn:admin1_code":"12",
    "gn:asciiname":"Al Qalaj",
    "gn:country_code":"EG",
    "gn:dem":25,
    "gn:feature_class":"P",
    "gn:feature_code":"PPL",
    "gn:name":"Al Qalaj",
    "gn:population":0,
    "gn:timezone":"Africa/Cairo",
    "iso:country":"EG",
    "name:und_x_variant":[
        "El-Kalag",
        "El-Qalag",
        "Al Qalaj"
    ],
    "wof:name":"Al Qalaj",
    "wof:placetype":"locality"
},
  "geometry": {"coordinates":[31.35328,30.17781],"type":"Point"}
}