{
  "type": "Feature",
  "properties": {
    "gn:admin1_code":"05",
    "gn:asciiname":"`Izbat Rakinah",
    "gn:country_code":"EG",
    "gn:dem":10,
    "gn:feature_class":"P",
    "gn:feature_code":"PPL",
    "gn:name":"\u2018Izbat Rak\u012bnah",
    "gn:population":0,
    "gn:timezone":"Africa/Cairo",
    "iso:country":"EG",
    "name:ara_x_preferred":[
        "\u0639\u0632\u0628\u0629 \u0631\u0643\u064a\u0646\u0629"
    ],
    "name:und_x_variant":[
        "\u2018Izbat Rak\u012bnah"
    ],
    "wof:name":"`Izbat Rakinah",
    "wof:placetype":"locality"
},
  "geometry": {"coordinates":[31.24548,30.64463],"type":"Point"}
}