{
  "type": "Feature",
  "properties": {
    "gn:admin1_code":"17",
    "gn:asciiname":"As Sahil",
    "gn:country_code":"EG",
    "gn:dem":63,
    "gn:feature_class":"P",
    "gn:feature_code":"PPL",
    "gn:name":"As S\u0101\u1e29il",
    "gn:population":0,
    "gn:timezone":"Africa/Cairo",
    "iso:country":"EG",
    "name:ara_x_preferred":[
        "\u0633\u0627\u062d\u0644 \u0633\u0644\u064a\u0645"
    ],
    "name:arz_x_preferred":[
        "\u0633\u0627\u062d\u0644 \u0633\u0644\u064a\u0645"
    ],
    "name:fas_x_preferred":[
        "\u0633\u0627\u062d\u0644 \u0633\u0644\u06cc\u0645"
    ],
    "name:pol_x_preferred":[
        "Sahil Salim"
    ],
    "name:rus_x_preferred":[
        "\u0421\u0430\u0445\u0438\u043b\u044c-\u0421\u0430\u043b\u0438\u043c"
    ],
    "name:und_x_variant":[
        "El S\u00e2hil",
        "Es S\u0101hil",
        "Sahil Siliim",
        "As S\u0101\u1e29il"
    ],
    "wof:name":"As Sahil",
    "wof:placetype":"locality"
},
  "geometry": {"coordinates":[31.34283,27.06333],"type":"Point"}
}