{
  "type": "Feature",
  "properties": {
    "gn:admin1_code":"03",
    "gn:asciiname":"Itay al Barud",
    "gn:country_code":"EG",
    "gn:dem":8,
    "gn:feature_class":"P",
    "gn:feature_code":"PPL",
    "gn:name":"\u012at\u0101y al B\u0101r\u016bd",
    "gn:population":0,
    "gn:timezone":"Africa/Cairo",
    "iso:country":"EG",
    "name:und_x_variant":[
        "El Bar\u00fbd",
        "Ity\u0101y al B\u0101r\u016bd",
        "Tell el Barud",
        "\u00cet\u00e2i el-B\u00e2r\u00fbd",
        "Ity\u00e2i el-B\u00e2r\u00fbd",
        "\u012at\u0101y al B\u0101r\u016bd"
    ],
    "wof:name":"Itay al Barud",
    "wof:placetype":"locality"
},
  "geometry": {"coordinates":[30.66575,30.88528],"type":"Point"}
}