{
  "type": "Feature",
  "properties": {
    "gn:admin1_code":"24",
    "gn:asciiname":"Al Bayadi",
    "gn:country_code":"EG",
    "gn:dem":72,
    "gn:feature_class":"P",
    "gn:feature_code":"PPL",
    "gn:name":"Al Bay\u0101\u1e11\u012b",
    "gn:population":0,
    "gn:timezone":"Africa/Cairo",
    "iso:country":"EG",
    "name:und_x_variant":[
        "El Bay\u00e2di",
        "Al Bay\u0101\u1e11\u012b wa Al Qaryah",
        "Al Bay\u0101\u1e11\u012b"
    ],
    "wof:name":"Al Bayadi",
    "wof:placetype":"locality"
},
  "geometry": {"coordinates":[31.88322,26.36143],"type":"Point"}
}