{
  "type": "Feature",
  "properties": {
    "gn:admin1_code":"21",
    "gn:asciiname":"`Izbat al Hjjaziyah",
    "gn:country_code":"EG",
    "gn:dem":1,
    "gn:feature_class":"P",
    "gn:feature_code":"PPL",
    "gn:name":"\u2018Izbat al \u1e28jj\u0101z\u012byah",
    "gn:population":0,
    "gn:timezone":"Africa/Cairo",
    "iso:country":"EG",
    "name:ara_x_preferred":[
        "\u0639\u0632\u0628\u0629 \u0627\u0644\u062d\u062c\u0627\u0632\u064a\u0629"
    ],
    "name:und_x_variant":[
        "\u2018Izbat al \u1e28jj\u0101z\u012byah"
    ],
    "wof:name":"`Izbat al Hjjaziyah",
    "wof:placetype":"locality"
},
  "geometry": {"coordinates":[30.63006,31.30726],"type":"Point"}
}