{
  "type": "Feature",
  "properties": {
    "gn:admin1_code":"13",
    "gn:asciiname":"Ar Rashidah",
    "gn:country_code":"EG",
    "gn:dem":95,
    "gn:feature_class":"P",
    "gn:feature_code":"PPL",
    "gn:name":"Ar R\u0101shidah",
    "gn:population":0,
    "gn:timezone":"Africa/Cairo",
    "iso:country":"EG",
    "name:und_x_variant":[
        "Er Rashda",
        "Rashida",
        "El Rashda",
        "Ar R\u0101shidah"
    ],
    "wof:name":"Ar Rashidah",
    "wof:placetype":"locality"
},
  "geometry": {"coordinates":[28.94123,25.58255],"type":"Point"}
}