{
  "type": "Feature",
  "properties": {
    "gn:admin1_code":"12",
    "gn:asciiname":"Kafr ad Dayr",
    "gn:country_code":"EG",
    "gn:dem":21,
    "gn:feature_class":"P",
    "gn:feature_code":"PPL",
    "gn:name":"Kafr ad Dayr",
    "gn:population":0,
    "gn:timezone":"Africa/Cairo",
    "iso:country":"EG",
    "name:und_x_variant":[
        "Kafr el-Deir",
        "Kafr ad Dayr"
    ],
    "wof:name":"Kafr ad Dayr",
    "wof:placetype":"locality"
},
  "geometry": {"coordinates":[31.28169,30.30867000000001],"type":"Point"}
}