{
  "type": "Feature",
  "properties": {
    "gn:admin1_code":"01",
    "gn:asciiname":"Kafr `Azzam",
    "gn:country_code":"EG",
    "gn:dem":8,
    "gn:feature_class":"P",
    "gn:feature_code":"PPL",
    "gn:name":"Kafr \u2018Azz\u0101m",
    "gn:population":0,
    "gn:timezone":"Africa/Cairo",
    "iso:country":"EG",
    "name:und_x_variant":[
        "Kafr \u2018Azz\u0101m"
    ],
    "wof:name":"Kafr `Azzam",
    "wof:placetype":"locality"
},
  "geometry": {"coordinates":[31.51068,30.83448],"type":"Point"}
}