{
  "type": "Feature",
  "properties": {
    "gn:admin1_code":"03",
    "gn:asciiname":"Kawm at Tayyar",
    "gn:country_code":"EG",
    "gn:dem":4,
    "gn:feature_class":"P",
    "gn:feature_code":"PPL",
    "gn:name":"Kawm a\u0163 \u0162ayy\u0101r",
    "gn:population":0,
    "gn:timezone":"Africa/Cairo",
    "iso:country":"EG",
    "name:ara_x_preferred":[
        "\u0643\u0648\u0645 \u0627\u0644\u0637\u064a\u0627\u0631"
    ],
    "name:und_x_variant":[
        "Kawm a\u0163 \u0162ayy\u0101r",
        "Kawm a\u1e6d-\u1e6cayy\u0101r"
    ],
    "wof:name":"Kawm at Tayyar",
    "wof:placetype":"locality"
},
  "geometry": {"coordinates":[30.43871,31.05556],"type":"Point"}
}