{
  "type": "Feature",
  "properties": {
    "gn:admin1_code":"12",
    "gn:asciiname":"Ikyad Dijwi",
    "gn:country_code":"EG",
    "gn:dem":18,
    "gn:feature_class":"P",
    "gn:feature_code":"PPL",
    "gn:name":"Iky\u0101d Dijw\u012b",
    "gn:population":0,
    "gn:timezone":"Africa/Cairo",
    "iso:country":"EG",
    "name:ara_x_preferred":[
        "Iky\u0101d Dijw\u012b"
    ],
    "name:ara_x_variant":[
        "\u0625\u0643\u064a\u0627\u062f \u062f\u062c\u0648\u064a"
    ],
    "wof:name":"Ikyad Dijwi",
    "wof:placetype":"locality"
},
  "geometry": {"coordinates":[31.10312,30.36371],"type":"Point"}
}