{
  "type": "Feature",
  "properties": {
    "gn:admin1_code":"17",
    "gn:asciiname":"Nazlat al `Amriyah",
    "gn:country_code":"EG",
    "gn:dem":56,
    "gn:feature_class":"P",
    "gn:feature_code":"PPL",
    "gn:name":"Nazlat al \u2018Amr\u012byah",
    "gn:population":0,
    "gn:timezone":"Africa/Cairo",
    "iso:country":"EG",
    "wof:name":"Nazlat al `Amriyah",
    "wof:placetype":"locality"
},
  "geometry": {"coordinates":[31.45,26.98333],"type":"Point"}
}