{
  "type": "Feature",
  "properties": {
    "gn:admin1_code":"05",
    "gn:asciiname":"Salamun",
    "gn:country_code":"EG",
    "gn:dem":12,
    "gn:feature_class":"P",
    "gn:feature_code":"PPL",
    "gn:name":"Sal\u0101m\u016bn",
    "gn:population":0,
    "gn:timezone":"Africa/Cairo",
    "iso:country":"EG",
    "name:ara_x_preferred":[
        "\u0633\u0644\u0627\u0645\u0648\u0646"
    ],
    "name:und_x_variant":[
        "Sal\u00e2m\u00fbn el-Ghuy\u00e2r",
        "Sal\u00e2m\u00fbn el-Ghub\u00e2r",
        "Sal\u0101m\u016bn al Ghub\u0101r",
        "Sal\u0101m\u016bn"
    ],
    "wof:name":"Salamun",
    "wof:placetype":"locality"
},
  "geometry": {"coordinates":[30.81468,31.00027],"type":"Point"}
}