{
  "type": "Feature",
  "properties": {
    "gn:admin1_code":"01",
    "gn:asciiname":"`Izbat at Tarzi",
    "gn:country_code":"EG",
    "gn:dem":7,
    "gn:feature_class":"P",
    "gn:feature_code":"PPL",
    "gn:name":"\u2018Izbat at Tarz\u012b",
    "gn:population":0,
    "gn:timezone":"Africa/Cairo",
    "iso:country":"EG",
    "name:ara_x_preferred":[
        "\u0639\u0632\u0628\u0629 \u0627\u0644\u062a\u0631\u0632\u064a"
    ],
    "name:und_x_variant":[
        "\u2018Izbat at Tarz\u012b",
        "\u2018Ezbet el-Larzi",
        "\u2018Izbat at-Tarz\u012b"
    ],
    "wof:name":"`Izbat at Tarzi",
    "wof:placetype":"locality"
},
  "geometry": {"coordinates":[31.38541,31.21933],"type":"Point"}
}