{
  "type": "Feature",
  "properties": {
    "gn:admin1_code":"03",
    "gn:asciiname":"Qaryat Nasir",
    "gn:country_code":"EG",
    "gn:dem":7,
    "gn:feature_class":"P",
    "gn:feature_code":"PPL",
    "gn:name":"Qaryat N\u0101\u015fir",
    "gn:population":0,
    "gn:timezone":"Africa/Cairo",
    "iso:country":"EG",
    "wof:name":"Qaryat Nasir",
    "wof:placetype":"locality"
},
  "geometry": {"coordinates":[30.33613,30.79888],"type":"Point"}
}