{
  "type": "Feature",
  "properties": {
    "gn:admin1_code":"05",
    "gn:asciiname":"`Izbat `Amashah",
    "gn:country_code":"EG",
    "gn:dem":9,
    "gn:feature_class":"P",
    "gn:feature_code":"PPLF",
    "gn:name":"\u2018Izbat \u2018Am\u0101shah",
    "gn:population":0,
    "gn:timezone":"Africa/Cairo",
    "iso:country":"EG",
    "name:ara_x_preferred":[
        "\u0639\u0632\u0628\u0629 \u0639\u0645\u0627\u0634\u0629"
    ],
    "name:und_x_variant":[
        "\u2018Izbat \u2018Am\u0101shah"
    ],
    "wof:name":"`Izbat `Amashah",
    "wof:placetype":"locality"
},
  "geometry": {"coordinates":[31.26096,31.04568],"type":"Point"}
}