{
  "type": "Feature",
  "properties": {
    "gn:admin1_code":"03",
    "gn:asciiname":"Ad Dawdarah",
    "gn:country_code":"EG",
    "gn:dem":0,
    "gn:feature_class":"P",
    "gn:feature_code":"PPL",
    "gn:name":"Ad Dawdarah",
    "gn:population":0,
    "gn:timezone":"Africa/Cairo",
    "iso:country":"EG",
    "name:ara_x_preferred":[
        "\u0627\u0644\u062f\u0648\u062f\u0631\u0629"
    ],
    "wof:name":"Ad Dawdarah",
    "wof:placetype":"locality"
},
  "geometry": {"coordinates":[30.49563,31.15665],"type":"Point"}
}