{
  "type": "Feature",
  "properties": {
    "gn:admin1_code":"18",
    "gn:asciiname":"Al Qayat",
    "gn:country_code":"EG",
    "gn:dem":37,
    "gn:feature_class":"P",
    "gn:feature_code":"PPL",
    "gn:name":"Al Q\u0101y\u0101t",
    "gn:population":0,
    "gn:timezone":"Africa/Cairo",
    "iso:country":"EG",
    "name:und_x_variant":[
        "El-Q\u00e2iy\u00e2t",
        "Al Q\u0101y\u0101t"
    ],
    "wof:name":"Al Qayat",
    "wof:placetype":"locality"
},
  "geometry": {"coordinates":[30.68792,28.66637],"type":"Point"}
}