{
  "type": "Feature",
  "properties": {
    "gn:admin1_code":"21",
    "gn:asciiname":"Shubra Tu",
    "gn:country_code":"EG",
    "gn:dem":7,
    "gn:feature_class":"P",
    "gn:feature_code":"PPL",
    "gn:name":"Shubr\u0101 \u0162\u016b",
    "gn:population":0,
    "gn:timezone":"Africa/Cairo",
    "iso:country":"EG",
    "name:und_x_variant":[
        "Shubra \u1e6cu",
        "Shubr\u0101 \u0162\u016b"
    ],
    "wof:name":"Shubra Tu",
    "wof:placetype":"locality"
},
  "geometry": {"coordinates":[30.83958,30.99197],"type":"Point"}
}