{
  "type": "Feature",
  "properties": {
    "gn:admin1_code":"14",
    "gn:asciiname":"Hawd at Tarfah",
    "gn:country_code":"EG",
    "gn:dem":12,
    "gn:feature_class":"P",
    "gn:feature_code":"PPL",
    "gn:name":"\u1e28aw\u1e11 a\u0163 \u0162arfah",
    "gn:population":0,
    "gn:timezone":"Africa/Cairo",
    "iso:country":"EG",
    "name:ara_x_preferred":[
        "\u062d\u0648\u0636 \u0627\u0644\u0637\u0631\u0641\u0629"
    ],
    "name:und_x_variant":[
        "\u1e24\u00f4\u1e0d el-\u1e6carfa",
        "\u1e28aw\u1e11 a\u0163 \u0162arf\u0101\u2019",
        "\u1e28aw\u1e11 a\u0163 \u0162arfah"
    ],
    "wof:name":"Hawd at Tarfah",
    "wof:placetype":"locality"
},
  "geometry": {"coordinates":[31.39185,30.61834],"type":"Point"}
}