{
  "type": "Feature",
  "properties": {
    "gn:admin1_code":"21",
    "gn:asciiname":"`Izbah Raqm Arba`ah wa Sittun",
    "gn:country_code":"EG",
    "gn:dem":3,
    "gn:feature_class":"P",
    "gn:feature_code":"PPL",
    "gn:name":"\u2018Izbah Raqm Arba\u2018ah wa Sitt\u016bn",
    "gn:population":0,
    "gn:timezone":"Africa/Cairo",
    "iso:country":"EG",
    "name:ara_x_preferred":[
        "\u0639\u0632\u0628\u0629 \u0631\u0642\u0645 \u0666\u0664"
    ],
    "name:ara_x_variant":[
        "\u0639\u0632\u0628\u0629 \u0631\u0642\u0645 64"
    ],
    "name:und_x_variant":[
        "\u2018Izbah Raqm Arba\u2018ah wa Sitt\u016bn",
        "\u2018Izbah Raqm 64"
    ],
    "wof:name":"`Izbah Raqm Arba`ah wa Sittun",
    "wof:placetype":"locality"
},
  "geometry": {"coordinates":[31.09558,31.4517],"type":"Point"}
}