{
  "type": "Feature",
  "properties": {
    "gn:admin1_code":"06",
    "gn:asciiname":"Qaryat Ithnayn/Sab`ah",
    "gn:country_code":"EG",
    "gn:dem":-4,
    "gn:feature_class":"P",
    "gn:feature_code":"PPL",
    "gn:name":"Qaryat Ithnayn/Sab\u2018ah",
    "gn:population":0,
    "gn:timezone":"Africa/Cairo",
    "iso:country":"EG",
    "name:ara_x_preferred":[
        "\u0642\u0631\u064a\u0629 \u0667/\u0662"
    ],
    "name:und_x_variant":[
        "Qaryat Ithnayn/Sab\u2018ah",
        "Qaryat 2/7"
    ],
    "wof:name":"Qaryat Ithnayn/Sab`ah",
    "wof:placetype":"locality"
},
  "geometry": {"coordinates":[29.95603,31.14861],"type":"Point"}
}