{
  "type": "Feature",
  "properties": {
    "gn:admin1_code":"04",
    "gn:asciiname":"`Izbat al Manshiyah",
    "gn:country_code":"EG",
    "gn:dem":14,
    "gn:feature_class":"P",
    "gn:feature_code":"PPL",
    "gn:name":"\u2018Izbat al Mansh\u012byah",
    "gn:population":0,
    "gn:timezone":"Africa/Cairo",
    "iso:country":"EG",
    "name:und_x_variant":[
        "\u2018Ezbet el-Mans\u00eeya",
        "El Mansh\u00eeya",
        "\u2018Izbat al Mansh\u012byah"
    ],
    "wof:name":"`Izbat al Manshiyah",
    "wof:placetype":"locality"
},
  "geometry": {"coordinates":[30.82582,29.40169],"type":"Point"}
}