{
  "type": "Feature",
  "properties": {
    "gn:admin1_code":"04",
    "gn:asciiname":"Abu Salih",
    "gn:country_code":"EG",
    "gn:dem":23,
    "gn:feature_class":"P",
    "gn:feature_code":"PPL",
    "gn:name":"Ab\u00fb S\u00e2li\u1e25",
    "gn:population":0,
    "gn:timezone":"Africa/Cairo",
    "iso:country":"EG",
    "wof:name":"Abu Salih",
    "wof:placetype":"locality"
},
  "geometry": {"coordinates":[31.18333,29.18333],"type":"Point"}
}