{
  "type": "Feature",
  "properties": {
    "gn:admin1_code":"14",
    "gn:asciiname":"`Izbat Abu Zahran",
    "gn:country_code":"EG",
    "gn:dem":14,
    "gn:feature_class":"P",
    "gn:feature_code":"PPL",
    "gn:name":"\u2018Izbat Ab\u016b Zahr\u0101n",
    "gn:population":0,
    "gn:timezone":"Africa/Cairo",
    "iso:country":"EG",
    "name:ara_x_preferred":[
        "\u0639\u0632\u0628\u0629 \u0623\u0628\u0648 \u0632\u0647\u0631\u0627\u0646"
    ],
    "name:und_x_variant":[
        "\u2018Izbat Ab\u016b Zahr\u0101n"
    ],
    "wof:name":"`Izbat Abu Zahran",
    "wof:placetype":"locality"
},
  "geometry": {"coordinates":[31.69186,30.60944000000001],"type":"Point"}
}