{
  "type": "Feature",
  "properties": {
    "gn:admin1_code":"14",
    "gn:asciiname":"`Izbat al Malayiqah",
    "gn:country_code":"EG",
    "gn:dem":13,
    "gn:feature_class":"P",
    "gn:feature_code":"PPL",
    "gn:name":"\u2018Izbat al Mal\u0101yiqah",
    "gn:population":0,
    "gn:timezone":"Africa/Cairo",
    "iso:country":"EG",
    "name:ara_x_preferred":[
        "\u0639\u0632\u0628\u0629 \u0627\u0644\u0645\u0644\u0627\u064a\u0642\u0629"
    ],
    "name:und_x_variant":[
        "\u2018Izbat al Mal\u0101yiqah",
        "\u2018Izbat al Mal\u0101yqah"
    ],
    "wof:name":"`Izbat al Malayiqah",
    "wof:placetype":"locality"
},
  "geometry": {"coordinates":[31.57733,30.47437],"type":"Point"}
}