{
  "type": "Feature",
  "properties": {
    "gn:admin1_code":"06",
    "gn:asciiname":"Burj al `Arab",
    "gn:country_code":"EG",
    "gn:dem":25,
    "gn:feature_class":"P",
    "gn:feature_code":"PPL",
    "gn:name":"Burj al \u2018Arab",
    "gn:population":0,
    "gn:timezone":"Africa/Cairo",
    "iso:country":"EG",
    "name:und_x_variant":[
        "Burg el \u2018Arab",
        "Burj al \u2018Arab"
    ],
    "wof:name":"Burj al `Arab",
    "wof:placetype":"locality"
},
  "geometry": {"coordinates":[29.55357,30.90349],"type":"Point"}
}