{
  "type": "Feature",
  "properties": {
    "gn:admin1_code":"05",
    "gn:asciiname":"`Izbat Sharaf Hammudah",
    "gn:country_code":"EG",
    "gn:dem":12,
    "gn:feature_class":"P",
    "gn:feature_code":"PPL",
    "gn:name":"\u2018Izbat Sharaf \u1e28amm\u016bdah",
    "gn:population":0,
    "gn:timezone":"Africa/Cairo",
    "iso:country":"EG",
    "name:ara_x_preferred":[
        "\u0639\u0632\u0628\u0629 \u0634\u0631\u0641 \u062d\u0645\u0648\u062f\u0629"
    ],
    "name:und_x_variant":[
        "\u2018Izbat Sharaf \u1e28amm\u016bdah",
        "\u2018Izbat Sharaf \u1e24amm\u016bdah"
    ],
    "wof:name":"`Izbat Sharaf Hammudah",
    "wof:placetype":"locality"
},
  "geometry": {"coordinates":[31.06845,30.76206],"type":"Point"}
}