{
  "type": "Feature",
  "properties": {
    "gn:admin1_code":"03",
    "gn:asciiname":"Atlamis",
    "gn:country_code":"EG",
    "gn:dem":4,
    "gn:feature_class":"P",
    "gn:feature_code":"PPL",
    "gn:name":"A\u0163lam\u012bs",
    "gn:population":0,
    "gn:timezone":"Africa/Cairo",
    "iso:country":"EG",
    "name:und_x_variant":[
        "A\u1e6dlamas",
        "A\u0163lam\u012bs"
    ],
    "wof:name":"Atlamis",
    "wof:placetype":"locality"
},
  "geometry": {"coordinates":[30.50607,30.93199000000001],"type":"Point"}
}