{
  "type": "Feature",
  "properties": {
    "gn:admin1_code":"23",
    "gn:asciiname":"Naj` az Zunayqah",
    "gn:country_code":"EG",
    "gn:dem":83,
    "gn:feature_class":"P",
    "gn:feature_code":"PPL",
    "gn:name":"Naj\u2018 az Zunayqah",
    "gn:population":0,
    "gn:timezone":"Africa/Cairo",
    "iso:country":"EG",
    "wof:name":"Naj` az Zunayqah",
    "wof:placetype":"locality"
},
  "geometry": {"coordinates":[32.51013,25.38451],"type":"Point"}
}