{
  "type": "Feature",
  "properties": {
    "gn:admin1_code":"10.0",
    "gn:asciiname":"Tukh",
    "gn:country_code":"EG",
    "gn:dem":51,
    "gn:feature_class":"P",
    "gn:feature_code":"PPL",
    "gn:name":"\u0162\u016bkh",
    "gn:population":0,
    "gn:timezone":"Africa/Cairo",
    "iso:country":"EG",
    "wof:name":"Tukh",
    "wof:placetype":"locality"
},
  "geometry": {"coordinates":[30.81603,27.68293],"type":"Point"}
}