{
  "type": "Feature",
  "properties": {
    "gn:admin1_code":"14",
    "gn:asciiname":"Kafr al Qamamishah",
    "gn:cc2":"EG",
    "gn:country_code":"EG",
    "gn:dem":15,
    "gn:feature_class":"P",
    "gn:feature_code":"PPL",
    "gn:name":"Kafr al Qam\u0101mishah",
    "gn:population":0,
    "gn:timezone":"Africa/Cairo",
    "iso:country":"EG",
    "name:und_x_variant":[
        "Kafr el Qamenisha",
        "Kafr el-Qam\u00e2msha",
        "Kafr al Qam\u0101mishah"
    ],
    "wof:name":"Kafr al Qamamishah",
    "wof:placetype":"locality"
},
  "geometry": {"coordinates":[31.74972,30.60028],"type":"Point"}
}