{
  "type": "Feature",
  "properties": {
    "gn:admin1_code":"3.0",
    "gn:asciiname":"Zawiyat Nu`aym",
    "gn:country_code":"EG",
    "gn:dem":-1,
    "gn:feature_class":"P",
    "gn:feature_code":"PPL",
    "gn:name":"Z\u0101wiyat Nu\u2018aym",
    "gn:population":0,
    "gn:timezone":"Africa/Cairo",
    "iso:country":"EG",
    "name:und_x_variant":[
        "Z\u00e2wyet Na\u2018\u00eem",
        "Z\u00e2wyet Ni\u2018eim",
        "Z\u0101wiyat Nu\u2018aym"
    ],
    "wof:name":"Zawiyat Nu`aym",
    "wof:placetype":"locality"
},
  "geometry": {"coordinates":[30.34278,31.05306],"type":"Point"}
}