{
  "type": "Feature",
  "properties": {
    "gn:admin1_code":"14",
    "gn:asciiname":"Bishat Qa'id",
    "gn:country_code":"EG",
    "gn:dem":13,
    "gn:feature_class":"P",
    "gn:feature_code":"PPL",
    "gn:name":"B\u012bshat Q\u0101\u2019id",
    "gn:population":0,
    "gn:timezone":"Africa/Cairo",
    "iso:country":"EG",
    "name:ara_x_preferred":[
        "\u0628\u064a\u0634\u0629 \u0642\u0627\u064a\u062f"
    ],
    "name:und_x_variant":[
        "B\u00eeshet Q\u00e2yid",
        "B\u012bshat Q\u0101\u2019id"
    ],
    "wof:name":"Bishat Qa'id",
    "wof:placetype":"locality"
},
  "geometry": {"coordinates":[31.54188,30.63852],"type":"Point"}
}