{
  "type": "Feature",
  "properties": {
    "gn:admin1_code":"03",
    "gn:asciiname":"`Izbat al `Antabli",
    "gn:country_code":"EG",
    "gn:dem":-3,
    "gn:feature_class":"P",
    "gn:feature_code":"PPL",
    "gn:name":"\u2018Izbat al \u2018Antabl\u012b",
    "gn:population":0,
    "gn:timezone":"Africa/Cairo",
    "iso:country":"EG",
    "name:ara_x_preferred":[
        "\u0639\u0632\u0628\u0629 \u0627\u0644\u0639\u0646\u062a\u0628\u0644\u064a"
    ],
    "name:und_x_variant":[
        "\u2018Izbat al \u2018Antabl\u012b"
    ],
    "wof:name":"`Izbat al `Antabli",
    "wof:placetype":"locality"
},
  "geometry": {"coordinates":[30.25905,31.00642],"type":"Point"}
}