{
  "type": "Feature",
  "properties": {
    "gn:admin1_code":"05",
    "gn:asciiname":"Munsha'at as Santah",
    "gn:country_code":"EG",
    "gn:dem":13,
    "gn:feature_class":"P",
    "gn:feature_code":"PPL",
    "gn:name":"Munsha\u2019at as San\u0163ah",
    "gn:population":0,
    "gn:timezone":"Africa/Cairo",
    "iso:country":"EG",
    "name:ara_x_preferred":[
        "\u0645\u0646\u0634\u0623\u0629 \u0627\u0644\u0633\u0646\u0637\u0629"
    ],
    "name:und_x_variant":[
        "Minsh\u00e2t el-San\u1e6da",
        "Munsha\u2019at as San\u0163ah"
    ],
    "wof:name":"Munsha'at as Santah",
    "wof:placetype":"locality"
},
  "geometry": {"coordinates":[31.11886,30.72953],"type":"Point"}
}