{
  "type": "Feature",
  "properties": {
    "gn:admin1_code":"10",
    "gn:asciiname":"`Izbat Abu Janah",
    "gn:country_code":"EG",
    "gn:dem":35,
    "gn:feature_class":"P",
    "gn:feature_code":"PPL",
    "gn:name":"\u2018Izbat Ab\u016b Jan\u0101\u1e29",
    "gn:population":0,
    "gn:timezone":"Africa/Cairo",
    "iso:country":"EG",
    "name:und_x_variant":[
        "Nazlet Abu Gin\u00e2h",
        "\u2018Izbat Ab\u016b Jan\u0101\u1e29"
    ],
    "wof:name":"`Izbat Abu Janah",
    "wof:placetype":"locality"
},
  "geometry": {"coordinates":[30.86667000000001,27.95],"type":"Point"}
}