{
  "type": "Feature",
  "properties": {
    "gn:admin1_code":"01",
    "gn:asciiname":"Dumayrah",
    "gn:country_code":"EG",
    "gn:dem":18,
    "gn:feature_class":"P",
    "gn:feature_code":"PPL",
    "gn:name":"Dumayrah",
    "gn:population":0,
    "gn:timezone":"Africa/Cairo",
    "iso:country":"EG",
    "name:ara_x_preferred":[
        "\u062f\u0645\u064a\u0631\u0629"
    ],
    "name:und_x_variant":[
        "Demeira",
        "Dim\u012brah",
        "Dimeira",
        "Dumayrah",
        "Dimayrah"
    ],
    "wof:name":"Dumayrah",
    "wof:placetype":"locality"
},
  "geometry": {"coordinates":[31.36574,31.12769],"type":"Point"}
}