{
  "type": "Feature",
  "properties": {
    "gn:admin1_code":"12",
    "gn:asciiname":"Kafr ash Shaykh `Amir",
    "gn:country_code":"EG",
    "gn:dem":16,
    "gn:feature_class":"P",
    "gn:feature_code":"PPL",
    "gn:name":"Kafr ash Shaykh \u2018\u0100mir",
    "gn:population":0,
    "gn:timezone":"Africa/Cairo",
    "iso:country":"EG",
    "name:ara_x_preferred":[
        "\u0643\u0641\u0631 \u0627\u0644\u0634\u064a\u062e \u0639\u0627\u0645\u0631"
    ],
    "name:und_x_variant":[
        "Kafr el-Sheikh \u2018\u00c2mir",
        "Kafr \u2018\u00c2mir",
        "Kafr ash Shaykh \u2018\u0100mir"
    ],
    "wof:name":"Kafr ash Shaykh `Amir",
    "wof:placetype":"locality"
},
  "geometry": {"coordinates":[31.22784,30.51832000000001],"type":"Point"}
}