{
  "type": "Feature",
  "properties": {
    "gn:admin1_code":"12",
    "gn:asciiname":"`Izbat Hasan Qasim",
    "gn:country_code":"EG",
    "gn:dem":16,
    "gn:feature_class":"P",
    "gn:feature_code":"PPL",
    "gn:name":"\u2018Izbat \u1e28asan Q\u0101sim",
    "gn:population":0,
    "gn:timezone":"Africa/Cairo",
    "iso:country":"EG",
    "name:ara_x_preferred":[
        "\u0639\u0632\u0628\u0629 \u062d\u0633\u0646 \u0642\u0627\u0633\u0645"
    ],
    "name:und_x_variant":[
        "\u2018Izbat \u1e28asan Q\u0101sim"
    ],
    "wof:name":"`Izbat Hasan Qasim",
    "wof:placetype":"locality"
},
  "geometry": {"coordinates":[31.21551,30.39698],"type":"Point"}
}