{
  "type": "Feature",
  "properties": {
    "gn:admin1_code":"01",
    "gn:asciiname":"`Izbat Iskandar Fahmi",
    "gn:country_code":"EG",
    "gn:dem":7,
    "gn:feature_class":"P",
    "gn:feature_code":"PPL",
    "gn:name":"\u2018Izbat Iskandar Fahm\u012b",
    "gn:population":0,
    "gn:timezone":"Africa/Cairo",
    "iso:country":"EG",
    "name:ara_x_preferred":[
        "\u0639\u0632\u0628\u0629 \u0625\u0633\u0643\u0646\u062f\u0631 \u0641\u0647\u0645\u064a"
    ],
    "name:und_x_variant":[
        "\u2018Izbat Iskandar Fahm\u012b"
    ],
    "wof:name":"`Izbat Iskandar Fahmi",
    "wof:placetype":"locality"
},
  "geometry": {"coordinates":[31.46496,31.03916],"type":"Point"}
}