{
  "type": "Feature",
  "properties": {
    "gn:admin1_code":"01",
    "gn:asciiname":"Kafr Tanbul al Jadid",
    "gn:country_code":"EG",
    "gn:dem":12,
    "gn:feature_class":"P",
    "gn:feature_code":"PPL",
    "gn:name":"Kafr \u0162anb\u016bl al Jad\u012bd",
    "gn:population":0,
    "gn:timezone":"Africa/Cairo",
    "iso:country":"EG",
    "name:ara_x_preferred":[
        "\u0643\u0641\u0631 \u0637\u0646\u0628\u0648\u0644 \u0627\u0644\u062c\u062f\u064a\u062f"
    ],
    "name:und_x_variant":[
        "Kafr \u1e6camb\u00fbl el-Ged\u00eed",
        "Kafr \u0162anb\u016bl al Jad\u012bd",
        "Kafr \u1e6canb\u016bl al-Jad\u012bd"
    ],
    "wof:name":"Kafr Tanbul al Jadid",
    "wof:placetype":"locality"
},
  "geometry": {"coordinates":[31.39854,30.85896],"type":"Point"}
}