{
  "type": "Feature",
  "properties": {
    "gn:admin1_code":"14",
    "gn:asciiname":"Kafr al Madinah",
    "gn:country_code":"EG",
    "gn:dem":9,
    "gn:feature_class":"P",
    "gn:feature_code":"PPL",
    "gn:name":"Kafr al Mad\u012bnah",
    "gn:population":0,
    "gn:timezone":"Africa/Cairo",
    "iso:country":"EG",
    "name:und_x_variant":[
        "\u2018Ezbet Ibr\u00e2h\u00eem \u1e24usayn \u2018Omar",
        "Kafr al Mad\u012bnah"
    ],
    "wof:name":"Kafr al Madinah",
    "wof:placetype":"locality"
},
  "geometry": {"coordinates":[32.04444,30.89972],"type":"Point"}
}