{
  "type": "Feature",
  "properties": {
    "gn:admin1_code":"18",
    "gn:asciiname":"Nazlat Abu Salim",
    "gn:cc2":"EG",
    "gn:country_code":"EG",
    "gn:dem":28,
    "gn:feature_class":"P",
    "gn:feature_code":"PPL",
    "gn:name":"Nazlat Ab\u016b Sal\u012bm",
    "gn:population":0,
    "gn:timezone":"Africa/Cairo",
    "iso:country":"EG",
    "name:und_x_variant":[
        "Nazlet Abu Sil\u00eem",
        "Nazlat Ab\u016b Sal\u012bm"
    ],
    "wof:name":"Nazlat Abu Salim",
    "wof:placetype":"locality"
},
  "geometry": {"coordinates":[31.11667000000001,29.08333],"type":"Point"}
}