{
  "type": "Feature",
  "properties": {
    "gn:admin1_code":"15",
    "gn:asciiname":"Qaryat al Jana'in",
    "gn:country_code":"EG",
    "gn:dem":29,
    "gn:feature_class":"P",
    "gn:feature_code":"PPL",
    "gn:name":"Qaryat al Jan\u0101\u2019in",
    "gn:population":0,
    "gn:timezone":"Africa/Cairo",
    "iso:country":"EG",
    "name:und_x_variant":[
        "Qaryet el-Ganayin",
        "Qaryat al Jan\u0101\u2019in"
    ],
    "wof:name":"Qaryat al Jana'in",
    "wof:placetype":"locality"
},
  "geometry": {"coordinates":[32.51667,30.15],"type":"Point"}
}