{
  "type": "Feature",
  "properties": {
    "gn:admin1_code":"24",
    "gn:asciiname":"As Sahil Qibli",
    "gn:cc2":"EG",
    "gn:country_code":"EG",
    "gn:dem":63,
    "gn:feature_class":"P",
    "gn:feature_code":"PPL",
    "gn:name":"As S\u0101\u1e29il Qibl\u012b",
    "gn:population":0,
    "gn:timezone":"Africa/Cairo",
    "iso:country":"EG",
    "name:und_x_variant":[
        "El S\u00e2\u1e25il",
        "Es S\u0101hil Qibli",
        "El S\u00e2\u1e25il Qibl\u00ee",
        "As S\u0101\u1e29il Qibl\u012b"
    ],
    "wof:name":"As Sahil Qibli",
    "wof:placetype":"locality"
},
  "geometry": {"coordinates":[31.98333,26.25],"type":"Point"}
}