{
  "type": "Feature",
  "properties": {
    "gn:admin1_code":"21",
    "gn:asciiname":"Anglo Egyptian `Ezba",
    "gn:country_code":"EG",
    "gn:dem":3,
    "gn:feature_class":"P",
    "gn:feature_code":"PPL",
    "gn:name":"Anglo Egyptian \u2018Ezba",
    "gn:population":0,
    "gn:timezone":"Africa/Cairo",
    "iso:country":"EG",
    "wof:name":"Anglo Egyptian `Ezba",
    "wof:placetype":"locality"
},
  "geometry": {"coordinates":[31.01667,31.16667],"type":"Point"}
}