{
  "type": "Feature",
  "properties": {
    "gn:admin1_code":"03",
    "gn:asciiname":"Nikla al `Inab",
    "gn:country_code":"EG",
    "gn:dem":11,
    "gn:feature_class":"P",
    "gn:feature_code":"PPL",
    "gn:name":"Nikl\u00e1 al \u2018Inab",
    "gn:population":0,
    "gn:timezone":"Africa/Cairo",
    "iso:country":"EG",
    "name:und_x_variant":[
        "Nikla el-\u2018Inab",
        "Nekla Enab",
        "Nekla el Enab",
        "Nikl\u00e1 al \u2018Inab"
    ],
    "wof:name":"Nikla al `Inab",
    "wof:placetype":"locality"
},
  "geometry": {"coordinates":[30.75882,30.91124000000001],"type":"Point"}
}