{
  "type": "Feature",
  "properties": {
    "gn:admin1_code":"21",
    "gn:asciiname":"`Izbat al Makanah",
    "gn:country_code":"EG",
    "gn:dem":3,
    "gn:feature_class":"P",
    "gn:feature_code":"PPL",
    "gn:name":"\u2018Izbat al Makanah",
    "gn:population":0,
    "gn:timezone":"Africa/Cairo",
    "iso:country":"EG",
    "name:ara_x_preferred":[
        "\u0639\u0632\u0628\u0629 \u0627\u0644\u0645\u0643\u0646\u0629"
    ],
    "name:und_x_variant":[
        "\u2018Izbat al Makanah"
    ],
    "wof:name":"`Izbat al Makanah",
    "wof:placetype":"locality"
},
  "geometry": {"coordinates":[30.9294,31.24738],"type":"Point"}
}