{
  "type": "Feature",
  "properties": {
    "gn:admin1_code":"17",
    "gn:asciiname":"Naj` al Jazirah",
    "gn:country_code":"EG",
    "gn:dem":60,
    "gn:feature_class":"P",
    "gn:feature_code":"PPL",
    "gn:name":"Naj` al Jaz\u012brah",
    "gn:population":0,
    "gn:timezone":"Africa/Cairo",
    "iso:country":"EG",
    "wof:name":"Naj` al Jazirah",
    "wof:placetype":"locality"
},
  "geometry": {"coordinates":[31.44194,26.92806],"type":"Point"}
}