{
  "type": "Feature",
  "properties": {
    "gn:admin1_code":"17",
    "gn:asciiname":"Bani Shuqayr",
    "gn:country_code":"EG",
    "gn:dem":51,
    "gn:feature_class":"P",
    "gn:feature_code":"PPL",
    "gn:name":"Ban\u012b Shuqayr",
    "gn:population":0,
    "gn:timezone":"Africa/Cairo",
    "iso:country":"EG",
    "name:ara_x_preferred":[
        "\u0628\u0646\u064a \u0634\u0642\u064a\u0631"
    ],
    "name:und_x_variant":[
        "Ban\u012b Shugayr",
        "Beni Shoqeir",
        "Beni Shiqeir",
        "Beni Shiquir",
        "Ban\u012b Shuqayr"
    ],
    "wof:name":"Bani Shuqayr",
    "wof:placetype":"locality"
},
  "geometry": {"coordinates":[30.95359,27.36202],"type":"Point"}
}