{
  "type": "Feature",
  "properties": {
    "gn:admin1_code":"24",
    "gn:asciiname":"Al Wahliyah al Kabirah",
    "gn:cc2":"EG",
    "gn:country_code":"EG",
    "gn:dem":64,
    "gn:feature_class":"P",
    "gn:feature_code":"PPL",
    "gn:name":"Al Wa\u1e29l\u012byah al Kab\u012brah",
    "gn:population":0,
    "gn:timezone":"Africa/Cairo",
    "iso:country":"EG",
    "name:und_x_variant":[
        "El Wa\u1e25l\u00eeya el Keb\u00eera",
        "Al Wa\u1e29l\u012byah al Kab\u012brah"
    ],
    "wof:name":"Al Wahliyah al Kabirah",
    "wof:placetype":"locality"
},
  "geometry": {"coordinates":[31.91667,26.25],"type":"Point"}
}