{
  "type": "Feature",
  "properties": {
    "gn:admin1_code":"14",
    "gn:asciiname":"`Izbat Husayn al `Ayyat",
    "gn:country_code":"EG",
    "gn:dem":12,
    "gn:feature_class":"P",
    "gn:feature_code":"PPLF",
    "gn:name":"\u2018Izbat \u1e28usayn al \u2018Ayy\u0101\u0163",
    "gn:population":0,
    "gn:timezone":"Africa/Cairo",
    "iso:country":"EG",
    "name:ara_x_preferred":[
        "\u0639\u0632\u0628\u0629 \u062d\u0633\u064a\u0646 \u0627\u0644\u0639\u064a\u0627\u0637"
    ],
    "name:und_x_variant":[
        "\u2018Izbat \u1e28usayn al \u2018Ayy\u0101\u0163",
        "\u2018Izbat \u1e24usayn al-\u2018Ayy\u0101\u1e6d"
    ],
    "wof:name":"`Izbat Husayn al `Ayyat",
    "wof:placetype":"locality"
},
  "geometry": {"coordinates":[31.77124,30.50713],"type":"Point"}
}