{
  "type": "Feature",
  "properties": {
    "gn:admin1_code":"06",
    "gn:asciiname":"Qaryat Shuruq",
    "gn:country_code":"EG",
    "gn:dem":14,
    "gn:feature_class":"P",
    "gn:feature_code":"PPL",
    "gn:name":"Qaryat Shur\u016bq",
    "gn:population":0,
    "gn:timezone":"Africa/Cairo",
    "iso:country":"EG",
    "wof:name":"Qaryat Shuruq",
    "wof:placetype":"locality"
},
  "geometry": {"coordinates":[29.58514000000001,30.98364],"type":"Point"}
}