{
  "type": "Feature",
  "properties": {
    "gn:admin1_code":"21",
    "gn:asciiname":"At Tarawi",
    "gn:country_code":"EG",
    "gn:dem":5,
    "gn:feature_class":"P",
    "gn:feature_code":"PPL",
    "gn:name":"A\u0163 \u0162ar\u0101w\u012b",
    "gn:population":0,
    "gn:timezone":"Africa/Cairo",
    "iso:country":"EG",
    "name:ara_x_preferred":[
        "\u0627\u0644\u0637\u0631\u0627\u0648\u064a"
    ],
    "name:und_x_variant":[
        "A\u0163 \u0162ar\u0101w\u012b"
    ],
    "wof:name":"At Tarawi",
    "wof:placetype":"locality"
},
  "geometry": {"coordinates":[30.71159,31.25275],"type":"Point"}
}