{
  "type": "Feature",
  "properties": {
    "gn:admin1_code":"01",
    "gn:asciiname":"`Izbat Iskandar Naqqash",
    "gn:country_code":"EG",
    "gn:dem":6,
    "gn:feature_class":"P",
    "gn:feature_code":"PPL",
    "gn:name":"\u2018Izbat Iskandar Naqq\u0101sh",
    "gn:population":0,
    "gn:timezone":"Africa/Cairo",
    "iso:country":"EG",
    "name:ara_x_preferred":[
        "\u0639\u0632\u0628\u0629 \u0625\u0633\u0643\u0646\u062f\u0631 \u0646\u0642\u0627\u0634"
    ],
    "name:und_x_variant":[
        "\u2018Izbat Iskandar Naqq\u0101sh",
        "\u2018Iz. Iskandar Naqq\u0101sh"
    ],
    "wof:name":"`Izbat Iskandar Naqqash",
    "wof:placetype":"locality"
},
  "geometry": {"coordinates":[31.72511,31.12304],"type":"Point"}
}