{
  "type": "Feature",
  "properties": {
    "gn:admin1_code":"01",
    "gn:asciiname":"`Izbat Hasubah",
    "gn:country_code":"EG",
    "gn:dem":6,
    "gn:feature_class":"P",
    "gn:feature_code":"PPL",
    "gn:name":"\u2018Izbat \u1e28as\u016bbah",
    "gn:population":0,
    "gn:timezone":"Africa/Cairo",
    "iso:country":"EG",
    "name:ara_x_preferred":[
        "\u0639\u0632\u0628\u0629 \u062d\u0633\u0648\u0628\u0647"
    ],
    "name:und_x_variant":[
        "\u2018Izbat \u1e28as\u016bbah",
        "\u2018Iz. \u1e24us\u016bbah"
    ],
    "wof:name":"`Izbat Hasubah",
    "wof:placetype":"locality"
},
  "geometry": {"coordinates":[31.66961,31.18533],"type":"Point"}
}