{
  "type": "Feature",
  "properties": {
    "gn:admin1_code":"10",
    "gn:asciiname":"Al Hawasiliyah",
    "gn:country_code":"EG",
    "gn:dem":47,
    "gn:feature_class":"P",
    "gn:feature_code":"PPL",
    "gn:name":"Al \u1e28aw\u0101\u015fil\u012byah",
    "gn:population":0,
    "gn:timezone":"Africa/Cairo",
    "iso:country":"EG",
    "name:und_x_variant":[
        "El \u1e24awasl\u00eeya",
        "Al \u1e28aw\u0101\u015fil\u012byah"
    ],
    "wof:name":"Al Hawasiliyah",
    "wof:placetype":"locality"
},
  "geometry": {"coordinates":[30.80239000000001,28.02563],"type":"Point"}
}