{
  "type": "Feature",
  "properties": {
    "gn:admin1_code":"14",
    "gn:asciiname":"Shirshimah",
    "gn:country_code":"EG",
    "gn:dem":10,
    "gn:feature_class":"P",
    "gn:feature_code":"PPL",
    "gn:name":"Shirsh\u012bmah",
    "gn:population":0,
    "gn:timezone":"Africa/Cairo",
    "iso:country":"EG",
    "name:ara_x_preferred":[
        "\u0634\u0631\u0634\u064a\u0645\u0629"
    ],
    "name:und_x_variant":[
        "Shirsh\u00eema",
        "Shersh\u00eema",
        "Shirsh\u012bmah"
    ],
    "wof:name":"Shirshimah",
    "wof:placetype":"locality"
},
  "geometry": {"coordinates":[31.62095,30.6837],"type":"Point"}
}