{
  "type": "Feature",
  "properties": {
    "gn:admin1_code":"21",
    "gn:asciiname":"Al `Abbasi",
    "gn:country_code":"EG",
    "gn:dem":5,
    "gn:feature_class":"P",
    "gn:feature_code":"PPL",
    "gn:name":"Al \u2018Abb\u0101s\u012b",
    "gn:population":0,
    "gn:timezone":"Africa/Cairo",
    "iso:country":"EG",
    "name:ara_x_preferred":[
        "\u0627\u0644\u0639\u0628\u0627\u0633\u064a"
    ],
    "name:fas_x_preferred":[
        "\u0627\u0644\u0639\u0628\u0627\u0633\u06cc"
    ],
    "name:nno_x_preferred":[
        "Al `Abbasi"
    ],
    "name:und_x_variant":[
        "Al \u2018Abb\u0101s\u012b"
    ],
    "wof:name":"Al `Abbasi",
    "wof:placetype":"locality"
},
  "geometry": {"coordinates":[30.71426,31.28775],"type":"Point"}
}