{
  "type": "Feature",
  "properties": {
    "gn:admin1_code":"10",
    "gn:asciiname":"Ma`sarat Hajjaj",
    "gn:country_code":"EG",
    "gn:dem":36,
    "gn:feature_class":"P",
    "gn:feature_code":"PPL",
    "gn:name":"Ma\u2018\u015farat \u1e28ajj\u0101j",
    "gn:population":0,
    "gn:timezone":"Africa/Cairo",
    "iso:country":"EG",
    "name:und_x_variant":[
        "Ma\u2018saret Hagg\u00e2g",
        "Ma\u2018\u015farat \u1e28ajj\u0101j"
    ],
    "wof:name":"Ma`sarat Hajjaj",
    "wof:placetype":"locality"
},
  "geometry": {"coordinates":[30.67599,28.47216],"type":"Point"}
}