{
  "type": "Feature",
  "properties": {
    "gn:admin1_code":"21",
    "gn:asciiname":"Qaryah Thalathun",
    "gn:country_code":"EG",
    "gn:dem":0,
    "gn:feature_class":"P",
    "gn:feature_code":"PPL",
    "gn:name":"Qaryah Thal\u0101th\u016bn",
    "gn:population":0,
    "gn:timezone":"Africa/Cairo",
    "iso:country":"EG",
    "name:ara_x_preferred":[
        "\u0642\u0631\u064a\u0629 \u0663\u0660"
    ],
    "name:und_x_variant":[
        "Qaryah Thal\u0101th\u016bn",
        "Qaryah 30"
    ],
    "wof:name":"Qaryah Thalathun",
    "wof:placetype":"locality"
},
  "geometry": {"coordinates":[31.26258,31.36691],"type":"Point"}
}