{
  "type": "Feature",
  "properties": {
    "gn:admin1_code":"01",
    "gn:asciiname":"`Izbat Mahmud ash Shinnawi",
    "gn:country_code":"EG",
    "gn:dem":5,
    "gn:feature_class":"P",
    "gn:feature_code":"PPL",
    "gn:name":"\u2018Izbat Ma\u1e29m\u016bd ash Shinn\u0101w\u012b",
    "gn:population":0,
    "gn:timezone":"Africa/Cairo",
    "iso:country":"EG",
    "name:ara_x_preferred":[
        "\u0639\u0632\u0628\u0629 \u0645\u062d\u0645\u0648\u062f \u0627\u0644\u0634\u0646\u0627\u0648\u064a"
    ],
    "name:und_x_variant":[
        "\u2018Izbat Ma\u1e29m\u016bd ash Shinn\u0101w\u012b",
        "\u2018Iz. Ma\u1e25m\u016bd ash- Shinn\u0101w\u012b"
    ],
    "wof:name":"`Izbat Mahmud ash Shinnawi",
    "wof:placetype":"locality"
},
  "geometry": {"coordinates":[31.56909000000001,31.04512],"type":"Point"}
}