{
  "type": "Feature",
  "properties": {
    "gn:admin1_code":"14",
    "gn:asciiname":"Al Jazirah al Khadra'",
    "gn:country_code":"EG",
    "gn:dem":6,
    "gn:feature_class":"P",
    "gn:feature_code":"PPL",
    "gn:name":"Al Jaz\u012brah al Kha\u1e11r\u0101\u2019",
    "gn:population":0,
    "gn:timezone":"Africa/Cairo",
    "iso:country":"EG",
    "name:ara_x_preferred":[
        "\u0627\u0644\u062c\u0632\u064a\u0631\u0629 \u0627\u0644\u062e\u0636\u0631\u0627\u0621"
    ],
    "name:und_x_variant":[
        "El-Gez\u00eera el-Kha\u1e0dra",
        "Al Jaz\u012brah al Kha\u1e11r\u0101\u2019",
        "Al-Jaz\u012brah al-Kha\u1e0dr\u0101\u2019"
    ],
    "wof:name":"Al Jazirah al Khadra'",
    "wof:placetype":"locality"
},
  "geometry": {"coordinates":[31.83059,30.53434],"type":"Point"}
}