{
  "type": "Feature",
  "properties": {
    "gn:admin1_code":"09",
    "gn:asciiname":"`Izbat al Hirasah",
    "gn:country_code":"EG",
    "gn:dem":10,
    "gn:feature_class":"P",
    "gn:feature_code":"PPL",
    "gn:name":"\u2018Izbat al \u1e28ir\u0101sah",
    "gn:population":0,
    "gn:timezone":"Africa/Cairo",
    "iso:country":"EG",
    "name:ara_x_preferred":[
        "\u0639\u0632\u0628\u0629 \u0627\u0644\u062d\u0631\u0627\u0633\u0629"
    ],
    "name:und_x_variant":[
        "\u2018Izbat al \u1e28ir\u0101sah",
        "\u2018Izbat al \u1e24ir\u0101sah"
    ],
    "wof:name":"`Izbat al Hirasah",
    "wof:placetype":"locality"
},
  "geometry": {"coordinates":[30.96395,30.31676],"type":"Point"}
}