{
  "type": "Feature",
  "properties": {
    "gn:admin1_code":"23",
    "gn:asciiname":"Naj` al Jidd",
    "gn:country_code":"EG",
    "gn:dem":78,
    "gn:feature_class":"P",
    "gn:feature_code":"PPL",
    "gn:name":"Naj\u2018 al Jidd",
    "gn:population":0,
    "gn:timezone":"Africa/Cairo",
    "iso:country":"EG",
    "wof:name":"Naj` al Jidd",
    "wof:placetype":"locality"
},
  "geometry": {"coordinates":[32.81788,26.07363],"type":"Point"}
}