{
  "type": "Feature",
  "properties": {
    "iso:country":"EG",
    "name:ara_x_preferred":[
        "\u0632\u0641\u062a\u0649"
    ],
    "name:arz_x_preferred":[
        "\u0632\u0641\u062a\u0627"
    ],
    "name:ast_x_preferred":[
        "Zefta"
    ],
    "name:ceb_x_preferred":[
        "Zift\u00e1"
    ],
    "name:deu_x_preferred":[
        "Zifta"
    ],
    "name:ell_x_preferred":[
        "\u0396\u03af\u03c6\u03c4\u03b1"
    ],
    "name:eng_x_preferred":[
        "Zefta"
    ],
    "name:fas_x_preferred":[
        "\u0632\u0641\u062a\u06cc"
    ],
    "name:fra_x_preferred":[
        "Zefta"
    ],
    "name:hun_x_preferred":[
        "Zefta"
    ],
    "name:ita_x_preferred":[
        "Zefta"
    ],
    "name:kat_x_preferred":[
        "\u10d6\u10d8\u10e4\u10d7\u10d8"
    ],
    "name:kaz_x_preferred":[
        "\u0417\u0438\u0444\u0442\u0430"
    ],
    "name:mlg_x_preferred":[
        "Zefta"
    ],
    "name:nld_x_preferred":[
        "Zefta"
    ],
    "name:nob_x_preferred":[
        "Zifta"
    ],
    "name:pol_x_preferred":[
        "Zifta"
    ],
    "name:rus_x_preferred":[
        "\u0417\u0438\u0444\u0442\u0430"
    ],
    "name:sco_x_preferred":[
        "Zifta"
    ],
    "name:spa_x_preferred":[
        "Zifta"
    ],
    "name:swe_x_preferred":[
        "Zifta"
    ],
    "name:ukr_x_preferred":[
        "\u0417\u0456\u0444\u0442\u0430"
    ],
    "name:zho_x_preferred":[
        "\u6fdf\u592b\u5854"
    ],
    "name:zul_x_preferred":[
        "Zefta"
    ],
    "qs:gn_country":"EG",
    "qs:gn_fcode":"PPL",
    "qs:gn_pop":92667,
    "qs:name":"\u0645\u0631\u0643\u0632 \u0632\u0641\u062a\u0649",
    "qs:name_adm0":"\u0645\u0635\u0631",
    "qs:name_adm1":"\u0627\u0644\u063a\u0631\u0628\u064a\u0629",
    "qs:photos":0,
    "qs:photos_1k":0,
    "qs:photos_9k":1,
    "qs:photos_9r":1,
    "qs:photos_all":4,
    "qs:photos_sr":0,
    "qs:placetype":"Town",
    "qs:pop_sr":"8",
    "qs:woe_adm0":23424802,
    "wof:name":"\u0645\u0631\u0643\u0632 \u0632\u0641\u062a\u0649",
    "wof:placetype":"locality",
    "wof:population":92667
},
  "geometry": {"coordinates":[31.24425,30.7142],"type":"Point"}
}