{
  "type": "Feature",
  "properties": {
    "gn:admin1_code":"20",
    "gn:asciiname":"Al Mashayikh",
    "gn:country_code":"EG",
    "gn:dem":3,
    "gn:feature_class":"P",
    "gn:feature_code":"PPL",
    "gn:name":"Al Mash\u0101yikh",
    "gn:population":0,
    "gn:timezone":"Africa/Cairo",
    "iso:country":"EG",
    "name:ara_x_preferred":[
        "\u0627\u0644\u0645\u0634\u0627\u064a\u062e"
    ],
    "name:fas_x_preferred":[
        "\u0627\u0644\u0645\u0634\u0627\u06cc\u062e"
    ],
    "name:nno_x_preferred":[
        "Al Mashayikh"
    ],
    "name:und_x_variant":[
        "Al Mash\u0101yikh"
    ],
    "wof:name":"Al Mashayikh",
    "wof:placetype":"locality"
},
  "geometry": {"coordinates":[31.714,31.38414],"type":"Point"}
}