{
  "type": "Feature",
  "properties": {
    "gn:admin1_code":"01",
    "gn:asciiname":"`Izbat Ibrahim Rabi`",
    "gn:country_code":"EG",
    "gn:dem":4,
    "gn:feature_class":"P",
    "gn:feature_code":"PPL",
    "gn:name":"\u2018Izbat Ibr\u0101h\u012bm Rab\u012b\u2018",
    "gn:population":0,
    "gn:timezone":"Africa/Cairo",
    "iso:country":"EG",
    "name:ara_x_preferred":[
        "\u0639\u0632\u0628\u0629 \u0625\u0628\u0631\u0627\u0647\u064a\u0645 \u0631\u0628\u064a\u0639"
    ],
    "name:und_x_variant":[
        "\u2018Izbat Ibr\u0101h\u012bm Rab\u012b\u2018"
    ],
    "wof:name":"`Izbat Ibrahim Rabi`",
    "wof:placetype":"locality"
},
  "geometry": {"coordinates":[31.44944000000001,31.28712],"type":"Point"}
}