{
  "type": "Feature",
  "properties": {
    "gn:admin1_code":"06",
    "gn:asciiname":"`Ilwat `Abd an Nabi",
    "gn:country_code":"EG",
    "gn:dem":-3,
    "gn:feature_class":"P",
    "gn:feature_code":"PPL",
    "gn:name":"\u2018Ilwat \u2018Abd an Nab\u012b",
    "gn:population":0,
    "gn:timezone":"Africa/Cairo",
    "iso:country":"EG",
    "name:ara_x_preferred":[
        "\u0639\u0644\u0648\u0629 \u0639\u0628\u062f \u0627\u0644\u0646\u0628\u064a"
    ],
    "name:und_x_variant":[
        "\u2018Ilwat \u2018Abd an Nab\u012b"
    ],
    "wof:name":"`Ilwat `Abd an Nabi",
    "wof:placetype":"locality"
},
  "geometry": {"coordinates":[29.93392,31.08035],"type":"Point"}
}