{
  "type": "Feature",
  "properties": {
    "gn:admin1_code":"01",
    "gn:asciiname":"Kawm al Yahud",
    "gn:country_code":"EG",
    "gn:dem":4,
    "gn:feature_class":"P",
    "gn:feature_code":"PPL",
    "gn:name":"Kawm al Yah\u016bd",
    "gn:population":0,
    "gn:timezone":"Africa/Cairo",
    "iso:country":"EG",
    "name:ara_x_preferred":[
        "\u0643\u0648\u0645 \u0627\u0644\u064a\u0647\u0648\u062f"
    ],
    "name:und_x_variant":[
        "Kawm al Yah\u016bd",
        "Kawm al-Yah\u016bd"
    ],
    "wof:name":"Kawm al Yahud",
    "wof:placetype":"locality"
},
  "geometry": {"coordinates":[31.39951,31.24485],"type":"Point"}
}