{
  "type": "Feature",
  "properties": {
    "gn:admin1_code":"13",
    "gn:asciiname":"Naj` Abu Badr",
    "gn:country_code":"EG",
    "gn:dem":91,
    "gn:feature_class":"P",
    "gn:feature_code":"PPL",
    "gn:name":"Naj\u2018 Ab\u016b Badr",
    "gn:population":0,
    "gn:timezone":"Africa/Cairo",
    "iso:country":"EG",
    "wof:name":"Naj` Abu Badr",
    "wof:placetype":"locality"
},
  "geometry": {"coordinates":[32.59135,25.21565],"type":"Point"}
}