{
  "type": "Feature",
  "properties": {
    "gn:admin1_code":"03",
    "gn:asciiname":"`Izbat al Kudwah",
    "gn:country_code":"EG",
    "gn:dem":1,
    "gn:feature_class":"P",
    "gn:feature_code":"PPL",
    "gn:name":"\u2018Izbat al Kudwah",
    "gn:population":0,
    "gn:timezone":"Africa/Cairo",
    "iso:country":"EG",
    "name:ara_x_preferred":[
        "\u0639\u0632\u0628\u0629 \u0627\u0644\u0643\u062f\u0648\u0629"
    ],
    "name:und_x_variant":[
        "\u2018Ezbet el-Kidwa",
        "\u2018Izbat al Kudwah",
        "\u2018Izbat al Kidwah"
    ],
    "wof:name":"`Izbat al Kudwah",
    "wof:placetype":"locality"
},
  "geometry": {"coordinates":[30.22172,31.16654],"type":"Point"}
}