{
  "type": "Feature",
  "properties": {
    "gn:admin1_code":"21",
    "gn:asciiname":"`Izbat Abu as Su`ud",
    "gn:country_code":"EG",
    "gn:dem":4,
    "gn:feature_class":"P",
    "gn:feature_code":"PPL",
    "gn:name":"\u2018Izbat Ab\u016b as Su\u2018\u016bd",
    "gn:population":0,
    "gn:timezone":"Africa/Cairo",
    "iso:country":"EG",
    "name:ara_x_preferred":[
        "\u0639\u0632\u0628\u0629 \u0623\u0628\u0648 \u0627\u0644\u0633\u0639\u0648\u062f"
    ],
    "name:und_x_variant":[
        "\u2018Izbat Ab\u016b as Su\u2018\u016bd"
    ],
    "wof:name":"`Izbat Abu as Su`ud",
    "wof:placetype":"locality"
},
  "geometry": {"coordinates":[30.69672000000001,31.11897],"type":"Point"}
}