{
  "type": "Feature",
  "properties": {
    "gn:admin1_code":"01",
    "gn:asciiname":"`Izbat al Islah al Jadidah",
    "gn:country_code":"EG",
    "gn:dem":6,
    "gn:feature_class":"P",
    "gn:feature_code":"PPL",
    "gn:name":"\u2018Izbat al I\u015fl\u0101\u1e29 al Jad\u012bdah",
    "gn:population":0,
    "gn:timezone":"Africa/Cairo",
    "iso:country":"EG",
    "name:ara_x_preferred":[
        "\u0639\u0632\u0628\u0629 \u0627\u0644\u0625\u0635\u0644\u0627\u062d \u0627\u0644\u062c\u062f\u064a\u062f\u0629"
    ],
    "name:und_x_variant":[
        "\u2018Izbat al I\u015fl\u0101\u1e29 al Jad\u012bdah"
    ],
    "wof:name":"`Izbat al Islah al Jadidah",
    "wof:placetype":"locality"
},
  "geometry": {"coordinates":[31.6074,30.98591],"type":"Point"}
}