{
  "type": "Feature",
  "properties": {
    "gn:admin1_code":"09",
    "gn:asciiname":"Darajil",
    "gn:country_code":"EG",
    "gn:dem":9,
    "gn:feature_class":"P",
    "gn:feature_code":"PPL",
    "gn:name":"Dar\u0101j\u012bl",
    "gn:population":0,
    "gn:timezone":"Africa/Cairo",
    "iso:country":"EG",
    "name:und_x_variant":[
        "Dar\u00e2g\u00eel",
        "Dar\u0101j\u012bl"
    ],
    "wof:name":"Darajil",
    "wof:placetype":"locality"
},
  "geometry": {"coordinates":[30.86271,30.65476],"type":"Point"}
}