{
  "type": "Feature",
  "properties": {
    "gn:admin1_code":"09",
    "gn:asciiname":"Minshat Bakhati",
    "gn:country_code":"EG",
    "gn:dem":12,
    "gn:feature_class":"P",
    "gn:feature_code":"PPL",
    "gn:name":"Minsh\u0101t Bakh\u0101t\u012b",
    "gn:population":0,
    "gn:timezone":"Africa/Cairo",
    "iso:country":"EG",
    "name:ara_x_preferred":[
        "\u0645\u0646\u0634\u0623\u0629 \u0628\u062e\u0627\u062a\u064a"
    ],
    "name:und_x_variant":[
        "Munsha'\u0101t Bakh\u0101t\u012b",
        "Minsh\u0101t Bakh\u0101t\u012b"
    ],
    "wof:name":"Minshat Bakhati",
    "wof:placetype":"locality"
},
  "geometry": {"coordinates":[30.95715,30.57327],"type":"Point"}
}