{
  "type": "Feature",
  "properties": {
    "gn:admin1_code":"23",
    "gn:asciiname":"Naj` Abu Yusif",
    "gn:country_code":"EG",
    "gn:dem":77,
    "gn:feature_class":"P",
    "gn:feature_code":"PPL",
    "gn:name":"Naj\u2018 Ab\u016b Y\u016bsif",
    "gn:population":0,
    "gn:timezone":"Africa/Cairo",
    "iso:country":"EG",
    "wof:name":"Naj` Abu Yusif",
    "wof:placetype":"locality"
},
  "geometry": {"coordinates":[32.79509,26.02511],"type":"Point"}
}