{
  "type": "Feature",
  "properties": {
    "gn:admin1_code":"14",
    "gn:asciiname":"`Izbat at Tukhi",
    "gn:country_code":"EG",
    "gn:dem":10,
    "gn:feature_class":"P",
    "gn:feature_code":"PPL",
    "gn:name":"\u2018Izbat a\u0163 \u0162\u016bkh\u012b",
    "gn:population":0,
    "gn:timezone":"Africa/Cairo",
    "iso:country":"EG",
    "name:ara_x_preferred":[
        "\u0639\u0632\u0628\u0629 \u0627\u0644\u0637\u0648\u062e\u064a"
    ],
    "name:und_x_variant":[
        "\u2018Izbat a\u0163 \u0162\u016bkh\u012b"
    ],
    "wof:name":"`Izbat at Tukhi",
    "wof:placetype":"locality"
},
  "geometry": {"coordinates":[31.6614,30.66301],"type":"Point"}
}