{
  "type": "Feature",
  "properties": {
    "gn:gn_country":"EG",
    "gn:gn_fcode":"PPLX",
    "gn:gn_pop":0,
    "iso:country":"EG",
    "name:ara_x_preferred":[
        "\u0645\u0633\u0627\u0643\u0646 \u0632\u064a\u0646\u0647\u0645"
    ],
    "name:eng_x_preferred":[
        "Masakin Zainhum"
    ],
    "name:unk_x_variant":[
        "Masakin Zainhum",
        "Mas\u0101kin Zaynhum"
    ],
    "qs:gn_adm0_cc":"EG",
    "qs:gn_fcode":"PPLX",
    "qs:gn_local":360630,
    "qs:gn_nam_loc":"\u0627\u0644\u0642\u0627\u0647\u0631\u0629, \u0627\u0644\u0642\u0627\u0647\u0631\u0629, EG",
    "qs:gn_namadm1":"11",
    "qs:gn_name":"Mas\u0101kin Zaynhum",
    "qs:local_max":6277,
    "qs:local_sum":54808,
    "qs:localhoods":36,
    "qs:name":"Masakin Zainhum",
    "qs:name_adm0":"\u0645\u0635\u0631",
    "qs:name_adm1":"\u0627\u0644\u0642\u0627\u0647\u0631\u0629",
    "qs:name_local":"\u0627\u0644\u0642\u0627\u0647\u0631\u0629",
    "qs:photo_max":255,
    "qs:photo_sum":873,
    "qs:placetype":"Suburb",
    "qs:quad_count":19,
    "qs:woe_adm0":23424802,
    "qs:woe_adm1":2345233,
    "qs:woe_adm2":0,
    "qs:woe_lau":0,
    "qs:woe_local":1521894,
    "qs:woe_ver":"7.10.0",
    "qs_pg:aaroncc":"EG",
    "qs_pg:gn_country":"EG",
    "qs_pg:gn_fcode":"PPLX",
    "qs_pg:gn_pop":0,
    "qs_pg:name":"Masakin Zainhum",
    "qs_pg:name_adm0":"\u0645\u0635\u0631",
    "qs_pg:name_adm1":"\u0627\u0644\u0642\u0627\u0647\u0631\u0629",
    "qs_pg:photos":766,
    "qs_pg:photos_1k":155,
    "qs_pg:photos_9k":3,
    "qs_pg:photos_9r":6,
    "qs_pg:photos_all":766,
    "qs_pg:photos_sr":9,
    "qs_pg:pop_sr":0,
    "qs_pg:qs_pg_placetype":"neighbourhood",
    "qs_pg:qs_pg_placetype_gp":"Suburb",
    "qs_pg:woe_adm0":23424802,
    "wof:lang":[
        "eng"
    ],
    "wof:name":"Masakin Zainhum",
    "wof:placetype":"neighbourhood"
},
  "geometry": {"coordinates":[31.249872,30.028574],"type":"Point"}
}