{
  "type": "Feature",
  "properties": {
    "gn:admin1_code":"06",
    "gn:asciiname":"`Izbat Badwani",
    "gn:country_code":"EG",
    "gn:dem":-3,
    "gn:feature_class":"P",
    "gn:feature_code":"PPL",
    "gn:name":"\u2018Izbat Badw\u0101n\u012b",
    "gn:population":0,
    "gn:timezone":"Africa/Cairo",
    "iso:country":"EG",
    "name:ara_x_preferred":[
        "\u0639\u0632\u0628\u0629 \u0628\u062f\u0648\u0627\u0646\u064a"
    ],
    "name:und_x_variant":[
        "\u2018Ezbet I\u1e63\u1e6daf\u00e2n\u00fbs",
        "\u2018Izbat Badw\u0101n\u012b al Kab\u012brah",
        "\u2018Izbat I\u015f\u0163af\u0101n\u016bs",
        "\u2018Ezbet Bidw\u00e2ni el Keb\u00eera",
        "\u2018Izbat Badw\u0101n\u012b",
        "\u2018Ezbet Bidw\u00e2ni el Sagh\u00eera",
        "\u2018Izbat Badw\u0101n\u012b a\u015f \u015eagh\u012brah",
        "\u2018Izbat \u2018Al\u012b Mu\u015f\u0163af\u00e1",
        "\u2018Ezbet \u2018Ali-Mu\u1e63\u1e6dafa"
    ],
    "wof:name":"`Izbat Badwani",
    "wof:placetype":"locality"
},
  "geometry": {"coordinates":[30.03537,31.22599],"type":"Point"}
}