{
  "type": "Feature",
  "properties": {
    "gn:admin1_code":"21",
    "gn:asciiname":"`Izbah Raqm Tis`ah wa Khamsun",
    "gn:country_code":"EG",
    "gn:dem":2,
    "gn:feature_class":"P",
    "gn:feature_code":"PPL",
    "gn:name":"\u2018Izbah Raqm Tis\u2018ah wa Khams\u016bn",
    "gn:population":0,
    "gn:timezone":"Africa/Cairo",
    "iso:country":"EG",
    "name:ara_x_preferred":[
        "\u0639\u0632\u0628\u0629 \u0631\u0642\u0645 \u0665\u06f9"
    ],
    "name:und_x_variant":[
        "\u2018Izbah Raqm Tis\u2018ah wa Khams\u016bn",
        "\u2018Izbat Raqm 59"
    ],
    "wof:name":"`Izbah Raqm Tis`ah wa Khamsun",
    "wof:placetype":"locality"
},
  "geometry": {"coordinates":[30.95778,31.37164000000001],"type":"Point"}
}