{
  "type": "Feature",
  "properties": {
    "gn:admin1_code":"14",
    "gn:asciiname":"`Izbat Abu `Utman",
    "gn:country_code":"EG",
    "gn:dem":13,
    "gn:feature_class":"P",
    "gn:feature_code":"PPL",
    "gn:name":"\u2018Izbat Ab\u016b \u2018Utm\u0101n",
    "gn:population":0,
    "gn:timezone":"Africa/Cairo",
    "iso:country":"EG",
    "name:ara_x_preferred":[
        "\u0639\u0632\u0628\u0629 \u0623\u0628\u0648 \u0639\u062a\u0645\u0627\u0646"
    ],
    "name:und_x_variant":[
        "\u2018Izbat Ab\u016b \u2018Utm\u0101n",
        "\u2018Izbat Ab\u016b \u2018Itm\u0101n"
    ],
    "wof:name":"`Izbat Abu `Utman",
    "wof:placetype":"locality"
},
  "geometry": {"coordinates":[31.50276,30.40916],"type":"Point"}
}