{
  "type": "Feature",
  "properties": {
    "gn:admin1_code":"03",
    "gn:asciiname":"Al Hilbawi",
    "gn:country_code":"EG",
    "gn:dem":0,
    "gn:feature_class":"P",
    "gn:feature_code":"PPL",
    "gn:name":"Al Hilb\u0101w\u012b",
    "gn:population":0,
    "gn:timezone":"Africa/Cairo",
    "iso:country":"EG",
    "name:ara_x_preferred":[
        "\u0627\u0644\u0647\u0644\u0628\u0627\u0648\u064a"
    ],
    "name:und_x_variant":[
        "Mansh\u00eeyet el-Hilb\u00e2wi",
        "Mansh\u012byat al Hilb\u0101w\u012b",
        "Al Hilb\u0101w\u012b",
        "\u2018Izbat at Turjum\u0101n",
        "\u2018Ezbet el Turguman",
        "\u2018Ezbet Ibr\u00e2h\u00eem Bey el-\u1e24ilb\u00e2wi",
        "\u2018Izbat Ibr\u0101h\u012bm Bey al \u1e28ilb\u0101w\u012b",
        "Al \u2018Izbah al \u1e28amr\u0101\u2019",
        "El \u1e24amra",
        "Al \u1e28amr\u0101\u2019",
        "\u2018Ezbet el Mansh\u00eeya el-Ged\u00eeda",
        "\u2018Ezbet Ibr\u00e2h\u00eem Bey el-Hilb\u00e2wi",
        "\u2018Izbat Ibr\u0101h\u012bm Bey al Hilb\u0101w\u012b"
    ],
    "wof:name":"Al Hilbawi",
    "wof:placetype":"locality"
},
  "geometry": {"coordinates":[30.144,31.0393],"type":"Point"}
}