{
  "type": "Feature",
  "properties": {
    "gn:admin1_code":"04",
    "gn:asciiname":"`Izbat `Abdallah Bayk al Bahri",
    "gn:country_code":"EG",
    "gn:dem":9,
    "gn:feature_class":"P",
    "gn:feature_code":"PPL",
    "gn:name":"\u2018Izbat \u2018Abdallah Bayk al Ba\u1e29r\u012b",
    "gn:population":0,
    "gn:timezone":"Africa/Cairo",
    "iso:country":"EG",
    "wof:name":"`Izbat `Abdallah Bayk al Bahri",
    "wof:placetype":"locality"
},
  "geometry": {"coordinates":[30.71018,29.27082],"type":"Point"}
}