{
  "type": "Feature",
  "properties": {
    "gn:admin1_code":"09",
    "gn:asciiname":"Mit Abu Shaykhah",
    "gn:country_code":"EG",
    "gn:dem":15,
    "gn:feature_class":"P",
    "gn:feature_code":"PPL",
    "gn:name":"M\u012bt Ab\u016b Shaykhah",
    "gn:population":0,
    "gn:timezone":"Africa/Cairo",
    "iso:country":"EG",
    "name:ara_x_preferred":[
        "\u0645\u064a\u062a \u0623\u0628\u0648 \u0634\u064a\u062e\u0647"
    ],
    "name:und_x_variant":[
        "M\u00eet Abu Sheikha",
        "M\u012bt Ab\u016b Shaykhah"
    ],
    "wof:name":"Mit Abu Shaykhah",
    "wof:placetype":"locality"
},
  "geometry": {"coordinates":[31.0665,30.54819],"type":"Point"}
}