{
  "type": "Feature",
  "properties": {
    "gn:admin1_code":"14",
    "gn:asciiname":"`Izbat Salim",
    "gn:country_code":"EG",
    "gn:dem":12,
    "gn:feature_class":"P",
    "gn:feature_code":"PPL",
    "gn:name":"\u2018Izbat S\u0101lim",
    "gn:population":0,
    "gn:timezone":"Africa/Cairo",
    "iso:country":"EG",
    "name:ara_x_preferred":[
        "\u0639\u0632\u0628\u0629 \u0633\u0627\u0644\u0645"
    ],
    "name:und_x_variant":[
        "\u2018Izbat S\u0101lim"
    ],
    "wof:name":"`Izbat Salim",
    "wof:placetype":"locality"
},
  "geometry": {"coordinates":[31.66703,30.57682],"type":"Point"}
}