{
  "type": "Feature",
  "properties": {
    "gn:admin1_code":"14",
    "gn:asciiname":"`Izbat Raqam Sittah al Jadidah",
    "gn:country_code":"EG",
    "gn:dem":4,
    "gn:feature_class":"P",
    "gn:feature_code":"PPL",
    "gn:name":"\u2018Izbat Raqam Sittah al Jad\u012bdah",
    "gn:population":0,
    "gn:timezone":"Africa/Cairo",
    "iso:country":"EG",
    "name:ara_x_preferred":[
        "\u0639\u0632\u0628\u0629 \u0631\u0642\u0645 \u0633\u062a\u0629 \u0627\u0644\u062c\u062f\u064a\u062f\u0629"
    ],
    "name:und_x_variant":[
        "\u2018Izbat Raqam Sittah al Jad\u012bdah",
        "\u2018Izbat Number Six al-Jad\u012bdah"
    ],
    "wof:name":"`Izbat Raqam Sittah al Jadidah",
    "wof:placetype":"locality"
},
  "geometry": {"coordinates":[31.88924,31.00543],"type":"Point"}
}