{
  "type": "Feature",
  "properties": {
    "gn:admin1_code":"05",
    "gn:asciiname":"`Izbat ad Dab`ah",
    "gn:country_code":"EG",
    "gn:dem":6,
    "gn:feature_class":"P",
    "gn:feature_code":"PPL",
    "gn:name":"\u2018Izbat a\u1e11 \u1e10ab\u2018ah",
    "gn:population":0,
    "gn:timezone":"Africa/Cairo",
    "iso:country":"EG",
    "name:ara_x_preferred":[
        "\u0639\u0632\u0628\u0629 \u0627\u0644\u0636\u0628\u0639\u0629"
    ],
    "name:und_x_variant":[
        "\u2018Izbat a\u1e11 \u1e10ab\u2018ah",
        "\u2018Izbat a\u1e0d-\u1e0cab\u2018ah"
    ],
    "wof:name":"`Izbat ad Dab`ah",
    "wof:placetype":"locality"
},
  "geometry": {"coordinates":[31.14314,31.10669],"type":"Point"}
}