{
  "type": "Feature",
  "properties": {
    "gn:admin1_code":"05",
    "gn:asciiname":"`Izbat `Ali al Jahash",
    "gn:country_code":"EG",
    "gn:dem":11,
    "gn:feature_class":"P",
    "gn:feature_code":"PPL",
    "gn:name":"\u2018Izbat \u2018Al\u012b al Ja\u1e29ash",
    "gn:population":0,
    "gn:timezone":"Africa/Cairo",
    "iso:country":"EG",
    "name:ara_x_preferred":[
        "\u0639\u0632\u0628\u0629 \u0639\u0644\u064a \u0627\u0644\u062c\u062d\u0634"
    ],
    "name:und_x_variant":[
        "\u2018Izbat \u2018Al\u012b al Ja\u1e29ash"
    ],
    "wof:name":"`Izbat `Ali al Jahash",
    "wof:placetype":"locality"
},
  "geometry": {"coordinates":[31.24537,30.68538],"type":"Point"}
}