{
  "type": "Feature",
  "properties": {
    "gn:admin1_code":"14",
    "gn:asciiname":"Al Walaja",
    "gn:country_code":"EG",
    "gn:dem":19,
    "gn:feature_class":"P",
    "gn:feature_code":"PPL",
    "gn:name":"Al Walaj\u0101",
    "gn:population":0,
    "gn:timezone":"Africa/Cairo",
    "iso:country":"EG",
    "name:ara_x_preferred":[
        "\u0627\u0644\u0648\u0644\u062c\u0627"
    ],
    "name:und_x_variant":[
        "El-Walaga",
        "Al Walajah",
        "Al Walaja",
        "Al Walaj\u0101"
    ],
    "wof:name":"Al Walaja",
    "wof:placetype":"locality"
},
  "geometry": {"coordinates":[31.29733,30.52154],"type":"Point"}
}