{
  "type": "Feature",
  "properties": {
    "gn:admin1_code":"23",
    "gn:asciiname":"Ad Dahasah",
    "gn:country_code":"EG",
    "gn:dem":70,
    "gn:feature_class":"P",
    "gn:feature_code":"PPL",
    "gn:name":"Ad Dahasah",
    "gn:population":0,
    "gn:timezone":"Africa/Cairo",
    "iso:country":"EG",
    "name:und_x_variant":[
        "El Dahasa",
        "Ad Dahasah"
    ],
    "wof:name":"Ad Dahasah",
    "wof:placetype":"locality"
},
  "geometry": {"coordinates":[32.15407,26.04295],"type":"Point"}
}