{
  "type": "Feature",
  "properties": {
    "gn:admin1_code":"14",
    "gn:asciiname":"Munsha'at Radwan",
    "gn:country_code":"EG",
    "gn:dem":10,
    "gn:feature_class":"P",
    "gn:feature_code":"PPL",
    "gn:name":"Munsha\u2019at Ra\u1e11w\u0101n",
    "gn:population":0,
    "gn:timezone":"Africa/Cairo",
    "iso:country":"EG",
    "name:ara_x_preferred":[
        "\u0645\u0646\u0634\u0623\u0629 \u0631\u0636\u0648\u0627\u0646"
    ],
    "name:und_x_variant":[
        "Minsh\u00e2t Ra\u1e0dw\u00e2h",
        "Minsh\u0101t Ri\u1e11w\u0101n",
        "Munsha\u2019at Ra\u1e11w\u0101n"
    ],
    "wof:name":"Munsha'at Radwan",
    "wof:placetype":"locality"
},
  "geometry": {"coordinates":[31.69004,30.78394],"type":"Point"}
}