{
  "type": "Feature",
  "properties": {
    "gn:admin1_code":"03",
    "gn:asciiname":"`Izbat Thalathah/Tis`ah",
    "gn:country_code":"EG",
    "gn:dem":-5,
    "gn:feature_class":"P",
    "gn:feature_code":"PPL",
    "gn:name":"\u2018Izbat Thal\u0101thah/Tis\u2018ah",
    "gn:population":0,
    "gn:timezone":"Africa/Cairo",
    "iso:country":"EG",
    "name:ara_x_preferred":[
        "\u0639\u0632\u0628\u0629 \u0663/\u0669"
    ],
    "name:und_x_variant":[
        "\u2018Izbat Thal\u0101thah/Tis\u2018ah"
    ],
    "wof:name":"`Izbat Thalathah/Tis`ah",
    "wof:placetype":"locality"
},
  "geometry": {"coordinates":[30.05089000000001,31.1489],"type":"Point"}
}