{
  "type": "Feature",
  "properties": {
    "gn:admin1_code":"21",
    "gn:asciiname":"`Izbat Daqalt",
    "gn:country_code":"EG",
    "gn:dem":7,
    "gn:feature_class":"P",
    "gn:feature_code":"PPL",
    "gn:name":"\u2018Izbat Daqalt",
    "gn:population":0,
    "gn:timezone":"Africa/Cairo",
    "iso:country":"EG",
    "name:ara_x_preferred":[
        "\u0639\u0632\u0628\u0629 \u062f\u0642\u0644\u062a"
    ],
    "name:und_x_variant":[
        "\u2018Izbat Daqalt"
    ],
    "wof:name":"`Izbat Daqalt",
    "wof:placetype":"locality"
},
  "geometry": {"coordinates":[30.96494,31.16226],"type":"Point"}
}