{
  "type": "Feature",
  "properties": {
    "gn:admin1_code":"21",
    "gn:asciiname":"`Izbat Mukhtar `Abd al Latif",
    "gn:country_code":"EG",
    "gn:dem":3,
    "gn:feature_class":"P",
    "gn:feature_code":"PPL",
    "gn:name":"\u2018Izbat Mukht\u0101r \u2018Abd al La\u0163\u012bf",
    "gn:population":0,
    "gn:timezone":"Africa/Cairo",
    "iso:country":"EG",
    "name:ara_x_preferred":[
        "\u0639\u0632\u0628\u0629 \u0645\u062e\u062a\u0627\u0631 \u0639\u0628\u062f \u0627\u0644\u0644\u0637\u064a\u0641"
    ],
    "name:und_x_variant":[
        "\u2018Izbat Mukht\u0101r \u2018Abd al La\u0163\u012bf",
        "\u2018Izbat Mukht\u0101r \u2018Abd al-Lat\u012bf"
    ],
    "wof:name":"`Izbat Mukhtar `Abd al Latif",
    "wof:placetype":"locality"
},
  "geometry": {"coordinates":[30.79552,31.21296],"type":"Point"}
}