{
  "type": "Feature",
  "properties": {
    "gn:admin1_code":"14",
    "gn:asciiname":"Naj` Tall ad Diba`",
    "gn:country_code":"EG",
    "gn:dem":14,
    "gn:feature_class":"P",
    "gn:feature_code":"PPL",
    "gn:name":"Naj\u2018 Tall a\u1e11 \u1e10ib\u0101\u2018",
    "gn:population":0,
    "gn:timezone":"Africa/Cairo",
    "iso:country":"EG",
    "name:ara_x_preferred":[
        "\u0646\u062c\u0639 \u062a\u0644 \u0627\u0644\u0636\u0628\u0627\u0639"
    ],
    "name:und_x_variant":[
        "Naj\u2018 Tall a\u1e11 \u1e10ib\u0101\u2018"
    ],
    "wof:name":"Naj` Tall ad Diba`",
    "wof:placetype":"locality"
},
  "geometry": {"coordinates":[31.42696,30.52696],"type":"Point"}
}