{
  "type": "Feature",
  "properties": {
    "gn:admin1_code":"10",
    "gn:asciiname":"Kawm Matay",
    "gn:country_code":"EG",
    "gn:dem":37,
    "gn:feature_class":"P",
    "gn:feature_code":"PPL",
    "gn:name":"Kawm Ma\u0163\u0101y",
    "gn:population":0,
    "gn:timezone":"Africa/Cairo",
    "iso:country":"EG",
    "name:und_x_variant":[
        "K\u00f4m Mat\u00e2i",
        "Kawm Ma\u0163\u0101y"
    ],
    "wof:name":"Kawm Matay",
    "wof:placetype":"locality"
},
  "geometry": {"coordinates":[30.76769,28.44108],"type":"Point"}
}