{
  "type": "Feature",
  "properties": {
    "gn:admin1_code":"03",
    "gn:asciiname":"`Ezbet el-Qadi Hafs",
    "gn:country_code":"EG",
    "gn:dem":2,
    "gn:feature_class":"P",
    "gn:feature_code":"PPL",
    "gn:name":"\u2018Ezbet el-Q\u00e2di Hafs",
    "gn:population":0,
    "gn:timezone":"Africa/Cairo",
    "iso:country":"EG",
    "wof:name":"`Ezbet el-Qadi Hafs",
    "wof:placetype":"locality"
},
  "geometry": {"coordinates":[30.33861,30.99528],"type":"Point"}
}