{
  "type": "Feature",
  "properties": {
    "gn:admin1_code":"03",
    "gn:asciiname":"Daqduqah",
    "gn:country_code":"EG",
    "gn:dem":9,
    "gn:feature_class":"P",
    "gn:feature_code":"PPL",
    "gn:name":"Daqd\u016bqah",
    "gn:population":0,
    "gn:timezone":"Africa/Cairo",
    "iso:country":"EG",
    "name:und_x_variant":[
        "Daqd\u016bqah",
        "Daqd\u00fbqa"
    ],
    "wof:name":"Daqduqah",
    "wof:placetype":"locality"
},
  "geometry": {"coordinates":[30.61766,30.85382],"type":"Point"}
}