{
  "type": "Feature",
  "properties": {
    "gn:admin1_code":"14",
    "gn:asciiname":"`Izbat Abu Murrah",
    "gn:country_code":"EG",
    "gn:dem":9,
    "gn:feature_class":"P",
    "gn:feature_code":"PPL",
    "gn:name":"\u2018Izbat Ab\u016b Murrah",
    "gn:population":0,
    "gn:timezone":"Africa/Cairo",
    "iso:country":"EG",
    "name:ara_x_preferred":[
        "\u0639\u0632\u0628\u0629 \u0623\u0628\u0648 \u0645\u0631\u0629"
    ],
    "name:und_x_variant":[
        "\u2018Izbat Ab\u016b Murrah"
    ],
    "wof:name":"`Izbat Abu Murrah",
    "wof:placetype":"locality"
},
  "geometry": {"coordinates":[31.38847,30.70904],"type":"Point"}
}