{
  "type": "Feature",
  "properties": {
    "gn:admin1_code":"05",
    "gn:asciiname":"Kafr as Sahil",
    "gn:country_code":"EG",
    "gn:dem":13,
    "gn:feature_class":"P",
    "gn:feature_code":"PPL",
    "gn:name":"Kafr as S\u0101\u1e29il",
    "gn:population":0,
    "gn:timezone":"Africa/Cairo",
    "iso:country":"EG",
    "name:ara_x_preferred":[
        "\u0643\u0641\u0631 \u0627\u0644\u0633\u0627\u062d\u0644"
    ],
    "name:und_x_variant":[
        "Kafr es-S\u00e2\u1e25il",
        "Kafr el-S\u00e2\u1e25il",
        "Kafr as S\u0101\u1e29il",
        "Kafr as-S\u0101\u1e25il"
    ],
    "wof:name":"Kafr as Sahil",
    "wof:placetype":"locality"
},
  "geometry": {"coordinates":[30.95653,30.75681],"type":"Point"}
}