{
  "type": "Feature",
  "properties": {
    "gn:admin1_code":"14",
    "gn:asciiname":"Qaryat Khalid Bin al Walid",
    "gn:country_code":"EG",
    "gn:dem":0,
    "gn:feature_class":"P",
    "gn:feature_code":"PPL",
    "gn:name":"Qaryat Kh\u0101lid Bin al Wal\u012bd",
    "gn:population":0,
    "gn:timezone":"Africa/Cairo",
    "iso:country":"EG",
    "name:ara_x_preferred":[
        "\u0642\u0631\u064a\u0629 \u062e\u0627\u0644\u062f \u0628\u0646 \u0627\u0644\u0648\u0644\u064a\u062f"
    ],
    "name:und_x_variant":[
        "Qaryat Kh\u0101lid Bin al Wal\u012bd"
    ],
    "wof:name":"Qaryat Khalid Bin al Walid",
    "wof:placetype":"locality"
},
  "geometry": {"coordinates":[32.044,31.0054],"type":"Point"}
}