{
  "type": "Feature",
  "properties": {
    "gn:admin1_code":"01",
    "gn:asciiname":"Kafr Badawi",
    "gn:country_code":"EG",
    "gn:dem":7,
    "gn:feature_class":"P",
    "gn:feature_code":"PPL",
    "gn:name":"Kafr Badaw\u012b",
    "gn:population":0,
    "gn:timezone":"Africa/Cairo",
    "iso:country":"EG",
    "name:ara_x_preferred":[
        "\u0643\u0641\u0631 \u0628\u062f\u0648\u064a"
    ],
    "name:und_x_variant":[
        "Kafr Badaw\u012b",
        "Kafr Badawi"
    ],
    "wof:name":"Kafr Badawi",
    "wof:placetype":"locality"
},
  "geometry": {"coordinates":[31.4742,30.89116],"type":"Point"}
}