{
  "type": "Feature",
  "properties": {
    "gn:admin1_code":"03",
    "gn:asciiname":"`Izbat Bahnasi",
    "gn:country_code":"EG",
    "gn:dem":3,
    "gn:feature_class":"P",
    "gn:feature_code":"PPL",
    "gn:name":"\u2018Izbat Bahnas\u012b",
    "gn:population":0,
    "gn:timezone":"Africa/Cairo",
    "iso:country":"EG",
    "name:ara_x_preferred":[
        "\u0639\u0632\u0628\u0629 \u0628\u0647\u0646\u0633\u064a"
    ],
    "name:und_x_variant":[
        "\u2018Izbat Bahnas\u012b"
    ],
    "wof:name":"`Izbat Bahnasi",
    "wof:placetype":"locality"
},
  "geometry": {"coordinates":[30.3988,31.42415],"type":"Point"}
}