{
  "type": "Feature",
  "properties": {
    "gn:admin1_code":"04",
    "gn:asciiname":"`Ezbet el- Sa`da el-Bahariya",
    "gn:country_code":"EG",
    "gn:dem":14,
    "gn:feature_class":"P",
    "gn:feature_code":"PPL",
    "gn:name":"\u2018Ezbet el- Sa\u2018da el-Bahar\u00eeya",
    "gn:population":0,
    "gn:timezone":"Africa/Cairo",
    "iso:country":"EG",
    "wof:name":"`Ezbet el- Sa`da el-Bahariya",
    "wof:placetype":"locality"
},
  "geometry": {"coordinates":[30.83333,29.18333],"type":"Point"}
}