{
  "type": "Feature",
  "properties": {
    "gn:admin1_code":"01",
    "gn:asciiname":"`Izbat Muhammad al Masiri",
    "gn:country_code":"EG",
    "gn:dem":2,
    "gn:feature_class":"P",
    "gn:feature_code":"PPL",
    "gn:name":"\u2018Izbat Mu\u1e29ammad al Mas\u012br\u012b",
    "gn:population":0,
    "gn:timezone":"Africa/Cairo",
    "iso:country":"EG",
    "name:ara_x_preferred":[
        "\u0639\u0632\u0628\u0629 \u0645\u062d\u0645\u062f \u0627\u0644\u0645\u0633\u064a\u0631\u064a"
    ],
    "name:und_x_variant":[
        "\u2018Izbat Mu\u1e29ammad al Mis\u012br\u012b",
        "\u2018Izbat Mu\u1e29ammad al Mas\u012br\u012b"
    ],
    "wof:name":"`Izbat Muhammad al Masiri",
    "wof:placetype":"locality"
},
  "geometry": {"coordinates":[31.59956,31.29215],"type":"Point"}
}