{
  "type": "Feature",
  "properties": {
    "gn:admin1_code":"05",
    "gn:asciiname":"`Izbat Sulayman `Abd Allah",
    "gn:country_code":"EG",
    "gn:dem":6,
    "gn:feature_class":"P",
    "gn:feature_code":"PPL",
    "gn:name":"\u2018Izbat Sulaym\u0101n \u2018Abd All\u0101h",
    "gn:population":0,
    "gn:timezone":"Africa/Cairo",
    "iso:country":"EG",
    "name:ara_x_preferred":[
        "\u0639\u0632\u0628\u0629 \u0633\u0644\u064a\u0645\u0627\u0646 \u0639\u0628\u062f \u0627\u0644\u0644\u0647"
    ],
    "name:und_x_variant":[
        "\u2018Izbat Sulaym\u0101n \u2018Abd All\u0101h"
    ],
    "wof:name":"`Izbat Sulayman `Abd Allah",
    "wof:placetype":"locality"
},
  "geometry": {"coordinates":[31.03077,31.01808],"type":"Point"}
}