{
  "type": "Feature",
  "properties": {
    "gn:admin1_code":"21",
    "gn:asciiname":"Al Banna'in",
    "gn:country_code":"EG",
    "gn:dem":5,
    "gn:feature_class":"P",
    "gn:feature_code":"PPL",
    "gn:name":"Al Bann\u0101\u2019\u012bn",
    "gn:population":0,
    "gn:timezone":"Africa/Cairo",
    "iso:country":"EG",
    "name:ara_x_preferred":[
        "\u0627\u0644\u0628\u0646\u0627\u0626\u064a\u0646"
    ],
    "name:und_x_variant":[
        "El-Bann\u00e2\u2019\u00een",
        "El-Bann\u00e2y\u00een",
        "Al Bann\u0101\u2019\u012bn"
    ],
    "wof:name":"Al Banna'in",
    "wof:placetype":"locality"
},
  "geometry": {"coordinates":[31.00975,31.58388],"type":"Point"}
}