{
  "type": "Feature",
  "properties": {
    "gn:admin1_code":"03",
    "gn:asciiname":"`Izbat ash Shami",
    "gn:country_code":"EG",
    "gn:dem":2,
    "gn:feature_class":"P",
    "gn:feature_code":"PPL",
    "gn:name":"\u2018Izbat ash Sh\u0101m\u012b",
    "gn:population":0,
    "gn:timezone":"Africa/Cairo",
    "iso:country":"EG",
    "name:ara_x_preferred":[
        "\u0639\u0632\u0628\u0629 \u0627\u0644\u0634\u0627\u0645\u064a"
    ],
    "name:und_x_variant":[
        "\u2018Izbat ash Sh\u0101m\u012b"
    ],
    "wof:name":"`Izbat ash Shami",
    "wof:placetype":"locality"
},
  "geometry": {"coordinates":[30.39005,31.0887],"type":"Point"}
}