{
  "type": "Feature",
  "properties": {
    "gn:admin1_code":"09",
    "gn:asciiname":"Kafr el-Sanabsa",
    "gn:country_code":"EG",
    "gn:dem":16,
    "gn:feature_class":"P",
    "gn:feature_code":"PPL",
    "gn:name":"Kafr el-San\u00e2bsa",
    "gn:population":0,
    "gn:timezone":"Africa/Cairo",
    "iso:country":"EG",
    "name:ara_x_preferred":[
        "\u0643\u0641\u0631 \u0627\u0644\u0633\u0646\u0627\u0628\u0633\u0629"
    ],
    "name:und_x_variant":[
        "Kafr al-Sanabisa",
        "Kafr as-Sanabisah"
    ],
    "wof:name":"Kafr el-Sanabsa",
    "wof:placetype":"locality"
},
  "geometry": {"coordinates":[30.90353,30.43968],"type":"Point"}
}