{
  "type": "Feature",
  "properties": {
    "gn:admin1_code":"12",
    "gn:asciiname":"Kafr `Ulaym",
    "gn:country_code":"EG",
    "gn:dem":22,
    "gn:feature_class":"P",
    "gn:feature_code":"PPL",
    "gn:name":"Kafr \u2018Ulaym",
    "gn:population":0,
    "gn:timezone":"Africa/Cairo",
    "iso:country":"EG",
    "name:ara_x_preferred":[
        "\u0643\u0641\u0631 \u0639\u0644\u064a\u0645"
    ],
    "name:und_x_variant":[
        "Kafr \u2018Ileim",
        "Kafr \u2018Ulaym",
        "Kafr \u2018Ilaym"
    ],
    "wof:name":"Kafr `Ulaym",
    "wof:placetype":"locality"
},
  "geometry": {"coordinates":[31.12681,30.25692],"type":"Point"}
}