{
  "type": "Feature",
  "properties": {
    "gn:admin1_code":"14",
    "gn:asciiname":"Manshiyat Shalabi",
    "gn:country_code":"EG",
    "gn:dem":10,
    "gn:feature_class":"P",
    "gn:feature_code":"PPL",
    "gn:name":"Mansh\u012byat Shalab\u012b",
    "gn:population":0,
    "gn:timezone":"Africa/Cairo",
    "iso:country":"EG",
    "name:ara_x_preferred":[
        "\u0645\u0646\u0634\u064a\u0629 \u0634\u0644\u0628\u064a"
    ],
    "name:und_x_variant":[
        "Mansh\u012byat Shalab\u012b"
    ],
    "wof:name":"Manshiyat Shalabi",
    "wof:placetype":"locality"
},
  "geometry": {"coordinates":[31.61969,30.80596],"type":"Point"}
}