{
  "type": "Feature",
  "properties": {
    "gn:admin1_code":"20",
    "gn:asciiname":"`Izbat an Najjar",
    "gn:country_code":"EG",
    "gn:dem":1,
    "gn:feature_class":"P",
    "gn:feature_code":"PPL",
    "gn:name":"\u2018Izbat an Najj\u0101r",
    "gn:population":0,
    "gn:timezone":"Africa/Cairo",
    "iso:country":"EG",
    "name:ara_x_preferred":[
        "\u0639\u0632\u0628\u0629 \u0627\u0644\u0646\u062c\u0627\u0631"
    ],
    "name:und_x_variant":[
        "\u2018Izbat an Najj\u0101r"
    ],
    "wof:name":"`Izbat an Najjar",
    "wof:placetype":"locality"
},
  "geometry": {"coordinates":[31.7105,31.2895],"type":"Point"}
}