{
  "type": "Feature",
  "properties": {
    "gn:admin1_code":"14",
    "gn:asciiname":"Kafr Ibrahim al `Ayidi",
    "gn:country_code":"EG",
    "gn:dem":15,
    "gn:feature_class":"P",
    "gn:feature_code":"PPL",
    "gn:name":"Kafr Ibr\u0101h\u012bm al \u2018\u0100yid\u012b",
    "gn:population":0,
    "gn:timezone":"Africa/Cairo",
    "iso:country":"EG",
    "name:ara_x_preferred":[
        "\u0643\u0641\u0631 \u0625\u0628\u0631\u0627\u0647\u064a\u0645 \u0627\u0644\u0639\u0627\u064a\u062f\u064a"
    ],
    "name:und_x_variant":[
        "Kafr Ibr\u00e2h\u00eem el \u2018\u00c2y\u00eedi",
        "Kafr Ibr\u0101h\u012bm al \u2018\u0100\u2019id\u012b",
        "Kafr Ibr\u0101h\u012bm al \u2018\u0100yd\u012b",
        "Kafr Ibr\u0101h\u012bm al \u2018\u0100yid\u012b"
    ],
    "wof:name":"Kafr Ibrahim al `Ayidi",
    "wof:placetype":"locality"
},
  "geometry": {"coordinates":[31.58229,30.44804],"type":"Point"}
}