{
  "type": "Feature",
  "properties": {
    "gn:admin1_code":"10",
    "gn:asciiname":"Nazlat ad Dalil",
    "gn:country_code":"EG",
    "gn:dem":37,
    "gn:feature_class":"P",
    "gn:feature_code":"PPL",
    "gn:name":"Nazlat ad Dal\u012bl",
    "gn:population":0,
    "gn:timezone":"Africa/Cairo",
    "iso:country":"EG",
    "name:und_x_variant":[
        "Nazlet el D\u00e2lil",
        "Nazlat ad Dal\u012bl"
    ],
    "wof:name":"Nazlat ad Dalil",
    "wof:placetype":"locality"
},
  "geometry": {"coordinates":[30.81563,28.4806],"type":"Point"}
}