{
  "type": "Feature",
  "properties": {
    "gn:admin1_code":"21",
    "gn:asciiname":"`Izbat al Mahjub",
    "gn:country_code":"EG",
    "gn:dem":2,
    "gn:feature_class":"P",
    "gn:feature_code":"PPL",
    "gn:name":"\u2018Izbat al Ma\u1e29j\u016bb",
    "gn:population":0,
    "gn:timezone":"Africa/Cairo",
    "iso:country":"EG",
    "name:ara_x_preferred":[
        "\u0639\u0632\u0628\u0629 \u0627\u0644\u0645\u062d\u062c\u0648\u0628"
    ],
    "name:und_x_variant":[
        "\u2018Izbat al Ma\u1e29j\u016bb"
    ],
    "wof:name":"`Izbat al Mahjub",
    "wof:placetype":"locality"
},
  "geometry": {"coordinates":[30.6215,31.30318],"type":"Point"}
}