{
  "type": "Feature",
  "properties": {
    "gn:admin1_code":"14",
    "gn:asciiname":"Kafr Abu Daqn",
    "gn:country_code":"EG",
    "gn:dem":17,
    "gn:feature_class":"P",
    "gn:feature_code":"PPL",
    "gn:name":"Kafr Ab\u016b Daqn",
    "gn:population":0,
    "gn:timezone":"Africa/Cairo",
    "iso:country":"EG",
    "name:und_x_variant":[
        "Kafr Abdu Daqn",
        "Kafr Ab\u016b Daqn"
    ],
    "wof:name":"Kafr Abu Daqn",
    "wof:placetype":"locality"
},
  "geometry": {"coordinates":[31.34843,30.4159],"type":"Point"}
}