{
  "type": "Feature",
  "properties": {
    "gn:admin1_code":"16",
    "gn:asciiname":"Faris",
    "gn:country_code":"EG",
    "gn:dem":101,
    "gn:feature_class":"P",
    "gn:feature_code":"PPL",
    "gn:name":"F\u0101ris",
    "gn:population":0,
    "gn:timezone":"Africa/Cairo",
    "iso:country":"EG",
    "name:und_x_variant":[
        "Fares",
        "F\u0101ris"
    ],
    "wof:name":"Faris",
    "wof:placetype":"locality"
},
  "geometry": {"coordinates":[32.90163,24.61465],"type":"Point"}
}