{
  "type": "Feature",
  "properties": {
    "gn:admin1_code":"14",
    "gn:asciiname":"Sintris",
    "gn:country_code":"EG",
    "gn:dem":11,
    "gn:feature_class":"P",
    "gn:feature_code":"PPL",
    "gn:name":"Sintr\u012bs",
    "gn:population":0,
    "gn:timezone":"Africa/Cairo",
    "iso:country":"EG",
    "name:ara_x_preferred":[
        "Sintr\u012bs"
    ],
    "name:ara_x_variant":[
        "\u0633\u0646\u062a\u0631\u064a\u0633"
    ],
    "wof:name":"Sintris",
    "wof:placetype":"locality"
},
  "geometry": {"coordinates":[31.7188,30.73055],"type":"Point"}
}