{
  "type": "Feature",
  "properties": {
    "gn:admin1_code":"28",
    "gn:asciiname":"Naj` Hilami",
    "gn:country_code":"EG",
    "gn:dem":81,
    "gn:feature_class":"P",
    "gn:feature_code":"PPL",
    "gn:name":"Naj\u2018 Hil\u0101m\u012b",
    "gn:population":0,
    "gn:timezone":"Africa/Cairo",
    "iso:country":"EG",
    "name:ara_x_preferred":[
        "\u0646\u062c\u0639 \u0647\u0644\u0627\u0645\u064a"
    ],
    "name:und_x_variant":[
        "Naj\u2018 Hil\u0101m\u012b"
    ],
    "wof:name":"Naj` Hilami",
    "wof:placetype":"locality"
},
  "geometry": {"coordinates":[32.67740999999999,25.75017],"type":"Point"}
}