{
  "type": "Feature",
  "properties": {
    "gn:admin1_code":"21",
    "gn:asciiname":"`Izbat Basyuni Rizq",
    "gn:country_code":"EG",
    "gn:dem":7,
    "gn:feature_class":"P",
    "gn:feature_code":"PPL",
    "gn:name":"\u2018Izbat Basy\u016bn\u012b Rizq",
    "gn:population":0,
    "gn:timezone":"Africa/Cairo",
    "iso:country":"EG",
    "name:ara_x_preferred":[
        "\u0639\u0632\u0628\u0629 \u0628\u0633\u064a\u0648\u0646\u0649 \u0631\u0632\u0642"
    ],
    "name:und_x_variant":[
        "\u2018Izbat Basy\u016bn\u012b Rizq"
    ],
    "wof:name":"`Izbat Basyuni Rizq",
    "wof:placetype":"locality"
},
  "geometry": {"coordinates":[30.7645,31.11994],"type":"Point"}
}