{
  "type": "Feature",
  "properties": {
    "gn:admin1_code":"14",
    "gn:asciiname":"Ad Dahtamun",
    "gn:country_code":"EG",
    "gn:dem":13,
    "gn:feature_class":"P",
    "gn:feature_code":"PPL",
    "gn:name":"Ad Dahtam\u016bn",
    "gn:population":0,
    "gn:timezone":"Africa/Cairo",
    "iso:country":"EG",
    "name:ara_x_preferred":[
        "\u0627\u0644\u062f\u0647\u062a\u0645\u0648\u0646"
    ],
    "name:und_x_variant":[
        "El-Dahtam\u00fbn",
        "Ad Dahtam\u016bn"
    ],
    "wof:name":"Ad Dahtamun",
    "wof:placetype":"locality"
},
  "geometry": {"coordinates":[31.70839,30.68288],"type":"Point"}
}