{
  "type": "Feature",
  "properties": {
    "gn:admin1_code":"03",
    "gn:asciiname":"`Izbat ash Sharif al Gharbiyah",
    "gn:country_code":"EG",
    "gn:dem":10,
    "gn:feature_class":"P",
    "gn:feature_code":"PPL",
    "gn:name":"\u2018Izbat ash Shar\u012bf al Gharb\u012byah",
    "gn:population":0,
    "gn:timezone":"Africa/Cairo",
    "iso:country":"EG",
    "wof:name":"`Izbat ash Sharif al Gharbiyah",
    "wof:placetype":"locality"
},
  "geometry": {"coordinates":[30.71865,30.70943],"type":"Point"}
}