{
  "type": "Feature",
  "properties": {
    "gn:admin1_code":"05",
    "gn:asciiname":"Qasta",
    "gn:country_code":"EG",
    "gn:dem":14,
    "gn:feature_class":"P",
    "gn:feature_code":"PPL",
    "gn:name":"Qas\u0163\u0101",
    "gn:population":0,
    "gn:timezone":"Africa/Cairo",
    "iso:country":"EG",
    "name:und_x_variant":[
        "Qas\u1e6da",
        "Qas\u0163\u0101"
    ],
    "wof:name":"Qasta",
    "wof:placetype":"locality"
},
  "geometry": {"coordinates":[30.79961,30.89181],"type":"Point"}
}