{
  "type": "Feature",
  "properties": {
    "gn:admin1_code":"20",
    "gn:asciiname":"`Izbat Zakariya Zahir",
    "gn:country_code":"EG",
    "gn:dem":3,
    "gn:feature_class":"P",
    "gn:feature_code":"PPL",
    "gn:name":"\u2018Izbat Zakar\u012by\u0101 Z\u0101hir",
    "gn:population":0,
    "gn:timezone":"Africa/Cairo",
    "iso:country":"EG",
    "name:ara_x_preferred":[
        "\u0639\u0632\u0628\u0629 \u0632\u0643\u0631\u064a\u0627 \u0632\u0627\u0647\u0631"
    ],
    "name:und_x_variant":[
        "\u2018Izbat Zakar\u012by\u0101 Z\u0101hir"
    ],
    "wof:name":"`Izbat Zakariya Zahir",
    "wof:placetype":"locality"
},
  "geometry": {"coordinates":[31.58822,31.40239],"type":"Point"}
}