{
  "type": "Feature",
  "properties": {
    "gn:admin1_code":"18",
    "gn:asciiname":"Nazlat Iqfahs",
    "gn:country_code":"EG",
    "gn:dem":35,
    "gn:feature_class":"P",
    "gn:feature_code":"PPL",
    "gn:name":"Nazlat Iqfah\u015f",
    "gn:population":0,
    "gn:timezone":"Africa/Cairo",
    "iso:country":"EG",
    "name:ara_x_preferred":[
        "\u0646\u0632\u0644\u0629 \u0627\u0642\u0641\u0647\u0635"
    ],
    "name:und_x_variant":[
        "Nazlet Iqfalis",
        "Nazlat Iqfah\u015f"
    ],
    "wof:name":"Nazlat Iqfahs",
    "wof:placetype":"locality"
},
  "geometry": {"coordinates":[30.8349,28.7731],"type":"Point"}
}