{
  "type": "Feature",
  "properties": {
    "gn:admin1_code":"14",
    "gn:asciiname":"Al Hijaziyah",
    "gn:country_code":"EG",
    "gn:dem":9,
    "gn:feature_class":"P",
    "gn:feature_code":"PPL",
    "gn:name":"Al \u1e28ij\u0101z\u012byah",
    "gn:population":0,
    "gn:timezone":"Africa/Cairo",
    "iso:country":"EG",
    "name:und_x_variant":[
        "\u2018Izbat al \u1e28\u0101jj Sayyid M\u016bs\u00e1",
        "El-\u1e24ig\u00e2z\u00eeya",
        "Al \u1e28ij\u0101z\u012byah"
    ],
    "wof:name":"Al Hijaziyah",
    "wof:placetype":"locality"
},
  "geometry": {"coordinates":[31.87439,30.8577],"type":"Point"}
}