{
  "type": "Feature",
  "properties": {
    "gn:admin1_code":"03",
    "gn:asciiname":"Al Balakus",
    "gn:country_code":"EG",
    "gn:dem":9,
    "gn:feature_class":"P",
    "gn:feature_code":"PPL",
    "gn:name":"Al Bal\u0101k\u016bs",
    "gn:population":0,
    "gn:timezone":"Africa/Cairo",
    "iso:country":"EG",
    "name:und_x_variant":[
        "El-Bal\u00e2k\u00fbs",
        "Al Bal\u0101k\u016bs"
    ],
    "wof:name":"Al Balakus",
    "wof:placetype":"locality"
},
  "geometry": {"coordinates":[30.71184,30.75208],"type":"Point"}
}