{
  "type": "Feature",
  "properties": {
    "gn:admin1_code":"09",
    "gn:asciiname":"Diya al Kawm",
    "gn:country_code":"EG",
    "gn:dem":18,
    "gn:feature_class":"P",
    "gn:feature_code":"PPL",
    "gn:name":"Diy\u0101 al Kawm",
    "gn:population":0,
    "gn:timezone":"Africa/Cairo",
    "iso:country":"EG",
    "name:ara_x_preferred":[
        "\u062f\u064a\u0627 \u0627\u0644\u0643\u0648\u0645"
    ],
    "name:und_x_variant":[
        "Diya el-K\u00f4m",
        "Diy\u0101 al Kawm"
    ],
    "wof:name":"Diya al Kawm",
    "wof:placetype":"locality"
},
  "geometry": {"coordinates":[31.08166,30.63795],"type":"Point"}
}