{
  "type": "Feature",
  "properties": {
    "gn:admin1_code":"07",
    "gn:asciiname":"Al Mahsamah al Qadimah",
    "gn:country_code":"EG",
    "gn:dem":12,
    "gn:feature_class":"P",
    "gn:feature_code":"PPL",
    "gn:name":"Al Ma\u1e29samah al Qad\u012bmah",
    "gn:population":0,
    "gn:timezone":"Africa/Cairo",
    "iso:country":"EG",
    "name:und_x_variant":[
        "El-Mahsama el-Qad\u00eema",
        "Al Ma\u1e29samah al Qad\u012bmah"
    ],
    "wof:name":"Al Mahsamah al Qadimah",
    "wof:placetype":"locality"
},
  "geometry": {"coordinates":[32.02442,30.5465],"type":"Point"}
}