{
  "type": "Feature",
  "properties": {
    "gn:admin1_code":"03",
    "gn:asciiname":"`Izbat Ibrahim Makkawi",
    "gn:country_code":"EG",
    "gn:dem":14,
    "gn:feature_class":"P",
    "gn:feature_code":"PPL",
    "gn:name":"\u2018Izbat Ibr\u0101him Makk\u0101w\u012b",
    "gn:population":0,
    "gn:timezone":"Africa/Cairo",
    "iso:country":"EG",
    "name:ara_x_preferred":[
        "\u0639\u0632\u0628\u0629 \u0625\u0628\u0631\u0627\u0647\u064a\u0645 \u0645\u0643\u0627\u0648\u064a"
    ],
    "name:und_x_variant":[
        "\u2018Izbat Ibr\u0101him Makk\u0101w\u012b",
        "\u2018Izbat Ibr\u0101him Mikk\u0101w\u012b"
    ],
    "wof:name":"`Izbat Ibrahim Makkawi",
    "wof:placetype":"locality"
},
  "geometry": {"coordinates":[30.82227,30.33357],"type":"Point"}
}