{
  "type": "Feature",
  "properties": {
    "gn:admin1_code":"09",
    "gn:asciiname":"`Izbat Nur",
    "gn:country_code":"EG",
    "gn:dem":15,
    "gn:feature_class":"P",
    "gn:feature_code":"PPL",
    "gn:name":"\u2018Izbat N\u016br",
    "gn:population":0,
    "gn:timezone":"Africa/Cairo",
    "iso:country":"EG",
    "name:ara_x_preferred":[
        "\u0639\u0632\u0628\u0629 \u0646\u0648\u0631"
    ],
    "name:und_x_variant":[
        "\u2018Izbat N\u016br"
    ],
    "wof:name":"`Izbat Nur",
    "wof:placetype":"locality"
},
  "geometry": {"coordinates":[30.83784,30.49839],"type":"Point"}
}