{
  "type": "Feature",
  "properties": {
    "gn:admin1_code":"14",
    "gn:asciiname":"Kafr Bani `Amr",
    "gn:country_code":"EG",
    "gn:dem":4,
    "gn:feature_class":"P",
    "gn:feature_code":"PPL",
    "gn:name":"Kafr Ban\u012b \u2018Amr",
    "gn:population":0,
    "gn:timezone":"Africa/Cairo",
    "iso:country":"EG",
    "name:und_x_variant":[
        "Kafr Beni \u2018Amr",
        "Kafr Ban\u012b \u2018Amr"
    ],
    "wof:name":"Kafr Bani `Amr",
    "wof:placetype":"locality"
},
  "geometry": {"coordinates":[31.88417,30.77722],"type":"Point"}
}