{
  "type": "Feature",
  "properties": {
    "gn:admin1_code":"01",
    "gn:asciiname":"`Izbat al Fath",
    "gn:country_code":"EG",
    "gn:dem":9,
    "gn:feature_class":"P",
    "gn:feature_code":"PPL",
    "gn:name":"\u2018Izbat al Fat\u1e29",
    "gn:population":0,
    "gn:timezone":"Africa/Cairo",
    "iso:country":"EG",
    "name:ara_x_preferred":[
        "\u0639\u0632\u0628\u0629 \u0627\u0644\u0641\u062a\u062d"
    ],
    "name:und_x_variant":[
        "\u2018Izbat al Fat\u1e29"
    ],
    "wof:name":"`Izbat al Fath",
    "wof:placetype":"locality"
},
  "geometry": {"coordinates":[31.52152,30.86541],"type":"Point"}
}