{
  "type": "Feature",
  "properties": {
    "gn:admin1_code":"03",
    "gn:asciiname":"El-Fa'iza",
    "gn:country_code":"EG",
    "gn:dem":0,
    "gn:feature_class":"P",
    "gn:feature_code":"PPL",
    "gn:name":"El-F\u00e2\u2019iza",
    "gn:population":0,
    "gn:timezone":"Africa/Cairo",
    "iso:country":"EG",
    "wof:name":"El-Fa'iza",
    "wof:placetype":"locality"
},
  "geometry": {"coordinates":[30.48056,31.2675],"type":"Point"}
}