{
  "type": "Feature",
  "properties": {
    "gn:admin1_code":"21",
    "gn:asciiname":"`Izbat Abu Sulayman",
    "gn:country_code":"EG",
    "gn:dem":3,
    "gn:feature_class":"P",
    "gn:feature_code":"PPL",
    "gn:name":"\u2018Izbat Ab\u016b Sulaym\u0101n",
    "gn:population":0,
    "gn:timezone":"Africa/Cairo",
    "iso:country":"EG",
    "name:ara_x_preferred":[
        "\u0639\u0632\u0628\u0629 \u0623\u0628\u0648 \u0633\u0644\u064a\u0645\u0627\u0646"
    ],
    "name:und_x_variant":[
        "\u2018Izbat Ab\u016b Sulaym\u0101n"
    ],
    "wof:name":"`Izbat Abu Sulayman",
    "wof:placetype":"locality"
},
  "geometry": {"coordinates":[31.12694,31.22823],"type":"Point"}
}