{
  "type": "Feature",
  "properties": {
    "gn:admin1_code":"18",
    "gn:asciiname":"Nazlat `Arafah",
    "gn:country_code":"EG",
    "gn:dem":28,
    "gn:feature_class":"P",
    "gn:feature_code":"PPL",
    "gn:name":"Nazlat \u2018Arafah",
    "gn:population":0,
    "gn:timezone":"Africa/Cairo",
    "iso:country":"EG",
    "name:und_x_variant":[
        "Nazlet \u2018Arafa",
        "Nazlat \u2018Arafah"
    ],
    "wof:name":"Nazlat `Arafah",
    "wof:placetype":"locality"
},
  "geometry": {"coordinates":[30.93333,28.93333],"type":"Point"}
}