{
  "type": "Feature",
  "properties": {
    "gn:admin1_code":"03",
    "gn:asciiname":"`Izbat Shams ad Din",
    "gn:country_code":"EG",
    "gn:dem":1,
    "gn:feature_class":"P",
    "gn:feature_code":"PPL",
    "gn:name":"\u2018Izbat Shams ad D\u012bn",
    "gn:population":0,
    "gn:timezone":"Africa/Cairo",
    "iso:country":"EG",
    "name:ara_x_preferred":[
        "\u0639\u0632\u0628\u0629 \u0634\u0645\u0633 \u0627\u0644\u062f\u064a\u0646"
    ],
    "name:und_x_variant":[
        "\u2018Izbat Shams ad D\u012bn"
    ],
    "wof:name":"`Izbat Shams ad Din",
    "wof:placetype":"locality"
},
  "geometry": {"coordinates":[30.34256,31.04726],"type":"Point"}
}