{
  "type": "Feature",
  "properties": {
    "gn:admin1_code":"17",
    "gn:asciiname":"Ballut",
    "gn:country_code":"EG",
    "gn:dem":51,
    "gn:feature_class":"P",
    "gn:feature_code":"PPL",
    "gn:name":"Ball\u016b\u0163",
    "gn:population":0,
    "gn:timezone":"Africa/Cairo",
    "iso:country":"EG",
    "wof:name":"Ballut",
    "wof:placetype":"locality"
},
  "geometry": {"coordinates":[30.84318,27.37005],"type":"Point"}
}