{
  "type": "Feature",
  "properties": {
    "gn:admin1_code":"04",
    "gn:asciiname":"`Ezbet Muhammad Gad",
    "gn:country_code":"EG",
    "gn:dem":-25,
    "gn:feature_class":"P",
    "gn:feature_code":"PPL",
    "gn:name":"\u2018Ezbet Mu\u1e25ammad G\u00e2d",
    "gn:population":0,
    "gn:timezone":"Africa/Cairo",
    "iso:country":"EG",
    "wof:name":"`Ezbet Muhammad Gad",
    "wof:placetype":"locality"
},
  "geometry": {"coordinates":[30.86667000000001,29.45],"type":"Point"}
}