{
  "type": "Feature",
  "properties": {
    "gn:admin1_code":"14",
    "gn:asciiname":"`Izbat `Abd al Hadi Badr",
    "gn:country_code":"EG",
    "gn:dem":8,
    "gn:feature_class":"P",
    "gn:feature_code":"PPL",
    "gn:name":"\u2018Izbat \u2018Abd al H\u0101d\u012b Badr",
    "gn:population":0,
    "gn:timezone":"Africa/Cairo",
    "iso:country":"EG",
    "name:ara_x_preferred":[
        "\u0639\u0632\u0628\u0629 \u0639\u0628\u062f \u0627\u0644\u0647\u0627\u062f\u064a \u0628\u062f\u0631"
    ],
    "name:und_x_variant":[
        "\u2018Izbat \u2018Abd al H\u0101d\u012b Badr"
    ],
    "wof:name":"`Izbat `Abd al Hadi Badr",
    "wof:placetype":"locality"
},
  "geometry": {"coordinates":[31.41272,30.6741],"type":"Point"}
}