{
  "type": "Feature",
  "properties": {
    "gn:admin1_code":"21",
    "gn:asciiname":"`Izbat Ibrahim al Far",
    "gn:country_code":"EG",
    "gn:dem":3,
    "gn:feature_class":"P",
    "gn:feature_code":"PPL",
    "gn:name":"\u2018Izbat Ibr\u0101h\u012bm al F\u0101r",
    "gn:population":0,
    "gn:timezone":"Africa/Cairo",
    "iso:country":"EG",
    "name:ara_x_preferred":[
        "\u0639\u0632\u0628\u0629 \u0625\u0628\u0631\u0627\u0647\u064a\u0645 \u0627\u0644\u0641\u0627\u0631"
    ],
    "name:und_x_variant":[
        "\u2018Izbat Ibr\u0101h\u012bm al F\u0101r"
    ],
    "wof:name":"`Izbat Ibrahim al Far",
    "wof:placetype":"locality"
},
  "geometry": {"coordinates":[30.69715,31.15965],"type":"Point"}
}