{
  "type": "Feature",
  "properties": {
    "gn:admin1_code":"03",
    "gn:asciiname":"`Ezbet el-Rub`umaya",
    "gn:country_code":"EG",
    "gn:dem":7,
    "gn:feature_class":"P",
    "gn:feature_code":"PPL",
    "gn:name":"\u2018Ezbet el-Rub\u2018um\u00e2ya",
    "gn:population":0,
    "gn:timezone":"Africa/Cairo",
    "iso:country":"EG",
    "wof:name":"`Ezbet el-Rub`umaya",
    "wof:placetype":"locality"
},
  "geometry": {"coordinates":[30.26157000000001,30.8148],"type":"Point"}
}