{
  "type": "Feature",
  "properties": {
    "gn:admin1_code":"05",
    "gn:asciiname":"`Izbat as Sayyid Husayn al Qasabi",
    "gn:country_code":"EG",
    "gn:dem":7,
    "gn:feature_class":"P",
    "gn:feature_code":"PPL",
    "gn:name":"\u2018Izbat as Sayyid \u1e28usayn al Qa\u015fab\u012b",
    "gn:population":0,
    "gn:timezone":"Africa/Cairo",
    "iso:country":"EG",
    "name:ara_x_preferred":[
        "\u0639\u0632\u0628\u0629 \u0627\u0644\u0633\u064a\u062f \u062d\u0633\u064a\u0646 \u0627\u0644\u0642\u0635\u0628\u064a"
    ],
    "name:und_x_variant":[
        "\u2018Izbat as Sayyid \u1e28usayn al Qa\u015fab\u012b",
        "\u2018Izbat as-Sayyid \u1e24usayn al-Qa\u1e63ab\u012b"
    ],
    "wof:name":"`Izbat as Sayyid Husayn al Qasabi",
    "wof:placetype":"locality"
},
  "geometry": {"coordinates":[31.07012000000001,30.88202],"type":"Point"}
}