{
  "type": "Feature",
  "properties": {
    "gn:admin1_code":"12",
    "gn:asciiname":"Kafr al Hasafah",
    "gn:cc2":"EG",
    "gn:country_code":"EG",
    "gn:dem":22,
    "gn:feature_class":"P",
    "gn:feature_code":"PPL",
    "gn:name":"Kafr al \u1e28a\u015f\u0101fah",
    "gn:population":0,
    "gn:timezone":"Africa/Cairo",
    "iso:country":"EG",
    "name:und_x_variant":[
        "Kafr el-\u1e24i\u1e63\u00e2fa",
        "Kafr al \u1e28a\u015f\u0101fah"
    ],
    "wof:name":"Kafr al Hasafah",
    "wof:placetype":"locality"
},
  "geometry": {"coordinates":[31.25204,30.32729],"type":"Point"}
}