{
  "type": "Feature",
  "properties": {
    "gn:admin1_code":"01",
    "gn:asciiname":"`Izbat as Sab`in",
    "gn:country_code":"EG",
    "gn:dem":8,
    "gn:feature_class":"P",
    "gn:feature_code":"PPL",
    "gn:name":"\u2018Izbat as Sab\u2018\u012bn",
    "gn:population":0,
    "gn:timezone":"Africa/Cairo",
    "iso:country":"EG",
    "name:ara_x_preferred":[
        "\u0639\u0632\u0628\u0629 \u0627\u0644\u0633\u0628\u0639\u064a\u0646"
    ],
    "name:und_x_variant":[
        "\u2018Ezbet el-Sab\u2018\u00een",
        "\u2018Izbat as Sab\u2018\u012bn",
        "\u2018Iz. as-Sab\u2018\u012bn"
    ],
    "wof:name":"`Izbat as Sab`in",
    "wof:placetype":"locality"
},
  "geometry": {"coordinates":[31.45448,30.85274],"type":"Point"}
}