{
  "type": "Feature",
  "properties": {
    "gn:admin1_code":"05",
    "gn:asciiname":"Dilibshan",
    "gn:country_code":"EG",
    "gn:dem":10,
    "gn:feature_class":"P",
    "gn:feature_code":"PPL",
    "gn:name":"Dilibsh\u0101n",
    "gn:population":0,
    "gn:timezone":"Africa/Cairo",
    "iso:country":"EG",
    "name:und_x_variant":[
        "Dilibsh\u00e2n",
        "Dilibsh\u0101n"
    ],
    "wof:name":"Dilibshan",
    "wof:placetype":"locality"
},
  "geometry": {"coordinates":[30.80555,30.78374],"type":"Point"}
}