{
  "type": "Feature",
  "properties": {
    "gn:admin1_code":"05",
    "gn:asciiname":"Kafr Abu Jundi",
    "gn:country_code":"EG",
    "gn:dem":10,
    "gn:feature_class":"P",
    "gn:feature_code":"PPL",
    "gn:name":"Kafr Ab\u016b Jund\u012b",
    "gn:population":0,
    "gn:timezone":"Africa/Cairo",
    "iso:country":"EG",
    "name:und_x_variant":[
        "Kafr Abu Gindi",
        "Kafr Ab\u016b Jund\u012b"
    ],
    "wof:name":"Kafr Abu Jundi",
    "wof:placetype":"locality"
},
  "geometry": {"coordinates":[30.9341,30.91345],"type":"Point"}
}