{
  "type": "Feature",
  "properties": {
    "gn:admin1_code":"01",
    "gn:asciiname":"`Izbat Muhyi ad Din al Badrawi",
    "gn:country_code":"EG",
    "gn:dem":7,
    "gn:feature_class":"P",
    "gn:feature_code":"PPL",
    "gn:name":"\u2018Izbat Mu\u1e29y\u012b ad D\u012bn al Badr\u0101w\u012b",
    "gn:population":0,
    "gn:timezone":"Africa/Cairo",
    "iso:country":"EG",
    "name:ara_x_preferred":[
        "\u0639\u0632\u0628\u0629 \u0645\u062d\u064a \u0627\u0644\u062f\u064a\u0646 \u0627\u0644\u0628\u062f\u0631\u0627\u0648\u064a"
    ],
    "name:und_x_variant":[
        "\u2018Izbat Mu\u1e29y\u012b ad D\u012bn al Badr\u0101w\u012b",
        "\u2018Izbat Mu\u1e25y\u012b ad-D\u012bn al-Badr\u0101w\u012b"
    ],
    "wof:name":"`Izbat Muhyi ad Din al Badrawi",
    "wof:placetype":"locality"
},
  "geometry": {"coordinates":[31.27019,31.10341],"type":"Point"}
}