{
  "type": "Feature",
  "properties": {
    "gn:admin1_code":"14",
    "gn:asciiname":"`Izbat `Abd ar Rahman Nusayr",
    "gn:country_code":"EG",
    "gn:dem":9,
    "gn:feature_class":"P",
    "gn:feature_code":"PPL",
    "gn:name":"\u2018Izbat \u2018Abd ar Ra\u1e29m\u0101n Nu\u015fayr",
    "gn:population":0,
    "gn:timezone":"Africa/Cairo",
    "iso:country":"EG",
    "name:ara_x_preferred":[
        "\u0639\u0632\u0628\u0629 \u0639\u0628\u062f \u0627\u0644\u0631\u062d\u0645\u0646 \u0646\u0635\u064a\u0631"
    ],
    "name:und_x_variant":[
        "\u2018Izbat \u2018Abd ar Ra\u1e29m\u0101n Nu\u015fayr"
    ],
    "wof:name":"`Izbat `Abd ar Rahman Nusayr",
    "wof:placetype":"locality"
},
  "geometry": {"coordinates":[31.66326,30.74189],"type":"Point"}
}