{
  "type": "Feature",
  "properties": {
    "gn:admin1_code":"03",
    "gn:asciiname":"`Izbat Tawhid",
    "gn:country_code":"EG",
    "gn:dem":0,
    "gn:feature_class":"P",
    "gn:feature_code":"PPL",
    "gn:name":"\u2018Izbat Taw\u1e29\u012bd",
    "gn:population":0,
    "gn:timezone":"Africa/Cairo",
    "iso:country":"EG",
    "wof:name":"`Izbat Tawhid",
    "wof:placetype":"locality"
},
  "geometry": {"coordinates":[30.64835,30.90592],"type":"Point"}
}