{
  "type": "Feature",
  "properties": {
    "gn:admin1_code":"14",
    "gn:asciiname":"`Izbat al Birins",
    "gn:country_code":"EG",
    "gn:dem":8,
    "gn:feature_class":"P",
    "gn:feature_code":"PPL",
    "gn:name":"\u2018Izbat al Birins",
    "gn:population":0,
    "gn:timezone":"Africa/Cairo",
    "iso:country":"EG",
    "name:ara_x_preferred":[
        "\u0639\u0632\u0628\u0629 \u0627\u0644\u0628\u0631\u0646\u0633"
    ],
    "name:und_x_variant":[
        "\u2018Izbat al Birins"
    ],
    "wof:name":"`Izbat al Birins",
    "wof:placetype":"locality"
},
  "geometry": {"coordinates":[31.62392,30.69173],"type":"Point"}
}