{
  "type": "Feature",
  "properties": {
    "gn:admin1_code":"05",
    "gn:asciiname":"Kafr Nusayr",
    "gn:country_code":"EG",
    "gn:dem":10,
    "gn:feature_class":"P",
    "gn:feature_code":"PPL",
    "gn:name":"Kafr Nu\u015fayr",
    "gn:population":0,
    "gn:timezone":"Africa/Cairo",
    "iso:country":"EG",
    "name:und_x_variant":[
        "Kafr Nu\u1e63eir",
        "Kafr Nu\u015fayr"
    ],
    "wof:name":"Kafr Nusayr",
    "wof:placetype":"locality"
},
  "geometry": {"coordinates":[30.86473,30.91365],"type":"Point"}
}