{
  "type": "Feature",
  "properties": {
    "gn:admin1_code":"03",
    "gn:asciiname":"Al Bihay",
    "gn:country_code":"EG",
    "gn:dem":7,
    "gn:feature_class":"P",
    "gn:feature_code":"PPL",
    "gn:name":"Al Bihay",
    "gn:population":0,
    "gn:timezone":"Africa/Cairo",
    "iso:country":"EG",
    "name:und_x_variant":[
        "El-Bihai",
        "Al Bihay"
    ],
    "wof:name":"Al Bihay",
    "wof:placetype":"locality"
},
  "geometry": {"coordinates":[30.56212,30.92075],"type":"Point"}
}