{
  "type": "Feature",
  "properties": {
    "gn:admin1_code":"01",
    "gn:asciiname":"`Izbat `Ali Muhammad",
    "gn:country_code":"EG",
    "gn:dem":10,
    "gn:feature_class":"P",
    "gn:feature_code":"PPL",
    "gn:name":"\u2018Izbat \u2018Al\u012b Mu\u1e29ammad",
    "gn:population":0,
    "gn:timezone":"Africa/Cairo",
    "iso:country":"EG",
    "name:ara_x_preferred":[
        "\u0639\u0632\u0628\u0629 \u0639\u0644\u064a \u0645\u062d\u0645\u062f"
    ],
    "name:und_x_variant":[
        "\u2018Izbat \u2018Al\u012b Mu\u1e29ammad"
    ],
    "wof:name":"`Izbat `Ali Muhammad",
    "wof:placetype":"locality"
},
  "geometry": {"coordinates":[31.36722,30.69755],"type":"Point"}
}