{
  "type": "Feature",
  "properties": {
    "gn:country":"EG",
    "gn:fcode":"PPL",
    "gn:pop":56302,
    "iso:country":"EG",
    "name:ara_x_preferred":[
        "\u0627\u0644\u0642\u0646\u0627\u0637\u0631 \u0627\u0644\u062e\u064a\u0631\u064a\u0629"
    ],
    "name:arz_x_preferred":[
        "\u062a\u0627\u0631\u064a\u062e \u0627\u0644\u0642\u0646\u0627\u0637\u0631 \u0627\u0644\u062e\u064a\u0631\u064a\u0629"
    ],
    "name:dut_x_preferred":[
        "Qanatir el Qahiriya"
    ],
    "name:eng_x_preferred":[
        "Qanatir el Qahiriya"
    ],
    "name:fre_x_preferred":[
        "Qanatir el Qahiriya"
    ],
    "name:ger_x_preferred":[
        "al-Qanatir al-Chairiyya"
    ],
    "name:per_x_preferred":[
        "\u0642\u0646\u0627\u0637\u0631 \u062e\u06cc\u0631\u06cc\u0647"
    ],
    "name:pol_x_preferred":[
        "Al-Kanatir al-Chajrijja"
    ],
    "name:rus_x_preferred":[
        "\u042d\u043b\u044c-\u041a\u0430\u043d\u0430\u0442\u0438\u0440-\u044d\u043b\u044c-\u0425\u0435\u0439\u0440\u0438\u044f"
    ],
    "name:unk_x_variant":[
        "El-Qan\u00e2\u1e6dir el-Khair\u00eeya"
    ],
    "qs:name":"Al Qan\u0101\u0163ir al Khayr\u012byah",
    "qs:photos_9r":0,
    "qs:photos_sr":0,
    "qs:pop_sr":"8",
    "wof:name":"Al Qan\u0101\u0163ir al Khayr\u012byah",
    "wof:placetype":"locality",
    "wof:population":56302
},
  "geometry": {"coordinates":[31.13703,30.19327],"type":"Point"}
}