{
  "type": "Feature",
  "properties": {
    "gn:admin1_code":"09",
    "gn:asciiname":"Kafr el- Dawwar Ikyad",
    "gn:country_code":"EG",
    "gn:dem":17,
    "gn:feature_class":"P",
    "gn:feature_code":"PPL",
    "gn:name":"Kafr el- Dawwar Iky\u00e2d",
    "gn:population":0,
    "gn:timezone":"Africa/Cairo",
    "iso:country":"EG",
    "wof:name":"Kafr el- Dawwar Ikyad",
    "wof:placetype":"locality"
},
  "geometry": {"coordinates":[31.06667,30.36667000000001],"type":"Point"}
}