{
  "type": "Feature",
  "properties": {
    "gn:admin1_code":"01",
    "gn:asciiname":"`Izbat al Islah",
    "gn:country_code":"EG",
    "gn:dem":9,
    "gn:feature_class":"P",
    "gn:feature_code":"PPL",
    "gn:name":"\u2018Izbat al I\u015fl\u0101\u1e29",
    "gn:population":0,
    "gn:timezone":"Africa/Cairo",
    "iso:country":"EG",
    "name:ara_x_preferred":[
        "\u0639\u0632\u0628\u0629 \u0627\u0644\u0625\u0635\u0644\u0627\u062d"
    ],
    "name:und_x_variant":[
        "\u2018Izbat al I\u015fl\u0101\u1e29",
        "\u2018Izbat al Isl\u0101\u1e29",
        "\u2018Izbat al-I\u1e63l\u0101\u1e25"
    ],
    "wof:name":"`Izbat al Islah",
    "wof:placetype":"locality"
},
  "geometry": {"coordinates":[31.2388,31.10453],"type":"Point"}
}