{
  "type": "Feature",
  "properties": {
    "gn:admin1_code":"21",
    "gn:asciiname":"`Izbat `Abd Allah Abu Musa`id",
    "gn:country_code":"EG",
    "gn:dem":4,
    "gn:feature_class":"P",
    "gn:feature_code":"PPL",
    "gn:name":"\u2018Izbat \u2018Abd All\u0101h Ab\u016b Mus\u0101\u2018id",
    "gn:population":0,
    "gn:timezone":"Africa/Cairo",
    "iso:country":"EG",
    "name:ara_x_preferred":[
        "\u0639\u0632\u0628\u0629 \u0639\u0628\u062f \u0627\u0644\u0644\u0647 \u0623\u0628\u0648 \u0645\u0633\u0627\u0639\u062f"
    ],
    "name:und_x_variant":[
        "\u2018Izbat \u2018Abd All\u0101h Ab\u016b Mus\u0101\u2018id",
        "\u2018Izbat \u2018Abd All\u0101h Ab\u016b Mis\u0101\u2018id"
    ],
    "wof:name":"`Izbat `Abd Allah Abu Musa`id",
    "wof:placetype":"locality"
},
  "geometry": {"coordinates":[30.79578,31.30335],"type":"Point"}
}