{
  "type": "Feature",
  "properties": {
    "gn:admin1_code":"03",
    "gn:asciiname":"`Izbat as Sabiriyah",
    "gn:country_code":"EG",
    "gn:dem":-1,
    "gn:feature_class":"P",
    "gn:feature_code":"PPL",
    "gn:name":"\u2018Izbat a\u015f \u015e\u0101bir\u012byah",
    "gn:population":0,
    "gn:timezone":"Africa/Cairo",
    "iso:country":"EG",
    "name:ara_x_preferred":[
        "\u0639\u0632\u0628\u0629 \u0627\u0644\u0635\u0627\u0628\u0631\u064a\u0629"
    ],
    "name:und_x_variant":[
        "\u2018Izbat a\u015f \u015e\u0101bir\u012byah",
        "\u2018Izbat a\u1e63-\u1e62\u0101biriyyah"
    ],
    "wof:name":"`Izbat as Sabiriyah",
    "wof:placetype":"locality"
},
  "geometry": {"coordinates":[30.49222,31.09488],"type":"Point"}
}