{
  "type": "Feature",
  "properties": {
    "gn:admin1_code":"20",
    "gn:asciiname":"As Sinaniyah",
    "gn:country_code":"EG",
    "gn:dem":11,
    "gn:feature_class":"P",
    "gn:feature_code":"PPL",
    "gn:name":"As Sin\u0101n\u012byah",
    "gn:population":0,
    "gn:timezone":"Africa/Cairo",
    "iso:country":"EG",
    "name:und_x_variant":[
        "El-Sin\u00e2n\u00eeya",
        "As Sin\u0101n\u012byah"
    ],
    "wof:name":"As Sinaniyah",
    "wof:placetype":"locality"
},
  "geometry": {"coordinates":[31.78593,31.41597],"type":"Point"}
}