{
  "type": "Feature",
  "properties": {
    "gn:admin1_code":"01",
    "gn:asciiname":"`Izbat Hasab Allah",
    "gn:country_code":"EG",
    "gn:dem":6,
    "gn:feature_class":"P",
    "gn:feature_code":"PPL",
    "gn:name":"\u2018Izbat \u1e28asab All\u0101h",
    "gn:population":0,
    "gn:timezone":"Africa/Cairo",
    "iso:country":"EG",
    "name:ara_x_preferred":[
        "\u0639\u0632\u0628\u0629 \u062d\u0633\u0628 \u0627\u0644\u0644\u0647"
    ],
    "name:und_x_variant":[
        "\u2018Izbat \u1e28asab All\u0101h"
    ],
    "wof:name":"`Izbat Hasab Allah",
    "wof:placetype":"locality"
},
  "geometry": {"coordinates":[31.58144,31.31179],"type":"Point"}
}