{
  "type": "Feature",
  "properties": {
    "gn:admin1_code":"03",
    "gn:asciiname":"`Izbat al Wakil",
    "gn:country_code":"EG",
    "gn:dem":3,
    "gn:feature_class":"P",
    "gn:feature_code":"PPL",
    "gn:name":"\u2018Izbat al Wak\u012bl",
    "gn:population":0,
    "gn:timezone":"Africa/Cairo",
    "iso:country":"EG",
    "name:ara_x_preferred":[
        "\u0639\u0632\u0628\u0629 \u0627\u0644\u0648\u0643\u064a\u0644"
    ],
    "name:und_x_variant":[
        "\u2018Izbat al Wak\u012bl",
        "\u2018Izbat Al-Wak\u012bl",
        "\u2018Izbat al Wakil"
    ],
    "wof:name":"`Izbat al Wakil",
    "wof:placetype":"locality"
},
  "geometry": {"coordinates":[30.51986,31.0173],"type":"Point"}
}