{
  "type": "Feature",
  "properties": {
    "gn:admin1_code":"23",
    "gn:asciiname":"Naj` al Hamidat",
    "gn:country_code":"EG",
    "gn:dem":93,
    "gn:feature_class":"P",
    "gn:feature_code":"PPL",
    "gn:name":"Naj\u2018 al \u1e28am\u012bd\u0101t",
    "gn:population":0,
    "gn:timezone":"Africa/Cairo",
    "iso:country":"EG",
    "name:und_x_variant":[
        "Nag\u2018 el-Hamad\u00e2t",
        "Naj\u2018 al \u1e28am\u012bd\u0101t"
    ],
    "wof:name":"Naj` al Hamidat",
    "wof:placetype":"locality"
},
  "geometry": {"coordinates":[32.57609,25.3989],"type":"Point"}
}