{
  "type": "Feature",
  "properties": {
    "gn:admin1_code":"06",
    "gn:asciiname":"`Izbat al `Ula",
    "gn:country_code":"EG",
    "gn:dem":46,
    "gn:feature_class":"P",
    "gn:feature_code":"PPL",
    "gn:name":"\u2018Izbat al \u2018Ul\u0101",
    "gn:population":0,
    "gn:timezone":"Africa/Cairo",
    "iso:country":"EG",
    "wof:name":"`Izbat al `Ula",
    "wof:placetype":"locality"
},
  "geometry": {"coordinates":[29.6217,30.82128],"type":"Point"}
}