{
  "type": "Feature",
  "properties": {
    "gn:admin1_code":"12",
    "gn:asciiname":"Kafr Tahlah",
    "gn:country_code":"EG",
    "gn:dem":15,
    "gn:feature_class":"P",
    "gn:feature_code":"PPL",
    "gn:name":"Kafr \u0162a\u1e29lah",
    "gn:population":0,
    "gn:timezone":"Africa/Cairo",
    "iso:country":"EG",
    "name:ara_x_preferred":[
        "\u0643\u0641\u0631 \u0637\u062d\u0644\u0629"
    ],
    "name:azb_x_preferred":[
        "\u06a9\u0641\u0631 \u0637\u062d\u0644\u0647"
    ],
    "name:fas_x_preferred":[
        "\u06a9\u0641\u0631 \u0637\u062d\u0644\u0647"
    ],
    "name:sco_x_preferred":[
        "Kafr Tahla"
    ],
    "name:und_x_variant":[
        "\u1e6ca\u1e25la",
        "Kafr \u1e6ca\u1e25la",
        "Kafr \u0162a\u1e29lah"
    ],
    "wof:name":"Kafr Tahlah",
    "wof:placetype":"locality"
},
  "geometry": {"coordinates":[31.13295,30.39831],"type":"Point"}
}