{
  "type": "Feature",
  "properties": {
    "gn:admin1_code":"10",
    "gn:asciiname":"At Tayyibah",
    "gn:country_code":"EG",
    "gn:dem":40,
    "gn:feature_class":"P",
    "gn:feature_code":"PPL",
    "gn:name":"A\u0163 \u0162ayyibah",
    "gn:population":0,
    "gn:timezone":"Africa/Cairo",
    "iso:country":"EG",
    "name:und_x_variant":[
        "El Ta\u00eeyiba",
        "Et Taiyiba",
        "A\u0163 \u0162ayyibah"
    ],
    "wof:name":"At Tayyibah",
    "wof:placetype":"locality"
},
  "geometry": {"coordinates":[30.648,28.26728],"type":"Point"}
}