{
  "type": "Feature",
  "properties": {
    "gn:admin1_code":"08",
    "gn:asciiname":"Kafr Turki",
    "gn:country_code":"EG",
    "gn:dem":25,
    "gn:feature_class":"P",
    "gn:feature_code":"PPL",
    "gn:name":"Kafr Turk\u012b",
    "gn:population":0,
    "gn:timezone":"Africa/Cairo",
    "iso:country":"EG",
    "wof:name":"Kafr Turki",
    "wof:placetype":"locality"
},
  "geometry": {"coordinates":[31.22417,29.48667],"type":"Point"}
}