{
  "type": "Feature",
  "properties": {
    "gn:admin1_code":"23",
    "gn:asciiname":"Al Jaziriyah",
    "gn:country_code":"EG",
    "gn:dem":75,
    "gn:feature_class":"P",
    "gn:feature_code":"PPL",
    "gn:name":"Al Jaz\u012br\u012byah",
    "gn:population":0,
    "gn:timezone":"Africa/Cairo",
    "iso:country":"EG",
    "name:und_x_variant":[
        "Nag\u2018 el-Girz\u00eeya",
        "Al Jaz\u012br\u012byah"
    ],
    "wof:name":"Al Jaziriyah",
    "wof:placetype":"locality"
},
  "geometry": {"coordinates":[32.78979,26.0303],"type":"Point"}
}