{
  "type": "Feature",
  "properties": {
    "gn:admin1_code":"23",
    "gn:asciiname":"Naj` al Fawiyah",
    "gn:country_code":"EG",
    "gn:dem":76,
    "gn:feature_class":"P",
    "gn:feature_code":"PPL",
    "gn:name":"Naj\u2018 al F\u0101w\u012byah",
    "gn:population":0,
    "gn:timezone":"Africa/Cairo",
    "iso:country":"EG",
    "wof:name":"Naj` al Fawiyah",
    "wof:placetype":"locality"
},
  "geometry": {"coordinates":[32.49119,26.15474],"type":"Point"}
}