{
  "type": "Feature",
  "properties": {
    "gn:admin1_code":"09",
    "gn:asciiname":"`Izbat Bahajat",
    "gn:country_code":"EG",
    "gn:dem":13,
    "gn:feature_class":"P",
    "gn:feature_code":"PPL",
    "gn:name":"\u2018Izbat Bahajat",
    "gn:population":0,
    "gn:timezone":"Africa/Cairo",
    "iso:country":"EG",
    "name:ara_x_preferred":[
        "\u0639\u0632\u0628\u0629 \u0628\u0647\u062c\u062a"
    ],
    "name:und_x_variant":[
        "\u2018Izbat Bahajat"
    ],
    "wof:name":"`Izbat Bahajat",
    "wof:placetype":"locality"
},
  "geometry": {"coordinates":[31.2111,30.60688],"type":"Point"}
}