{
  "type": "Feature",
  "properties": {
    "gn:admin1_code":"3.0",
    "gn:asciiname":"Waqid",
    "gn:country_code":"EG",
    "gn:dem":7,
    "gn:feature_class":"P",
    "gn:feature_code":"PPL",
    "gn:name":"W\u0101qid",
    "gn:population":0,
    "gn:timezone":"Africa/Cairo",
    "iso:country":"EG",
    "name:und_x_variant":[
        "W\u00e2gid",
        "W\u0101qid"
    ],
    "wof:name":"Waqid",
    "wof:placetype":"locality"
},
  "geometry": {"coordinates":[30.74184,30.69456],"type":"Point"}
}