{
  "type": "Feature",
  "properties": {
    "gn:admin1_code":"03",
    "gn:asciiname":"`Izbat Sayf ad Din al Bahariyah",
    "gn:country_code":"EG",
    "gn:dem":4,
    "gn:feature_class":"P",
    "gn:feature_code":"PPL",
    "gn:name":"\u2018Izbat Sayf ad D\u012bn al Ba\u1e29ar\u012byah",
    "gn:population":0,
    "gn:timezone":"Africa/Cairo",
    "iso:country":"EG",
    "wof:name":"`Izbat Sayf ad Din al Bahariyah",
    "wof:placetype":"locality"
},
  "geometry": {"coordinates":[30.57233,30.99157],"type":"Point"}
}