{
  "type": "Feature",
  "properties": {
    "gn:admin1_code":"06",
    "gn:asciiname":"Al Qaryah al `Ashirah Abis",
    "gn:country_code":"EG",
    "gn:dem":-2,
    "gn:feature_class":"P",
    "gn:feature_code":"PPL",
    "gn:name":"Al Qaryah al \u2018\u0100shirah Ab\u012bs",
    "gn:population":0,
    "gn:timezone":"Africa/Cairo",
    "iso:country":"EG",
    "name:ara_x_preferred":[
        "\u0627\u0644\u0642\u0631\u064a\u0629 \u0627\u0644\u0639\u0627\u0634\u0631\u0647 \u0623\u0628\u064a\u0633"
    ],
    "name:und_x_variant":[
        "Al Qaryah al \u2018\u0100shirah Ab\u012bs"
    ],
    "wof:name":"Al Qaryah al `Ashirah Abis",
    "wof:placetype":"locality"
},
  "geometry": {"coordinates":[29.97298,31.17355],"type":"Point"}
}