{
  "type": "Feature",
  "properties": {
    "gn:admin1_code":"09",
    "gn:asciiname":"Shuni",
    "gn:country_code":"EG",
    "gn:dem":14,
    "gn:feature_class":"P",
    "gn:feature_code":"PPL",
    "gn:name":"Sh\u016bn\u012b",
    "gn:population":0,
    "gn:timezone":"Africa/Cairo",
    "iso:country":"EG",
    "name:und_x_variant":[
        "Shawn\u012b",
        "Sh\u00f4ni",
        "Sh\u016bn\u012b"
    ],
    "wof:name":"Shuni",
    "wof:placetype":"locality"
},
  "geometry": {"coordinates":[30.92065,30.75002000000001],"type":"Point"}
}