{
  "type": "Feature",
  "properties": {
    "gn:admin1_code":"21",
    "gn:asciiname":"`Izbat Zahran",
    "gn:country_code":"EG",
    "gn:dem":5,
    "gn:feature_class":"P",
    "gn:feature_code":"PPL",
    "gn:name":"\u2018Izbat Zahr\u0101n",
    "gn:population":0,
    "gn:timezone":"Africa/Cairo",
    "iso:country":"EG",
    "name:ara_x_preferred":[
        "\u0639\u0632\u0628\u0629 \u0632\u0647\u0631\u0627\u0646"
    ],
    "name:und_x_variant":[
        "\u2018Izbat Zahr\u0101n"
    ],
    "wof:name":"`Izbat Zahran",
    "wof:placetype":"locality"
},
  "geometry": {"coordinates":[31.00409,31.19567],"type":"Point"}
}