{
  "type": "Feature",
  "properties": {
    "gn:admin1_code":"09",
    "gn:asciiname":"`Izbat ad Dababiyah",
    "gn:country_code":"EG",
    "gn:dem":14,
    "gn:feature_class":"P",
    "gn:feature_code":"PPL",
    "gn:name":"\u2018Izbat ad Dab\u0101b\u012byah",
    "gn:population":0,
    "gn:timezone":"Africa/Cairo",
    "iso:country":"EG",
    "name:ara_x_preferred":[
        "\u0639\u0632\u0628\u0629 \u0627\u0644\u062f\u0628\u0627\u0628\u064a\u0629"
    ],
    "name:und_x_variant":[
        "\u2018Izbat ad Dab\u0101b\u012byah"
    ],
    "wof:name":"`Izbat ad Dababiyah",
    "wof:placetype":"locality"
},
  "geometry": {"coordinates":[31.06719,30.60912],"type":"Point"}
}