{
  "type": "Feature",
  "properties": {
    "gn:admin1_code":"14",
    "gn:asciiname":"`Izbat as Sa`di",
    "gn:country_code":"EG",
    "gn:dem":8,
    "gn:feature_class":"P",
    "gn:feature_code":"PPL",
    "gn:name":"\u2018Izbat as Sa\u2018d\u012b",
    "gn:population":0,
    "gn:timezone":"Africa/Cairo",
    "iso:country":"EG",
    "name:ara_x_preferred":[
        "\u0639\u0632\u0628\u0629 \u0627\u0644\u0633\u0639\u062f\u064a"
    ],
    "name:und_x_variant":[
        "\u2018Izbat as Sa\u2018d\u012b"
    ],
    "wof:name":"`Izbat as Sa`di",
    "wof:placetype":"locality"
},
  "geometry": {"coordinates":[31.84201,30.7065],"type":"Point"}
}