{
  "type": "Feature",
  "properties": {
    "gn:admin1_code":"14",
    "gn:asciiname":"Shubak Bastah",
    "gn:country_code":"EG",
    "gn:dem":15,
    "gn:feature_class":"P",
    "gn:feature_code":"PPL",
    "gn:name":"Sh\u016bbak Bas\u0163ah",
    "gn:population":0,
    "gn:timezone":"Africa/Cairo",
    "iso:country":"EG",
    "name:ara_x_preferred":[
        "\u0634\u0648\u0628\u0643 \u0628\u0633\u0637\u0629"
    ],
    "name:und_x_variant":[
        "Sh\u00f4bak Bas\u1e6da",
        "Shawbak Bas\u0163ah",
        "Sh\u016bbak Bas\u0163ah"
    ],
    "wof:name":"Shubak Bastah",
    "wof:placetype":"locality"
},
  "geometry": {"coordinates":[31.53723,30.57666],"type":"Point"}
}