{
  "type": "Feature",
  "properties": {
    "gn:admin1_code":"01",
    "gn:asciiname":"Mit Khamis",
    "gn:country_code":"EG",
    "gn:dem":13,
    "gn:feature_class":"P",
    "gn:feature_code":"PPL",
    "gn:name":"M\u012bt Kham\u012bs",
    "gn:population":0,
    "gn:timezone":"Africa/Cairo",
    "iso:country":"EG",
    "name:ara_x_preferred":[
        "\u0645\u064a\u062a \u062e\u0645\u064a\u0633"
    ],
    "name:und_x_variant":[
        "M\u00eet Khami",
        "M\u00eet Kham\u00ees",
        "M\u012bt Kham\u012bs"
    ],
    "wof:name":"Mit Khamis",
    "wof:placetype":"locality"
},
  "geometry": {"coordinates":[31.34295,31.04001],"type":"Point"}
}