{
  "type": "Feature",
  "properties": {
    "gn:admin1_code":"08",
    "gn:asciiname":"`Izbat `Abd al Hamid Ahmad",
    "gn:country_code":"EG",
    "gn:dem":17,
    "gn:feature_class":"P",
    "gn:feature_code":"PPL",
    "gn:name":"\u2018Izbat \u2018Abd al \u1e28am\u012bd A\u1e29mad",
    "gn:population":0,
    "gn:timezone":"Africa/Cairo",
    "iso:country":"EG",
    "name:ara_x_preferred":[
        "\u0639\u0632\u0628\u0629 \u0639\u0628\u062f \u0627\u0644\u062d\u0645\u064a\u062f \u0623\u062d\u0645\u062f"
    ],
    "name:und_x_variant":[
        "\u2018Izbat \u2018Abd al \u1e28am\u012bd A\u1e29mad",
        "\u2018Izbat \u2018Abd al \u1e24am\u012bd A\u1e25mad"
    ],
    "wof:name":"`Izbat `Abd al Hamid Ahmad",
    "wof:placetype":"locality"
},
  "geometry": {"coordinates":[30.95628,30.26289],"type":"Point"}
}