{
  "type": "Feature",
  "properties": {
    "gn:admin1_code":"14",
    "gn:asciiname":"Tall ad Dibah",
    "gn:country_code":"EG",
    "gn:dem":16,
    "gn:feature_class":"P",
    "gn:feature_code":"PPL",
    "gn:name":"Tall ad D\u012bbah",
    "gn:population":0,
    "gn:timezone":"Africa/Cairo",
    "iso:country":"EG",
    "name:ara_x_preferred":[
        "\u062a\u0644 \u0627\u0644\u062f\u064a\u0628\u0629"
    ],
    "name:und_x_variant":[
        "Tall ad D\u012bbah"
    ],
    "wof:name":"Tall ad Dibah",
    "wof:placetype":"locality"
},
  "geometry": {"coordinates":[31.42161,30.52112],"type":"Point"}
}