{
  "type": "Feature",
  "properties": {
    "gn:admin1_code":"06",
    "gn:asciiname":"Qaryah",
    "gn:country_code":"EG",
    "gn:dem":-4,
    "gn:feature_class":"P",
    "gn:feature_code":"PPL",
    "gn:name":"Qaryah",
    "gn:population":0,
    "gn:timezone":"Africa/Cairo",
    "iso:country":"EG",
    "name:ara_x_preferred":[
        "\u0642\u0631\u064a\u0629"
    ],
    "name:und_x_variant":[
        "Qaryat 5/7"
    ],
    "wof:name":"Qaryah",
    "wof:placetype":"locality"
},
  "geometry": {"coordinates":[29.94521,31.15171],"type":"Point"}
}