{
  "type": "Feature",
  "properties": {
    "gn:admin1_code":"17",
    "gn:asciiname":"Al Mandarah Qibli",
    "gn:country_code":"EG",
    "gn:dem":55,
    "gn:feature_class":"P",
    "gn:feature_code":"PPL",
    "gn:name":"Al Mandarah Qibl\u012b",
    "gn:population":0,
    "gn:timezone":"Africa/Cairo",
    "iso:country":"EG",
    "name:und_x_variant":[
        "El Mandara Qibli",
        "Al Mandarah Qibl\u012b"
    ],
    "wof:name":"Al Mandarah Qibli",
    "wof:placetype":"locality"
},
  "geometry": {"coordinates":[31.00252,27.28279],"type":"Point"}
}