{
  "type": "Feature",
  "properties": {
    "gn:admin1_code":"23",
    "gn:asciiname":"Naj` al Kalh",
    "gn:country_code":"EG",
    "gn:dem":73,
    "gn:feature_class":"P",
    "gn:feature_code":"PPL",
    "gn:name":"Naj\u2018 al Kal\u1e29",
    "gn:population":0,
    "gn:timezone":"Africa/Cairo",
    "iso:country":"EG",
    "wof:name":"Naj` al Kalh",
    "wof:placetype":"locality"
},
  "geometry": {"coordinates":[32.23218,26.0352],"type":"Point"}
}