{
  "type": "Feature",
  "properties": {
    "gn:admin1_code":"09",
    "gn:asciiname":"Qashtukh",
    "gn:country_code":"EG",
    "gn:dem":14,
    "gn:feature_class":"P",
    "gn:feature_code":"PPL",
    "gn:name":"Qash\u0163\u016bkh",
    "gn:population":0,
    "gn:timezone":"Africa/Cairo",
    "iso:country":"EG",
    "name:ara_x_preferred":[
        "\u0642\u0634\u0637\u0648\u062e"
    ],
    "name:und_x_variant":[
        "Qash\u1e6d\u00fbkh",
        "Qasht\u00fbkli",
        "Qash\u0163\u016bkh"
    ],
    "wof:name":"Qashtukh",
    "wof:placetype":"locality"
},
  "geometry": {"coordinates":[30.93708,30.74156],"type":"Point"}
}