{
  "type": "Feature",
  "properties": {
    "gn:admin1_code":"01",
    "gn:asciiname":"`Izbat al Juni",
    "gn:country_code":"EG",
    "gn:dem":2,
    "gn:feature_class":"P",
    "gn:feature_code":"PPLF",
    "gn:name":"\u2018Izbat al J\u016bn\u012b",
    "gn:population":0,
    "gn:timezone":"Africa/Cairo",
    "iso:country":"EG",
    "name:ara_x_preferred":[
        "\u0639\u0632\u0628\u0629 \u0627\u0644\u062c\u0648\u0646\u064a"
    ],
    "name:und_x_variant":[
        "\u2018Izbat al J\u016bn\u012b",
        "\u2018Izbat al-J\u016bn\u012b"
    ],
    "wof:name":"`Izbat al Juni",
    "wof:placetype":"locality"
},
  "geometry": {"coordinates":[31.28917,31.19731],"type":"Point"}
}