{
  "type": "Feature",
  "properties": {
    "gn:admin1_code":"16",
    "gn:asciiname":"Ar Raghamah",
    "gn:country_code":"EG",
    "gn:dem":99,
    "gn:feature_class":"P",
    "gn:feature_code":"PPL",
    "gn:name":"Ar Ragh\u0101mah",
    "gn:population":0,
    "gn:timezone":"Africa/Cairo",
    "iso:country":"EG",
    "name:und_x_variant":[
        "El Ragh\u00e2ma",
        "Ar Ragh\u0101mah"
    ],
    "wof:name":"Ar Raghamah",
    "wof:placetype":"locality"
},
  "geometry": {"coordinates":[32.91393,24.54999],"type":"Point"}
}