{
  "type": "Feature",
  "properties": {
    "gn:admin1_code":"01",
    "gn:asciiname":"`Izbat al Mahfuzah",
    "gn:country_code":"EG",
    "gn:dem":6,
    "gn:feature_class":"P",
    "gn:feature_code":"PPL",
    "gn:name":"\u2018Izbat al Ma\u1e29f\u016bz\u0327ah",
    "gn:population":0,
    "gn:timezone":"Africa/Cairo",
    "iso:country":"EG",
    "name:ara_x_preferred":[
        "\u0639\u0632\u0628\u0629 \u0627\u0644\u0645\u062d\u0641\u0648\u0638\u0629"
    ],
    "name:und_x_variant":[
        "\u2018Izbat al Ma\u1e29f\u016bz\u0327ah",
        "\u2018Izbat al Ma\u1e25f\u016bz\u0327ah"
    ],
    "wof:name":"`Izbat al Mahfuzah",
    "wof:placetype":"locality"
},
  "geometry": {"coordinates":[31.40957,31.20528],"type":"Point"}
}