{
  "type": "Feature",
  "properties": {
    "iso:country":"EG",
    "name:ara_x_preferred":[
        "\u062f\u0631\u0627\u0648"
    ],
    "name:arz_x_preferred":[
        "\u062f\u0631\u0627\u0648"
    ],
    "name:ast_x_preferred":[
        "Daraw"
    ],
    "name:deu_x_preferred":[
        "Darau"
    ],
    "name:eng_x_preferred":[
        "Daraw"
    ],
    "name:fas_x_preferred":[
        "\u062f\u0631\u0627\u0648"
    ],
    "name:fra_x_preferred":[
        "Daraw"
    ],
    "name:nld_x_preferred":[
        "Daraw"
    ],
    "name:pol_x_preferred":[
        "Darau"
    ],
    "name:rus_x_preferred":[
        "\u0414\u0430\u0440\u0430\u0443"
    ],
    "name:spa_x_preferred":[
        "Daraw"
    ],
    "name:ukr_x_preferred":[
        "\u0414\u0430\u0440\u0430\u0432"
    ],
    "qs:gn_country":"EG",
    "qs:gn_fcode":"PPL",
    "qs:gn_pop":0,
    "qs:name":"Daraw",
    "qs:name_adm0":"\u0645\u0635\u0631",
    "qs:name_adm1":"\u0627\u0633\u0648\u0627\u0646",
    "qs:photos":419,
    "qs:photos_1k":85,
    "qs:photos_9k":2,
    "qs:photos_9r":5,
    "qs:photos_all":419,
    "qs:photos_sr":6,
    "qs:placetype":"Town",
    "qs:pop_sr":"6",
    "qs:woe_adm0":23424802,
    "wof:name":"Daraw",
    "wof:placetype":"locality"
},
  "geometry": {"coordinates":[32.92324,24.40796],"type":"Point"}
}