{
  "type": "Feature",
  "properties": {
    "gn:admin1_code":"14",
    "gn:asciiname":"`Izbat Hilanah",
    "gn:country_code":"EG",
    "gn:dem":10,
    "gn:feature_class":"P",
    "gn:feature_code":"PPL",
    "gn:name":"\u2018Izbat H\u012bl\u0101nah",
    "gn:population":0,
    "gn:timezone":"Africa/Cairo",
    "iso:country":"EG",
    "name:ara_x_preferred":[
        "\u0639\u0632\u0628\u0629 \u0647\u064a\u0644\u0627\u0646\u0629"
    ],
    "name:und_x_variant":[
        "\u2018Izbat H\u012bl\u0101nah"
    ],
    "wof:name":"`Izbat Hilanah",
    "wof:placetype":"locality"
},
  "geometry": {"coordinates":[31.37856,30.73315],"type":"Point"}
}