{
  "type": "Feature",
  "properties": {
    "gn:admin1_code":"14",
    "gn:asciiname":"`Izbat al Khamsin",
    "gn:country_code":"EG",
    "gn:dem":13,
    "gn:feature_class":"P",
    "gn:feature_code":"PPL",
    "gn:name":"\u2018Izbat al Khams\u012bn",
    "gn:population":0,
    "gn:timezone":"Africa/Cairo",
    "iso:country":"EG",
    "name:ara_x_preferred":[
        "\u0639\u0632\u0628\u0629 \u0627\u0644\u062e\u0645\u0633\u064a\u0646"
    ],
    "name:und_x_variant":[
        "\u2018Izbat al Khams\u012bn"
    ],
    "wof:name":"`Izbat al Khamsin",
    "wof:placetype":"locality"
},
  "geometry": {"coordinates":[31.52136,30.50192],"type":"Point"}
}