{
  "type": "Feature",
  "properties": {
    "gn:admin1_code":"03",
    "gn:asciiname":"Kawm as Saqyah",
    "gn:country_code":"EG",
    "gn:dem":1,
    "gn:feature_class":"P",
    "gn:feature_code":"PPL",
    "gn:name":"Kawm as S\u0101qyah",
    "gn:population":0,
    "gn:timezone":"Africa/Cairo",
    "iso:country":"EG",
    "wof:name":"Kawm as Saqyah",
    "wof:placetype":"locality"
},
  "geometry": {"coordinates":[30.18509,30.95097],"type":"Point"}
}