{
  "type": "Feature",
  "properties": {
    "gn:admin1_code":"28",
    "gn:asciiname":"Naj` az Zanati",
    "gn:country_code":"EG",
    "gn:dem":84,
    "gn:feature_class":"P",
    "gn:feature_code":"PPL",
    "gn:name":"Naj\u2018 az Zan\u0101t\u012b",
    "gn:population":0,
    "gn:timezone":"Africa/Cairo",
    "iso:country":"EG",
    "name:ara_x_preferred":[
        "\u0646\u062c\u0639 \u0627\u0644\u0632\u0646\u0627\u062a\u064a"
    ],
    "name:und_x_variant":[
        "Naj\u2018 az Zan\u0101t\u012b",
        "Naj\u2018 az-Zan\u0101t\u012b"
    ],
    "wof:name":"Naj` az Zanati",
    "wof:placetype":"locality"
},
  "geometry": {"coordinates":[32.56814,25.69132],"type":"Point"}
}