{
  "type": "Feature",
  "properties": {
    "gn:admin1_code":"11",
    "gn:asciiname":"Ghammazah al Kubra",
    "gn:country_code":"EG",
    "gn:dem":28,
    "gn:feature_class":"P",
    "gn:feature_code":"PPL",
    "gn:name":"Ghamm\u0101zah al Kubr\u00e1",
    "gn:population":0,
    "gn:timezone":"Africa/Cairo",
    "iso:country":"EG",
    "name:und_x_variant":[
        "Ghamm\u00e2za el-Kubra",
        "Ghamm\u0101zah al Kubr\u00e1"
    ],
    "wof:name":"Ghammazah al Kubra",
    "wof:placetype":"locality"
},
  "geometry": {"coordinates":[31.29923,29.70879],"type":"Point"}
}