{
  "type": "Feature",
  "properties": {
    "gn:admin1_code":"01",
    "gn:asciiname":"`Izbat Sayyid Ahmad",
    "gn:country_code":"EG",
    "gn:dem":6,
    "gn:feature_class":"P",
    "gn:feature_code":"PPL",
    "gn:name":"\u2018Izbat Sayyid A\u1e29mad",
    "gn:population":0,
    "gn:timezone":"Africa/Cairo",
    "iso:country":"EG",
    "name:ara_x_preferred":[
        "\u0639\u0632\u0628\u0629 \u0633\u064a\u062f \u0623\u062d\u0645\u062f"
    ],
    "name:und_x_variant":[
        "\u2018Izbat Sayyid A\u1e29mad"
    ],
    "wof:name":"`Izbat Sayyid Ahmad",
    "wof:placetype":"locality"
},
  "geometry": {"coordinates":[31.57798,30.93579],"type":"Point"}
}