{
  "type": "Feature",
  "properties": {
    "gn:admin1_code":"24",
    "gn:asciiname":"Al Haridiyah",
    "gn:country_code":"EG",
    "gn:dem":64,
    "gn:feature_class":"P",
    "gn:feature_code":"PPL",
    "gn:name":"Al \u1e28ar\u012bd\u012byah",
    "gn:population":0,
    "gn:timezone":"Africa/Cairo",
    "iso:country":"EG",
    "name:und_x_variant":[
        "El \u1e24\u00eer\u00eed\u00eeya el Ba\u1e25ar\u00eeya",
        "El \u1e24ir\u00eed\u00eeya el Qibl\u00eeya",
        "El \u1e24ir\u00eed\u00eeya",
        "Al \u1e28ar\u012bd\u012byah"
    ],
    "wof:name":"Al Haridiyah",
    "wof:placetype":"locality"
},
  "geometry": {"coordinates":[31.46333,26.76839],"type":"Point"}
}