{
  "type": "Feature",
  "properties": {
    "gn:admin1_code":"14",
    "gn:asciiname":"`Izbat al Falahwah",
    "gn:country_code":"EG",
    "gn:dem":6,
    "gn:feature_class":"P",
    "gn:feature_code":"PPL",
    "gn:name":"\u2018Izbat al Fal\u0101\u1e29wah",
    "gn:population":0,
    "gn:timezone":"Africa/Cairo",
    "iso:country":"EG",
    "name:ara_x_preferred":[
        "\u0639\u0632\u0628\u0629 \u0627\u0644\u0641\u0644\u0627\u062d\u0648\u0629"
    ],
    "name:und_x_variant":[
        "\u2018Izbat al Fal\u0101\u1e29wah",
        "\u2018Izbat al-Fal\u0101hwah"
    ],
    "wof:name":"`Izbat al Falahwah",
    "wof:placetype":"locality"
},
  "geometry": {"coordinates":[31.87215,30.72671],"type":"Point"}
}