{
  "type": "Feature",
  "properties": {
    "gn:admin1_code":"21",
    "gn:asciiname":"`Izbat `Azmi `Ashur",
    "gn:country_code":"EG",
    "gn:dem":4,
    "gn:feature_class":"P",
    "gn:feature_code":"PPL",
    "gn:name":"\u2018Izbat \u2018Azm\u012b \u2018\u0100sh\u016br",
    "gn:population":0,
    "gn:timezone":"Africa/Cairo",
    "iso:country":"EG",
    "name:ara_x_preferred":[
        "\u0639\u0632\u0628\u0629 \u0639\u0632\u0645\u064a \u0639\u0627\u0634\u0648\u0631"
    ],
    "name:und_x_variant":[
        "\u2018Izbat \u2018Azm\u012b \u2018\u0100sh\u016br",
        "\u2018Izbat Azm\u012b \u2018\u0100sh\u016br"
    ],
    "wof:name":"`Izbat `Azmi `Ashur",
    "wof:placetype":"locality"
},
  "geometry": {"coordinates":[30.76533,31.24677],"type":"Point"}
}