{
  "type": "Feature",
  "properties": {
    "gn:admin1_code":"01",
    "gn:asciiname":"Az Zahayirah",
    "gn:country_code":"EG",
    "gn:dem":7,
    "gn:feature_class":"P",
    "gn:feature_code":"PPL",
    "gn:name":"Az Zah\u0101yirah",
    "gn:population":0,
    "gn:timezone":"Africa/Cairo",
    "iso:country":"EG",
    "name:ara_x_preferred":[
        "\u0627\u0644\u0632\u0647\u0627\u064a\u0631\u0629"
    ],
    "name:und_x_variant":[
        "Az Zah\u0101yrah",
        "Az-Zah\u0101yrah",
        "Az Zah\u0101yirah"
    ],
    "wof:name":"Az Zahayirah",
    "wof:placetype":"locality"
},
  "geometry": {"coordinates":[31.47173,30.91734000000001],"type":"Point"}
}