{
  "type": "Feature",
  "properties": {
    "gn:admin1_code":"10",
    "gn:asciiname":"`Ezbet Muhammad Gad",
    "gn:country_code":"EG",
    "gn:dem":30,
    "gn:feature_class":"P",
    "gn:feature_code":"PPL",
    "gn:name":"\u2018Ezbet Muhammad G\u00e2d",
    "gn:population":0,
    "gn:timezone":"Africa/Cairo",
    "iso:country":"EG",
    "wof:name":"`Ezbet Muhammad Gad",
    "wof:placetype":"locality"
},
  "geometry": {"coordinates":[30.85,28.66667],"type":"Point"}
}