{
  "type": "Feature",
  "properties": {
    "gn:admin1_code":"09",
    "gn:asciiname":"`Izbat Khayrat",
    "gn:country_code":"EG",
    "gn:dem":12,
    "gn:feature_class":"P",
    "gn:feature_code":"PPL",
    "gn:name":"\u2018Izbat Khayr\u0101t",
    "gn:population":0,
    "gn:timezone":"Africa/Cairo",
    "iso:country":"EG",
    "name:ara_x_preferred":[
        "\u0639\u0632\u0628\u0629 \u062e\u064a\u0631\u0627\u062a"
    ],
    "name:und_x_variant":[
        "\u2018Izbat Khayr\u0101t"
    ],
    "wof:name":"`Izbat Khayrat",
    "wof:placetype":"locality"
},
  "geometry": {"coordinates":[30.85613,30.38751],"type":"Point"}
}