{
  "type": "Feature",
  "properties": {
    "gn:admin1_code":"21",
    "gn:asciiname":"`Izbat Muharram",
    "gn:country_code":"EG",
    "gn:dem":5,
    "gn:feature_class":"P",
    "gn:feature_code":"PPL",
    "gn:name":"\u2018Izbat Mu\u1e29arram",
    "gn:population":0,
    "gn:timezone":"Africa/Cairo",
    "iso:country":"EG",
    "name:ara_x_preferred":[
        "\u0639\u0632\u0628\u0629 \u0645\u062d\u0631\u0645"
    ],
    "name:und_x_variant":[
        "\u2018Izbat Mu\u1e29arram"
    ],
    "wof:name":"`Izbat Muharram",
    "wof:placetype":"locality"
},
  "geometry": {"coordinates":[30.72618,31.19718],"type":"Point"}
}