{
  "type": "Feature",
  "properties": {
    "gn:admin1_code":"18",
    "gn:asciiname":"Naj` al Mudill al Qibli",
    "gn:country_code":"EG",
    "gn:dem":38,
    "gn:feature_class":"P",
    "gn:feature_code":"PPL",
    "gn:name":"Naj\u2018 al Mu\u1e11ill al Qibl\u012b",
    "gn:population":0,
    "gn:timezone":"Africa/Cairo",
    "iso:country":"EG",
    "name:und_x_variant":[
        "El Mudil el Qibli",
        "Naj\u2018 al Mu\u1e11ill al Qibl\u012b"
    ],
    "wof:name":"Naj` al Mudill al Qibli",
    "wof:placetype":"locality"
},
  "geometry": {"coordinates":[30.93483,28.85645],"type":"Point"}
}