{
  "type": "Feature",
  "properties": {
    "gn:admin1_code":"01",
    "gn:asciiname":"`Izbat ash Shurafa",
    "gn:country_code":"EG",
    "gn:dem":8,
    "gn:feature_class":"P",
    "gn:feature_code":"PPL",
    "gn:name":"\u2018Izbat ash Shuraf\u0101",
    "gn:population":0,
    "gn:timezone":"Africa/Cairo",
    "iso:country":"EG",
    "name:ara_x_preferred":[
        "\u0639\u0632\u0628\u0629 \u0627\u0644\u0634\u0631\u0641\u0627"
    ],
    "name:und_x_variant":[
        "\u2018Izbat ash Shuraf\u0101"
    ],
    "wof:name":"`Izbat ash Shurafa",
    "wof:placetype":"locality"
},
  "geometry": {"coordinates":[31.64753,30.95415],"type":"Point"}
}