{
  "type": "Feature",
  "properties": {
    "gn:admin1_code":"17",
    "gn:asciiname":"Ash Shaykh `Awn Allah",
    "gn:country_code":"EG",
    "gn:dem":47,
    "gn:feature_class":"P",
    "gn:feature_code":"PPL",
    "gn:name":"Ash Shaykh \u2018Awn All\u0101h",
    "gn:population":0,
    "gn:timezone":"Africa/Cairo",
    "iso:country":"EG",
    "name:und_x_variant":[
        "El Sheikh \u2018Onalla",
        "Ash Shaykh \u2018Awn All\u0101h"
    ],
    "wof:name":"Ash Shaykh `Awn Allah",
    "wof:placetype":"locality"
},
  "geometry": {"coordinates":[30.83333,27.41667],"type":"Point"}
}