{
  "type": "Feature",
  "properties": {
    "gn:admin1_code":"03",
    "gn:asciiname":"`Izbat Abu ar Rish al Bahriyah",
    "gn:country_code":"EG",
    "gn:dem":-1,
    "gn:feature_class":"P",
    "gn:feature_code":"PPL",
    "gn:name":"\u2018Izbat Ab\u016b ar R\u012bsh al Ba\u1e29r\u012byah",
    "gn:population":0,
    "gn:timezone":"Africa/Cairo",
    "iso:country":"EG",
    "name:ara_x_preferred":[
        "\u0639\u0632\u0628\u0629 \u0623\u0628\u0648 \u0631\u064a\u0634 \u0627\u0644\u0628\u062d\u0631\u064a\u0629"
    ],
    "name:und_x_variant":[
        "\u2018Ezbet Abu el-R\u00eesh",
        "\u2018Izbat Ab\u016b ar R\u012bsh",
        "\u2018Izbat Ab\u016b ar R\u012bsh al Ba\u1e29r\u012byah",
        "\u2018Ezbet \u2018Abb\u00e2s Ab\u00fb el-R\u00eesh",
        "\u2018Izbat \u2018Abb\u0101s Ab\u016b ar R\u012bsh"
    ],
    "wof:name":"`Izbat Abu ar Rish al Bahriyah",
    "wof:placetype":"locality"
},
  "geometry": {"coordinates":[30.18043,31.0133],"type":"Point"}
}