{
  "type": "Feature",
  "properties": {
    "gn:admin1_code":"21",
    "gn:asciiname":"`Izbat al Wazir",
    "gn:country_code":"EG",
    "gn:dem":2,
    "gn:feature_class":"P",
    "gn:feature_code":"PPL",
    "gn:name":"\u2018Izbat al Waz\u012br",
    "gn:population":0,
    "gn:timezone":"Africa/Cairo",
    "iso:country":"EG",
    "name:ara_x_preferred":[
        "\u0639\u0632\u0628\u0629 \u0627\u0644\u0648\u0632\u064a\u0631"
    ],
    "name:und_x_variant":[
        "\u2018Izbat al Waz\u012br"
    ],
    "wof:name":"`Izbat al Wazir",
    "wof:placetype":"locality"
},
  "geometry": {"coordinates":[30.60436,31.25416],"type":"Point"}
}