{
  "type": "Feature",
  "properties": {
    "gn:admin1_code":"04",
    "gn:asciiname":"`Izbat Bahr Abu al Mir",
    "gn:country_code":"EG",
    "gn:dem":11,
    "gn:feature_class":"P",
    "gn:feature_code":"PPL",
    "gn:name":"\u2018Izbat Ba\u1e29r Ab\u016b al Mir",
    "gn:population":0,
    "gn:timezone":"Africa/Cairo",
    "iso:country":"EG",
    "wof:name":"`Izbat Bahr Abu al Mir",
    "wof:placetype":"locality"
},
  "geometry": {"coordinates":[30.74443,29.25800000000001],"type":"Point"}
}