{
  "type": "Feature",
  "properties": {
    "gn:admin1_code":"03",
    "gn:asciiname":"El-Sheikh Muhammad Rif`at",
    "gn:country_code":"EG",
    "gn:dem":16,
    "gn:feature_class":"P",
    "gn:feature_code":"PPL",
    "gn:name":"El-Sheikh Mu\u1e25ammad Rif\u2018at",
    "gn:population":0,
    "gn:timezone":"Africa/Cairo",
    "iso:country":"EG",
    "wof:name":"El-Sheikh Muhammad Rif`at",
    "wof:placetype":"locality"
},
  "geometry": {"coordinates":[30.33323,30.74504],"type":"Point"}
}