{
  "type": "Feature",
  "properties": {
    "gn:admin1_code":"12",
    "gn:asciiname":"`Izbat Abu Sunnah",
    "gn:country_code":"EG",
    "gn:dem":18,
    "gn:feature_class":"P",
    "gn:feature_code":"PPL",
    "gn:name":"\u2018Izbat Ab\u016b Sunnah",
    "gn:population":0,
    "gn:timezone":"Africa/Cairo",
    "iso:country":"EG",
    "name:ara_x_preferred":[
        "\u0639\u0632\u0628\u0629 \u0623\u0628\u0648 \u0633\u0646\u0629"
    ],
    "name:und_x_variant":[
        "\u2018Izbat Ab\u016b Sinnah",
        "\u2018Izbat Ab\u016b Sunnah"
    ],
    "wof:name":"`Izbat Abu Sunnah",
    "wof:placetype":"locality"
},
  "geometry": {"coordinates":[31.22244,30.15371],"type":"Point"}
}