{
  "type": "Feature",
  "properties": {
    "gn:admin1_code":"14",
    "gn:asciiname":"`Izbat Mustafa Nimr",
    "gn:country_code":"EG",
    "gn:dem":10,
    "gn:feature_class":"P",
    "gn:feature_code":"PPL",
    "gn:name":"\u2018Izbat Mu\u015f\u0163af\u00e1 Nimr",
    "gn:population":0,
    "gn:timezone":"Africa/Cairo",
    "iso:country":"EG",
    "name:ara_x_preferred":[
        "\u0639\u0632\u0628\u0629 \u0645\u0635\u0637\u0641\u0649 \u0646\u0645\u0631"
    ],
    "name:und_x_variant":[
        "\u2018Izbat Mu\u015f\u0163af\u00e1 Nimr",
        "\u2018Izbat Mu\u1e63\u1e6daf\u00e1 Nimr"
    ],
    "wof:name":"`Izbat Mustafa Nimr",
    "wof:placetype":"locality"
},
  "geometry": {"coordinates":[31.76319,30.64042],"type":"Point"}
}