{
  "type": "Feature",
  "properties": {
    "gn:admin1_code":"21",
    "gn:asciiname":"`Izbat al Manawifah al Bahriyah",
    "gn:country_code":"EG",
    "gn:dem":5,
    "gn:feature_class":"P",
    "gn:feature_code":"PPL",
    "gn:name":"\u2018Izbat al Man\u0101wifah al Ba\u1e29r\u012byah",
    "gn:population":0,
    "gn:timezone":"Africa/Cairo",
    "iso:country":"EG",
    "name:ara_x_preferred":[
        "\u0639\u0632\u0628\u0629 \u0627\u0644\u0645\u0646\u0627\u0648\u0641\u0629 \u0627\u0644\u0628\u062d\u0631\u064a\u0629"
    ],
    "name:und_x_variant":[
        "\u2018Izbat al Man\u0101wfah al Ba\u1e29r\u012byah",
        "\u2018Izbat al Man\u0101wifah al Ba\u1e29r\u012byah"
    ],
    "wof:name":"`Izbat al Manawifah al Bahriyah",
    "wof:placetype":"locality"
},
  "geometry": {"coordinates":[31.11686,31.26758],"type":"Point"}
}