{
  "type": "Feature",
  "properties": {
    "gn:admin1_code":"14",
    "gn:asciiname":"`Izbat al Ghazali",
    "gn:country_code":"EG",
    "gn:dem":12,
    "gn:feature_class":"P",
    "gn:feature_code":"PPL",
    "gn:name":"\u2018Izbat al Ghaz\u0101l\u012b",
    "gn:population":0,
    "gn:timezone":"Africa/Cairo",
    "iso:country":"EG",
    "name:ara_x_preferred":[
        "\u0627\u0644\u063a\u0632\u0627\u0644\u064a"
    ],
    "name:und_x_variant":[
        "El-Ghaz\u00e2li",
        "\u2018Izbat al Ghaz\u0101l\u012b"
    ],
    "wof:name":"`Izbat al Ghazali",
    "wof:placetype":"locality"
},
  "geometry": {"coordinates":[31.81574,30.8149],"type":"Point"}
}