{
  "type": "Feature",
  "properties": {
    "gn:admin1_code":"14",
    "gn:asciiname":"`Izbat az Zajazijah",
    "gn:country_code":"EG",
    "gn:dem":11,
    "gn:feature_class":"P",
    "gn:feature_code":"PPL",
    "gn:name":"\u2018Izbat az Zaj\u0101zijah",
    "gn:population":0,
    "gn:timezone":"Africa/Cairo",
    "iso:country":"EG",
    "name:ara_x_preferred":[
        "\u0639\u0632\u0628\u0629 \u0627\u0644\u0632\u062c\u0627\u0632\u062c\u0629"
    ],
    "name:und_x_variant":[
        "\u2018Izbat az Zaj\u0101zijah",
        "\u2018Izbat az Zaj\u0101zjah"
    ],
    "wof:name":"`Izbat az Zajazijah",
    "wof:placetype":"locality"
},
  "geometry": {"coordinates":[31.62101,30.50724],"type":"Point"}
}