{
  "type": "Feature",
  "properties": {
    "gn:admin1_code":"24",
    "gn:asciiname":"Balasfurah",
    "gn:country_code":"EG",
    "gn:dem":67,
    "gn:feature_class":"P",
    "gn:feature_code":"PPL",
    "gn:name":"Bala\u015ff\u016brah",
    "gn:population":0,
    "gn:timezone":"Africa/Cairo",
    "iso:country":"EG",
    "name:und_x_variant":[
        "Balasf\u016bra",
        "Bala\u015ff\u016brah"
    ],
    "wof:name":"Balasfurah",
    "wof:placetype":"locality"
},
  "geometry": {"coordinates":[31.74202,26.52277],"type":"Point"}
}