{
  "type": "Feature",
  "properties": {
    "gn:admin1_code":"27",
    "gn:asciiname":"Qabr `Umayr",
    "gn:country_code":"EG",
    "gn:dem":20,
    "gn:feature_class":"P",
    "gn:feature_code":"PPL",
    "gn:name":"Qabr \u2018Umayr",
    "gn:population":0,
    "gn:timezone":"Africa/Cairo",
    "iso:country":"EG",
    "name:ara_x_preferred":[
        "\u0642\u0628\u0631 \u0639\u0645\u064a\u0631"
    ],
    "name:und_x_variant":[
        "Qabr \u2018Umayr",
        "Qabrameir"
    ],
    "wof:name":"Qabr `Umayr",
    "wof:placetype":"locality"
},
  "geometry": {"coordinates":[34.00906,31.18678],"type":"Point"}
}