{
  "type": "Feature",
  "properties": {
    "gn:admin1_code":"14",
    "gn:asciiname":"`Izbat `Abbas",
    "gn:country_code":"EG",
    "gn:dem":11,
    "gn:feature_class":"P",
    "gn:feature_code":"PPL",
    "gn:name":"\u2018Izbat \u2018Abb\u0101s",
    "gn:population":0,
    "gn:timezone":"Africa/Cairo",
    "iso:country":"EG",
    "name:ara_x_preferred":[
        "\u0639\u0632\u0628\u0629 \u0639\u0628\u0627\u0633"
    ],
    "name:und_x_variant":[
        "\u2018Izbat \u2018Abb\u0101s"
    ],
    "wof:name":"`Izbat `Abbas",
    "wof:placetype":"locality"
},
  "geometry": {"coordinates":[31.48154000000001,30.64768],"type":"Point"}
}