{
  "type": "Feature",
  "properties": {
    "gn:admin1_code":"08",
    "gn:asciiname":"Bamha",
    "gn:country_code":"EG",
    "gn:dem":23,
    "gn:feature_class":"P",
    "gn:feature_code":"PPL",
    "gn:name":"Bamh\u0101",
    "gn:population":0,
    "gn:timezone":"Africa/Cairo",
    "iso:country":"EG",
    "wof:name":"Bamha",
    "wof:placetype":"locality"
},
  "geometry": {"coordinates":[31.23333,29.58333],"type":"Point"}
}