{
  "type": "Feature",
  "properties": {
    "gn:admin1_code":"05",
    "gn:asciiname":"`Izbat as Sitt Zaynab al Qibaniyah",
    "gn:country_code":"EG",
    "gn:dem":9,
    "gn:feature_class":"P",
    "gn:feature_code":"PPL",
    "gn:name":"\u2018Izbat as Sitt Zaynab al Qib\u0101n\u012byah",
    "gn:population":0,
    "gn:timezone":"Africa/Cairo",
    "iso:country":"EG",
    "name:ara_x_preferred":[
        "\u0639\u0632\u0628\u0629 \u0627\u0644\u0633\u062a \u0632\u064a\u0646\u0628 \u0627\u0644\u0642\u0628\u0627\u0646\u064a\u0629"
    ],
    "name:und_x_variant":[
        "\u2018Izbat as Sitt Zaynab al Qib\u0101n\u012byah",
        "\u2018Izbat as-Sitt Zaynab al-Qabb\u0101niyyah"
    ],
    "wof:name":"`Izbat as Sitt Zaynab al Qibaniyah",
    "wof:placetype":"locality"
},
  "geometry": {"coordinates":[31.16372,31.06198],"type":"Point"}
}