{
  "type": "Feature",
  "properties": {
    "gn:admin1_code":"01",
    "gn:asciiname":"Bishla",
    "gn:country_code":"EG",
    "gn:dem":16,
    "gn:feature_class":"P",
    "gn:feature_code":"PPL",
    "gn:name":"Bishl\u0101",
    "gn:population":0,
    "gn:timezone":"Africa/Cairo",
    "iso:country":"EG",
    "name:ara_x_preferred":[
        "\u0628\u0634\u0644\u0627"
    ],
    "name:und_x_variant":[
        "Bishl\u0101"
    ],
    "wof:name":"Bishla",
    "wof:placetype":"locality"
},
  "geometry": {"coordinates":[31.26256,30.77597],"type":"Point"}
}