{
  "type": "Feature",
  "properties": {
    "gn:admin1_code":"23.0",
    "gn:asciiname":"Tafnis al Mata`inah",
    "gn:country_code":"EG",
    "gn:dem":85,
    "gn:feature_class":"P",
    "gn:feature_code":"PPL",
    "gn:name":"\u0162afn\u012bs al Ma\u0163\u0101\u2018inah",
    "gn:population":0,
    "gn:timezone":"Africa/Cairo",
    "iso:country":"EG",
    "name:und_x_variant":[
        "\u1e6cafnis el Mat\u00e2\u2018na",
        "\u0162afn\u012bs al Ma\u0163\u0101\u2018inah"
    ],
    "wof:name":"Tafnis al Mata`inah",
    "wof:placetype":"locality"
},
  "geometry": {"coordinates":[32.5269,25.43079],"type":"Point"}
}