{
  "type": "Feature",
  "properties": {
    "gn:admin1_code":"21",
    "gn:asciiname":"`Izbat al Bayda",
    "gn:country_code":"EG",
    "gn:dem":6,
    "gn:feature_class":"P",
    "gn:feature_code":"PPL",
    "gn:name":"\u2018Izbat al Bay\u1e11\u0101",
    "gn:population":0,
    "gn:timezone":"Africa/Cairo",
    "iso:country":"EG",
    "name:ara_x_preferred":[
        "\u0639\u0632\u0628\u0629 \u0627\u0644\u0628\u064a\u0636\u0627"
    ],
    "name:und_x_variant":[
        "\u2018Izbat al Bay\u1e11\u0101",
        "\u2018Izbat al Bay\u1e11\u0101\u2019",
        "\u2018Izbat al-Bay\u1e0d\u0101"
    ],
    "wof:name":"`Izbat al Bayda",
    "wof:placetype":"locality"
},
  "geometry": {"coordinates":[30.87129,31.06886],"type":"Point"}
}