{
  "type": "Feature",
  "properties": {
    "gn:admin1_code":"27",
    "gn:asciiname":"Misfaq",
    "gn:country_code":"EG",
    "gn:dem":5,
    "gn:feature_class":"P",
    "gn:feature_code":"PPL",
    "gn:name":"Mi\u015ffaq",
    "gn:population":0,
    "gn:timezone":"Africa/Cairo",
    "iso:country":"EG",
    "name:ara_x_preferred":[
        "\u0645\u0635\u0641\u0642"
    ],
    "name:und_x_variant":[
        "Mi\u015ffaq",
        "Ma\u015ffaq"
    ],
    "wof:name":"Misfaq",
    "wof:placetype":"locality"
},
  "geometry": {"coordinates":[33.16658,31.03493],"type":"Point"}
}