{
  "type": "Feature",
  "properties": {
    "gn:gn_country":"EG",
    "gn:gn_fcode":"PPLX",
    "gn:gn_pop":0,
    "iso:country":"EG",
    "name:ara_x_preferred":[
        "\u0634\u0628\u0631\u0627"
    ],
    "name:ara_x_variant":[
        "Shubr\u0101"
    ],
    "name:eng_x_colloquial":[
        "Shubra",
        "Shubraa"
    ],
    "name:eng_x_preferred":[
        "Shubr\u00e5"
    ],
    "name:eng_x_variant":[
        "Shoubra",
        "Shubr\u00e5"
    ],
    "name:unk_x_variant":[
        "\u0634\u0628\u0631\u0627",
        "Shoubra"
    ],
    "qs_pg:aaroncc":"EG",
    "qs_pg:gn_country":"EG",
    "qs_pg:gn_fcode":"PPLX",
    "qs_pg:gn_pop":0,
    "qs_pg:name":"\u0634\u0628\u0631\u0627",
    "qs_pg:name_adm0":"\u0645\u0635\u0631",
    "qs_pg:name_adm1":"\u0627\u0644\u0642\u0627\u0647\u0631\u0629",
    "qs_pg:photos":236,
    "qs_pg:photos_1k":48,
    "qs_pg:photos_9k":1,
    "qs_pg:photos_9r":4,
    "qs_pg:photos_all":236,
    "qs_pg:photos_sr":4,
    "qs_pg:pop_sr":0,
    "qs_pg:qs_pg_placetype":"neighbourhood",
    "qs_pg:qs_pg_placetype_gp":"Suburb",
    "qs_pg:woe_adm0":23424802,
    "woe:adm0_id":23424802,
    "woe:name_adm0":"\u0645\u0635\u0631",
    "woe:name_adm1":"\u0627\u0644\u0642\u0627\u0647\u0631\u0629",
    "woe:placetype":"Suburb",
    "wof:name":"\u0634\u0628\u0631\u0627",
    "wof:placetype":"neighbourhood"
},
  "geometry": {"coordinates":[31.23866,30.08505],"type":"Point"}
}