{
  "type": "Feature",
  "properties": {
    "gn:admin1_code":"03",
    "gn:asciiname":"Kafr Amlit",
    "gn:country_code":"EG",
    "gn:dem":8,
    "gn:feature_class":"P",
    "gn:feature_code":"PPL",
    "gn:name":"Kafr Aml\u012b\u0163",
    "gn:population":0,
    "gn:timezone":"Africa/Cairo",
    "iso:country":"EG",
    "name:ara_x_preferred":[
        "\u0643\u0641\u0631 \u0623\u0645\u0644\u064a\u0637"
    ],
    "name:und_x_variant":[
        "Kafr Aml\u012b\u0163",
        "Kafr Aml\u012b\u1e6d"
    ],
    "wof:name":"Kafr Amlit",
    "wof:placetype":"locality"
},
  "geometry": {"coordinates":[30.52597,31.17933],"type":"Point"}
}