{
  "type": "Feature",
  "properties": {
    "gn:admin1_code":"27",
    "gn:asciiname":"Um Qataf",
    "gn:country_code":"EG",
    "gn:dem":178,
    "gn:feature_class":"P",
    "gn:feature_code":"PPL",
    "gn:name":"Um Qataf",
    "gn:population":0,
    "gn:timezone":"Africa/Cairo",
    "iso:country":"EG",
    "name:und_x_variant":[
        "Umm Qa\u0163af"
    ],
    "wof:name":"Um Qataf",
    "wof:placetype":"locality"
},
  "geometry": {"coordinates":[34.25881,30.83343],"type":"Point"}
}