{
  "type": "Feature",
  "properties": {
    "gn:admin1_code":"03",
    "gn:asciiname":"Al Manshiyah al Kabirah",
    "gn:country_code":"EG",
    "gn:dem":4,
    "gn:feature_class":"P",
    "gn:feature_code":"PPL",
    "gn:name":"Al Mansh\u012byah al Kab\u012brah",
    "gn:population":0,
    "gn:timezone":"Africa/Cairo",
    "iso:country":"EG",
    "name:ara_x_preferred":[
        "\u0627\u0644\u0645\u0646\u0634\u064a\u0629 \u0627\u0644\u0643\u0628\u064a\u0631\u0629"
    ],
    "name:und_x_variant":[
        "Niz\u00e2ret el-Mansh\u00eeya",
        "Niz\u0327\u0101rat al Mansh\u012byah",
        "Al Mansh\u012byah al Kab\u012brah",
        "Al Manshiyyah al Kab\u012brah"
    ],
    "wof:name":"Al Manshiyah al Kabirah",
    "wof:placetype":"locality"
},
  "geometry": {"coordinates":[30.51989,31.10502],"type":"Point"}
}