{
  "type": "Feature",
  "properties": {
    "gn:admin1_code":"14",
    "gn:asciiname":"`Izbat ad Daraksah",
    "gn:country_code":"EG",
    "gn:dem":7,
    "gn:feature_class":"P",
    "gn:feature_code":"PPL",
    "gn:name":"\u2018Izbat ad Dar\u0101ksah",
    "gn:population":0,
    "gn:timezone":"Africa/Cairo",
    "iso:country":"EG",
    "name:ara_x_preferred":[
        "\u0639\u0632\u0628\u0629 \u0627\u0644\u062f\u0631\u0627\u0643\u0633\u0629"
    ],
    "name:und_x_variant":[
        "Kafr el Darr\u00e2ka",
        "Kafr el-Daraka",
        "Kafr ad Darr\u0101kah",
        "\u2018Izbat ad Dar\u0101ksah",
        "\u2018Izbat ad-Dar\u0101ksah"
    ],
    "wof:name":"`Izbat ad Daraksah",
    "wof:placetype":"locality"
},
  "geometry": {"coordinates":[31.89025,30.74481],"type":"Point"}
}