{
  "type": "Feature",
  "properties": {
    "gn:admin1_code":"08",
    "gn:asciiname":"Al Kawm al Akhdar",
    "gn:country_code":"EG",
    "gn:dem":21,
    "gn:feature_class":"P",
    "gn:feature_code":"PPL",
    "gn:name":"Al Kawm al Akh\u1e11ar",
    "gn:population":0,
    "gn:timezone":"Africa/Cairo",
    "iso:country":"EG",
    "name:und_x_variant":[
        "El-K\u00f4m el-Akh\u1e0dar",
        "K\u014dm el Akhdar",
        "Al Kawm al Akh\u1e11ar"
    ],
    "wof:name":"Al Kawm al Akhdar",
    "wof:placetype":"locality"
},
  "geometry": {"coordinates":[31.15892,29.98893],"type":"Point"}
}