{
  "type": "Feature",
  "properties": {
    "gn:admin1_code":"03",
    "gn:asciiname":"`Izbat Hawd Sittah",
    "gn:country_code":"EG",
    "gn:dem":-2,
    "gn:feature_class":"P",
    "gn:feature_code":"PPL",
    "gn:name":"\u2018Izbat \u1e28aw\u1e11 Sittah",
    "gn:population":0,
    "gn:timezone":"Africa/Cairo",
    "iso:country":"EG",
    "name:ara_x_preferred":[
        "\u0639\u0632\u0628\u0629 \u062d\u0648\u0636 \u0666"
    ],
    "name:und_x_variant":[
        "\u2018Izbat \u1e28aw\u1e11 Sittah"
    ],
    "wof:name":"`Izbat Hawd Sittah",
    "wof:placetype":"locality"
},
  "geometry": {"coordinates":[30.07800000000001,31.22377],"type":"Point"}
}