{
  "type": "Feature",
  "properties": {
    "gn:admin1_code":"01",
    "gn:asciiname":"Nisha",
    "gn:country_code":"EG",
    "gn:dem":10,
    "gn:feature_class":"P",
    "gn:feature_code":"PPL",
    "gn:name":"Nish\u0101",
    "gn:population":0,
    "gn:timezone":"Africa/Cairo",
    "iso:country":"EG",
    "name:ara_x_preferred":[
        "Nish\u0101"
    ],
    "name:ara_x_variant":[
        "\u0646\u0634\u0627"
    ],
    "name:ceb_x_preferred":[
        "Nisha"
    ],
    "name:deu_x_preferred":[
        "Nisha"
    ],
    "name:swe_x_preferred":[
        "Nisha"
    ],
    "wof:name":"Nisha",
    "wof:placetype":"locality"
},
  "geometry": {"coordinates":[31.29008,31.12589],"type":"Point"}
}