{
  "type": "Feature",
  "properties": {
    "gn:admin1_code":"05",
    "gn:asciiname":"At Talibiyah",
    "gn:country_code":"EG",
    "gn:dem":11,
    "gn:feature_class":"P",
    "gn:feature_code":"PPL",
    "gn:name":"A\u0163 \u0162\u0101lib\u012byah",
    "gn:population":0,
    "gn:timezone":"Africa/Cairo",
    "iso:country":"EG",
    "name:und_x_variant":[
        "El-\u1e6c\u00e2lb\u00eeya",
        "A\u0163 \u0162\u0101lib\u012byah"
    ],
    "wof:name":"At Talibiyah",
    "wof:placetype":"locality"
},
  "geometry": {"coordinates":[30.87136,30.75819000000001],"type":"Point"}
}