{
  "type": "Feature",
  "properties": {
    "gn:admin1_code":"14",
    "gn:asciiname":"`Izbat Siyam",
    "gn:country_code":"EG",
    "gn:dem":11,
    "gn:feature_class":"P",
    "gn:feature_code":"PPL",
    "gn:name":"\u2018Izbat \u015eiy\u0101m",
    "gn:population":0,
    "gn:timezone":"Africa/Cairo",
    "iso:country":"EG",
    "name:ara_x_preferred":[
        "\u0639\u0632\u0628\u0629 \u0635\u064a\u0627\u0645"
    ],
    "name:und_x_variant":[
        "\u2018Izbat \u015eiy\u0101m"
    ],
    "wof:name":"`Izbat Siyam",
    "wof:placetype":"locality"
},
  "geometry": {"coordinates":[31.51455,30.52942],"type":"Point"}
}