{
  "type": "Feature",
  "properties": {
    "gn:admin1_code":"21",
    "gn:asciiname":"Al Kawm al Ahmar al Bahri",
    "gn:country_code":"EG",
    "gn:dem":2,
    "gn:feature_class":"P",
    "gn:feature_code":"PPL",
    "gn:name":"Al Kawm al A\u1e29mar al Ba\u1e29r\u012b",
    "gn:population":0,
    "gn:timezone":"Africa/Cairo",
    "iso:country":"EG",
    "name:ara_x_preferred":[
        "\u0627\u0644\u0643\u0648\u0645 \u0627\u0644\u0623\u062d\u0645\u0631 \u0627\u0644\u0628\u062d\u0631\u064a"
    ],
    "name:und_x_variant":[
        "El-K\u00f4m el-A\u1e25mar el-Ba\u1e25ari",
        "Al Kawm al A\u1e29mar al Ba\u1e29r\u012b",
        "Al-Kawm al-A\u1e25mar al-Ba\u1e25r\u012b"
    ],
    "wof:name":"Al Kawm al Ahmar al Bahri",
    "wof:placetype":"locality"
},
  "geometry": {"coordinates":[31.0692,31.56665],"type":"Point"}
}