{
  "type": "Feature",
  "properties": {
    "gn:admin1_code":"09",
    "gn:asciiname":"Samalij",
    "gn:country_code":"EG",
    "gn:dem":15,
    "gn:feature_class":"P",
    "gn:feature_code":"PPL",
    "gn:name":"Sam\u0101l\u012bj",
    "gn:population":0,
    "gn:timezone":"Africa/Cairo",
    "iso:country":"EG",
    "name:und_x_variant":[
        "Sam\u00e2l\u00eeg",
        "Sam\u0101l\u012bj"
    ],
    "wof:name":"Samalij",
    "wof:placetype":"locality"
},
  "geometry": {"coordinates":[30.99869,30.64872],"type":"Point"}
}