{
  "type": "Feature",
  "properties": {
    "gn:admin1_code":"21",
    "gn:asciiname":"As Sayyar",
    "gn:cc2":"EG",
    "gn:country_code":"EG",
    "gn:dem":4,
    "gn:feature_class":"P",
    "gn:feature_code":"PPL",
    "gn:name":"As Sayy\u0101r",
    "gn:population":0,
    "gn:timezone":"Africa/Cairo",
    "iso:country":"EG",
    "name:und_x_variant":[
        "El-Sa\u00eey\u00e2r",
        "As Sayy\u0101r"
    ],
    "wof:name":"As Sayyar",
    "wof:placetype":"locality"
},
  "geometry": {"coordinates":[31.04167,31.59194],"type":"Point"}
}