{
  "type": "Feature",
  "properties": {
    "gn:admin1_code":"01",
    "gn:asciiname":"`Izbat Qa'im al `Abd",
    "gn:country_code":"EG",
    "gn:dem":6,
    "gn:feature_class":"P",
    "gn:feature_code":"PPL",
    "gn:name":"\u2018Izbat Q\u0101\u2019im al \u2018Abd",
    "gn:population":0,
    "gn:timezone":"Africa/Cairo",
    "iso:country":"EG",
    "name:ara_x_preferred":[
        "\u0639\u0632\u0628\u0629 \u0642\u0627\u0626\u0645 \u0627\u0644\u0639\u0628\u062f"
    ],
    "name:und_x_variant":[
        "\u2018Izbat Q\u0101\u2019im al \u2018Abd"
    ],
    "wof:name":"`Izbat Qa'im al `Abd",
    "wof:placetype":"locality"
},
  "geometry": {"coordinates":[31.44188,31.36317],"type":"Point"}
}