{
  "type": "Feature",
  "properties": {
    "gn:admin1_code":"16",
    "gn:asciiname":"Nag` el Hagg Zeidan",
    "gn:country_code":"EG",
    "gn:dem":122,
    "gn:feature_class":"P",
    "gn:feature_code":"PPL",
    "gn:name":"Nag\u2018 el Hagg Zeidan",
    "gn:population":0,
    "gn:timezone":"Africa/Cairo",
    "iso:country":"EG",
    "wof:name":"Nag` el Hagg Zeidan",
    "wof:placetype":"locality"
},
  "geometry": {"coordinates":[32.83333,24.86667000000001],"type":"Point"}
}