{
  "type": "Feature",
  "properties": {
    "gn:admin1_code":"01",
    "gn:asciiname":"`Ezbet Saiyid Hasan",
    "gn:country_code":"EG",
    "gn:dem":2,
    "gn:feature_class":"P",
    "gn:feature_code":"PPL",
    "gn:name":"\u2018Ezbet Saiyid \u1e24asan",
    "gn:population":0,
    "gn:timezone":"Africa/Cairo",
    "iso:country":"EG",
    "wof:name":"`Ezbet Saiyid Hasan",
    "wof:placetype":"locality"
},
  "geometry": {"coordinates":[31.76667,31.08333],"type":"Point"}
}