{
  "type": "Feature",
  "properties": {
    "gn:admin1_code":"21",
    "gn:asciiname":"`Izbat `Abbas `Ubaydi",
    "gn:country_code":"EG",
    "gn:dem":4,
    "gn:feature_class":"P",
    "gn:feature_code":"PPL",
    "gn:name":"\u2018Izbat \u2018Abb\u0101s \u2018Ubayd\u012b",
    "gn:population":0,
    "gn:timezone":"Africa/Cairo",
    "iso:country":"EG",
    "name:ara_x_preferred":[
        "\u0639\u0632\u0628\u0629 \u0639\u0628\u0627\u0633 \u0639\u0628\u064a\u062f\u064a"
    ],
    "name:und_x_variant":[
        "\u2018Izbat \u2018Abb\u0101s \u2018Ubayd\u012b"
    ],
    "wof:name":"`Izbat `Abbas `Ubaydi",
    "wof:placetype":"locality"
},
  "geometry": {"coordinates":[30.80303,31.26621],"type":"Point"}
}