{
  "type": "Feature",
  "properties": {
    "gn:country":"EG",
    "gn:fcode":"PPL",
    "gn:pop":63793,
    "iso:country":"EG",
    "name:ara_x_preferred":[
        "\u0627\u0644\u0641\u0634\u0646"
    ],
    "name:dut_x_preferred":[
        "Al Fashn"
    ],
    "name:eng_x_preferred":[
        "Al Fashn"
    ],
    "name:est_x_preferred":[
        "Al-Fashn"
    ],
    "name:per_x_preferred":[
        "\u0627\u0644\u0641\u0634\u0646"
    ],
    "name:rus_x_preferred":[
        "\u042d\u043b\u044c-\u0424\u0430\u0448\u043d"
    ],
    "name:swe_x_preferred":[
        "Al Fashn"
    ],
    "name:unk_x_variant":[
        "El Fashn"
    ],
    "qs:name":"Al Fashn",
    "qs:photos_9r":0,
    "qs:photos_sr":0,
    "qs:pop_sr":"8",
    "wd:wordcount":22,
    "wof:name":"Al Fashn",
    "wof:placetype":"locality",
    "wof:population":63793
},
  "geometry": {"coordinates":[30.89948,28.82431],"type":"Point"}
}