{
  "type": "Feature",
  "properties": {
    "gn:admin1_code":"04",
    "gn:asciiname":"`Izbat Awlad Muhammad al Kashif",
    "gn:country_code":"EG",
    "gn:dem":15,
    "gn:feature_class":"P",
    "gn:feature_code":"PPL",
    "gn:name":"\u2018Izbat Awl\u0101d Mu\u1e29ammad al K\u0101shif",
    "gn:population":0,
    "gn:timezone":"Africa/Cairo",
    "iso:country":"EG",
    "wof:name":"`Izbat Awlad Muhammad al Kashif",
    "wof:placetype":"locality"
},
  "geometry": {"coordinates":[30.81626,29.19112],"type":"Point"}
}