{
  "type": "Feature",
  "properties": {
    "gn:admin1_code":"21",
    "gn:asciiname":"`Izbat ash Sharnubi",
    "gn:country_code":"EG",
    "gn:dem":2,
    "gn:feature_class":"P",
    "gn:feature_code":"PPL",
    "gn:name":"\u2018Izbat ash Sharn\u016bb\u012b",
    "gn:population":0,
    "gn:timezone":"Africa/Cairo",
    "iso:country":"EG",
    "name:ara_x_preferred":[
        "\u0639\u0632\u0628\u0629 \u0627\u0644\u0634\u0631\u0646\u0648\u0628\u064a"
    ],
    "name:und_x_variant":[
        "\u2018Izbat ash Sharn\u016bb\u012b"
    ],
    "wof:name":"`Izbat ash Sharnubi",
    "wof:placetype":"locality"
},
  "geometry": {"coordinates":[30.68617,31.3201],"type":"Point"}
}