{
  "type": "Feature",
  "properties": {
    "gn:admin1_code":"18",
    "gn:asciiname":"Dayr Barawah",
    "gn:country_code":"EG",
    "gn:dem":31,
    "gn:feature_class":"P",
    "gn:feature_code":"PPL",
    "gn:name":"Dayr Bar\u0101wah",
    "gn:population":0,
    "gn:timezone":"Africa/Cairo",
    "iso:country":"EG",
    "name:und_x_variant":[
        "Deir Barawa",
        "Dayr Bar\u0101wah"
    ],
    "wof:name":"Dayr Barawah",
    "wof:placetype":"locality"
},
  "geometry": {"coordinates":[30.90938,29.01929],"type":"Point"}
}