{
  "type": "Feature",
  "properties": {
    "gn:admin1_code":"13",
    "gn:asciiname":"`Ezbet Galal Pasha",
    "gn:country_code":"EG",
    "gn:dem":49,
    "gn:feature_class":"P",
    "gn:feature_code":"PPL",
    "gn:name":"\u2018Ezbet Gal\u00e2l Pasha",
    "gn:population":0,
    "gn:timezone":"Africa/Cairo",
    "iso:country":"EG",
    "wof:name":"`Ezbet Galal Pasha",
    "wof:placetype":"locality"
},
  "geometry": {"coordinates":[30.88333,27.68333],"type":"Point"}
}