{
  "type": "Feature",
  "properties": {
    "gn:admin1_code":"14",
    "gn:asciiname":"Hanut",
    "gn:country_code":"EG",
    "gn:dem":6,
    "gn:feature_class":"P",
    "gn:feature_code":"PPL",
    "gn:name":"\u1e28\u0101n\u016bt",
    "gn:population":0,
    "gn:timezone":"Africa/Cairo",
    "iso:country":"EG",
    "name:ara_x_preferred":[
        "\u1e28\u0101n\u016bt"
    ],
    "name:ara_x_variant":[
        "\u062d\u0627\u0646\u0648\u062a"
    ],
    "wof:name":"Hanut",
    "wof:placetype":"locality"
},
  "geometry": {"coordinates":[31.64306,30.88178],"type":"Point"}
}