{
  "type": "Feature",
  "properties": {
    "gn:admin1_code":"24",
    "gn:asciiname":"As Sufayhah",
    "gn:country_code":"EG",
    "gn:dem":63,
    "gn:feature_class":"P",
    "gn:feature_code":"PPL",
    "gn:name":"A\u015f \u015eufay\u1e29ah",
    "gn:population":0,
    "gn:timezone":"Africa/Cairo",
    "iso:country":"EG",
    "name:und_x_variant":[
        "El-Shiffeiha",
        "A\u015f \u015eufay\u1e29ah"
    ],
    "wof:name":"As Sufayhah",
    "wof:placetype":"locality"
},
  "geometry": {"coordinates":[31.40644,26.79179],"type":"Point"}
}