{
  "type": "Feature",
  "properties": {
    "iso:country":"EG",
    "qs:gn_pop":0,
    "qs:name":"El Ibr\u0101h\u012bm\u012bya",
    "qs:name_adm0":"\u0645\u0635\u0631",
    "qs:name_adm1":"\u0627\u0644\u0627\u0633\u0643\u0646\u062f\u0631\u064a\u0629",
    "qs:photos":145,
    "qs:photos_1k":29,
    "qs:photos_9k":1,
    "qs:photos_9r":3,
    "qs:photos_all":145,
    "qs:photos_sr":3,
    "qs:placetype":"Suburb",
    "qs:pop_sr":"0",
    "qs:woe_adm0":23424802,
    "wof:name":"El Ibr\u0101h\u012bm\u012bya",
    "wof:placetype":"neighbourhood"
},
  "geometry": {"coordinates":[29.939804,31.222197],"type":"Point"}
}