{
  "type": "Feature",
  "properties": {
    "iso:country":"EG",
    "name:ara_x_preferred":[
        "\u062f\u064a\u0631\u0628 \u0646\u062c\u0645"
    ],
    "name:unk_x_variant":[
        "Diarb Negm"
    ],
    "qs:gn_country":"EG",
    "qs:gn_fcode":"PPL",
    "qs:gn_pop":51841,
    "qs:name":"\u062f\u064a\u0631\u0628 \u0646\u062c\u0645",
    "qs:name_adm0":"\u0645\u0635\u0631",
    "qs:name_adm1":"\u0627\u0644\u0634\u0631\u0642\u064a\u0629",
    "qs:photos":0,
    "qs:photos_1k":0,
    "qs:photos_9k":0,
    "qs:photos_9r":0,
    "qs:photos_all":0,
    "qs:photos_sr":0,
    "qs:placetype":"Town",
    "qs:pop_sr":"8",
    "qs:woe_adm0":23424802,
    "wof:name":"\u062f\u064a\u0631\u0628 \u0646\u062c\u0645",
    "wof:placetype":"locality",
    "wof:population":51841
},
  "geometry": {"coordinates":[31.43925,30.75422],"type":"Point"}
}