{
  "type": "Feature",
  "properties": {
    "gn:admin1_code":"21",
    "gn:asciiname":"Al Hilmiyah",
    "gn:country_code":"EG",
    "gn:dem":3,
    "gn:feature_class":"P",
    "gn:feature_code":"PPL",
    "gn:name":"Al \u1e28ilm\u012byah",
    "gn:population":0,
    "gn:timezone":"Africa/Cairo",
    "iso:country":"EG",
    "name:ara_x_preferred":[
        "\u0627\u0644\u062d\u0644\u0645\u064a\u0629"
    ],
    "name:und_x_variant":[
        "Al \u1e28ilm\u012byah"
    ],
    "wof:name":"Al Hilmiyah",
    "wof:placetype":"locality"
},
  "geometry": {"coordinates":[31.14173,31.47237],"type":"Point"}
}