{
  "type": "Feature",
  "properties": {
    "gn:admin1_code":"14",
    "gn:asciiname":"Mit Rikab",
    "gn:country_code":"EG",
    "gn:dem":11,
    "gn:feature_class":"P",
    "gn:feature_code":"PPL",
    "gn:name":"M\u012bt Rik\u0101b",
    "gn:population":0,
    "gn:timezone":"Africa/Cairo",
    "iso:country":"EG",
    "name:ara_x_preferred":[
        "M\u012bt Rik\u0101b"
    ],
    "name:ara_x_variant":[
        "\u0645\u064a\u062a \u0631\u0643\u0627\u0628"
    ],
    "name:und_x_variant":[
        "M\u00eet Rik\u00e2b and Kafr Sul\u00eem\u00e2n el-Qam\u1e25\u00e2wi",
        "M\u012bt Rik\u0101b wa Kafr Sulaym\u0101n al Qam\u1e29\u0101w\u012b",
        "M\u00eet Rik\u00e2b wa Kafr Sul\u00eem\u00e2n el-Qam\u1e25\u00e2wi"
    ],
    "wof:name":"Mit Rikab",
    "wof:placetype":"locality"
},
  "geometry": {"coordinates":[31.56671,30.5468],"type":"Point"}
}