{
  "type": "Feature",
  "properties": {
    "gn:admin1_code":"21",
    "gn:asciiname":"`Izbat al Khawalid al Bahriyah",
    "gn:country_code":"EG",
    "gn:dem":1,
    "gn:feature_class":"P",
    "gn:feature_code":"PPL",
    "gn:name":"\u2018Izbat al Khaw\u0101lid al Ba\u1e29r\u012byah",
    "gn:population":0,
    "gn:timezone":"Africa/Cairo",
    "iso:country":"EG",
    "name:ara_x_preferred":[
        "\u0639\u0632\u0628\u0629 \u0627\u0644\u062e\u0648\u0627\u0644\u062f \u0627\u0644\u0628\u062d\u0631\u064a\u0629"
    ],
    "name:und_x_variant":[
        "\u2018Izbat al Khaw\u0101lid al Ba\u1e29r\u012byah",
        "\u2018Izbat al Khaw\u0101lid al Ba\u1e29ar\u012byah"
    ],
    "wof:name":"`Izbat al Khawalid al Bahriyah",
    "wof:placetype":"locality"
},
  "geometry": {"coordinates":[30.85818,31.35294],"type":"Point"}
}