{
  "type": "Feature",
  "properties": {
    "gn:admin1_code":"21",
    "gn:asciiname":"`Izbat al Barrajah",
    "gn:country_code":"EG",
    "gn:dem":3,
    "gn:feature_class":"P",
    "gn:feature_code":"PPL",
    "gn:name":"\u2018Izbat al Barr\u0101jah",
    "gn:population":0,
    "gn:timezone":"Africa/Cairo",
    "iso:country":"EG",
    "name:ara_x_preferred":[
        "\u0639\u0632\u0628\u0629 \u0627\u0644\u0628\u0631\u0627\u062c\u0629"
    ],
    "name:und_x_variant":[
        "\u2018Izbat al Barr\u0101jah"
    ],
    "wof:name":"`Izbat al Barrajah",
    "wof:placetype":"locality"
},
  "geometry": {"coordinates":[30.45846,31.34811],"type":"Point"}
}