{
  "type": "Feature",
  "properties": {
    "gn:admin1_code":"21",
    "gn:asciiname":"`Izbat Fathiyah",
    "gn:country_code":"EG",
    "gn:dem":7,
    "gn:feature_class":"P",
    "gn:feature_code":"PPL",
    "gn:name":"\u2018Izbat Fat\u1e29\u012byah",
    "gn:population":0,
    "gn:timezone":"Africa/Cairo",
    "iso:country":"EG",
    "name:ara_x_preferred":[
        "\u0639\u0632\u0628\u0629 \u0641\u062a\u062d\u064a\u0629"
    ],
    "name:und_x_variant":[
        "\u2018Izbat Fat\u1e29\u012byah",
        "\u2018Izbat Fat\u1e25iyyah",
        "\u2018Izbat al Fat\u1e29iyyah"
    ],
    "wof:name":"`Izbat Fathiyah",
    "wof:placetype":"locality"
},
  "geometry": {"coordinates":[31.15283,31.24237],"type":"Point"}
}