{
  "type": "Feature",
  "properties": {
    "gn:admin1_code":"24",
    "gn:asciiname":"Banja",
    "gn:country_code":"EG",
    "gn:dem":65,
    "gn:feature_class":"P",
    "gn:feature_code":"PPL",
    "gn:name":"Banj\u0101",
    "gn:population":0,
    "gn:timezone":"Africa/Cairo",
    "iso:country":"EG",
    "name:bos_x_preferred":[
        "Banja"
    ],
    "name:ceb_x_preferred":[
        "Banja"
    ],
    "name:fra_x_preferred":[
        "Banja"
    ],
    "name:hrv_x_preferred":[
        "Banja"
    ],
    "name:hun_x_preferred":[
        "Banja"
    ],
    "name:ita_x_preferred":[
        "Banja"
    ],
    "name:nld_x_preferred":[
        "Banja"
    ],
    "name:por_x_preferred":[
        "Banja"
    ],
    "name:slv_x_preferred":[
        "Banja"
    ],
    "name:srp_x_preferred":[
        "\u0411\u0430\u045a\u0430"
    ],
    "name:swe_x_preferred":[
        "Banja"
    ],
    "name:und_x_variant":[
        "Banga",
        "Banjah",
        "Banj\u0101"
    ],
    "wof:name":"Banja",
    "wof:placetype":"locality"
},
  "geometry": {"coordinates":[31.47881,26.8007],"type":"Point"}
}