{
  "type": "Feature",
  "properties": {
    "gn:admin1_code":"18",
    "gn:asciiname":"Biba",
    "gn:country_code":"EG",
    "gn:dem":37,
    "gn:feature_class":"P",
    "gn:feature_code":"PPL",
    "gn:name":"Bib\u0101",
    "gn:population":0,
    "gn:timezone":"Africa/Cairo",
    "iso:country":"EG",
    "name:und_x_variant":[
        "Beba",
        "Bib\u0101"
    ],
    "wof:name":"Biba",
    "wof:placetype":"locality"
},
  "geometry": {"coordinates":[30.98352,28.9233],"type":"Point"}
}