{
  "type": "Feature",
  "properties": {
    "gn:admin1_code":"18",
    "gn:asciiname":"Biba",
    "gn:country_code":"EG",
    "gn:dem":37,
    "gn:feature_class":"P",
    "gn:feature_code":"PPL",
    "gn:name":"Bib\u0101",
    "gn:population":0,
    "gn:timezone":"Africa/Cairo",
    "iso:country":"EG",
    "name:ara_x_preferred":[
        "\u0628\u0628\u0627"
    ],
    "name:azb_x_preferred":[
        "\u0628\u0628\u0627"
    ],
    "name:fas_x_preferred":[
        "\u0628\u0628\u0627"
    ],
    "name:pol_x_preferred":[
        "Biba"
    ],
    "name:rus_x_preferred":[
        "\u0411\u0438\u0431\u0430"
    ],
    "name:und_x_variant":[
        "Beba",
        "Bib\u0101"
    ],
    "wof:name":"Biba",
    "wof:placetype":"locality"
},
  "geometry": {"coordinates":[30.98352,28.9233],"type":"Point"}
}