{
  "type": "Feature",
  "properties": {
    "gn:admin1_code":"03",
    "gn:asciiname":"Qaryat al Andalus",
    "gn:country_code":"EG",
    "gn:dem":-4,
    "gn:feature_class":"P",
    "gn:feature_code":"PPL",
    "gn:name":"Qaryat al Andalus",
    "gn:population":0,
    "gn:timezone":"Africa/Cairo",
    "iso:country":"EG",
    "name:ara_x_preferred":[
        "\u0642\u0631\u064a\u0648 \u0627\u0644\u0627\u0646\u062f\u0644\u0633"
    ],
    "wof:name":"Qaryat al Andalus",
    "wof:placetype":"locality"
},
  "geometry": {"coordinates":[29.99002,31.00376],"type":"Point"}
}