{
  "type": "Feature",
  "properties": {
    "gn:admin1_code":"10",
    "gn:asciiname":"Ad Da'udiyah",
    "gn:country_code":"EG",
    "gn:dem":38,
    "gn:feature_class":"P",
    "gn:feature_code":"PPL",
    "gn:name":"Ad D\u0101\u2019\u016bd\u012byah",
    "gn:population":0,
    "gn:timezone":"Africa/Cairo",
    "iso:country":"EG",
    "name:und_x_variant":[
        "El D\u00e2w\u00fbd\u00eeya",
        "Ad D\u0101\u2019\u016bd\u012byah"
    ],
    "wof:name":"Ad Da'udiyah",
    "wof:placetype":"locality"
},
  "geometry": {"coordinates":[30.76667,28.15],"type":"Point"}
}