{
  "type": "Feature",
  "properties": {
    "gn:admin1_code":"03",
    "gn:asciiname":"`Izbat Arba`ah/Sab`ah",
    "gn:country_code":"EG",
    "gn:dem":-2,
    "gn:feature_class":"P",
    "gn:feature_code":"PPL",
    "gn:name":"\u2018Izbat Arba\u2018ah/Sab\u2018ah",
    "gn:population":0,
    "gn:timezone":"Africa/Cairo",
    "iso:country":"EG",
    "name:ara_x_preferred":[
        "\u0639\u0632\u0628\u0629 \u0664/\u0667"
    ],
    "name:und_x_variant":[
        "\u2018Izbat Arba\u2018ah/Sab\u2018ah"
    ],
    "wof:name":"`Izbat Arba`ah/Sab`ah",
    "wof:placetype":"locality"
},
  "geometry": {"coordinates":[30.02276,31.14479],"type":"Point"}
}