{
  "type": "Feature",
  "properties": {
    "gn:admin1_code":"23",
    "gn:asciiname":"Naj` al Fakhurah",
    "gn:country_code":"EG",
    "gn:dem":85,
    "gn:feature_class":"P",
    "gn:feature_code":"PPL",
    "gn:name":"Naj\u2018 al F\u0101kh\u016brah",
    "gn:population":0,
    "gn:timezone":"Africa/Cairo",
    "iso:country":"EG",
    "wof:name":"Naj` al Fakhurah",
    "wof:placetype":"locality"
},
  "geometry": {"coordinates":[32.59048,25.27836],"type":"Point"}
}