{
  "type": "Feature",
  "properties": {
    "gn:admin1_code":"14",
    "gn:asciiname":"Faqus al Balad",
    "gn:country_code":"EG",
    "gn:dem":12,
    "gn:feature_class":"P",
    "gn:feature_code":"PPL",
    "gn:name":"F\u0101q\u016bs al Balad",
    "gn:population":0,
    "gn:timezone":"Africa/Cairo",
    "iso:country":"EG",
    "name:ara_x_preferred":[
        "\u0641\u0627\u0642\u0648\u0633 \u0627\u0644\u0628\u0644\u062f"
    ],
    "name:und_x_variant":[
        "F\u00e2qus el-Balad",
        "F\u0101q\u016bs al Balad"
    ],
    "wof:name":"Faqus al Balad",
    "wof:placetype":"locality"
},
  "geometry": {"coordinates":[31.80122,30.72047],"type":"Point"}
}