{
  "type": "Feature",
  "properties": {
    "gn:admin1_code":"03",
    "gn:asciiname":"Jarjalah",
    "gn:country_code":"EG",
    "gn:dem":3,
    "gn:feature_class":"P",
    "gn:feature_code":"PPL",
    "gn:name":"Jarjalah",
    "gn:population":0,
    "gn:timezone":"Africa/Cairo",
    "iso:country":"EG",
    "name:ara_x_preferred":[
        "\u062c\u0631\u062c\u0644\u0629"
    ],
    "name:und_x_variant":[
        "Jarajullah"
    ],
    "wof:name":"Jarjalah",
    "wof:placetype":"locality"
},
  "geometry": {"coordinates":[30.21321,31.12924000000001],"type":"Point"}
}