{
  "type": "Feature",
  "properties": {
    "gn:admin1_code":"21",
    "gn:asciiname":"`Arab al Hanafi",
    "gn:country_code":"EG",
    "gn:dem":0,
    "gn:feature_class":"P",
    "gn:feature_code":"PPLL",
    "gn:name":"\u2018Arab al \u1e28anaf\u012b",
    "gn:population":0,
    "gn:timezone":"Africa/Cairo",
    "iso:country":"EG",
    "name:und_x_variant":[
        "\u2018Arab el-\u1e24anafi",
        "\u2018Arab al \u1e28anaf\u012b"
    ],
    "wof:name":"`Arab al Hanafi",
    "wof:placetype":"locality"
},
  "geometry": {"coordinates":[30.84167,31.5375],"type":"Point"}
}