{
  "type": "Feature",
  "properties": {
    "gn:admin1_code":"21",
    "gn:asciiname":"`Izbat ash Shadhli",
    "gn:country_code":"EG",
    "gn:dem":6,
    "gn:feature_class":"P",
    "gn:feature_code":"PPL",
    "gn:name":"\u2018Izbat ash Sh\u0101dhl\u012b",
    "gn:population":0,
    "gn:timezone":"Africa/Cairo",
    "iso:country":"EG",
    "name:ara_x_preferred":[
        "\u0639\u0632\u0628\u0629 \u0627\u0644\u0634\u0627\u0630\u0644\u064a"
    ],
    "name:ara_x_variant":[
        "\u0623\u0628\u0648 \u062d\u0645\u064a\u062f"
    ],
    "name:und_x_variant":[
        "\u2018Izbat ash Sh\u0101dhl\u012b",
        "Ab\u016b \u1e28imayd"
    ],
    "wof:name":"`Izbat ash Shadhli",
    "wof:placetype":"locality"
},
  "geometry": {"coordinates":[30.78104,31.03497],"type":"Point"}
}