{
  "type": "Feature",
  "properties": {
    "gn:admin1_code":"10",
    "gn:asciiname":"Kafr al Madawir",
    "gn:cc2":"EG",
    "gn:country_code":"EG",
    "gn:dem":31,
    "gn:feature_class":"P",
    "gn:feature_code":"PPL",
    "gn:name":"Kafr al Mad\u0101wir",
    "gn:population":0,
    "gn:timezone":"Africa/Cairo",
    "iso:country":"EG",
    "name:und_x_variant":[
        "Kafr el Mad\u00e2wir",
        "Kafr al Mad\u0101wir"
    ],
    "wof:name":"Kafr al Madawir",
    "wof:placetype":"locality"
},
  "geometry": {"coordinates":[30.81667,28.66667],"type":"Point"}
}