{
  "type": "Feature",
  "properties": {
    "gn:admin1_code":"03",
    "gn:asciiname":"Kafr Ghunaym al Bahriyah",
    "gn:country_code":"EG",
    "gn:dem":11,
    "gn:feature_class":"P",
    "gn:feature_code":"PPL",
    "gn:name":"Kafr Ghunaym al Ba\u1e29r\u012byah",
    "gn:population":0,
    "gn:timezone":"Africa/Cairo",
    "iso:country":"EG",
    "name:ara_x_preferred":[
        "\u0643\u0641\u0631 \u063a\u0646\u064a\u0645 \u0627\u0644\u0628\u062d\u0631\u064a\u0629"
    ],
    "name:und_x_variant":[
        "Kafr Ghuneim",
        "Kafr Ghunaym",
        "Kafr Ghunaym al Ba\u1e29r\u012byah",
        "Kafr Ghunaym al Ba\u1e25ariyyah"
    ],
    "wof:name":"Kafr Ghunaym al Bahriyah",
    "wof:placetype":"locality"
},
  "geometry": {"coordinates":[30.61434,31.14111],"type":"Point"}
}