{
  "type": "Feature",
  "properties": {
    "gn:admin1_code":"21",
    "gn:asciiname":"`Izbat Badr ad Din",
    "gn:country_code":"EG",
    "gn:dem":5,
    "gn:feature_class":"P",
    "gn:feature_code":"PPL",
    "gn:name":"\u2018Izbat Badr ad D\u012bn",
    "gn:population":0,
    "gn:timezone":"Africa/Cairo",
    "iso:country":"EG",
    "name:ara_x_preferred":[
        "\u0639\u0632\u0628\u0629 \u0628\u062f\u0631 \u0627\u0644\u062f\u064a\u0646"
    ],
    "name:und_x_variant":[
        "\u2018Izbat Badr ad D\u012bn"
    ],
    "wof:name":"`Izbat Badr ad Din",
    "wof:placetype":"locality"
},
  "geometry": {"coordinates":[30.77474,31.13426],"type":"Point"}
}