{
  "type": "Feature",
  "properties": {
    "gn:admin1_code":"09",
    "gn:asciiname":"`Izbat `Abd al Hafiz `Amru",
    "gn:country_code":"EG",
    "gn:dem":13,
    "gn:feature_class":"P",
    "gn:feature_code":"PPL",
    "gn:name":"\u2018Izbat \u2018Abd al \u1e28\u0101fiz\u0327 \u2018Amr\u016b",
    "gn:population":0,
    "gn:timezone":"Africa/Cairo",
    "iso:country":"EG",
    "name:ara_x_preferred":[
        "\u0639\u0632\u0628\u0629 \u0639\u0628\u062f \u0627\u0644\u062d\u0627\u0641\u0638 \u0639\u0645\u0631\u0648"
    ],
    "name:und_x_variant":[
        "\u2018Izbat \u2018Abd al \u1e28\u0101fiz\u0327 \u2018Amr\u016b",
        "\u2018Izbat \u2018Abd al \u1e24\u0101fi\u1e93 \u2018Amr"
    ],
    "wof:name":"`Izbat `Abd al Hafiz `Amru",
    "wof:placetype":"locality"
},
  "geometry": {"coordinates":[30.94483,30.32015],"type":"Point"}
}