{
  "type": "Feature",
  "properties": {
    "gn:admin1_code":"14",
    "gn:asciiname":"`Izbat al Malakiyin Qibliyah",
    "gn:country_code":"EG",
    "gn:dem":9,
    "gn:feature_class":"P",
    "gn:feature_code":"PPL",
    "gn:name":"\u2018Izbat al Malak\u012by\u012bn Qibliyah",
    "gn:population":0,
    "gn:timezone":"Africa/Cairo",
    "iso:country":"EG",
    "name:und_x_variant":[
        "Al Malik\u012by\u012bn al Qibl\u012byah",
        "Malk\u00eey\u00een el Sharq",
        "El-Malakiy\u00een el-Qibl\u00eeya",
        "\u2018Izbat al Malak\u012by\u012bn Qibliyah"
    ],
    "wof:name":"`Izbat al Malakiyin Qibliyah",
    "wof:placetype":"locality"
},
  "geometry": {"coordinates":[31.91342,30.80427],"type":"Point"}
}