{
  "type": "Feature",
  "properties": {
    "gn:admin1_code":"12.0",
    "gn:asciiname":"Tisfa",
    "gn:country_code":"EG",
    "gn:dem":18,
    "gn:feature_class":"P",
    "gn:feature_code":"PPL",
    "gn:name":"\u0162i\u015ff\u0101",
    "gn:population":0,
    "gn:timezone":"Africa/Cairo",
    "iso:country":"EG",
    "name:ara_x_preferred":[
        "\u0162i\u015ff\u0101"
    ],
    "name:ara_x_variant":[
        "\u062a\u0635\u0641\u0627"
    ],
    "wof:name":"Tisfa",
    "wof:placetype":"locality"
},
  "geometry": {"coordinates":[31.28359,30.56579],"type":"Point"}
}