{
  "type": "Feature",
  "properties": {
    "gn:admin1_code":"04",
    "gn:asciiname":"`Izbat Isma`il Badr",
    "gn:country_code":"EG",
    "gn:dem":13,
    "gn:feature_class":"P",
    "gn:feature_code":"PPL",
    "gn:name":"\u2018Izbat Ism\u0101\u2018\u012bl Badr",
    "gn:population":0,
    "gn:timezone":"Africa/Cairo",
    "iso:country":"EG",
    "wof:name":"`Izbat Isma`il Badr",
    "wof:placetype":"locality"
},
  "geometry": {"coordinates":[30.97228,29.54761],"type":"Point"}
}