{
  "type": "Feature",
  "properties": {
    "gn:admin1_code":"01",
    "gn:asciiname":"`Izbat al Barshah",
    "gn:country_code":"EG",
    "gn:dem":5,
    "gn:feature_class":"P",
    "gn:feature_code":"PPL",
    "gn:name":"\u2018Izbat al Barshah",
    "gn:population":0,
    "gn:timezone":"Africa/Cairo",
    "iso:country":"EG",
    "name:ara_x_preferred":[
        "\u0639\u0632\u0628\u0629 \u0627\u0644\u0628\u0631\u0634\u0629"
    ],
    "name:und_x_variant":[
        "\u2018Izbat al Barshah"
    ],
    "wof:name":"`Izbat al Barshah",
    "wof:placetype":"locality"
},
  "geometry": {"coordinates":[31.53339,31.25401],"type":"Point"}
}