{
  "type": "Feature",
  "properties": {
    "gn:admin1_code":"09",
    "gn:asciiname":"Kafr Sulayman Salamah",
    "gn:country_code":"EG",
    "gn:dem":14,
    "gn:feature_class":"P",
    "gn:feature_code":"PPL",
    "gn:name":"Kafr Sulaym\u0101n Sal\u0101mah",
    "gn:population":0,
    "gn:timezone":"Africa/Cairo",
    "iso:country":"EG",
    "name:ara_x_preferred":[
        "\u0643\u0641\u0631 \u0633\u0644\u064a\u0645\u0627\u0646 \u0633\u0644\u0627\u0645\u0629"
    ],
    "name:und_x_variant":[
        "\u2018Izbat Tit\u0101",
        "Kafr Sul\u00eem\u00e2n Sal\u00e2ma",
        "Kafr Sulaym\u0101n Sal\u0101mah"
    ],
    "wof:name":"Kafr Sulayman Salamah",
    "wof:placetype":"locality"
},
  "geometry": {"coordinates":[30.94583,30.49738],"type":"Point"}
}