{
  "type": "Feature",
  "properties": {
    "gn:admin1_code":"05",
    "gn:asciiname":"`Izbat Riyad Rizq Allah",
    "gn:country_code":"EG",
    "gn:dem":6,
    "gn:feature_class":"P",
    "gn:feature_code":"PPL",
    "gn:name":"\u2018Izbat Riy\u0101\u1e11 Rizq All\u0101h",
    "gn:population":0,
    "gn:timezone":"Africa/Cairo",
    "iso:country":"EG",
    "name:ara_x_preferred":[
        "\u0639\u0632\u0628\u0629 \u0631\u064a\u0627\u0636 \u0631\u0632\u0642 \u0627\u0644\u0644\u0647"
    ],
    "name:und_x_variant":[
        "\u2018Izbat Riy\u0101\u1e11 Rizq All\u0101h",
        "\u2018Izbat Riy\u0101\u1e0d Rizq All\u0101h"
    ],
    "wof:name":"`Izbat Riyad Rizq Allah",
    "wof:placetype":"locality"
},
  "geometry": {"coordinates":[31.19711,31.00799],"type":"Point"}
}