{
  "type": "Feature",
  "properties": {
    "gn:admin1_code":"21",
    "gn:asciiname":"Diminkah",
    "gn:country_code":"EG",
    "gn:dem":6,
    "gn:feature_class":"P",
    "gn:feature_code":"PPL",
    "gn:name":"Dim\u012bnkah",
    "gn:population":0,
    "gn:timezone":"Africa/Cairo",
    "iso:country":"EG",
    "name:ara_x_preferred":[
        "\u062f\u0645\u064a\u0646\u0643\u0629"
    ],
    "name:und_x_variant":[
        "Dim\u00eenka",
        "Dim\u012bnkah"
    ],
    "wof:name":"Diminkah",
    "wof:placetype":"locality"
},
  "geometry": {"coordinates":[30.70371,31.09021],"type":"Point"}
}