{
  "type": "Feature",
  "properties": {
    "gn:admin1_code":"04",
    "gn:asciiname":"`Izbat `Abd as Salam Karim",
    "gn:country_code":"EG",
    "gn:dem":-37,
    "gn:feature_class":"P",
    "gn:feature_code":"PPL",
    "gn:name":"\u2018Izbat \u2018Abd as Sal\u0101m Kar\u012bm",
    "gn:population":0,
    "gn:timezone":"Africa/Cairo",
    "iso:country":"EG",
    "wof:name":"`Izbat `Abd as Salam Karim",
    "wof:placetype":"locality"
},
  "geometry": {"coordinates":[30.84303,29.4629],"type":"Point"}
}