{
  "type": "Feature",
  "properties": {
    "gn:admin1_code":"14",
    "gn:asciiname":"Dawwar Awlad Salamah",
    "gn:cc2":"EG",
    "gn:country_code":"EG",
    "gn:dem":4,
    "gn:feature_class":"P",
    "gn:feature_code":"PPL",
    "gn:name":"Daww\u0101r Awl\u0101d Sal\u0101mah",
    "gn:population":0,
    "gn:timezone":"Africa/Cairo",
    "iso:country":"EG",
    "name:und_x_variant":[
        "Dauw\u00e2r Aul\u00e2d Sal\u00e2ma",
        "Daww\u0101r Awl\u0101d Sal\u0101mah"
    ],
    "wof:name":"Dawwar Awlad Salamah",
    "wof:placetype":"locality"
},
  "geometry": {"coordinates":[31.73361,30.99528],"type":"Point"}
}