{
  "type": "Feature",
  "properties": {
    "gn:admin1_code":"03",
    "gn:asciiname":"Ruzzafah",
    "gn:country_code":"EG",
    "gn:dem":5,
    "gn:feature_class":"P",
    "gn:feature_code":"PPL",
    "gn:name":"Ruzz\u0101fah",
    "gn:population":0,
    "gn:timezone":"Africa/Cairo",
    "iso:country":"EG",
    "name:und_x_variant":[
        "\u2018Ezbet Ruzz\u00e2qa",
        "Ruzz\u00e2fa",
        "Ruzz\u0101fah"
    ],
    "wof:name":"Ruzzafah",
    "wof:placetype":"locality"
},
  "geometry": {"coordinates":[30.50333,30.88505],"type":"Point"}
}