{
  "type": "Feature",
  "properties": {
    "gn:admin1_code":"01",
    "gn:asciiname":"`Izbat Abu `Iwad",
    "gn:country_code":"EG",
    "gn:dem":10,
    "gn:feature_class":"P",
    "gn:feature_code":"PPL",
    "gn:name":"\u2018Izbat Ab\u016b \u2018Iwa\u1e11",
    "gn:population":0,
    "gn:timezone":"Africa/Cairo",
    "iso:country":"EG",
    "name:ara_x_preferred":[
        "\u0639\u0632\u0628\u0629 \u0623\u0628\u0648 \u0639\u0648\u0636"
    ],
    "name:und_x_variant":[
        "\u2018Izbat Ab\u016b \u2018Iwa\u1e11",
        "\u2018Izbat Ab\u016b \u2018Awa\u1e11",
        "\u2018Iz. Ab\u016b \u2018Awa\u1e0d"
    ],
    "wof:name":"`Izbat Abu `Iwad",
    "wof:placetype":"locality"
},
  "geometry": {"coordinates":[31.28932,30.9127],"type":"Point"}
}