{
  "type": "Feature",
  "properties": {
    "gn:admin1_code":"21",
    "gn:asciiname":"Kafr Difriyah",
    "gn:country_code":"EG",
    "gn:dem":7,
    "gn:feature_class":"P",
    "gn:feature_code":"PPL",
    "gn:name":"Kafr Difr\u012byah",
    "gn:population":0,
    "gn:timezone":"Africa/Cairo",
    "iso:country":"EG",
    "name:ara_x_preferred":[
        "\u0643\u0641\u0631 \u062f\u0641\u0631\u064a\u0629"
    ],
    "name:und_x_variant":[
        "Kafr Difr\u00eeya",
        "Kafr Difr\u012byah",
        "Kafr Difriyyah"
    ],
    "wof:name":"Kafr Difriyah",
    "wof:placetype":"locality"
},
  "geometry": {"coordinates":[30.94297000000001,31.05362],"type":"Point"}
}