{
  "type": "Feature",
  "properties": {
    "gn:admin1_code":"07",
    "gn:asciiname":"`Izbat al Husari",
    "gn:country_code":"EG",
    "gn:dem":8,
    "gn:feature_class":"P",
    "gn:feature_code":"PPL",
    "gn:name":"\u2018Izbat al \u1e28u\u015far\u012b",
    "gn:population":0,
    "gn:timezone":"Africa/Cairo",
    "iso:country":"EG",
    "name:und_x_variant":[
        "\u2018Ezbet el-\u1e24u\u1e63ari",
        "\u2018Izbat al \u1e28u\u015far\u012b"
    ],
    "wof:name":"`Izbat al Husari",
    "wof:placetype":"locality"
},
  "geometry": {"coordinates":[32.32056,30.51611],"type":"Point"}
}