{
  "type": "Feature",
  "properties": {
    "gn:admin1_code":"14",
    "gn:asciiname":"Inshas",
    "gn:country_code":"EG",
    "gn:dem":12,
    "gn:feature_class":"P",
    "gn:feature_code":"PPL",
    "gn:name":"Insh\u0101\u015f",
    "gn:population":0,
    "gn:timezone":"Africa/Cairo",
    "iso:country":"EG",
    "name:ara_x_preferred":[
        "Insh\u0101\u015f"
    ],
    "name:ara_x_variant":[
        "\u0627\u0646\u0634\u0627\u0635",
        "\u0623\u0646\u0634\u0627\u0635 \u0627\u0644\u0631\u0645\u0644"
    ],
    "name:ell_x_preferred":[
        "\u038a\u03bd\u03c3\u03c7\u03b1\u03c2"
    ],
    "name:pol_x_preferred":[
        "Inszas"
    ],
    "name:und_x_variant":[
        "Insh\u0101\u015f al Ba\u015fal",
        "Insh\u00e2\u1e63 el-Ba\u1e63al"
    ],
    "wof:name":"Inshas",
    "wof:placetype":"locality"
},
  "geometry": {"coordinates":[31.5642,30.50216],"type":"Point"}
}