{
  "type": "Feature",
  "properties": {
    "gn:admin1_code":"04",
    "gn:asciiname":"Kafr Hindawi at Tahawi",
    "gn:country_code":"EG",
    "gn:dem":-27,
    "gn:feature_class":"P",
    "gn:feature_code":"PPL",
    "gn:name":"Kafr Hind\u0101w\u012b a\u0163 \u0162\u0101\u1e29\u0101w\u012b",
    "gn:population":0,
    "gn:timezone":"Africa/Cairo",
    "iso:country":"EG",
    "name:und_x_variant":[
        "Kafr Hind\u00e2wi el Tah\u00e2wi",
        "Kafr Hind\u0101w\u012b a\u0163 \u0162\u0101\u1e29\u0101w\u012b"
    ],
    "wof:name":"Kafr Hindawi at Tahawi",
    "wof:placetype":"locality"
},
  "geometry": {"coordinates":[30.70103,29.40461],"type":"Point"}
}