{
  "type": "Feature",
  "properties": {
    "gn:admin1_code":"05",
    "gn:asciiname":"`Izbat al Bank",
    "gn:country_code":"EG",
    "gn:dem":11,
    "gn:feature_class":"P",
    "gn:feature_code":"PPL",
    "gn:name":"\u2018Izbat al Bank",
    "gn:population":0,
    "gn:timezone":"Africa/Cairo",
    "iso:country":"EG",
    "name:ara_x_preferred":[
        "\u0639\u0632\u0628\u0629 \u0627\u0644\u0628\u0646\u0643"
    ],
    "name:und_x_variant":[
        "\u2018Izbat al Bank",
        "\u2018Izbat al-Bank"
    ],
    "wof:name":"`Izbat al Bank",
    "wof:placetype":"locality"
},
  "geometry": {"coordinates":[31.12211,30.89605],"type":"Point"}
}