{
  "type": "Feature",
  "properties": {
    "gn:admin1_code":"23",
    "gn:asciiname":"Qusayr Bakhanis",
    "gn:country_code":"EG",
    "gn:dem":72,
    "gn:feature_class":"P",
    "gn:feature_code":"PPL",
    "gn:name":"Qu\u015fayr Bakh\u0101nis",
    "gn:population":0,
    "gn:timezone":"Africa/Cairo",
    "iso:country":"EG",
    "name:und_x_variant":[
        "Quseir Bakh\u00e2nis",
        "Qu\u015fayr Bakh\u0101nis"
    ],
    "wof:name":"Qusayr Bakhanis",
    "wof:placetype":"locality"
},
  "geometry": {"coordinates":[32.12356,26.14618],"type":"Point"}
}