{
  "type": "Feature",
  "properties": {
    "gn:admin1_code":"12",
    "gn:asciiname":"Munsha'at Shubra Haris",
    "gn:country_code":"EG",
    "gn:dem":16,
    "gn:feature_class":"P",
    "gn:feature_code":"PPL",
    "gn:name":"Munsha\u2019at Shubr\u0101 H\u0101ris",
    "gn:population":0,
    "gn:timezone":"Africa/Cairo",
    "iso:country":"EG",
    "name:ara_x_preferred":[
        "\u0645\u0646\u0634\u0623\u0629 \u0634\u0628\u0631\u0627 \u0647\u0627\u0631\u0633"
    ],
    "name:und_x_variant":[
        "Munsha\u2019at Shubr\u0101 H\u0101ris",
        "Minsh\u0101t Shubr\u0101 H\u0101ris"
    ],
    "wof:name":"Munsha'at Shubra Haris",
    "wof:placetype":"locality"
},
  "geometry": {"coordinates":[31.20781,30.31099],"type":"Point"}
}