{
  "type": "Feature",
  "properties": {
    "gn:admin1_code":"05",
    "gn:asciiname":"`Izbat al `Arab",
    "gn:country_code":"EG",
    "gn:dem":8,
    "gn:feature_class":"P",
    "gn:feature_code":"PPL",
    "gn:name":"\u2018Izbat al \u2018Arab",
    "gn:population":0,
    "gn:timezone":"Africa/Cairo",
    "iso:country":"EG",
    "name:ara_x_preferred":[
        "\u0639\u0632\u0628\u0629 \u0627\u0644\u0639\u0631\u0628"
    ],
    "name:und_x_variant":[
        "\u2018Izbat al \u2018Arab",
        "\u2018Izbat al-\u2018Arab"
    ],
    "wof:name":"`Izbat al `Arab",
    "wof:placetype":"locality"
},
  "geometry": {"coordinates":[31.03481,31.00856],"type":"Point"}
}