{
  "type": "Feature",
  "properties": {
    "gn:admin1_code":"03",
    "gn:asciiname":"`Izbat `Abd al Hafiz",
    "gn:country_code":"EG",
    "gn:dem":-2,
    "gn:feature_class":"P",
    "gn:feature_code":"PPL",
    "gn:name":"\u2018Izbat \u2018Abd al \u1e28af\u012bz\u0327",
    "gn:population":0,
    "gn:timezone":"Africa/Cairo",
    "iso:country":"EG",
    "name:ara_x_preferred":[
        "\u0639\u0632\u0628\u0629 \u0639\u0628\u062f \u0627\u0644\u062d\u0641\u064a\u0638"
    ],
    "name:und_x_variant":[
        "\u2018Izbat \u2018Abd al \u1e28af\u012bz\u0327",
        "\u2018Izbat \u2018Abd al-\u1e24af\u012b\u1e93"
    ],
    "wof:name":"`Izbat `Abd al Hafiz",
    "wof:placetype":"locality"
},
  "geometry": {"coordinates":[30.46249000000001,31.20544000000001],"type":"Point"}
}