{
  "type": "Feature",
  "properties": {
    "gn:admin1_code":"03",
    "gn:asciiname":"Zinzu",
    "gn:country_code":"EG",
    "gn:dem":6,
    "gn:feature_class":"P",
    "gn:feature_code":"PPL",
    "gn:name":"Zinz\u016b",
    "gn:population":0,
    "gn:timezone":"Africa/Cairo",
    "iso:country":"EG",
    "name:ara_x_preferred":[
        "\u0632\u0646\u0632\u0648"
    ],
    "name:und_x_variant":[
        "Zinz\u016b"
    ],
    "wof:name":"Zinzu",
    "wof:placetype":"locality"
},
  "geometry": {"coordinates":[30.13415,31.16427],"type":"Point"}
}