{
  "type": "Feature",
  "properties": {
    "gn:admin1_code":"05",
    "gn:asciiname":"Manshiyat Tunbarah",
    "gn:country_code":"EG",
    "gn:dem":9,
    "gn:feature_class":"P",
    "gn:feature_code":"PPL",
    "gn:name":"Mansh\u012byat \u0162unb\u0101rah",
    "gn:population":0,
    "gn:timezone":"Africa/Cairo",
    "iso:country":"EG",
    "name:ara_x_preferred":[
        "\u0645\u0646\u0634\u064a\u0629 \u0637\u0646\u0628\u0627\u0631\u0629"
    ],
    "name:und_x_variant":[
        "Mansh\u00eeyet \u1e6cumb\u00e2ra",
        "Mansh\u012byat \u0162unb\u0101rah",
        "Al Mansh\u012byah",
        "El-Mansh\u00eeya",
        "Manshiyyat \u1e6cunb\u0101rah",
        "Manshiyyat \u0162unb\u0101rah"
    ],
    "wof:name":"Manshiyat Tunbarah",
    "wof:placetype":"locality"
},
  "geometry": {"coordinates":[31.13298,31.09577],"type":"Point"}
}