{
  "type": "Feature",
  "properties": {
    "gn:admin1_code":"27",
    "gn:asciiname":"Rumanah",
    "gn:country_code":"EG",
    "gn:dem":7,
    "gn:feature_class":"P",
    "gn:feature_code":"PPL",
    "gn:name":"Rum\u0101nah",
    "gn:population":0,
    "gn:timezone":"Africa/Cairo",
    "iso:country":"EG",
    "name:und_x_variant":[
        "Rum\u00e2na",
        "Rum\u0101nah"
    ],
    "wof:name":"Rumanah",
    "wof:placetype":"locality"
},
  "geometry": {"coordinates":[32.6638,31.01121],"type":"Point"}
}