{
  "type": "Feature",
  "properties": {
    "gn:admin1_code":"03",
    "gn:asciiname":"`Izbat ash Shubaki",
    "gn:country_code":"EG",
    "gn:dem":1,
    "gn:feature_class":"P",
    "gn:feature_code":"PPL",
    "gn:name":"\u2018Izbat ash Sh\u016bbak\u012b",
    "gn:population":0,
    "gn:timezone":"Africa/Cairo",
    "iso:country":"EG",
    "name:ara_x_preferred":[
        "\u0639\u0632\u0628\u0629 \u0627\u0644\u0634\u0648\u0628\u0643\u064a"
    ],
    "name:und_x_variant":[
        "\u2018Izbat ash Sh\u016bbak\u012b"
    ],
    "wof:name":"`Izbat ash Shubaki",
    "wof:placetype":"locality"
},
  "geometry": {"coordinates":[30.42007000000001,31.09869],"type":"Point"}
}