{
  "type": "Feature",
  "properties": {
    "gn:admin1_code":"21",
    "gn:asciiname":"`Izbat al `Arjan",
    "gn:country_code":"EG",
    "gn:dem":3,
    "gn:feature_class":"P",
    "gn:feature_code":"PPL",
    "gn:name":"\u2018Izbat al \u2018Arj\u0101n",
    "gn:population":0,
    "gn:timezone":"Africa/Cairo",
    "iso:country":"EG",
    "name:ara_x_preferred":[
        "\u0639\u0632\u0628\u0629 \u0627\u0644\u0639\u0631\u062c\u0627\u0646"
    ],
    "name:und_x_variant":[
        "\u2018Izbat al \u2018Arj\u0101n"
    ],
    "wof:name":"`Izbat al `Arjan",
    "wof:placetype":"locality"
},
  "geometry": {"coordinates":[30.49,31.35906],"type":"Point"}
}