{
  "type": "Feature",
  "properties": {
    "gn:admin1_code":"27",
    "gn:asciiname":"El Avoa",
    "gn:country_code":"EG",
    "gn:dem":216,
    "gn:feature_class":"P",
    "gn:feature_code":"PPL",
    "gn:name":"El Avoa",
    "gn:population":0,
    "gn:timezone":"Africa/Cairo",
    "iso:country":"EG",
    "wof:name":"El Avoa",
    "wof:placetype":"locality"
},
  "geometry": {"coordinates":[34.38023,30.8858],"type":"Point"}
}