{
  "type": "Feature",
  "properties": {
    "gn:admin1_code":"03",
    "gn:asciiname":"`Izbat Yusuf Qumbur",
    "gn:country_code":"EG",
    "gn:dem":1,
    "gn:feature_class":"P",
    "gn:feature_code":"PPL",
    "gn:name":"\u2018Izbat Y\u016bsuf Qumbur",
    "gn:population":0,
    "gn:timezone":"Africa/Cairo",
    "iso:country":"EG",
    "name:ara_x_preferred":[
        "\u0639\u0632\u0628\u0629 \u064a\u0648\u0633\u0641 \u0642\u0645\u0628\u0631"
    ],
    "name:und_x_variant":[
        "\u2018Izbat Y\u016bsuf Qumbur",
        "\u2018Izbat Y\u016bsif Qumbur"
    ],
    "wof:name":"`Izbat Yusuf Qumbur",
    "wof:placetype":"locality"
},
  "geometry": {"coordinates":[30.29063,31.04566],"type":"Point"}
}