{
  "type": "Feature",
  "properties": {
    "gn:admin1_code":"21",
    "gn:asciiname":"Minyat al Murshid",
    "gn:country_code":"EG",
    "gn:dem":12,
    "gn:feature_class":"P",
    "gn:feature_code":"PPL",
    "gn:name":"Minyat al Murshid",
    "gn:population":0,
    "gn:timezone":"Africa/Cairo",
    "iso:country":"EG",
    "name:ara_x_preferred":[
        "\u0645\u0646\u064a\u0629 \u0627\u0644\u0645\u0631\u0634\u062f"
    ],
    "name:und_x_variant":[
        "Minyet el-Murshid",
        "Minyat al Murshid"
    ],
    "wof:name":"Minyat al Murshid",
    "wof:placetype":"locality"
},
  "geometry": {"coordinates":[30.53407,31.32737],"type":"Point"}
}