{
  "type": "Feature",
  "properties": {
    "gn:admin1_code":"03",
    "gn:asciiname":"Mahallat Nasr",
    "gn:country_code":"EG",
    "gn:dem":4,
    "gn:feature_class":"P",
    "gn:feature_code":"PPL",
    "gn:name":"Ma\u1e29allat Na\u015fr",
    "gn:population":0,
    "gn:timezone":"Africa/Cairo",
    "iso:country":"EG",
    "name:ara_x_preferred":[
        "\u0645\u062d\u0644\u0629 \u0646\u0635\u0631"
    ],
    "name:und_x_variant":[
        "Ma\u1e25allet Na\u1e63r",
        "Ma\u1e29allat Na\u015fr",
        "Ma\u1e25allat Na\u1e63r"
    ],
    "wof:name":"Mahallat Nasr",
    "wof:placetype":"locality"
},
  "geometry": {"coordinates":[30.60949,31.00722],"type":"Point"}
}