{
  "type": "Feature",
  "properties": {
    "gn:admin1_code":"18",
    "gn:asciiname":"Bani Ahmad",
    "gn:country_code":"EG",
    "gn:dem":31,
    "gn:feature_class":"P",
    "gn:feature_code":"PPL",
    "gn:name":"Ban\u012b A\u1e29mad",
    "gn:population":0,
    "gn:timezone":"Africa/Cairo",
    "iso:country":"EG",
    "name:und_x_variant":[
        "Beni A\u1e25mad",
        "Ban\u012b A\u1e29mad"
    ],
    "wof:name":"Bani Ahmad",
    "wof:placetype":"locality"
},
  "geometry": {"coordinates":[30.99032,29.01347],"type":"Point"}
}