{
  "type": "Feature",
  "properties": {
    "gn:admin1_code":"14.0",
    "gn:asciiname":"Umm Ramad",
    "gn:country_code":"EG",
    "gn:dem":12,
    "gn:feature_class":"P",
    "gn:feature_code":"PPL",
    "gn:name":"Umm Ram\u0101d",
    "gn:population":0,
    "gn:timezone":"Africa/Cairo",
    "iso:country":"EG",
    "name:ara_x_preferred":[
        "\u0623\u0645 \u0631\u0645\u0627\u062f"
    ],
    "name:und_x_variant":[
        "Umm Ram\u0101d"
    ],
    "wof:name":"Umm Ramad",
    "wof:placetype":"locality"
},
  "geometry": {"coordinates":[31.44277,30.65229],"type":"Point"}
}