{
  "type": "Feature",
  "properties": {
    "gn:admin1_code":"10",
    "gn:asciiname":"Kawm al Lufi",
    "gn:country_code":"EG",
    "gn:dem":41,
    "gn:feature_class":"P",
    "gn:feature_code":"PPL",
    "gn:name":"Kawm al L\u016bf\u012b",
    "gn:population":0,
    "gn:timezone":"Africa/Cairo",
    "iso:country":"EG",
    "name:und_x_variant":[
        "K\u00f4m el L\u00fbfi",
        "Kawm al L\u016bf\u012b"
    ],
    "wof:name":"Kawm al Lufi",
    "wof:placetype":"locality"
},
  "geometry": {"coordinates":[30.70404000000001,28.2583],"type":"Point"}
}