{
  "type": "Feature",
  "properties": {
    "iso:country":"EG",
    "qs:gn_country":"EG",
    "qs:gn_fcode":"PPLX",
    "qs:gn_pop":0,
    "qs:name":"Kafr R\u00e5shid",
    "qs:name_adm0":"\u0645\u0635\u0631",
    "qs:name_adm1":"\u0627\u0644\u0633\u0648\u064a\u0633",
    "qs:photos":31,
    "qs:photos_1k":6,
    "qs:photos_9k":1,
    "qs:photos_9r":2,
    "qs:photos_all":31,
    "qs:photos_sr":2,
    "qs:placetype":"Suburb",
    "qs:pop_sr":"0",
    "qs:woe_adm0":23424802,
    "wof:name":"Kafr R\u00e5shid",
    "wof:placetype":"neighbourhood"
},
  "geometry": {"coordinates":[32.53333,29.98333],"type":"Point"}
}