{
  "type": "Feature",
  "properties": {
    "gn:admin1_code":"14",
    "gn:asciiname":"Kafr Ahmad Burham",
    "gn:country_code":"EG",
    "gn:dem":10,
    "gn:feature_class":"P",
    "gn:feature_code":"PPL",
    "gn:name":"Kafr A\u1e29mad Burh\u0101m",
    "gn:population":0,
    "gn:timezone":"Africa/Cairo",
    "iso:country":"EG",
    "name:ara_x_preferred":[
        "\u0643\u0641\u0631 \u0623\u062c\u0645\u062f \u0628\u0631\u0647\u0627\u0645"
    ],
    "name:und_x_variant":[
        "Kafr A\u1e29mad Burh\u0101m"
    ],
    "wof:name":"Kafr Ahmad Burham",
    "wof:placetype":"locality"
},
  "geometry": {"coordinates":[31.60594,30.60961],"type":"Point"}
}