{
  "type": "Feature",
  "properties": {
    "gn:admin1_code":"21",
    "gn:asciiname":"Mahallat al Qasab",
    "gn:country_code":"EG",
    "gn:dem":10,
    "gn:feature_class":"P",
    "gn:feature_code":"PPL",
    "gn:name":"Ma\u1e29allat al Qa\u015fab",
    "gn:population":0,
    "gn:timezone":"Africa/Cairo",
    "iso:country":"EG",
    "name:ara_x_preferred":[
        "\u0645\u062d\u0644\u0629 \u0627\u0644\u0642\u0635\u0628"
    ],
    "name:und_x_variant":[
        "Ma\u1e25allet el-Qa\u1e63ab",
        "Ma\u1e29allat al Qa\u015fab",
        "Mi\u1e25allat al-Qa\u1e63ab"
    ],
    "wof:name":"Mahallat al Qasab",
    "wof:placetype":"locality"
},
  "geometry": {"coordinates":[30.90102000000001,31.14175],"type":"Point"}
}