{
  "type": "Feature",
  "properties": {
    "gn:admin1_code":"02",
    "gn:asciiname":"Al Hibah ash Sharqi",
    "gn:cc2":"EG",
    "gn:country_code":"EG",
    "gn:dem":31,
    "gn:feature_class":"P",
    "gn:feature_code":"PPL",
    "gn:name":"Al \u1e28\u012bbah ash Sharq\u012b",
    "gn:population":0,
    "gn:timezone":"Africa/Cairo",
    "iso:country":"EG",
    "name:und_x_variant":[
        "El \u1e24\u00eeba el Sharqi",
        "Al \u1e28\u012bbah ash Sharq\u012b"
    ],
    "wof:name":"Al Hibah ash Sharqi",
    "wof:placetype":"locality"
},
  "geometry": {"coordinates":[30.91667,28.76667],"type":"Point"}
}