{
  "type": "Feature",
  "properties": {
    "gn:admin1_code":"14",
    "gn:asciiname":"`Izbat Salah al Hawwari",
    "gn:country_code":"EG",
    "gn:dem":4,
    "gn:feature_class":"P",
    "gn:feature_code":"PPL",
    "gn:name":"\u2018Izbat \u015eal\u0101\u1e29 al Haww\u0101r\u012b",
    "gn:population":0,
    "gn:timezone":"Africa/Cairo",
    "iso:country":"EG",
    "name:ara_x_preferred":[
        "\u0639\u0632\u0628\u0629 \u0635\u0644\u0627\u062d \u0627\u0644\u0647\u0648\u0627\u0631\u064a"
    ],
    "name:und_x_variant":[
        "\u2018Izbat \u015eal\u0101\u1e29 al Haww\u0101r\u012b",
        "\u2018Izbat \u1e62al\u0101\u1e25 al-Haww\u0101ri"
    ],
    "wof:name":"`Izbat Salah al Hawwari",
    "wof:placetype":"locality"
},
  "geometry": {"coordinates":[31.77827000000001,31.01842000000001],"type":"Point"}
}