{
  "type": "Feature",
  "properties": {
    "gn:admin1_code":"03",
    "gn:asciiname":"`Izbat Ghallab",
    "gn:country_code":"EG",
    "gn:dem":2,
    "gn:feature_class":"P",
    "gn:feature_code":"PPL",
    "gn:name":"\u2018Izbat Ghall\u0101b",
    "gn:population":0,
    "gn:timezone":"Africa/Cairo",
    "iso:country":"EG",
    "name:ara_x_preferred":[
        "\u0639\u0632\u0628\u0629 \u063a\u0644\u0627\u0628"
    ],
    "name:und_x_variant":[
        "\u2018Izbat Ghall\u0101b"
    ],
    "wof:name":"`Izbat Ghallab",
    "wof:placetype":"locality"
},
  "geometry": {"coordinates":[30.46591,31.25667],"type":"Point"}
}