{
  "type": "Feature",
  "properties": {
    "gn:admin1_code":"08",
    "gn:asciiname":"Al Widy wa Kafr ad Dismi",
    "gn:cc2":"EG",
    "gn:country_code":"EG",
    "gn:dem":29,
    "gn:feature_class":"P",
    "gn:feature_code":"PPL",
    "gn:name":"Al Widy wa Kafr ad Dism\u012b",
    "gn:population":0,
    "gn:timezone":"Africa/Cairo",
    "iso:country":"EG",
    "name:und_x_variant":[
        "El-Widy wa Kafr el-Disam\u00ee",
        "Al Widy wa Kafr ad Dism\u012b"
    ],
    "wof:name":"Al Widy wa Kafr ad Dismi",
    "wof:placetype":"locality"
},
  "geometry": {"coordinates":[31.275,29.49111],"type":"Point"}
}