{
  "type": "Feature",
  "properties": {
    "gn:admin1_code":"01",
    "gn:asciiname":"Sahrajat as Sughra",
    "gn:country_code":"EG",
    "gn:dem":11,
    "gn:feature_class":"P",
    "gn:feature_code":"PPL",
    "gn:name":"\u015eahrajat a\u015f \u015eughr\u00e1",
    "gn:population":0,
    "gn:timezone":"Africa/Cairo",
    "iso:country":"EG",
    "name:ara_x_preferred":[
        "\u0635\u0647\u0631\u062c\u062a \u0627\u0644\u0635\u063a\u0631\u0649"
    ],
    "name:und_x_variant":[
        "\u015eahrajat a\u015f \u015eughr\u00e1 wa Kafr as Sayyid",
        "\u1e62ahragt el-Sughra",
        "\u1e62ahragt el-Sughra wa Kafr el-Saiyid",
        "\u015eahrajt as \u015eughr\u00e1",
        "\u015eahrajat a\u015f \u015eughr\u00e1",
        "\u1e62ahrajt a\u1e63-\u1e62ughra"
    ],
    "wof:name":"Sahrajat as Sughra",
    "wof:placetype":"locality"
},
  "geometry": {"coordinates":[31.27563,30.80178],"type":"Point"}
}