{
  "type": "Feature",
  "properties": {
    "gn:admin1_code":"14",
    "gn:asciiname":"Tahrat Humayd",
    "gn:country_code":"EG",
    "gn:dem":11,
    "gn:feature_class":"P",
    "gn:feature_code":"PPL",
    "gn:name":"\u0162ahrat \u1e28umayd",
    "gn:population":0,
    "gn:timezone":"Africa/Cairo",
    "iso:country":"EG",
    "name:ara_x_preferred":[
        "\u0637\u0647\u0631\u0629 \u062d\u0645\u064a\u062f"
    ],
    "name:und_x_variant":[
        "\u0162ahrat \u1e28umayd",
        "\u0162ahrit \u1e28imayd"
    ],
    "wof:name":"Tahrat Humayd",
    "wof:placetype":"locality"
},
  "geometry": {"coordinates":[31.56943,30.53268],"type":"Point"}
}