{
  "type": "Feature",
  "properties": {
    "gn:admin1_code":"01",
    "gn:asciiname":"Kafr Humaydah",
    "gn:country_code":"EG",
    "gn:dem":5,
    "gn:feature_class":"P",
    "gn:feature_code":"PPL",
    "gn:name":"Kafr \u1e28umaydah",
    "gn:population":0,
    "gn:timezone":"Africa/Cairo",
    "iso:country":"EG",
    "name:und_x_variant":[
        "Kafr \u1e24emeida",
        "Kafr \u1e28umaydah"
    ],
    "wof:name":"Kafr Humaydah",
    "wof:placetype":"locality"
},
  "geometry": {"coordinates":[31.83383,31.49293],"type":"Point"}
}