{
  "type": "Feature",
  "properties": {
    "gn:admin1_code":"05",
    "gn:asciiname":"Kafr Ghazi",
    "gn:country_code":"EG",
    "gn:dem":13,
    "gn:feature_class":"P",
    "gn:feature_code":"PPL",
    "gn:name":"Kafr Gh\u0101z\u012b",
    "gn:population":0,
    "gn:timezone":"Africa/Cairo",
    "iso:country":"EG",
    "name:ara_x_preferred":[
        "\u0643\u0641\u0631 \u063a\u0627\u0632\u064a"
    ],
    "name:und_x_variant":[
        "Kafr Gh\u00e2zi",
        "Kafr Gh\u0101z\u012b"
    ],
    "wof:name":"Kafr Ghazi",
    "wof:placetype":"locality"
},
  "geometry": {"coordinates":[31.21334,30.6243],"type":"Point"}
}