{
  "type": "Feature",
  "properties": {
    "gn:admin1_code":"10",
    "gn:asciiname":"`Izbat al Masharqah",
    "gn:country_code":"EG",
    "gn:dem":41,
    "gn:feature_class":"P",
    "gn:feature_code":"PPL",
    "gn:name":"\u2018Izbat al Mash\u0101rqah",
    "gn:population":0,
    "gn:timezone":"Africa/Cairo",
    "iso:country":"EG",
    "wof:name":"`Izbat al Masharqah",
    "wof:placetype":"locality"
},
  "geometry": {"coordinates":[30.63352,28.24723],"type":"Point"}
}