{
  "type": "Feature",
  "properties": {
    "gn:admin1_code":"12",
    "gn:asciiname":"Kafr Sa`d",
    "gn:country_code":"EG",
    "gn:dem":14,
    "gn:feature_class":"P",
    "gn:feature_code":"PPL",
    "gn:name":"Kafr Sa\u2018d",
    "gn:population":0,
    "gn:timezone":"Africa/Cairo",
    "iso:country":"EG",
    "name:ara_x_preferred":[
        "\u0643\u0641\u0631 \u0633\u0639\u062f"
    ],
    "name:und_x_variant":[
        "Kafr Sa\u2018d"
    ],
    "wof:name":"Kafr Sa`d",
    "wof:placetype":"locality"
},
  "geometry": {"coordinates":[31.20138,30.49164],"type":"Point"}
}