{
  "type": "Feature",
  "properties": {
    "gn:admin1_code":"17",
    "gn:asciiname":"Sallam",
    "gn:country_code":"EG",
    "gn:dem":51,
    "gn:feature_class":"P",
    "gn:feature_code":"PPL",
    "gn:name":"Sall\u0101m",
    "gn:population":0,
    "gn:timezone":"Africa/Cairo",
    "iso:country":"EG",
    "wof:name":"Sallam",
    "wof:placetype":"locality"
},
  "geometry": {"coordinates":[31.11374,27.23229000000001],"type":"Point"}
}