{
  "type": "Feature",
  "properties": {
    "gn:admin1_code":"21",
    "gn:asciiname":"`Izbat Muhammad Abu as Sayyid",
    "gn:country_code":"EG",
    "gn:dem":4,
    "gn:feature_class":"P",
    "gn:feature_code":"PPL",
    "gn:name":"\u2018Izbat Mu\u1e29ammad Ab\u016b as Sayyid",
    "gn:population":0,
    "gn:timezone":"Africa/Cairo",
    "iso:country":"EG",
    "name:ara_x_preferred":[
        "\u0639\u0632\u0628\u0629 \u0645\u062d\u0645\u062f \u0623\u0628\u0648 \u0627\u0644\u0633\u064a\u062f"
    ],
    "name:und_x_variant":[
        "\u2018Izbat Mu\u1e29ammad Ab\u016b as Sayyid"
    ],
    "wof:name":"`Izbat Muhammad Abu as Sayyid",
    "wof:placetype":"locality"
},
  "geometry": {"coordinates":[30.93936,31.27981],"type":"Point"}
}