{
  "type": "Feature",
  "properties": {
    "gn:admin1_code":"14",
    "gn:asciiname":"`Izbat Imam",
    "gn:country_code":"EG",
    "gn:dem":11,
    "gn:feature_class":"P",
    "gn:feature_code":"PPL",
    "gn:name":"\u2018Izbat Im\u0101m",
    "gn:population":0,
    "gn:timezone":"Africa/Cairo",
    "iso:country":"EG",
    "name:ara_x_preferred":[
        "\u0639\u0632\u0628\u0629 \u0625\u0645\u0627\u0645"
    ],
    "name:und_x_variant":[
        "\u2018Izbat Im\u0101m"
    ],
    "wof:name":"`Izbat Imam",
    "wof:placetype":"locality"
},
  "geometry": {"coordinates":[31.49252000000001,30.61452],"type":"Point"}
}