{
  "type": "Feature",
  "properties": {
    "gn:admin1_code":"21",
    "gn:asciiname":"`Izbat al Basha",
    "gn:country_code":"EG",
    "gn:dem":2,
    "gn:feature_class":"P",
    "gn:feature_code":"PPL",
    "gn:name":"\u2018Izbat al B\u0101sh\u0101",
    "gn:population":0,
    "gn:timezone":"Africa/Cairo",
    "iso:country":"EG",
    "name:ara_x_preferred":[
        "\u0639\u0632\u0628\u0629 \u0627\u0644\u0628\u0627\u0634\u0627"
    ],
    "name:und_x_variant":[
        "\u2018Izbat al B\u0101sh\u0101"
    ],
    "wof:name":"`Izbat al Basha",
    "wof:placetype":"locality"
},
  "geometry": {"coordinates":[30.6063,31.33761],"type":"Point"}
}