{
  "type": "Feature",
  "properties": {
    "gn:admin1_code":"01",
    "gn:asciiname":"Qaryah Thalathah wa Khamsun",
    "gn:country_code":"EG",
    "gn:dem":3,
    "gn:feature_class":"P",
    "gn:feature_code":"PPL",
    "gn:name":"Qaryah Thal\u0101thah wa Khams\u016bn",
    "gn:population":0,
    "gn:timezone":"Africa/Cairo",
    "iso:country":"EG",
    "name:ara_x_preferred":[
        "\u0642\u0631\u064a\u0629 \u0665\u0663"
    ],
    "name:ara_x_variant":[
        "\u0642\u0631\u064a\u0629 53"
    ],
    "name:und_x_variant":[
        "Qaryah Thal\u0101thah wa Khams\u016bn",
        "Qaryah 53"
    ],
    "wof:name":"Qaryah Thalathah wa Khamsun",
    "wof:placetype":"locality"
},
  "geometry": {"coordinates":[31.30103,31.42509],"type":"Point"}
}