{
  "type": "Feature",
  "properties": {
    "gn:admin1_code":"16",
    "gn:asciiname":"Al Manshiyah",
    "gn:cc2":"EG",
    "gn:country_code":"EG",
    "gn:dem":104,
    "gn:feature_class":"P",
    "gn:feature_code":"PPL",
    "gn:name":"Al Mansh\u012byah",
    "gn:population":0,
    "gn:timezone":"Africa/Cairo",
    "iso:country":"EG",
    "name:und_x_variant":[
        "El Manshiya",
        "Al Mansh\u012byah"
    ],
    "wof:name":"Al Manshiyah",
    "wof:placetype":"locality"
},
  "geometry": {"coordinates":[32.91667,24.08333],"type":"Point"}
}