{
  "type": "Feature",
  "properties": {
    "gn:admin1_code":"10",
    "gn:asciiname":"Al Badraman",
    "gn:country_code":"EG",
    "gn:dem":48,
    "gn:feature_class":"P",
    "gn:feature_code":"PPL",
    "gn:name":"Al Badram\u0101n",
    "gn:population":0,
    "gn:timezone":"Africa/Cairo",
    "iso:country":"EG",
    "name:und_x_variant":[
        "El Badram\u00e2n",
        "Al Badram\u0101n"
    ],
    "wof:name":"Al Badraman",
    "wof:placetype":"locality"
},
  "geometry": {"coordinates":[30.74299,27.66681],"type":"Point"}
}