{
  "type": "Feature",
  "properties": {
    "gn:admin1_code":"23",
    "gn:asciiname":"Naj` al Tud",
    "gn:country_code":"EG",
    "gn:dem":72,
    "gn:feature_class":"P",
    "gn:feature_code":"PPL",
    "gn:name":"Naj\u2018 al \u0162\u016bd",
    "gn:population":0,
    "gn:timezone":"Africa/Cairo",
    "iso:country":"EG",
    "name:und_x_variant":[
        "Nag\u2018 el-T\u00f4d",
        "Naj\u2018 al \u0162\u016bd"
    ],
    "wof:name":"Naj` al Tud",
    "wof:placetype":"locality"
},
  "geometry": {"coordinates":[32.07398,26.16409],"type":"Point"}
}