{
  "type": "Feature",
  "properties": {
    "gn:admin1_code":"01",
    "gn:asciiname":"Al Gharraqah",
    "gn:country_code":"EG",
    "gn:dem":10,
    "gn:feature_class":"P",
    "gn:feature_code":"PPL",
    "gn:name":"Al Gharr\u0101qah",
    "gn:population":0,
    "gn:timezone":"Africa/Cairo",
    "iso:country":"EG",
    "name:ara_x_preferred":[
        "\u0639\u0632\u0628\u0629 \u0627\u0644\u063a\u0631\u0627\u0642\u0629"
    ],
    "name:und_x_variant":[
        "El-Gharr\u00e2qa",
        "El-Gbarraqa",
        "Al Gharr\u0101qah",
        "Al-Gharr\u0101qah"
    ],
    "wof:name":"Al Gharraqah",
    "wof:placetype":"locality"
},
  "geometry": {"coordinates":[31.32495,30.88074000000001],"type":"Point"}
}