{
  "type": "Feature",
  "properties": {
    "gn:admin1_code":"01",
    "gn:asciiname":"Al Qalyubiyah",
    "gn:country_code":"EG",
    "gn:dem":6,
    "gn:feature_class":"P",
    "gn:feature_code":"PPL",
    "gn:name":"Al Qaly\u016bb\u012byah",
    "gn:population":0,
    "gn:timezone":"Africa/Cairo",
    "iso:country":"EG",
    "name:ara_x_preferred":[
        "\u0627\u0644\u0642\u0644\u064a\u0648\u0628\u064a\u0629"
    ],
    "name:und_x_variant":[
        "El-Qaly\u00fbb\u00eeya",
        "Al Qaly\u016bb\u012byah",
        "Al-Qaly\u016bbiyyah"
    ],
    "wof:name":"Al Qalyubiyah",
    "wof:placetype":"locality"
},
  "geometry": {"coordinates":[31.56868,31.11237],"type":"Point"}
}