{
  "type": "Feature",
  "properties": {
    "gn:admin1_code":"14",
    "gn:asciiname":"Al `Abbasah al Gharbiyah",
    "gn:country_code":"EG",
    "gn:dem":9,
    "gn:feature_class":"P",
    "gn:feature_code":"PPL",
    "gn:name":"Al \u2018Abb\u0101sah al Gharb\u012byah",
    "gn:population":0,
    "gn:timezone":"Africa/Cairo",
    "iso:country":"EG",
    "name:und_x_variant":[
        "Abbas\u00eea el Gharb\u00eea",
        "El-\u2018Abb\u00e2sa el-Gharb\u00eeya",
        "Al \u2018Abb\u0101sah al Gharb\u012byah"
    ],
    "wof:name":"Al `Abbasah al Gharbiyah",
    "wof:placetype":"locality"
},
  "geometry": {"coordinates":[31.64889,30.52389],"type":"Point"}
}