{
  "type": "Feature",
  "properties": {
    "gn:admin1_code":"03",
    "gn:asciiname":"Nitma",
    "gn:country_code":"EG",
    "gn:dem":7,
    "gn:feature_class":"P",
    "gn:feature_code":"PPL",
    "gn:name":"Nitm\u0101",
    "gn:population":0,
    "gn:timezone":"Africa/Cairo",
    "iso:country":"EG",
    "name:und_x_variant":[
        "Nitm\u0101"
    ],
    "wof:name":"Nitma",
    "wof:placetype":"locality"
},
  "geometry": {"coordinates":[30.77182,30.74726],"type":"Point"}
}