{
  "type": "Feature",
  "properties": {
    "gn:admin1_code":"12",
    "gn:asciiname":"Marsafa",
    "gn:country_code":"EG",
    "gn:dem":16,
    "gn:feature_class":"P",
    "gn:feature_code":"PPL",
    "gn:name":"Marsafa",
    "gn:population":0,
    "gn:timezone":"Africa/Cairo",
    "iso:country":"EG",
    "name:ara_x_preferred":[
        "\u0645\u0631\u0635\u0641\u0627"
    ],
    "name:und_x_variant":[
        "Mar\u015faf\u0101 wa Kafr A\u1e29mad \u2019ash\u012bsh",
        "Mar\u1e63afa and Kafr A\u1e25mad \u1e24ash\u00eesh",
        "Mar\u1e63afa and Kafr A\u1e25med \u1e24ash\u00eesh",
        "Mar\u1e63afa wa Kafr A\u1e25mad \u1e24ash\u00eesh",
        "Marsafa"
    ],
    "wof:name":"Marsafa",
    "wof:placetype":"locality"
},
  "geometry": {"coordinates":[31.24771,30.40992],"type":"Point"}
}