{
  "type": "Feature",
  "properties": {
    "gn:admin1_code":"12",
    "gn:asciiname":"`Izbat `Abd al Hamid Nasr",
    "gn:country_code":"EG",
    "gn:dem":16,
    "gn:feature_class":"P",
    "gn:feature_code":"PPL",
    "gn:name":"\u2018Izbat \u2018Abd al \u1e28am\u012bd Na\u015fr",
    "gn:population":0,
    "gn:timezone":"Africa/Cairo",
    "iso:country":"EG",
    "name:ara_x_preferred":[
        "\u0639\u0632\u0628\u0629 \u0639\u0628\u062f \u0627\u0644\u062d\u0645\u064a\u062f \u0646\u0635\u0631"
    ],
    "name:und_x_variant":[
        "\u2018Izbat \u2018Abd al \u1e28am\u012bd Na\u015fr"
    ],
    "wof:name":"`Izbat `Abd al Hamid Nasr",
    "wof:placetype":"locality"
},
  "geometry": {"coordinates":[31.24684,30.49631],"type":"Point"}
}