{
  "type": "Feature",
  "properties": {
    "gn:admin1_code":"01",
    "gn:asciiname":"Minyat Badaway",
    "gn:country_code":"EG",
    "gn:dem":12,
    "gn:feature_class":"P",
    "gn:feature_code":"PPL",
    "gn:name":"Minyat Badaw\u0101y",
    "gn:population":0,
    "gn:timezone":"Africa/Cairo",
    "iso:country":"EG",
    "name:ara_x_preferred":[
        "\u0645\u0646\u064a\u0629 \u0628\u062f\u0648\u0627\u064a"
    ],
    "name:und_x_variant":[
        "Minyet Badaw\u00e2i",
        "Minyat Badaw\u0101y"
    ],
    "wof:name":"Minyat Badaway",
    "wof:placetype":"locality"
},
  "geometry": {"coordinates":[31.49808,31.16105],"type":"Point"}
}