{
  "type": "Feature",
  "properties": {
    "gn:admin1_code":"03",
    "gn:asciiname":"Turujah",
    "gn:country_code":"EG",
    "gn:dem":0,
    "gn:feature_class":"P",
    "gn:feature_code":"PPL",
    "gn:name":"Tur\u016bjah",
    "gn:population":0,
    "gn:timezone":"Africa/Cairo",
    "iso:country":"EG",
    "name:und_x_variant":[
        "\u2018Ezbet Tur\u00fbga",
        "Tur\u016bjah"
    ],
    "wof:name":"Turujah",
    "wof:placetype":"locality"
},
  "geometry": {"coordinates":[30.17343,30.97089],"type":"Point"}
}