{
  "type": "Feature",
  "properties": {
    "gn:admin1_code":"24",
    "gn:asciiname":"Kawm al Hamid",
    "gn:country_code":"EG",
    "gn:dem":58,
    "gn:feature_class":"P",
    "gn:feature_code":"PPL",
    "gn:name":"Kawm al \u1e28\u0101mi\u1e11",
    "gn:population":0,
    "gn:timezone":"Africa/Cairo",
    "iso:country":"EG",
    "wof:name":"Kawm al Hamid",
    "wof:placetype":"locality"
},
  "geometry": {"coordinates":[31.41667,26.83333],"type":"Point"}
}