{
  "type": "Feature",
  "properties": {
    "gn:admin1_code":"3.0",
    "gn:asciiname":"Zawiyat Khunayzah",
    "gn:country_code":"EG",
    "gn:dem":8,
    "gn:feature_class":"P",
    "gn:feature_code":"PPL",
    "gn:name":"Z\u0101wiyat Khunayzah",
    "gn:population":0,
    "gn:timezone":"Africa/Cairo",
    "iso:country":"EG",
    "name:und_x_variant":[
        "Z\u00e2wyet Khuneiza",
        "Z\u0101wiyat Khunayzah"
    ],
    "wof:name":"Zawiyat Khunayzah",
    "wof:placetype":"locality"
},
  "geometry": {"coordinates":[30.67603,30.72077],"type":"Point"}
}