{
  "type": "Feature",
  "properties": {
    "gn:admin1_code":"06",
    "gn:asciiname":"Qaryat al Waqqad",
    "gn:country_code":"EG",
    "gn:dem":2,
    "gn:feature_class":"P",
    "gn:feature_code":"PPL",
    "gn:name":"Qaryat al Waqq\u0101d",
    "gn:population":0,
    "gn:timezone":"Africa/Cairo",
    "iso:country":"EG",
    "name:ara_x_preferred":[
        "\u0642\u0631\u064a\u0629 \u0627\u0644\u0648\u0642\u0627\u062f"
    ],
    "name:und_x_variant":[
        "Qaryat al Waqq\u0101d"
    ],
    "wof:name":"Qaryat al Waqqad",
    "wof:placetype":"locality"
},
  "geometry": {"coordinates":[29.8968,31.00497],"type":"Point"}
}