{
  "type": "Feature",
  "properties": {
    "gn:admin1_code":"21",
    "gn:asciiname":"`Izbat Abu Ghallab",
    "gn:country_code":"EG",
    "gn:dem":6,
    "gn:feature_class":"P",
    "gn:feature_code":"PPL",
    "gn:name":"\u2018Izbat Ab\u016b Ghall\u0101b",
    "gn:population":0,
    "gn:timezone":"Africa/Cairo",
    "iso:country":"EG",
    "name:ara_x_preferred":[
        "\u0639\u0632\u0628\u0629 \u0623\u0628\u0648 \u063a\u0644\u0627\u0628"
    ],
    "name:und_x_variant":[
        "\u2018Izbat Ab\u016b Ghall\u0101b"
    ],
    "wof:name":"`Izbat Abu Ghallab",
    "wof:placetype":"locality"
},
  "geometry": {"coordinates":[30.9394,31.18895],"type":"Point"}
}