{
  "type": "Feature",
  "properties": {
    "gn:admin1_code":"21",
    "gn:asciiname":"Shalimah",
    "gn:country_code":"EG",
    "gn:dem":9,
    "gn:feature_class":"P",
    "gn:feature_code":"PPL",
    "gn:name":"Sh\u0101limah",
    "gn:population":0,
    "gn:timezone":"Africa/Cairo",
    "iso:country":"EG",
    "name:ara_x_preferred":[
        "\u0634\u0627\u0644\u0645\u0629"
    ],
    "name:und_x_variant":[
        "Sh\u00e2lma",
        "Sh\u0101limah"
    ],
    "wof:name":"Shalimah",
    "wof:placetype":"locality"
},
  "geometry": {"coordinates":[30.87348,31.23485],"type":"Point"}
}