{
  "type": "Feature",
  "properties": {
    "gn:admin1_code":"05",
    "gn:asciiname":"Shubra Qas",
    "gn:country_code":"EG",
    "gn:dem":15,
    "gn:feature_class":"P",
    "gn:feature_code":"PPL",
    "gn:name":"Shubr\u0101 Q\u0101\u015f",
    "gn:population":0,
    "gn:timezone":"Africa/Cairo",
    "iso:country":"EG",
    "name:ara_x_preferred":[
        "Shubr\u0101 Q\u0101\u015f"
    ],
    "name:ara_x_variant":[
        "\u0634\u0628\u0631\u0627 \u0642\u0627\u0635"
    ],
    "name:und_x_variant":[
        "Shubra G\u00e2s",
        "Shubra Q\u00e2\u1e63"
    ],
    "wof:name":"Shubra Qas",
    "wof:placetype":"locality"
},
  "geometry": {"coordinates":[31.06784,30.74098],"type":"Point"}
}