{
  "type": "Feature",
  "properties": {
    "gn:admin1_code":"23",
    "gn:asciiname":"Abu Manna` Bahri",
    "gn:country_code":"EG",
    "gn:dem":76,
    "gn:feature_class":"P",
    "gn:feature_code":"PPL",
    "gn:name":"Ab\u016b Mann\u0101\u2018 Ba\u1e29r\u012b",
    "gn:population":0,
    "gn:timezone":"Africa/Cairo",
    "iso:country":"EG",
    "name:und_x_variant":[
        "Abu Mann\u00e2\u2018 Ba\u1e25ari",
        "Ab\u016b Mann\u0101\u2018 Ba\u1e29r\u012b"
    ],
    "wof:name":"Abu Manna` Bahri",
    "wof:placetype":"locality"
},
  "geometry": {"coordinates":[32.42156,26.15319],"type":"Point"}
}