{
  "type": "Feature",
  "properties": {
    "gn:admin1_code":"14",
    "gn:asciiname":"`Izbat Salamah Shahin",
    "gn:country_code":"EG",
    "gn:dem":9,
    "gn:feature_class":"P",
    "gn:feature_code":"PPL",
    "gn:name":"\u2018Izbat Sal\u0101mah Sh\u0101h\u012bn",
    "gn:population":0,
    "gn:timezone":"Africa/Cairo",
    "iso:country":"EG",
    "name:ara_x_preferred":[
        "\u0639\u0632\u0628\u0629 \u0633\u0644\u0627\u0645\u0629 \u0634\u0627\u0647\u0646"
    ],
    "name:und_x_variant":[
        "\u2018Izbat Sal\u0101mah Sh\u0101h\u012bn"
    ],
    "wof:name":"`Izbat Salamah Shahin",
    "wof:placetype":"locality"
},
  "geometry": {"coordinates":[31.45932,30.70698],"type":"Point"}
}