{
  "type": "Feature",
  "properties": {
    "gn:admin1_code":"22.0",
    "gn:asciiname":"Zawiyat al `Awwamah",
    "gn:country_code":"EG",
    "gn:dem":8,
    "gn:feature_class":"P",
    "gn:feature_code":"PPL",
    "gn:name":"Z\u0101wiyat al \u2018Aww\u0101mah",
    "gn:population":0,
    "gn:timezone":"Africa/Cairo",
    "iso:country":"EG",
    "name:und_x_variant":[
        "Zawiyet el \u2018Auw\u0101ma",
        "Zawyet el \u2018Auw\u00e2ma",
        "Z\u0101wiyat al \u2018Aww\u0101mah"
    ],
    "wof:name":"Zawiyat al `Awwamah",
    "wof:placetype":"locality"
},
  "geometry": {"coordinates":[28.09817,31.0865],"type":"Point"}
}