{
  "type": "Feature",
  "properties": {
    "gn:admin1_code":"03",
    "gn:asciiname":"`Izbat Salim",
    "gn:country_code":"EG",
    "gn:dem":5,
    "gn:feature_class":"P",
    "gn:feature_code":"PPL",
    "gn:name":"\u2018Izbat Sal\u012bm",
    "gn:population":0,
    "gn:timezone":"Africa/Cairo",
    "iso:country":"EG",
    "name:ara_x_preferred":[
        "\u0639\u0632\u0628\u0629 \u0633\u0644\u064a\u0645"
    ],
    "name:und_x_variant":[
        "\u2018Izbat Sal\u012bm",
        "\u2018Izbat Sil\u012bm"
    ],
    "wof:name":"`Izbat Salim",
    "wof:placetype":"locality"
},
  "geometry": {"coordinates":[30.45152,31.0869],"type":"Point"}
}