{
  "type": "Feature",
  "properties": {
    "gn:admin1_code":"10",
    "gn:asciiname":"Abu Qaltah",
    "gn:country_code":"EG",
    "gn:dem":46,
    "gn:feature_class":"P",
    "gn:feature_code":"PPL",
    "gn:name":"Ab\u016b Qaltah",
    "gn:population":0,
    "gn:timezone":"Africa/Cairo",
    "iso:country":"EG",
    "name:und_x_variant":[
        "Abu Qalta",
        "Ab\u016b Qaltah"
    ],
    "wof:name":"Abu Qaltah",
    "wof:placetype":"locality"
},
  "geometry": {"coordinates":[30.74156,27.80887],"type":"Point"}
}