{
  "type": "Feature",
  "properties": {
    "gn:admin1_code":"20",
    "gn:asciiname":"Kafr al Munazalah",
    "gn:country_code":"EG",
    "gn:dem":5,
    "gn:feature_class":"P",
    "gn:feature_code":"PPL",
    "gn:name":"Kafr al Mun\u0101zalah",
    "gn:population":0,
    "gn:timezone":"Africa/Cairo",
    "iso:country":"EG",
    "name:ara_x_preferred":[
        "\u0643\u0641\u0631 \u0627\u0644\u0645\u0646\u0627\u0632\u0644\u0629"
    ],
    "name:und_x_variant":[
        "Kafr el-Man\u00e2zla",
        "Kafr al Man\u0101zilah",
        "Kafr al Mun\u0101zalah"
    ],
    "wof:name":"Kafr al Munazalah",
    "wof:placetype":"locality"
},
  "geometry": {"coordinates":[31.69213,31.31536],"type":"Point"}
}