{
  "type": "Feature",
  "properties": {
    "gn:admin1_code":"03",
    "gn:asciiname":"Qubur al Umara'",
    "gn:country_code":"EG",
    "gn:dem":5,
    "gn:feature_class":"P",
    "gn:feature_code":"PPL",
    "gn:name":"Qub\u016br al Umar\u0101\u2019",
    "gn:population":0,
    "gn:timezone":"Africa/Cairo",
    "iso:country":"EG",
    "name:und_x_variant":[
        "Qub\u00fbr el-Umara",
        "Qub\u016br al Umar\u0101\u2019"
    ],
    "wof:name":"Qubur al Umara'",
    "wof:placetype":"locality"
},
  "geometry": {"coordinates":[30.57306,30.77222],"type":"Point"}
}