{
  "type": "Feature",
  "properties": {
    "gn:admin1_code":"14",
    "gn:asciiname":"`Izbat as Sis",
    "gn:country_code":"EG",
    "gn:dem":7,
    "gn:feature_class":"P",
    "gn:feature_code":"PPL",
    "gn:name":"\u2018Izbat as S\u012bs",
    "gn:population":0,
    "gn:timezone":"Africa/Cairo",
    "iso:country":"EG",
    "name:ara_x_preferred":[
        "\u0639\u0632\u0628\u0629 \u0627\u0644\u0633\u064a\u0633"
    ],
    "name:und_x_variant":[
        "\u2018Izbat as S\u012bs"
    ],
    "wof:name":"`Izbat as Sis",
    "wof:placetype":"locality"
},
  "geometry": {"coordinates":[31.68219,30.73315],"type":"Point"}
}