{
  "type": "Feature",
  "properties": {
    "gn:admin1_code":"06",
    "gn:asciiname":"Abu Mas`ud",
    "gn:country_code":"EG",
    "gn:dem":23,
    "gn:feature_class":"P",
    "gn:feature_code":"PPL",
    "gn:name":"Ab\u016b Mas\u2018\u016bd",
    "gn:population":0,
    "gn:timezone":"Africa/Cairo",
    "iso:country":"EG",
    "wof:name":"Abu Mas`ud",
    "wof:placetype":"locality"
},
  "geometry": {"coordinates":[29.85053,30.84951],"type":"Point"}
}