{
  "type": "Feature",
  "properties": {
    "gn:admin1_code":"21",
    "gn:asciiname":"`Izbat `Adli",
    "gn:country_code":"EG",
    "gn:dem":5,
    "gn:feature_class":"P",
    "gn:feature_code":"PPL",
    "gn:name":"\u2018Izbat \u2018Adl\u012b",
    "gn:population":0,
    "gn:timezone":"Africa/Cairo",
    "iso:country":"EG",
    "name:ara_x_preferred":[
        "\u0639\u0632\u0628\u0629 \u0639\u062f\u0644\u064a"
    ],
    "name:und_x_variant":[
        "\u2018Izbat \u2018Adl\u012b"
    ],
    "wof:name":"`Izbat `Adli",
    "wof:placetype":"locality"
},
  "geometry": {"coordinates":[31.10874,31.16915],"type":"Point"}
}