{
  "type": "Feature",
  "properties": {
    "gn:admin1_code":"14",
    "gn:asciiname":"At Tawilah",
    "gn:country_code":"EG",
    "gn:dem":16,
    "gn:feature_class":"P",
    "gn:feature_code":"PPL",
    "gn:name":"A\u0163 \u0162aw\u012blah",
    "gn:population":0,
    "gn:timezone":"Africa/Cairo",
    "iso:country":"EG",
    "name:ara_x_preferred":[
        "\u0627\u0644\u0637\u0648\u064a\u0644\u0629"
    ],
    "name:und_x_variant":[
        "El-\u1e6caw\u00eela",
        "Al Taw\u012bla",
        "A\u0163 \u0162aw\u012blah"
    ],
    "wof:name":"At Tawilah",
    "wof:placetype":"locality"
},
  "geometry": {"coordinates":[31.7356,30.6542],"type":"Point"}
}