{
  "type": "Feature",
  "properties": {
    "gn:admin1_code":"01",
    "gn:asciiname":"Kafr at Tur`ah al Qadim",
    "gn:country_code":"EG",
    "gn:dem":8,
    "gn:feature_class":"P",
    "gn:feature_code":"PPL",
    "gn:name":"Kafr at Tur\u2018ah al Qad\u012bm",
    "gn:population":0,
    "gn:timezone":"Africa/Cairo",
    "iso:country":"EG",
    "name:ara_x_preferred":[
        "\u0643\u0641\u0631 \u0627\u0644\u062a\u0631\u0639\u0629 \u0627\u0644\u0642\u062f\u064a\u0645"
    ],
    "name:und_x_variant":[
        "Kafr el-Tir\u2018a el-Qad\u00eem",
        "Kafr at Tur\u2018ah al Qad\u012bm",
        "Kafr at-Tir\u2018ah al-Qad\u012bm"
    ],
    "wof:name":"Kafr at Tur`ah al Qadim",
    "wof:placetype":"locality"
},
  "geometry": {"coordinates":[31.61065,31.23302],"type":"Point"}
}