{
  "type": "Feature",
  "properties": {
    "gn:admin1_code":"03",
    "gn:asciiname":"`Izbat Qisim Thalith Jabaris",
    "gn:country_code":"EG",
    "gn:dem":10,
    "gn:feature_class":"P",
    "gn:feature_code":"PPL",
    "gn:name":"\u2018Izbat Qisim Th\u0101lith Jab\u0101ris",
    "gn:population":0,
    "gn:timezone":"Africa/Cairo",
    "iso:country":"EG",
    "wof:name":"`Izbat Qisim Thalith Jabaris",
    "wof:placetype":"locality"
},
  "geometry": {"coordinates":[30.59219,30.88105],"type":"Point"}
}