{
  "type": "Feature",
  "properties": {
    "gn:admin1_code":"03",
    "gn:asciiname":"Al Jarayisah",
    "gn:country_code":"EG",
    "gn:dem":6,
    "gn:feature_class":"P",
    "gn:feature_code":"PPL",
    "gn:name":"Al Jar\u0101yisah",
    "gn:population":0,
    "gn:timezone":"Africa/Cairo",
    "iso:country":"EG",
    "name:ara_x_preferred":[
        "\u0627\u0644\u062c\u0631\u0627\u064a\u0633\u0629"
    ],
    "name:und_x_variant":[
        "Al Jar\u0101yisah",
        "Al-Jar\u0101ysah"
    ],
    "wof:name":"Al Jarayisah",
    "wof:placetype":"locality"
},
  "geometry": {"coordinates":[30.65661,31.01187],"type":"Point"}
}