{
  "type": "Feature",
  "properties": {
    "gn:admin1_code":"01",
    "gn:asciiname":"Al Hasainah",
    "gn:country_code":"EG",
    "gn:dem":5,
    "gn:feature_class":"P",
    "gn:feature_code":"PPL",
    "gn:name":"Al \u1e28as\u0101inah",
    "gn:population":0,
    "gn:timezone":"Africa/Cairo",
    "iso:country":"EG",
    "name:und_x_variant":[
        "El-\u1e24as\u00e2yna",
        "Al \u1e28as\u0101inah"
    ],
    "wof:name":"Al Hasainah",
    "wof:placetype":"locality"
},
  "geometry": {"coordinates":[31.82632000000001,31.40713],"type":"Point"}
}