{
  "type": "Feature",
  "properties": {
    "gn:admin1_code":"08",
    "gn:asciiname":"`Ezbet Muhammad Yasin",
    "gn:country_code":"EG",
    "gn:dem":62,
    "gn:feature_class":"P",
    "gn:feature_code":"PPL",
    "gn:name":"\u2018Ezbet Mu\u1e25ammad Yas\u00een",
    "gn:population":0,
    "gn:timezone":"Africa/Cairo",
    "iso:country":"EG",
    "wof:name":"`Ezbet Muhammad Yasin",
    "wof:placetype":"locality"
},
  "geometry": {"coordinates":[31.16667,29.91667],"type":"Point"}
}