{
  "type": "Feature",
  "properties": {
    "gn:admin1_code":"09",
    "gn:asciiname":"Dinshaway",
    "gn:cc2":"EG",
    "gn:country_code":"EG",
    "gn:dem":10,
    "gn:feature_class":"P",
    "gn:feature_code":"PPL",
    "gn:name":"Dinshaw\u0101y",
    "gn:population":0,
    "gn:timezone":"Africa/Cairo",
    "iso:country":"EG",
    "name:ara_x_preferred":[
        "\u062f\u0646\u0634\u0648\u0627\u064a"
    ],
    "name:pol_x_preferred":[
        "Dinszawaj"
    ],
    "name:und_x_variant":[
        "Denshawai",
        "Dinshaw\u00e2i",
        "Dinshaw\u0101y"
    ],
    "wof:name":"Dinshaway",
    "wof:placetype":"locality"
},
  "geometry": {"coordinates":[30.82056,30.60139],"type":"Point"}
}