{
  "type": "Feature",
  "properties": {
    "gn:admin1_code":"13",
    "gn:asciiname":"`Ezbet Dib Waer",
    "gn:country_code":"EG",
    "gn:dem":84,
    "gn:feature_class":"P",
    "gn:feature_code":"PPL",
    "gn:name":"\u2018Ezbet Dib Waer",
    "gn:population":0,
    "gn:timezone":"Africa/Cairo",
    "iso:country":"EG",
    "wof:name":"`Ezbet Dib Waer",
    "wof:placetype":"locality"
},
  "geometry": {"coordinates":[30.50418,25.40259],"type":"Point"}
}