{
  "type": "Feature",
  "properties": {
    "gn:admin1_code":"14",
    "gn:asciiname":"Kafr al `Ayid",
    "gn:country_code":"EG",
    "gn:dem":11,
    "gn:feature_class":"P",
    "gn:feature_code":"PPL",
    "gn:name":"Kafr al \u2018\u0100yid",
    "gn:population":0,
    "gn:timezone":"Africa/Cairo",
    "iso:country":"EG",
    "name:ara_x_preferred":[
        "\u0643\u0641\u0631 \u0627\u0644\u0639\u0627\u064a\u062f"
    ],
    "name:und_x_variant":[
        "Kafr el- \u2018\u00c2yid",
        "Kafr al \u2018\u0100\u2019id",
        "Kafr al \u2018\u0100yid"
    ],
    "wof:name":"Kafr al `Ayid",
    "wof:placetype":"locality"
},
  "geometry": {"coordinates":[31.51588,30.67806],"type":"Point"}
}