{
  "type": "Feature",
  "properties": {
    "gn:admin1_code":"03",
    "gn:asciiname":"Kafr Nikla",
    "gn:country_code":"EG",
    "gn:dem":5,
    "gn:feature_class":"P",
    "gn:feature_code":"PPL",
    "gn:name":"Kafr Nikl\u0101",
    "gn:population":0,
    "gn:timezone":"Africa/Cairo",
    "iso:country":"EG",
    "name:ara_x_preferred":[
        "\u0643\u0641\u0631 \u0646\u0643\u0644\u0627"
    ],
    "name:und_x_variant":[
        "Kafr Nikl\u0101"
    ],
    "wof:name":"Kafr Nikla",
    "wof:placetype":"locality"
},
  "geometry": {"coordinates":[30.52448,31.16604],"type":"Point"}
}