{
  "type": "Feature",
  "properties": {
    "iso:country":"EG",
    "name:und_x_variant":[
        "El \u1e24usein\u00eeya"
    ],
    "qs:gn_country":"EG",
    "qs:gn_fcode":"PPL",
    "qs:gn_pop":0,
    "qs:name":"Al Husayniyah",
    "qs:name_adm0":"\u0645\u0635\u0631",
    "qs:name_adm1":"\u0627\u0644\u0634\u0631\u0642\u064a\u0629",
    "qs:photos":21,
    "qs:photos_1k":4,
    "qs:photos_9k":1,
    "qs:photos_9r":1,
    "qs:photos_all":21,
    "qs:photos_sr":1,
    "qs:placetype":"Town",
    "qs:pop_sr":"0",
    "qs:woe_adm0":23424802,
    "wof:name":"Al Husayniyah",
    "wof:placetype":"locality"
},
  "geometry": {"coordinates":[31.92161,30.86235],"type":"Point"}
}