{
  "type": "Feature",
  "properties": {
    "gn:admin1_code":"28",
    "gn:asciiname":"Al `Ashshi",
    "gn:country_code":"EG",
    "gn:dem":82,
    "gn:feature_class":"P",
    "gn:feature_code":"PPL",
    "gn:name":"Al \u2018Ashsh\u012b",
    "gn:population":0,
    "gn:timezone":"Africa/Cairo",
    "iso:country":"EG",
    "name:ara_x_preferred":[
        "\u0627\u0644\u0639\u0634\u0649"
    ],
    "name:und_x_variant":[
        "El \u2018Ash-shi",
        "Al \u2018Ashsh\u012b"
    ],
    "wof:name":"Al `Ashshi",
    "wof:placetype":"locality"
},
  "geometry": {"coordinates":[32.73397,25.77404],"type":"Point"}
}