{
  "type": "Feature",
  "properties": {
    "gn:admin1_code":"04",
    "gn:asciiname":"Az Zawiyah al Khadra'",
    "gn:country_code":"EG",
    "gn:dem":15,
    "gn:feature_class":"P",
    "gn:feature_code":"PPL",
    "gn:name":"Az Z\u0101wiyah al Kha\u1e11r\u0101\u2019",
    "gn:population":0,
    "gn:timezone":"Africa/Cairo",
    "iso:country":"EG",
    "name:und_x_variant":[
        "El-Z\u00e2wya el-Kha\u1e0dra",
        "Az Z\u0101wiyah al Kha\u1e11r\u0101\u2019"
    ],
    "wof:name":"Az Zawiyah al Khadra'",
    "wof:placetype":"locality"
},
  "geometry": {"coordinates":[30.85171,29.41447],"type":"Point"}
}