{
  "type": "Feature",
  "properties": {
    "gn:admin1_code":"21",
    "gn:asciiname":"`Izbat Makram",
    "gn:country_code":"EG",
    "gn:dem":4,
    "gn:feature_class":"P",
    "gn:feature_code":"PPL",
    "gn:name":"\u2018Izbat Makram",
    "gn:population":0,
    "gn:timezone":"Africa/Cairo",
    "iso:country":"EG",
    "name:ara_x_preferred":[
        "\u0639\u0632\u0628\u0629 \u0645\u0643\u0631\u0645"
    ],
    "name:und_x_variant":[
        "\u2018Izbat Makram"
    ],
    "wof:name":"`Izbat Makram",
    "wof:placetype":"locality"
},
  "geometry": {"coordinates":[30.60598,31.22513],"type":"Point"}
}