{
  "type": "Feature",
  "properties": {
    "gn:admin1_code":"3.0",
    "gn:asciiname":"`Izbat al Armal",
    "gn:country_code":"EG",
    "gn:dem":-3,
    "gn:feature_class":"P",
    "gn:feature_code":"PPL",
    "gn:name":"\u2018Izbat al Armal",
    "gn:population":0,
    "gn:timezone":"Africa/Cairo",
    "iso:country":"EG",
    "name:ara_x_preferred":[
        "\u0639\u0632\u0628\u0629 \u0627\u0644\u0623\u0631\u0645\u0644"
    ],
    "name:und_x_variant":[
        "\u2018Izbat al Armal",
        "\u2018Azbat \u015eub\u1e29\u012b Bay Ghali",
        "\u2018Ezbet el Arman",
        "\u2018Ezbet \u1e62ub\u1e25i Bey Gh\u00e2li",
        "\u2018Izbat \u015eub\u1e29\u012b Bey Gh\u0101l\u012b",
        "\u2018Ezbet K\u00f4m el-\u1e24\u00e2gg",
        "Kawm al \u1e28ajj"
    ],
    "wof:name":"`Izbat al Armal",
    "wof:placetype":"locality"
},
  "geometry": {"coordinates":[30.00579,31.08651],"type":"Point"}
}