{
  "type": "Feature",
  "properties": {
    "gn:admin1_code":"03",
    "gn:asciiname":"Qaryat Salah ad Din",
    "gn:country_code":"EG",
    "gn:dem":14,
    "gn:feature_class":"P",
    "gn:feature_code":"PPL",
    "gn:name":"Qaryat \u015eal\u0101\u1e29 ad D\u012bn",
    "gn:population":0,
    "gn:timezone":"Africa/Cairo",
    "iso:country":"EG",
    "wof:name":"Qaryat Salah ad Din",
    "wof:placetype":"locality"
},
  "geometry": {"coordinates":[30.72149000000001,30.59227000000001],"type":"Point"}
}