{
  "type": "Feature",
  "properties": {
    "gn:admin1_code":"04",
    "gn:asciiname":"Dimishqin",
    "gn:country_code":"EG",
    "gn:dem":29,
    "gn:feature_class":"P",
    "gn:feature_code":"PPL",
    "gn:name":"Dimishq\u012bn",
    "gn:population":0,
    "gn:timezone":"Africa/Cairo",
    "iso:country":"EG",
    "wof:name":"Dimishqin",
    "wof:placetype":"locality"
},
  "geometry": {"coordinates":[30.93496,29.23267],"type":"Point"}
}