{
  "type": "Feature",
  "properties": {
    "gn:admin1_code":"01",
    "gn:asciiname":"`Izbat al Mustajiddah al Gharbiyah",
    "gn:country_code":"EG",
    "gn:dem":3,
    "gn:feature_class":"P",
    "gn:feature_code":"PPL",
    "gn:name":"\u2018Izbat al Mustajiddah al Gharb\u012byah",
    "gn:population":0,
    "gn:timezone":"Africa/Cairo",
    "iso:country":"EG",
    "name:ara_x_preferred":[
        "\u0639\u0632\u0628\u0629 \u0627\u0644\u0645\u0633\u062a\u062c\u062f\u0629 \u0627\u0644\u063a\u0631\u0628\u064a\u0629"
    ],
    "name:und_x_variant":[
        "\u2018Izbat al Mustajiddah al Gharb\u012byah"
    ],
    "wof:name":"`Izbat al Mustajiddah al Gharbiyah",
    "wof:placetype":"locality"
},
  "geometry": {"coordinates":[31.38846,31.38135],"type":"Point"}
}