{
  "type": "Feature",
  "properties": {
    "gn:admin1_code":"14.0",
    "gn:asciiname":"Tall al Qadi",
    "gn:country_code":"EG",
    "gn:dem":10,
    "gn:feature_class":"P",
    "gn:feature_code":"PPL",
    "gn:name":"Tall al Q\u0101\u1e11\u012b",
    "gn:population":0,
    "gn:timezone":"Africa/Cairo",
    "iso:country":"EG",
    "name:ara_x_preferred":[
        "\u062a\u0644 \u0627\u0644\u0642\u0627\u0636\u064a"
    ],
    "name:und_x_variant":[
        "Tell el-Q\u00e2\u1e0di",
        "Tall al Q\u0101\u1e11\u012b"
    ],
    "wof:name":"Tall al Qadi",
    "wof:placetype":"locality"
},
  "geometry": {"coordinates":[31.45061,30.74256],"type":"Point"}
}