{
  "type": "Feature",
  "properties": {
    "gn:admin1_code":"28",
    "gn:asciiname":"Az Zayniyah Qibli",
    "gn:country_code":"EG",
    "gn:dem":81,
    "gn:feature_class":"P",
    "gn:feature_code":"PPL",
    "gn:name":"Az Zayn\u012byah Qibl\u012b",
    "gn:population":0,
    "gn:timezone":"Africa/Cairo",
    "iso:country":"EG",
    "name:und_x_variant":[
        "El Zein\u00eeya Qibli",
        "Az Zayn\u012byah Qibl\u012b"
    ],
    "wof:name":"Az Zayniyah Qibli",
    "wof:placetype":"locality"
},
  "geometry": {"coordinates":[32.67895,25.75196],"type":"Point"}
}