{
  "type": "Feature",
  "properties": {
    "gn:admin1_code":"09",
    "gn:asciiname":"`Izbat Mahmud Nur ad Din",
    "gn:country_code":"EG",
    "gn:dem":13,
    "gn:feature_class":"P",
    "gn:feature_code":"PPL",
    "gn:name":"\u2018Izbat Ma\u1e29m\u016bd N\u016br ad D\u012bn",
    "gn:population":0,
    "gn:timezone":"Africa/Cairo",
    "iso:country":"EG",
    "name:ara_x_preferred":[
        "\u0639\u0632\u0628\u0629 \u0645\u062d\u0645\u0648\u062f \u0646\u0648\u0631 \u0627\u0644\u062f\u064a\u0646"
    ],
    "name:und_x_variant":[
        "\u2018Izbat Ma\u1e29m\u016bd N\u016br ad D\u012bn",
        "\u2018Izbat Ma\u1e25m\u016bd N\u016br ad-D\u012bn"
    ],
    "wof:name":"`Izbat Mahmud Nur ad Din",
    "wof:placetype":"locality"
},
  "geometry": {"coordinates":[30.986,30.34511],"type":"Point"}
}