{
  "type": "Feature",
  "properties": {
    "gn:admin1_code":"21",
    "gn:asciiname":"Al Hidud",
    "gn:country_code":"EG",
    "gn:dem":5,
    "gn:feature_class":"P",
    "gn:feature_code":"PPL",
    "gn:name":"Al \u1e28id\u016bd",
    "gn:population":0,
    "gn:timezone":"Africa/Cairo",
    "iso:country":"EG",
    "name:ara_x_preferred":[
        "\u0627\u0644\u062d\u062f\u0648\u062f"
    ],
    "name:und_x_variant":[
        "El-\u1e24ud\u00fbd",
        "Al \u1e28ud\u016bd",
        "Al \u1e28id\u016bd",
        "Al-\u1e24idud"
    ],
    "wof:name":"Al Hidud",
    "wof:placetype":"locality"
},
  "geometry": {"coordinates":[30.8864,31.14857],"type":"Point"}
}