{
  "type": "Feature",
  "properties": {
    "gn:admin1_code":"01",
    "gn:asciiname":"`Izbat al Batt",
    "gn:country_code":"EG",
    "gn:dem":8,
    "gn:feature_class":"P",
    "gn:feature_code":"PPL",
    "gn:name":"\u2018Izbat al Ba\u0163\u0163",
    "gn:population":0,
    "gn:timezone":"Africa/Cairo",
    "iso:country":"EG",
    "name:ara_x_preferred":[
        "\u0639\u0632\u0628\u0629 \u0627\u0644\u0628\u0637"
    ],
    "name:und_x_variant":[
        "\u2018Izbat al Ba\u0163\u0163",
        "\u2018Izbat al-Ba\u1e6d\u1e6d"
    ],
    "wof:name":"`Izbat al Batt",
    "wof:placetype":"locality"
},
  "geometry": {"coordinates":[31.48768,31.20418],"type":"Point"}
}