{
  "type": "Feature",
  "properties": {
    "iso:country":"EG",
    "qs:gn_pop":0,
    "qs:name":"Burg Migheizil",
    "qs:name_adm0":"\u0645\u0635\u0631",
    "qs:name_adm1":"\u0643\u0641\u0631 \u0627\u0644\u0634\u064a\u062e",
    "qs:photos":18,
    "qs:photos_1k":4,
    "qs:photos_9k":1,
    "qs:photos_9r":1,
    "qs:photos_all":18,
    "qs:photos_sr":1,
    "qs:placetype":"Town",
    "qs:pop_sr":"0",
    "qs:woe_adm0":23424802,
    "wof:name":"Burg Migheizil",
    "wof:placetype":"locality"
},
  "geometry": {"coordinates":[30.390724,31.445067],"type":"Point"}
}