{
  "type": "Feature",
  "properties": {
    "gn:admin1_code":"23",
    "gn:asciiname":"Ar Rayayinah",
    "gn:country_code":"EG",
    "gn:dem":83,
    "gn:feature_class":"P",
    "gn:feature_code":"PPL",
    "gn:name":"Ar Ray\u0101yinah",
    "gn:population":0,
    "gn:timezone":"Africa/Cairo",
    "iso:country":"EG",
    "name:und_x_variant":[
        "El Ray\u00e2yna",
        "Ar Ray\u0101yinah"
    ],
    "wof:name":"Ar Rayayinah",
    "wof:placetype":"locality"
},
  "geometry": {"coordinates":[32.47423,25.60816],"type":"Point"}
}