{
  "type": "Feature",
  "properties": {
    "gn:admin1_code":"20",
    "gn:asciiname":"As Salimiyah",
    "gn:country_code":"EG",
    "gn:dem":5,
    "gn:feature_class":"P",
    "gn:feature_code":"PPL",
    "gn:name":"As S\u0101lim\u012byah",
    "gn:population":0,
    "gn:timezone":"Africa/Cairo",
    "iso:country":"EG",
    "name:und_x_variant":[
        "El-S\u00e2lm\u00eeya",
        "As S\u0101lim\u012byah"
    ],
    "wof:name":"As Salimiyah",
    "wof:placetype":"locality"
},
  "geometry": {"coordinates":[31.76028,31.35661],"type":"Point"}
}