{
  "type": "Feature",
  "properties": {
    "gn:admin1_code":"23",
    "gn:asciiname":"Al Kawm al Ahmar",
    "gn:country_code":"EG",
    "gn:dem":74,
    "gn:feature_class":"P",
    "gn:feature_code":"PPL",
    "gn:name":"Al Kawm al A\u1e29mar",
    "gn:population":0,
    "gn:timezone":"Africa/Cairo",
    "iso:country":"EG",
    "name:und_x_variant":[
        "El K\u00f4m el A\u1e25mar",
        "K\u00f4m el Ahmar",
        "Al Kawm al A\u1e29mar"
    ],
    "wof:name":"Al Kawm al Ahmar",
    "wof:placetype":"locality"
},
  "geometry": {"coordinates":[32.14542,26.07559],"type":"Point"}
}