{
  "type": "Feature",
  "properties": {
    "gn:admin1_code":"03",
    "gn:asciiname":"Khunayzah",
    "gn:country_code":"EG",
    "gn:dem":6,
    "gn:feature_class":"P",
    "gn:feature_code":"PPL",
    "gn:name":"Khunayzah",
    "gn:population":0,
    "gn:timezone":"Africa/Cairo",
    "iso:country":"EG",
    "name:und_x_variant":[
        "Khune\u00eeza",
        "Khunayzah"
    ],
    "wof:name":"Khunayzah",
    "wof:placetype":"locality"
},
  "geometry": {"coordinates":[30.67754,30.71416],"type":"Point"}
}