{
  "type": "Feature",
  "properties": {
    "gn:admin1_code":"01",
    "gn:asciiname":"Munsha'at `Asim",
    "gn:country_code":"EG",
    "gn:dem":10,
    "gn:feature_class":"P",
    "gn:feature_code":"PPL",
    "gn:name":"Munsha\u2019at \u2018\u0100\u015fim",
    "gn:population":0,
    "gn:timezone":"Africa/Cairo",
    "iso:country":"EG",
    "name:ara_x_preferred":[
        "\u0645\u0646\u0634\u0623\u0629 \u0639\u0627\u0635\u0645"
    ],
    "name:und_x_variant":[
        "Minsha\u2019at \u2018A\u1e63im",
        "Minshat \u2018Asem",
        "Minsh\u00e2t \u2018\u00c2\u1e63im",
        "Munsha\u2019at \u2018\u0100\u015fim",
        "Minsh\u0101t \u2018\u0100\u1e63im"
    ],
    "wof:name":"Munsha'at `Asim",
    "wof:placetype":"locality"
},
  "geometry": {"coordinates":[31.69234,31.12558],"type":"Point"}
}