{
  "type": "Feature",
  "properties": {
    "gn:admin1_code":"04",
    "gn:asciiname":"Bani Hani",
    "gn:country_code":"EG",
    "gn:dem":26,
    "gn:feature_class":"P",
    "gn:feature_code":"PPL",
    "gn:name":"Ban\u012b H\u0101n\u012b",
    "gn:population":0,
    "gn:timezone":"Africa/Cairo",
    "iso:country":"EG",
    "name:und_x_variant":[
        "El Zir\u00eeba",
        "Beni H\u00e2ni",
        "Ban\u012b H\u0101n\u012b"
    ],
    "wof:name":"Bani Hani",
    "wof:placetype":"locality"
},
  "geometry": {"coordinates":[30.92336,29.15648],"type":"Point"}
}