{
  "type": "Feature",
  "properties": {
    "gn:admin1_code":"21",
    "gn:asciiname":"Munsha'at `Abbas",
    "gn:country_code":"EG",
    "gn:dem":6,
    "gn:feature_class":"P",
    "gn:feature_code":"PPL",
    "gn:name":"Munsha\u2019at \u2018Abb\u0101s",
    "gn:population":0,
    "gn:timezone":"Africa/Cairo",
    "iso:country":"EG",
    "name:ara_x_preferred":[
        "\u0645\u0646\u0634\u0627\u0629 \u0639\u0628\u0627\u0633"
    ],
    "name:und_x_variant":[
        "Munsha\u2019at \u2018Abb\u0101s",
        "Minsh\u0101t \u2018Abb\u0101s"
    ],
    "wof:name":"Munsha'at `Abbas",
    "wof:placetype":"locality"
},
  "geometry": {"coordinates":[30.8744,31.26124],"type":"Point"}
}