{
  "type": "Feature",
  "properties": {
    "gn:admin1_code":"14",
    "gn:asciiname":"`Izbat `Ilwayat ash Shaqaf",
    "gn:country_code":"EG",
    "gn:dem":10,
    "gn:feature_class":"P",
    "gn:feature_code":"PPL",
    "gn:name":"\u2018Izbat \u2018Ilw\u0101yat ash Shaqaf",
    "gn:population":0,
    "gn:timezone":"Africa/Cairo",
    "iso:country":"EG",
    "name:ara_x_preferred":[
        "\u0639\u0632\u0628\u0629 \u0639\u0644\u0648\u0627\u064a\u0629 \u0627\u0644\u0634\u0642\u0641"
    ],
    "name:und_x_variant":[
        "\u2018Izbat \u2018Ilw\u0101yat ash Shaqaf"
    ],
    "wof:name":"`Izbat `Ilwayat ash Shaqaf",
    "wof:placetype":"locality"
},
  "geometry": {"coordinates":[31.59709,30.50108],"type":"Point"}
}