{
  "type": "Feature",
  "properties": {
    "gn:admin1_code":"14",
    "gn:asciiname":"`Izbat Mansur",
    "gn:country_code":"EG",
    "gn:dem":6,
    "gn:feature_class":"P",
    "gn:feature_code":"PPL",
    "gn:name":"\u2018Izbat Man\u015f\u016br",
    "gn:population":0,
    "gn:timezone":"Africa/Cairo",
    "iso:country":"EG",
    "name:ara_x_preferred":[
        "\u0639\u0632\u0628\u0629 \u0645\u0646\u0635\u0648\u0631"
    ],
    "name:und_x_variant":[
        "\u2018Izbat Man\u015f\u016br"
    ],
    "wof:name":"`Izbat Mansur",
    "wof:placetype":"locality"
},
  "geometry": {"coordinates":[31.6519,30.80466],"type":"Point"}
}