{
  "type": "Feature",
  "properties": {
    "gn:admin1_code":"21",
    "gn:asciiname":"Qaryat Sab`at `Ashar",
    "gn:country_code":"EG",
    "gn:dem":3,
    "gn:feature_class":"P",
    "gn:feature_code":"PPL",
    "gn:name":"Qaryat Sab\u2018at \u2018Ashar",
    "gn:population":0,
    "gn:timezone":"Africa/Cairo",
    "iso:country":"EG",
    "name:ara_x_preferred":[
        "\u0642\u0631\u064a\u0629 \u0661\u06f7"
    ],
    "name:ara_x_variant":[
        "\u0642\u0631\u064a\u0629 17"
    ],
    "name:und_x_variant":[
        "Qaryat Sab\u2018at \u2018Ashar",
        "Qaryat 17"
    ],
    "wof:name":"Qaryat Sab`at `Ashar",
    "wof:placetype":"locality"
},
  "geometry": {"coordinates":[31.11434,31.47864],"type":"Point"}
}