{
  "type": "Feature",
  "properties": {
    "gn:admin1_code":"14",
    "gn:asciiname":"`Izbat al Jisr",
    "gn:country_code":"EG",
    "gn:dem":12,
    "gn:feature_class":"P",
    "gn:feature_code":"PPL",
    "gn:name":"\u2018Izbat al Jisr",
    "gn:population":0,
    "gn:timezone":"Africa/Cairo",
    "iso:country":"EG",
    "name:ara_x_preferred":[
        "\u0639\u0632\u0628\u0629 \u0627\u0644\u062c\u0633\u0631"
    ],
    "name:und_x_variant":[
        "\u2018Izbat al Jisr"
    ],
    "wof:name":"`Izbat al Jisr",
    "wof:placetype":"locality"
},
  "geometry": {"coordinates":[31.69314,30.50181],"type":"Point"}
}