{
  "type": "Feature",
  "properties": {
    "gn:admin1_code":"05",
    "gn:asciiname":"`Izbat Shikarah",
    "gn:country_code":"EG",
    "gn:dem":7,
    "gn:feature_class":"P",
    "gn:feature_code":"PPL",
    "gn:name":"\u2018Izbat Sh\u012bk\u0101rah",
    "gn:population":0,
    "gn:timezone":"Africa/Cairo",
    "iso:country":"EG",
    "name:ara_x_preferred":[
        "\u0639\u0632\u0628\u0629 \u0634\u064a\u0643\u0627\u0631\u0629"
    ],
    "name:und_x_variant":[
        "\u2018Izbat Sh\u012bk\u0101rah"
    ],
    "wof:name":"`Izbat Shikarah",
    "wof:placetype":"locality"
},
  "geometry": {"coordinates":[31.16293,30.92473],"type":"Point"}
}