{
  "type": "Feature",
  "properties": {
    "gn:admin1_code":"21",
    "gn:asciiname":"Munsha'at al Jaraydah",
    "gn:country_code":"EG",
    "gn:dem":5,
    "gn:feature_class":"P",
    "gn:feature_code":"PPL",
    "gn:name":"Munsha\u2019at al Jar\u0101ydah",
    "gn:population":0,
    "gn:timezone":"Africa/Cairo",
    "iso:country":"EG",
    "name:ara_x_preferred":[
        "\u0645\u0646\u0634\u0623\u0629 \u0627\u0644\u062c\u0631\u0627\u064a\u062f\u0629"
    ],
    "name:und_x_variant":[
        "Munsha\u2019at al Jar\u0101ydah"
    ],
    "wof:name":"Munsha'at al Jaraydah",
    "wof:placetype":"locality"
},
  "geometry": {"coordinates":[31.25531,31.25676],"type":"Point"}
}