{
  "type": "Feature",
  "properties": {
    "gn:admin1_code":"21",
    "gn:asciiname":"`Izbat ash Sharaqiwah al Qibliyah",
    "gn:country_code":"EG",
    "gn:dem":4,
    "gn:feature_class":"P",
    "gn:feature_code":"PPL",
    "gn:name":"\u2018Izbat ash Shar\u0101qiwah al Qibl\u012byah",
    "gn:population":0,
    "gn:timezone":"Africa/Cairo",
    "iso:country":"EG",
    "name:ara_x_preferred":[
        "\u0639\u0632\u0628\u0629 \u0627\u0644\u0634\u0631\u0627\u0642\u0648\u0629 \u0627\u0644\u0642\u0628\u0644\u064a\u0629"
    ],
    "name:und_x_variant":[
        "\u2018Ezbet el-Shar\u00e2qwa",
        "\u2018Izbat ash Shar\u0101qwah al Qibl\u012byah",
        "\u2018Izbat ash Shar\u0101qiwah al Qibl\u012byah"
    ],
    "wof:name":"`Izbat ash Sharaqiwah al Qibliyah",
    "wof:placetype":"locality"
},
  "geometry": {"coordinates":[30.77256,31.33645],"type":"Point"}
}