{
  "type": "Feature",
  "properties": {
    "gn:admin1_code":"14",
    "gn:asciiname":"Kafr ad Daya'ibah",
    "gn:country_code":"EG",
    "gn:dem":7,
    "gn:feature_class":"P",
    "gn:feature_code":"PPL",
    "gn:name":"Kafr ad Day\u0101\u2019ibah",
    "gn:population":0,
    "gn:timezone":"Africa/Cairo",
    "iso:country":"EG",
    "name:und_x_variant":[
        "Kafr el-Day\u00e2yba",
        "Kafr ad Day\u0101\u2019ibah"
    ],
    "wof:name":"Kafr ad Daya'ibah",
    "wof:placetype":"locality"
},
  "geometry": {"coordinates":[31.71639,30.63361],"type":"Point"}
}