{
  "type": "Feature",
  "properties": {
    "iso:country":"EG",
    "name:ara_x_preferred":[
        "\u0645\u0631\u0643\u0632 \u0646\u062c\u0639 \u062d\u0645\u0627\u062f\u064a"
    ],
    "name:eng_x_preferred":[
        "Nagaa Hamadi Centre"
    ],
    "qs:gn_pop":0,
    "qs:name":"\u0645\u0631\u0643\u0632 \u0646\u062c\u0639 \u062d\u0645\u0627\u062f\u064a",
    "qs:name_adm0":"\u0645\u0635\u0631",
    "qs:name_adm1":"\u0642\u0646\u0627",
    "qs:photos":63,
    "qs:photos_1k":13,
    "qs:photos_9k":1,
    "qs:photos_9r":2,
    "qs:photos_all":63,
    "qs:photos_sr":2,
    "qs:placetype":"Town",
    "qs:pop_sr":"0",
    "qs:woe_adm0":23424802,
    "wof:name":"Nagaa Hamadi Centre",
    "wof:placetype":"locality"
},
  "geometry": {"coordinates":[32.240753,26.053698],"type":"Point"}
}