{
  "type": "Feature",
  "properties": {
    "gn:admin1_code":"05",
    "gn:asciiname":"Shubra an Nunah",
    "gn:country_code":"EG",
    "gn:dem":8,
    "gn:feature_class":"P",
    "gn:feature_code":"PPL",
    "gn:name":"Shubr\u0101 an N\u016bnah",
    "gn:population":0,
    "gn:timezone":"Africa/Cairo",
    "iso:country":"EG",
    "name:und_x_variant":[
        "Shubra el-N\u00fbna",
        "Shubra en-N\u00fbna",
        "Shubr\u0101 an N\u016bnah"
    ],
    "wof:name":"Shubra an Nunah",
    "wof:placetype":"locality"
},
  "geometry": {"coordinates":[30.59334,30.91844],"type":"Point"}
}