{
  "type": "Feature",
  "properties": {
    "gn:admin1_code":"24",
    "gn:asciiname":"Ash Shaykh Yusuf",
    "gn:country_code":"EG",
    "gn:dem":66,
    "gn:feature_class":"P",
    "gn:feature_code":"PPL",
    "gn:name":"Ash Shaykh Y\u016bsuf",
    "gn:population":0,
    "gn:timezone":"Africa/Cairo",
    "iso:country":"EG",
    "name:und_x_variant":[
        "El Sheikh Y\u00fbsef",
        "Ash Shaykh Y\u016bsuf"
    ],
    "wof:name":"Ash Shaykh Yusuf",
    "wof:placetype":"locality"
},
  "geometry": {"coordinates":[31.63077,26.63909],"type":"Point"}
}