{
  "type": "Feature",
  "properties": {
    "gn:admin1_code":"01",
    "gn:asciiname":"Dinjaway",
    "gn:country_code":"EG",
    "gn:dem":10,
    "gn:feature_class":"P",
    "gn:feature_code":"PPL",
    "gn:name":"Dinjaw\u0101y",
    "gn:population":0,
    "gn:timezone":"Africa/Cairo",
    "iso:country":"EG",
    "name:ara_x_preferred":[
        "\u062f\u0646\u062c\u0648\u0627\u064a"
    ],
    "name:und_x_variant":[
        "Dengaw\u00e2i",
        "Dinjaw\u0101y"
    ],
    "wof:name":"Dinjaway",
    "wof:placetype":"locality"
},
  "geometry": {"coordinates":[31.5484,31.18899],"type":"Point"}
}