{
  "type": "Feature",
  "properties": {
    "gn:admin1_code":"17",
    "gn:asciiname":"Al `Udar",
    "gn:country_code":"EG",
    "gn:dem":54,
    "gn:feature_class":"P",
    "gn:feature_code":"PPL",
    "gn:name":"Al \u2018Udar",
    "gn:population":0,
    "gn:timezone":"Africa/Cairo",
    "iso:country":"EG",
    "wof:name":"Al `Udar",
    "wof:placetype":"locality"
},
  "geometry": {"coordinates":[31.10222000000001,27.24389],"type":"Point"}
}