{
  "type": "Feature",
  "properties": {
    "gn:admin1_code":"01",
    "gn:asciiname":"`Izbat al Halbuni",
    "gn:country_code":"EG",
    "gn:dem":4,
    "gn:feature_class":"P",
    "gn:feature_code":"PPL",
    "gn:name":"\u2018Izbat al \u1e28alb\u016bni",
    "gn:population":0,
    "gn:timezone":"Africa/Cairo",
    "iso:country":"EG",
    "name:ara_x_preferred":[
        "\u0639\u0632\u0628\u0629 \u0627\u0644\u062d\u0644\u0628\u0648\u0646\u064a"
    ],
    "name:und_x_variant":[
        "\u2018Izbat al \u1e28alb\u016bni"
    ],
    "wof:name":"`Izbat al Halbuni",
    "wof:placetype":"locality"
},
  "geometry": {"coordinates":[31.51783,31.3035],"type":"Point"}
}