{
  "type": "Feature",
  "properties": {
    "gn:admin1_code":"04",
    "gn:asciiname":"`Izbat Ahmad Basha",
    "gn:country_code":"EG",
    "gn:dem":13,
    "gn:feature_class":"P",
    "gn:feature_code":"PPL",
    "gn:name":"\u2018Izbat A\u1e29mad B\u0101sh\u0101",
    "gn:population":0,
    "gn:timezone":"Africa/Cairo",
    "iso:country":"EG",
    "wof:name":"`Izbat Ahmad Basha",
    "wof:placetype":"locality"
},
  "geometry": {"coordinates":[30.83753,29.18812],"type":"Point"}
}