{
  "type": "Feature",
  "properties": {
    "gn:admin1_code":"04",
    "gn:asciiname":"Ad Dawaltah",
    "gn:cc2":"EG",
    "gn:country_code":"EG",
    "gn:dem":29,
    "gn:feature_class":"P",
    "gn:feature_code":"PPL",
    "gn:name":"Ad Daw\u0101l\u0163ah",
    "gn:population":0,
    "gn:timezone":"Africa/Cairo",
    "iso:country":"EG",
    "name:und_x_variant":[
        "El Daw\u00e2lta",
        "Ad Daw\u0101li\u0163ah",
        "Ad Daw\u0101l\u0163ah"
    ],
    "wof:name":"Ad Dawaltah",
    "wof:placetype":"locality"
},
  "geometry": {"coordinates":[31.04722000000001,29.06944],"type":"Point"}
}