{
  "type": "Feature",
  "properties": {
    "gn:admin1_code":"05",
    "gn:asciiname":"Al Farastaq",
    "gn:country_code":"EG",
    "gn:dem":13,
    "gn:feature_class":"P",
    "gn:feature_code":"PPL",
    "gn:name":"Al Farastaq",
    "gn:population":0,
    "gn:timezone":"Africa/Cairo",
    "iso:country":"EG",
    "name:und_x_variant":[
        "El-Farastaq",
        "Al Farastaq"
    ],
    "wof:name":"Al Farastaq",
    "wof:placetype":"locality"
},
  "geometry": {"coordinates":[30.7808,30.91053],"type":"Point"}
}