{
  "type": "Feature",
  "properties": {
    "gn:admin1_code":"16",
    "gn:asciiname":"Naj` Suhayl Gharb",
    "gn:country_code":"EG",
    "gn:dem":111,
    "gn:feature_class":"P",
    "gn:feature_code":"PPL",
    "gn:name":"Naj\u2018 Suhayl Gharb",
    "gn:population":0,
    "gn:timezone":"Africa/Cairo",
    "iso:country":"EG",
    "name:und_x_variant":[
        "Nug\u00fb\u2018 Gharb Siheil",
        "Nag\u2018 Siheil Gharb",
        "W\u00e2di K\u00fbki",
        "Naj Suhayl Ghaib",
        "Nag\u2018 Gharb Siheil",
        "Naj\u2018 Suhayl Gharb"
    ],
    "wof:name":"Naj` Suhayl Gharb",
    "wof:placetype":"locality"
},
  "geometry": {"coordinates":[32.86004000000001,24.0548],"type":"Point"}
}