{
  "type": "Feature",
  "properties": {
    "gn:admin1_code":"14",
    "gn:asciiname":"`Izbat Abu Hazin",
    "gn:country_code":"EG",
    "gn:dem":13,
    "gn:feature_class":"P",
    "gn:feature_code":"PPL",
    "gn:name":"\u2018Izbat Ab\u016b \u1e28az\u012bn",
    "gn:population":0,
    "gn:timezone":"Africa/Cairo",
    "iso:country":"EG",
    "name:ara_x_preferred":[
        "\u0639\u0632\u0628\u0629 \u0623\u0628\u0648 \u062d\u0632\u064a\u0646"
    ],
    "name:und_x_variant":[
        "\u2018Izbat Ab\u016b \u1e28az\u012bn"
    ],
    "wof:name":"`Izbat Abu Hazin",
    "wof:placetype":"locality"
},
  "geometry": {"coordinates":[31.64456,30.48273],"type":"Point"}
}