{
  "type": "Feature",
  "properties": {
    "iso:country":"EG",
    "name:unk_x_variant":[
        "Ibshawai"
    ],
    "qs:gn_country":"EG",
    "qs:gn_fcode":"PPL",
    "qs:gn_pop":51173,
    "qs:name":"Ibshaway",
    "qs:name_adm0":"\u0645\u0635\u0631",
    "qs:name_adm1":"\u0627\u0644\u0641\u064a\u0648\u0645",
    "qs:photos":0,
    "qs:photos_1k":0,
    "qs:photos_9k":1,
    "qs:photos_9r":1,
    "qs:photos_all":7,
    "qs:photos_sr":0,
    "qs:placetype":"Town",
    "qs:pop_sr":"8",
    "qs:woe_adm0":23424802,
    "wof:name":"Ibshaway",
    "wof:placetype":"locality",
    "wof:population":51173
},
  "geometry": {"coordinates":[30.68142,29.35804],"type":"Point"}
}