{
  "type": "Feature",
  "properties": {
    "gn:admin1_code":"01",
    "gn:asciiname":"`Izbat Abu Isma`il",
    "gn:country_code":"EG",
    "gn:dem":8,
    "gn:feature_class":"P",
    "gn:feature_code":"PPL",
    "gn:name":"\u2018Izbat Ab\u016b Ism\u0101\u2018\u012bl",
    "gn:population":0,
    "gn:timezone":"Africa/Cairo",
    "iso:country":"EG",
    "name:ara_x_preferred":[
        "\u0639\u0632\u0628\u0629 \u0623\u0628\u0648 \u0623\u0633\u0645\u0627\u0639\u064a\u0644"
    ],
    "name:und_x_variant":[
        "\u2018Izbat Ab\u016b Ism\u0101\u2018\u012bl",
        "\u2018Iz. Ab\u016b Ism\u0101\u2018\u012bl"
    ],
    "wof:name":"`Izbat Abu Isma`il",
    "wof:placetype":"locality"
},
  "geometry": {"coordinates":[31.46416,30.8999],"type":"Point"}
}