{
  "type": "Feature",
  "properties": {
    "gn:admin1_code":"01",
    "gn:asciiname":"`Izbat al Balatini",
    "gn:country_code":"EG",
    "gn:dem":9,
    "gn:feature_class":"P",
    "gn:feature_code":"PPL",
    "gn:name":"\u2018Izbat al Bal\u0101\u0163\u012bn\u012b",
    "gn:population":0,
    "gn:timezone":"Africa/Cairo",
    "iso:country":"EG",
    "name:ara_x_preferred":[
        "\u0639\u0632\u0628\u0629 \u0627\u0644\u0628\u0644\u0627\u0637\u064a\u0646\u064a"
    ],
    "name:und_x_variant":[
        "\u2018Izbat al Bal\u0101\u0163\u012bn\u012b"
    ],
    "wof:name":"`Izbat al Balatini",
    "wof:placetype":"locality"
},
  "geometry": {"coordinates":[31.35598,30.65513],"type":"Point"}
}