{
  "type": "Feature",
  "properties": {
    "gn:admin1_code":"20",
    "gn:asciiname":"`Izbat at Tawfiqiyah Ithnan",
    "gn:country_code":"EG",
    "gn:dem":5,
    "gn:feature_class":"P",
    "gn:feature_code":"PPL",
    "gn:name":"\u2018Izbat at Tawf\u012bq\u012byah Ithn\u0101n",
    "gn:population":0,
    "gn:timezone":"Africa/Cairo",
    "iso:country":"EG",
    "name:ara_x_preferred":[
        "\u0639\u0632\u0628\u0629 \u0627\u0644\u062a\u0648\u0641\u064a\u0642\u064a\u0629 \u0662"
    ],
    "name:und_x_variant":[
        "\u2018Izbat at Tawf\u012bq\u012byah Ithn\u0101n",
        "\u2018Izbat at Tawf\u012bq\u012byah 2"
    ],
    "wof:name":"`Izbat at Tawfiqiyah Ithnan",
    "wof:placetype":"locality"
},
  "geometry": {"coordinates":[31.68832,31.38906],"type":"Point"}
}