{
  "type": "Feature",
  "properties": {
    "gn:admin1_code":"09",
    "gn:asciiname":"Kafr Mujahid",
    "gn:cc2":"EG",
    "gn:country_code":"EG",
    "gn:dem":12,
    "gn:feature_class":"P",
    "gn:feature_code":"PPL",
    "gn:name":"Kafr Muj\u0101hid",
    "gn:population":0,
    "gn:timezone":"Africa/Cairo",
    "iso:country":"EG",
    "name:und_x_variant":[
        "Kafr Mig\u00e2hid",
        "Kafr Muj\u0101hid"
    ],
    "wof:name":"Kafr Mujahid",
    "wof:placetype":"locality"
},
  "geometry": {"coordinates":[30.96667,30.35],"type":"Point"}
}