{
  "type": "Feature",
  "properties": {
    "gn:admin1_code":"27",
    "gn:asciiname":"As Sakasikah",
    "gn:country_code":"EG",
    "gn:dem":20,
    "gn:feature_class":"P",
    "gn:feature_code":"PPL",
    "gn:name":"As Sak\u0101sikah",
    "gn:population":0,
    "gn:timezone":"Africa/Cairo",
    "iso:country":"EG",
    "name:ara_x_preferred":[
        "\u0627\u0644\u0633\u0643\u0627\u0633\u0643\u0629"
    ],
    "name:und_x_variant":[
        "Skaska",
        "As Sak\u0101sikah"
    ],
    "wof:name":"As Sakasikah",
    "wof:placetype":"locality"
},
  "geometry": {"coordinates":[33.88361,31.14462],"type":"Point"}
}