{
  "type": "Feature",
  "properties": {
    "gn:admin1_code":"14",
    "gn:asciiname":"Manshiyat Abu `Abdun",
    "gn:country_code":"EG",
    "gn:dem":9,
    "gn:feature_class":"P",
    "gn:feature_code":"PPL",
    "gn:name":"Mansh\u012byat Ab\u016b \u2018Abd\u016bn",
    "gn:population":0,
    "gn:timezone":"Africa/Cairo",
    "iso:country":"EG",
    "name:ara_x_preferred":[
        "\u0645\u0646\u0634\u064a\u0629 \u0623\u0628\u0648 \u0639\u0628\u062f\u0648\u0646"
    ],
    "name:und_x_variant":[
        "Mansh\u012byat Ab\u016b \u2018Abd\u016bn",
        "Manshiyyat Ab\u016b \u2018Abd\u016bn"
    ],
    "wof:name":"Manshiyat Abu `Abdun",
    "wof:placetype":"locality"
},
  "geometry": {"coordinates":[31.81718,30.73817],"type":"Point"}
}