{
  "type": "Feature",
  "properties": {
    "gn:admin1_code":"03",
    "gn:asciiname":"`Izbat al Ahmad `Abd ar Rida",
    "gn:country_code":"EG",
    "gn:dem":0,
    "gn:feature_class":"P",
    "gn:feature_code":"PPL",
    "gn:name":"\u2018Izbat al A\u1e29mad \u2018Abd ar Ri\u1e11\u00e1",
    "gn:population":0,
    "gn:timezone":"Africa/Cairo",
    "iso:country":"EG",
    "name:ara_x_preferred":[
        "\u0639\u0632\u0628\u0629 \u0623\u062d\u0645\u062f \u0639\u0628\u062f \u0627\u0644\u0631\u0636\u0649"
    ],
    "name:und_x_variant":[
        "\u2018Izbat al A\u1e29mad \u2018Abd ar Ri\u1e11\u00e1",
        "\u2018Izbat A\u1e29mad Ab\u016b ar Ri\u1e11\u00e1"
    ],
    "wof:name":"`Izbat al Ahmad `Abd ar Rida",
    "wof:placetype":"locality"
},
  "geometry": {"coordinates":[30.45686,31.27086],"type":"Point"}
}