{
  "type": "Feature",
  "properties": {
    "gn:admin1_code":"14",
    "gn:asciiname":"`Izbat al Baz",
    "gn:country_code":"EG",
    "gn:dem":9,
    "gn:feature_class":"P",
    "gn:feature_code":"PPL",
    "gn:name":"\u2018Izbat al B\u0101z",
    "gn:population":0,
    "gn:timezone":"Africa/Cairo",
    "iso:country":"EG",
    "name:ara_x_preferred":[
        "\u0639\u0632\u0628\u0629 \u0627\u0644\u0628\u0627\u0632"
    ],
    "name:und_x_variant":[
        "\u2018Izbat al B\u0101z"
    ],
    "wof:name":"`Izbat al Baz",
    "wof:placetype":"locality"
},
  "geometry": {"coordinates":[31.56036,30.81095],"type":"Point"}
}