{
  "type": "Feature",
  "properties": {
    "gn:admin1_code":"14",
    "gn:asciiname":"Kafr ash Shaykh Musa `Umran",
    "gn:country_code":"EG",
    "gn:dem":8,
    "gn:feature_class":"P",
    "gn:feature_code":"PPL",
    "gn:name":"Kafr ash Shaykh M\u016bs\u00e1 \u2018Umr\u0101n",
    "gn:population":0,
    "gn:timezone":"Africa/Cairo",
    "iso:country":"EG",
    "name:und_x_variant":[
        "Kafr el-Sheikh M\u00fbsa \u2018Imr\u00e2n",
        "Kafr ash Shaykh M\u016bs\u00e1 \u2018Umr\u0101n"
    ],
    "wof:name":"Kafr ash Shaykh Musa `Umran",
    "wof:placetype":"locality"
},
  "geometry": {"coordinates":[31.62861,30.61667000000001],"type":"Point"}
}