{
  "type": "Feature",
  "properties": {
    "gn:admin1_code":"18",
    "gn:asciiname":"`Ezbet el-Mailahiya",
    "gn:country_code":"EG",
    "gn:dem":30,
    "gn:feature_class":"P",
    "gn:feature_code":"PPL",
    "gn:name":"\u2018Ezbet el-Mail\u00e2h\u00eeya",
    "gn:population":0,
    "gn:timezone":"Africa/Cairo",
    "iso:country":"EG",
    "wof:name":"`Ezbet el-Mailahiya",
    "wof:placetype":"locality"
},
  "geometry": {"coordinates":[31.01667,28.98333],"type":"Point"}
}