{
  "type": "Feature",
  "properties": {
    "gn:admin1_code":"14",
    "gn:asciiname":"`Izbat as Sarraf",
    "gn:country_code":"EG",
    "gn:dem":9,
    "gn:feature_class":"P",
    "gn:feature_code":"PPL",
    "gn:name":"\u2018Izbat a\u015f \u015earr\u0101f",
    "gn:population":0,
    "gn:timezone":"Africa/Cairo",
    "iso:country":"EG",
    "name:ara_x_preferred":[
        "\u0639\u0632\u0628\u0629 \u0627\u0644\u0635\u0631\u0627\u0641"
    ],
    "name:und_x_variant":[
        "\u2018Izbat a\u015f \u015earr\u0101f"
    ],
    "wof:name":"`Izbat as Sarraf",
    "wof:placetype":"locality"
},
  "geometry": {"coordinates":[31.67807,30.50887],"type":"Point"}
}