{
  "type": "Feature",
  "properties": {
    "gn:admin1_code":"03",
    "gn:asciiname":"Al `Akrishah",
    "gn:country_code":"EG",
    "gn:dem":0,
    "gn:feature_class":"P",
    "gn:feature_code":"PPL",
    "gn:name":"Al \u2018Akr\u012bshah",
    "gn:population":0,
    "gn:timezone":"Africa/Cairo",
    "iso:country":"EG",
    "name:ara_x_preferred":[
        "\u0627\u0644\u0639\u0643\u0631\u064a\u0634\u0629"
    ],
    "name:und_x_variant":[
        "El-\u2018Akr\u00eesha",
        "Al \u2018Akr\u012bshah"
    ],
    "wof:name":"Al `Akrishah",
    "wof:placetype":"locality"
},
  "geometry": {"coordinates":[30.14467,31.13123],"type":"Point"}
}