{
  "type": "Feature",
  "properties": {
    "gn:admin1_code":"21",
    "gn:asciiname":"Qaryah Raqm Sittah wa Arba`un",
    "gn:country_code":"EG",
    "gn:dem":4,
    "gn:feature_class":"P",
    "gn:feature_code":"PPL",
    "gn:name":"Qaryah Raqm Sittah wa Arba\u2018\u016bn",
    "gn:population":0,
    "gn:timezone":"Africa/Cairo",
    "iso:country":"EG",
    "name:ara_x_preferred":[
        "\u0642\u0631\u064a\u0629 \u0631\u0642\u0645 \u0664\u0666"
    ],
    "name:ara_x_variant":[
        "\u0642\u0631\u064a\u0629 \u0631\u0642\u0645 46"
    ],
    "name:und_x_variant":[
        "Qaryah Raqm Sittah wa Arba\u2018\u016bn",
        "Qaryah Raqm 46"
    ],
    "wof:name":"Qaryah Raqm Sittah wa Arba`un",
    "wof:placetype":"locality"
},
  "geometry": {"coordinates":[31.20859,31.42475],"type":"Point"}
}