{
  "type": "Feature",
  "properties": {
    "gn:admin1_code":"01",
    "gn:asciiname":"Kafr Dumayah al Jadid",
    "gn:country_code":"EG",
    "gn:dem":12,
    "gn:feature_class":"P",
    "gn:feature_code":"PPL",
    "gn:name":"Kafr Dumayah al Jad\u012bd",
    "gn:population":0,
    "gn:timezone":"Africa/Cairo",
    "iso:country":"EG",
    "name:ara_x_preferred":[
        "\u0643\u0641\u0631 \u062f\u0645\u064a\u0631\u0629 \u0627\u0644\u062c\u062f\u064a\u062f"
    ],
    "name:und_x_variant":[
        "Kafr Dimeira el-Ged\u00eed",
        "Kafr Dumayrah al-Jad\u012bd",
        "Kafr Dumayah al Jad\u012bd"
    ],
    "wof:name":"Kafr Dumayah al Jadid",
    "wof:placetype":"locality"
},
  "geometry": {"coordinates":[31.37203,31.14857],"type":"Point"}
}