{
  "type": "Feature",
  "properties": {
    "gn:admin1_code":"05",
    "gn:asciiname":"Kalbishu",
    "gn:cc2":"EG",
    "gn:country_code":"EG",
    "gn:dem":16,
    "gn:feature_class":"P",
    "gn:feature_code":"PPL",
    "gn:name":"Kalbish\u016b",
    "gn:population":0,
    "gn:timezone":"Africa/Cairo",
    "iso:country":"EG",
    "name:und_x_variant":[
        "Kaibishu",
        "Kalbish\u016b"
    ],
    "wof:name":"Kalbishu",
    "wof:placetype":"locality"
},
  "geometry": {"coordinates":[31.06917,30.66278],"type":"Point"}
}