{
  "type": "Feature",
  "properties": {
    "gn:admin1_code":"01",
    "gn:asciiname":"`Izbat Sattutah",
    "gn:country_code":"EG",
    "gn:dem":6,
    "gn:feature_class":"P",
    "gn:feature_code":"PPL",
    "gn:name":"\u2018Izbat Satt\u016btah",
    "gn:population":0,
    "gn:timezone":"Africa/Cairo",
    "iso:country":"EG",
    "name:ara_x_preferred":[
        "\u0639\u0632\u0628\u0629 \u0633\u062a\u0648\u062a\u0629"
    ],
    "name:ara_x_variant":[
        "Y\u016bsuf",
        "\u064a\u0648\u0633\u0641"
    ],
    "name:und_x_variant":[
        "\u2018Izbat Satt\u016btah",
        "Y\u016bsif"
    ],
    "wof:name":"`Izbat Sattutah",
    "wof:placetype":"locality"
},
  "geometry": {"coordinates":[31.45942,31.18838],"type":"Point"}
}