{
  "type": "Feature",
  "properties": {
    "gn:admin1_code":"03",
    "gn:asciiname":"Al Imam al Ghazali",
    "gn:country_code":"EG",
    "gn:dem":19,
    "gn:feature_class":"P",
    "gn:feature_code":"PPL",
    "gn:name":"Al Im\u0101m al Ghaz\u0101l\u012b",
    "gn:population":0,
    "gn:timezone":"Africa/Cairo",
    "iso:country":"EG",
    "name:und_x_variant":[
        "El-Im\u00e2m el-Ghaz\u00e2li",
        "Al Im\u0101m al Ghaz\u0101l\u012b"
    ],
    "wof:name":"Al Imam al Ghazali",
    "wof:placetype":"locality"
},
  "geometry": {"coordinates":[30.37811,30.69247],"type":"Point"}
}