{
  "type": "Feature",
  "properties": {
    "gn:admin1_code":"14",
    "gn:asciiname":"Kafr al Hajj Hasan",
    "gn:country_code":"EG",
    "gn:dem":10,
    "gn:feature_class":"P",
    "gn:feature_code":"PPL",
    "gn:name":"Kafr al \u1e28\u0101jj \u1e28asan",
    "gn:population":0,
    "gn:timezone":"Africa/Cairo",
    "iso:country":"EG",
    "name:ara_x_preferred":[
        "\u0643\u0641\u0631 \u0627\u0644\u062d\u0627\u062c \u062d\u0633\u0646"
    ],
    "name:und_x_variant":[
        "Kafr el-\u1e24agg \u1e24asan",
        "Kafr al \u1e28\u0101jj \u1e28asan",
        "Kafr al-\u1e24\u0101jj \u1e24asan"
    ],
    "wof:name":"Kafr al Hajj Hasan",
    "wof:placetype":"locality"
},
  "geometry": {"coordinates":[31.48963,30.78628],"type":"Point"}
}