{
  "type": "Feature",
  "properties": {
    "gn:admin1_code":"14",
    "gn:asciiname":"`Izbat Abu Taha",
    "gn:country_code":"EG",
    "gn:dem":13,
    "gn:feature_class":"P",
    "gn:feature_code":"PPL",
    "gn:name":"\u2018Izbat Ab\u016b \u0162\u0101h\u0101",
    "gn:population":0,
    "gn:timezone":"Africa/Cairo",
    "iso:country":"EG",
    "name:ara_x_preferred":[
        "\u0639\u0632\u0628\u0629 \u0623\u0628\u0648 \u0637\u0647"
    ],
    "name:und_x_variant":[
        "\u2018Izbat Ab\u016b \u0162\u0101h\u0101",
        "\u2018Izbat Ab\u016b \u0162aha"
    ],
    "wof:name":"`Izbat Abu Taha",
    "wof:placetype":"locality"
},
  "geometry": {"coordinates":[31.5416,30.61527],"type":"Point"}
}