{
  "type": "Feature",
  "properties": {
    "gn:admin1_code":"14",
    "gn:asciiname":"`Izbat Abu Kurum",
    "gn:country_code":"EG",
    "gn:dem":12,
    "gn:feature_class":"P",
    "gn:feature_code":"PPL",
    "gn:name":"\u2018Izbat Ab\u016b Kur\u016bm",
    "gn:population":0,
    "gn:timezone":"Africa/Cairo",
    "iso:country":"EG",
    "name:ara_x_preferred":[
        "\u0639\u0632\u0628\u0629 \u0623\u0628\u0648 \u0643\u0631\u0648\u0645"
    ],
    "name:und_x_variant":[
        "\u2018Izbat Ab\u016b Kur\u016bm"
    ],
    "wof:name":"`Izbat Abu Kurum",
    "wof:placetype":"locality"
},
  "geometry": {"coordinates":[31.99652,30.53952],"type":"Point"}
}