{
  "type": "Feature",
  "properties": {
    "gn:admin1_code":"21",
    "gn:asciiname":"Kafr as Sudan",
    "gn:country_code":"EG",
    "gn:dem":6,
    "gn:feature_class":"P",
    "gn:feature_code":"PPL",
    "gn:name":"Kafr as S\u016bd\u0101n",
    "gn:population":0,
    "gn:timezone":"Africa/Cairo",
    "iso:country":"EG",
    "name:ara_x_preferred":[
        "\u0643\u0641\u0631 \u0627\u0644\u0633\u0648\u062f\u0627\u0646"
    ],
    "name:und_x_variant":[
        "Kafr el-S\u00fbd\u00e2n",
        "Kafr as S\u016bd\u0101n"
    ],
    "wof:name":"Kafr as Sudan",
    "wof:placetype":"locality"
},
  "geometry": {"coordinates":[30.62808,31.17928],"type":"Point"}
}