{
  "type": "Feature",
  "properties": {
    "gn:admin1_code":"23",
    "gn:asciiname":"Abu Dhi'ab",
    "gn:country_code":"EG",
    "gn:dem":73,
    "gn:feature_class":"P",
    "gn:feature_code":"PPL",
    "gn:name":"Ab\u016b Dhi\u2019\u0101b",
    "gn:population":0,
    "gn:timezone":"Africa/Cairo",
    "iso:country":"EG",
    "name:und_x_variant":[
        "Abu Diy\u00e2b",
        "Ab\u016b Dhi\u2019\u0101b"
    ],
    "wof:name":"Abu Dhi'ab",
    "wof:placetype":"locality"
},
  "geometry": {"coordinates":[32.55,26.18333],"type":"Point"}
}