{
  "type": "Feature",
  "properties": {
    "gn:admin1_code":"24",
    "gn:asciiname":"Ar Rayayinah al Mu`allaq",
    "gn:country_code":"EG",
    "gn:dem":62,
    "gn:feature_class":"P",
    "gn:feature_code":"PPL",
    "gn:name":"Ar Ray\u0101yinah al Mu\u2018allaq",
    "gn:population":0,
    "gn:timezone":"Africa/Cairo",
    "iso:country":"EG",
    "name:und_x_variant":[
        "Ar Ray\u0101yinah al Mu\u2018allaq",
        "El Rayayna el Mi\u2018allaq",
        "Er Ray\u0101ina el Mi\u2018allaq",
        "Ar Ray\u0101ynah al Mi\u2018allaq"
    ],
    "wof:name":"Ar Rayayinah al Mu`allaq",
    "wof:placetype":"locality"
},
  "geometry": {"coordinates":[31.40391,26.89815],"type":"Point"}
}