{
  "type": "Feature",
  "properties": {
    "gn:admin1_code":"21",
    "gn:asciiname":"`Izbah Raqm Ithna `Ashar",
    "gn:country_code":"EG",
    "gn:dem":2,
    "gn:feature_class":"P",
    "gn:feature_code":"PPL",
    "gn:name":"\u2018Izbah Raqm Ithn\u0101 \u2018Ashar",
    "gn:population":0,
    "gn:timezone":"Africa/Cairo",
    "iso:country":"EG",
    "name:ara_x_preferred":[
        "\u0639\u0632\u0628\u0629 \u0631\u0642\u0645 \u0661\u0662"
    ],
    "name:ara_x_variant":[
        "\u0639\u0632\u0628\u0629 \u0631\u0642\u0645 12"
    ],
    "name:und_x_variant":[
        "\u2018Izbah Raqm Ithn\u0101 \u2018Ashar",
        "\u2018Izbah Raqm 12"
    ],
    "wof:name":"`Izbah Raqm Ithna `Ashar",
    "wof:placetype":"locality"
},
  "geometry": {"coordinates":[31.07575,31.40872],"type":"Point"}
}