{
  "type": "Feature",
  "properties": {
    "gn:admin1_code":"05",
    "gn:asciiname":"`Izbat `Abd Allah Mikha'il",
    "gn:country_code":"EG",
    "gn:dem":7,
    "gn:feature_class":"P",
    "gn:feature_code":"PPL",
    "gn:name":"\u2018Izbat \u2018Abd All\u0101h M\u012bkh\u0101\u2019\u012bl",
    "gn:population":0,
    "gn:timezone":"Africa/Cairo",
    "iso:country":"EG",
    "name:ara_x_preferred":[
        "\u0639\u0632\u0628\u0629 \u0639\u0628\u062f \u0627\u0644\u0644\u0647 \u0645\u064a\u062e\u0627\u0626\u064a\u0644"
    ],
    "name:und_x_variant":[
        "\u2018Izbat \u2018Abd All\u0101h M\u012bkh\u0101\u2019\u012bl",
        "\u012bl \u2018Izbat \u2018Abd All\u0101h Mikh\u0101"
    ],
    "wof:name":"`Izbat `Abd Allah Mikha'il",
    "wof:placetype":"locality"
},
  "geometry": {"coordinates":[31.09014,31.08331],"type":"Point"}
}