{
  "type": "Feature",
  "properties": {
    "gn:admin1_code":"20",
    "gn:asciiname":"`Izbat Nasir",
    "gn:country_code":"EG",
    "gn:dem":3,
    "gn:feature_class":"P",
    "gn:feature_code":"PPL",
    "gn:name":"\u2018Izbat N\u0101\u015fir",
    "gn:population":0,
    "gn:timezone":"Africa/Cairo",
    "iso:country":"EG",
    "name:ara_x_preferred":[
        "\u0639\u0632\u0628\u0629 \u0646\u0627\u0635\u0631"
    ],
    "name:und_x_variant":[
        "\u2018Izbat N\u0101\u015fir"
    ],
    "wof:name":"`Izbat Nasir",
    "wof:placetype":"locality"
},
  "geometry": {"coordinates":[31.59779,31.36805],"type":"Point"}
}