{
  "type": "Feature",
  "properties": {
    "gn:admin1_code":"05",
    "gn:asciiname":"`Izbat al `Ayyatin",
    "gn:country_code":"EG",
    "gn:dem":9,
    "gn:feature_class":"P",
    "gn:feature_code":"PPL",
    "gn:name":"\u2018Izbat al \u2018Ayy\u0101\u0163\u012bn",
    "gn:population":0,
    "gn:timezone":"Africa/Cairo",
    "iso:country":"EG",
    "name:ara_x_preferred":[
        "\u0639\u0632\u0628\u0629 \u0627\u0644\u0639\u064a\u0627\u0637\u064a\u0646"
    ],
    "name:und_x_variant":[
        "\u2018Izbat al \u2018Ayy\u0101\u0163\u012bn",
        "\u2018Izbat al-\u2018Aayy\u0101\u1e6d\u012bn"
    ],
    "wof:name":"`Izbat al `Ayyatin",
    "wof:placetype":"locality"
},
  "geometry": {"coordinates":[30.92974,30.76591],"type":"Point"}
}