{
  "type": "Feature",
  "properties": {
    "gn:admin1_code":"14.0",
    "gn:asciiname":"`Izbat al Mallahah",
    "gn:country_code":"EG",
    "gn:dem":2,
    "gn:feature_class":"P",
    "gn:feature_code":"PPL",
    "gn:name":"\u2018Izbat al Mall\u0101\u1e29ah",
    "gn:population":0,
    "gn:timezone":"Africa/Cairo",
    "iso:country":"EG",
    "name:ara_x_preferred":[
        "\u0639\u0632\u0628\u0629 \u0627\u0644\u0645\u0644\u0627\u062d\u0629"
    ],
    "name:und_x_variant":[
        "\u2018Ushash el-Mall\u00e2\u1e25a",
        "\u2018Ushash al Mall\u0101\u1e29ah",
        "\u2018Izbat al Mall\u0101\u1e29ah"
    ],
    "wof:name":"`Izbat al Mallahah",
    "wof:placetype":"locality"
},
  "geometry": {"coordinates":[32.035,31.0281],"type":"Point"}
}