{
  "type": "Feature",
  "properties": {
    "gn:admin1_code":"14",
    "gn:asciiname":"`Izbat al Hajj Sa`id Mubarak",
    "gn:country_code":"EG",
    "gn:dem":3,
    "gn:feature_class":"P",
    "gn:feature_code":"PPL",
    "gn:name":"\u2018Izbat al \u1e28ajj Sa\u2018\u012bd Mub\u0101rak",
    "gn:population":0,
    "gn:timezone":"Africa/Cairo",
    "iso:country":"EG",
    "name:ara_x_preferred":[
        "\u0639\u0632\u0628\u0629 \u0627\u0644\u062d\u0627\u062c \u0633\u0639\u064a\u062f \u0645\u0628\u0627\u0631\u0643"
    ],
    "name:und_x_variant":[
        "\u2018Izbat al \u1e28ajj Sa\u2018\u012bd Mub\u0101rak",
        "\u2018Izbat al \u1e28\u0101jj Sa\u2018\u012bd Mub\u0101rak",
        "\u2018Izbat al \u1e24ajj Sa\u2018\u012bd Mub\u0101rak"
    ],
    "wof:name":"`Izbat al Hajj Sa`id Mubarak",
    "wof:placetype":"locality"
},
  "geometry": {"coordinates":[31.93942,31.06682],"type":"Point"}
}