{
  "type": "Feature",
  "properties": {
    "gn:admin1_code":"23",
    "gn:asciiname":"`Izbat al Busah",
    "gn:country_code":"EG",
    "gn:dem":73,
    "gn:feature_class":"P",
    "gn:feature_code":"PPL",
    "gn:name":"\u2018Izbat al B\u016b\u015fah",
    "gn:population":0,
    "gn:timezone":"Africa/Cairo",
    "iso:country":"EG",
    "wof:name":"`Izbat al Busah",
    "wof:placetype":"locality"
},
  "geometry": {"coordinates":[32.30982,26.09448],"type":"Point"}
}