{
  "type": "Feature",
  "properties": {
    "gn:admin1_code":"14",
    "gn:asciiname":"`Izbat at Tawahin",
    "gn:country_code":"EG",
    "gn:dem":11,
    "gn:feature_class":"P",
    "gn:feature_code":"PPL",
    "gn:name":"\u2018Izbat a\u0163 \u0162aw\u0101\u1e29\u012bn",
    "gn:population":0,
    "gn:timezone":"Africa/Cairo",
    "iso:country":"EG",
    "name:ara_x_preferred":[
        "\u0639\u0632\u0628\u0629 \u0627\u0644\u0637\u0648\u0627\u062d\u064a\u0646"
    ],
    "name:und_x_variant":[
        "\u2018Ezbet el-Taw\u00e2h\u00een",
        "\u2018Izbat a\u0163 \u0162aw\u0101\u1e29\u012bn"
    ],
    "wof:name":"`Izbat at Tawahin",
    "wof:placetype":"locality"
},
  "geometry": {"coordinates":[31.73377,30.51594],"type":"Point"}
}