{
  "type": "Feature",
  "properties": {
    "gn:admin1_code":"03",
    "gn:asciiname":"`Izbat Shubra an Nunah ash Sharqiyah",
    "gn:country_code":"EG",
    "gn:dem":2,
    "gn:feature_class":"P",
    "gn:feature_code":"PPL",
    "gn:name":"\u2018Izbat Shubr\u0101 an N\u016bnah ash Sharq\u012byah",
    "gn:population":0,
    "gn:timezone":"Africa/Cairo",
    "iso:country":"EG",
    "wof:name":"`Izbat Shubra an Nunah ash Sharqiyah",
    "wof:placetype":"locality"
},
  "geometry": {"coordinates":[30.5375,30.93083],"type":"Point"}
}