{
  "type": "Feature",
  "properties": {
    "gn:admin1_code":"01",
    "gn:asciiname":"`Izbat al Islah ash Sharqiyah",
    "gn:country_code":"EG",
    "gn:dem":8,
    "gn:feature_class":"P",
    "gn:feature_code":"PPL",
    "gn:name":"\u2018Izbat al I\u015fl\u0101\u1e29 ash Sharq\u012byah",
    "gn:population":0,
    "gn:timezone":"Africa/Cairo",
    "iso:country":"EG",
    "name:ara_x_preferred":[
        "\u0639\u0632\u0628\u0629 \u0627\u0644\u0627\u0635\u0644\u0627\u062d \u0627\u0644\u0634\u0631\u0642\u064a\u0629"
    ],
    "name:und_x_variant":[
        "\u2018Izbat al I\u015fl\u0101\u1e29 ash Sharq\u012byah"
    ],
    "wof:name":"`Izbat al Islah ash Sharqiyah",
    "wof:placetype":"locality"
},
  "geometry": {"coordinates":[31.59843,30.98364],"type":"Point"}
}