{
  "type": "Feature",
  "properties": {
    "gn:admin1_code":"8.0",
    "gn:asciiname":"Tirsa",
    "gn:country_code":"EG",
    "gn:dem":23,
    "gn:feature_class":"P",
    "gn:feature_code":"PPL",
    "gn:name":"Tirs\u0101",
    "gn:population":0,
    "gn:timezone":"Africa/Cairo",
    "iso:country":"EG",
    "name:cat_x_preferred":[
        "Tirsa"
    ],
    "name:und_x_variant":[
        "Tersa",
        "Tirs\u0101"
    ],
    "name:vie_x_preferred":[
        "Tirsa"
    ],
    "wof:name":"Tirsa",
    "wof:placetype":"locality"
},
  "geometry": {"coordinates":[31.20682,29.97003],"type":"Point"}
}