{
  "type": "Feature",
  "properties": {
    "gn:admin1_code":"03",
    "gn:asciiname":"`Izbat Abu ad Dud",
    "gn:country_code":"EG",
    "gn:dem":2,
    "gn:feature_class":"P",
    "gn:feature_code":"PPL",
    "gn:name":"\u2018Izbat Ab\u016b ad D\u016bd",
    "gn:population":0,
    "gn:timezone":"Africa/Cairo",
    "iso:country":"EG",
    "name:ara_x_preferred":[
        "\u0639\u0632\u0628\u0629 \u0623\u0628\u0648 \u0627\u0644\u062f\u0648\u062f"
    ],
    "name:und_x_variant":[
        "\u2018Izbat Ab\u016b ad D\u016bd",
        "\u2018Ezbet Abu el-D\u00fbd"
    ],
    "wof:name":"`Izbat Abu ad Dud",
    "wof:placetype":"locality"
},
  "geometry": {"coordinates":[30.37065,31.0678],"type":"Point"}
}