{
  "type": "Feature",
  "properties": {
    "gn:admin1_code":"21",
    "gn:asciiname":"At Tanbawi",
    "gn:country_code":"EG",
    "gn:dem":5,
    "gn:feature_class":"P",
    "gn:feature_code":"PPL",
    "gn:name":"A\u0163 \u0162anb\u0101w\u012b",
    "gn:population":0,
    "gn:timezone":"Africa/Cairo",
    "iso:country":"EG",
    "name:ara_x_preferred":[
        "\u0627\u0644\u0637\u0646\u0628\u0627\u0648\u064a"
    ],
    "name:und_x_variant":[
        "A\u0163 \u0162anb\u0101w\u012b",
        "A\u1e6d \u1e6canb\u0101w\u012b"
    ],
    "wof:name":"At Tanbawi",
    "wof:placetype":"locality"
},
  "geometry": {"coordinates":[31.23033,31.14729],"type":"Point"}
}