{
  "type": "Feature",
  "properties": {
    "gn:admin1_code":"03",
    "gn:asciiname":"`Izbat Mihanna",
    "gn:country_code":"EG",
    "gn:dem":0,
    "gn:feature_class":"P",
    "gn:feature_code":"PPL",
    "gn:name":"\u2018Izbat Mihann\u00e1",
    "gn:population":0,
    "gn:timezone":"Africa/Cairo",
    "iso:country":"EG",
    "name:ara_x_preferred":[
        "\u0639\u0632\u0628\u0629 \u0645\u0647\u0646\u0649"
    ],
    "name:und_x_variant":[
        "\u2018Izbat Mihann\u00e1",
        "\u2018Ezbet Mihanni \u2018Abd el-R\u00e2ziq"
    ],
    "wof:name":"`Izbat Mihanna",
    "wof:placetype":"locality"
},
  "geometry": {"coordinates":[30.42585,31.23763],"type":"Point"}
}