{
  "type": "Feature",
  "properties": {
    "gn:admin1_code":"01",
    "gn:asciiname":"`Izbat `Abd al Qadir",
    "gn:country_code":"EG",
    "gn:dem":4,
    "gn:feature_class":"P",
    "gn:feature_code":"PPL",
    "gn:name":"\u2018Izbat \u2018Abd al Q\u0101dir",
    "gn:population":0,
    "gn:timezone":"Africa/Cairo",
    "iso:country":"EG",
    "name:ara_x_preferred":[
        "\u0639\u0632\u0628\u0629 \u0639\u0628\u062f \u0627\u0644\u0642\u0627\u062f\u0631"
    ],
    "name:und_x_variant":[
        "\u2018Izbat \u2018Abd al Q\u0101dir",
        "Minsh\u00e2t \u2018Abd el-Q\u00e2dir"
    ],
    "wof:name":"`Izbat `Abd al Qadir",
    "wof:placetype":"locality"
},
  "geometry": {"coordinates":[31.28705,31.31852],"type":"Point"}
}