{
  "type": "Feature",
  "properties": {
    "gn:admin1_code":"22",
    "gn:asciiname":"Kafret el Tawarsa",
    "gn:country_code":"EG",
    "gn:dem":12,
    "gn:feature_class":"P",
    "gn:feature_code":"PPL",
    "gn:name":"Kafret el Tawarsa",
    "gn:population":0,
    "gn:timezone":"Africa/Cairo",
    "iso:country":"EG",
    "name:und_x_variant":[
        "Kafret el Taw\u00e2rsa",
        "Kafret el Tawarsa"
    ],
    "wof:name":"Kafret el Tawarsa",
    "wof:placetype":"locality"
},
  "geometry": {"coordinates":[26.43365,31.50581],"type":"Point"}
}