{
  "type": "Feature",
  "properties": {
    "gn:admin1_code":"08",
    "gn:asciiname":"`Izbat al Hajr al Jadidah",
    "gn:country_code":"EG",
    "gn:dem":19,
    "gn:feature_class":"P",
    "gn:feature_code":"PPL",
    "gn:name":"\u2018Izbat al \u1e28\u0101jr al Jad\u012bdah",
    "gn:population":0,
    "gn:timezone":"Africa/Cairo",
    "iso:country":"EG",
    "name:ara_x_preferred":[
        "\u0639\u0632\u0628\u0629 \u0627\u0644\u062d\u0627\u062c\u0631 \u0627\u0644\u062c\u062f\u064a\u062f\u0629"
    ],
    "name:und_x_variant":[
        "\u2018Izbat al \u1e28\u0101jr al Jad\u012bdah",
        "\u2018Izbat al \u1e24\u0101jir al-Jad\u012bdah"
    ],
    "wof:name":"`Izbat al Hajr al Jadidah",
    "wof:placetype":"locality"
},
  "geometry": {"coordinates":[30.91843,30.27266],"type":"Point"}
}