{
  "type": "Feature",
  "properties": {
    "gn:admin1_code":"16",
    "gn:asciiname":"As Sinqari",
    "gn:cc2":"EG",
    "gn:country_code":"EG",
    "gn:dem":232,
    "gn:feature_class":"P",
    "gn:feature_code":"PPL",
    "gn:name":"As Sinq\u0101r\u012b",
    "gn:population":0,
    "gn:timezone":"Africa/Cairo",
    "iso:country":"EG",
    "name:und_x_variant":[
        "El Sinq\u00e2ri",
        "Es Sinq\u0101ri",
        "As Sinq\u0101r\u012b"
    ],
    "wof:name":"As Sinqari",
    "wof:placetype":"locality"
},
  "geometry": {"coordinates":[32.41667,22.61667000000001],"type":"Point"}
}