{
  "type": "Feature",
  "properties": {
    "gn:admin1_code":"05",
    "gn:asciiname":"Mansha'at Ramalu",
    "gn:country_code":"EG",
    "gn:dem":12,
    "gn:feature_class":"P",
    "gn:feature_code":"PPL",
    "gn:name":"Mansha\u2019at Ramal\u016b",
    "gn:population":0,
    "gn:timezone":"Africa/Cairo",
    "iso:country":"EG",
    "name:ara_x_preferred":[
        "\u0645\u0646\u0634\u0627\u0629 \u0631\u0645\u0644\u0648"
    ],
    "name:und_x_variant":[
        "Mansha\u2019at Ramal\u016b"
    ],
    "wof:name":"Mansha'at Ramalu",
    "wof:placetype":"locality"
},
  "geometry": {"coordinates":[31.161,30.51989],"type":"Point"}
}