{
  "type": "Feature",
  "properties": {
    "gn:admin1_code":"21",
    "gn:asciiname":"`Izbat Abu Husayn",
    "gn:country_code":"EG",
    "gn:dem":2,
    "gn:feature_class":"P",
    "gn:feature_code":"PPL",
    "gn:name":"\u2018Izbat Ab\u016b \u1e28usayn",
    "gn:population":0,
    "gn:timezone":"Africa/Cairo",
    "iso:country":"EG",
    "name:ara_x_preferred":[
        "\u0639\u0632\u0628\u0629 \u0623\u0628\u0648 \u062d\u0633\u064a\u0646"
    ],
    "name:und_x_variant":[
        "\u2018Izbat Ab\u016b \u1e28usayn"
    ],
    "wof:name":"`Izbat Abu Husayn",
    "wof:placetype":"locality"
},
  "geometry": {"coordinates":[30.79338,31.29797],"type":"Point"}
}