{
  "type": "Feature",
  "properties": {
    "gn:admin1_code":"03",
    "gn:asciiname":"Al Imam al Husayn",
    "gn:country_code":"EG",
    "gn:dem":17,
    "gn:feature_class":"P",
    "gn:feature_code":"PPL",
    "gn:name":"Al Im\u0101m al \u1e28usayn",
    "gn:population":0,
    "gn:timezone":"Africa/Cairo",
    "iso:country":"EG",
    "name:und_x_variant":[
        "El-Im\u00e2m el-\u1e24usein",
        "Al Im\u0101m al \u1e28usayn"
    ],
    "wof:name":"Al Imam al Husayn",
    "wof:placetype":"locality"
},
  "geometry": {"coordinates":[30.35508,30.72062],"type":"Point"}
}