{
  "type": "Feature",
  "properties": {
    "gn:admin1_code":"05",
    "gn:asciiname":"`Izbat al Burullusi",
    "gn:country_code":"EG",
    "gn:dem":12,
    "gn:feature_class":"P",
    "gn:feature_code":"PPL",
    "gn:name":"\u2018Izbat al Burullus\u012b",
    "gn:population":0,
    "gn:timezone":"Africa/Cairo",
    "iso:country":"EG",
    "name:ara_x_preferred":[
        "\u0639\u0632\u0628\u0629 \u0627\u0644\u0628\u0631\u0644\u0633\u064a"
    ],
    "name:und_x_variant":[
        "\u2018Izbat al Burullus\u012b",
        "\u2018Izbat al-Burullus\u012b"
    ],
    "wof:name":"`Izbat al Burullusi",
    "wof:placetype":"locality"
},
  "geometry": {"coordinates":[31.14475,30.94019],"type":"Point"}
}