{
  "type": "Feature",
  "properties": {
    "gn:admin1_code":"14",
    "gn:asciiname":"Kafr al Jundi",
    "gn:country_code":"EG",
    "gn:dem":11,
    "gn:feature_class":"P",
    "gn:feature_code":"PPL",
    "gn:name":"Kafr al Jund\u012b",
    "gn:population":0,
    "gn:timezone":"Africa/Cairo",
    "iso:country":"EG",
    "name:ara_x_preferred":[
        "\u0643\u0641\u0631 \u0627\u0644\u062c\u0646\u062f\u064a"
    ],
    "name:und_x_variant":[
        "Kafr al Jund\u012b",
        "Kafr al Jind\u012b"
    ],
    "wof:name":"Kafr al Jundi",
    "wof:placetype":"locality"
},
  "geometry": {"coordinates":[31.46413,30.51638],"type":"Point"}
}