{
  "type": "Feature",
  "properties": {
    "gn:admin1_code":"14",
    "gn:asciiname":"`Izbat Tadrus Hanna",
    "gn:country_code":"EG",
    "gn:dem":12,
    "gn:feature_class":"P",
    "gn:feature_code":"PPL",
    "gn:name":"\u2018Izbat T\u0101drus \u1e28ann\u0101",
    "gn:population":0,
    "gn:timezone":"Africa/Cairo",
    "iso:country":"EG",
    "name:ara_x_preferred":[
        "\u0639\u0632\u0628\u0629 \u062a\u0627\u062f\u0631\u0633 \u062d\u0646\u0627"
    ],
    "name:und_x_variant":[
        "\u2018Izbat T\u0101drus \u1e28ann\u0101"
    ],
    "wof:name":"`Izbat Tadrus Hanna",
    "wof:placetype":"locality"
},
  "geometry": {"coordinates":[31.41329,30.50458],"type":"Point"}
}