{
  "type": "Feature",
  "properties": {
    "gn:admin1_code":"24",
    "gn:asciiname":"Awlad Tuq Gharb",
    "gn:country_code":"EG",
    "gn:dem":70,
    "gn:feature_class":"P",
    "gn:feature_code":"PPL",
    "gn:name":"Awl\u0101d \u0162\u016bq Gharb",
    "gn:population":0,
    "gn:timezone":"Africa/Cairo",
    "iso:country":"EG",
    "name:und_x_variant":[
        "Awl\u0101d \u0162awq Gharb",
        "Aul\u00e2d T\u00f4q Gharb",
        "Awl\u0101d \u0162\u016bq Gharb"
    ],
    "wof:name":"Awlad Tuq Gharb",
    "wof:placetype":"locality"
},
  "geometry": {"coordinates":[32.0507,26.25519],"type":"Point"}
}