{
  "type": "Feature",
  "properties": {
    "gn:admin1_code":"09",
    "gn:asciiname":"Ibshadi",
    "gn:country_code":"EG",
    "gn:dem":13,
    "gn:feature_class":"P",
    "gn:feature_code":"PPL",
    "gn:name":"Ibsh\u0101d\u012b",
    "gn:population":0,
    "gn:timezone":"Africa/Cairo",
    "iso:country":"EG",
    "name:und_x_variant":[
        "Ibsh\u00e2d\u00ee",
        "Ibsh\u0101d\u012b"
    ],
    "wof:name":"Ibshadi",
    "wof:placetype":"locality"
},
  "geometry": {"coordinates":[30.83757,30.62446],"type":"Point"}
}