{
  "type": "Feature",
  "properties": {
    "gn:admin1_code":"03",
    "gn:asciiname":"`Izbat al Jurf",
    "gn:country_code":"EG",
    "gn:dem":0,
    "gn:feature_class":"P",
    "gn:feature_code":"PPL",
    "gn:name":"\u2018Izbat al Jurf",
    "gn:population":0,
    "gn:timezone":"Africa/Cairo",
    "iso:country":"EG",
    "name:ara_x_preferred":[
        "\u0639\u0632\u0628\u0629 \u0627\u0644\u062c\u0631\u0641"
    ],
    "name:und_x_variant":[
        "\u2018Izbat al Jurf",
        "\u2018Ezbet el-Garf"
    ],
    "wof:name":"`Izbat al Jurf",
    "wof:placetype":"locality"
},
  "geometry": {"coordinates":[30.3147,31.24713],"type":"Point"}
}