{
  "type": "Feature",
  "properties": {
    "gn:admin1_code":"04",
    "gn:asciiname":"Munsha'at `Abd al Majid",
    "gn:country_code":"EG",
    "gn:dem":13,
    "gn:feature_class":"P",
    "gn:feature_code":"PPL",
    "gn:name":"Munsha\u2019at \u2018Abd al Maj\u012bd",
    "gn:population":0,
    "gn:timezone":"Africa/Cairo",
    "iso:country":"EG",
    "name:und_x_variant":[
        "Munsha\u2019at \u2018Abd al Maj\u012bd",
        "Minsha\u2019t \u2018Abd al Maj\u012bd",
        "Minsh\u00e2t Mu\u1e25ammad Abd el Mag\u00eed",
        "Danyal el Bahar\u00eeya",
        "Minsh\u0101t \u2018Abd al Maj\u012bd"
    ],
    "wof:name":"Munsha'at `Abd al Majid",
    "wof:placetype":"locality"
},
  "geometry": {"coordinates":[30.72949,29.15138],"type":"Point"}
}