{
  "type": "Feature",
  "properties": {
    "gn:admin1_code":"03",
    "gn:asciiname":"Kafr Ziyadah",
    "gn:country_code":"EG",
    "gn:dem":7,
    "gn:feature_class":"P",
    "gn:feature_code":"PPL",
    "gn:name":"Kafr Ziy\u0101dah",
    "gn:population":0,
    "gn:timezone":"Africa/Cairo",
    "iso:country":"EG",
    "name:und_x_variant":[
        "Kafr Ziy\u00e2da",
        "Kafr Ziy\u0101dah"
    ],
    "wof:name":"Kafr Ziyadah",
    "wof:placetype":"locality"
},
  "geometry": {"coordinates":[30.62644,30.75379],"type":"Point"}
}