{
  "type": "Feature",
  "properties": {
    "gn:admin1_code":"10",
    "gn:asciiname":"Saft Abu Jirj",
    "gn:country_code":"EG",
    "gn:dem":40,
    "gn:feature_class":"P",
    "gn:feature_code":"PPL",
    "gn:name":"\u015eaf\u0163 Ab\u016b Jirj",
    "gn:population":0,
    "gn:timezone":"Africa/Cairo",
    "iso:country":"EG",
    "name:und_x_variant":[
        "\u1e62af\u1e6d Abu Girg",
        "\u015eaf\u0163 Ab\u016b Jirj"
    ],
    "wof:name":"Saft Abu Jirj",
    "wof:placetype":"locality"
},
  "geometry": {"coordinates":[30.77749,28.53691],"type":"Point"}
}