{
  "type": "Feature",
  "properties": {
    "gn:admin1_code":"10",
    "gn:asciiname":"Ash Shaykh Fadl",
    "gn:country_code":"EG",
    "gn:dem":40,
    "gn:feature_class":"P",
    "gn:feature_code":"PPL",
    "gn:name":"Ash Shaykh Fa\u1e11l",
    "gn:population":0,
    "gn:timezone":"Africa/Cairo",
    "iso:country":"EG",
    "name:ara_x_preferred":[
        "\u0627\u0644\u0634\u064a\u062e \u0641\u0636\u0644"
    ],
    "name:und_x_variant":[
        "El Sheikh Fa\u1e0dl",
        "Ash Shayk Fa\u1e11l",
        "Sheikh Fadl",
        "Ash Shaykh Fa\u1e11l"
    ],
    "wof:name":"Ash Shaykh Fadl",
    "wof:placetype":"locality"
},
  "geometry": {"coordinates":[30.84999,28.48902],"type":"Point"}
}