{
  "type": "Feature",
  "properties": {
    "gn:admin1_code":"20",
    "gn:asciiname":"`Izbat an Najajirah",
    "gn:country_code":"EG",
    "gn:dem":6,
    "gn:feature_class":"P",
    "gn:feature_code":"PPL",
    "gn:name":"\u2018Izbat an Naj\u0101jirah",
    "gn:population":0,
    "gn:timezone":"Africa/Cairo",
    "iso:country":"EG",
    "name:ara_x_preferred":[
        "\u0639\u0632\u0628\u0629 \u0627\u0644\u0646\u062c\u0627\u062c\u0631\u0629"
    ],
    "name:und_x_variant":[
        "\u2018Izbat an Naj\u0101jrah",
        "\u2018Izbat an Naj\u0101jirah"
    ],
    "wof:name":"`Izbat an Najajirah",
    "wof:placetype":"locality"
},
  "geometry": {"coordinates":[31.58231,31.31237],"type":"Point"}
}