{
  "type": "Feature",
  "properties": {
    "gn:admin1_code":"03",
    "gn:asciiname":"Kafr al Waq",
    "gn:country_code":"EG",
    "gn:dem":1,
    "gn:feature_class":"P",
    "gn:feature_code":"PPL",
    "gn:name":"Kafr al W\u0101q",
    "gn:population":0,
    "gn:timezone":"Africa/Cairo",
    "iso:country":"EG",
    "name:und_x_variant":[
        "Kafr el-W\u00e2q",
        "Kafr al W\u0101q"
    ],
    "wof:name":"Kafr al Waq",
    "wof:placetype":"locality"
},
  "geometry": {"coordinates":[30.24842,30.91302],"type":"Point"}
}