{
  "type": "Feature",
  "properties": {
    "gn:admin1_code":"27",
    "gn:asciiname":"Qaryat Iblal at Tarabin",
    "gn:country_code":"EG",
    "gn:dem":105,
    "gn:feature_class":"P",
    "gn:feature_code":"PPL",
    "gn:name":"Qaryat Ibl\u0101l at Tar\u0101b\u012bn",
    "gn:population":0,
    "gn:timezone":"Africa/Cairo",
    "iso:country":"EG",
    "name:ara_x_preferred":[
        "\u0642\u0631\u064a\u0629 \u0627\u0628\u0644\u0627\u0644 \u0627\u0644\u062a\u0631\u0627\u0628\u064a\u0646"
    ],
    "name:und_x_variant":[
        "Qaryat Ibl\u0101l at Tar\u0101b\u012bn"
    ],
    "wof:name":"Qaryat Iblal at Tarabin",
    "wof:placetype":"locality"
},
  "geometry": {"coordinates":[34.18707,31.06935],"type":"Point"}
}