{
  "type": "Feature",
  "properties": {
    "gn:admin1_code":"21",
    "gn:asciiname":"Ash Shaykh Sulayman",
    "gn:country_code":"EG",
    "gn:dem":2,
    "gn:feature_class":"P",
    "gn:feature_code":"PPL",
    "gn:name":"Ash Shaykh Sulaym\u0101n",
    "gn:population":0,
    "gn:timezone":"Africa/Cairo",
    "iso:country":"EG",
    "name:ara_x_preferred":[
        "\u0627\u0644\u0634\u064a\u062e \u0633\u0644\u064a\u0645\u0627\u0646"
    ],
    "name:und_x_variant":[
        "Ash Shaykh Sulaym\u0101n"
    ],
    "wof:name":"Ash Shaykh Sulayman",
    "wof:placetype":"locality"
},
  "geometry": {"coordinates":[30.74238,31.26454],"type":"Point"}
}