{
  "type": "Feature",
  "properties": {
    "gn:admin1_code":"01",
    "gn:asciiname":"Al Bayluq",
    "gn:cc2":"EG",
    "gn:country_code":"EG",
    "gn:dem":12,
    "gn:feature_class":"P",
    "gn:feature_code":"PPL",
    "gn:name":"Al Bayl\u016bq",
    "gn:population":0,
    "gn:timezone":"Africa/Cairo",
    "iso:country":"EG",
    "name:und_x_variant":[
        "El-Bail\u00fbq",
        "Al Bayl\u016bq"
    ],
    "wof:name":"Al Bayluq",
    "wof:placetype":"locality"
},
  "geometry": {"coordinates":[31.29389,30.945],"type":"Point"}
}