{
  "type": "Feature",
  "properties": {
    "gn:admin1_code":"01",
    "gn:asciiname":"Kafr al Miqdam",
    "gn:country_code":"EG",
    "gn:dem":15,
    "gn:feature_class":"P",
    "gn:feature_code":"PPL",
    "gn:name":"Kafr al Miqd\u0101m",
    "gn:population":0,
    "gn:timezone":"Africa/Cairo",
    "iso:country":"EG",
    "name:ara_x_preferred":[
        "\u0643\u0641\u0631 \u0627\u0644\u0645\u0642\u062f\u0627\u0645"
    ],
    "name:und_x_variant":[
        "Kafr el-Muqd\u00e2m",
        "Kafr al Miqd\u0101m",
        "Kafr al Muqd\u0101m"
    ],
    "wof:name":"Kafr al Miqdam",
    "wof:placetype":"locality"
},
  "geometry": {"coordinates":[31.35656,30.67888],"type":"Point"}
}