{
  "type": "Feature",
  "properties": {
    "gn:admin1_code":"04",
    "gn:asciiname":"Minsha'at Qarun",
    "gn:country_code":"EG",
    "gn:dem":-8,
    "gn:feature_class":"P",
    "gn:feature_code":"PPL",
    "gn:name":"Minsha\u2019at Q\u0101r\u016bn",
    "gn:population":0,
    "gn:timezone":"Africa/Cairo",
    "iso:country":"EG",
    "wof:name":"Minsha'at Qarun",
    "wof:placetype":"locality"
},
  "geometry": {"coordinates":[30.4335,29.40939],"type":"Point"}
}