{
  "type": "Feature",
  "properties": {
    "gn:admin1_code":"14",
    "gn:asciiname":"Mit Ridin",
    "gn:country_code":"EG",
    "gn:dem":13,
    "gn:feature_class":"P",
    "gn:feature_code":"PPL",
    "gn:name":"M\u012bt Rid\u012bn",
    "gn:population":0,
    "gn:timezone":"Africa/Cairo",
    "iso:country":"EG",
    "name:ara_x_preferred":[
        "M\u012bt Rid\u012bn"
    ],
    "name:ara_x_variant":[
        "\u0645\u064a\u062a \u0631\u062f\u064a\u0646"
    ],
    "name:und_x_variant":[
        "M\u00eet Ridein",
        "M\u012bt Rudayn"
    ],
    "wof:name":"Mit Ridin",
    "wof:placetype":"locality"
},
  "geometry": {"coordinates":[31.63075,30.58183],"type":"Point"}
}