{
  "type": "Feature",
  "properties": {
    "gn:admin1_code":"03",
    "gn:asciiname":"Al Kafr al Jadid",
    "gn:country_code":"EG",
    "gn:dem":8,
    "gn:feature_class":"P",
    "gn:feature_code":"PPL",
    "gn:name":"Al Kafr al Jad\u012bd",
    "gn:population":0,
    "gn:timezone":"Africa/Cairo",
    "iso:country":"EG",
    "name:ara_x_preferred":[
        "\u0627\u0644\u0643\u0641\u0631 \u0627\u0644\u062c\u062f\u064a\u062f"
    ],
    "name:und_x_variant":[
        "El-Kafr el-Ged\u00eed",
        "Al Kafr al Jad\u012bd"
    ],
    "wof:name":"Al Kafr al Jadid",
    "wof:placetype":"locality"
},
  "geometry": {"coordinates":[30.64094,31.06596],"type":"Point"}
}