{
  "type": "Feature",
  "properties": {
    "gn:admin1_code":"05",
    "gn:asciiname":"`Izbat at Tarabulusi",
    "gn:country_code":"EG",
    "gn:dem":4,
    "gn:feature_class":"P",
    "gn:feature_code":"PPL",
    "gn:name":"\u2018Izbat a\u0163 \u0162ar\u0101bulus\u012b",
    "gn:population":0,
    "gn:timezone":"Africa/Cairo",
    "iso:country":"EG",
    "name:ara_x_preferred":[
        "\u0639\u0632\u0628\u0629 \u0627\u0644\u0637\u0631\u0627\u0628\u0644\u0633\u064a"
    ],
    "name:und_x_variant":[
        "\u2018Izbat a\u0163 \u0162ar\u0101bulus\u012b",
        "\u2018Izbat a\u1e6d-\u1e6car\u0101buls\u012b"
    ],
    "wof:name":"`Izbat at Tarabulusi",
    "wof:placetype":"locality"
},
  "geometry": {"coordinates":[31.18461,31.09229],"type":"Point"}
}