{
  "type": "Feature",
  "properties": {
    "gn:admin1_code":"11",
    "gn:asciiname":"Maadi Cornish",
    "gn:cc2":"EG",
    "gn:country_code":"EG",
    "gn:dem":25,
    "gn:feature_class":"P",
    "gn:feature_code":"PPL",
    "gn:name":"Maadi Cornish",
    "gn:population":0,
    "gn:timezone":"Africa/Cairo",
    "iso:country":"EG",
    "name:und_x_variant":[
        "Cornish El-Ma'adi"
    ],
    "wof:name":"Maadi Cornish",
    "wof:placetype":"locality"
},
  "geometry": {"coordinates":[31.2332,29.9782],"type":"Point"}
}