{
  "type": "Feature",
  "properties": {
    "gn:admin1_code":"01",
    "gn:asciiname":"`Izbat al `Alayili",
    "gn:country_code":"EG",
    "gn:dem":7,
    "gn:feature_class":"P",
    "gn:feature_code":"PPL",
    "gn:name":"\u2018Izbat al \u2018Al\u0101yil\u012b",
    "gn:population":0,
    "gn:timezone":"Africa/Cairo",
    "iso:country":"EG",
    "name:ara_x_preferred":[
        "\u0639\u0632\u0628\u0629 \u0627\u0644\u0639\u0644\u0627\u064a\u0644\u064a"
    ],
    "name:und_x_variant":[
        "\u2018Izbat al \u2018Al\u0101yil\u012b",
        "\u2018Izbat al-\u2018Al\u0101yl\u012b"
    ],
    "wof:name":"`Izbat al `Alayili",
    "wof:placetype":"locality"
},
  "geometry": {"coordinates":[31.44148,31.13305],"type":"Point"}
}