{
  "type": "Feature",
  "properties": {
    "gn:admin1_code":"03",
    "gn:asciiname":"`Izbat al Hawsh",
    "gn:country_code":"EG",
    "gn:dem":3,
    "gn:feature_class":"P",
    "gn:feature_code":"PPL",
    "gn:name":"\u2018Izbat al \u1e28awsh",
    "gn:population":0,
    "gn:timezone":"Africa/Cairo",
    "iso:country":"EG",
    "name:ara_x_preferred":[
        "\u0639\u0632\u0628\u0629 \u0627\u0644\u062d\u0648\u0634"
    ],
    "name:und_x_variant":[
        "\u2018Izbat al \u1e28awsh",
        "\u2018Izbat al-\u1e24awsh"
    ],
    "wof:name":"`Izbat al Hawsh",
    "wof:placetype":"locality"
},
  "geometry": {"coordinates":[30.45152,31.05746],"type":"Point"}
}