{
  "type": "Feature",
  "properties": {
    "gn:admin1_code":"14",
    "gn:asciiname":"`Ezbet Muhammad Nisim",
    "gn:country_code":"EG",
    "gn:dem":2,
    "gn:feature_class":"P",
    "gn:feature_code":"PPL",
    "gn:name":"\u2018Ezbet Mu\u1e25ammad Nis\u00eem",
    "gn:population":0,
    "gn:timezone":"Africa/Cairo",
    "iso:country":"EG",
    "wof:name":"`Ezbet Muhammad Nisim",
    "wof:placetype":"locality"
},
  "geometry": {"coordinates":[31.72333,30.96111],"type":"Point"}
}