{
  "type": "Feature",
  "properties": {
    "gn:admin1_code":"03",
    "gn:asciiname":"`Izbat Kawm Mazin",
    "gn:country_code":"EG",
    "gn:dem":-1,
    "gn:feature_class":"P",
    "gn:feature_code":"PPL",
    "gn:name":"\u2018Izbat Kawm M\u0101zin",
    "gn:population":0,
    "gn:timezone":"Africa/Cairo",
    "iso:country":"EG",
    "name:und_x_variant":[
        "\u2018Ezbet K\u00f4m M\u00e2zin",
        "\u2018Izbat Kawm M\u0101zin"
    ],
    "wof:name":"`Izbat Kawm Mazin",
    "wof:placetype":"locality"
},
  "geometry": {"coordinates":[30.16139,31.19583],"type":"Point"}
}