{
  "type": "Feature",
  "properties": {
    "gn:admin1_code":"11",
    "gn:asciiname":"testing",
    "gn:country_code":"EG",
    "gn:dem":87,
    "gn:feature_class":"P",
    "gn:feature_code":"PPL",
    "gn:name":"testing",
    "gn:population":0,
    "gn:timezone":"Africa/Cairo",
    "iso:country":"EG",
    "wof:name":"testing",
    "wof:placetype":"locality"
},
  "geometry": {"coordinates":[31.40551,30.12191],"type":"Point"}
}