{
  "type": "Feature",
  "properties": {
    "gn:admin1_code":"21",
    "gn:asciiname":"Al Ghunaymi",
    "gn:country_code":"EG",
    "gn:dem":9,
    "gn:feature_class":"P",
    "gn:feature_code":"PPL",
    "gn:name":"Al Ghunaym\u012b",
    "gn:population":0,
    "gn:timezone":"Africa/Cairo",
    "iso:country":"EG",
    "name:ara_x_preferred":[
        "\u0627\u0644\u063a\u0646\u064a\u0645\u064a"
    ],
    "name:und_x_variant":[
        "El-Ghuneimi",
        "Al Ghunaym\u012b"
    ],
    "wof:name":"Al Ghunaymi",
    "wof:placetype":"locality"
},
  "geometry": {"coordinates":[30.77769,31.12828],"type":"Point"}
}