{
  "type": "Feature",
  "properties": {
    "gn:admin1_code":"16",
    "gn:asciiname":"Ar Ramadi Bahri",
    "gn:cc2":"EG",
    "gn:country_code":"EG",
    "gn:dem":89,
    "gn:feature_class":"P",
    "gn:feature_code":"PPL",
    "gn:name":"Ar Ram\u0101d\u012b Ba\u1e29r\u012b",
    "gn:population":0,
    "gn:timezone":"Africa/Cairo",
    "iso:country":"EG",
    "name:und_x_variant":[
        "El Ram\u00e2di Bahari",
        "Zim\u0101m ar Ram\u0101d\u012b Ba\u1e29r\u012b",
        "Er Ram\u0101di Bahri",
        "Er Ram\u0101di Bahari",
        "Ar Ram\u0101d\u012b Ba\u1e29r\u012b"
    ],
    "wof:name":"Ar Ramadi Bahri",
    "wof:placetype":"locality"
},
  "geometry": {"coordinates":[32.85,24.88333],"type":"Point"}
}