{
  "type": "Feature",
  "properties": {
    "gn:admin1_code":"14",
    "gn:asciiname":"Kafr al Jirayah",
    "gn:country_code":"EG",
    "gn:dem":14,
    "gn:feature_class":"P",
    "gn:feature_code":"PPL",
    "gn:name":"Kafr al Jir\u0101yah",
    "gn:population":0,
    "gn:timezone":"Africa/Cairo",
    "iso:country":"EG",
    "name:ara_x_preferred":[
        "\u0643\u0641\u0631 \u0627\u0644\u062c\u0631\u0627\u064a\u0629"
    ],
    "name:und_x_variant":[
        "Kafr el-Gir\u00e2ya",
        "Kafr al Jir\u0101yah"
    ],
    "wof:name":"Kafr al Jirayah",
    "wof:placetype":"locality"
},
  "geometry": {"coordinates":[31.41078,30.57118],"type":"Point"}
}