{
  "type": "Feature",
  "properties": {
    "gn:admin1_code":"05",
    "gn:asciiname":"`Izbat Masihah az Ziyadi",
    "gn:country_code":"EG",
    "gn:dem":4,
    "gn:feature_class":"P",
    "gn:feature_code":"PPL",
    "gn:name":"\u2018Izbat Mas\u012b\u1e29ah az Z\u012by\u0101d\u012b",
    "gn:population":0,
    "gn:timezone":"Africa/Cairo",
    "iso:country":"EG",
    "name:ara_x_preferred":[
        "\u0639\u0632\u0628\u0629 \u0645\u0633\u064a\u062d\u0629 \u0627\u0644\u0632\u064a\u0627\u062f\u064a"
    ],
    "name:und_x_variant":[
        "\u2018Izbat Mas\u012b\u1e29ah az Z\u012by\u0101d\u012b",
        "\u2018Izbat Mis\u012b\u1e25ah az-Z\u012byy\u0101d\u012b",
        "\u2018Ezbet \u2018Az\u00eez el-Ziy\u00e2da"
    ],
    "wof:name":"`Izbat Masihah az Ziyadi",
    "wof:placetype":"locality"
},
  "geometry": {"coordinates":[31.12258,31.12306],"type":"Point"}
}