{
  "type": "Feature",
  "properties": {
    "gn:admin1_code":"04",
    "gn:asciiname":"Abjij",
    "gn:country_code":"EG",
    "gn:dem":20,
    "gn:feature_class":"P",
    "gn:feature_code":"PPL",
    "gn:name":"Abj\u012bj",
    "gn:population":0,
    "gn:timezone":"Africa/Cairo",
    "iso:country":"EG",
    "name:und_x_variant":[
        "Abgig",
        "Abj\u012bj"
    ],
    "wof:name":"Abjij",
    "wof:placetype":"locality"
},
  "geometry": {"coordinates":[30.81517,29.28619],"type":"Point"}
}