{
  "type": "Feature",
  "properties": {
    "gn:admin1_code":"10.0",
    "gn:asciiname":"Tuwah Bani Ibrahim",
    "gn:country_code":"EG",
    "gn:dem":38,
    "gn:feature_class":"P",
    "gn:feature_code":"PPL",
    "gn:name":"T\u016bwah Ban\u012b Ibr\u0101h\u012bm",
    "gn:population":0,
    "gn:timezone":"Africa/Cairo",
    "iso:country":"EG",
    "name:und_x_variant":[
        "Beni Ibr\u00e2h\u00eem",
        "Tuwa Beni Ibr\u00e2h\u00eem",
        "T\u016bwah Ban\u012b Ibr\u0101h\u012bm"
    ],
    "wof:name":"Tuwah Bani Ibrahim",
    "wof:placetype":"locality"
},
  "geometry": {"coordinates":[30.68396,28.07504],"type":"Point"}
}