{
  "type": "Feature",
  "properties": {
    "gn:admin1_code":"05",
    "gn:asciiname":"Kafr al Mansurah",
    "gn:country_code":"EG",
    "gn:dem":12,
    "gn:feature_class":"P",
    "gn:feature_code":"PPL",
    "gn:name":"Kafr al Man\u015f\u016brah",
    "gn:population":0,
    "gn:timezone":"Africa/Cairo",
    "iso:country":"EG",
    "name:und_x_variant":[
        "Kafr el-Man\u1e63\u00fbra",
        "Kafr al Man\u015f\u016brah"
    ],
    "wof:name":"Kafr al Mansurah",
    "wof:placetype":"locality"
},
  "geometry": {"coordinates":[30.91298,30.82097000000001],"type":"Point"}
}