{
  "type": "Feature",
  "properties": {
    "gn:admin1_code":"14",
    "gn:asciiname":"Ashnit al Harabwah",
    "gn:country_code":"EG",
    "gn:dem":11,
    "gn:feature_class":"P",
    "gn:feature_code":"PPL",
    "gn:name":"Ashn\u012b\u0163 al \u1e28ar\u0101bwah",
    "gn:population":0,
    "gn:timezone":"Africa/Cairo",
    "iso:country":"EG",
    "name:ara_x_preferred":[
        "\u0623\u0634\u0646\u064a\u0637 \u0627\u0644\u062d\u0631\u0627\u0628\u0648\u0629"
    ],
    "name:und_x_variant":[
        "Ishnit el-Harabwa",
        "Ishn\u00ee\u1e6d el-\u1e24ar\u00e2biwa",
        "Ishn\u012b\u0163 al \u1e28ar\u0101biwah",
        "Ashn\u012b\u0163 al \u1e28ar\u0101bwah"
    ],
    "wof:name":"Ashnit al Harabwah",
    "wof:placetype":"locality"
},
  "geometry": {"coordinates":[31.60452,30.79196],"type":"Point"}
}