{
  "type": "Feature",
  "properties": {
    "gn:admin1_code":"12",
    "gn:asciiname":"`Izbat Sa`d Mikha'il",
    "gn:country_code":"EG",
    "gn:dem":17,
    "gn:feature_class":"P",
    "gn:feature_code":"PPL",
    "gn:name":"\u2018Izbat Sa\u2018d M\u012bkh\u0101\u2019\u012bl",
    "gn:population":0,
    "gn:timezone":"Africa/Cairo",
    "iso:country":"EG",
    "name:ara_x_preferred":[
        "\u0639\u0632\u0628\u0629 \u0633\u0639\u062f \u0645\u064a\u062e\u0627\u0626\u064a\u0644"
    ],
    "name:und_x_variant":[
        "\u2018Izbat Sa\u2018d M\u012bkh\u0101\u2019\u012bl"
    ],
    "wof:name":"`Izbat Sa`d Mikha'il",
    "wof:placetype":"locality"
},
  "geometry": {"coordinates":[31.23568,30.37216],"type":"Point"}
}