{
  "type": "Feature",
  "properties": {
    "gn:admin1_code":"01",
    "gn:asciiname":"`Izbat Mustafa Agha",
    "gn:country_code":"EG",
    "gn:dem":8,
    "gn:feature_class":"P",
    "gn:feature_code":"PPL",
    "gn:name":"\u2018Izbat Mu\u015f\u0163af\u00e1 Agh\u0101",
    "gn:population":0,
    "gn:timezone":"Africa/Cairo",
    "iso:country":"EG",
    "name:ara_x_preferred":[
        "\u0639\u0632\u0628\u0629 \u0645\u0635\u0637\u0641\u0649 \u0623\u063a\u0627"
    ],
    "name:und_x_variant":[
        "\u2018Izbat Mu\u015f\u0163af\u00e1 Agh\u0101",
        "\u2018Izbat Mu\u1e63\u1e6dafa\u2019 Agha"
    ],
    "wof:name":"`Izbat Mustafa Agha",
    "wof:placetype":"locality"
},
  "geometry": {"coordinates":[31.4766,31.11454],"type":"Point"}
}