{
  "type": "Feature",
  "properties": {
    "gn:admin1_code":"18",
    "gn:asciiname":"Ihwah",
    "gn:country_code":"EG",
    "gn:dem":34,
    "gn:feature_class":"P",
    "gn:feature_code":"PPL",
    "gn:name":"Ihwah",
    "gn:population":0,
    "gn:timezone":"Africa/Cairo",
    "iso:country":"EG",
    "name:und_x_variant":[
        "Ihwa",
        "Ihwah"
    ],
    "wof:name":"Ihwah",
    "wof:placetype":"locality"
},
  "geometry": {"coordinates":[31.00365,29.04418],"type":"Point"}
}