{
  "type": "Feature",
  "properties": {
    "gn:admin1_code":"05",
    "gn:asciiname":"`Izbat `Arafan Husayn",
    "gn:country_code":"EG",
    "gn:dem":16,
    "gn:feature_class":"P",
    "gn:feature_code":"PPL",
    "gn:name":"\u2018Izbat \u2018Araf\u0101n \u1e28usayn",
    "gn:population":0,
    "gn:timezone":"Africa/Cairo",
    "iso:country":"EG",
    "name:ara_x_preferred":[
        "\u0639\u0632\u0628\u0629 \u0639\u0631\u0641\u0627\u0646 \u062d\u0633\u064a\u0646"
    ],
    "name:und_x_variant":[
        "\u2018Izbat \u2018Araf\u0101n \u1e28usayn"
    ],
    "wof:name":"`Izbat `Arafan Husayn",
    "wof:placetype":"locality"
},
  "geometry": {"coordinates":[31.08945,30.68231],"type":"Point"}
}