{
  "type": "Feature",
  "properties": {
    "gn:admin1_code":"03",
    "gn:asciiname":"`Izbat Halq al Jamal",
    "gn:country_code":"EG",
    "gn:dem":2,
    "gn:feature_class":"P",
    "gn:feature_code":"PPL",
    "gn:name":"\u2018Izbat \u1e28alq al Jamal",
    "gn:population":0,
    "gn:timezone":"Africa/Cairo",
    "iso:country":"EG",
    "name:ara_x_preferred":[
        "\u0639\u0632\u0628\u0629 \u062d\u0644\u0642 \u0627\u0644\u062c\u0645\u0644"
    ],
    "name:und_x_variant":[
        "\u2018Izbat \u1e28alq al Jamal"
    ],
    "wof:name":"`Izbat Halq al Jamal",
    "wof:placetype":"locality"
},
  "geometry": {"coordinates":[30.51707,31.20723],"type":"Point"}
}