{
  "type": "Feature",
  "properties": {
    "gn:admin1_code":"04",
    "gn:asciiname":"Ifwah",
    "gn:cc2":"EG",
    "gn:country_code":"EG",
    "gn:dem":28,
    "gn:feature_class":"P",
    "gn:feature_code":"PPL",
    "gn:name":"Ifwah",
    "gn:population":0,
    "gn:timezone":"Africa/Cairo",
    "iso:country":"EG",
    "name:und_x_variant":[
        "Afwa",
        "Ifwa",
        "Ifwah"
    ],
    "wof:name":"Ifwah",
    "wof:placetype":"locality"
},
  "geometry": {"coordinates":[31.19556,29.35583],"type":"Point"}
}