{
  "type": "Feature",
  "properties": {
    "gn:admin1_code":"14",
    "gn:asciiname":"Al Faruqiyah",
    "gn:cc2":"EG",
    "gn:country_code":"EG",
    "gn:dem":10,
    "gn:feature_class":"P",
    "gn:feature_code":"PPL",
    "gn:name":"Al F\u0101r\u016bq\u012byah",
    "gn:population":0,
    "gn:timezone":"Africa/Cairo",
    "iso:country":"EG",
    "name:und_x_variant":[
        "El-Farukia",
        "El-F\u00e2r\u00fbq\u00eeya",
        "Al F\u0101r\u016bq\u012byah"
    ],
    "wof:name":"Al Faruqiyah",
    "wof:placetype":"locality"
},
  "geometry": {"coordinates":[31.58333,30.45],"type":"Point"}
}