{
  "type": "Feature",
  "properties": {
    "gn:admin1_code":"20",
    "gn:asciiname":"`Izbat Muhammad Abu Sa`id",
    "gn:country_code":"EG",
    "gn:dem":2,
    "gn:feature_class":"P",
    "gn:feature_code":"PPL",
    "gn:name":"\u2018Izbat Mu\u1e29ammad Ab\u016b Sa\u2018\u012bd",
    "gn:population":0,
    "gn:timezone":"Africa/Cairo",
    "iso:country":"EG",
    "name:ara_x_preferred":[
        "\u0639\u0632\u0628\u0629 \u0645\u062d\u0645\u062f \u0623\u0628\u0648 \u0633\u0639\u064a\u062f"
    ],
    "name:und_x_variant":[
        "\u2018Izbat Mu\u1e29ammad Ab\u016b Sa\u2018\u012bd"
    ],
    "wof:name":"`Izbat Muhammad Abu Sa`id",
    "wof:placetype":"locality"
},
  "geometry": {"coordinates":[31.58773,31.3071],"type":"Point"}
}