{
  "type": "Feature",
  "properties": {
    "iso:country":"EG",
    "name:eng_x_preferred":[
        "Tall al Qulzum"
    ],
    "name:eng_x_variant":[
        "Qulzum, Tell El -"
    ],
    "name:und_x_variant":[
        "Tell el-Qulzum"
    ],
    "qs:gn_adm0_cc":"EG",
    "qs:gn_fcode":"PPLX",
    "qs:gn_local":359796,
    "qs:gn_nam_loc":"\u0627\u0644\u0633\u0648\u064a\u0633, \u0627\u0644\u0633\u0648\u064a\u0633, EG",
    "qs:gn_namadm1":"15",
    "qs:gn_name":"Tall al Qulzum",
    "qs:local_max":20,
    "qs:local_sum":20,
    "qs:localhoods":1,
    "qs:name":"Tall al Qulzum",
    "qs:name_adm0":"\u0645\u0635\u0631",
    "qs:name_adm1":"\u0627\u0644\u0633\u0648\u064a\u0633",
    "qs:name_local":"\u0627\u0644\u0633\u0648\u064a\u0633",
    "qs:photo_max":9,
    "qs:photo_sum":20,
    "qs:placetype":"Suburb",
    "qs:quad_count":9,
    "qs:woe_adm0":23424802,
    "qs:woe_adm1":2345237,
    "qs:woe_adm2":0,
    "qs:woe_lau":0,
    "qs:woe_local":1526398,
    "qs:woe_ver":"7.10.0",
    "wof:lang":[
        "eng"
    ],
    "wof:name":"Tall al Qulzum",
    "wof:placetype":"neighbourhood"
},
  "geometry": {"coordinates":[32.551666,29.958504],"type":"Point"}
}