{
  "type": "Feature",
  "properties": {
    "gn:admin1_code":"01",
    "gn:asciiname":"`Izbat ash Shatt al Bahriyah",
    "gn:country_code":"EG",
    "gn:dem":5,
    "gn:feature_class":"P",
    "gn:feature_code":"PPL",
    "gn:name":"\u2018Izbat ash Sha\u0163\u0163 al Ba\u1e29r\u012byah",
    "gn:population":0,
    "gn:timezone":"Africa/Cairo",
    "iso:country":"EG",
    "name:ara_x_preferred":[
        "\u0639\u0632\u0628\u0629 \u0627\u0644\u0634\u0637 \u0627\u0644\u0628\u062d\u0631\u064a\u0629"
    ],
    "name:und_x_variant":[
        "\u2018Izbat ash Sha\u0163\u0163 al Ba\u1e29r\u012byah"
    ],
    "wof:name":"`Izbat ash Shatt al Bahriyah",
    "wof:placetype":"locality"
},
  "geometry": {"coordinates":[31.54448,31.31114],"type":"Point"}
}