{
  "type": "Feature",
  "properties": {
    "gn:admin1_code":"03",
    "gn:asciiname":"`Izbat `Askar",
    "gn:country_code":"EG",
    "gn:dem":1,
    "gn:feature_class":"P",
    "gn:feature_code":"PPL",
    "gn:name":"\u2018Izbat \u2018Askar",
    "gn:population":0,
    "gn:timezone":"Africa/Cairo",
    "iso:country":"EG",
    "name:ara_x_preferred":[
        "\u0639\u0632\u0628\u0629 \u0639\u0633\u0643\u0631"
    ],
    "name:und_x_variant":[
        "\u2018Ezbet el-Askar",
        "\u2018Izbat al \u2018Askar",
        "\u2018Izbat \u2018Askar"
    ],
    "wof:name":"`Izbat `Askar",
    "wof:placetype":"locality"
},
  "geometry": {"coordinates":[30.41817,31.19844],"type":"Point"}
}