{
  "type": "Feature",
  "properties": {
    "gn:admin1_code":"18",
    "gn:asciiname":"Nazlat al Mashariqah",
    "gn:country_code":"EG",
    "gn:dem":28,
    "gn:feature_class":"P",
    "gn:feature_code":"PPL",
    "gn:name":"Nazlat al Mash\u0101riqah",
    "gn:population":0,
    "gn:timezone":"Africa/Cairo",
    "iso:country":"EG",
    "name:ara_x_preferred":[
        "\u0646\u0632\u0644\u0629 \u0627\u0644\u0645\u0634\u0627\u0631\u0642\u0629"
    ],
    "name:und_x_variant":[
        "Nazlet el Mash\u00e2rqa",
        "Nazlat al Mash\u0101riqah"
    ],
    "wof:name":"Nazlat al Mashariqah",
    "wof:placetype":"locality"
},
  "geometry": {"coordinates":[30.97292,29.04744],"type":"Point"}
}