{
  "type": "Feature",
  "properties": {
    "gn:admin1_code":"03",
    "gn:asciiname":"`Izbat Sikkat al Hadid",
    "gn:country_code":"EG",
    "gn:dem":0,
    "gn:feature_class":"P",
    "gn:feature_code":"PPL",
    "gn:name":"\u2018Izbat Sikkat al \u1e28ad\u012bd",
    "gn:population":0,
    "gn:timezone":"Africa/Cairo",
    "iso:country":"EG",
    "name:ara_x_preferred":[
        "\u0639\u0632\u0628\u0629 \u0633\u0643\u0629 \u0627\u0644\u062d\u062f\u064a\u062f"
    ],
    "name:ara_x_variant":[
        "\u0639\u0632\u0628\u0629 \u0627\u0644\u0633\u0643\u0629 \u0627\u0644\u062d\u062f\u064a\u062f"
    ],
    "name:und_x_variant":[
        "\u2018Izbat Sikkat al \u1e28ad\u012bd",
        "\u2018Izbat as Sikkah al \u1e28ad\u012bd"
    ],
    "wof:name":"`Izbat Sikkat al Hadid",
    "wof:placetype":"locality"
},
  "geometry": {"coordinates":[30.40445,31.3346],"type":"Point"}
}