{
  "type": "Feature",
  "properties": {
    "gn:admin1_code":"14",
    "gn:asciiname":"`Izbat al Babli",
    "gn:country_code":"EG",
    "gn:dem":11,
    "gn:feature_class":"P",
    "gn:feature_code":"PPL",
    "gn:name":"\u2018Izbat al B\u0101bl\u012b",
    "gn:population":0,
    "gn:timezone":"Africa/Cairo",
    "iso:country":"EG",
    "name:ara_x_preferred":[
        "\u0639\u0632\u0628\u0629 \u0627\u0644\u0628\u0627\u0628\u0644\u064a"
    ],
    "name:und_x_variant":[
        "\u2018Izbat al B\u0101bl\u012b"
    ],
    "wof:name":"`Izbat al Babli",
    "wof:placetype":"locality"
},
  "geometry": {"coordinates":[31.41068,30.61279],"type":"Point"}
}