{
  "type": "Feature",
  "properties": {
    "gn:admin1_code":"23",
    "gn:asciiname":"Naj` al Hayy",
    "gn:country_code":"EG",
    "gn:dem":77,
    "gn:feature_class":"P",
    "gn:feature_code":"PPL",
    "gn:name":"Naj\u2018 al \u1e28ayy",
    "gn:population":0,
    "gn:timezone":"Africa/Cairo",
    "iso:country":"EG",
    "wof:name":"Naj` al Hayy",
    "wof:placetype":"locality"
},
  "geometry": {"coordinates":[32.79684,26.0987],"type":"Point"}
}