{
  "type": "Feature",
  "properties": {
    "gn:admin1_code":"21",
    "gn:asciiname":"Kafr al Khayr",
    "gn:country_code":"EG",
    "gn:dem":10,
    "gn:feature_class":"P",
    "gn:feature_code":"PPL",
    "gn:name":"Kafr al Khayr",
    "gn:population":0,
    "gn:timezone":"Africa/Cairo",
    "iso:country":"EG",
    "name:ara_x_preferred":[
        "\u0643\u0641\u0631 \u0627\u0644\u062e\u064a\u0631"
    ],
    "name:und_x_variant":[
        "Kafr el-Kheir",
        "Kafr al Khayr",
        "\u2018Izbat Kafr al-Khayr"
    ],
    "wof:name":"Kafr al Khayr",
    "wof:placetype":"locality"
},
  "geometry": {"coordinates":[30.74467000000001,31.03909],"type":"Point"}
}