{
  "type": "Feature",
  "properties": {
    "gn:admin1_code":"01",
    "gn:asciiname":"`Izbat al Hazimi",
    "gn:country_code":"EG",
    "gn:dem":9,
    "gn:feature_class":"P",
    "gn:feature_code":"PPL",
    "gn:name":"\u2018Izbat al \u1e28\u0101zim\u012b",
    "gn:population":0,
    "gn:timezone":"Africa/Cairo",
    "iso:country":"EG",
    "name:ara_x_preferred":[
        "\u0639\u0632\u0628\u0629 \u0627\u0644\u062d\u0627\u0632\u0645\u064a"
    ],
    "name:und_x_variant":[
        "\u2018Izbat al \u1e28\u0101zim\u012b",
        "\u2018Izbat al \u1e28\u0101zm\u012b",
        "\u2018Izbat al-\u1e24\u0101zm\u012b"
    ],
    "wof:name":"`Izbat al Hazimi",
    "wof:placetype":"locality"
},
  "geometry": {"coordinates":[31.4303,30.84956],"type":"Point"}
}