{
  "type": "Feature",
  "properties": {
    "gn:admin1_code":"05",
    "gn:asciiname":"Ibshaway al Malaq",
    "gn:country_code":"EG",
    "gn:dem":14,
    "gn:feature_class":"P",
    "gn:feature_code":"PPL",
    "gn:name":"Ibsh\u0101w\u0101y al Malaq",
    "gn:population":0,
    "gn:timezone":"Africa/Cairo",
    "iso:country":"EG",
    "name:ara_x_preferred":[
        "\u0627\u0628\u0634\u0627\u0648\u0627\u064a \u0627\u0644\u0645\u0644\u0642"
    ],
    "name:und_x_variant":[
        "Ibsh\u0101w\u0101y al Malaq",
        "Ibshaw\u00e2i el-Malaq",
        "Ibsh\u0101w\u0101y al-Malaq"
    ],
    "wof:name":"Ibshaway al Malaq",
    "wof:placetype":"locality"
},
  "geometry": {"coordinates":[31.02208,30.94346],"type":"Point"}
}