{
  "type": "Feature",
  "properties": {
    "gn:admin1_code":"13",
    "gn:asciiname":"El-Zuwak el-Sharqiya",
    "gn:country_code":"EG",
    "gn:dem":362,
    "gn:feature_class":"P",
    "gn:feature_code":"PPL",
    "gn:name":"El-Zuwak el-Sharq\u00eeya",
    "gn:population":0,
    "gn:timezone":"Africa/Cairo",
    "iso:country":"EG",
    "wof:name":"El-Zuwak el-Sharqiya",
    "wof:placetype":"locality"
},
  "geometry": {"coordinates":[31.21667,26.43333],"type":"Point"}
}