{
  "type": "Feature",
  "properties": {
    "iso:country":"EG",
    "name:ara_x_preferred":[
        "\u0623\u0628\u0648 \u0633\u0645\u0628\u0644"
    ],
    "name:dut_x_preferred":[
        "Aboe Simbel"
    ],
    "name:eng_x_preferred":[
        "Abu Simbel"
    ],
    "name:epo_x_preferred":[
        "Abu Simbel"
    ],
    "name:est_x_preferred":[
        "Ab\u016b Sunbul"
    ],
    "name:fre_x_preferred":[
        "Abou Simbel"
    ],
    "name:geo_x_preferred":[
        "\u10d0\u10d1\u10e3-\u10e1\u10d8\u10db\u10d1\u10d0\u10da\u10d8"
    ],
    "name:ger_x_preferred":[
        "Abu Simbel"
    ],
    "name:heb_x_preferred":[
        "\u05d0\u05d1\u05d5 \u05e1\u05d9\u05de\u05d1\u05dc"
    ],
    "name:hun_x_preferred":[
        "Abu Szimbel"
    ],
    "name:jpn_x_preferred":[
        "\u30a2\u30d6\u30fb\u30b7\u30f3\u30d9\u30eb"
    ],
    "name:pol_x_preferred":[
        "Abu Sunbul"
    ],
    "name:por_x_preferred":[
        "Abu Simbel"
    ],
    "name:rus_x_preferred":[
        "\u0410\u0431\u0443-\u0421\u0438\u043c\u0431\u0435\u043b"
    ],
    "name:slo_x_preferred":[
        "Abu Simbel"
    ],
    "name:spa_x_preferred":[
        "Abu Simbel"
    ],
    "name:swe_x_preferred":[
        "Abu Simbel"
    ],
    "qs:gn_pop":0,
    "qs:name":"Abu Simbel",
    "qs:name_adm0":"\u0645\u0635\u0631",
    "qs:name_adm1":"\u0627\u0633\u0648\u0627\u0646",
    "qs:photos":5000,
    "qs:photos_1k":1000,
    "qs:photos_9k":22,
    "qs:photos_9r":14,
    "qs:photos_all":5000,
    "qs:photos_sr":24,
    "qs:placetype":"Town",
    "qs:pop_sr":"0",
    "qs:woe_adm0":23424802,
    "wof:name":"Abu Simbel",
    "wof:placetype":"locality"
},
  "geometry": {"coordinates":[31.626205,22.348488],"type":"Point"}
}