{
  "type": "Feature",
  "properties": {
    "gn:admin1_code":"04",
    "gn:asciiname":"`Izbat Abu Tahun",
    "gn:country_code":"EG",
    "gn:dem":3,
    "gn:feature_class":"P",
    "gn:feature_code":"PPL",
    "gn:name":"\u2018Izbat Ab\u016b \u0162\u0101\u1e29\u016bn",
    "gn:population":0,
    "gn:timezone":"Africa/Cairo",
    "iso:country":"EG",
    "name:und_x_variant":[
        "\u2018Ezbet Ab\u00fb \u1e6ca\u1e25\u00fbn",
        "\u2018Izbat Ab\u016b \u0162\u0101\u1e29\u016bn"
    ],
    "wof:name":"`Izbat Abu Tahun",
    "wof:placetype":"locality"
},
  "geometry": {"coordinates":[30.59299,29.30294],"type":"Point"}
}