{
  "type": "Feature",
  "properties": {
    "gn:admin1_code":"01",
    "gn:asciiname":"`Izbat Musa Muhammad Mansur",
    "gn:country_code":"EG",
    "gn:dem":1,
    "gn:feature_class":"P",
    "gn:feature_code":"PPL",
    "gn:name":"\u2018Izbat M\u016bs\u00e1 Mu\u1e29ammad Man\u015f\u016br",
    "gn:population":0,
    "gn:timezone":"Africa/Cairo",
    "iso:country":"EG",
    "name:ara_x_preferred":[
        "\u0639\u0632\u0628\u0629 \u0645\u0648\u0633\u0649 \u0645\u062d\u0645\u062f \u0645\u0646\u0635\u0648\u0631"
    ],
    "name:und_x_variant":[
        "\u2018Izbat M\u016bs\u00e1 Mu\u1e29ammad Man\u015f\u016br"
    ],
    "wof:name":"`Izbat Musa Muhammad Mansur",
    "wof:placetype":"locality"
},
  "geometry": {"coordinates":[31.59941,31.28575],"type":"Point"}
}