{
  "type": "Feature",
  "properties": {
    "gn:admin1_code":"04",
    "gn:asciiname":"`Ezbet el-Waqf",
    "gn:country_code":"EG",
    "gn:dem":26,
    "gn:feature_class":"P",
    "gn:feature_code":"PPL",
    "gn:name":"\u2018Ezbet el-Waqf",
    "gn:population":0,
    "gn:timezone":"Africa/Cairo",
    "iso:country":"EG",
    "wof:name":"`Ezbet el-Waqf",
    "wof:placetype":"locality"
},
  "geometry": {"coordinates":[31.18333,29.26667],"type":"Point"}
}