{
  "type": "Feature",
  "properties": {
    "gn:admin1_code":"14",
    "gn:asciiname":"Kafr an Nasiri",
    "gn:country_code":"EG",
    "gn:dem":10,
    "gn:feature_class":"P",
    "gn:feature_code":"PPL",
    "gn:name":"Kafr an Na\u015f\u012br\u012b",
    "gn:population":0,
    "gn:timezone":"Africa/Cairo",
    "iso:country":"EG",
    "name:ara_x_preferred":[
        "\u0643\u0641\u0631 \u0627\u0644\u0646\u0635\u064a\u0631\u064a"
    ],
    "name:und_x_variant":[
        "Kafr el Na\u1e63iri",
        "Kafr an Nu\u015fayr\u012b",
        "Kafr an Na\u015f\u012br\u012b"
    ],
    "wof:name":"Kafr an Nasiri",
    "wof:placetype":"locality"
},
  "geometry": {"coordinates":[31.62077,30.7523],"type":"Point"}
}