{
  "type": "Feature",
  "properties": {
    "gn:admin1_code":"03",
    "gn:asciiname":"Sanhur",
    "gn:country_code":"EG",
    "gn:dem":5,
    "gn:feature_class":"P",
    "gn:feature_code":"PPL",
    "gn:name":"Sanh\u016br",
    "gn:population":0,
    "gn:timezone":"Africa/Cairo",
    "iso:country":"EG",
    "name:ara_x_preferred":[
        "\u0633\u0646\u0647\u0648\u0631"
    ],
    "name:und_x_variant":[
        "Sanh\u016br"
    ],
    "wof:name":"Sanhur",
    "wof:placetype":"locality"
},
  "geometry": {"coordinates":[30.54815,31.07077],"type":"Point"}
}