{
  "type": "Feature",
  "properties": {
    "gn:admin1_code":"10",
    "gn:asciiname":"`Izbat Salih Basil",
    "gn:country_code":"EG",
    "gn:dem":43,
    "gn:feature_class":"P",
    "gn:feature_code":"PPL",
    "gn:name":"\u2018Izbat \u015e\u0101li\u1e29 B\u0101sil",
    "gn:population":0,
    "gn:timezone":"Africa/Cairo",
    "iso:country":"EG",
    "wof:name":"`Izbat Salih Basil",
    "wof:placetype":"locality"
},
  "geometry": {"coordinates":[30.63342,28.17978],"type":"Point"}
}