{
  "type": "Feature",
  "properties": {
    "gn:admin1_code":"03",
    "gn:asciiname":"`Izbat Jab Allah Zayd",
    "gn:country_code":"EG",
    "gn:dem":-1,
    "gn:feature_class":"P",
    "gn:feature_code":"PPL",
    "gn:name":"\u2018Izbat J\u0101b All\u0101h Zayd",
    "gn:population":0,
    "gn:timezone":"Africa/Cairo",
    "iso:country":"EG",
    "name:und_x_variant":[
        "\u2018Ezbet Gaballa Zeid",
        "\u2018Izbat J\u0101b All\u0101h Zayd",
        "\u2018Ezbet \u2018Abdalla Zeid"
    ],
    "wof:name":"`Izbat Jab Allah Zayd",
    "wof:placetype":"locality"
},
  "geometry": {"coordinates":[30.24389,31.14972],"type":"Point"}
}