{
  "type": "Feature",
  "properties": {
    "gn:admin1_code":"01",
    "gn:asciiname":"`Izbat Mashriqi",
    "gn:country_code":"EG",
    "gn:dem":7,
    "gn:feature_class":"P",
    "gn:feature_code":"PPL",
    "gn:name":"\u2018Izbat Mashriq\u012b",
    "gn:population":0,
    "gn:timezone":"Africa/Cairo",
    "iso:country":"EG",
    "name:ara_x_preferred":[
        "\u0639\u0632\u0628\u0629 \u0645\u0634\u0631\u0642\u064a"
    ],
    "name:und_x_variant":[
        "\u2018Izbat Mashriq\u012b",
        "\u2018Izbat Mishriq\u012b",
        "\u2018Iz. Mishriq\u012b"
    ],
    "wof:name":"`Izbat Mashriqi",
    "wof:placetype":"locality"
},
  "geometry": {"coordinates":[31.31945,30.89333],"type":"Point"}
}