{
  "type": "Feature",
  "properties": {
    "gn:admin1_code":"14",
    "gn:asciiname":"`Izbat Ikyad",
    "gn:country_code":"EG",
    "gn:dem":11,
    "gn:feature_class":"P",
    "gn:feature_code":"PPL",
    "gn:name":"\u2018Izbat Iky\u0101d",
    "gn:population":0,
    "gn:timezone":"Africa/Cairo",
    "iso:country":"EG",
    "name:ara_x_preferred":[
        "\u0639\u0632\u0628\u0629 \u0625\u0643\u064a\u0627\u062f"
    ],
    "name:und_x_variant":[
        "Iky\u00e2d el-Qibl\u00eeya",
        "Iky\u0101d al Qibl\u012byah",
        "\u2018Izbat Iky\u0101d"
    ],
    "wof:name":"`Izbat Ikyad",
    "wof:placetype":"locality"
},
  "geometry": {"coordinates":[31.87526,30.73978],"type":"Point"}
}