{
  "type": "Feature",
  "properties": {
    "gn:admin1_code":"12",
    "gn:asciiname":"Al Hasafah",
    "gn:country_code":"EG",
    "gn:dem":20,
    "gn:feature_class":"P",
    "gn:feature_code":"PPL",
    "gn:name":"Al \u1e28a\u015f\u0101fah",
    "gn:population":0,
    "gn:timezone":"Africa/Cairo",
    "iso:country":"EG",
    "name:ara_x_preferred":[
        "\u0627\u0644\u062d\u0635\u0627\u0641\u0629\u200e"
    ],
    "name:und_x_variant":[
        "El-\u1e24i\u1e63afa",
        "Al \u1e28a\u015f\u0101fah"
    ],
    "wof:name":"Al Hasafah",
    "wof:placetype":"locality"
},
  "geometry": {"coordinates":[31.27415,30.30905],"type":"Point"}
}