{
  "type": "Feature",
  "properties": {
    "gn:admin1_code":"02",
    "gn:asciiname":"Nazlat al Harajat",
    "gn:country_code":"EG",
    "gn:dem":52,
    "gn:feature_class":"P",
    "gn:feature_code":"PPL",
    "gn:name":"Nazlat al \u1e28araj\u0101t",
    "gn:population":0,
    "gn:timezone":"Africa/Cairo",
    "iso:country":"EG",
    "wof:name":"Nazlat al Harajat",
    "wof:placetype":"locality"
},
  "geometry": {"coordinates":[31.05204,27.31464],"type":"Point"}
}