{
  "type": "Feature",
  "properties": {
    "gn:admin1_code":"14",
    "gn:asciiname":"`Izbat Tall ar Rakham",
    "gn:country_code":"EG",
    "gn:dem":13,
    "gn:feature_class":"P",
    "gn:feature_code":"PPL",
    "gn:name":"\u2018Izbat Tall ar Rakham",
    "gn:population":0,
    "gn:timezone":"Africa/Cairo",
    "iso:country":"EG",
    "name:ara_x_preferred":[
        "\u0639\u0632\u0628\u0629 \u062a\u0644 \u0627\u0644\u0631\u062e\u0645"
    ],
    "name:und_x_variant":[
        "\u2018Ezbet Tall el-Rakham",
        "\u2018Izbat Tall ar Rakham"
    ],
    "wof:name":"`Izbat Tall ar Rakham",
    "wof:placetype":"locality"
},
  "geometry": {"coordinates":[31.7231,30.52545],"type":"Point"}
}