{
  "type": "Feature",
  "properties": {
    "gn:admin1_code":"21",
    "gn:asciiname":"`Izbah Raqm Khamsah wa Sittun",
    "gn:country_code":"EG",
    "gn:dem":2,
    "gn:feature_class":"P",
    "gn:feature_code":"PPL",
    "gn:name":"\u2018Izbah Raqm Khamsah wa Sitt\u016bn",
    "gn:population":0,
    "gn:timezone":"Africa/Cairo",
    "iso:country":"EG",
    "name:ara_x_preferred":[
        "\u0639\u0632\u0628\u0629 \u0631\u0642\u0645 \u0666\u0665"
    ],
    "name:ara_x_variant":[
        "\u0639\u0632\u0628\u0629 \u0631\u0642\u0645 65"
    ],
    "name:und_x_variant":[
        "\u2018Izbah Raqm Khamsah wa Sitt\u016bn",
        "\u2018Izbah Raqm 65"
    ],
    "wof:name":"`Izbah Raqm Khamsah wa Sittun",
    "wof:placetype":"locality"
},
  "geometry": {"coordinates":[31.06739,31.46943],"type":"Point"}
}