{
  "type": "Feature",
  "properties": {
    "gn:admin1_code":"03",
    "gn:asciiname":"`Izbat Murad Makram",
    "gn:country_code":"EG",
    "gn:dem":2,
    "gn:feature_class":"P",
    "gn:feature_code":"PPL",
    "gn:name":"\u2018Izbat Mur\u0101d Makram",
    "gn:population":0,
    "gn:timezone":"Africa/Cairo",
    "iso:country":"EG",
    "name:ara_x_preferred":[
        "\u0639\u0632\u0628\u0629 \u0645\u0631\u0627\u062f \u0645\u0643\u0631\u0645"
    ],
    "name:und_x_variant":[
        "\u2018Izbat Mur\u0101d Makram"
    ],
    "wof:name":"`Izbat Murad Makram",
    "wof:placetype":"locality"
},
  "geometry": {"coordinates":[30.52133,31.03564],"type":"Point"}
}