{
  "type": "Feature",
  "properties": {
    "gn:admin1_code":"05",
    "gn:asciiname":"`Izbat `Ali Sabrah wa Shurakah",
    "gn:country_code":"EG",
    "gn:dem":4,
    "gn:feature_class":"P",
    "gn:feature_code":"PPL",
    "gn:name":"\u2018Izbat \u2018Al\u012b \u015eabrah wa Shurak\u0101h",
    "gn:population":0,
    "gn:timezone":"Africa/Cairo",
    "iso:country":"EG",
    "name:ara_x_preferred":[
        "\u0639\u0632\u0628\u0629 \u0639\u0644\u064a \u0635\u0628\u0631\u0629 \u0648 \u0634\u0631\u0643\u0627\u0629"
    ],
    "name:und_x_variant":[
        "\u2018Izbat \u2018Al\u012b \u015eabrah wa Shurak\u0101h",
        "\u2018Izbat \u2018Al\u012b \u1e62abrah & Shurak\u0101h"
    ],
    "wof:name":"`Izbat `Ali Sabrah wa Shurakah",
    "wof:placetype":"locality"
},
  "geometry": {"coordinates":[31.17787,31.08631],"type":"Point"}
}