{
  "type": "Feature",
  "properties": {
    "gn:admin1_code":"14",
    "gn:asciiname":"`Izbat al Muhami",
    "gn:country_code":"EG",
    "gn:dem":13,
    "gn:feature_class":"P",
    "gn:feature_code":"PPL",
    "gn:name":"\u2018Izbat al Mu\u1e29\u0101m\u012b",
    "gn:population":0,
    "gn:timezone":"Africa/Cairo",
    "iso:country":"EG",
    "name:ara_x_preferred":[
        "\u0639\u0632\u0628\u0629 \u0627\u0644\u0645\u062d\u0627\u0645\u064a"
    ],
    "name:und_x_variant":[
        "\u2018Izbat al Mu\u1e29\u0101m\u012b"
    ],
    "wof:name":"`Izbat al Muhami",
    "wof:placetype":"locality"
},
  "geometry": {"coordinates":[31.5036,30.45919],"type":"Point"}
}