{
  "type": "Feature",
  "properties": {
    "gn:admin1_code":"21",
    "gn:asciiname":"`Izbat Muhammad Hamzah",
    "gn:country_code":"EG",
    "gn:dem":5,
    "gn:feature_class":"P",
    "gn:feature_code":"PPL",
    "gn:name":"\u2018Izbat Mu\u1e29ammad \u1e28amzah",
    "gn:population":0,
    "gn:timezone":"Africa/Cairo",
    "iso:country":"EG",
    "name:ara_x_preferred":[
        "\u0639\u0632\u0628\u0629 \u0645\u062d\u0645\u062f \u062d\u0645\u0632\u0629"
    ],
    "name:und_x_variant":[
        "\u2018Izbat Mu\u1e29ammad \u1e28amzah"
    ],
    "wof:name":"`Izbat Muhammad Hamzah",
    "wof:placetype":"locality"
},
  "geometry": {"coordinates":[30.9334,31.33912],"type":"Point"}
}