{
  "type": "Feature",
  "properties": {
    "gn:admin1_code":"03",
    "gn:asciiname":"Bastarah",
    "gn:country_code":"EG",
    "gn:dem":5,
    "gn:feature_class":"P",
    "gn:feature_code":"PPL",
    "gn:name":"Bas\u0163arah",
    "gn:population":0,
    "gn:timezone":"Africa/Cairo",
    "iso:country":"EG",
    "name:ara_x_preferred":[
        "\u0628\u0633\u0637\u0631\u0629"
    ],
    "name:und_x_variant":[
        "Bas\u1e6dara",
        "Bas\u0163arah",
        "Bas\u1e6darah"
    ],
    "wof:name":"Bastarah",
    "wof:placetype":"locality"
},
  "geometry": {"coordinates":[30.42423,31.07671],"type":"Point"}
}