{
  "type": "Feature",
  "properties": {
    "gn:admin1_code":"03",
    "gn:asciiname":"`Izbat as Sayyad",
    "gn:country_code":"EG",
    "gn:dem":4,
    "gn:feature_class":"P",
    "gn:feature_code":"PPL",
    "gn:name":"\u2018Izbat a\u015f \u015eayy\u0101d",
    "gn:population":0,
    "gn:timezone":"Africa/Cairo",
    "iso:country":"EG",
    "wof:name":"`Izbat as Sayyad",
    "wof:placetype":"locality"
},
  "geometry": {"coordinates":[30.55199,30.98389],"type":"Point"}
}