{
  "type": "Feature",
  "properties": {
    "gn:admin1_code":"21",
    "gn:asciiname":"Rashid",
    "gn:country_code":"EG",
    "gn:dem":3,
    "gn:feature_class":"P",
    "gn:feature_code":"PPL",
    "gn:name":"R\u0101shid",
    "gn:population":0,
    "gn:timezone":"Africa/Cairo",
    "iso:country":"EG",
    "name:ara_x_preferred":[
        "\u0631\u0627\u0634\u062f"
    ],
    "name:ara_x_variant":[
        "\u0631\u0634\u064a\u062f"
    ],
    "name:aze_x_preferred":[
        "R\u0259\u015fid"
    ],
    "name:bul_x_preferred":[
        "\u0420\u0430\u0448\u0438\u0434"
    ],
    "name:deu_x_preferred":[
        "Raschid"
    ],
    "name:fra_x_preferred":[
        "Rachid"
    ],
    "name:ita_x_preferred":[
        "Rashid"
    ],
    "name:kaz_x_preferred":[
        "\u0420\u0430\u0448\u0438\u0434 \u049b\u0430\u043b\u0430\u0441\u044b"
    ],
    "name:por_x_preferred":[
        "Rashid"
    ],
    "name:rus_x_preferred":[
        "\u0420\u0430\u0448\u0438\u0434"
    ],
    "name:swe_x_preferred":[
        "Rashid"
    ],
    "name:und_x_variant":[
        "R\u0101shid"
    ],
    "wof:name":"Rashid",
    "wof:placetype":"locality"
},
  "geometry": {"coordinates":[30.74225,31.27043],"type":"Point"}
}