{
  "type": "Feature",
  "properties": {
    "gn:admin1_code":"23",
    "gn:asciiname":"Naj` al Bashshariyah",
    "gn:country_code":"EG",
    "gn:dem":79,
    "gn:feature_class":"P",
    "gn:feature_code":"PPL",
    "gn:name":"Naj\u2018 al Bashsh\u0101r\u012byah",
    "gn:population":0,
    "gn:timezone":"Africa/Cairo",
    "iso:country":"EG",
    "name:und_x_variant":[
        "\u2018Arab al \u2018Ab\u0101\u2019idah",
        "Nag\u2018 el Bash\u00e2r\u00eeya",
        "\u2018Arab el \u2018Ab\u00e2bda",
        "Naj\u2018 al Bashsh\u0101r\u012byah"
    ],
    "wof:name":"Naj` al Bashshariyah",
    "wof:placetype":"locality"
},
  "geometry": {"coordinates":[32.81406,26.08109],"type":"Point"}
}