{
  "type": "Feature",
  "properties": {
    "gn:admin1_code":"14",
    "gn:asciiname":"As Salatinah",
    "gn:country_code":"EG",
    "gn:dem":11,
    "gn:feature_class":"P",
    "gn:feature_code":"PPL",
    "gn:name":"As Sal\u0101\u0163inah",
    "gn:population":0,
    "gn:timezone":"Africa/Cairo",
    "iso:country":"EG",
    "name:ara_x_preferred":[
        "\u0627\u0644\u0633\u0644\u0627\u0637\u0646\u0629"
    ],
    "name:und_x_variant":[
        "As Sal\u0101\u0163inah",
        "Qaryat as-Sal\u0101\u1e6dnah"
    ],
    "wof:name":"As Salatinah",
    "wof:placetype":"locality"
},
  "geometry": {"coordinates":[31.75215,30.74008],"type":"Point"}
}