{
  "type": "Feature",
  "properties": {
    "gn:admin1_code":"24",
    "gn:asciiname":"Mishta",
    "gn:country_code":"EG",
    "gn:dem":65,
    "gn:feature_class":"P",
    "gn:feature_code":"PPL",
    "gn:name":"Mish\u0163\u0101",
    "gn:population":0,
    "gn:timezone":"Africa/Cairo",
    "iso:country":"EG",
    "wof:name":"Mishta",
    "wof:placetype":"locality"
},
  "geometry": {"coordinates":[31.4727,26.86405],"type":"Point"}
}