{
  "type": "Feature",
  "properties": {
    "gn:admin1_code":"01",
    "gn:asciiname":"`Izbat Jabr",
    "gn:country_code":"EG",
    "gn:dem":8,
    "gn:feature_class":"P",
    "gn:feature_code":"PPL",
    "gn:name":"\u2018Izbat Jabr",
    "gn:population":0,
    "gn:timezone":"Africa/Cairo",
    "iso:country":"EG",
    "name:und_x_variant":[
        "\u2018Izbat Jabr",
        "\u0639\u0632\u0628\u0629 \u062c\u0628\u0631",
        "\u2018Iz. Jabr"
    ],
    "wof:name":"`Izbat Jabr",
    "wof:placetype":"locality"
},
  "geometry": {"coordinates":[31.48617,30.8563],"type":"Point"}
}