{
  "type": "Feature",
  "properties": {
    "gn:admin1_code":"14",
    "gn:asciiname":"`Izbat al Ku`",
    "gn:country_code":"EG",
    "gn:dem":11,
    "gn:feature_class":"P",
    "gn:feature_code":"PPL",
    "gn:name":"\u2018Izbat al K\u016b\u2018",
    "gn:population":0,
    "gn:timezone":"Africa/Cairo",
    "iso:country":"EG",
    "name:ara_x_preferred":[
        "\u0639\u0632\u0628\u0629 \u0627\u0644\u0643\u0648\u0639"
    ],
    "name:und_x_variant":[
        "\u2018Izbat al K\u016b\u2018"
    ],
    "wof:name":"`Izbat al Ku`",
    "wof:placetype":"locality"
},
  "geometry": {"coordinates":[31.92711,30.5237],"type":"Point"}
}