{
  "type": "Feature",
  "properties": {
    "gn:admin1_code":"14",
    "gn:asciiname":"`Izbat Salih Badr",
    "gn:country_code":"EG",
    "gn:dem":14,
    "gn:feature_class":"P",
    "gn:feature_code":"PPL",
    "gn:name":"\u2018Izbat \u015e\u0101li\u1e29 Badr",
    "gn:population":0,
    "gn:timezone":"Africa/Cairo",
    "iso:country":"EG",
    "name:ara_x_preferred":[
        "\u0639\u0632\u0628\u0629 \u0635\u0627\u0644\u062d \u0628\u062f\u0631"
    ],
    "name:und_x_variant":[
        "\u2018Izbat \u015e\u0101li\u1e29 Badr"
    ],
    "wof:name":"`Izbat Salih Badr",
    "wof:placetype":"locality"
},
  "geometry": {"coordinates":[31.68494,30.57869],"type":"Point"}
}