{
  "type": "Feature",
  "properties": {
    "gn:admin1_code":"14",
    "gn:asciiname":"`Izbat as Sajjad",
    "gn:country_code":"EG",
    "gn:dem":9,
    "gn:feature_class":"P",
    "gn:feature_code":"PPL",
    "gn:name":"\u2018Izbat as Sajj\u0101d",
    "gn:population":0,
    "gn:timezone":"Africa/Cairo",
    "iso:country":"EG",
    "name:ara_x_preferred":[
        "\u0639\u0632\u0628\u0629 \u0627\u0644\u0633\u062c\u0627\u062f"
    ],
    "name:und_x_variant":[
        "\u2018Izbat as Sajj\u0101d",
        "\u2018Izbat as Sijj\u0101d"
    ],
    "wof:name":"`Izbat as Sajjad",
    "wof:placetype":"locality"
},
  "geometry": {"coordinates":[31.63904,30.70182],"type":"Point"}
}