{
  "type": "Feature",
  "properties": {
    "gn:admin1_code":"10",
    "gn:asciiname":"Bani `Ali",
    "gn:country_code":"EG",
    "gn:dem":36,
    "gn:feature_class":"P",
    "gn:feature_code":"PPL",
    "gn:name":"Ban\u012b \u2018Al\u012b",
    "gn:population":0,
    "gn:timezone":"Africa/Cairo",
    "iso:country":"EG",
    "name:ara_x_preferred":[
        "\u0628\u0646\u0649 \u0639\u0644\u0649"
    ],
    "name:und_x_variant":[
        "Beni Ali",
        "Ban\u012b \u2018Al\u012b"
    ],
    "wof:name":"Bani `Ali",
    "wof:placetype":"locality"
},
  "geometry": {"coordinates":[30.71938,28.47818],"type":"Point"}
}