{
  "type": "Feature",
  "properties": {
    "gn:admin1_code":"09",
    "gn:asciiname":"Ar Rimali",
    "gn:country_code":"EG",
    "gn:dem":15,
    "gn:feature_class":"P",
    "gn:feature_code":"PPL",
    "gn:name":"Ar Rim\u0101l\u012b",
    "gn:population":0,
    "gn:timezone":"Africa/Cairo",
    "iso:country":"EG",
    "name:ara_x_preferred":[
        "\u0627\u0644\u0631\u0645\u0627\u0644\u064a"
    ],
    "name:und_x_variant":[
        "El-Rim\u00e2li",
        "Ar Rim\u0101l\u012b"
    ],
    "wof:name":"Ar Rimali",
    "wof:placetype":"locality"
},
  "geometry": {"coordinates":[31.14541,30.59736],"type":"Point"}
}