{
  "type": "Feature",
  "properties": {
    "gn:admin1_code":"14",
    "gn:asciiname":"`Izbat Ayyub",
    "gn:country_code":"EG",
    "gn:dem":3,
    "gn:feature_class":"P",
    "gn:feature_code":"PPL",
    "gn:name":"\u2018Izbat Ayy\u016bb",
    "gn:population":0,
    "gn:timezone":"Africa/Cairo",
    "iso:country":"EG",
    "name:ara_x_preferred":[
        "\u0639\u0632\u0628\u0629 \u0623\u064a\u0648\u0628"
    ],
    "name:und_x_variant":[
        "\u2018Izbat Ayy\u016bb"
    ],
    "wof:name":"`Izbat Ayyub",
    "wof:placetype":"locality"
},
  "geometry": {"coordinates":[31.82775,31.01858],"type":"Point"}
}