{
  "type": "Feature",
  "properties": {
    "gn:admin1_code":"23",
    "gn:asciiname":"Awlad Nijm Bahjurah",
    "gn:country_code":"EG",
    "gn:dem":70,
    "gn:feature_class":"P",
    "gn:feature_code":"PPL",
    "gn:name":"Awl\u0101d Nijm Bahj\u016brah",
    "gn:population":0,
    "gn:timezone":"Africa/Cairo",
    "iso:country":"EG",
    "name:und_x_variant":[
        "Aul\u0101d Nigm Bahg\u016bra",
        "Awl\u0101d Najm Bahjur\u0101h",
        "Awl\u0101d Nijm Bahj\u016brah"
    ],
    "wof:name":"Awlad Nijm Bahjurah",
    "wof:placetype":"locality"
},
  "geometry": {"coordinates":[32.20733,26.0867],"type":"Point"}
}