{
  "type": "Feature",
  "properties": {
    "gn:admin1_code":"14",
    "gn:asciiname":"`Izbat al Maghribi al `Azimah",
    "gn:country_code":"EG",
    "gn:dem":4,
    "gn:feature_class":"P",
    "gn:feature_code":"PPL",
    "gn:name":"\u2018Izbat al Maghrib\u012b al \u2018Az\u0327\u012bmah",
    "gn:population":0,
    "gn:timezone":"Africa/Cairo",
    "iso:country":"EG",
    "name:ara_x_preferred":[
        "\u0639\u0632\u0628\u0629 \u0627\u0644\u0645\u063a\u0631\u0628\u064a \u0627\u0644\u0639\u0638\u064a\u0645\u0629"
    ],
    "name:ara_x_variant":[
        "\u0627\u0644\u0646\u062d\u0627\u0633\u064a\u0646"
    ],
    "name:und_x_variant":[
        "\u2018Izbat al Maghrib\u012b al \u2018Az\u0327\u012bmah",
        "An Na\u1e29\u1e29\u0101s\u012bn"
    ],
    "wof:name":"`Izbat al Maghribi al `Azimah",
    "wof:placetype":"locality"
},
  "geometry": {"coordinates":[31.82919,30.88993],"type":"Point"}
}