{
  "type": "Feature",
  "properties": {
    "gn:admin1_code":"01",
    "gn:asciiname":"`Izbat Binyamin",
    "gn:country_code":"EG",
    "gn:dem":4,
    "gn:feature_class":"P",
    "gn:feature_code":"PPL",
    "gn:name":"\u2018Izbat Biny\u0101m\u012bn",
    "gn:population":0,
    "gn:timezone":"Africa/Cairo",
    "iso:country":"EG",
    "name:ara_x_preferred":[
        "\u0639\u0632\u0628\u0629 \u0628\u0646\u064a\u0627\u0645\u064a\u0646"
    ],
    "name:und_x_variant":[
        "\u2018Izbat Biny\u0101m\u012bn"
    ],
    "wof:name":"`Izbat Binyamin",
    "wof:placetype":"locality"
},
  "geometry": {"coordinates":[31.60158,31.25438],"type":"Point"}
}