{
  "type": "Feature",
  "properties": {
    "gn:admin1_code":"03",
    "gn:asciiname":"`Izbat Tu`mah",
    "gn:country_code":"EG",
    "gn:dem":-4,
    "gn:feature_class":"P",
    "gn:feature_code":"PPL",
    "gn:name":"\u2018Izbat \u0162u\u2018mah",
    "gn:population":0,
    "gn:timezone":"Africa/Cairo",
    "iso:country":"EG",
    "name:ara_x_preferred":[
        "\u0639\u0632\u0628\u0629 \u0637\u0639\u0645\u0629"
    ],
    "name:und_x_variant":[
        "\u2018Ezbat Ism\u00e2\u2018\u00eel \u1e24amza",
        "\u2018Izbat Sal\u012bm \u0162u\u2018mah",
        "\u2018Izbat \u0162u\u2018mah",
        "\u2018Ezbet Ism\u00e2\u2018\u00eel \u1e24amza"
    ],
    "wof:name":"`Izbat Tu`mah",
    "wof:placetype":"locality"
},
  "geometry": {"coordinates":[30.15837,31.02213],"type":"Point"}
}