{
  "type": "Feature",
  "properties": {
    "gn:admin1_code":"14",
    "gn:asciiname":"`Izbat al Jumhuriyah",
    "gn:country_code":"EG",
    "gn:dem":19,
    "gn:feature_class":"P",
    "gn:feature_code":"PPL",
    "gn:name":"\u2018Izbat al Jumh\u016br\u012byah",
    "gn:population":0,
    "gn:timezone":"Africa/Cairo",
    "iso:country":"EG",
    "name:ara_x_preferred":[
        "\u0639\u0632\u0628\u0629 \u0627\u0644\u062c\u0645\u0647\u0648\u0631\u064a\u0629"
    ],
    "name:und_x_variant":[
        "\u2018Izbat al Jumh\u016br\u012byah"
    ],
    "wof:name":"`Izbat al Jumhuriyah",
    "wof:placetype":"locality"
},
  "geometry": {"coordinates":[31.542,30.37569],"type":"Point"}
}