{
  "type": "Feature",
  "properties": {
    "gn:admin1_code":"23",
    "gn:asciiname":"Awlad `Amr",
    "gn:country_code":"EG",
    "gn:dem":80,
    "gn:feature_class":"P",
    "gn:feature_code":"PPL",
    "gn:name":"Awl\u0101d \u2018Amr",
    "gn:population":0,
    "gn:timezone":"Africa/Cairo",
    "iso:country":"EG",
    "name:ara_x_preferred":[
        "\u0627\u0648\u0644\u0627\u062f \u0639\u0645\u0631\u0648"
    ],
    "name:und_x_variant":[
        "Aul\u00e2d \u2018Amr",
        "Awl\u0101d \u2018Amr"
    ],
    "wof:name":"Awlad `Amr",
    "wof:placetype":"locality"
},
  "geometry": {"coordinates":[32.59794,26.1451],"type":"Point"}
}