{
  "type": "Feature",
  "properties": {
    "iso:country":"EG",
    "qs:gn_pop":0,
    "qs:name":"\u0643\u0631\u062f\u0627\u0633\u0629",
    "qs:name_adm0":"\u0645\u0635\u0631",
    "qs:name_adm1":"\u0627\u0644\u062c\u064a\u0632\u0629",
    "qs:photos":4145,
    "qs:photos_1k":840,
    "qs:photos_9k":18,
    "qs:photos_9r":12,
    "qs:photos_all":4145,
    "qs:photos_sr":22,
    "qs:placetype":"Town",
    "qs:pop_sr":"0",
    "qs:woe_adm0":23424802,
    "wof:name":"\u0643\u0631\u062f\u0627\u0633\u0629",
    "wof:placetype":"locality"
},
  "geometry": {"coordinates":[31.132721,29.977092],"type":"Point"}
}