{
  "type": "Feature",
  "properties": {
    "gn:admin1_code":"14",
    "gn:asciiname":"`Izbat Raqam al Hadiyat `Ashar",
    "gn:country_code":"EG",
    "gn:dem":3,
    "gn:feature_class":"P",
    "gn:feature_code":"PPL",
    "gn:name":"\u2018Izbat Raqam al \u1e28\u0101diyat \u2018Ashar",
    "gn:population":0,
    "gn:timezone":"Africa/Cairo",
    "iso:country":"EG",
    "name:ara_x_preferred":[
        "\u0639\u0632\u0628\u0629 \u0631\u0642\u0645 \u0627\u0644\u062d\u0627\u062f\u064a\u0629 \u0639\u0634\u0631"
    ],
    "name:und_x_variant":[
        "\u2018Izbat Raqam al \u1e28\u0101diyat \u2018Ashar",
        "\u2018Izbat Number Eleven"
    ],
    "wof:name":"`Izbat Raqam al Hadiyat `Ashar",
    "wof:placetype":"locality"
},
  "geometry": {"coordinates":[31.88091,31.06334],"type":"Point"}
}