{
  "type": "Feature",
  "properties": {
    "gn:admin1_code":"14",
    "gn:asciiname":"`Izbat `Abd al Latif Shalabi",
    "gn:country_code":"EG",
    "gn:dem":5,
    "gn:feature_class":"P",
    "gn:feature_code":"PPL",
    "gn:name":"\u2018Izbat \u2018Abd al La\u0163\u012bf Shalab\u012b",
    "gn:population":0,
    "gn:timezone":"Africa/Cairo",
    "iso:country":"EG",
    "name:ara_x_preferred":[
        "\u0639\u0632\u0628\u0629 \u0639\u0628\u062f \u0627\u0644\u0644\u0637\u064a\u0641 \u0634\u0644\u0628\u064a"
    ],
    "name:und_x_variant":[
        "\u2018Izbat \u2018Abd al La\u0163\u012bf Shalab\u012b",
        "\u2018Izbat \u2018Abd al-La\u1e6d\u012bf Shalab\u012b"
    ],
    "wof:name":"`Izbat `Abd al Latif Shalabi",
    "wof:placetype":"locality"
},
  "geometry": {"coordinates":[31.8015,31.01414],"type":"Point"}
}