{
  "type": "Feature",
  "properties": {
    "gn:admin1_code":"21",
    "gn:asciiname":"`Izbat al Ghubaysi",
    "gn:country_code":"EG",
    "gn:dem":8,
    "gn:feature_class":"P",
    "gn:feature_code":"PPL",
    "gn:name":"\u2018Izbat al Ghubays\u012b",
    "gn:population":0,
    "gn:timezone":"Africa/Cairo",
    "iso:country":"EG",
    "name:ara_x_preferred":[
        "\u0639\u0632\u0628\u0629 \u0627\u0644\u063a\u0628\u064a\u0633\u064a"
    ],
    "name:und_x_variant":[
        "\u2018Izbat al Ghubays\u012b"
    ],
    "wof:name":"`Izbat al Ghubaysi",
    "wof:placetype":"locality"
},
  "geometry": {"coordinates":[30.84015,31.22439],"type":"Point"}
}