{
  "type": "Feature",
  "properties": {
    "gn:admin1_code":"22",
    "gn:asciiname":"Kafret `Eilet Imshazz",
    "gn:country_code":"EG",
    "gn:dem":62,
    "gn:feature_class":"P",
    "gn:feature_code":"PPL",
    "gn:name":"Kafret \u2018Eilet Imsh\u00e2zz",
    "gn:population":0,
    "gn:timezone":"Africa/Cairo",
    "iso:country":"EG",
    "wof:name":"Kafret `Eilet Imshazz",
    "wof:placetype":"locality"
},
  "geometry": {"coordinates":[26.51667,31.46667],"type":"Point"}
}