{
  "type": "Feature",
  "properties": {
    "gn:admin1_code":"09",
    "gn:asciiname":"Qalata al Kubra",
    "gn:country_code":"EG",
    "gn:dem":16,
    "gn:feature_class":"P",
    "gn:feature_code":"PPL",
    "gn:name":"Qalat\u00e1 al Kubr\u00e1",
    "gn:population":0,
    "gn:timezone":"Africa/Cairo",
    "iso:country":"EG",
    "name:ara_x_preferred":[
        "\u0642\u0644\u062a\u0649 \u0627\u0644\u0643\u0628\u0631\u0649"
    ],
    "name:und_x_variant":[
        "Qalata el-Kubra",
        "Qalat\u00e1 al Kubr\u00e1"
    ],
    "wof:name":"Qalata al Kubra",
    "wof:placetype":"locality"
},
  "geometry": {"coordinates":[31.01471,30.36993],"type":"Point"}
}