{
  "type": "Feature",
  "properties": {
    "gn:admin1_code":"01",
    "gn:asciiname":"`Izbat `Abd al Latif al Mikbati",
    "gn:country_code":"EG",
    "gn:dem":4,
    "gn:feature_class":"P",
    "gn:feature_code":"PPL",
    "gn:name":"\u2018Izbat \u2018Abd al La\u0163\u012bf al Mikb\u0101t\u012b",
    "gn:population":0,
    "gn:timezone":"Africa/Cairo",
    "iso:country":"EG",
    "name:ara_x_preferred":[
        "\u0639\u0632\u0628\u0629 \u0639\u0628\u062f \u0627\u0644\u0644\u0637\u064a\u0641 \u0627\u0644\u0645\u0643\u0628\u0627\u062a\u064a"
    ],
    "name:und_x_variant":[
        "\u2018Izbat \u2018Abd al La\u0163\u012bf al Mikb\u0101t\u012b",
        "\u2018Izbat \u2018Abd al Lat\u012bf al Makabb\u0101t\u012b",
        "\u2018Iz. \u2018Abd Al-La\u1e6d\u012bf al-Makabb\u0101t\u012b"
    ],
    "wof:name":"`Izbat `Abd al Latif al Mikbati",
    "wof:placetype":"locality"
},
  "geometry": {"coordinates":[31.74693,31.12422],"type":"Point"}
}