{
  "type": "Feature",
  "properties": {
    "gn:admin1_code":"05",
    "gn:asciiname":"`Izbat Ahmad as Safta",
    "gn:country_code":"EG",
    "gn:dem":10,
    "gn:feature_class":"P",
    "gn:feature_code":"PPL",
    "gn:name":"\u2018Izbat A\u1e29mad a\u015f \u015eaft\u0101",
    "gn:population":0,
    "gn:timezone":"Africa/Cairo",
    "iso:country":"EG",
    "name:ara_x_preferred":[
        "\u0639\u0632\u0628\u0629 \u0627\u062d\u0645\u062f \u0627\u0644\u0635\u0641\u062a\u0649"
    ],
    "name:und_x_variant":[
        "\u2018Izbat A\u1e29mad a\u015f \u015eaft\u0101"
    ],
    "wof:name":"`Izbat Ahmad as Safta",
    "wof:placetype":"locality"
},
  "geometry": {"coordinates":[31.15061,30.70328],"type":"Point"}
}