{
  "type": "Feature",
  "properties": {
    "gn:admin1_code":"21",
    "gn:asciiname":"`Izbah Raqm Thamanun",
    "gn:country_code":"EG",
    "gn:dem":4,
    "gn:feature_class":"P",
    "gn:feature_code":"PPL",
    "gn:name":"\u2018Izbah Raqm Tham\u0101n\u016bn",
    "gn:population":0,
    "gn:timezone":"Africa/Cairo",
    "iso:country":"EG",
    "name:ara_x_preferred":[
        "\u0639\u0632\u0628\u0629 \u0631\u0642\u0645 \u0668\u0660"
    ],
    "name:ara_x_variant":[
        "\u0639\u0632\u0628\u0629 \u0631\u0642\u0645 80"
    ],
    "name:und_x_variant":[
        "\u2018Izbah Raqm Tham\u0101n\u016bn",
        "\u2018Izbah Raqm 80"
    ],
    "wof:name":"`Izbah Raqm Thamanun",
    "wof:placetype":"locality"
},
  "geometry": {"coordinates":[31.16579,31.3774],"type":"Point"}
}