{
  "type": "Feature",
  "properties": {
    "gn:admin1_code":"03",
    "gn:asciiname":"`Izbat Abu Gharib",
    "gn:country_code":"EG",
    "gn:dem":0,
    "gn:feature_class":"P",
    "gn:feature_code":"PPL",
    "gn:name":"\u2018Izbat Ab\u016b Ghar\u012bb",
    "gn:population":0,
    "gn:timezone":"Africa/Cairo",
    "iso:country":"EG",
    "name:und_x_variant":[
        "\u2018Ezbet Ghar\u00eeb",
        "\u2018Izbat Ab\u016b Ghar\u012bb"
    ],
    "wof:name":"`Izbat Abu Gharib",
    "wof:placetype":"locality"
},
  "geometry": {"coordinates":[30.21032,30.92585],"type":"Point"}
}