{
  "type": "Feature",
  "properties": {
    "gn:admin1_code":"28",
    "gn:asciiname":"Naj` al `Arab",
    "gn:country_code":"EG",
    "gn:dem":83,
    "gn:feature_class":"P",
    "gn:feature_code":"PPL",
    "gn:name":"Naj\u2018 al \u2018Arab",
    "gn:population":0,
    "gn:timezone":"Africa/Cairo",
    "iso:country":"EG",
    "name:ara_x_preferred":[
        "\u0646\u062c\u0639 \u0627\u0644\u0639\u0631\u0628"
    ],
    "name:und_x_variant":[
        "Naj\u2018 al \u2018Arab",
        "Naj\u2018 al-\u2018Arab"
    ],
    "wof:name":"Naj` al `Arab",
    "wof:placetype":"locality"
},
  "geometry": {"coordinates":[32.71024,25.68763],"type":"Point"}
}