{
  "type": "Feature",
  "properties": {
    "gn:admin1_code":"14",
    "gn:asciiname":"Kafr Abu Jad",
    "gn:country_code":"EG",
    "gn:dem":12,
    "gn:feature_class":"P",
    "gn:feature_code":"PPL",
    "gn:name":"Kafr Ab\u016b J\u0101d",
    "gn:population":0,
    "gn:timezone":"Africa/Cairo",
    "iso:country":"EG",
    "name:ara_x_preferred":[
        "\u0643\u0641\u0631 \u0623\u0628\u0648 \u062c\u0627\u062f"
    ],
    "name:und_x_variant":[
        "Kafr Ab\u016b J\u0101d"
    ],
    "wof:name":"Kafr Abu Jad",
    "wof:placetype":"locality"
},
  "geometry": {"coordinates":[31.73164,30.65849],"type":"Point"}
}