{
  "type": "Feature",
  "properties": {
    "gn:admin1_code":"03",
    "gn:asciiname":"Mahallat al Amir",
    "gn:country_code":"EG",
    "gn:dem":9,
    "gn:feature_class":"P",
    "gn:feature_code":"PPL",
    "gn:name":"Ma\u1e29allat al Am\u012br",
    "gn:population":0,
    "gn:timezone":"Africa/Cairo",
    "iso:country":"EG",
    "name:ara_x_preferred":[
        "\u0645\u062d\u0644\u0629 \u0627\u0644\u0623\u0645\u064a\u0631"
    ],
    "name:und_x_variant":[
        "Mahallet el-Emir",
        "Ma\u1e25allet el-Am\u00eer",
        "Ma\u1e29allat al Am\u012br",
        "Ma\u1e25allat al-Am\u012br"
    ],
    "wof:name":"Mahallat al Amir",
    "wof:placetype":"locality"
},
  "geometry": {"coordinates":[30.48969,31.3402],"type":"Point"}
}