{
  "type": "Feature",
  "properties": {
    "gn:admin1_code":"01",
    "gn:asciiname":"`Izbat ad Dawwar",
    "gn:country_code":"EG",
    "gn:dem":9,
    "gn:feature_class":"P",
    "gn:feature_code":"PPL",
    "gn:name":"\u2018Izbat ad Daww\u0101r",
    "gn:population":0,
    "gn:timezone":"Africa/Cairo",
    "iso:country":"EG",
    "name:ara_x_preferred":[
        "\u0639\u0632\u0628\u0629 \u0627\u0644\u062f\u0648\u0627\u0631"
    ],
    "name:und_x_variant":[
        "\u2018Izbat ad Daww\u0101r",
        "\u2018Izbat ad-Daww\u0101r"
    ],
    "wof:name":"`Izbat ad Dawwar",
    "wof:placetype":"locality"
},
  "geometry": {"coordinates":[31.47284,31.22397],"type":"Point"}
}