{
  "type": "Feature",
  "properties": {
    "gn:admin1_code":"14",
    "gn:asciiname":"`Izbat Ahmad Rizq",
    "gn:country_code":"EG",
    "gn:dem":10,
    "gn:feature_class":"P",
    "gn:feature_code":"PPL",
    "gn:name":"\u2018Izbat A\u1e29mad Rizq",
    "gn:population":0,
    "gn:timezone":"Africa/Cairo",
    "iso:country":"EG",
    "name:ara_x_preferred":[
        "\u0639\u0632\u0628\u0629 \u0627\u062d\u0645\u062f \u0631\u0632\u0642"
    ],
    "name:und_x_variant":[
        "\u2018Izbat A\u1e29mad Rizq"
    ],
    "wof:name":"`Izbat Ahmad Rizq",
    "wof:placetype":"locality"
},
  "geometry": {"coordinates":[31.48857000000001,30.68372],"type":"Point"}
}