{
  "type": "Feature",
  "properties": {
    "gn:admin1_code":"08",
    "gn:asciiname":"Ar Riqqah al Bahriyah",
    "gn:cc2":"EG",
    "gn:country_code":"EG",
    "gn:dem":24,
    "gn:feature_class":"P",
    "gn:feature_code":"PPL",
    "gn:name":"Ar Riqqah al Ba\u1e29r\u012byah",
    "gn:population":0,
    "gn:timezone":"Africa/Cairo",
    "iso:country":"EG",
    "name:und_x_variant":[
        "El Riqqa el Sharq\u00eeya el Bahar\u00eeya",
        "Er Riqa esh Sharq\u012bya el Bahar\u012bya",
        "Ar Riqqah al Ba\u1e29r\u012byah"
    ],
    "wof:name":"Ar Riqqah al Bahriyah",
    "wof:placetype":"locality"
},
  "geometry": {"coordinates":[31.21667,29.43333],"type":"Point"}
}