{
  "type": "Feature",
  "properties": {
    "gn:admin1_code":"16",
    "gn:asciiname":"Naj` al Hawwari",
    "gn:country_code":"EG",
    "gn:dem":86,
    "gn:feature_class":"P",
    "gn:feature_code":"PPL",
    "gn:name":"Naj\u2018 al Haww\u0101r\u012b",
    "gn:population":0,
    "gn:timezone":"Africa/Cairo",
    "iso:country":"EG",
    "wof:name":"Naj` al Hawwari",
    "wof:placetype":"locality"
},
  "geometry": {"coordinates":[32.76694000000001,25.10969],"type":"Point"}
}