{
  "type": "Feature",
  "properties": {
    "gn:admin1_code":"04",
    "gn:asciiname":"`Ezab Galala",
    "gn:country_code":"EG",
    "gn:dem":-13,
    "gn:feature_class":"P",
    "gn:feature_code":"PPL",
    "gn:name":"\u2018Ezab Gal\u00e2la",
    "gn:population":0,
    "gn:timezone":"Africa/Cairo",
    "iso:country":"EG",
    "wof:name":"`Ezab Galala",
    "wof:placetype":"locality"
},
  "geometry": {"coordinates":[30.95,29.48333],"type":"Point"}
}