{
  "type": "Feature",
  "properties": {
    "gn:admin1_code":"10",
    "gn:asciiname":"Dimshaw Hashim",
    "gn:country_code":"EG",
    "gn:dem":47,
    "gn:feature_class":"P",
    "gn:feature_code":"PPL",
    "gn:name":"Dimsh\u0101w H\u0101shim",
    "gn:population":0,
    "gn:timezone":"Africa/Cairo",
    "iso:country":"EG",
    "name:ara_x_preferred":[
        "\u062f\u0645\u0634\u0627\u0648 \u0647\u0627\u0634\u0645"
    ],
    "name:und_x_variant":[
        "Dimsh\u0101w H\u0101shim"
    ],
    "wof:name":"Dimshaw Hashim",
    "wof:placetype":"locality"
},
  "geometry": {"coordinates":[30.71094,28.02296],"type":"Point"}
}