{
  "type": "Feature",
  "properties": {
    "gn:admin1_code":"09",
    "gn:asciiname":"Bihnay",
    "gn:country_code":"EG",
    "gn:dem":18,
    "gn:feature_class":"P",
    "gn:feature_code":"PPL",
    "gn:name":"Bihn\u0101y",
    "gn:population":0,
    "gn:timezone":"Africa/Cairo",
    "iso:country":"EG",
    "name:ara_x_preferred":[
        "Bihn\u0101y"
    ],
    "name:ara_x_variant":[
        "\u0628\u0647\u0646\u0627\u064a"
    ],
    "name:und_x_variant":[
        "Bahn\u00e2i"
    ],
    "wof:name":"Bihnay",
    "wof:placetype":"locality"
},
  "geometry": {"coordinates":[31.06978,30.39271],"type":"Point"}
}