{
  "type": "Feature",
  "properties": {
    "gn:admin1_code":"01",
    "gn:asciiname":"Kafr at Tur`ah al Jadid",
    "gn:country_code":"EG",
    "gn:dem":6,
    "gn:feature_class":"P",
    "gn:feature_code":"PPL",
    "gn:name":"Kafr at Tur\u2018ah al Jad\u012bd",
    "gn:population":0,
    "gn:timezone":"Africa/Cairo",
    "iso:country":"EG",
    "name:ara_x_preferred":[
        "\u0643\u0641\u0631 \u0627\u0644\u062a\u0631\u0639\u0629 \u0627\u0644\u062c\u062f\u064a\u062f"
    ],
    "name:und_x_variant":[
        "Kafr el-Tir\u2018a el-Ged\u00eed",
        "Kafr at Tur\u2018ah al Jad\u012bd",
        "Kafr at-Tir\u2018ah al-Jad\u012bd"
    ],
    "wof:name":"Kafr at Tur`ah al Jadid",
    "wof:placetype":"locality"
},
  "geometry": {"coordinates":[31.62974,31.25019],"type":"Point"}
}