{
  "type": "Feature",
  "properties": {
    "gn:admin1_code":"05",
    "gn:asciiname":"Kafr al `Awayisah",
    "gn:country_code":"EG",
    "gn:dem":12,
    "gn:feature_class":"P",
    "gn:feature_code":"PPL",
    "gn:name":"Kafr al \u2018Aw\u0101yisah",
    "gn:population":0,
    "gn:timezone":"Africa/Cairo",
    "iso:country":"EG",
    "name:ara_x_preferred":[
        "\u0643\u0641\u0631 \u0627\u0644\u0639\u0648\u0627\u064a\u0633\u0629"
    ],
    "name:und_x_variant":[
        "Kafr al \u2018Aw\u0101yisah",
        "\u2018Izbat al \u2018Aw\u0101yisah",
        "Kafr al-\u2018Aw\u0101ysah"
    ],
    "wof:name":"Kafr al `Awayisah",
    "wof:placetype":"locality"
},
  "geometry": {"coordinates":[30.93747,30.78005],"type":"Point"}
}