{
  "type": "Feature",
  "properties": {
    "gn:admin1_code":"01",
    "gn:asciiname":"As Sinbillawayn",
    "gn:country_code":"EG",
    "gn:dem":13,
    "gn:feature_class":"P",
    "gn:feature_code":"PPL",
    "gn:name":"As Sinbill\u0101wayn",
    "gn:population":0,
    "gn:timezone":"Africa/Cairo",
    "iso:country":"EG",
    "name:ara_x_preferred":[
        "\u0627\u0644\u0633\u0646\u0628\u0644\u0627\u0648\u064a\u0646"
    ],
    "name:und_x_variant":[
        "El-Simbill\u00e2wein",
        "As Sunbull\u0101wayn",
        "Es Simbill\u0101wein",
        "As Sinbill\u0101wayn",
        "As-Sinbill\u0101wayn"
    ],
    "wof:name":"As Sinbillawayn",
    "wof:placetype":"locality"
},
  "geometry": {"coordinates":[31.46275,30.88251],"type":"Point"}
}