{
  "type": "Feature",
  "properties": {
    "iso:country":"EG",
    "name:ara_x_preferred":[
        "\u0627\u0644\u0627\u0633\u0643\u0646\u062f\u0631\u064a\u0629"
    ],
    "name:eng_x_preferred":[
        "Alexandria "
    ],
    "qs:gn_pop":0,
    "qs:name":"\u0627\u0644\u0627\u0633\u0643\u0646\u062f\u0631\u064a\u0629",
    "qs:name_adm0":"\u0645\u0635\u0631",
    "qs:name_adm1":"\u0627\u0644\u0627\u0633\u0643\u0646\u062f\u0631\u064a\u0629",
    "qs:photos":1950,
    "qs:photos_1k":395,
    "qs:photos_9k":53,
    "qs:photos_9r":17,
    "qs:photos_all":11860,
    "qs:photos_sr":15,
    "qs:placetype":"Town",
    "qs:pop_sr":"0",
    "qs:woe_adm0":23424802,
    "wof:name":"Alexandria ",
    "wof:placetype":"locality"
},
  "geometry": {"coordinates":[29.926414,31.210305],"type":"Point"}
}