{
  "type": "Feature",
  "properties": {
    "gn:admin1_code":"14",
    "gn:asciiname":"`Izbat Fikturya",
    "gn:country_code":"EG",
    "gn:dem":9,
    "gn:feature_class":"P",
    "gn:feature_code":"PPL",
    "gn:name":"\u2018Izbat F\u012bkt\u016bry\u0101",
    "gn:population":0,
    "gn:timezone":"Africa/Cairo",
    "iso:country":"EG",
    "name:ara_x_preferred":[
        "\u0639\u0632\u0628\u0629 \u0641\u064a\u0643\u062a\u0648\u0631\u064a\u0627"
    ],
    "name:und_x_variant":[
        "\u2018Izbat F\u012bkt\u016bry\u0101"
    ],
    "wof:name":"`Izbat Fikturya",
    "wof:placetype":"locality"
},
  "geometry": {"coordinates":[31.47091,30.63491],"type":"Point"}
}