{
  "type": "Feature",
  "properties": {
    "gn:admin1_code":"14",
    "gn:asciiname":"Kafr Abu Taha'",
    "gn:country_code":"EG",
    "gn:dem":13,
    "gn:feature_class":"P",
    "gn:feature_code":"PPL",
    "gn:name":"Kafr Ab\u016b \u0162\u0101h\u0101\u2019",
    "gn:population":0,
    "gn:timezone":"Africa/Cairo",
    "iso:country":"EG",
    "name:und_x_variant":[
        "Abu T\u00e2ha",
        "Kafr Ab\u016b \u0162\u0101h\u0101\u2019"
    ],
    "wof:name":"Kafr Abu Taha'",
    "wof:placetype":"locality"
},
  "geometry": {"coordinates":[31.73333,30.61667000000001],"type":"Point"}
}