{
  "type": "Feature",
  "properties": {
    "gn:admin1_code":"21",
    "gn:asciiname":"`Izbah Raqm Thamaniyat `Ashar",
    "gn:country_code":"EG",
    "gn:dem":4,
    "gn:feature_class":"P",
    "gn:feature_code":"PPL",
    "gn:name":"\u2018Izbah Raqm Tham\u0101niyat \u2018Ashar",
    "gn:population":0,
    "gn:timezone":"Africa/Cairo",
    "iso:country":"EG",
    "name:ara_x_preferred":[
        "\u0639\u0632\u0628\u0629 \u0631\u0642\u0645 \u0661\u0668"
    ],
    "name:ara_x_variant":[
        "\u0639\u0632\u0628\u0629 \u0631\u0642\u0645 18"
    ],
    "name:und_x_variant":[
        "\u2018Izbah Raqm Tham\u0101niyat \u2018Ashar",
        "\u2018Izbah Raqm 18"
    ],
    "wof:name":"`Izbah Raqm Thamaniyat `Ashar",
    "wof:placetype":"locality"
},
  "geometry": {"coordinates":[31.0893,31.37298],"type":"Point"}
}