{
  "type": "Feature",
  "properties": {
    "gn:admin1_code":"09",
    "gn:asciiname":"Minshat Jurays",
    "gn:country_code":"EG",
    "gn:dem":18,
    "gn:feature_class":"P",
    "gn:feature_code":"PPL",
    "gn:name":"Minsh\u0101t Jurays",
    "gn:population":0,
    "gn:timezone":"Africa/Cairo",
    "iso:country":"EG",
    "name:ara_x_preferred":[
        "\u0645\u0646\u0634\u0627\u0629 \u062c\u0631\u064a\u0633"
    ],
    "name:und_x_variant":[
        "Minsh\u00e2t Gireis",
        "Minsh\u0101t Jurays",
        "Minsh\u0101t Jirays"
    ],
    "wof:name":"Minshat Jurays",
    "wof:placetype":"locality"
},
  "geometry": {"coordinates":[30.90204,30.34325],"type":"Point"}
}