{
  "type": "Feature",
  "properties": {
    "gn:admin1_code":"24",
    "gn:asciiname":"Al Harafishah",
    "gn:country_code":"EG",
    "gn:dem":64,
    "gn:feature_class":"P",
    "gn:feature_code":"PPL",
    "gn:name":"Al \u1e28ar\u0101fishah",
    "gn:population":0,
    "gn:timezone":"Africa/Cairo",
    "iso:country":"EG",
    "name:und_x_variant":[
        "El Har\u00e2fsha",
        "Al \u1e28ar\u0101fishah"
    ],
    "wof:name":"Al Harafishah",
    "wof:placetype":"locality"
},
  "geometry": {"coordinates":[31.47653,26.71583],"type":"Point"}
}