{
  "type": "Feature",
  "properties": {
    "gn:admin1_code":"03",
    "gn:asciiname":"`Izbat Habib",
    "gn:country_code":"EG",
    "gn:dem":2,
    "gn:feature_class":"P",
    "gn:feature_code":"PPL",
    "gn:name":"\u2018Izbat \u1e28ab\u012bb",
    "gn:population":0,
    "gn:timezone":"Africa/Cairo",
    "iso:country":"EG",
    "name:ara_x_preferred":[
        "\u0639\u0632\u0628\u0629 \u062d\u0628\u064a\u0628"
    ],
    "name:und_x_variant":[
        "\u2018Izbat \u1e28ab\u012bb"
    ],
    "wof:name":"`Izbat Habib",
    "wof:placetype":"locality"
},
  "geometry": {"coordinates":[30.50614,31.17841],"type":"Point"}
}