{
  "type": "Feature",
  "properties": {
    "gn:admin1_code":"01",
    "gn:asciiname":"Kafr Hajjaj",
    "gn:country_code":"EG",
    "gn:dem":8,
    "gn:feature_class":"P",
    "gn:feature_code":"PPL",
    "gn:name":"Kafr \u1e24ajj\u0101j",
    "gn:population":0,
    "gn:timezone":"Africa/Cairo",
    "iso:country":"EG",
    "name:ara_x_preferred":[
        "\u0643\u0641\u0631 \u062d\u062c\u0627\u062c"
    ],
    "name:und_x_variant":[
        "Kafr \u1e24agg\u00e2g",
        "Kafr \u1e28ajj\u0101j",
        "Kafr \u1e24ajj\u0101j",
        "Kafr \u1e24ijj\u0101j"
    ],
    "wof:name":"Kafr Hajjaj",
    "wof:placetype":"locality"
},
  "geometry": {"coordinates":[31.88966,31.15443],"type":"Point"}
}