{
  "type": "Feature",
  "properties": {
    "gn:admin1_code":"14",
    "gn:asciiname":"Jazirat ash Shaykh",
    "gn:country_code":"EG",
    "gn:dem":8,
    "gn:feature_class":"P",
    "gn:feature_code":"PPL",
    "gn:name":"Jaz\u012brat ash Shaykh",
    "gn:population":0,
    "gn:timezone":"Africa/Cairo",
    "iso:country":"EG",
    "name:ara_x_preferred":[
        "\u062c\u0632\u064a\u0631\u0629 \u0627\u0644\u0634\u064a\u062e"
    ],
    "name:und_x_variant":[
        "Gez\u00eeret el-Sheikh",
        "Jaz\u012brat ash Shaykh"
    ],
    "wof:name":"Jazirat ash Shaykh",
    "wof:placetype":"locality"
},
  "geometry": {"coordinates":[31.71964,30.72311],"type":"Point"}
}