{
  "type": "Feature",
  "properties": {
    "gn:admin1_code":"01",
    "gn:asciiname":"`Izbat Muhammad Tantawi",
    "gn:country_code":"EG",
    "gn:dem":4,
    "gn:feature_class":"P",
    "gn:feature_code":"PPL",
    "gn:name":"\u2018Izbat Mu\u1e29ammad \u0162an\u0163\u0101w\u012b",
    "gn:population":0,
    "gn:timezone":"Africa/Cairo",
    "iso:country":"EG",
    "name:ara_x_preferred":[
        "\u0639\u0632\u0628\u0629 \u0645\u062d\u0645\u062f \u0637\u0646\u0637\u0627\u0648\u064a"
    ],
    "name:und_x_variant":[
        "\u2018Izbat Mu\u1e29ammad \u0162an\u0163\u0101w\u012b",
        "\u2018Iz. Mu\u1e25. \u1e6can\u1e6d\u0101w\u012b"
    ],
    "wof:name":"`Izbat Muhammad Tantawi",
    "wof:placetype":"locality"
},
  "geometry": {"coordinates":[31.71103,31.05107000000001],"type":"Point"}
}