{
  "type": "Feature",
  "properties": {
    "gn:admin1_code":"09",
    "gn:asciiname":"Mit Mas`ud",
    "gn:country_code":"EG",
    "gn:dem":13,
    "gn:feature_class":"P",
    "gn:feature_code":"PPL",
    "gn:name":"M\u012bt Mas\u2018\u016bd",
    "gn:population":0,
    "gn:timezone":"Africa/Cairo",
    "iso:country":"EG",
    "name:ara_x_preferred":[
        "\u0645\u064a\u062a \u0645\u0633\u0639\u0648\u062f"
    ],
    "name:und_x_variant":[
        "M\u00eet Mas\u2018\u00fbd",
        "M\u012bt Mas\u2018\u016bd"
    ],
    "wof:name":"Mit Mas`ud",
    "wof:placetype":"locality"
},
  "geometry": {"coordinates":[31.04976,30.52417],"type":"Point"}
}