{
  "type": "Feature",
  "properties": {
    "gn:admin1_code":"21",
    "gn:asciiname":"`Izbat al Awqaf al Jadidah",
    "gn:country_code":"EG",
    "gn:dem":7,
    "gn:feature_class":"P",
    "gn:feature_code":"PPL",
    "gn:name":"\u2018Izbat al Awq\u0101f al Jad\u012bdah",
    "gn:population":0,
    "gn:timezone":"Africa/Cairo",
    "iso:country":"EG",
    "name:ara_x_preferred":[
        "\u0639\u0632\u0628\u0629 \u0627\u0644\u0623\u0648\u0642\u0627\u0641 \u0627\u0644\u062c\u062f\u064a\u062f\u0629"
    ],
    "name:und_x_variant":[
        "\u2018Izbat al Awq\u0101f al Jad\u012bdah"
    ],
    "wof:name":"`Izbat al Awqaf al Jadidah",
    "wof:placetype":"locality"
},
  "geometry": {"coordinates":[30.80546,31.06673],"type":"Point"}
}