{
  "type": "Feature",
  "properties": {
    "gn:admin1_code":"16",
    "gn:asciiname":"Al Hajz Bahri",
    "gn:cc2":"EG",
    "gn:country_code":"EG",
    "gn:dem":76,
    "gn:feature_class":"P",
    "gn:feature_code":"PPL",
    "gn:name":"Al \u1e28ajz Ba\u1e29r\u012b",
    "gn:population":0,
    "gn:timezone":"Africa/Cairo",
    "iso:country":"EG",
    "name:und_x_variant":[
        "Zim\u0101m al Hajz Ba\u1e29r\u012b",
        "El Higz Bahari",
        "Al \u1e28ajz Ba\u1e29r\u012b"
    ],
    "wof:name":"Al Hajz Bahri",
    "wof:placetype":"locality"
},
  "geometry": {"coordinates":[32.73333,25.15],"type":"Point"}
}