{
  "type": "Feature",
  "properties": {
    "gn:admin1_code":"01",
    "gn:asciiname":"Kafr Abu `Ali",
    "gn:country_code":"EG",
    "gn:dem":4,
    "gn:feature_class":"P",
    "gn:feature_code":"PPL",
    "gn:name":"Kafr Ab\u016b \u2018Ali",
    "gn:population":0,
    "gn:timezone":"Africa/Cairo",
    "iso:country":"EG",
    "name:ara_x_preferred":[
        "\u0643\u0641\u0631 \u0623\u0628\u0648 \u0639\u0644\u064a"
    ],
    "name:und_x_variant":[
        "Kafr Ab\u016b \u2018Ali",
        "Kafr Abu \u2018Ali",
        "Kafr Ab\u016b \u2018Al\u012b"
    ],
    "wof:name":"Kafr Abu `Ali",
    "wof:placetype":"locality"
},
  "geometry": {"coordinates":[31.57946,31.14574],"type":"Point"}
}