{
  "type": "Feature",
  "properties": {
    "gn:admin1_code":"21",
    "gn:asciiname":"Qaryah Raqm Wahid",
    "gn:country_code":"EG",
    "gn:dem":1,
    "gn:feature_class":"P",
    "gn:feature_code":"PPL",
    "gn:name":"Qaryah Raqm W\u0101\u1e29id",
    "gn:population":0,
    "gn:timezone":"Africa/Cairo",
    "iso:country":"EG",
    "name:ara_x_preferred":[
        "\u0642\u0631\u064a\u0629 \u0631\u0642\u0645 \u0661"
    ],
    "name:ara_x_variant":[
        "\u0642\u0631\u064a\u0629 \u0631\u0642\u0645 1"
    ],
    "name:und_x_variant":[
        "Qaryah Raqm W\u0101\u1e29id",
        "Qaryah Raqm 1"
    ],
    "wof:name":"Qaryah Raqm Wahid",
    "wof:placetype":"locality"
},
  "geometry": {"coordinates":[31.05228,31.26301],"type":"Point"}
}