{
  "type": "Feature",
  "properties": {
    "gn:admin1_code":"17",
    "gn:asciiname":"Bisrah",
    "gn:country_code":"EG",
    "gn:dem":58,
    "gn:feature_class":"P",
    "gn:feature_code":"PPL",
    "gn:name":"Bi\u015frah",
    "gn:population":0,
    "gn:timezone":"Africa/Cairo",
    "iso:country":"EG",
    "name:und_x_variant":[
        "Bisra",
        "Bi\u015frah"
    ],
    "wof:name":"Bisrah",
    "wof:placetype":"locality"
},
  "geometry": {"coordinates":[31.25889,27.17216],"type":"Point"}
}