{
  "type": "Feature",
  "properties": {
    "gn:admin1_code":"14",
    "gn:asciiname":"`Izbat Bahir",
    "gn:country_code":"EG",
    "gn:dem":9,
    "gn:feature_class":"P",
    "gn:feature_code":"PPL",
    "gn:name":"\u2018Izbat B\u0101hir",
    "gn:population":0,
    "gn:timezone":"Africa/Cairo",
    "iso:country":"EG",
    "name:ara_x_preferred":[
        "\u0639\u0632\u0628\u0629 \u0628\u0627\u0647\u0631"
    ],
    "name:und_x_variant":[
        "\u2018Izbat B\u0101hir"
    ],
    "wof:name":"`Izbat Bahir",
    "wof:placetype":"locality"
},
  "geometry": {"coordinates":[31.72208,30.73993],"type":"Point"}
}