{
  "type": "Feature",
  "properties": {
    "gn:admin1_code":"01",
    "gn:asciiname":"`Izbat Abu Laban",
    "gn:country_code":"EG",
    "gn:dem":13,
    "gn:feature_class":"P",
    "gn:feature_code":"PPL",
    "gn:name":"\u2018Izbat Ab\u016b Laban",
    "gn:population":0,
    "gn:timezone":"Africa/Cairo",
    "iso:country":"EG",
    "name:und_x_variant":[
        "\u2018Izbat Ab\u016b Laban",
        "\u0639\u0632\u0628\u0629 \u0623\u0628\u0648 \u0644\u0628\u0646",
        "\u2018Iz. Ab\u016b Laban"
    ],
    "wof:name":"`Izbat Abu Laban",
    "wof:placetype":"locality"
},
  "geometry": {"coordinates":[31.4697,30.89308],"type":"Point"}
}