{
  "type": "Feature",
  "properties": {
    "gn:admin1_code":"05",
    "gn:asciiname":"Kawm Ishnaway",
    "gn:country_code":"EG",
    "gn:dem":10,
    "gn:feature_class":"P",
    "gn:feature_code":"PPL",
    "gn:name":"Kawm Ishn\u0101w\u0101y",
    "gn:population":0,
    "gn:timezone":"Africa/Cairo",
    "iso:country":"EG",
    "name:ara_x_preferred":[
        "\u0643\u0648\u0645 \u0627\u0634\u0646\u0627\u0648\u0627\u064a"
    ],
    "name:und_x_variant":[
        "Kom Ishn\u00e2w\u00e2i",
        "Kawm Ishn\u0101w\u0101y"
    ],
    "wof:name":"Kawm Ishnaway",
    "wof:placetype":"locality"
},
  "geometry": {"coordinates":[31.06718,30.79046],"type":"Point"}
}