{
  "type": "Feature",
  "properties": {
    "gn:admin1_code":"01",
    "gn:asciiname":"`Izbat Najib",
    "gn:country_code":"EG",
    "gn:dem":5,
    "gn:feature_class":"P",
    "gn:feature_code":"PPL",
    "gn:name":"\u2018Izbat Naj\u012bb",
    "gn:population":0,
    "gn:timezone":"Africa/Cairo",
    "iso:country":"EG",
    "name:ara_x_preferred":[
        "\u0639\u0632\u0628\u0629 \u0646\u062c\u064a\u0628"
    ],
    "name:und_x_variant":[
        "\u2018Izbat Naj\u012bb",
        "\u2018Izbat Najib"
    ],
    "wof:name":"`Izbat Najib",
    "wof:placetype":"locality"
},
  "geometry": {"coordinates":[31.79798,31.14072],"type":"Point"}
}