{
  "type": "Feature",
  "properties": {
    "gn:admin1_code":"21",
    "gn:asciiname":"`Izbat as Sawi",
    "gn:country_code":"EG",
    "gn:dem":2,
    "gn:feature_class":"P",
    "gn:feature_code":"PPL",
    "gn:name":"\u2018Izbat as \u015e\u0101w\u012b",
    "gn:population":0,
    "gn:timezone":"Africa/Cairo",
    "iso:country":"EG",
    "name:ara_x_preferred":[
        "\u0639\u0632\u0628\u0629 \u0627\u0644\u0635\u0627\u0648\u064a"
    ],
    "name:und_x_variant":[
        "\u2018Izbat as \u015e\u0101w\u012b"
    ],
    "wof:name":"`Izbat as Sawi",
    "wof:placetype":"locality"
},
  "geometry": {"coordinates":[30.82163,31.29035],"type":"Point"}
}