{
  "type": "Feature",
  "properties": {
    "gn:admin1_code":"05",
    "gn:asciiname":"`Izbat Zaynab Ahmad",
    "gn:country_code":"EG",
    "gn:dem":9,
    "gn:feature_class":"P",
    "gn:feature_code":"PPL",
    "gn:name":"\u2018Izbat Zaynab A\u1e29mad",
    "gn:population":0,
    "gn:timezone":"Africa/Cairo",
    "iso:country":"EG",
    "name:ara_x_preferred":[
        "\u0639\u0632\u0628\u0629 \u0632\u064a\u0646\u0628 \u0623\u062d\u0645\u062f"
    ],
    "name:und_x_variant":[
        "\u2018Izbat Zaynab A\u1e29mad",
        "\u2018Izbat Zaynab A\u1e25mad"
    ],
    "wof:name":"`Izbat Zaynab Ahmad",
    "wof:placetype":"locality"
},
  "geometry": {"coordinates":[30.9765,30.82675],"type":"Point"}
}