{
  "type": "Feature",
  "properties": {
    "gn:admin1_code":"03",
    "gn:asciiname":"Qaryat Abu Bakr as Siddiq",
    "gn:country_code":"EG",
    "gn:dem":20,
    "gn:feature_class":"P",
    "gn:feature_code":"PPL",
    "gn:name":"Qaryat Ab\u016b Bakr a\u015f \u015eidd\u012bq",
    "gn:population":0,
    "gn:timezone":"Africa/Cairo",
    "iso:country":"EG",
    "wof:name":"Qaryat Abu Bakr as Siddiq",
    "wof:placetype":"locality"
},
  "geometry": {"coordinates":[30.63033,30.60796],"type":"Point"}
}