{
  "type": "Feature",
  "properties": {
    "gn:admin1_code":"01",
    "gn:asciiname":"Al Qustantiniyah",
    "gn:cc2":"EG",
    "gn:country_code":"EG",
    "gn:dem":3,
    "gn:feature_class":"P",
    "gn:feature_code":"PPL",
    "gn:name":"Al Qus\u0163an\u0163\u012bn\u012byah",
    "gn:population":0,
    "gn:timezone":"Africa/Cairo",
    "iso:country":"EG",
    "name:und_x_variant":[
        "El-Costantin\u00eeya",
        "El Qustantin\u00eeya",
        "Al Qus\u0163an\u0163\u012bn\u012byah"
    ],
    "wof:name":"Al Qustantiniyah",
    "wof:placetype":"locality"
},
  "geometry": {"coordinates":[31.46667,31.23333],"type":"Point"}
}