{
  "type": "Feature",
  "properties": {
    "gn:admin1_code":"21",
    "gn:asciiname":"`Izbat Sharikat al Ittihad al Qadimah",
    "gn:country_code":"EG",
    "gn:dem":7,
    "gn:feature_class":"P",
    "gn:feature_code":"PPL",
    "gn:name":"\u2018Izbat Sharikat al Itti\u1e29\u0101d al Qad\u012bmah",
    "gn:population":0,
    "gn:timezone":"Africa/Cairo",
    "iso:country":"EG",
    "name:ara_x_preferred":[
        "\u0639\u0632\u0628\u0629 \u0634\u0631\u0643\u0629 \u0627\u0644\u0625\u062a\u062d\u0627\u062f \u0627\u0644\u0642\u062f\u064a\u0645\u0629"
    ],
    "name:und_x_variant":[
        "\u2018Izbat Sharikat al Itti\u1e29\u0101d al Qad\u012bmah",
        "\u2018Izbat Sharikat al-Itti\u1e25\u0101d al-Qad\u012bmah"
    ],
    "wof:name":"`Izbat Sharikat al Ittihad al Qadimah",
    "wof:placetype":"locality"
},
  "geometry": {"coordinates":[30.9989,31.18278],"type":"Point"}
}