{
  "type": "Feature",
  "properties": {
    "gn:admin1_code":"05",
    "gn:asciiname":"`Izbat Mustafa Sahranak",
    "gn:country_code":"EG",
    "gn:dem":17,
    "gn:feature_class":"P",
    "gn:feature_code":"PPL",
    "gn:name":"\u2018Izbat Mu\u015f\u0163af\u00e1 Sahranak",
    "gn:population":0,
    "gn:timezone":"Africa/Cairo",
    "iso:country":"EG",
    "name:ara_x_preferred":[
        "\u0639\u0632\u0628\u0629 \u0645\u0635\u0637\u0641\u0649 \u0633\u0647\u0631\u0646\u0643"
    ],
    "name:und_x_variant":[
        "\u2018Izbat Mu\u015f\u0163af\u00e1 Sahranak"
    ],
    "wof:name":"`Izbat Mustafa Sahranak",
    "wof:placetype":"locality"
},
  "geometry": {"coordinates":[31.24594,30.63724],"type":"Point"}
}