{
  "type": "Feature",
  "properties": {
    "gn:admin1_code":"08",
    "gn:asciiname":"`Izbat Abu Isma`il",
    "gn:country_code":"EG",
    "gn:dem":20,
    "gn:feature_class":"P",
    "gn:feature_code":"PPL",
    "gn:name":"`Izbat Ab\u016b Ism\u0101`\u012bl",
    "gn:population":0,
    "gn:timezone":"Africa/Cairo",
    "iso:country":"EG",
    "wof:name":"`Izbat Abu Isma`il",
    "wof:placetype":"locality"
},
  "geometry": {"coordinates":[31.02083,30.1675],"type":"Point"}
}