{
  "type": "Feature",
  "properties": {
    "gn:admin1_code":"14",
    "gn:asciiname":"`Izbat Sayyid Yusuf",
    "gn:country_code":"EG",
    "gn:dem":12,
    "gn:feature_class":"P",
    "gn:feature_code":"PPL",
    "gn:name":"\u2018Izbat Sayyid Y\u016bsuf",
    "gn:population":0,
    "gn:timezone":"Africa/Cairo",
    "iso:country":"EG",
    "name:ara_x_preferred":[
        "\u0639\u0632\u0628\u0629 \u0633\u064a\u062f \u064a\u0648\u0633\u0641"
    ],
    "name:und_x_variant":[
        "\u2018Izbat Sayyid Y\u016bsuf",
        "\u2018Izbat ash Shaykh Y\u016bsif"
    ],
    "wof:name":"`Izbat Sayyid Yusuf",
    "wof:placetype":"locality"
},
  "geometry": {"coordinates":[31.54647000000001,30.51034000000001],"type":"Point"}
}