{
  "type": "Feature",
  "properties": {
    "gn:admin1_code":"12",
    "gn:asciiname":"Shalaqan",
    "gn:country_code":"EG",
    "gn:dem":22,
    "gn:feature_class":"P",
    "gn:feature_code":"PPL",
    "gn:name":"Shalaq\u0101n",
    "gn:population":0,
    "gn:timezone":"Africa/Cairo",
    "iso:country":"EG",
    "name:ara_x_preferred":[
        "\u0634\u0644\u0642\u0627\u0646"
    ],
    "name:und_x_variant":[
        "Shalaq\u0101n"
    ],
    "wof:name":"Shalaqan",
    "wof:placetype":"locality"
},
  "geometry": {"coordinates":[31.16118,30.19115],"type":"Point"}
}