{
  "type": "Feature",
  "properties": {
    "gn:admin1_code":"21",
    "gn:asciiname":"Al `Azizah",
    "gn:country_code":"EG",
    "gn:dem":3,
    "gn:feature_class":"P",
    "gn:feature_code":"PPL",
    "gn:name":"Al \u2018Az\u012bzah",
    "gn:population":0,
    "gn:timezone":"Africa/Cairo",
    "iso:country":"EG",
    "name:ara_x_preferred":[
        "\u0627\u0644\u0639\u0632\u064a\u0632\u0629"
    ],
    "name:und_x_variant":[
        "Al \u2018Az\u012bzah"
    ],
    "wof:name":"Al `Azizah",
    "wof:placetype":"locality"
},
  "geometry": {"coordinates":[30.74651,31.34665],"type":"Point"}
}