{
  "type": "Feature",
  "properties": {
    "gn:admin1_code":"14",
    "gn:asciiname":"Al Qassasin al Jadidah",
    "gn:country_code":"EG",
    "gn:dem":10,
    "gn:feature_class":"P",
    "gn:feature_code":"PPL",
    "gn:name":"Al Qa\u015f\u015f\u0101s\u012bn al Jad\u012bdah",
    "gn:population":0,
    "gn:timezone":"Africa/Cairo",
    "iso:country":"EG",
    "name:ara_x_preferred":[
        "\u0627\u0644\u0642\u0635\u0627\u0635\u064a\u0646 \u0627\u0644\u062c\u062f\u064a\u062f\u0629"
    ],
    "name:und_x_variant":[
        "Al Qa\u015f\u015f\u0101s\u012bn al Jad\u012bdah",
        "Al-Qa\u1e63\u1e63\u0101s\u012bn al-Jad\u012bdah"
    ],
    "wof:name":"Al Qassasin al Jadidah",
    "wof:placetype":"locality"
},
  "geometry": {"coordinates":[31.99191,30.55734],"type":"Point"}
}