{
  "type": "Feature",
  "properties": {
    "gn:admin1_code":"01",
    "gn:asciiname":"Kafr al A`jar",
    "gn:country_code":"EG",
    "gn:dem":7,
    "gn:feature_class":"P",
    "gn:feature_code":"PPL",
    "gn:name":"Kafr al A\u2018jar",
    "gn:population":0,
    "gn:timezone":"Africa/Cairo",
    "iso:country":"EG",
    "name:ara_x_preferred":[
        "\u0643\u0641\u0631 \u0627\u0644\u0623\u0639\u062c\u0631"
    ],
    "name:und_x_variant":[
        "Kafr el-A\u2018gar",
        "Kafr al A\u2018jar",
        "\u2018Izbat Kafr al-A\u2018jar",
        "\u2018Izbat Kafr al A\u2018jar"
    ],
    "wof:name":"Kafr al A`jar",
    "wof:placetype":"locality"
},
  "geometry": {"coordinates":[31.49176,31.11833],"type":"Point"}
}