{
  "type": "Feature",
  "properties": {
    "gn:admin1_code":"03",
    "gn:asciiname":"`Izbat Sa`d Mas`ud",
    "gn:country_code":"EG",
    "gn:dem":1,
    "gn:feature_class":"P",
    "gn:feature_code":"PPL",
    "gn:name":"\u2018Izbat Sa\u2018d Mas\u2018\u016bd",
    "gn:population":0,
    "gn:timezone":"Africa/Cairo",
    "iso:country":"EG",
    "name:ara_x_preferred":[
        "\u0639\u0632\u0628\u0629 \u0633\u0639\u062f \u0645\u0633\u0639\u0648\u062f"
    ],
    "name:und_x_variant":[
        "\u2018Izbat Sa\u2018d Mas\u2018\u016bd"
    ],
    "wof:name":"`Izbat Sa`d Mas`ud",
    "wof:placetype":"locality"
},
  "geometry": {"coordinates":[30.32348,31.04636],"type":"Point"}
}