{
  "type": "Feature",
  "properties": {
    "gn:admin1_code":"18",
    "gn:asciiname":"Hanna",
    "gn:country_code":"EG",
    "gn:dem":34,
    "gn:feature_class":"P",
    "gn:feature_code":"PPL",
    "gn:name":"\u1e28ann\u0101",
    "gn:population":0,
    "gn:timezone":"Africa/Cairo",
    "iso:country":"EG",
    "wof:name":"Hanna",
    "wof:placetype":"locality"
},
  "geometry": {"coordinates":[30.90424,28.85023],"type":"Point"}
}