{
  "type": "Feature",
  "properties": {
    "gn:admin1_code":"03",
    "gn:asciiname":"`Izbat Sidi `Umar",
    "gn:country_code":"EG",
    "gn:dem":2,
    "gn:feature_class":"P",
    "gn:feature_code":"PPL",
    "gn:name":"\u2018Izbat S\u012bd\u012b \u2018Umar",
    "gn:population":0,
    "gn:timezone":"Africa/Cairo",
    "iso:country":"EG",
    "name:ara_x_preferred":[
        "\u0639\u0632\u0628\u0629 \u0633\u064a\u062f\u064a \u0639\u0645\u0631"
    ],
    "name:und_x_variant":[
        "\u2018Izbat S\u012bd\u012b \u2018Umar"
    ],
    "wof:name":"`Izbat Sidi `Umar",
    "wof:placetype":"locality"
},
  "geometry": {"coordinates":[30.4354,31.31893],"type":"Point"}
}