{
  "type": "Feature",
  "properties": {
    "gn:admin1_code":"05",
    "gn:asciiname":"`Izbat `Ali `Uthman",
    "gn:country_code":"EG",
    "gn:dem":8,
    "gn:feature_class":"P",
    "gn:feature_code":"PPL",
    "gn:name":"\u2018Izbat \u2018Al\u012b \u2018Uthm\u0101n",
    "gn:population":0,
    "gn:timezone":"Africa/Cairo",
    "iso:country":"EG",
    "name:ara_x_preferred":[
        "\u0639\u0632\u0628\u0629 \u0639\u0644\u064a \u0639\u062b\u0645\u0627\u0646"
    ],
    "name:und_x_variant":[
        "\u2018Izbat \u2018Al\u012b \u2018Uthm\u0101n"
    ],
    "wof:name":"`Izbat `Ali `Uthman",
    "wof:placetype":"locality"
},
  "geometry": {"coordinates":[31.0777,30.91359000000001],"type":"Point"}
}