{
  "type": "Feature",
  "properties": {
    "gn:admin1_code":"05",
    "gn:asciiname":"Kafr Juwayyah",
    "gn:country_code":"EG",
    "gn:dem":12,
    "gn:feature_class":"P",
    "gn:feature_code":"PPL",
    "gn:name":"Kafr Juwayyah",
    "gn:population":0,
    "gn:timezone":"Africa/Cairo",
    "iso:country":"EG",
    "name:und_x_variant":[
        "Kafr Guwaiya",
        "Kafr ed-Dagw\u00eeya",
        "Kafr Juwayyah"
    ],
    "wof:name":"Kafr Juwayyah",
    "wof:placetype":"locality"
},
  "geometry": {"coordinates":[30.82776,30.88987],"type":"Point"}
}