{
  "type": "Feature",
  "properties": {
    "gn:admin1_code":"14",
    "gn:asciiname":"`Izbat Hasan Agha",
    "gn:country_code":"EG",
    "gn:dem":13,
    "gn:feature_class":"P",
    "gn:feature_code":"PPL",
    "gn:name":"\u2018Izbat \u1e28asan Agh\u0101",
    "gn:population":0,
    "gn:timezone":"Africa/Cairo",
    "iso:country":"EG",
    "name:ara_x_preferred":[
        "\u0639\u0632\u0628\u0629 \u062d\u0633\u0646 \u0623\u063a\u0627"
    ],
    "name:und_x_variant":[
        "\u2018Izbat \u1e28asan Agh\u0101"
    ],
    "wof:name":"`Izbat Hasan Agha",
    "wof:placetype":"locality"
},
  "geometry": {"coordinates":[31.53287000000001,30.56619],"type":"Point"}
}