{
  "type": "Feature",
  "properties": {
    "gn:admin1_code":"10",
    "gn:asciiname":"Al Atlat",
    "gn:country_code":"EG",
    "gn:dem":37,
    "gn:feature_class":"P",
    "gn:feature_code":"PPL",
    "gn:name":"Al Atl\u0101t",
    "gn:population":0,
    "gn:timezone":"Africa/Cairo",
    "iso:country":"EG",
    "wof:name":"Al Atlat",
    "wof:placetype":"locality"
},
  "geometry": {"coordinates":[30.75485,28.44463],"type":"Point"}
}