{
  "type": "Feature",
  "properties": {
    "gn:admin1_code":"14",
    "gn:asciiname":"As Salihiyah al Jadidah",
    "gn:country_code":"EG",
    "gn:dem":26,
    "gn:feature_class":"P",
    "gn:feature_code":"PPL",
    "gn:name":"A\u015f \u015e\u0101li\u1e29\u012byah al Jad\u012bdah",
    "gn:population":0,
    "gn:timezone":"Africa/Cairo",
    "iso:country":"EG",
    "name:ara_x_preferred":[
        "\u0627\u0644\u0635\u0627\u0644\u062d\u064a\u0629 \u0627\u0644\u062c\u062f\u064a\u062f\u0629"
    ],
    "name:und_x_variant":[
        "A\u015f \u015e\u0101li\u1e29\u012byah al Jad\u012bdah",
        "A\u1e63-\u1e62\u0101li\u1e25iyyah al-Jad\u012bdah"
    ],
    "wof:name":"As Salihiyah al Jadidah",
    "wof:placetype":"locality"
},
  "geometry": {"coordinates":[31.93927,30.63146],"type":"Point"}
}