{
  "type": "Feature",
  "properties": {
    "gn:admin1_code":"3.0",
    "gn:asciiname":"Zahr at Timsah",
    "gn:country_code":"EG",
    "gn:dem":9,
    "gn:feature_class":"P",
    "gn:feature_code":"PPL",
    "gn:name":"Z\u0327ahr at Tims\u0101\u1e29",
    "gn:population":0,
    "gn:timezone":"Africa/Cairo",
    "iso:country":"EG",
    "name:und_x_variant":[
        "\u1e94ahr el-Tims\u00e2\u1e25",
        "\u1e94ahr et-Tims\u00e2\u1e25",
        "Z\u0327ahr at Tims\u0101\u1e29"
    ],
    "wof:name":"Zahr at Timsah",
    "wof:placetype":"locality"
},
  "geometry": {"coordinates":[30.72958,30.92955],"type":"Point"}
}