{
  "type": "Feature",
  "properties": {
    "gn:admin1_code":"03",
    "gn:asciiname":"Balaqtar",
    "gn:country_code":"EG",
    "gn:dem":1,
    "gn:feature_class":"P",
    "gn:feature_code":"PPL",
    "gn:name":"Balaq\u0163ar",
    "gn:population":0,
    "gn:timezone":"Africa/Cairo",
    "iso:country":"EG",
    "name:ara_x_preferred":[
        "\u0628\u0644\u0642\u0637\u0631"
    ],
    "name:und_x_variant":[
        "Balaq\u0163ar",
        "Balaq\u1e6dar"
    ],
    "wof:name":"Balaqtar",
    "wof:placetype":"locality"
},
  "geometry": {"coordinates":[30.21393,31.07405],"type":"Point"}
}