{
  "type": "Feature",
  "properties": {
    "gn:admin1_code":"01",
    "gn:asciiname":"`Izbat Wizarat az Zira`ah 'Arb`at `Ashar",
    "gn:country_code":"EG",
    "gn:dem":3,
    "gn:feature_class":"P",
    "gn:feature_code":"PPL",
    "gn:name":"\u2018Izbat Wiz\u0101rat az Zir\u0101\u2018ah \u2019Arb\u2018at \u2018Ashar",
    "gn:population":0,
    "gn:timezone":"Africa/Cairo",
    "iso:country":"EG",
    "name:ara_x_preferred":[
        "\u0639\u0632\u0628\u0629 \u0648\u0632\u0627\u0631\u0629 \u0627\u0644\u0632\u0631\u0627\u0639\u0629 \u0661\u0664"
    ],
    "name:und_x_variant":[
        "\u2018Izbat Wiz\u0101rat az Zir\u0101\u2018ah \u2019Arb\u2018at \u2018Ashar",
        "\u2018Iz. Wiz\u0101rat az-Zir\u0101\u2018ah No. 14"
    ],
    "wof:name":"`Izbat Wizarat az Zira`ah 'Arb`at `Ashar",
    "wof:placetype":"locality"
},
  "geometry": {"coordinates":[31.75113,31.22432],"type":"Point"}
}