{
  "type": "Feature",
  "properties": {
    "gn:admin1_code":"12",
    "gn:asciiname":"`Izbat Faris Yusuf",
    "gn:country_code":"EG",
    "gn:dem":16,
    "gn:feature_class":"P",
    "gn:feature_code":"PPL",
    "gn:name":"\u2018Izbat F\u0101ris Y\u016bsuf",
    "gn:population":0,
    "gn:timezone":"Africa/Cairo",
    "iso:country":"EG",
    "name:ara_x_preferred":[
        "\u0639\u0632\u0628\u0629 \u0641\u0627\u0631\u0633 \u064a\u0648\u0633\u0641"
    ],
    "name:und_x_variant":[
        "\u2018Izbat F\u0101ris Y\u016bsuf",
        "\u2018Izbat F\u0101ris Y\u016bsif"
    ],
    "wof:name":"`Izbat Faris Yusuf",
    "wof:placetype":"locality"
},
  "geometry": {"coordinates":[31.21399000000001,30.32684],"type":"Point"}
}