{
  "type": "Feature",
  "properties": {
    "gn:admin1_code":"21",
    "gn:asciiname":"`Izbat al Bakariwah ash Sharqiyah",
    "gn:country_code":"EG",
    "gn:dem":4,
    "gn:feature_class":"P",
    "gn:feature_code":"PPL",
    "gn:name":"\u2018Izbat al Bak\u0101riwah ash Sharq\u012byah",
    "gn:population":0,
    "gn:timezone":"Africa/Cairo",
    "iso:country":"EG",
    "name:ara_x_preferred":[
        "\u0639\u0632\u0628\u0629 \u0627\u0644\u0628\u0643\u0627\u0631\u0648\u0629 \u0627\u0644\u0634\u0631\u0642\u064a\u0629"
    ],
    "name:und_x_variant":[
        "\u2018Ezbet el-Bak\u00e2rwa el-Sharq\u00eeya",
        "\u2018Izbat al Bak\u0101rwah ash Sharq\u012byah",
        "\u2018Izbat al Bak\u0101riwah ash Sharq\u012byah"
    ],
    "wof:name":"`Izbat al Bakariwah ash Sharqiyah",
    "wof:placetype":"locality"
},
  "geometry": {"coordinates":[30.79018,31.28391],"type":"Point"}
}