{
  "type": "Feature",
  "properties": {
    "gn:admin1_code":"02",
    "gn:asciiname":"Qadd el-Barud",
    "gn:country_code":"EG",
    "gn:dem":33,
    "gn:feature_class":"P",
    "gn:feature_code":"PPL",
    "gn:name":"Qadd el-Bar\u00fbd",
    "gn:population":0,
    "gn:timezone":"Africa/Cairo",
    "iso:country":"EG",
    "wof:name":"Qadd el-Barud",
    "wof:placetype":"locality"
},
  "geometry": {"coordinates":[33.93333,26.75],"type":"Point"}
}