{
  "type": "Feature",
  "properties": {
    "gn:admin1_code":"14",
    "gn:asciiname":"Kafr Abu Salih",
    "gn:country_code":"EG",
    "gn:dem":13,
    "gn:feature_class":"P",
    "gn:feature_code":"PPL",
    "gn:name":"Kafr Ab\u016b \u015eali\u1e29",
    "gn:population":0,
    "gn:timezone":"Africa/Cairo",
    "iso:country":"EG",
    "name:ara_x_preferred":[
        "\u0643\u0641\u0631 \u0623\u0628\u0648 \u0635\u0627\u0644\u062d"
    ],
    "name:und_x_variant":[
        "Kafr Ab\u016b \u015eali\u1e29"
    ],
    "wof:name":"Kafr Abu Salih",
    "wof:placetype":"locality"
},
  "geometry": {"coordinates":[31.45998,30.5459],"type":"Point"}
}