{
  "type": "Feature",
  "properties": {
    "gn:admin1_code":"03",
    "gn:asciiname":"`Izbat Yusuf Fulayfil",
    "gn:country_code":"EG",
    "gn:dem":0,
    "gn:feature_class":"P",
    "gn:feature_code":"PPL",
    "gn:name":"\u2018Izbat Y\u016bsuf Fulayfil",
    "gn:population":0,
    "gn:timezone":"Africa/Cairo",
    "iso:country":"EG",
    "name:ara_x_preferred":[
        "\u0639\u0632\u0628\u0629 \u064a\u0648\u0633\u0641 \u0641\u0644\u064a\u0641\u0644"
    ],
    "name:und_x_variant":[
        "\u2018Izbat Y\u016bsuf Fulayfil",
        "\u2018Izbat Y\u016bsif Fulayfil"
    ],
    "wof:name":"`Izbat Yusuf Fulayfil",
    "wof:placetype":"locality"
},
  "geometry": {"coordinates":[30.26704,31.16169],"type":"Point"}
}