{
  "type": "Feature",
  "properties": {
    "gn:admin1_code":"03",
    "gn:asciiname":"`Izbat Hamzah",
    "gn:country_code":"EG",
    "gn:dem":0,
    "gn:feature_class":"P",
    "gn:feature_code":"PPL",
    "gn:name":"\u2018Izbat \u1e28amzah",
    "gn:population":0,
    "gn:timezone":"Africa/Cairo",
    "iso:country":"EG",
    "name:ara_x_preferred":[
        "\u0639\u0632\u0628\u0629 \u062d\u0645\u0632\u0629"
    ],
    "name:und_x_variant":[
        "\u2018Izbat \u1e28amzah",
        "\u2018Izbat \u1e24amzah"
    ],
    "wof:name":"`Izbat Hamzah",
    "wof:placetype":"locality"
},
  "geometry": {"coordinates":[30.2989,31.13009000000001],"type":"Point"}
}