{
  "type": "Feature",
  "properties": {
    "gn:admin1_code":"18",
    "gn:asciiname":"Ibwit al Qadimah",
    "gn:cc2":"EG",
    "gn:country_code":"EG",
    "gn:dem":24,
    "gn:feature_class":"P",
    "gn:feature_code":"PPL",
    "gn:name":"Ibw\u012b\u0163 al Qad\u012bmah",
    "gn:population":0,
    "gn:timezone":"Africa/Cairo",
    "iso:country":"EG",
    "name:und_x_variant":[
        "Ibw\u00eet el Qad\u00eema",
        "Ibw\u012b\u0163 al Qad\u012bmah"
    ],
    "wof:name":"Ibwit al Qadimah",
    "wof:placetype":"locality"
},
  "geometry": {"coordinates":[31.13333,29.33333],"type":"Point"}
}