{
  "type": "Feature",
  "properties": {
    "gn:admin1_code":"12",
    "gn:asciiname":"Kafr Abu Dhikri",
    "gn:country_code":"EG",
    "gn:dem":18,
    "gn:feature_class":"P",
    "gn:feature_code":"PPL",
    "gn:name":"Kafr Ab\u016b Dhikr\u012b",
    "gn:population":0,
    "gn:timezone":"Africa/Cairo",
    "iso:country":"EG",
    "name:ara_x_preferred":[
        "\u0643\u0641\u0631 \u0623\u0628\u0648 \u0630\u0643\u0631\u064a"
    ],
    "name:und_x_variant":[
        "Kafr Abu Zikri",
        "Kafr Abu Dhiki",
        "Kafr Ab\u016b Dhikr\u012b"
    ],
    "wof:name":"Kafr Abu Dhikri",
    "wof:placetype":"locality"
},
  "geometry": {"coordinates":[31.15448,30.45831],"type":"Point"}
}