{
  "type": "Feature",
  "properties": {
    "gn:admin1_code":"09",
    "gn:asciiname":"`Izbat ash Shaykh",
    "gn:country_code":"EG",
    "gn:dem":12,
    "gn:feature_class":"P",
    "gn:feature_code":"PPL",
    "gn:name":"\u2018Izbat ash Shaykh",
    "gn:population":0,
    "gn:timezone":"Africa/Cairo",
    "iso:country":"EG",
    "name:ara_x_preferred":[
        "\u0639\u0632\u0628\u0629 \u0627\u0644\u0634\u064a\u062e"
    ],
    "name:und_x_variant":[
        "\u2018Izbat ash Shaykh"
    ],
    "wof:name":"`Izbat ash Shaykh",
    "wof:placetype":"locality"
},
  "geometry": {"coordinates":[30.84362,30.37298],"type":"Point"}
}