{
  "type": "Feature",
  "properties": {
    "gn:admin1_code":"20",
    "gn:asciiname":"`Izbat ar Ratmah",
    "gn:country_code":"EG",
    "gn:dem":6,
    "gn:feature_class":"P",
    "gn:feature_code":"PPL",
    "gn:name":"\u2018Izbat ar Ra\u0163mah",
    "gn:population":0,
    "gn:timezone":"Africa/Cairo",
    "iso:country":"EG",
    "name:und_x_variant":[
        "\u2018Izbat ar Ra\u0163mah",
        "\u2018Ezbet el-Ra\u1e6dma"
    ],
    "wof:name":"`Izbat ar Ratmah",
    "wof:placetype":"locality"
},
  "geometry": {"coordinates":[31.83192,31.47447],"type":"Point"}
}