{
  "type": "Feature",
  "properties": {
    "gn:admin1_code":"01",
    "gn:asciiname":"`Izbat al Khawli",
    "gn:country_code":"EG",
    "gn:dem":9,
    "gn:feature_class":"P",
    "gn:feature_code":"PPL",
    "gn:name":"\u2018Izbat al Khawl\u012b",
    "gn:population":0,
    "gn:timezone":"Africa/Cairo",
    "iso:country":"EG",
    "name:ara_x_preferred":[
        "\u0639\u0632\u0628\u0629 \u0627\u0644\u062e\u0648\u0644\u064a"
    ],
    "name:und_x_variant":[
        "\u2018Izbat al Khawl\u012b",
        "\u2018Izbat al-Kh\u016bl\u012b"
    ],
    "wof:name":"`Izbat al Khawli",
    "wof:placetype":"locality"
},
  "geometry": {"coordinates":[31.40387,31.02669],"type":"Point"}
}