{
  "type": "Feature",
  "properties": {
    "gn:admin1_code":"01",
    "gn:asciiname":"Kafr Muhammad ash Shinnawi",
    "gn:cc2":"EG",
    "gn:country_code":"EG",
    "gn:dem":4,
    "gn:feature_class":"P",
    "gn:feature_code":"PPL",
    "gn:name":"Kafr Mu\u1e29ammad ash Shinn\u0101w\u012b",
    "gn:population":0,
    "gn:timezone":"Africa/Cairo",
    "iso:country":"EG",
    "name:und_x_variant":[
        "Kafr Mu\u1e25ammad el-Shinn\u00e2wi",
        "Kafr Mu\u1e29ammad ash Shinn\u0101w\u012b"
    ],
    "wof:name":"Kafr Muhammad ash Shinnawi",
    "wof:placetype":"locality"
},
  "geometry": {"coordinates":[31.47889,30.90194],"type":"Point"}
}