{
  "type": "Feature",
  "properties": {
    "gn:admin1_code":"01",
    "gn:asciiname":"`Izbat Raqam Tis`ah",
    "gn:country_code":"EG",
    "gn:dem":4,
    "gn:feature_class":"P",
    "gn:feature_code":"PPL",
    "gn:name":"\u2018Izbat Raqam Tis\u2018ah",
    "gn:population":0,
    "gn:timezone":"Africa/Cairo",
    "iso:country":"EG",
    "name:ara_x_preferred":[
        "\u0639\u0632\u0628\u0629 \u0631\u0642\u0645 \u062a\u0633\u0639\u0629"
    ],
    "name:und_x_variant":[
        "\u2018Izbat Raqam Tis\u2018ah",
        "\u2018Izbat Number Nine"
    ],
    "wof:name":"`Izbat Raqam Tis`ah",
    "wof:placetype":"locality"
},
  "geometry": {"coordinates":[31.79688,31.09104],"type":"Point"}
}