{
  "type": "Feature",
  "properties": {
    "gn:admin1_code":"03",
    "gn:asciiname":"Ad Dasasinah",
    "gn:country_code":"EG",
    "gn:dem":2,
    "gn:feature_class":"P",
    "gn:feature_code":"PPL",
    "gn:name":"Ad Das\u0101sinah",
    "gn:population":0,
    "gn:timezone":"Africa/Cairo",
    "iso:country":"EG",
    "name:ara_x_preferred":[
        "\u0627\u0644\u062f\u0633\u0627\u0633\u0646\u0629"
    ],
    "name:und_x_variant":[
        "Ad Das\u0101sinah",
        "\u2018Ezbet el-Dasansa",
        "Ad-Das\u0101snah"
    ],
    "wof:name":"Ad Dasasinah",
    "wof:placetype":"locality"
},
  "geometry": {"coordinates":[30.34948,31.13532],"type":"Point"}
}