{
  "type": "Feature",
  "properties": {
    "gn:admin1_code":"03",
    "gn:asciiname":"Kafr Gharin",
    "gn:cc2":"EG",
    "gn:country_code":"EG",
    "gn:dem":9,
    "gn:feature_class":"P",
    "gn:feature_code":"PPL",
    "gn:name":"Kafr Ghar\u012bn",
    "gn:population":0,
    "gn:timezone":"Africa/Cairo",
    "iso:country":"EG",
    "name:und_x_variant":[
        "Kafr Ghir\u00een",
        "Kafr Ghar\u012bn"
    ],
    "wof:name":"Kafr Gharin",
    "wof:placetype":"locality"
},
  "geometry": {"coordinates":[30.76389,30.75472],"type":"Point"}
}