{
  "type": "Feature",
  "properties": {
    "gn:admin1_code":"21",
    "gn:asciiname":"`Izbat Abu Farah",
    "gn:country_code":"EG",
    "gn:dem":3,
    "gn:feature_class":"P",
    "gn:feature_code":"PPL",
    "gn:name":"\u2018Izbat Ab\u016b Fara\u1e29",
    "gn:population":0,
    "gn:timezone":"Africa/Cairo",
    "iso:country":"EG",
    "name:ara_x_preferred":[
        "\u0639\u0632\u0628\u0629 \u0627\u0628\u0648 \u0641\u0631\u062d"
    ],
    "name:und_x_variant":[
        "\u2018Izbat Ab\u016b Fara\u1e29"
    ],
    "wof:name":"`Izbat Abu Farah",
    "wof:placetype":"locality"
},
  "geometry": {"coordinates":[30.42418,31.44943],"type":"Point"}
}