{
  "type": "Feature",
  "properties": {
    "gn:admin1_code":"14",
    "gn:asciiname":"`Izbat al Marzuqi",
    "gn:country_code":"EG",
    "gn:dem":14,
    "gn:feature_class":"P",
    "gn:feature_code":"PPL",
    "gn:name":"\u2018Izbat al Marz\u016bq\u012b",
    "gn:population":0,
    "gn:timezone":"Africa/Cairo",
    "iso:country":"EG",
    "name:ara_x_preferred":[
        "\u0639\u0632\u0628\u0629 \u0627\u0644\u0645\u0631\u0632\u0648\u0642\u064a"
    ],
    "name:und_x_variant":[
        "\u2018Izbat al Marz\u016bq\u012b"
    ],
    "wof:name":"`Izbat al Marzuqi",
    "wof:placetype":"locality"
},
  "geometry": {"coordinates":[31.68711,30.60983],"type":"Point"}
}