{
  "type": "Feature",
  "properties": {
    "gn:admin1_code":"01",
    "gn:asciiname":"Kafr al Wazir",
    "gn:country_code":"EG",
    "gn:dem":12,
    "gn:feature_class":"P",
    "gn:feature_code":"PPL",
    "gn:name":"Kafr al Waz\u012br",
    "gn:population":0,
    "gn:timezone":"Africa/Cairo",
    "iso:country":"EG",
    "name:ara_x_preferred":[
        "\u0643\u0641\u0631 \u0627\u0644\u0648\u0632\u064a\u0631"
    ],
    "name:und_x_variant":[
        "Kafr el-Waz\u00eer",
        "Kafr al Waz\u012br"
    ],
    "wof:name":"Kafr al Wazir",
    "wof:placetype":"locality"
},
  "geometry": {"coordinates":[31.33261,30.6793],"type":"Point"}
}