{
  "type": "Feature",
  "properties": {
    "gn:admin1_code":"03",
    "gn:asciiname":"`Ezbet Sidi `Isa",
    "gn:country_code":"EG",
    "gn:dem":5,
    "gn:feature_class":"P",
    "gn:feature_code":"PPL",
    "gn:name":"\u2018Ezbet S\u00eedi \u2018\u00cesa",
    "gn:population":0,
    "gn:timezone":"Africa/Cairo",
    "iso:country":"EG",
    "wof:name":"`Ezbet Sidi `Isa",
    "wof:placetype":"locality"
},
  "geometry": {"coordinates":[30.45206,30.81885],"type":"Point"}
}