{
  "type": "Feature",
  "properties": {
    "gn:admin1_code":"01",
    "gn:asciiname":"Shirinqash",
    "gn:country_code":"EG",
    "gn:dem":10,
    "gn:feature_class":"P",
    "gn:feature_code":"PPL",
    "gn:name":"Shirinq\u0101sh",
    "gn:population":0,
    "gn:timezone":"Africa/Cairo",
    "iso:country":"EG",
    "name:ara_x_preferred":[
        "Shirinq\u0101sh"
    ],
    "name:ara_x_variant":[
        "\u0634\u0631\u0646\u0642\u0627\u0634"
    ],
    "wof:name":"Shirinqash",
    "wof:placetype":"locality"
},
  "geometry": {"coordinates":[31.41207,31.08971],"type":"Point"}
}