{
  "type": "Feature",
  "properties": {
    "gn:admin1_code":"03",
    "gn:asciiname":"`Izbat Kawm Rizq",
    "gn:country_code":"EG",
    "gn:dem":3,
    "gn:feature_class":"P",
    "gn:feature_code":"PPL",
    "gn:name":"\u2018Izbat Kawm Rizq",
    "gn:population":0,
    "gn:timezone":"Africa/Cairo",
    "iso:country":"EG",
    "name:ara_x_preferred":[
        "\u0639\u0632\u0628\u0629 \u0643\u0648\u0645 \u0631\u0632\u0642"
    ],
    "name:und_x_variant":[
        "\u2018Ezbet K\u00f4m Rizq",
        "\u2018Izbat Kawm Rizq"
    ],
    "wof:name":"`Izbat Kawm Rizq",
    "wof:placetype":"locality"
},
  "geometry": {"coordinates":[30.31163,31.0028],"type":"Point"}
}