{
  "type": "Feature",
  "properties": {
    "gn:admin1_code":"14",
    "gn:asciiname":"`Izbat al Bih",
    "gn:country_code":"EG",
    "gn:dem":14,
    "gn:feature_class":"P",
    "gn:feature_code":"PPL",
    "gn:name":"\u2018Izbat al B\u012bh",
    "gn:population":0,
    "gn:timezone":"Africa/Cairo",
    "iso:country":"EG",
    "name:ara_x_preferred":[
        "\u0639\u0632\u0628\u0629 \u0627\u0644\u0628\u064a\u0629"
    ],
    "name:und_x_variant":[
        "\u2018Izbat al B\u012bh"
    ],
    "wof:name":"`Izbat al Bih",
    "wof:placetype":"locality"
},
  "geometry": {"coordinates":[31.40175,30.53387],"type":"Point"}
}