{
  "type": "Feature",
  "properties": {
    "gn:admin1_code":"17",
    "gn:asciiname":"Tasa",
    "gn:country_code":"EG",
    "gn:dem":61,
    "gn:feature_class":"P",
    "gn:feature_code":"PPL",
    "gn:name":"T\u0101s\u0101",
    "gn:population":0,
    "gn:timezone":"Africa/Cairo",
    "iso:country":"EG",
    "name:ceb_x_preferred":[
        "Tasa"
    ],
    "name:fra_x_preferred":[
        "Tasa"
    ],
    "name:ita_x_preferred":[
        "Tasa"
    ],
    "name:nld_x_preferred":[
        "Tasa"
    ],
    "name:ron_x_preferred":[
        "Tasa"
    ],
    "name:swe_x_preferred":[
        "Tasa"
    ],
    "name:vie_x_preferred":[
        "Tasa"
    ],
    "name:war_x_preferred":[
        "Tasa"
    ],
    "wof:name":"Tasa",
    "wof:placetype":"locality"
},
  "geometry": {"coordinates":[31.38333,27.05417000000001],"type":"Point"}
}