{
  "type": "Feature",
  "properties": {
    "gn:admin1_code":"04",
    "gn:asciiname":"Kafr al Jubb",
    "gn:country_code":"EG",
    "gn:dem":20,
    "gn:feature_class":"P",
    "gn:feature_code":"PPL",
    "gn:name":"Kafr al Jubb",
    "gn:population":0,
    "gn:timezone":"Africa/Cairo",
    "iso:country":"EG",
    "wof:name":"Kafr al Jubb",
    "wof:placetype":"locality"
},
  "geometry": {"coordinates":[30.8283,29.25539],"type":"Point"}
}