{
  "type": "Feature",
  "properties": {
    "gn:admin1_code":"21",
    "gn:asciiname":"`Ezbet el Baron de Menascha",
    "gn:country_code":"EG",
    "gn:dem":4,
    "gn:feature_class":"P",
    "gn:feature_code":"PPL",
    "gn:name":"\u2018Ezbet el Baron de Menascha",
    "gn:population":0,
    "gn:timezone":"Africa/Cairo",
    "iso:country":"EG",
    "wof:name":"`Ezbet el Baron de Menascha",
    "wof:placetype":"locality"
},
  "geometry": {"coordinates":[31.03333,31.21667],"type":"Point"}
}