{
  "type": "Feature",
  "properties": {
    "gn:admin1_code":"14",
    "gn:asciiname":"Kafr al Libba",
    "gn:country_code":"EG",
    "gn:dem":10,
    "gn:feature_class":"P",
    "gn:feature_code":"PPL",
    "gn:name":"Kafr al Libb\u0101",
    "gn:population":0,
    "gn:timezone":"Africa/Cairo",
    "iso:country":"EG",
    "name:ara_x_preferred":[
        "\u0643\u0641\u0631 \u0627\u0644\u0644\u0628\u0627"
    ],
    "name:und_x_variant":[
        "Kafr al Libb\u0101"
    ],
    "wof:name":"Kafr al Libba",
    "wof:placetype":"locality"
},
  "geometry": {"coordinates":[31.39197,30.73177],"type":"Point"}
}