{
  "type": "Feature",
  "properties": {
    "gn:admin1_code":"27",
    "gn:asciiname":"Al Qantarah ash Sharqiyah",
    "gn:country_code":"EG",
    "gn:dem":18,
    "gn:feature_class":"P",
    "gn:feature_code":"PPL",
    "gn:name":"Al Qan\u0163arah ash Sharq\u012byah",
    "gn:population":0,
    "gn:timezone":"Africa/Cairo",
    "iso:country":"EG",
    "name:und_x_variant":[
        "El-Qan\u1e6dara el-Sharq\u00eeya",
        "Al Qan\u0163arah ash Sharq\u012byah"
    ],
    "wof:name":"Al Qantarah ash Sharqiyah",
    "wof:placetype":"locality"
},
  "geometry": {"coordinates":[32.32318,30.84738],"type":"Point"}
}