{
  "type": "Feature",
  "properties": {
    "gn:admin1_code":"17",
    "gn:asciiname":"Nazlat Musbih",
    "gn:country_code":"EG",
    "gn:dem":64,
    "gn:feature_class":"P",
    "gn:feature_code":"PPL",
    "gn:name":"Nazlat Mu\u015fbi\u1e29",
    "gn:population":0,
    "gn:timezone":"Africa/Cairo",
    "iso:country":"EG",
    "wof:name":"Nazlat Musbih",
    "wof:placetype":"locality"
},
  "geometry": {"coordinates":[31.43333,26.96667],"type":"Point"}
}