{
  "type": "Feature",
  "properties": {
    "gn:admin1_code":"03",
    "gn:asciiname":"Ju`ayf",
    "gn:country_code":"EG",
    "gn:dem":9,
    "gn:feature_class":"P",
    "gn:feature_code":"PPL",
    "gn:name":"Ju\u2018ayf",
    "gn:population":0,
    "gn:timezone":"Africa/Cairo",
    "iso:country":"EG",
    "name:und_x_variant":[
        "Gi\u2018eif",
        "Ju\u2018ayf"
    ],
    "wof:name":"Ju`ayf",
    "wof:placetype":"locality"
},
  "geometry": {"coordinates":[30.59445,30.89364],"type":"Point"}
}