{
  "type": "Feature",
  "properties": {
    "gn:admin1_code":"01",
    "gn:asciiname":"Damas",
    "gn:country_code":"EG",
    "gn:dem":12,
    "gn:feature_class":"P",
    "gn:feature_code":"PPL",
    "gn:name":"Dam\u0101\u015f",
    "gn:population":0,
    "gn:timezone":"Africa/Cairo",
    "iso:country":"EG",
    "name:ara_x_preferred":[
        "\u062f\u0645\u0627\u0635"
    ],
    "name:und_x_variant":[
        "Dam\u00e2\u1e63",
        "Dam\u0101\u015f",
        "Dam\u0101\u1e63"
    ],
    "wof:name":"Damas",
    "wof:placetype":"locality"
},
  "geometry": {"coordinates":[31.32576,30.80552],"type":"Point"}
}