{
  "type": "Feature",
  "properties": {
    "gn:admin1_code":"01",
    "gn:asciiname":"`Izbat al Qutn",
    "gn:country_code":"EG",
    "gn:dem":3,
    "gn:feature_class":"P",
    "gn:feature_code":"PPL",
    "gn:name":"\u2018Izbat al Qu\u0163n",
    "gn:population":0,
    "gn:timezone":"Africa/Cairo",
    "iso:country":"EG",
    "name:ara_x_preferred":[
        "\u0639\u0632\u0628\u0629 \u0627\u0644\u0642\u0637\u0646"
    ],
    "name:und_x_variant":[
        "\u2018Izbat al Qu\u0163n"
    ],
    "wof:name":"`Izbat al Qutn",
    "wof:placetype":"locality"
},
  "geometry": {"coordinates":[31.45907,31.35376],"type":"Point"}
}