{
  "type": "Feature",
  "properties": {
    "gn:admin1_code":"20",
    "gn:asciiname":"`Izbat Muhammad Husayn",
    "gn:country_code":"EG",
    "gn:dem":6,
    "gn:feature_class":"P",
    "gn:feature_code":"PPL",
    "gn:name":"\u2018Izbat Mu\u1e29ammad \u1e28usayn",
    "gn:population":0,
    "gn:timezone":"Africa/Cairo",
    "iso:country":"EG",
    "name:ara_x_preferred":[
        "\u0639\u0632\u0628\u0629 \u0645\u062d\u0645\u062f \u062d\u0633\u064a\u0646"
    ],
    "name:und_x_variant":[
        "\u2018Izbat Mu\u1e29ammad \u1e28usayn"
    ],
    "wof:name":"`Izbat Muhammad Husayn",
    "wof:placetype":"locality"
},
  "geometry": {"coordinates":[31.6108,31.29713],"type":"Point"}
}