{
  "type": "Feature",
  "properties": {
    "gn:admin1_code":"12",
    "gn:asciiname":"Nawa",
    "gn:country_code":"EG",
    "gn:dem":21,
    "gn:feature_class":"P",
    "gn:feature_code":"PPL",
    "gn:name":"Naw\u00e1",
    "gn:population":0,
    "gn:timezone":"Africa/Cairo",
    "iso:country":"EG",
    "name:ceb_x_preferred":[
        "Nawa"
    ],
    "name:deu_x_preferred":[
        "Nawa"
    ],
    "name:ita_x_preferred":[
        "Nawa"
    ],
    "name:pol_x_preferred":[
        "Nawa"
    ],
    "name:rus_x_preferred":[
        "\u041d\u0430\u0432\u0430"
    ],
    "name:swe_x_preferred":[
        "Nawa"
    ],
    "name:ukr_x_preferred":[
        "\u041d\u0430\u0432\u0430"
    ],
    "wof:name":"Nawa",
    "wof:placetype":"locality"
},
  "geometry": {"coordinates":[31.26323,30.22728],"type":"Point"}
}