{
  "type": "Feature",
  "properties": {
    "gn:admin1_code":"14",
    "gn:asciiname":"`Izbat ash Shaykh Gharib",
    "gn:country_code":"EG",
    "gn:dem":8,
    "gn:feature_class":"P",
    "gn:feature_code":"PPL",
    "gn:name":"\u2018Izbat ash Shaykh Ghar\u012bb",
    "gn:population":0,
    "gn:timezone":"Africa/Cairo",
    "iso:country":"EG",
    "name:ara_x_preferred":[
        "\u0639\u0632\u0628\u0629 \u0627\u0644\u0634\u064a\u062e \u063a\u0631\u064a\u0628"
    ],
    "name:und_x_variant":[
        "\u2018Izbat ash Shaykh Ghar\u012bb"
    ],
    "wof:name":"`Izbat ash Shaykh Gharib",
    "wof:placetype":"locality"
},
  "geometry": {"coordinates":[31.95895,30.54193],"type":"Point"}
}