{
  "type": "Feature",
  "properties": {
    "gn:admin1_code":"03",
    "gn:asciiname":"Kom Turuga",
    "gn:cc2":"EG",
    "gn:country_code":"EG",
    "gn:dem":-1,
    "gn:feature_class":"P",
    "gn:feature_code":"PPL",
    "gn:name":"K\u00f4m Tur\u00fbga",
    "gn:population":0,
    "gn:timezone":"Africa/Cairo",
    "iso:country":"EG",
    "name:und_x_variant":[
        "\u2018Ezbet K\u00f4m Tur\u00fbga",
        "K\u00f4m Tur\u00fbga"
    ],
    "wof:name":"Kom Turuga",
    "wof:placetype":"locality"
},
  "geometry": {"coordinates":[30.15278,30.95944],"type":"Point"}
}