{
  "type": "Feature",
  "properties": {
    "gn:admin1_code":"21",
    "gn:asciiname":"Qaryah Raqm `Asharah",
    "gn:country_code":"EG",
    "gn:dem":3,
    "gn:feature_class":"P",
    "gn:feature_code":"PPL",
    "gn:name":"Qaryah Raqm \u2018Asharah",
    "gn:population":0,
    "gn:timezone":"Africa/Cairo",
    "iso:country":"EG",
    "name:ara_x_preferred":[
        "\u0642\u0631\u064a\u0629 \u0631\u0642\u0645 \u0661\u0660"
    ],
    "name:ara_x_variant":[
        "\u0642\u0631\u064a\u0629 \u0631\u0642\u0645 10"
    ],
    "name:und_x_variant":[
        "Qaryah Raqm \u2018Asharah",
        "Qaryah Raqm 10"
    ],
    "wof:name":"Qaryah Raqm `Asharah",
    "wof:placetype":"locality"
},
  "geometry": {"coordinates":[31.19975,31.4423],"type":"Point"}
}