{
  "type": "Feature",
  "properties": {
    "gn:admin1_code":"23",
    "gn:asciiname":"Naj` al Gharabwah al Bahri",
    "gn:country_code":"EG",
    "gn:dem":77,
    "gn:feature_class":"P",
    "gn:feature_code":"PPL",
    "gn:name":"Naj\u2018 al Ghar\u0101bwah al Ba\u1e29r\u012b",
    "gn:population":0,
    "gn:timezone":"Africa/Cairo",
    "iso:country":"EG",
    "wof:name":"Naj` al Gharabwah al Bahri",
    "wof:placetype":"locality"
},
  "geometry": {"coordinates":[32.51729,26.16808],"type":"Point"}
}