{
  "type": "Feature",
  "properties": {
    "gn:admin1_code":"10",
    "gn:asciiname":"Umm as Sas",
    "gn:country_code":"EG",
    "gn:dem":33,
    "gn:feature_class":"P",
    "gn:feature_code":"PPL",
    "gn:name":"Umm as S\u0101s",
    "gn:population":0,
    "gn:timezone":"Africa/Cairo",
    "iso:country":"EG",
    "wof:name":"Umm as Sas",
    "wof:placetype":"locality"
},
  "geometry": {"coordinates":[30.73822,28.5006],"type":"Point"}
}