{
  "type": "Feature",
  "properties": {
    "gn:admin1_code":"15",
    "gn:asciiname":"Ash Shallufah",
    "gn:country_code":"EG",
    "gn:dem":10,
    "gn:feature_class":"P",
    "gn:feature_code":"PPL",
    "gn:name":"Ash Shall\u016bfah",
    "gn:population":0,
    "gn:timezone":"Africa/Cairo",
    "iso:country":"EG",
    "name:und_x_variant":[
        "El-Shall\u00fbfa",
        "Ash Shall\u016bfah"
    ],
    "wof:name":"Ash Shallufah",
    "wof:placetype":"locality"
},
  "geometry": {"coordinates":[32.56381,30.12773],"type":"Point"}
}