{
  "type": "Feature",
  "properties": {
    "gn:admin1_code":"24",
    "gn:asciiname":"El-Firasiya",
    "gn:country_code":"EG",
    "gn:dem":52,
    "gn:feature_class":"P",
    "gn:feature_code":"PPL",
    "gn:name":"El-Fir\u00e2s\u00eeya",
    "gn:population":0,
    "gn:timezone":"Africa/Cairo",
    "iso:country":"EG",
    "wof:name":"El-Firasiya",
    "wof:placetype":"locality"
},
  "geometry": {"coordinates":[31.61667000000001,26.71667],"type":"Point"}
}