{
  "type": "Feature",
  "properties": {
    "gn:admin1_code":"14",
    "gn:asciiname":"Kafr `Abd al `Aziz",
    "gn:country_code":"EG",
    "gn:dem":8,
    "gn:feature_class":"P",
    "gn:feature_code":"PPL",
    "gn:name":"Kafr \u2018Abd al \u2018Az\u012bz",
    "gn:population":0,
    "gn:timezone":"Africa/Cairo",
    "iso:country":"EG",
    "name:und_x_variant":[
        "Kafr \u2018Abd el-\u2018Az\u00eez",
        "Kafr \u2018Abd al \u2018Az\u012bz"
    ],
    "wof:name":"Kafr `Abd al `Aziz",
    "wof:placetype":"locality"
},
  "geometry": {"coordinates":[31.5175,30.58472],"type":"Point"}
}