{
  "type": "Feature",
  "properties": {
    "gn:admin1_code":"14",
    "gn:asciiname":"`Izbat Burdayn",
    "gn:country_code":"EG",
    "gn:dem":16,
    "gn:feature_class":"P",
    "gn:feature_code":"PPL",
    "gn:name":"\u2018Izbat Burdayn",
    "gn:population":0,
    "gn:timezone":"Africa/Cairo",
    "iso:country":"EG",
    "name:ara_x_preferred":[
        "\u0639\u0632\u0628\u0629 \u0628\u0631\u062f\u064a\u0646"
    ],
    "name:und_x_variant":[
        "Burd\u00ean",
        "Burdein",
        "Burd\u00een",
        "Burdayn",
        "\u2018Izbat Burdayn"
    ],
    "wof:name":"`Izbat Burdayn",
    "wof:placetype":"locality"
},
  "geometry": {"coordinates":[31.53387,30.50226],"type":"Point"}
}