{
  "type": "Feature",
  "properties": {
    "gn:admin1_code":"03",
    "gn:asciiname":"`Izbat Jirjis",
    "gn:country_code":"EG",
    "gn:dem":4,
    "gn:feature_class":"P",
    "gn:feature_code":"PPL",
    "gn:name":"\u2018Izbat Jirjis",
    "gn:population":0,
    "gn:timezone":"Africa/Cairo",
    "iso:country":"EG",
    "name:ara_x_preferred":[
        "\u0639\u0632\u0628\u0629 \u062c\u0631\u062c\u0633"
    ],
    "name:und_x_variant":[
        "\u2018Izbat Jirjis"
    ],
    "wof:name":"`Izbat Jirjis",
    "wof:placetype":"locality"
},
  "geometry": {"coordinates":[30.60554,31.12348],"type":"Point"}
}