{
  "type": "Feature",
  "properties": {
    "gn:admin1_code":"20",
    "gn:asciiname":"`Izbat Umm Shihabi",
    "gn:country_code":"EG",
    "gn:dem":3,
    "gn:feature_class":"P",
    "gn:feature_code":"PPL",
    "gn:name":"\u2018Izbat Umm Shih\u0101b\u012b",
    "gn:population":0,
    "gn:timezone":"Africa/Cairo",
    "iso:country":"EG",
    "name:ara_x_preferred":[
        "\u0639\u0632\u0628\u0629 \u0623\u0645 \u0634\u0647\u0627\u0628\u064a"
    ],
    "name:und_x_variant":[
        "\u2018Izbat Umm Shih\u0101b\u012b"
    ],
    "wof:name":"`Izbat Umm Shihabi",
    "wof:placetype":"locality"
},
  "geometry": {"coordinates":[31.53566,31.36104000000001],"type":"Point"}
}