{
  "type": "Feature",
  "properties": {
    "gn:country":"EG",
    "gn:fcode":"PPL",
    "gn:population":62821,
    "iso:country":"EG",
    "name:ara_x_preferred":[
        "\u0641\u0627\u0642\u0648\u0633"
    ],
    "name:arz_x_preferred":[
        "\u0641\u0627\u0642\u0648\u0633"
    ],
    "name:azb_x_preferred":[
        "\u0641\u0627\u0642\u0648\u0633"
    ],
    "name:ceb_x_preferred":[
        "F\u0101q\u016bs"
    ],
    "name:eng_x_preferred":[
        "Faqous"
    ],
    "name:fas_x_preferred":[
        "\u0641\u0627\u0642\u0648\u0633"
    ],
    "name:hye_x_preferred":[
        "\u0556\u0561\u0584\u0578\u0582\u057d"
    ],
    "name:kaz_x_preferred":[
        "\u0424\u0430\u043a\u0443\u0441 \u049b\u0430\u043b\u0430\u0441\u044b"
    ],
    "name:nld_x_preferred":[
        "Faqous"
    ],
    "name:pol_x_preferred":[
        "Fakus"
    ],
    "name:rus_x_preferred":[
        "\u0424\u0430\u043a\u0443\u0441"
    ],
    "name:swe_x_preferred":[
        "F\u0101q\u016bs"
    ],
    "name:ukr_x_preferred":[
        "\u0424\u0430\u043a\u0443\u0441"
    ],
    "name:und_x_variant":[
        "Fakous"
    ],
    "name:zho_x_preferred":[
        "\u6cd5\u53e4\u65af"
    ],
    "qs_pg:aaroncc":"EG",
    "qs_pg:gn_country":"EG",
    "qs_pg:gn_fcode":"PPL",
    "qs_pg:gn_pop":62821,
    "qs_pg:name":"F\u0101q\u016bs",
    "qs_pg:photos_9r":0,
    "qs_pg:photos_sr":0,
    "qs_pg:pop_sr":8,
    "qs_pg:qs_pg_placetype":"locality",
    "wof:name":"F\u0101q\u016bs",
    "wof:placetype":"locality",
    "wof:population":62821
},
  "geometry": {"coordinates":[31.80182,30.73006],"type":"Point"}
}