{
  "type": "Feature",
  "properties": {
    "gn:admin1_code":"14",
    "gn:asciiname":"`Izbat al `Umdah",
    "gn:country_code":"EG",
    "gn:dem":14,
    "gn:feature_class":"P",
    "gn:feature_code":"PPL",
    "gn:name":"\u2018Izbat al \u2018Umdah",
    "gn:population":0,
    "gn:timezone":"Africa/Cairo",
    "iso:country":"EG",
    "name:ara_x_preferred":[
        "\u0639\u0632\u0628\u0629 \u0627\u0644\u0639\u0645\u062f\u0629"
    ],
    "name:ara_x_variant":[
        "\u0627\u0644\u0645\u0633\u0644\u0645\u064a\u0629"
    ],
    "name:und_x_variant":[
        "\u2018Izbat al \u2018Umdah",
        "Al Musallam\u012byah",
        "Al Misallam\u012byah"
    ],
    "wof:name":"`Izbat al `Umdah",
    "wof:placetype":"locality"
},
  "geometry": {"coordinates":[31.61735,30.59527000000001],"type":"Point"}
}