{
  "type": "Feature",
  "properties": {
    "gn:admin1_code":"03",
    "gn:asciiname":"Bawadi",
    "gn:country_code":"EG",
    "gn:dem":2,
    "gn:feature_class":"P",
    "gn:feature_code":"PPL",
    "gn:name":"Baw\u0101d\u012b",
    "gn:population":0,
    "gn:timezone":"Africa/Cairo",
    "iso:country":"EG",
    "name:ara_x_preferred":[
        "\u0628\u0648\u0627\u062f\u064a"
    ],
    "name:deu_x_preferred":[
        "Dubai Bawadi"
    ],
    "name:und_x_variant":[
        "Baw\u0101d\u012b",
        "Bawad\u012b"
    ],
    "wof:name":"Bawadi",
    "wof:placetype":"locality"
},
  "geometry": {"coordinates":[30.19227,31.13367],"type":"Point"}
}