{
  "type": "Feature",
  "properties": {
    "gn:admin1_code":"14",
    "gn:asciiname":"`Izbat Khurshid",
    "gn:country_code":"EG",
    "gn:dem":10,
    "gn:feature_class":"P",
    "gn:feature_code":"PPL",
    "gn:name":"\u2018Izbat Kh\u016brsh\u012bd",
    "gn:population":0,
    "gn:timezone":"Africa/Cairo",
    "iso:country":"EG",
    "name:ara_x_preferred":[
        "\u0639\u0632\u0628\u0629 \u062e\u0648\u0631\u0634\u064a\u062f"
    ],
    "name:und_x_variant":[
        "\u2018Izbat Kh\u016brsh\u012bd"
    ],
    "wof:name":"`Izbat Khurshid",
    "wof:placetype":"locality"
},
  "geometry": {"coordinates":[31.54593,30.43802],"type":"Point"}
}