{
  "type": "Feature",
  "properties": {
    "gn:admin1_code":"01",
    "gn:asciiname":"Diyast",
    "gn:country_code":"EG",
    "gn:dem":10,
    "gn:feature_class":"P",
    "gn:feature_code":"PPL",
    "gn:name":"Diyas\u0163",
    "gn:population":0,
    "gn:timezone":"Africa/Cairo",
    "iso:country":"EG",
    "name:ara_x_preferred":[
        "\u062f\u064a\u0633\u0637"
    ],
    "name:und_x_variant":[
        "Dias\u1e6d",
        "Diyas\u0163",
        "Diyas\u1e6d",
        "Diyast"
    ],
    "wof:name":"Diyast",
    "wof:placetype":"locality"
},
  "geometry": {"coordinates":[31.43533,31.15026],"type":"Point"}
}