{
  "type": "Feature",
  "properties": {
    "gn:admin1_code":"06",
    "gn:asciiname":"Naj` al `Arab",
    "gn:country_code":"EG",
    "gn:dem":3,
    "gn:feature_class":"P",
    "gn:feature_code":"PPL",
    "gn:name":"Naj\u2018 al \u2018Arab",
    "gn:population":0,
    "gn:timezone":"Africa/Cairo",
    "iso:country":"EG",
    "name:ara_x_preferred":[
        "\u0646\u062c\u0639 \u0627\u0644\u0639\u0631\u0628"
    ],
    "name:und_x_variant":[
        "Naj\u2018 al \u2018Arab"
    ],
    "wof:name":"Naj` al `Arab",
    "wof:placetype":"locality"
},
  "geometry": {"coordinates":[29.88829,31.16673],"type":"Point"}
}