{
  "type": "Feature",
  "properties": {
    "gn:admin1_code":"14",
    "gn:asciiname":"Kafr al Husr",
    "gn:country_code":"EG",
    "gn:dem":14,
    "gn:feature_class":"P",
    "gn:feature_code":"PPL",
    "gn:name":"Kafr al \u1e28u\u015fr",
    "gn:population":0,
    "gn:timezone":"Africa/Cairo",
    "iso:country":"EG",
    "name:ara_x_preferred":[
        "\u0643\u0641\u0631 \u0627\u0644\u062d\u0635\u0631"
    ],
    "name:und_x_variant":[
        "Kafr el \u1e24u\u1e63r",
        "Kafr al \u1e28u\u015fr"
    ],
    "wof:name":"Kafr al Husr",
    "wof:placetype":"locality"
},
  "geometry": {"coordinates":[31.51309,30.60232],"type":"Point"}
}