{
  "type": "Feature",
  "properties": {
    "gn:admin1_code":"08",
    "gn:asciiname":"`Izbat Abu Khalid",
    "gn:country_code":"EG",
    "gn:dem":21,
    "gn:feature_class":"P",
    "gn:feature_code":"PPL",
    "gn:name":"\u2018Izbat Ab\u016b Kh\u0101lid",
    "gn:population":0,
    "gn:timezone":"Africa/Cairo",
    "iso:country":"EG",
    "name:ara_x_preferred":[
        "\u0639\u0632\u0628\u0629 \u0623\u0628\u0648 \u062e\u0627\u0644\u062f"
    ],
    "name:und_x_variant":[
        "\u2018Izbat Ab\u016b Kh\u0101lid"
    ],
    "wof:name":"`Izbat Abu Khalid",
    "wof:placetype":"locality"
},
  "geometry": {"coordinates":[30.85919,30.32503],"type":"Point"}
}