{
  "type": "Feature",
  "properties": {
    "gn:admin1_code":"10",
    "gn:asciiname":"Al Jundiyah",
    "gn:country_code":"EG",
    "gn:dem":41,
    "gn:feature_class":"P",
    "gn:feature_code":"PPL",
    "gn:name":"Al Jund\u012byah",
    "gn:population":0,
    "gn:timezone":"Africa/Cairo",
    "iso:country":"EG",
    "name:und_x_variant":[
        "El Gind\u00eeya",
        "Al Jund\u012byah"
    ],
    "wof:name":"Al Jundiyah",
    "wof:placetype":"locality"
},
  "geometry": {"coordinates":[30.82818,28.56921],"type":"Point"}
}