{
  "type": "Feature",
  "properties": {
    "gn:admin1_code":"10",
    "gn:asciiname":"Al Mahras",
    "gn:country_code":"EG",
    "gn:dem":46,
    "gn:feature_class":"P",
    "gn:feature_code":"PPL",
    "gn:name":"Al Ma\u1e29ra\u015f",
    "gn:population":0,
    "gn:timezone":"Africa/Cairo",
    "iso:country":"EG",
    "name:und_x_variant":[
        "El Ma\u1e25ras",
        "Al Ma\u1e29ra\u015f"
    ],
    "wof:name":"Al Mahras",
    "wof:placetype":"locality"
},
  "geometry": {"coordinates":[30.79784,27.82888],"type":"Point"}
}