{
  "type": "Feature",
  "properties": {
    "gn:admin1_code":"03",
    "gn:asciiname":"`Izbat Mazhar",
    "gn:country_code":"EG",
    "gn:dem":0,
    "gn:feature_class":"P",
    "gn:feature_code":"PPL",
    "gn:name":"\u2018Izbat Maz\u0327har",
    "gn:population":0,
    "gn:timezone":"Africa/Cairo",
    "iso:country":"EG",
    "name:ara_x_preferred":[
        "\u0639\u0632\u0628\u0629 \u0645\u0638\u0647\u0631"
    ],
    "name:und_x_variant":[
        "\u2018Izbat Maz\u0327har",
        "\u2018Izbat Ma\u1e93har"
    ],
    "wof:name":"`Izbat Mazhar",
    "wof:placetype":"locality"
},
  "geometry": {"coordinates":[30.26666,31.14914000000001],"type":"Point"}
}