{
  "type": "Feature",
  "properties": {
    "gn:admin1_code":"10",
    "gn:asciiname":"Nag' Saiyid Muftah",
    "gn:country_code":"EG",
    "gn:dem":40,
    "gn:feature_class":"P",
    "gn:feature_code":"PPL",
    "gn:name":"Nag\u2019 Saiyid Muft\u00e2\u1e25",
    "gn:population":0,
    "gn:timezone":"Africa/Cairo",
    "iso:country":"EG",
    "wof:name":"Nag' Saiyid Muftah",
    "wof:placetype":"locality"
},
  "geometry": {"coordinates":[30.63333,28.11667000000001],"type":"Point"}
}