{
  "type": "Feature",
  "properties": {
    "gn:admin1_code":"01",
    "gn:asciiname":"`Izbat `Uwaylat Fudah",
    "gn:country_code":"EG",
    "gn:dem":7,
    "gn:feature_class":"P",
    "gn:feature_code":"PPL",
    "gn:name":"\u2018Izbat \u2018Uwaylat F\u016bdah",
    "gn:population":0,
    "gn:timezone":"Africa/Cairo",
    "iso:country":"EG",
    "name:ara_x_preferred":[
        "\u0639\u0632\u0628\u0629 \u0639\u0648\u064a\u0644\u0629 \u0641\u0648\u062f\u0629"
    ],
    "name:und_x_variant":[
        "\u2018Izbat \u2018Uwaylat F\u016bdah"
    ],
    "wof:name":"`Izbat `Uwaylat Fudah",
    "wof:placetype":"locality"
},
  "geometry": {"coordinates":[31.57834,30.88665],"type":"Point"}
}