{
  "type": "Feature",
  "properties": {
    "gn:admin1_code":"23",
    "gn:asciiname":"Naj` al Miyat",
    "gn:country_code":"EG",
    "gn:dem":101,
    "gn:feature_class":"P",
    "gn:feature_code":"PPL",
    "gn:name":"Naj\u2018 al Miy\u0101t",
    "gn:population":0,
    "gn:timezone":"Africa/Cairo",
    "iso:country":"EG",
    "wof:name":"Naj` al Miyat",
    "wof:placetype":"locality"
},
  "geometry": {"coordinates":[32.3875,26.18],"type":"Point"}
}