{
  "type": "Feature",
  "properties": {
    "gn:admin1_code":"03",
    "gn:asciiname":"`Izbat Hajjaj",
    "gn:country_code":"EG",
    "gn:dem":4,
    "gn:feature_class":"P",
    "gn:feature_code":"PPL",
    "gn:name":"\u2018Izbat \u1e28ajj\u0101j",
    "gn:population":0,
    "gn:timezone":"Africa/Cairo",
    "iso:country":"EG",
    "name:ara_x_preferred":[
        "\u0639\u0632\u0628\u0629 \u062d\u062c\u0627\u062c"
    ],
    "name:und_x_variant":[
        "\u2018Ezbet \u1e24agg\u00e2g",
        "\u2018Izbat \u1e28ajj\u0101j",
        "\u2018Izbat \u1e24ajj\u0101j"
    ],
    "wof:name":"`Izbat Hajjaj",
    "wof:placetype":"locality"
},
  "geometry": {"coordinates":[30.16167,31.1798],"type":"Point"}
}