{
  "type": "Feature",
  "properties": {
    "gn:admin1_code":"14",
    "gn:asciiname":"Al Misah",
    "gn:country_code":"EG",
    "gn:dem":9,
    "gn:feature_class":"P",
    "gn:feature_code":"PPL",
    "gn:name":"Al M\u012bs\u0101h",
    "gn:population":0,
    "gn:timezone":"Africa/Cairo",
    "iso:country":"EG",
    "name:ara_x_preferred":[
        "\u0627\u0644\u0645\u064a\u0633\u0627\u0629"
    ],
    "name:und_x_variant":[
        "El-M\u00ees\u00e2h",
        "Al M\u012bs\u0101h",
        "Al-M\u012bs\u0101h"
    ],
    "wof:name":"Al Misah",
    "wof:placetype":"locality"
},
  "geometry": {"coordinates":[31.45147,30.80347],"type":"Point"}
}