{
  "type": "Feature",
  "properties": {
    "gn:admin1_code":"28",
    "gn:asciiname":"Az Zayniyah Bahri",
    "gn:country_code":"EG",
    "gn:dem":80,
    "gn:feature_class":"P",
    "gn:feature_code":"PPL",
    "gn:name":"Az Zayn\u012byah Ba\u1e29r\u012b",
    "gn:population":0,
    "gn:timezone":"Africa/Cairo",
    "iso:country":"EG",
    "name:und_x_variant":[
        "Nag\u2018 \u1e24a\u1e6dab",
        "Naj\u2018 \u1e28a\u0163ab",
        "El-Zein\u00eeya Ba\u1e25ari",
        "El-Zeinly\u00e2t",
        "Az Zayn\u012byah Ba\u1e29r\u012b"
    ],
    "wof:name":"Az Zayniyah Bahri",
    "wof:placetype":"locality"
},
  "geometry": {"coordinates":[32.685,25.76469],"type":"Point"}
}