{
  "type": "Feature",
  "properties": {
    "gn:admin1_code":"21",
    "gn:asciiname":"Al Fuqaha' al Qibliyah",
    "gn:country_code":"EG",
    "gn:dem":3,
    "gn:feature_class":"P",
    "gn:feature_code":"PPL",
    "gn:name":"Al Fuqah\u0101\u2019 al Qibl\u012byah",
    "gn:population":0,
    "gn:timezone":"Africa/Cairo",
    "iso:country":"EG",
    "name:ara_x_preferred":[
        "\u0627\u0644\u0641\u0642\u0647\u0627\u0621 \u0627\u0644\u0642\u0628\u0644\u064a\u0629"
    ],
    "name:und_x_variant":[
        "Fuqah\u0101\u2019 al Qibl\u012byah",
        "Fuqaha el-Qibl\u00eeya",
        "Al Fuqah\u0101\u2019 al Qibl\u012byah",
        "Al-Fuqah\u0101\u2019 al-Qibliyyah"
    ],
    "wof:name":"Al Fuqaha' al Qibliyah",
    "wof:placetype":"locality"
},
  "geometry": {"coordinates":[30.69344,31.2919],"type":"Point"}
}