{
  "type": "Feature",
  "properties": {
    "gn:admin1_code":"21",
    "gn:asciiname":"`Izbat Abu Zuhrah",
    "gn:country_code":"EG",
    "gn:dem":4,
    "gn:feature_class":"P",
    "gn:feature_code":"PPL",
    "gn:name":"\u2018Izbat Ab\u016b Zuhrah",
    "gn:population":0,
    "gn:timezone":"Africa/Cairo",
    "iso:country":"EG",
    "name:ara_x_preferred":[
        "\u0639\u0632\u0628\u0629 \u0623\u0628\u0648 \u0632\u0647\u0631\u0629"
    ],
    "name:und_x_variant":[
        "\u2018Izbat Ab\u016b Zuhrah",
        "\u2018Izbat Ab\u016b Zahrah"
    ],
    "wof:name":"`Izbat Abu Zuhrah",
    "wof:placetype":"locality"
},
  "geometry": {"coordinates":[30.78719,31.2353],"type":"Point"}
}