{
  "type": "Feature",
  "properties": {
    "gn:admin1_code":"03",
    "gn:asciiname":"`Izbat ash Sharif",
    "gn:country_code":"EG",
    "gn:dem":4,
    "gn:feature_class":"P",
    "gn:feature_code":"PPL",
    "gn:name":"\u2018Izbat ash Shar\u012bf",
    "gn:population":0,
    "gn:timezone":"Africa/Cairo",
    "iso:country":"EG",
    "name:ara_x_preferred":[
        "\u0639\u0632\u0628\u0629 \u0627\u0644\u0634\u0631\u064a\u0641"
    ],
    "name:und_x_variant":[
        "\u2018Izbat ash Shar\u012bf"
    ],
    "wof:name":"`Izbat ash Sharif",
    "wof:placetype":"locality"
},
  "geometry": {"coordinates":[30.49309,31.33233],"type":"Point"}
}