{
  "type": "Feature",
  "properties": {
    "gn:admin1_code":"03",
    "gn:asciiname":"`Izbat Hutaytah",
    "gn:country_code":"EG",
    "gn:dem":0,
    "gn:feature_class":"P",
    "gn:feature_code":"PPL",
    "gn:name":"\u2018Izbat \u1e28utaytah",
    "gn:population":0,
    "gn:timezone":"Africa/Cairo",
    "iso:country":"EG",
    "name:ara_x_preferred":[
        "\u0639\u0632\u0628\u0629 \u062d\u062a\u064a\u062a\u0629"
    ],
    "name:und_x_variant":[
        "\u2018Izbat \u1e28utaytah",
        "\u2018Ezbet \u1e24iteita"
    ],
    "wof:name":"`Izbat Hutaytah",
    "wof:placetype":"locality"
},
  "geometry": {"coordinates":[30.30469,31.0712],"type":"Point"}
}