{
  "type": "Feature",
  "properties": {
    "gn:admin1_code":"10",
    "gn:asciiname":"Ismu al `Arus",
    "gn:country_code":"EG",
    "gn:dem":53,
    "gn:feature_class":"P",
    "gn:feature_code":"PPL",
    "gn:name":"Ism\u016b al \u2018Ar\u016bs",
    "gn:population":0,
    "gn:timezone":"Africa/Cairo",
    "iso:country":"EG",
    "name:und_x_variant":[
        "Ismu el Ar\u00fbs",
        "Ism\u016b al \u2018Ar\u016bs"
    ],
    "wof:name":"Ismu al `Arus",
    "wof:placetype":"locality"
},
  "geometry": {"coordinates":[30.76475,27.62619],"type":"Point"}
}