{
  "type": "Feature",
  "properties": {
    "gn:admin1_code":"03",
    "gn:asciiname":"Qaryat al Khartum",
    "gn:country_code":"EG",
    "gn:dem":27,
    "gn:feature_class":"P",
    "gn:feature_code":"PPL",
    "gn:name":"Qaryat al Khart\u016bm",
    "gn:population":0,
    "gn:timezone":"Africa/Cairo",
    "iso:country":"EG",
    "wof:name":"Qaryat al Khartum",
    "wof:placetype":"locality"
},
  "geometry": {"coordinates":[30.66475,30.55576],"type":"Point"}
}