{
  "type": "Feature",
  "properties": {
    "gn:admin1_code":"05",
    "gn:asciiname":"`Izbat al Qasabi",
    "gn:country_code":"EG",
    "gn:dem":8,
    "gn:feature_class":"P",
    "gn:feature_code":"PPL",
    "gn:name":"\u2018Izbat al Qa\u015fab\u012b",
    "gn:population":0,
    "gn:timezone":"Africa/Cairo",
    "iso:country":"EG",
    "name:ara_x_preferred":[
        "\u0639\u0632\u0628\u0629 \u0627\u0644\u0642\u0635\u0628\u064a"
    ],
    "name:und_x_variant":[
        "\u2018Izbat al Qa\u015fab\u012b",
        "\u2018Izbat al-Qa\u1e63ab\u012b"
    ],
    "wof:name":"`Izbat al Qasabi",
    "wof:placetype":"locality"
},
  "geometry": {"coordinates":[31.11156,30.91829],"type":"Point"}
}