{
  "type": "Feature",
  "properties": {
    "gn:admin1_code":"14",
    "gn:asciiname":"Kafr al Batil",
    "gn:cc2":"EG",
    "gn:country_code":"EG",
    "gn:dem":10,
    "gn:feature_class":"P",
    "gn:feature_code":"PPL",
    "gn:name":"Kafr al B\u0101\u0163il",
    "gn:population":0,
    "gn:timezone":"Africa/Cairo",
    "iso:country":"EG",
    "name:und_x_variant":[
        "Kafr el-B\u00e2\u1e6dil",
        "Kafr al B\u0101\u0163il"
    ],
    "wof:name":"Kafr al Batil",
    "wof:placetype":"locality"
},
  "geometry": {"coordinates":[31.71139,30.53833],"type":"Point"}
}