{
  "type": "Feature",
  "properties": {
    "gn:admin1_code":"03",
    "gn:asciiname":"Mahallat Qays",
    "gn:country_code":"EG",
    "gn:dem":6,
    "gn:feature_class":"P",
    "gn:feature_code":"PPL",
    "gn:name":"Ma\u1e29allat Qays",
    "gn:population":0,
    "gn:timezone":"Africa/Cairo",
    "iso:country":"EG",
    "name:und_x_variant":[
        "Ma\u1e25allet Qeis",
        "Ma\u1e29allat Qays"
    ],
    "wof:name":"Mahallat Qays",
    "wof:placetype":"locality"
},
  "geometry": {"coordinates":[30.66256,30.98396],"type":"Point"}
}