{
  "type": "Feature",
  "properties": {
    "gn:admin1_code":"24",
    "gn:asciiname":"Nag' Hammu'de",
    "gn:country_code":"EG",
    "gn:dem":58,
    "gn:feature_class":"P",
    "gn:feature_code":"PPL",
    "gn:name":"Nag\u2019 Hamm\u00fb\u2019de",
    "gn:population":0,
    "gn:timezone":"Africa/Cairo",
    "iso:country":"EG",
    "wof:name":"Nag' Hammu'de",
    "wof:placetype":"locality"
},
  "geometry": {"coordinates":[31.46667,26.76667],"type":"Point"}
}