{
  "type": "Feature",
  "properties": {
    "gn:admin1_code":"15",
    "gn:asciiname":"Al Adabiyah",
    "gn:country_code":"EG",
    "gn:dem":9,
    "gn:feature_class":"P",
    "gn:feature_code":"PPL",
    "gn:name":"Al Adab\u012byah",
    "gn:population":0,
    "gn:timezone":"Africa/Cairo",
    "iso:country":"EG",
    "name:ara_x_preferred":[
        "\u0622\u0644 \u0627\u0644\u0623\u062f\u0628\u064a\u0629"
    ],
    "name:und_x_variant":[
        "El-\u2018Adab\u00eeya",
        "Al Adab\u012byah"
    ],
    "wof:name":"Al Adabiyah",
    "wof:placetype":"locality"
},
  "geometry": {"coordinates":[32.4719,29.87668],"type":"Point"}
}