{
  "type": "Feature",
  "properties": {
    "gn:admin1_code":"13",
    "gn:asciiname":"Al Jadidah",
    "gn:country_code":"EG",
    "gn:dem":114,
    "gn:feature_class":"P",
    "gn:feature_code":"PPL",
    "gn:name":"Al Jad\u012bdah",
    "gn:population":0,
    "gn:timezone":"Africa/Cairo",
    "iso:country":"EG",
    "name:fas_x_preferred":[
        "\u0627\u0644\u062c\u062f\u06cc\u062f\u0627\u0647"
    ],
    "name:nno_x_preferred":[
        "Al Jadidah"
    ],
    "name:und_x_variant":[
        "El Gid\u012bda",
        "Al Jad\u012bdah"
    ],
    "wof:name":"Al Jadidah",
    "wof:placetype":"locality"
},
  "geometry": {"coordinates":[28.85917,25.57786],"type":"Point"}
}