{
  "type": "Feature",
  "properties": {
    "gn:admin1_code":"01",
    "gn:asciiname":"`Izbat `Asharah",
    "gn:country_code":"EG",
    "gn:dem":3,
    "gn:feature_class":"P",
    "gn:feature_code":"PPL",
    "gn:name":"\u2018Izbat \u2018Asharah",
    "gn:population":0,
    "gn:timezone":"Africa/Cairo",
    "iso:country":"EG",
    "name:ara_x_preferred":[
        "\u0639\u0632\u0628\u0629 \u0639\u0634\u0631\u0629"
    ],
    "name:und_x_variant":[
        "\u2018Izbat \u2018Asharah",
        "\u2018Izbat Ten"
    ],
    "wof:name":"`Izbat `Asharah",
    "wof:placetype":"locality"
},
  "geometry": {"coordinates":[31.9367,31.10476],"type":"Point"}
}