{
  "type": "Feature",
  "properties": {
    "gn:admin1_code":"04",
    "gn:asciiname":"`Izbat Hilmi Za`zu`",
    "gn:country_code":"EG",
    "gn:dem":27,
    "gn:feature_class":"P",
    "gn:feature_code":"PPL",
    "gn:name":"\u2018Izbat \u1e28ilm\u012b Za\u2018z\u016b\u2018",
    "gn:population":0,
    "gn:timezone":"Africa/Cairo",
    "iso:country":"EG",
    "wof:name":"`Izbat Hilmi Za`zu`",
    "wof:placetype":"locality"
},
  "geometry": {"coordinates":[30.94823,29.16611],"type":"Point"}
}