{
  "type": "Feature",
  "properties": {
    "gn:admin1_code":"03",
    "gn:asciiname":"Ash Shahabiyah",
    "gn:country_code":"EG",
    "gn:dem":3,
    "gn:feature_class":"P",
    "gn:feature_code":"PPL",
    "gn:name":"Ash Shah\u0101b\u012byah",
    "gn:population":0,
    "gn:timezone":"Africa/Cairo",
    "iso:country":"EG",
    "name:ara_x_preferred":[
        "\u0627\u0644\u0634\u0647\u0627\u0628\u064a\u0629"
    ],
    "name:und_x_variant":[
        "Ash Shah\u0101b\u012byah",
        "Ash-Shah\u0101biyyah"
    ],
    "wof:name":"Ash Shahabiyah",
    "wof:placetype":"locality"
},
  "geometry": {"coordinates":[30.45659,31.11824],"type":"Point"}
}