{
  "type": "Feature",
  "properties": {
    "gn:admin1_code":"14",
    "gn:asciiname":"Rawd al Falij",
    "gn:country_code":"EG",
    "gn:dem":25,
    "gn:feature_class":"P",
    "gn:feature_code":"PPL",
    "gn:name":"Raw\u1e11 al F\u0101lij",
    "gn:population":0,
    "gn:timezone":"Africa/Cairo",
    "iso:country":"EG",
    "name:ara_x_preferred":[
        "\u0631\u0648\u0636 \u0627\u0644\u0641\u0627\u0644\u062c"
    ],
    "name:und_x_variant":[
        "Raw\u1e11 al F\u0101lij"
    ],
    "wof:name":"Rawd al Falij",
    "wof:placetype":"locality"
},
  "geometry": {"coordinates":[31.93942,30.63903],"type":"Point"}
}