{
  "type": "Feature",
  "properties": {
    "gn:admin1_code":"21",
    "gn:asciiname":"`Izbat as Sayyid Mansur",
    "gn:country_code":"EG",
    "gn:dem":2,
    "gn:feature_class":"P",
    "gn:feature_code":"PPL",
    "gn:name":"\u2018Izbat as Sayyid Man\u015f\u016br",
    "gn:population":0,
    "gn:timezone":"Africa/Cairo",
    "iso:country":"EG",
    "name:ara_x_preferred":[
        "\u0639\u0632\u0628\u0629 \u0627\u0644\u0633\u064a\u062f \u0645\u0646\u0635\u0648\u0631"
    ],
    "name:und_x_variant":[
        "\u2018Izbat as Sayyid Man\u015f\u016br"
    ],
    "wof:name":"`Izbat as Sayyid Mansur",
    "wof:placetype":"locality"
},
  "geometry": {"coordinates":[30.67251,31.32179],"type":"Point"}
}