{
  "type": "Feature",
  "properties": {
    "gn:admin1_code":"05",
    "gn:asciiname":"`Izbat ar Rawdah",
    "gn:country_code":"EG",
    "gn:dem":3,
    "gn:feature_class":"P",
    "gn:feature_code":"PPL",
    "gn:name":"\u2018Izbat ar Raw\u1e11ah",
    "gn:population":0,
    "gn:timezone":"Africa/Cairo",
    "iso:country":"EG",
    "name:ara_x_preferred":[
        "\u0639\u0632\u0628\u0629 \u0627\u0644\u0631\u0648\u0636\u0629"
    ],
    "name:und_x_variant":[
        "\u2018Izbat ar Raw\u1e11ah",
        "\u2018Izbat ar-Raw\u1e0dah"
    ],
    "wof:name":"`Izbat ar Rawdah",
    "wof:placetype":"locality"
},
  "geometry": {"coordinates":[31.12705,31.13652],"type":"Point"}
}