{
  "type": "Feature",
  "properties": {
    "gn:admin1_code":"12",
    "gn:asciiname":"`Izbat Isma`il `Ali Yahya",
    "gn:country_code":"EG",
    "gn:dem":17,
    "gn:feature_class":"P",
    "gn:feature_code":"PPL",
    "gn:name":"\u2018Izbat Ism\u0101\u2018\u012bl \u2018Al\u012b Ya\u1e29y\u00e1",
    "gn:population":0,
    "gn:timezone":"Africa/Cairo",
    "iso:country":"EG",
    "name:ara_x_preferred":[
        "\u0639\u0632\u0628\u0629 \u0627\u0633\u0645\u0627\u0639\u064a\u0644 \u0639\u0644\u064a \u064a\u062d\u064a\u0649"
    ],
    "name:und_x_variant":[
        "\u2018Izbat Ism\u0101\u2018\u012bl \u2018Al\u012b Ya\u1e29y\u00e1"
    ],
    "wof:name":"`Izbat Isma`il `Ali Yahya",
    "wof:placetype":"locality"
},
  "geometry": {"coordinates":[31.24321,30.52106],"type":"Point"}
}