{
  "type": "Feature",
  "properties": {
    "gn:admin1_code":"23",
    "gn:asciiname":"Ad Dayr ash Sharqi",
    "gn:country_code":"EG",
    "gn:dem":77,
    "gn:feature_class":"P",
    "gn:feature_code":"PPL",
    "gn:name":"Ad Dayr ash Sharq\u012b",
    "gn:population":0,
    "gn:timezone":"Africa/Cairo",
    "iso:country":"EG",
    "wof:name":"Ad Dayr ash Sharqi",
    "wof:placetype":"locality"
},
  "geometry": {"coordinates":[32.75646,26.06691],"type":"Point"}
}