{
  "type": "Feature",
  "properties": {
    "gn:admin1_code":"05",
    "gn:asciiname":"`Izbat Baghus",
    "gn:country_code":"EG",
    "gn:dem":9,
    "gn:feature_class":"P",
    "gn:feature_code":"PPL",
    "gn:name":"\u2018Izbat B\u0101gh\u016b\u015f",
    "gn:population":0,
    "gn:timezone":"Africa/Cairo",
    "iso:country":"EG",
    "name:ara_x_preferred":[
        "\u0639\u0632\u0628\u0629 \u0628\u0627\u063a\u0648\u0635"
    ],
    "name:und_x_variant":[
        "\u2018Izbat B\u0101gh\u016b\u015f",
        "\u2018Izbat B\u0101gh\u016b\u1e63"
    ],
    "wof:name":"`Izbat Baghus",
    "wof:placetype":"locality"
},
  "geometry": {"coordinates":[31.05392,30.92498],"type":"Point"}
}