{
  "type": "Feature",
  "properties": {
    "gn:country":"EG",
    "iso:country":"EG",
    "qs:name":"The New Dekhelah Harbour",
    "qs:name_adm0":"\u0645\u0635\u0631",
    "qs:name_adm1":"\u0627\u0644\u0627\u0633\u0643\u0646\u062f\u0631\u064a\u0629",
    "qs:photos":4,
    "qs:photos_1k":1,
    "qs:photos_9k":1,
    "qs:photos_9r":1,
    "qs:photos_all":4,
    "qs:photos_sr":1,
    "qs:placetype":"Town",
    "qs:pop_sr":"0",
    "wof:name":"The New Dekhelah Harbour",
    "wof:placetype":"locality"
},
  "geometry": {"coordinates":[29.798612,31.1378965],"type":"Point"}
}