{
  "type": "Feature",
  "properties": {
    "gn:admin1_code":"05",
    "gn:asciiname":"An Nasiriyah",
    "gn:country_code":"EG",
    "gn:dem":17,
    "gn:feature_class":"P",
    "gn:feature_code":"PPL",
    "gn:name":"An N\u0101\u015fir\u012byah",
    "gn:population":0,
    "gn:timezone":"Africa/Cairo",
    "iso:country":"EG",
    "name:ara_x_preferred":[
        "\u0627\u0644\u0646\u0627\u0635\u0631\u064a\u0629"
    ],
    "name:und_x_variant":[
        "M\u00eet el-Na\u1e63\u00e2ra",
        "M\u012bt an Na\u015f\u0101r\u00e1",
        "An N\u0101\u015fir\u012byah",
        "An-N\u0101\u1e63iriyyah"
    ],
    "wof:name":"An Nasiriyah",
    "wof:placetype":"locality"
},
  "geometry": {"coordinates":[31.24287,30.94017],"type":"Point"}
}