{
  "type": "Feature",
  "properties": {
    "gn:admin1_code":"01",
    "gn:asciiname":"Kafr al `Ilw",
    "gn:country_code":"EG",
    "gn:dem":9,
    "gn:feature_class":"P",
    "gn:feature_code":"PPL",
    "gn:name":"Kafr al \u2018Ilw",
    "gn:population":0,
    "gn:timezone":"Africa/Cairo",
    "iso:country":"EG",
    "name:ara_x_preferred":[
        "\u0643\u0641\u0631 \u0627\u0644\u0639\u0644\u0648"
    ],
    "name:und_x_variant":[
        "Kafr el-\u2018Ilw",
        "Kafr al \u2018Ilw",
        "Kafr al-\u2018Ilw"
    ],
    "wof:name":"Kafr al `Ilw",
    "wof:placetype":"locality"
},
  "geometry": {"coordinates":[31.49253,31.09234],"type":"Point"}
}