{
  "type": "Feature",
  "properties": {
    "gn:admin1_code":"01",
    "gn:asciiname":"`Izbat ash Shu`aybah",
    "gn:country_code":"EG",
    "gn:dem":3,
    "gn:feature_class":"P",
    "gn:feature_code":"PPL",
    "gn:name":"\u2018Izbat ash Shu\u2018aybah",
    "gn:population":0,
    "gn:timezone":"Africa/Cairo",
    "iso:country":"EG",
    "name:ara_x_preferred":[
        "\u0639\u0632\u0628\u0629 \u0627\u0644\u0634\u0639\u0628\u0629"
    ],
    "name:und_x_variant":[
        "\u2018Izbat ash Shu\u2018aybah"
    ],
    "wof:name":"`Izbat ash Shu`aybah",
    "wof:placetype":"locality"
},
  "geometry": {"coordinates":[31.68885,30.98241],"type":"Point"}
}