{
  "type": "Feature",
  "properties": {
    "gn:admin1_code":"14",
    "gn:asciiname":"`Izbat al Hajj `Ali",
    "gn:country_code":"EG",
    "gn:dem":5,
    "gn:feature_class":"P",
    "gn:feature_code":"PPL",
    "gn:name":"\u2018Izbat al \u1e28\u0101jj \u2018Al\u012b",
    "gn:population":0,
    "gn:timezone":"Africa/Cairo",
    "iso:country":"EG",
    "name:ara_x_preferred":[
        "\u0639\u0632\u0628\u0629 \u0627\u0644\u062d\u0627\u062c \u0639\u0644\u064a"
    ],
    "name:und_x_variant":[
        "\u2018Izbat al \u1e28\u0101jj \u2018Al\u012b"
    ],
    "wof:name":"`Izbat al Hajj `Ali",
    "wof:placetype":"locality"
},
  "geometry": {"coordinates":[31.72074000000001,30.94735],"type":"Point"}
}