{
  "type": "Feature",
  "properties": {
    "gn:admin1_code":"21",
    "gn:asciiname":"`Izbat al Handaquqah",
    "gn:country_code":"EG",
    "gn:dem":4,
    "gn:feature_class":"P",
    "gn:feature_code":"PPL",
    "gn:name":"\u2018Izbat al \u1e28andaq\u016bqah",
    "gn:population":0,
    "gn:timezone":"Africa/Cairo",
    "iso:country":"EG",
    "name:ara_x_preferred":[
        "\u0639\u0632\u0628\u0629 \u0627\u0644\u062d\u0646\u062f\u0642\u0648\u0642\u0629"
    ],
    "name:und_x_variant":[
        "\u2018Izbat al \u1e28andaq\u016bqah",
        "\u2018Ezbet el-Handaq\u00fbqa"
    ],
    "wof:name":"`Izbat al Handaquqah",
    "wof:placetype":"locality"
},
  "geometry": {"coordinates":[31.18455,31.29361],"type":"Point"}
}