{
  "type": "Feature",
  "properties": {
    "gn:admin1_code":"04",
    "gn:asciiname":"Kahk al Bahriyah",
    "gn:country_code":"EG",
    "gn:dem":-33,
    "gn:feature_class":"P",
    "gn:feature_code":"PPL",
    "gn:name":"Ka\u1e29k al Ba\u1e29r\u012byah",
    "gn:population":0,
    "gn:timezone":"Africa/Cairo",
    "iso:country":"EG",
    "name:und_x_variant":[
        "Kafr \u2018Abd el- \u2018\u00c2l Ka\u1e25k",
        "Ka\u1e29k",
        "Ka\u1e29k al Ba\u1e29r\u012byah"
    ],
    "wof:name":"Kahk al Bahriyah",
    "wof:placetype":"locality"
},
  "geometry": {"coordinates":[30.62993,29.41513],"type":"Point"}
}