{
  "type": "Feature",
  "properties": {
    "gn:admin1_code":"04",
    "gn:asciiname":"`Izbat Hamidah Abu al Hasan",
    "gn:country_code":"EG",
    "gn:dem":24,
    "gn:feature_class":"P",
    "gn:feature_code":"PPL",
    "gn:name":"\u2018Izbat \u1e28am\u012bdah Ab\u016b al \u1e28asan",
    "gn:population":0,
    "gn:timezone":"Africa/Cairo",
    "iso:country":"EG",
    "wof:name":"`Izbat Hamidah Abu al Hasan",
    "wof:placetype":"locality"
},
  "geometry": {"coordinates":[31.07569,29.22622],"type":"Point"}
}