{
  "type": "Feature",
  "properties": {
    "gn:admin1_code":"14",
    "gn:asciiname":"`Izbat az Zawahiri",
    "gn:country_code":"EG",
    "gn:dem":11,
    "gn:feature_class":"P",
    "gn:feature_code":"PPL",
    "gn:name":"\u2018Izbat az\u0327 Z\u0327aw\u0101hir\u012b",
    "gn:population":0,
    "gn:timezone":"Africa/Cairo",
    "iso:country":"EG",
    "name:ara_x_preferred":[
        "\u0639\u0632\u0628\u0629 \u0627\u0644\u0638\u0648\u0627\u0647\u0631\u064a"
    ],
    "name:und_x_variant":[
        "\u2018Izbat az\u0327 Z\u0327aw\u0101hir\u012b",
        "\u2018Izbat az\u0327 Z\u0327aw\u0101hr\u012b"
    ],
    "wof:name":"`Izbat az Zawahiri",
    "wof:placetype":"locality"
},
  "geometry": {"coordinates":[31.6247,30.60423],"type":"Point"}
}