{
  "type": "Feature",
  "properties": {
    "gn:admin1_code":"10",
    "gn:asciiname":"Ban al `Alam",
    "gn:country_code":"EG",
    "gn:dem":31,
    "gn:feature_class":"P",
    "gn:feature_code":"PPL",
    "gn:name":"B\u0101n al \u2018Alam",
    "gn:population":0,
    "gn:timezone":"Africa/Cairo",
    "iso:country":"EG",
    "name:und_x_variant":[
        "B\u00e2n el \u2018Alam",
        "B\u0101n al \u2018Alam"
    ],
    "wof:name":"Ban al `Alam",
    "wof:placetype":"locality"
},
  "geometry": {"coordinates":[30.78639,28.75417],"type":"Point"}
}