{
  "type": "Feature",
  "properties": {
    "gn:admin1_code":"17",
    "gn:asciiname":"Biblaw wa Nazlat Badawi",
    "gn:country_code":"EG",
    "gn:dem":50,
    "gn:feature_class":"P",
    "gn:feature_code":"PPL",
    "gn:name":"Bibl\u0101w wa Nazlat Badaw\u012b",
    "gn:population":0,
    "gn:timezone":"Africa/Cairo",
    "iso:country":"EG",
    "name:und_x_variant":[
        "Bibl\u00e2w and Nazlet Badawi",
        "Biblaw",
        "Bibl\u0101u",
        "Bibl\u0101w wa Nazlat Badaw\u012b"
    ],
    "wof:name":"Biblaw wa Nazlat Badawi",
    "wof:placetype":"locality"
},
  "geometry": {"coordinates":[30.79091,27.53816],"type":"Point"}
}