{
  "type": "Feature",
  "properties": {
    "gn:admin1_code":"09",
    "gn:asciiname":"Al Ghunamiyah",
    "gn:country_code":"EG",
    "gn:dem":20,
    "gn:feature_class":"P",
    "gn:feature_code":"PPL",
    "gn:name":"Al Ghun\u0101m\u012byah",
    "gn:population":0,
    "gn:timezone":"Africa/Cairo",
    "iso:country":"EG",
    "name:ara_x_preferred":[
        "\u0627\u0644\u063a\u0646\u0627\u0645\u064a\u0629"
    ],
    "name:und_x_variant":[
        "El-Ghun\u00e2m\u00eeya",
        "Al Ghun\u0101m\u012byah",
        "Al Ghunn\u0101m\u012byah"
    ],
    "wof:name":"Al Ghunamiyah",
    "wof:placetype":"locality"
},
  "geometry": {"coordinates":[31.01035,30.21445],"type":"Point"}
}