{
  "type": "Feature",
  "properties": {
    "gn:admin1_code":"03",
    "gn:asciiname":"Al Qarawi",
    "gn:country_code":"EG",
    "gn:dem":4,
    "gn:feature_class":"P",
    "gn:feature_code":"PPL",
    "gn:name":"Al Qaraw\u012b",
    "gn:population":0,
    "gn:timezone":"Africa/Cairo",
    "iso:country":"EG",
    "name:ara_x_preferred":[
        "\u0627\u0644\u0642\u0631\u0648\u064a"
    ],
    "name:und_x_variant":[
        "El Qarawi",
        "Al Qaraw\u012b"
    ],
    "wof:name":"Al Qarawi",
    "wof:placetype":"locality"
},
  "geometry": {"coordinates":[30.34755,31.09082],"type":"Point"}
}