{
  "type": "Feature",
  "properties": {
    "gn:admin1_code":"21",
    "gn:asciiname":"Az Zayni",
    "gn:country_code":"EG",
    "gn:dem":3,
    "gn:feature_class":"P",
    "gn:feature_code":"PPL",
    "gn:name":"Az Zayn\u012b",
    "gn:population":0,
    "gn:timezone":"Africa/Cairo",
    "iso:country":"EG",
    "name:ara_x_preferred":[
        "\u0627\u0644\u0632\u064a\u0646\u064a"
    ],
    "name:und_x_variant":[
        "Az Zayn\u012b"
    ],
    "wof:name":"Az Zayni",
    "wof:placetype":"locality"
},
  "geometry": {"coordinates":[30.70353,31.29062],"type":"Point"}
}