{
  "type": "Feature",
  "properties": {
    "gn:admin1_code":"27",
    "gn:asciiname":"Qaryat al Hurriyah",
    "gn:country_code":"EG",
    "gn:dem":4,
    "gn:feature_class":"P",
    "gn:feature_code":"PPL",
    "gn:name":"Qaryat al \u1e28urr\u012byah",
    "gn:population":0,
    "gn:timezone":"Africa/Cairo",
    "iso:country":"EG",
    "name:ara_x_preferred":[
        "\u0642\u0631\u064a\u0629 \u0627\u0644\u062d\u0631\u064a\u0629"
    ],
    "name:und_x_variant":[
        "Qaryat al \u1e28urr\u012byah"
    ],
    "wof:name":"Qaryat al Hurriyah",
    "wof:placetype":"locality"
},
  "geometry": {"coordinates":[33.0796,31.05526],"type":"Point"}
}