{
  "type": "Feature",
  "properties": {
    "gn:admin1_code":"14",
    "gn:asciiname":"Kafr Abu Qawuq",
    "gn:country_code":"EG",
    "gn:dem":14,
    "gn:feature_class":"P",
    "gn:feature_code":"PPL",
    "gn:name":"Kafr Ab\u016b Q\u0101w\u016bq",
    "gn:population":0,
    "gn:timezone":"Africa/Cairo",
    "iso:country":"EG",
    "name:und_x_variant":[
        "Kafr Ab\u016b Q\u0101w\u016bq"
    ],
    "wof:name":"Kafr Abu Qawuq",
    "wof:placetype":"locality"
},
  "geometry": {"coordinates":[31.61639000000001,30.53361],"type":"Point"}
}