{
  "type": "Feature",
  "properties": {
    "gn:admin1_code":"03",
    "gn:asciiname":"As Sawwaf",
    "gn:country_code":"EG",
    "gn:dem":10,
    "gn:feature_class":"P",
    "gn:feature_code":"PPL",
    "gn:name":"A\u015f \u015eaww\u0101f",
    "gn:population":0,
    "gn:timezone":"Africa/Cairo",
    "iso:country":"EG",
    "name:und_x_variant":[
        "El-\u1e62auw\u00e2f",
        "A\u015f \u015eaww\u0101f"
    ],
    "wof:name":"As Sawwaf",
    "wof:placetype":"locality"
},
  "geometry": {"coordinates":[30.77632,30.69023],"type":"Point"}
}