{
  "type": "Feature",
  "properties": {
    "gn:admin1_code":"14",
    "gn:asciiname":"`Izbat Disuqi Abazah",
    "gn:country_code":"EG",
    "gn:dem":11,
    "gn:feature_class":"P",
    "gn:feature_code":"PPL",
    "gn:name":"\u2018Izbat Dis\u016bq\u012b Ab\u0101z\u0327ah",
    "gn:population":0,
    "gn:timezone":"Africa/Cairo",
    "iso:country":"EG",
    "name:ara_x_preferred":[
        "\u0639\u0632\u0628\u0629 \u062f\u0633\u0648\u0642\u064a \u0623\u0644\u0627\u0638\u0629"
    ],
    "name:und_x_variant":[
        "\u2018Izbat Dis\u016bq\u012b Ab\u0101z\u0327ah"
    ],
    "wof:name":"`Izbat Disuqi Abazah",
    "wof:placetype":"locality"
},
  "geometry": {"coordinates":[31.56225,30.51976],"type":"Point"}
}