{
  "type": "Feature",
  "properties": {
    "gn:admin1_code":"09",
    "gn:asciiname":"Kafr Janzur",
    "gn:country_code":"EG",
    "gn:dem":13,
    "gn:feature_class":"P",
    "gn:feature_code":"PPL",
    "gn:name":"Kafr Janz\u016br",
    "gn:population":0,
    "gn:timezone":"Africa/Cairo",
    "iso:country":"EG",
    "name:ara_x_preferred":[
        "\u0643\u0641\u0631 \u062c\u0646\u0632\u0648\u0631"
    ],
    "name:und_x_variant":[
        "Kafr Ganz\u00fbr",
        "Kafr Janz\u016br"
    ],
    "wof:name":"Kafr Janzur",
    "wof:placetype":"locality"
},
  "geometry": {"coordinates":[31.01136,30.66349],"type":"Point"}
}