{
  "type": "Feature",
  "properties": {
    "gn:admin1_code":"14",
    "gn:asciiname":"`Izbat Qummus",
    "gn:country_code":"EG",
    "gn:dem":12,
    "gn:feature_class":"P",
    "gn:feature_code":"PPL",
    "gn:name":"\u2018Izbat Qummu\u015f",
    "gn:population":0,
    "gn:timezone":"Africa/Cairo",
    "iso:country":"EG",
    "name:ara_x_preferred":[
        "\u0639\u0632\u0628\u0629 \u0642\u0645\u0635"
    ],
    "name:und_x_variant":[
        "\u2018Izbat Qummu\u015f"
    ],
    "wof:name":"`Izbat Qummus",
    "wof:placetype":"locality"
},
  "geometry": {"coordinates":[31.42206,30.67538],"type":"Point"}
}