{
  "type": "Feature",
  "properties": {
    "gn:admin1_code":"04",
    "gn:asciiname":"Aslan",
    "gn:cc2":"EG",
    "gn:country_code":"EG",
    "gn:dem":0,
    "gn:feature_class":"P",
    "gn:feature_code":"PPL",
    "gn:name":"A\u015fl\u0101n",
    "gn:population":0,
    "gn:timezone":"Africa/Cairo",
    "iso:country":"EG",
    "name:bel_x_preferred":[
        "\u0410\u0441\u043b\u0430\u043d"
    ],
    "name:bre_x_preferred":[
        "Aslan"
    ],
    "name:bul_x_preferred":[
        "\u0410\u0441\u043b\u0430\u043d"
    ],
    "name:ces_x_preferred":[
        "Aslan"
    ],
    "name:dan_x_preferred":[
        "Aslan"
    ],
    "name:deu_x_preferred":[
        "Aslan"
    ],
    "name:fas_x_preferred":[
        "\u0627\u0635\u0644\u0627\u0646"
    ],
    "name:fin_x_preferred":[
        "Aslan"
    ],
    "name:fra_x_preferred":[
        "Aslan"
    ],
    "name:glg_x_preferred":[
        "Aslan"
    ],
    "name:ind_x_preferred":[
        "Aslan"
    ],
    "name:ita_x_preferred":[
        "Aslan"
    ],
    "name:jpn_x_preferred":[
        "\u30a2\u30b9\u30e9\u30f3"
    ],
    "name:kor_x_preferred":[
        "\uc544\uc2ac\ub780"
    ],
    "name:lat_x_preferred":[
        "Aslan"
    ],
    "name:nld_x_preferred":[
        "Aslan"
    ],
    "name:nor_x_preferred":[
        "Aslan"
    ],
    "name:pol_x_preferred":[
        "Aslan"
    ],
    "name:por_x_preferred":[
        "Aslam"
    ],
    "name:rus_x_preferred":[
        "\u0410\u0441\u043b\u0430\u043d"
    ],
    "name:scn_x_preferred":[
        "Aslan"
    ],
    "name:tha_x_preferred":[
        "\u0e2d\u0e31\u0e2a\u0e25\u0e32\u0e19"
    ],
    "name:und_x_variant":[
        "\u2018Izbat Sharl Z\u012bjd\u016bn",
        "\u2018Ezbet Charles Zagdoun",
        "A\u015fl\u0101n"
    ],
    "name:uzb_x_preferred":[
        "Aslan"
    ],
    "wof:name":"Aslan",
    "wof:placetype":"locality"
},
  "geometry": {"coordinates":[31.04417,29.48028],"type":"Point"}
}