{
  "type": "Feature",
  "properties": {
    "gn:admin1_code":"04",
    "gn:asciiname":"Aslan",
    "gn:cc2":"EG",
    "gn:country_code":"EG",
    "gn:dem":0,
    "gn:feature_class":"P",
    "gn:feature_code":"PPL",
    "gn:name":"A\u015fl\u0101n",
    "gn:population":0,
    "gn:timezone":"Africa/Cairo",
    "iso:country":"EG",
    "name:und_x_variant":[
        "\u2018Izbat Sharl Z\u012bjd\u016bn",
        "\u2018Ezbet Charles Zagdoun",
        "A\u015fl\u0101n"
    ],
    "wof:name":"Aslan",
    "wof:placetype":"locality"
},
  "geometry": {"coordinates":[31.04417,29.48028],"type":"Point"}
}