{
  "type": "Feature",
  "properties": {
    "gn:admin1_code":"14",
    "gn:asciiname":"Qaryat al Ghar",
    "gn:country_code":"EG",
    "gn:dem":13,
    "gn:feature_class":"P",
    "gn:feature_code":"PPL",
    "gn:name":"Qaryat al Gh\u0101r",
    "gn:population":0,
    "gn:timezone":"Africa/Cairo",
    "iso:country":"EG",
    "name:ara_x_preferred":[
        "\u0642\u0631\u064a\u0629 \u0627\u0644\u063a\u0627\u0631"
    ],
    "name:und_x_variant":[
        "El-Gh\u00e2r",
        "Al Gh\u0101r",
        "Qaryat al Gh\u0101r"
    ],
    "wof:name":"Qaryat al Ghar",
    "wof:placetype":"locality"
},
  "geometry": {"coordinates":[31.53832,30.55851],"type":"Point"}
}