{
  "type": "Feature",
  "properties": {
    "gn:admin1_code":"03",
    "gn:asciiname":"Naj` al Aswad",
    "gn:country_code":"EG",
    "gn:dem":-14,
    "gn:feature_class":"P",
    "gn:feature_code":"PPL",
    "gn:name":"Naj\u2018 al Aswad",
    "gn:population":0,
    "gn:timezone":"Africa/Cairo",
    "iso:country":"EG",
    "name:ara_x_preferred":[
        "\u0646\u062c\u0639 \u0627\u0644\u0623\u0633\u0648\u062f"
    ],
    "name:und_x_variant":[
        "Naj\u2018 al Aswad"
    ],
    "wof:name":"Naj` al Aswad",
    "wof:placetype":"locality"
},
  "geometry": {"coordinates":[30.13027,30.48346],"type":"Point"}
}