{
  "type": "Feature",
  "properties": {
    "gn:admin1_code":"03",
    "gn:asciiname":"Khalwat at Tarranah",
    "gn:cc2":"EG",
    "gn:country_code":"EG",
    "gn:dem":11,
    "gn:feature_class":"P",
    "gn:feature_code":"PPL",
    "gn:name":"Khalwat a\u0163 \u0162arr\u0101nah",
    "gn:population":0,
    "gn:timezone":"Africa/Cairo",
    "iso:country":"EG",
    "name:und_x_variant":[
        "Khilwet el-\u1e6carr\u00e2na",
        "Khalwat a\u0163 \u0162arr\u0101nah"
    ],
    "wof:name":"Khalwat at Tarranah",
    "wof:placetype":"locality"
},
  "geometry": {"coordinates":[30.83333,30.43333],"type":"Point"}
}