{
  "type": "Feature",
  "properties": {
    "gn:admin1_code":"09",
    "gn:asciiname":"Mahallat Subk",
    "gn:country_code":"EG",
    "gn:dem":16,
    "gn:feature_class":"P",
    "gn:feature_code":"PPL",
    "gn:name":"Ma\u1e29allat Subk",
    "gn:population":0,
    "gn:timezone":"Africa/Cairo",
    "iso:country":"EG",
    "name:ara_x_preferred":[
        "\u0645\u062d\u0644\u0629 \u0633\u0628\u0643"
    ],
    "name:und_x_variant":[
        "Ma\u1e29allat Subk wa Minsh\u0101t Na\u015fr",
        "Ma\u1e25allet Subkt wa Minsh\u00e2t Na\u1e63r",
        "Ma\u1e29allat Subk",
        "Ma\u1e29allit Subk"
    ],
    "wof:name":"Mahallat Subk",
    "wof:placetype":"locality"
},
  "geometry": {"coordinates":[31.01593,30.2879],"type":"Point"}
}