{
  "type": "Feature",
  "properties": {
    "gn:admin1_code":"01",
    "gn:asciiname":"`Izbat al Jummayzah",
    "gn:country_code":"EG",
    "gn:dem":11,
    "gn:feature_class":"P",
    "gn:feature_code":"PPL",
    "gn:name":"\u2018Izbat al Jummayzah",
    "gn:population":0,
    "gn:timezone":"Africa/Cairo",
    "iso:country":"EG",
    "name:ara_x_preferred":[
        "\u0639\u0632\u0628\u0629 \u0627\u0644\u062c\u0645\u064a\u0632\u0629"
    ],
    "name:und_x_variant":[
        "Gimmeizet Bilg\u00e2i",
        "Jummayzat Bilj\u0101y",
        "\u2018Izbat al Jimmayzah",
        "\u2018Izbat al Jummayzah",
        "\u2018Iz. al-Jimmayzah"
    ],
    "wof:name":"`Izbat al Jummayzah",
    "wof:placetype":"locality"
},
  "geometry": {"coordinates":[31.38893,30.97106],"type":"Point"}
}