{
  "type": "Feature",
  "properties": {
    "gn:admin1_code":"10.0",
    "gn:asciiname":"Tandah",
    "gn:country_code":"EG",
    "gn:dem":44,
    "gn:feature_class":"P",
    "gn:feature_code":"PPL",
    "gn:name":"Tandah",
    "gn:population":0,
    "gn:timezone":"Africa/Cairo",
    "iso:country":"EG",
    "name:und_x_variant":[
        "Tanda",
        "Tandah"
    ],
    "wof:name":"Tandah",
    "wof:placetype":"locality"
},
  "geometry": {"coordinates":[30.78548,27.6906],"type":"Point"}
}