{
  "type": "Feature",
  "properties": {
    "gn:admin1_code":"14",
    "gn:asciiname":"Kafr Bani `Alim",
    "gn:country_code":"EG",
    "gn:dem":15,
    "gn:feature_class":"P",
    "gn:feature_code":"PPL",
    "gn:name":"Kafr Ban\u012b \u2018Al\u012bm",
    "gn:population":0,
    "gn:timezone":"Africa/Cairo",
    "iso:country":"EG",
    "name:ara_x_preferred":[
        "\u0643\u0641\u0631 \u0628\u0646\u064a \u0639\u0644\u064a\u0645"
    ],
    "name:und_x_variant":[
        "Ban\u012b \u2018Ulaym",
        "Beni \u2018Ileim",
        "Kafr Ban\u012b \u2018Al\u012bm"
    ],
    "wof:name":"Kafr Bani `Alim",
    "wof:placetype":"locality"
},
  "geometry": {"coordinates":[31.59368,30.46227],"type":"Point"}
}