{
  "type": "Feature",
  "properties": {
    "gn:admin1_code":"10.0",
    "gn:asciiname":"Tukh al Khayl",
    "gn:country_code":"EG",
    "gn:dem":44,
    "gn:feature_class":"P",
    "gn:feature_code":"PPL",
    "gn:name":"\u0162\u016bkh al Khayl",
    "gn:population":0,
    "gn:timezone":"Africa/Cairo",
    "iso:country":"EG",
    "name:und_x_variant":[
        "T\u00fbkh el Kheil",
        "\u0162\u016bkh al Khayl"
    ],
    "wof:name":"Tukh al Khayl",
    "wof:placetype":"locality"
},
  "geometry": {"coordinates":[30.66994,28.10572],"type":"Point"}
}