{
  "type": "Feature",
  "properties": {
    "gn:admin1_code":"14",
    "gn:asciiname":"`Izbat al `Abbasi",
    "gn:country_code":"EG",
    "gn:dem":7,
    "gn:feature_class":"P",
    "gn:feature_code":"PPL",
    "gn:name":"\u2018Izbat al \u2018Abb\u0101s\u012b",
    "gn:population":0,
    "gn:timezone":"Africa/Cairo",
    "iso:country":"EG",
    "name:ara_x_preferred":[
        "\u0639\u0632\u0628\u0629 \u0627\u0644\u0639\u0628\u0627\u0633\u064a"
    ],
    "name:und_x_variant":[
        "\u2018Izbat al \u2018Abb\u0101s\u012b"
    ],
    "wof:name":"`Izbat al `Abbasi",
    "wof:placetype":"locality"
},
  "geometry": {"coordinates":[31.73535,30.71808],"type":"Point"}
}