{
  "type": "Feature",
  "properties": {
    "gn:admin1_code":"05",
    "gn:asciiname":"Shishta",
    "gn:country_code":"EG",
    "gn:dem":11,
    "gn:feature_class":"P",
    "gn:feature_code":"PPL",
    "gn:name":"Shisht\u0101",
    "gn:population":0,
    "gn:timezone":"Africa/Cairo",
    "iso:country":"EG",
    "name:ara_x_preferred":[
        "\u0634\u0634\u062a\u0627"
    ],
    "name:und_x_variant":[
        "Shisht\u0101"
    ],
    "wof:name":"Shishta",
    "wof:placetype":"locality"
},
  "geometry": {"coordinates":[31.16142,30.85728],"type":"Point"}
}