{
  "type": "Feature",
  "properties": {
    "gn:admin1_code":"10",
    "gn:asciiname":"Dirwah",
    "gn:country_code":"EG",
    "gn:dem":47,
    "gn:feature_class":"P",
    "gn:feature_code":"PPL",
    "gn:name":"Dirwah",
    "gn:population":0,
    "gn:timezone":"Africa/Cairo",
    "iso:country":"EG",
    "name:und_x_variant":[
        "Dirwa",
        "Dirwah"
    ],
    "wof:name":"Dirwah",
    "wof:placetype":"locality"
},
  "geometry": {"coordinates":[30.74486,27.72366],"type":"Point"}
}