{
  "type": "Feature",
  "properties": {
    "gn:admin1_code":"10.0",
    "gn:asciiname":"Tanuf",
    "gn:country_code":"EG",
    "gn:dem":52,
    "gn:feature_class":"P",
    "gn:feature_code":"PPL",
    "gn:name":"T\u0101n\u016bf",
    "gn:population":0,
    "gn:timezone":"Africa/Cairo",
    "iso:country":"EG",
    "wof:name":"Tanuf",
    "wof:placetype":"locality"
},
  "geometry": {"coordinates":[30.82482000000001,27.64053],"type":"Point"}
}