{
  "type": "Feature",
  "properties": {
    "gn:admin1_code":"14.0",
    "gn:asciiname":"As Sunaytah",
    "gn:country_code":"EG",
    "gn:dem":12,
    "gn:feature_class":"P",
    "gn:feature_code":"PPL",
    "gn:name":"As Sunay\u0163ah",
    "gn:population":0,
    "gn:timezone":"Africa/Cairo",
    "iso:country":"EG",
    "name:und_x_variant":[
        "Sineitet el-Rif\u00e2\u2018\u00eeyin",
        "Kafr el Sine\u00eeta",
        "Sunay\u0163at ar Rif\u0101\u2018\u012by\u012bn",
        "As Sunay\u0163ah"
    ],
    "wof:name":"As Sunaytah",
    "wof:placetype":"locality"
},
  "geometry": {"coordinates":[31.79852,30.81839],"type":"Point"}
}