{
  "type": "Feature",
  "properties": {
    "gn:admin1_code":"01",
    "gn:asciiname":"Kafr ash Shinnawi",
    "gn:country_code":"EG",
    "gn:dem":10,
    "gn:feature_class":"P",
    "gn:feature_code":"PPL",
    "gn:name":"Kafr ash Shinn\u0101w\u012b",
    "gn:population":0,
    "gn:timezone":"Africa/Cairo",
    "iso:country":"EG",
    "name:ara_x_preferred":[
        "\u0643\u0641\u0631 \u0627\u0644\u0634\u0646\u0627\u0648\u064a"
    ],
    "name:und_x_variant":[
        "Kafr ash Shinn\u0101w",
        "Kafr ash Shinn\u0101w\u012b",
        "Kafr ash-Shinn\u0101w\u012b"
    ],
    "wof:name":"Kafr ash Shinnawi",
    "wof:placetype":"locality"
},
  "geometry": {"coordinates":[31.50024,30.88627],"type":"Point"}
}