{
  "type": "Feature",
  "properties": {
    "gn:admin1_code":"23",
    "gn:asciiname":"El-Ausat Qamula",
    "gn:country_code":"EG",
    "gn:dem":76,
    "gn:feature_class":"P",
    "gn:feature_code":"PPL",
    "gn:name":"El-Ausat Qam\u00fbla",
    "gn:population":0,
    "gn:timezone":"Africa/Cairo",
    "iso:country":"EG",
    "wof:name":"El-Ausat Qamula",
    "wof:placetype":"locality"
},
  "geometry": {"coordinates":[32.73333,25.81667],"type":"Point"}
}