{
  "type": "Feature",
  "properties": {
    "gn:admin1_code":"07",
    "gn:asciiname":"`Izbat Mahattat Abu Suwayr",
    "gn:country_code":"EG",
    "gn:dem":15,
    "gn:feature_class":"P",
    "gn:feature_code":"PPL",
    "gn:name":"\u2018Izbat Ma\u1e29a\u0163\u0163at Ab\u016b \u015euwayr",
    "gn:population":0,
    "gn:timezone":"Africa/Cairo",
    "iso:country":"EG",
    "name:und_x_variant":[
        "\u2018Ezbet Ma\u1e25ot\u1e6dot",
        "\u2018Ezbet Ma\u1e25a\u1e6d\u1e6dot Abu \u1e62uweir",
        "\u2018Izbat Ma\u1e29a\u0163\u0163at Ab\u016b \u015euwayr"
    ],
    "wof:name":"`Izbat Mahattat Abu Suwayr",
    "wof:placetype":"locality"
},
  "geometry": {"coordinates":[32.11667,30.56667],"type":"Point"}
}