{
  "type": "Feature",
  "properties": {
    "gn:admin1_code":"09",
    "gn:asciiname":"Kafr Bani Ghiryan",
    "gn:country_code":"EG",
    "gn:dem":12,
    "gn:feature_class":"P",
    "gn:feature_code":"PPL",
    "gn:name":"Kafr Ban\u012b Ghiry\u0101n",
    "gn:population":0,
    "gn:timezone":"Africa/Cairo",
    "iso:country":"EG",
    "name:ara_x_preferred":[
        "\u0643\u0641\u0631 \u0628\u0646\u064a \u063a\u0631\u064a\u0627\u0646"
    ],
    "name:und_x_variant":[
        "Kafr Beni Ghiry\u00e2n",
        "Kafr Ban\u012b Ghiry\u0101n"
    ],
    "wof:name":"Kafr Bani Ghiryan",
    "wof:placetype":"locality"
},
  "geometry": {"coordinates":[31.18681,30.62406],"type":"Point"}
}