{
  "type": "Feature",
  "properties": {
    "gn:admin1_code":"06",
    "gn:asciiname":"Dawwar Ruhayyim",
    "gn:country_code":"EG",
    "gn:dem":32,
    "gn:feature_class":"P",
    "gn:feature_code":"PPL",
    "gn:name":"Daww\u0101r Ru\u1e29ayyim",
    "gn:population":0,
    "gn:timezone":"Africa/Cairo",
    "iso:country":"EG",
    "name:und_x_variant":[
        "Dauw\u00e2r Ru\u1e25aiyim",
        "Daww\u0101r Ru\u1e29ayyim"
    ],
    "wof:name":"Dawwar Ruhayyim",
    "wof:placetype":"locality"
},
  "geometry": {"coordinates":[29.74714,30.88721],"type":"Point"}
}