{
  "type": "Feature",
  "properties": {
    "gn:admin1_code":"03",
    "gn:asciiname":"`Izbat Hidayah",
    "gn:country_code":"EG",
    "gn:dem":2,
    "gn:feature_class":"P",
    "gn:feature_code":"PPL",
    "gn:name":"\u2018Izbat \u1e28id\u0101yah",
    "gn:population":0,
    "gn:timezone":"Africa/Cairo",
    "iso:country":"EG",
    "name:ara_x_preferred":[
        "\u0639\u0632\u0628\u0629 \u062d\u062f\u0627\u064a\u0629"
    ],
    "name:und_x_variant":[
        "\u2018Izbat \u1e28id\u0101yah",
        "\u2018Izbat \u1e24idd\u0101yah"
    ],
    "wof:name":"`Izbat Hidayah",
    "wof:placetype":"locality"
},
  "geometry": {"coordinates":[30.47886,31.11363],"type":"Point"}
}