{
  "type": "Feature",
  "properties": {
    "gn:admin1_code":"17",
    "gn:asciiname":"Nazlat al Maghribi",
    "gn:cc2":"EG",
    "gn:country_code":"EG",
    "gn:dem":59,
    "gn:feature_class":"P",
    "gn:feature_code":"PPL",
    "gn:name":"Nazlat al Maghrib\u012b",
    "gn:population":0,
    "gn:timezone":"Africa/Cairo",
    "iso:country":"EG",
    "name:und_x_variant":[
        "Nazlet el Mughrebi",
        "Nazlat al Maghrib\u012b"
    ],
    "wof:name":"Nazlat al Maghribi",
    "wof:placetype":"locality"
},
  "geometry": {"coordinates":[31.41667,26.95],"type":"Point"}
}