{
  "type": "Feature",
  "properties": {
    "gn:admin1_code":"12",
    "gn:asciiname":"`Izbat Ash Shaykh As Saghir",
    "gn:country_code":"EG",
    "gn:dem":19,
    "gn:feature_class":"P",
    "gn:feature_code":"PPL",
    "gn:name":"\u2018Izbat Ash Shaykh A\u015f \u015eagh\u012br",
    "gn:population":0,
    "gn:timezone":"Africa/Cairo",
    "iso:country":"EG",
    "name:ara_x_preferred":[
        "\u0639\u0632\u0628\u0629 \u0627\u0644\u0634\u064a\u062e \u0627\u0644\u0635\u063a\u064a\u0631"
    ],
    "name:und_x_variant":[
        "\u2018Izbat Ash Shaykh A\u015f \u015eagh\u012br"
    ],
    "wof:name":"`Izbat Ash Shaykh As Saghir",
    "wof:placetype":"locality"
},
  "geometry": {"coordinates":[31.13075,30.28516],"type":"Point"}
}