{
  "type": "Feature",
  "properties": {
    "gn:admin1_code":"09",
    "gn:asciiname":"`Arab Abu Dhakri",
    "gn:country_code":"EG",
    "gn:dem":16,
    "gn:feature_class":"P",
    "gn:feature_code":"PPL",
    "gn:name":"\u2018Arab Ab\u016b Dhakr\u012b",
    "gn:population":0,
    "gn:timezone":"Africa/Cairo",
    "iso:country":"EG",
    "name:ara_x_preferred":[
        "\u0639\u0631\u0628 \u0623\u0628\u0648 \u0630\u0643\u0631\u064a"
    ],
    "name:und_x_variant":[
        "\u2018Arab Ab\u016b Dhakr\u012b"
    ],
    "wof:name":"`Arab Abu Dhakri",
    "wof:placetype":"locality"
},
  "geometry": {"coordinates":[31.18527000000001,30.52821],"type":"Point"}
}