{
  "type": "Feature",
  "properties": {
    "gn:admin1_code":"14",
    "gn:asciiname":"Ad Dahashinah",
    "gn:country_code":"EG",
    "gn:dem":12,
    "gn:feature_class":"P",
    "gn:feature_code":"PPL",
    "gn:name":"Ad Dah\u0101shinah",
    "gn:population":0,
    "gn:timezone":"Africa/Cairo",
    "iso:country":"EG",
    "name:ara_x_preferred":[
        "\u0627\u0644\u062f\u0647\u0627\u0634\u0646\u0629"
    ],
    "name:und_x_variant":[
        "El Dahashna",
        "Ad Dah\u0101shinah",
        "Ad Dah\u0101shnah"
    ],
    "wof:name":"Ad Dahashinah",
    "wof:placetype":"locality"
},
  "geometry": {"coordinates":[31.56392,30.48225],"type":"Point"}
}