{
  "type": "Feature",
  "properties": {
    "gn:admin1_code":"05",
    "gn:asciiname":"Burayk al Hajar",
    "gn:country_code":"EG",
    "gn:dem":10,
    "gn:feature_class":"P",
    "gn:feature_code":"PPL",
    "gn:name":"Burayk al \u1e28ajar",
    "gn:population":0,
    "gn:timezone":"Africa/Cairo",
    "iso:country":"EG",
    "name:und_x_variant":[
        "Bureik el-\u1e24agar",
        "Burayk al \u1e28ajar"
    ],
    "wof:name":"Burayk al Hajar",
    "wof:placetype":"locality"
},
  "geometry": {"coordinates":[30.99076,30.87378],"type":"Point"}
}