{
  "type": "Feature",
  "properties": {
    "gn:admin1_code":"03",
    "gn:asciiname":"Manshiyat Salih",
    "gn:country_code":"EG",
    "gn:dem":3,
    "gn:feature_class":"P",
    "gn:feature_code":"PPL",
    "gn:name":"Mansh\u012byat \u015e\u0101li\u1e29",
    "gn:population":0,
    "gn:timezone":"Africa/Cairo",
    "iso:country":"EG",
    "name:ara_x_preferred":[
        "\u0645\u0646\u0634\u064a\u0629 \u0635\u0627\u0644\u062d"
    ],
    "name:und_x_variant":[
        "Mansh\u012byat \u015e\u0101li\u1e29",
        "Manshiyyat \u1e62\u0101li\u1e25"
    ],
    "wof:name":"Manshiyat Salih",
    "wof:placetype":"locality"
},
  "geometry": {"coordinates":[30.40969,31.02147],"type":"Point"}
}