{
  "type": "Feature",
  "properties": {
    "gn:admin1_code":"11",
    "gn:asciiname":"`Arab ash Shaykh Zayid",
    "gn:country_code":"EG",
    "gn:dem":32,
    "gn:feature_class":"P",
    "gn:feature_code":"PPL",
    "gn:name":"\u2018Arab ash Shaykh Z\u0101yid",
    "gn:population":0,
    "gn:timezone":"Africa/Cairo",
    "iso:country":"EG",
    "name:und_x_variant":[
        "\u2018Izbat ash Shaykh Zayd",
        "\u2018Arab el-Sheikh Zeid",
        "\u2018Arab ash Shaykh Zayd",
        "\u2018Arab ash Shaykh Z\u0101yid"
    ],
    "wof:name":"`Arab ash Shaykh Zayid",
    "wof:placetype":"locality"
},
  "geometry": {"coordinates":[31.29248,29.5311],"type":"Point"}
}