{
  "type": "Feature",
  "properties": {
    "gn:admin1_code":"18",
    "gn:asciiname":"Kafr Jum`ah",
    "gn:country_code":"EG",
    "gn:dem":32,
    "gn:feature_class":"P",
    "gn:feature_code":"PPL",
    "gn:name":"Kafr Jum\u2018ah",
    "gn:population":0,
    "gn:timezone":"Africa/Cairo",
    "iso:country":"EG",
    "name:und_x_variant":[
        "Kafr Gum\u2018a",
        "Kafr Jum\u2018ah"
    ],
    "wof:name":"Kafr Jum`ah",
    "wof:placetype":"locality"
},
  "geometry": {"coordinates":[30.94816,28.90397],"type":"Point"}
}