{
  "type": "Feature",
  "properties": {
    "gn:admin1_code":"21",
    "gn:asciiname":"`Izbat Bahri",
    "gn:country_code":"EG",
    "gn:dem":2,
    "gn:feature_class":"P",
    "gn:feature_code":"PPL",
    "gn:name":"\u2018Izbat Ba\u1e29r\u012b",
    "gn:population":0,
    "gn:timezone":"Africa/Cairo",
    "iso:country":"EG",
    "name:ara_x_preferred":[
        "\u0639\u0632\u0628\u0629 \u0628\u062d\u0631\u064a"
    ],
    "name:und_x_variant":[
        "\u2018Izbat Ba\u1e29r\u012b",
        "\u2018Iz. Ba\u1e25ar\u012b"
    ],
    "wof:name":"`Izbat Bahri",
    "wof:placetype":"locality"
},
  "geometry": {"coordinates":[31.14808,31.50138],"type":"Point"}
}