{
  "type": "Feature",
  "properties": {
    "gn:admin1_code":"03",
    "gn:asciiname":"`Izbat Qandil",
    "gn:country_code":"EG",
    "gn:dem":2,
    "gn:feature_class":"P",
    "gn:feature_code":"PPL",
    "gn:name":"\u2018Izbat Qand\u012bl",
    "gn:population":0,
    "gn:timezone":"Africa/Cairo",
    "iso:country":"EG",
    "name:ara_x_preferred":[
        "\u0639\u0632\u0628\u0629 \u0642\u0646\u062f\u064a\u0644"
    ],
    "name:und_x_variant":[
        "\u2018Izbat Qand\u012bl"
    ],
    "wof:name":"`Izbat Qandil",
    "wof:placetype":"locality"
},
  "geometry": {"coordinates":[30.28637,31.10034000000001],"type":"Point"}
}