{
  "type": "Feature",
  "properties": {
    "gn:admin1_code":"21",
    "gn:asciiname":"`Izbat Salih",
    "gn:country_code":"EG",
    "gn:dem":4,
    "gn:feature_class":"P",
    "gn:feature_code":"PPL",
    "gn:name":"\u2018Izbat S\u0101li\u1e29",
    "gn:population":0,
    "gn:timezone":"Africa/Cairo",
    "iso:country":"EG",
    "name:ara_x_preferred":[
        "\u0639\u0632\u0628\u0629 \u0635\u0627\u0644\u062d"
    ],
    "name:und_x_variant":[
        "\u2018Izbat S\u0101li\u1e29"
    ],
    "wof:name":"`Izbat Salih",
    "wof:placetype":"locality"
},
  "geometry": {"coordinates":[31.1642,31.26981],"type":"Point"}
}