{
  "type": "Feature",
  "properties": {
    "gn:admin1_code":"18",
    "gn:asciiname":"`Izbat al Fant",
    "gn:country_code":"EG",
    "gn:dem":30,
    "gn:feature_class":"P",
    "gn:feature_code":"PPL",
    "gn:name":"\u2018Izbat al Fant",
    "gn:population":0,
    "gn:timezone":"Africa/Cairo",
    "iso:country":"EG",
    "name:und_x_variant":[
        "\u2018Ezbet el-Fant",
        "\u2018Izbat al Fant"
    ],
    "wof:name":"`Izbat al Fant",
    "wof:placetype":"locality"
},
  "geometry": {"coordinates":[30.87223,28.7849],"type":"Point"}
}