{
  "type": "Feature",
  "properties": {
    "gn:admin1_code":"05",
    "gn:asciiname":"Kafr al Jibaliyah",
    "gn:country_code":"EG",
    "gn:dem":13,
    "gn:feature_class":"P",
    "gn:feature_code":"PPL",
    "gn:name":"Kafr al Jib\u0101l\u012byah",
    "gn:population":0,
    "gn:timezone":"Africa/Cairo",
    "iso:country":"EG",
    "name:ara_x_preferred":[
        "\u0643\u0641\u0631 \u0627\u0644\u062c\u0628\u0627\u0644\u064a\u0629"
    ],
    "name:und_x_variant":[
        "Kafr el-Gibaliya",
        "Kafr el-Geb\u00e2l\u00eeya",
        "Kafr al Jib\u0101l\u012byah",
        "Kafr al-Jib\u0101liyyah"
    ],
    "wof:name":"Kafr al Jibaliyah",
    "wof:placetype":"locality"
},
  "geometry": {"coordinates":[30.92582,30.77613],"type":"Point"}
}