{
  "type": "Feature",
  "properties": {
    "gn:admin1_code":"14",
    "gn:asciiname":"`Ezbet Ibrahim Bey",
    "gn:country_code":"EG",
    "gn:dem":9,
    "gn:feature_class":"P",
    "gn:feature_code":"PPL",
    "gn:name":"\u2018Ezbet Ibr\u00e2h\u00eem Bey",
    "gn:population":0,
    "gn:timezone":"Africa/Cairo",
    "iso:country":"EG",
    "wof:name":"`Ezbet Ibrahim Bey",
    "wof:placetype":"locality"
},
  "geometry": {"coordinates":[31.60556,30.60222000000001],"type":"Point"}
}