{
  "type": "Feature",
  "properties": {
    "gn:asciiname":"Maqhaka",
    "gn:country_code":"EG",
    "gn:dem":1625,
    "gn:feature_class":"P",
    "gn:feature_code":"PPL",
    "gn:name":"Maqhaka",
    "gn:population":0,
    "gn:timezone":"Africa/Maseru",
    "iso:country":"EG",
    "wof:name":"Maqhaka",
    "wof:placetype":"locality"
},
  "geometry": {"coordinates":[27.60833,-29.24722],"type":"Point"}
}