{
  "type": "Feature",
  "properties": {
    "gn:admin1_code":"24",
    "gn:asciiname":"Naj` al Ahaywah",
    "gn:country_code":"EG",
    "gn:dem":66,
    "gn:feature_class":"P",
    "gn:feature_code":"PPL",
    "gn:name":"Naj\u2018 al A\u1e29\u0101ywah",
    "gn:population":0,
    "gn:timezone":"Africa/Cairo",
    "iso:country":"EG",
    "name:und_x_variant":[
        "Nag\u2019 el-Ah\u00e2ywa",
        "Naj\u2018 al A\u1e29\u0101ywah"
    ],
    "wof:name":"Naj` al Ahaywah",
    "wof:placetype":"locality"
},
  "geometry": {"coordinates":[31.82785,26.44444],"type":"Point"}
}