{
  "type": "Feature",
  "properties": {
    "gn:admin1_code":"09",
    "gn:asciiname":"Shubra Zinji",
    "gn:country_code":"EG",
    "gn:dem":13,
    "gn:feature_class":"P",
    "gn:feature_code":"PPL",
    "gn:name":"Shubr\u0101 Zinj\u012b",
    "gn:population":0,
    "gn:timezone":"Africa/Cairo",
    "iso:country":"EG",
    "name:ara_x_preferred":[
        "Shubr\u0101 Zinj\u012b"
    ],
    "name:ara_x_variant":[
        "\u0634\u0628\u0631\u0627 \u0632\u0646\u062c\u064a"
    ],
    "name:und_x_variant":[
        "Shubra Zangi"
    ],
    "wof:name":"Shubra Zinji",
    "wof:placetype":"locality"
},
  "geometry": {"coordinates":[31.00136,30.45754],"type":"Point"}
}