{
  "type": "Feature",
  "properties": {
    "gn:admin1_code":"21",
    "gn:asciiname":"Minyat Qillin",
    "gn:country_code":"EG",
    "gn:dem":9,
    "gn:feature_class":"P",
    "gn:feature_code":"PPL",
    "gn:name":"Minyat Qill\u012bn",
    "gn:population":0,
    "gn:timezone":"Africa/Cairo",
    "iso:country":"EG",
    "name:ara_x_preferred":[
        "\u0645\u0646\u064a\u0629 \u0642\u0644\u064a\u0646"
    ],
    "name:und_x_variant":[
        "Minyet Qall\u00een",
        "Minyat Qall\u012bn",
        "Minyat Qill\u012bn"
    ],
    "wof:name":"Minyat Qillin",
    "wof:placetype":"locality"
},
  "geometry": {"coordinates":[30.80861,31.0458],"type":"Point"}
}