{
  "type": "Feature",
  "properties": {
    "gn:admin1_code":"14",
    "gn:asciiname":"Kafr Abu Tariyah",
    "gn:country_code":"EG",
    "gn:dem":7,
    "gn:feature_class":"P",
    "gn:feature_code":"PPL",
    "gn:name":"Kafr Ab\u016b \u0162ar\u012byah",
    "gn:population":0,
    "gn:timezone":"Africa/Cairo",
    "iso:country":"EG",
    "wof:name":"Kafr Abu Tariyah",
    "wof:placetype":"locality"
},
  "geometry": {"coordinates":[31.52889,30.79778],"type":"Point"}
}