{
  "type": "Feature",
  "properties": {
    "gn:admin1_code":"09",
    "gn:asciiname":"Nadir",
    "gn:cc2":"EG",
    "gn:country_code":"EG",
    "gn:dem":10,
    "gn:feature_class":"P",
    "gn:feature_code":"PPL",
    "gn:name":"N\u0101dir",
    "gn:population":0,
    "gn:timezone":"Africa/Cairo",
    "iso:country":"EG",
    "name:und_x_variant":[
        "N\u00e2dir",
        "N\u0101dir"
    ],
    "wof:name":"Nadir",
    "wof:placetype":"locality"
},
  "geometry": {"coordinates":[30.85,30.55],"type":"Point"}
}