{
  "type": "Feature",
  "properties": {
    "gn:admin1_code":"10",
    "gn:asciiname":"`Ezbet Hanna",
    "gn:country_code":"EG",
    "gn:dem":36,
    "gn:feature_class":"P",
    "gn:feature_code":"PPL",
    "gn:name":"\u2018Ezbet \u1e24anna",
    "gn:population":0,
    "gn:timezone":"Africa/Cairo",
    "iso:country":"EG",
    "wof:name":"`Ezbet Hanna",
    "wof:placetype":"locality"
},
  "geometry": {"coordinates":[30.66667,28.11667000000001],"type":"Point"}
}