{
  "type": "Feature",
  "properties": {
    "gn:admin1_code":"15",
    "gn:asciiname":"Muhammad Ahmad Bakin",
    "gn:country_code":"EG",
    "gn:dem":11,
    "gn:feature_class":"P",
    "gn:feature_code":"PPL",
    "gn:name":"Mu\u1e29ammad A\u1e29mad B\u0101k\u012bn",
    "gn:population":0,
    "gn:timezone":"Africa/Cairo",
    "iso:country":"EG",
    "name:und_x_variant":[
        "Mu\u1e29ammad A\u1e29mad B\u0101k\u012bn",
        "Mu\u1e25ammad A\u1e25mad Baak\u00een"
    ],
    "wof:name":"Muhammad Ahmad Bakin",
    "wof:placetype":"locality"
},
  "geometry": {"coordinates":[32.56254000000001,30.10841],"type":"Point"}
}