{
  "type": "Feature",
  "properties": {
    "gn:admin1_code":"06",
    "gn:asciiname":"`Izbat Hawd Ithna `Ashar",
    "gn:country_code":"EG",
    "gn:dem":-2,
    "gn:feature_class":"P",
    "gn:feature_code":"PPL",
    "gn:name":"\u2018Izbat \u1e28aw\u1e11 Ithn\u0101 \u2018Ashar",
    "gn:population":0,
    "gn:timezone":"Africa/Cairo",
    "iso:country":"EG",
    "name:ara_x_preferred":[
        "\u0639\u0632\u0628\u0629 \u062d\u0648\u0636 \u06f1\u06f2"
    ],
    "name:und_x_variant":[
        "\u2018Izbat \u1e28aw\u1e11 Ithn\u0101 \u2018Ashar",
        "\u2018Izbat \u1e28aw\u1e11 12",
        "\u2018Izbat \u1e24aw\u1e0d Number Twelve"
    ],
    "wof:name":"`Izbat Hawd Ithna `Ashar",
    "wof:placetype":"locality"
},
  "geometry": {"coordinates":[30.05411,31.25884000000001],"type":"Point"}
}