{
  "type": "Feature",
  "properties": {
    "gn:admin1_code":"02",
    "gn:asciiname":"Port el Ghalib",
    "gn:country_code":"EG",
    "gn:dem":16,
    "gn:feature_class":"P",
    "gn:feature_code":"PPL",
    "gn:name":"Port el Ghalib",
    "gn:population":0,
    "gn:timezone":"Africa/Cairo",
    "iso:country":"EG",
    "name:und_x_variant":[
        "Port Ghalib"
    ],
    "wof:name":"Port el Ghalib",
    "wof:placetype":"locality"
},
  "geometry": {"coordinates":[34.62719,25.53578],"type":"Point"}
}