{
  "type": "Feature",
  "properties": {
    "gn:admin1_code":"03",
    "gn:asciiname":"`Izbat al Ibrinji",
    "gn:country_code":"EG",
    "gn:dem":6,
    "gn:feature_class":"P",
    "gn:feature_code":"PPL",
    "gn:name":"\u2018Izbat al Ibrinj\u012b",
    "gn:population":0,
    "gn:timezone":"Africa/Cairo",
    "iso:country":"EG",
    "name:ara_x_preferred":[
        "\u0639\u0632\u0628\u0629 \u0627\u0644\u0625\u0628\u0631\u0646\u062c\u064a"
    ],
    "name:und_x_variant":[
        "El-Abr\u00eeqgi",
        "Al Ibr\u012bqj\u012b",
        "Al Ibrinj\u012b",
        "\u2018Izbat al Ibrinj\u012b",
        "\u2018Izbat al-Ibrinji"
    ],
    "wof:name":"`Izbat al Ibrinji",
    "wof:placetype":"locality"
},
  "geometry": {"coordinates":[30.61995,31.07329],"type":"Point"}
}