{
  "type": "Feature",
  "properties": {
    "gn:admin1_code":"14",
    "gn:asciiname":"`Izbat Radwan Khatir",
    "gn:country_code":"EG",
    "gn:dem":8,
    "gn:feature_class":"P",
    "gn:feature_code":"PPL",
    "gn:name":"\u2018Izbat Ra\u1e11w\u0101n Kh\u0101\u0163ir",
    "gn:population":0,
    "gn:timezone":"Africa/Cairo",
    "iso:country":"EG",
    "name:ara_x_preferred":[
        "\u0639\u0632\u0628\u0629 \u0631\u0636\u0648\u0627\u0646 \u062e\u0627\u0637\u0631"
    ],
    "name:und_x_variant":[
        "\u2018Ezbet Radw\u00e2n Mu\u1e25ammad Kh\u00e2tir",
        "\u2018Izbat Ra\u1e11w\u0101n Kh\u0101\u0163ir"
    ],
    "wof:name":"`Izbat Radwan Khatir",
    "wof:placetype":"locality"
},
  "geometry": {"coordinates":[31.73853,30.87358],"type":"Point"}
}