{
  "type": "Feature",
  "properties": {
    "gn:admin1_code":"05",
    "gn:asciiname":"`Izbat Lutfi",
    "gn:country_code":"EG",
    "gn:dem":5,
    "gn:feature_class":"P",
    "gn:feature_code":"PPL",
    "gn:name":"\u2018Izbat Lu\u0163f\u012b",
    "gn:population":0,
    "gn:timezone":"Africa/Cairo",
    "iso:country":"EG",
    "name:ara_x_preferred":[
        "\u0639\u0632\u0628\u0629 \u0644\u0637\u0641\u064a"
    ],
    "name:und_x_variant":[
        "\u2018Izbat Lu\u0163f\u012b",
        "\u2018Izbat Lu\u1e6df\u012b"
    ],
    "wof:name":"`Izbat Lutfi",
    "wof:placetype":"locality"
},
  "geometry": {"coordinates":[31.17045,31.13044],"type":"Point"}
}