{
  "type": "Feature",
  "properties": {
    "gn:admin1_code":"03",
    "gn:asciiname":"`Izbat Abu Hawsh",
    "gn:country_code":"EG",
    "gn:dem":-1,
    "gn:feature_class":"P",
    "gn:feature_code":"PPL",
    "gn:name":"\u2018Izbat Ab\u016b Hawsh",
    "gn:population":0,
    "gn:timezone":"Africa/Cairo",
    "iso:country":"EG",
    "name:ara_x_preferred":[
        "\u0639\u0632\u0628\u0629 \u0623\u0628\u0648 \u0647\u0648\u0634"
    ],
    "name:und_x_variant":[
        "\u2018Izbat Ab\u016b Hawsh"
    ],
    "wof:name":"`Izbat Abu Hawsh",
    "wof:placetype":"locality"
},
  "geometry": {"coordinates":[30.40235,31.16496],"type":"Point"}
}