{
  "type": "Feature",
  "properties": {
    "gn:admin1_code":"21",
    "gn:asciiname":"Kafr at Tayifah",
    "gn:country_code":"EG",
    "gn:dem":6,
    "gn:feature_class":"P",
    "gn:feature_code":"PPL",
    "gn:name":"Kafr a\u0163 \u0162\u0101yifah",
    "gn:population":0,
    "gn:timezone":"Africa/Cairo",
    "iso:country":"EG",
    "name:ara_x_preferred":[
        "\u0643\u0641\u0631 \u0627\u0644\u0637\u0627\u064a\u0641\u0629"
    ],
    "name:und_x_variant":[
        "Kafr el-\u1e6c\u00e2yfa",
        "Kafr a\u0163 \u0162\u0101\u2019ifah",
        "Kafr a\u0163 \u0162\u0101yifah",
        "Kafr a\u1e6d-\u1e6c\u0101yifah"
    ],
    "wof:name":"Kafr at Tayifah",
    "wof:placetype":"locality"
},
  "geometry": {"coordinates":[30.98489,31.08737],"type":"Point"}
}