{
  "type": "Feature",
  "properties": {
    "gn:admin1_code":"08",
    "gn:asciiname":"Bashtil",
    "gn:country_code":"EG",
    "gn:dem":28,
    "gn:feature_class":"P",
    "gn:feature_code":"PPL",
    "gn:name":"Basht\u012bl",
    "gn:population":0,
    "gn:timezone":"Africa/Cairo",
    "iso:country":"EG",
    "name:ara_x_preferred":[
        "\u0628\u0634\u062a\u064a\u0644"
    ],
    "name:und_x_variant":[
        "Basht\u012bl"
    ],
    "wof:name":"Bashtil",
    "wof:placetype":"locality"
},
  "geometry": {"coordinates":[31.18606,30.08567],"type":"Point"}
}