{
  "type": "Feature",
  "properties": {
    "gn:admin1_code":"20",
    "gn:asciiname":"Al Husayniyah",
    "gn:country_code":"EG",
    "gn:dem":4,
    "gn:feature_class":"P",
    "gn:feature_code":"PPL",
    "gn:name":"Al \u1e28usayn\u012byah",
    "gn:population":0,
    "gn:timezone":"Africa/Cairo",
    "iso:country":"EG",
    "name:ara_x_preferred":[
        "\u0627\u0644\u062d\u0633\u064a\u0646\u064a\u0629"
    ],
    "name:und_x_variant":[
        "Al \u1e28usayn\u012byah"
    ],
    "wof:name":"Al Husayniyah",
    "wof:placetype":"locality"
},
  "geometry": {"coordinates":[31.66291,31.36594],"type":"Point"}
}