{
  "type": "Feature",
  "properties": {
    "iso:country":"EG",
    "ne:ADM0CAP":0.0,
    "ne:ADM0NAME":"Egypt",
    "ne:ADM0_A3":"EGY",
    "ne:ADM1NAME":"Janub Sina'",
    "ne:ADMIN1_COD":26,
    "ne:CAPALT":0,
    "ne:CHANGED":0,
    "ne:CHECKME":0,
    "ne:COMPARE":0,
    "ne:DIFFASCII":0,
    "ne:ELEVATION":0.0,
    "ne:FEATURECLA":"Admin-1 capital",
    "ne:FEATURE_CL":"P",
    "ne:FEATURE_CO":"PPL",
    "ne:GEONAMEID":359678,
    "ne:GEONAMESNO":"GeoNames spatial join with similar names only.",
    "ne:GN_ASCII":"At Tur",
    "ne:GN_POP":14972,
    "ne:GTOPO30":18.0,
    "ne:ISO_A2":"EG",
    "ne:LABELRANK":3,
    "ne:LATITUDE":28.239389,
    "ne:LONGITUDE":33.614797,
    "ne:LS_MATCH":1,
    "ne:LS_NAME":"El Tur",
    "ne:MAX_AREAKM":5.0,
    "ne:MAX_AREAMI":2.0,
    "ne:MAX_BBXMAX":33.633333,
    "ne:MAX_BBXMIN":33.616667,
    "ne:MAX_BBYMAX":28.25,
    "ne:MAX_BBYMIN":28.225,
    "ne:MAX_NATSCA":20.0,
    "ne:MAX_PERKM":9.0,
    "ne:MAX_PERMI":5.0,
    "ne:MAX_POP10":27628,
    "ne:MAX_POP20":27628,
    "ne:MAX_POP300":0,
    "ne:MAX_POP310":0,
    "ne:MAX_POP50":0,
    "ne:MEAN_BBXC":33.625,
    "ne:MEAN_BBYC":28.2375,
    "ne:MEGACITY":0,
    "ne:MIN_AREAKM":5.0,
    "ne:MIN_AREAMI":2.0,
    "ne:MIN_BBXMAX":33.633333,
    "ne:MIN_BBXMIN":33.616667,
    "ne:MIN_BBYMAX":28.25,
    "ne:MIN_BBYMIN":28.225,
    "ne:MIN_PERKM":9.0,
    "ne:MIN_PERMI":5.0,
    "ne:NAME":"El Tur",
    "ne:NAMEASCII":"El Tur",
    "ne:NAMEDIFF":0,
    "ne:NATSCALE":20,
    "ne:POP1950":0,
    "ne:POP1955":0,
    "ne:POP1960":0,
    "ne:POP1965":0,
    "ne:POP1970":0,
    "ne:POP1975":0,
    "ne:POP1980":0,
    "ne:POP1985":0,
    "ne:POP1990":0,
    "ne:POP1995":0,
    "ne:POP2000":0,
    "ne:POP2005":0,
    "ne:POP2010":0,
    "ne:POP2015":0,
    "ne:POP2020":0,
    "ne:POP2025":0,
    "ne:POP2050":0,
    "ne:POP_MAX":27628,
    "ne:POP_MIN":14972,
    "ne:POP_OTHER":0,
    "ne:RANK_MAX":7,
    "ne:RANK_MIN":6,
    "ne:SCALERANK":7,
    "ne:SOV0NAME":"Egypt",
    "ne:SOV_A3":"EGY",
    "ne:TIMEZONE":"Africa/Cairo",
    "ne:UN_FID":0,
    "ne:UN_LAT":0.0,
    "ne:UN_LONG":0.0,
    "ne:WORLDCITY":0,
    "ne:min_zoom":6.1,
    "wof:name":"El Tur",
    "wof:placetype":"locality"
},
  "geometry": {"coordinates":[33.61479726232278,28.23938900409155],"type":"Point"}
}