{
  "type": "Feature",
  "properties": {
    "gn:admin1_code":"21",
    "gn:asciiname":"As Salihat",
    "gn:country_code":"EG",
    "gn:dem":5,
    "gn:feature_class":"P",
    "gn:feature_code":"PPL",
    "gn:name":"A\u015f \u015e\u0101li\u1e29\u0101t",
    "gn:population":0,
    "gn:timezone":"Africa/Cairo",
    "iso:country":"EG",
    "name:ara_x_preferred":[
        "\u0627\u0644\u0635\u0627\u0644\u062d\u0627\u062a"
    ],
    "name:und_x_variant":[
        "A\u015f \u015e\u0101li\u1e29\u0101t",
        "A\u1e63-\u1e62\u0101li\u1e25\u0101t"
    ],
    "wof:name":"As Salihat",
    "wof:placetype":"locality"
},
  "geometry": {"coordinates":[30.82088,31.22615],"type":"Point"}
}