{
  "type": "Feature",
  "properties": {
    "gn:admin1_code":"09",
    "gn:asciiname":"Kafr Dimlij",
    "gn:country_code":"EG",
    "gn:dem":13,
    "gn:feature_class":"P",
    "gn:feature_code":"PPL",
    "gn:name":"Kafr Diml\u012bj",
    "gn:population":0,
    "gn:timezone":"Africa/Cairo",
    "iso:country":"EG",
    "name:ara_x_preferred":[
        "\u0643\u0641\u0631 \u062f\u0645\u0644\u064a\u062c"
    ],
    "name:und_x_variant":[
        "Kafr Damall\u00eeg",
        "Kafr Diml\u012bj",
        "Kafr Damallij"
    ],
    "wof:name":"Kafr Dimlij",
    "wof:placetype":"locality"
},
  "geometry": {"coordinates":[30.88323,30.4094],"type":"Point"}
}