{
  "type": "Feature",
  "properties": {
    "gn:admin1_code":"01",
    "gn:asciiname":"`Izbat Husayn Ja`far",
    "gn:country_code":"EG",
    "gn:dem":9,
    "gn:feature_class":"P",
    "gn:feature_code":"PPL",
    "gn:name":"\u2018Izbat \u1e28usayn Ja\u2018far",
    "gn:population":0,
    "gn:timezone":"Africa/Cairo",
    "iso:country":"EG",
    "name:ara_x_preferred":[
        "\u0639\u0632\u0628\u0629 \u062d\u0633\u064a\u0646 \u062c\u0639\u0641\u0631"
    ],
    "name:und_x_variant":[
        "\u2018Izbat \u1e28usayn Ja\u2018far"
    ],
    "wof:name":"`Izbat Husayn Ja`far",
    "wof:placetype":"locality"
},
  "geometry": {"coordinates":[31.55926,30.82969000000001],"type":"Point"}
}