{
  "type": "Feature",
  "properties": {
    "gn:admin1_code":"12",
    "gn:asciiname":"`Izbat ad Dirri",
    "gn:country_code":"EG",
    "gn:dem":12,
    "gn:feature_class":"P",
    "gn:feature_code":"PPL",
    "gn:name":"\u2018Izbat ad Dirr\u012b",
    "gn:population":0,
    "gn:timezone":"Africa/Cairo",
    "iso:country":"EG",
    "name:ara_x_preferred":[
        "\u0639\u0632\u0628\u0629 \u0627\u0644\u062f\u0631\u064a"
    ],
    "name:und_x_variant":[
        "\u2018Izbat ad Dirr\u012b"
    ],
    "wof:name":"`Izbat ad Dirri",
    "wof:placetype":"locality"
},
  "geometry": {"coordinates":[31.26353,30.51316],"type":"Point"}
}