{
  "type": "Feature",
  "properties": {
    "gn:admin1_code":"14",
    "gn:asciiname":"Hawd al Khayr",
    "gn:country_code":"EG",
    "gn:dem":5,
    "gn:feature_class":"P",
    "gn:feature_code":"PPL",
    "gn:name":"\u1e28aw\u1e11 al Khayr",
    "gn:population":0,
    "gn:timezone":"Africa/Cairo",
    "iso:country":"EG",
    "wof:name":"Hawd al Khayr",
    "wof:placetype":"locality"
},
  "geometry": {"coordinates":[31.76827,30.94861],"type":"Point"}
}