{
  "type": "Feature",
  "properties": {
    "gn:admin1_code":"23",
    "gn:asciiname":"Al `Atiyat",
    "gn:country_code":"EG",
    "gn:dem":77,
    "gn:feature_class":"P",
    "gn:feature_code":"PPL",
    "gn:name":"Al \u2018A\u0163\u012by\u0101t",
    "gn:population":0,
    "gn:timezone":"Africa/Cairo",
    "iso:country":"EG",
    "wof:name":"Al `Atiyat",
    "wof:placetype":"locality"
},
  "geometry": {"coordinates":[32.50545,26.1596],"type":"Point"}
}