{
  "type": "Feature",
  "properties": {
    "gn:admin1_code":"24",
    "gn:asciiname":"Mazatah Sharq",
    "gn:country_code":"EG",
    "gn:dem":67,
    "gn:feature_class":"P",
    "gn:feature_code":"PPL",
    "gn:name":"Maz\u0101tah Sharq",
    "gn:population":0,
    "gn:timezone":"Africa/Cairo",
    "iso:country":"EG",
    "name:und_x_variant":[
        "Mas\u00e2ta",
        "Maz\u00e2ta Sharq",
        "Maz\u0101tah Sharq"
    ],
    "wof:name":"Mazatah Sharq",
    "wof:placetype":"locality"
},
  "geometry": {"coordinates":[32.00445999999999,26.29452],"type":"Point"}
}