{
  "type": "Feature",
  "properties": {
    "gn:admin1_code":"14",
    "gn:asciiname":"Kafr `Awad Sulayman",
    "gn:country_code":"EG",
    "gn:dem":9,
    "gn:feature_class":"P",
    "gn:feature_code":"PPL",
    "gn:name":"Kafr \u2018Awa\u1e11 Sulaym\u0101n",
    "gn:population":0,
    "gn:timezone":"Africa/Cairo",
    "iso:country":"EG",
    "name:ara_x_preferred":[
        "\u0643\u0641\u0631 \u0639\u0648\u0635 \u0633\u0644\u064a\u0645\u0627\u0646"
    ],
    "name:und_x_variant":[
        "Kafr \u2018Awa\u1e0d Sul\u00eem\u00e2n",
        "Kafr \u2018Awa\u1e11 Sulaym\u0101n"
    ],
    "wof:name":"Kafr `Awad Sulayman",
    "wof:placetype":"locality"
},
  "geometry": {"coordinates":[31.55928,30.76434],"type":"Point"}
}