{
  "type": "Feature",
  "properties": {
    "gn:admin1_code":"21",
    "gn:asciiname":"`Izbat Warathat Muhammad `Allam",
    "gn:country_code":"EG",
    "gn:dem":7,
    "gn:feature_class":"P",
    "gn:feature_code":"PPL",
    "gn:name":"\u2018Izbat Warathat Mu\u1e29ammad \u2018All\u0101m",
    "gn:population":0,
    "gn:timezone":"Africa/Cairo",
    "iso:country":"EG",
    "name:ara_x_preferred":[
        "\u0639\u0632\u0628\u0629 \u0648\u0631\u062b\u0629 \u0645\u062d\u0645\u062f \u0639\u0644\u0627\u0645"
    ],
    "name:und_x_variant":[
        "\u2018Izbat Warathat Mu\u1e29ammad \u2018All\u0101m",
        "\u2018Izbat Warathat Mu\u1e25ammad \u2018All\u0101m"
    ],
    "wof:name":"`Izbat Warathat Muhammad `Allam",
    "wof:placetype":"locality"
},
  "geometry": {"coordinates":[30.91019,31.16788],"type":"Point"}
}