{
  "type": "Feature",
  "properties": {
    "gn:admin1_code":"01",
    "gn:asciiname":"Ulilah",
    "gn:country_code":"EG",
    "gn:dem":13,
    "gn:feature_class":"P",
    "gn:feature_code":"PPL",
    "gn:name":"\u016al\u012blah",
    "gn:population":0,
    "gn:timezone":"Africa/Cairo",
    "iso:country":"EG",
    "name:ara_x_preferred":[
        "\u0623\u0648\u0644\u064a\u0644\u0629"
    ],
    "name:und_x_variant":[
        "\u016al\u012blah"
    ],
    "wof:name":"Ulilah",
    "wof:placetype":"locality"
},
  "geometry": {"coordinates":[31.35085,30.72286],"type":"Point"}
}