{
  "type": "Feature",
  "properties": {
    "gn:admin1_code":"05",
    "gn:asciiname":"Mit ar Raja",
    "gn:country_code":"EG",
    "gn:dem":13,
    "gn:feature_class":"P",
    "gn:feature_code":"PPL",
    "gn:name":"M\u012bt ar Raj\u0101",
    "gn:population":0,
    "gn:timezone":"Africa/Cairo",
    "iso:country":"EG",
    "name:ara_x_preferred":[
        "\u0645\u064a\u062a \u0627\u0644\u0631\u062c\u0627"
    ],
    "name:und_x_variant":[
        "M\u012bt ar Raj\u0101"
    ],
    "wof:name":"Mit ar Raja",
    "wof:placetype":"locality"
},
  "geometry": {"coordinates":[31.22838,30.62668],"type":"Point"}
}