{
  "type": "Feature",
  "properties": {
    "gn:admin1_code":"14",
    "gn:asciiname":"Qaryat Raqm Thalathah as Salihiyah",
    "gn:country_code":"EG",
    "gn:dem":9,
    "gn:feature_class":"P",
    "gn:feature_code":"PPL",
    "gn:name":"Qaryat Raqm Thal\u0101thah a\u015f \u015e\u0101li\u1e29\u012byah",
    "gn:population":0,
    "gn:timezone":"Africa/Cairo",
    "iso:country":"EG",
    "name:ara_x_preferred":[
        "\u0642\u0631\u064a\u0629 \u0631\u0642\u0645 \u0663 \u0627\u0644\u0635\u0627\u0644\u062d\u064a\u0629"
    ],
    "name:und_x_variant":[
        "Qaryat Raqm Thal\u0101thah a\u015f \u015e\u0101li\u1e29\u012byah",
        "Qaryah Number Three a\u1e63-\u1e62\u0101li\u1e25iyyah"
    ],
    "wof:name":"Qaryat Raqm Thalathah as Salihiyah",
    "wof:placetype":"locality"
},
  "geometry": {"coordinates":[32.06738,30.82515],"type":"Point"}
}