{
  "type": "Feature",
  "properties": {
    "gn:admin1_code":"01",
    "gn:asciiname":"`Izbat al Ja`afirah",
    "gn:country_code":"EG",
    "gn:dem":3,
    "gn:feature_class":"P",
    "gn:feature_code":"PPL",
    "gn:name":"\u2018Izbat al Ja\u2018afirah",
    "gn:population":0,
    "gn:timezone":"Africa/Cairo",
    "iso:country":"EG",
    "name:ara_x_preferred":[
        "\u0639\u0632\u0628\u0629 \u0627\u0644\u062c\u0639\u0627\u0641\u0631\u0629"
    ],
    "name:und_x_variant":[
        "\u2018Izbat al Ja\u2018afirah",
        "\u2018Izbat al Ja\u2018\u0101frah",
        "\u2018Izbat al-Ja\u2018afrah"
    ],
    "wof:name":"`Izbat al Ja`afirah",
    "wof:placetype":"locality"
},
  "geometry": {"coordinates":[31.83775,31.12351],"type":"Point"}
}