{
  "type": "Feature",
  "properties": {
    "gn:admin1_code":"06",
    "gn:asciiname":"`Izbat Farhad",
    "gn:country_code":"EG",
    "gn:dem":-2,
    "gn:feature_class":"P",
    "gn:feature_code":"PPL",
    "gn:name":"\u2018Izbat Farh\u0101d",
    "gn:population":0,
    "gn:timezone":"Africa/Cairo",
    "iso:country":"EG",
    "name:ara_x_preferred":[
        "\u0639\u0632\u0628\u0629 \u0641\u0631\u0647\u0627\u062f"
    ],
    "name:und_x_variant":[
        "\u2018Izbat Farh\u0101d"
    ],
    "wof:name":"`Izbat Farhad",
    "wof:placetype":"locality"
},
  "geometry": {"coordinates":[30.0549,31.22728],"type":"Point"}
}