{
  "type": "Feature",
  "properties": {
    "gn:admin1_code":"14",
    "gn:asciiname":"Mit Hamal",
    "gn:country_code":"EG",
    "gn:dem":16,
    "gn:feature_class":"P",
    "gn:feature_code":"PPL",
    "gn:name":"M\u012bt \u1e28amal",
    "gn:population":0,
    "gn:timezone":"Africa/Cairo",
    "iso:country":"EG",
    "name:ara_x_preferred":[
        "\u0645\u064a\u062a \u062d\u0645\u0644"
    ],
    "name:und_x_variant":[
        "M\u012bt \u1e28amal"
    ],
    "wof:name":"Mit Hamal",
    "wof:placetype":"locality"
},
  "geometry": {"coordinates":[31.53714,30.43021],"type":"Point"}
}