{
  "type": "Feature",
  "properties": {
    "gn:admin1_code":"21",
    "gn:asciiname":"Mahallat Abu `Ali al Gharbiyah",
    "gn:country_code":"EG",
    "gn:dem":8,
    "gn:feature_class":"P",
    "gn:feature_code":"PPL",
    "gn:name":"Ma\u1e29allat Ab\u016b \u2018Al\u012b al Gharb\u012byah",
    "gn:population":0,
    "gn:timezone":"Africa/Cairo",
    "iso:country":"EG",
    "name:ara_x_preferred":[
        "\u0645\u062d\u0644\u0629 \u0623\u0628\u0648 \u0639\u0644\u064a \u0627\u0644\u063a\u0631\u0628\u064a\u0629"
    ],
    "name:und_x_variant":[
        "Ma\u1e25allet Abu \u2018Ali el-Gharb\u00eeya",
        "Ma\u1e29allat Ab\u016b \u2018Al\u012b al Gharb\u012byah",
        "Ma\u1e25allat Ab\u016b \u2018Ali al Gharbiyyah"
    ],
    "wof:name":"Mahallat Abu `Ali al Gharbiyah",
    "wof:placetype":"locality"
},
  "geometry": {"coordinates":[30.69539,31.09474],"type":"Point"}
}