{
  "type": "Feature",
  "properties": {
    "gn:admin1_code":"03",
    "gn:asciiname":"Kafr ar Rahmaniyah",
    "gn:country_code":"EG",
    "gn:dem":7,
    "gn:feature_class":"P",
    "gn:feature_code":"PPL",
    "gn:name":"Kafr ar Ra\u1e29m\u0101n\u012byah",
    "gn:population":0,
    "gn:timezone":"Africa/Cairo",
    "iso:country":"EG",
    "name:ara_x_preferred":[
        "\u0643\u0641\u0631 \u0627\u0644\u0631\u062d\u0645\u0627\u0646\u064a\u0629"
    ],
    "name:und_x_variant":[
        "Kafr el-Ra\u1e25m\u00e2n\u00eeya",
        "Kafr ar Ra\u1e29m\u0101n\u012byah",
        "Kafr ar Ra\u1e25m\u0101niyyah"
    ],
    "wof:name":"Kafr ar Rahmaniyah",
    "wof:placetype":"locality"
},
  "geometry": {"coordinates":[30.5286,31.16381],"type":"Point"}
}