{
  "type": "Feature",
  "properties": {
    "gn:admin1_code":"03",
    "gn:asciiname":"`Izbat Jawad Husni",
    "gn:country_code":"EG",
    "gn:dem":2,
    "gn:feature_class":"P",
    "gn:feature_code":"PPL",
    "gn:name":"\u2018Izbat Jaw\u0101d \u1e28usn\u012b",
    "gn:population":0,
    "gn:timezone":"Africa/Cairo",
    "iso:country":"EG",
    "name:ara_x_preferred":[
        "\u0639\u0632\u0628\u0629 \u062c\u0648\u0627\u062f \u062d\u0633\u0646\u064a"
    ],
    "name:und_x_variant":[
        "\u2018Izbat Jaw\u0101d \u1e28usn\u012b",
        "\u2018Izbat Jaw\u0101d \u1e24usn\u012b"
    ],
    "wof:name":"`Izbat Jawad Husni",
    "wof:placetype":"locality"
},
  "geometry": {"coordinates":[30.34151,31.04928],"type":"Point"}
}