{
  "type": "Feature",
  "properties": {
    "gn:admin1_code":"12",
    "gn:asciiname":"`Arab al Muqabilah",
    "gn:country_code":"EG",
    "gn:dem":16,
    "gn:feature_class":"P",
    "gn:feature_code":"PPL",
    "gn:name":"\u2018Arab al Muq\u0101bilah",
    "gn:population":0,
    "gn:timezone":"Africa/Cairo",
    "iso:country":"EG",
    "name:und_x_variant":[
        "\u2018Arab el-Muq\u00e2bla",
        "\u2018Arab al Muq\u0101bilah"
    ],
    "wof:name":"`Arab al Muqabilah",
    "wof:placetype":"locality"
},
  "geometry": {"coordinates":[31.29656,30.40044],"type":"Point"}
}