{
  "type": "Feature",
  "properties": {
    "gn:admin1_code":"21",
    "gn:asciiname":"Al `Anabirah",
    "gn:country_code":"EG",
    "gn:dem":5,
    "gn:feature_class":"P",
    "gn:feature_code":"PPL",
    "gn:name":"Al \u2018An\u0101birah",
    "gn:population":0,
    "gn:timezone":"Africa/Cairo",
    "iso:country":"EG",
    "name:ara_x_preferred":[
        "\u0627\u0644\u0639\u0646\u0627\u0628\u0631\u0629"
    ],
    "name:und_x_variant":[
        "Al \u2018An\u0101birah",
        "El-\u2018An\u00e2bra",
        "Al \u2018An\u0101brah"
    ],
    "wof:name":"Al `Anabirah",
    "wof:placetype":"locality"
},
  "geometry": {"coordinates":[31.02245,31.57744000000001],"type":"Point"}
}