{
  "type": "Feature",
  "properties": {
    "gn:admin1_code":"24",
    "gn:asciiname":"Minshat Bardis",
    "gn:country_code":"EG",
    "gn:dem":63,
    "gn:feature_class":"P",
    "gn:feature_code":"PPL",
    "gn:name":"Minsh\u0101t Bard\u012bs",
    "gn:population":0,
    "gn:timezone":"Africa/Cairo",
    "iso:country":"EG",
    "wof:name":"Minshat Bardis",
    "wof:placetype":"locality"
},
  "geometry": {"coordinates":[31.93333,26.28333],"type":"Point"}
}