{
  "type": "Feature",
  "properties": {
    "gn:admin1_code":"01",
    "gn:asciiname":"`Izbat Shata Haykal",
    "gn:country_code":"EG",
    "gn:dem":5,
    "gn:feature_class":"P",
    "gn:feature_code":"PPL",
    "gn:name":"\u2018Izbat Sha\u0163\u0101 Haykal",
    "gn:population":0,
    "gn:timezone":"Africa/Cairo",
    "iso:country":"EG",
    "name:ara_x_preferred":[
        "\u0639\u0632\u0628\u0629 \u0634\u0637\u0627 \u0647\u064a\u0643\u0644"
    ],
    "name:und_x_variant":[
        "\u2018Izbat Sha\u0163\u0101 Haykal",
        "\u2018Iz. Sha\u1e6d\u0101 Haykal"
    ],
    "wof:name":"`Izbat Shata Haykal",
    "wof:placetype":"locality"
},
  "geometry": {"coordinates":[31.61098,31.20515],"type":"Point"}
}