{
  "type": "Feature",
  "properties": {
    "gn:admin1_code":"14",
    "gn:asciiname":"Kafr al `Awadi",
    "gn:country_code":"EG",
    "gn:dem":12,
    "gn:feature_class":"P",
    "gn:feature_code":"PPL",
    "gn:name":"Kafr al \u2018Awa\u1e11\u012b",
    "gn:population":0,
    "gn:timezone":"Africa/Cairo",
    "iso:country":"EG",
    "name:ara_x_preferred":[
        "\u0643\u0641\u0631 \u0627\u0644\u0639\u0648\u0636\u064a"
    ],
    "name:und_x_variant":[
        "Kafr al \u2018Awa\u1e11\u012b"
    ],
    "wof:name":"Kafr al `Awadi",
    "wof:placetype":"locality"
},
  "geometry": {"coordinates":[31.51306,30.45859],"type":"Point"}
}