{
  "type": "Feature",
  "properties": {
    "gn:admin1_code":"03",
    "gn:asciiname":"`Izbat al Wanayisah",
    "gn:country_code":"EG",
    "gn:dem":4,
    "gn:feature_class":"P",
    "gn:feature_code":"PPL",
    "gn:name":"\u2018Izbat al Wan\u0101yisah",
    "gn:population":0,
    "gn:timezone":"Africa/Cairo",
    "iso:country":"EG",
    "name:ara_x_preferred":[
        "\u0639\u0632\u0628\u0629 \u0627\u0644\u0648\u0646\u0627\u064a\u0633\u0629"
    ],
    "name:und_x_variant":[
        "\u2018Izbat al Wan\u0101yisah",
        "\u2018Izbat al-Wan\u0101ysah"
    ],
    "wof:name":"`Izbat al Wanayisah",
    "wof:placetype":"locality"
},
  "geometry": {"coordinates":[30.42825,31.09228],"type":"Point"}
}