{
  "type": "Feature",
  "properties": {
    "gn:admin1_code":"01",
    "gn:asciiname":"`Izbat Jarrah",
    "gn:country_code":"EG",
    "gn:dem":9,
    "gn:feature_class":"P",
    "gn:feature_code":"PPL",
    "gn:name":"\u2018Izbat Jarr\u0101\u1e29",
    "gn:population":0,
    "gn:timezone":"Africa/Cairo",
    "iso:country":"EG",
    "name:ara_x_preferred":[
        "\u0639\u0632\u0628\u0629 \u062c\u0631\u0627\u062d"
    ],
    "name:und_x_variant":[
        "Garr\u00e2\u1e25",
        "Jarr\u0101\u1e29",
        "\u2018Izbat Jarr\u0101\u1e29",
        "\u2018Iz. Jarr\u0101\u1e25"
    ],
    "wof:name":"`Izbat Jarrah",
    "wof:placetype":"locality"
},
  "geometry": {"coordinates":[31.25866,30.93568],"type":"Point"}
}