{
  "type": "Feature",
  "properties": {
    "gn:admin1_code":"01",
    "gn:asciiname":"`Izbat al `Ayiqah al Kabirah",
    "gn:country_code":"EG",
    "gn:dem":5,
    "gn:feature_class":"P",
    "gn:feature_code":"PPL",
    "gn:name":"\u2018Izbat al \u2018\u0100yiqah al Kab\u012brah",
    "gn:population":0,
    "gn:timezone":"Africa/Cairo",
    "iso:country":"EG",
    "name:ara_x_preferred":[
        "\u0639\u0632\u0628\u0629 \u0627\u0644\u0639\u0627\u064a\u0642\u0629 \u0627\u0644\u0643\u0628\u064a\u0631\u0629"
    ],
    "name:und_x_variant":[
        "\u2018Izbat al \u2018\u0100yqah al Kab\u012brah",
        "\u2018Izbat al \u2018\u0100yiqah al Kab\u012brah"
    ],
    "wof:name":"`Izbat al `Ayiqah al Kabirah",
    "wof:placetype":"locality"
},
  "geometry": {"coordinates":[31.28746,31.26522000000001],"type":"Point"}
}