{
  "type": "Feature",
  "properties": {
    "gn:admin1_code":"24",
    "gn:asciiname":"Mazatat ash Shaykh Jabr",
    "gn:country_code":"EG",
    "gn:dem":72,
    "gn:feature_class":"P",
    "gn:feature_code":"PPL",
    "gn:name":"Maz\u0101tat ash Shaykh Jabr",
    "gn:population":0,
    "gn:timezone":"Africa/Cairo",
    "iso:country":"EG",
    "name:und_x_variant":[
        "Maz\u00e2ta and el Sheikh Gabr",
        "Maz\u0101tah wa ash Shaykh Jabr",
        "Maz\u0101tat ash Shaykh Jabr"
    ],
    "wof:name":"Mazatat ash Shaykh Jabr",
    "wof:placetype":"locality"
},
  "geometry": {"coordinates":[31.91317,26.30503],"type":"Point"}
}