{
  "type": "Feature",
  "properties": {
    "gn:admin1_code":"18",
    "gn:asciiname":"Al Qaryah al Qibliyah",
    "gn:country_code":"EG",
    "gn:dem":48,
    "gn:feature_class":"P",
    "gn:feature_code":"PPL",
    "gn:name":"Al Qaryah al Qibl\u012byah",
    "gn:population":0,
    "gn:timezone":"Africa/Cairo",
    "iso:country":"EG",
    "wof:name":"Al Qaryah al Qibliyah",
    "wof:placetype":"locality"
},
  "geometry": {"coordinates":[30.77891,28.9131],"type":"Point"}
}