{
  "type": "Feature",
  "properties": {
    "gn:admin1_code":"14",
    "gn:asciiname":"Jazirat al `Iraqi",
    "gn:country_code":"EG",
    "gn:dem":13,
    "gn:feature_class":"P",
    "gn:feature_code":"PPL",
    "gn:name":"Jaz\u012brat al \u2018Ir\u0101q\u012b",
    "gn:population":0,
    "gn:timezone":"Africa/Cairo",
    "iso:country":"EG",
    "name:ara_x_preferred":[
        "\u062c\u0632\u064a\u0631\u0629 \u0627\u0644\u0639\u0631\u0627\u0642\u064a"
    ],
    "name:und_x_variant":[
        "Gez\u00eeret el-\u2018Ir\u00e2qi",
        "Geziret al Iragi",
        "Jaz\u012brat al \u2018Ir\u0101q\u012b"
    ],
    "wof:name":"Jazirat al `Iraqi",
    "wof:placetype":"locality"
},
  "geometry": {"coordinates":[31.69094,30.52409],"type":"Point"}
}