{
  "type": "Feature",
  "properties": {
    "gn:admin1_code":"07",
    "gn:asciiname":"`Izbat Dawud Suliman",
    "gn:country_code":"EG",
    "gn:dem":8,
    "gn:feature_class":"P",
    "gn:feature_code":"PPL",
    "gn:name":"\u2018Izbat Daw\u016bd Sulim\u0101n",
    "gn:population":0,
    "gn:timezone":"Africa/Cairo",
    "iso:country":"EG",
    "name:und_x_variant":[
        "\u2018Ezbet Daw\u00fbd Suliman",
        "\u2018Izbat Daw\u016bd Sulim\u0101n"
    ],
    "wof:name":"`Izbat Dawud Suliman",
    "wof:placetype":"locality"
},
  "geometry": {"coordinates":[32.045,30.53694],"type":"Point"}
}