{
  "type": "Feature",
  "properties": {
    "gn:admin1_code":"01",
    "gn:asciiname":"`Izbat `Ali ash Shirbini",
    "gn:country_code":"EG",
    "gn:dem":5,
    "gn:feature_class":"P",
    "gn:feature_code":"PPL",
    "gn:name":"\u2018Izbat \u2018Al\u012b ash Shirb\u012bn\u012b",
    "gn:population":0,
    "gn:timezone":"Africa/Cairo",
    "iso:country":"EG",
    "name:ara_x_preferred":[
        "\u0639\u0632\u0628\u0629 \u0639\u0644\u064a \u0627\u0644\u0634\u0631\u0628\u064a\u0646\u064a"
    ],
    "name:und_x_variant":[
        "\u2018Izbat \u2018Al\u012b ash Shirb\u012bn\u012b"
    ],
    "wof:name":"`Izbat `Ali ash Shirbini",
    "wof:placetype":"locality"
},
  "geometry": {"coordinates":[31.86495,31.22487000000001],"type":"Point"}
}