{
  "type": "Feature",
  "properties": {
    "gn:admin1_code":"10",
    "gn:asciiname":"Shararah",
    "gn:cc2":"EG",
    "gn:country_code":"EG",
    "gn:dem":41,
    "gn:feature_class":"P",
    "gn:feature_code":"PPL",
    "gn:name":"Shar\u0101rah",
    "gn:population":0,
    "gn:timezone":"Africa/Cairo",
    "iso:country":"EG",
    "name:nno_x_preferred":[
        "Shararah"
    ],
    "name:und_x_variant":[
        "Shar\u00e2ra",
        "Shar\u0101rah"
    ],
    "wof:name":"Shararah",
    "wof:placetype":"locality"
},
  "geometry": {"coordinates":[30.85,27.96667],"type":"Point"}
}