{
  "type": "Feature",
  "properties": {
    "gn:admin1_code":"21",
    "gn:asciiname":"`Izbat al Hinnawi",
    "gn:country_code":"EG",
    "gn:dem":8,
    "gn:feature_class":"P",
    "gn:feature_code":"PPL",
    "gn:name":"\u2018Izbat al \u1e28inn\u0101w\u012b",
    "gn:population":0,
    "gn:timezone":"Africa/Cairo",
    "iso:country":"EG",
    "name:ara_x_preferred":[
        "\u0639\u0632\u0628\u0629 \u0627\u0644\u062d\u0646\u0627\u0648\u064a"
    ],
    "name:und_x_variant":[
        "\u2018Izbat al \u1e28inn\u0101w\u012b",
        "\u2018Izbat al-\u1e24inn\u0101w\u012b"
    ],
    "wof:name":"`Izbat al Hinnawi",
    "wof:placetype":"locality"
},
  "geometry": {"coordinates":[30.82391,31.06895],"type":"Point"}
}