{
  "type": "Feature",
  "properties": {
    "gn:admin1_code":"21",
    "gn:asciiname":"`Izbat Rajab",
    "gn:country_code":"EG",
    "gn:dem":2,
    "gn:feature_class":"P",
    "gn:feature_code":"PPL",
    "gn:name":"\u2018Izbat Rajab",
    "gn:population":0,
    "gn:timezone":"Africa/Cairo",
    "iso:country":"EG",
    "name:ara_x_preferred":[
        "\u0639\u0632\u0628\u0629 \u0631\u062c\u0628"
    ],
    "name:und_x_variant":[
        "\u2018Izbat Rajab"
    ],
    "wof:name":"`Izbat Rajab",
    "wof:placetype":"locality"
},
  "geometry": {"coordinates":[31.2697,31.29743],"type":"Point"}
}