{
  "type": "Feature",
  "properties": {
    "gn:admin1_code":"12",
    "gn:asciiname":"Dandana",
    "gn:country_code":"EG",
    "gn:dem":17,
    "gn:feature_class":"P",
    "gn:feature_code":"PPL",
    "gn:name":"Dandan\u0101",
    "gn:population":0,
    "gn:timezone":"Africa/Cairo",
    "iso:country":"EG",
    "name:ara_x_preferred":[
        "\u062f\u0646\u062f\u0646\u0627"
    ],
    "name:und_x_variant":[
        "Dandan\u0101"
    ],
    "wof:name":"Dandana",
    "wof:placetype":"locality"
},
  "geometry": {"coordinates":[31.20847,30.334],"type":"Point"}
}