{
  "type": "Feature",
  "properties": {
    "gn:admin1_code":"03",
    "gn:asciiname":"`Izbat al Banna",
    "gn:country_code":"EG",
    "gn:dem":3,
    "gn:feature_class":"P",
    "gn:feature_code":"PPL",
    "gn:name":"\u2018Izbat al Bann\u0101",
    "gn:population":0,
    "gn:timezone":"Africa/Cairo",
    "iso:country":"EG",
    "name:ara_x_preferred":[
        "\u0639\u0632\u0628\u0629 \u0627\u0644\u0628\u0646\u0627"
    ],
    "name:und_x_variant":[
        "\u2018Ezbet Y\u00fbsef el-Banna",
        "\u2018Izbat al \u1e28\u0101jj Y\u016bsuf al Bann\u0101\u2019",
        "\u2018Izbat al Bann\u0101"
    ],
    "wof:name":"`Izbat al Banna",
    "wof:placetype":"locality"
},
  "geometry": {"coordinates":[30.37833,31.10916],"type":"Point"}
}