{
  "type": "Feature",
  "properties": {
    "gn:admin1_code":"5.0",
    "gn:asciiname":"1 `Ezbet Has Salib",
    "gn:country_code":"EG",
    "gn:dem":11,
    "gn:feature_class":"P",
    "gn:feature_code":"PPL",
    "gn:name":"1 \u2018Ezbet Ha\u1e63 S\u00e2lib",
    "gn:population":0,
    "gn:timezone":"Africa/Cairo",
    "iso:country":"EG",
    "name:und_x_variant":[
        "\u2018Ezbet \u1e24asan \u1e62\u00e2li\u1e25",
        "1 \u2018Ezbet Ha\u1e63 S\u00e2lib"
    ],
    "wof:name":"1 `Ezbet Has Salib",
    "wof:placetype":"locality"
},
  "geometry": {"coordinates":[31.00361,30.98583],"type":"Point"}
}