{
  "type": "Feature",
  "properties": {
    "gn:admin1_code":"04",
    "gn:asciiname":"At Tall",
    "gn:cc2":"EG",
    "gn:country_code":"EG",
    "gn:dem":27,
    "gn:feature_class":"P",
    "gn:feature_code":"PPL",
    "gn:name":"At Tall",
    "gn:population":0,
    "gn:timezone":"Africa/Cairo",
    "iso:country":"EG",
    "name:und_x_variant":[
        "El Tell",
        "At Tall"
    ],
    "wof:name":"At Tall",
    "wof:placetype":"locality"
},
  "geometry": {"coordinates":[31.06667,29.11667000000001],"type":"Point"}
}