{
  "type": "Feature",
  "properties": {
    "gn:admin1_code":"04",
    "gn:asciiname":"Al `Aziziyah",
    "gn:country_code":"EG",
    "gn:dem":3,
    "gn:feature_class":"P",
    "gn:feature_code":"PPL",
    "gn:name":"Al \u2018Az\u012bz\u012byah",
    "gn:population":0,
    "gn:timezone":"Africa/Cairo",
    "iso:country":"EG",
    "name:und_x_variant":[
        "El \u2018Az\u00e2z\u00eeya",
        "Al \u2018Az\u012bz\u012byah"
    ],
    "wof:name":"Al `Aziziyah",
    "wof:placetype":"locality"
},
  "geometry": {"coordinates":[31.04528,29.41611],"type":"Point"}
}