{
  "type": "Feature",
  "properties": {
    "gn:admin1_code":"01",
    "gn:asciiname":"`Izbat Ra's Khalij al Mahattah",
    "gn:country_code":"EG",
    "gn:dem":7,
    "gn:feature_class":"P",
    "gn:feature_code":"PPL",
    "gn:name":"\u2018Izbat Ra\u2019s Khal\u012bj al Ma\u1e29attah",
    "gn:population":0,
    "gn:timezone":"Africa/Cairo",
    "iso:country":"EG",
    "name:ara_x_preferred":[
        "\u0639\u0632\u0628\u0629 \u0631\u0623\u0633 \u062e\u0644\u064a\u062c \u0627\u0644\u0645\u062d\u0637\u0629"
    ],
    "name:und_x_variant":[
        "\u2018Izbat Ra\u2019s Khal\u012bj al Ma\u1e29attah"
    ],
    "wof:name":"`Izbat Ra's Khalij al Mahattah",
    "wof:placetype":"locality"
},
  "geometry": {"coordinates":[31.61895,31.25117],"type":"Point"}
}