{
  "type": "Feature",
  "properties": {
    "gn:admin1_code":"3.0",
    "gn:asciiname":"Zawiyat Hammur",
    "gn:country_code":"EG",
    "gn:dem":7,
    "gn:feature_class":"P",
    "gn:feature_code":"PPL",
    "gn:name":"Z\u0101wiyat \u1e28amm\u016br",
    "gn:population":0,
    "gn:timezone":"Africa/Cairo",
    "iso:country":"EG",
    "name:und_x_variant":[
        "Z\u00e2wyet \u1e24am\u00fbr",
        "Z\u00e2wyer Hann\u00fbr",
        "Z\u00e2wyet \u1e24amm\u00fbr",
        "Z\u00e2wyet \u1e24annu",
        "Z\u0101wiyat \u1e28amm\u016br"
    ],
    "wof:name":"Zawiyat Hammur",
    "wof:placetype":"locality"
},
  "geometry": {"coordinates":[30.43615,30.84755],"type":"Point"}
}