{
  "type": "Feature",
  "properties": {
    "gn:admin1_code":"01",
    "gn:asciiname":"`Izbat Mahmud `Abd al Latif",
    "gn:country_code":"EG",
    "gn:dem":4,
    "gn:feature_class":"P",
    "gn:feature_code":"PPL",
    "gn:name":"\u2018Izbat Ma\u1e29m\u016bd \u2018Abd al La\u0163\u012bf",
    "gn:population":0,
    "gn:timezone":"Africa/Cairo",
    "iso:country":"EG",
    "name:ara_x_preferred":[
        "\u0639\u0632\u0628\u0629 \u0645\u062d\u0645\u0648\u062f \u0639\u0628\u062f \u0627\u0644\u0644\u0637\u064a\u0641"
    ],
    "name:und_x_variant":[
        "\u2018Izbat Ma\u1e29m\u016bd \u2018Abd al La\u0163\u012bf",
        "\u2018Izbat Ma\u1e25m\u016bd \u2018Abd al-La\u1e6dif"
    ],
    "wof:name":"`Izbat Mahmud `Abd al Latif",
    "wof:placetype":"locality"
},
  "geometry": {"coordinates":[31.84061,31.18499000000001],"type":"Point"}
}