{
  "type": "Feature",
  "properties": {
    "gn:admin1_code":"03",
    "gn:asciiname":"`Izbat Fayid",
    "gn:country_code":"EG",
    "gn:dem":3,
    "gn:feature_class":"P",
    "gn:feature_code":"PPL",
    "gn:name":"\u2018Izbat F\u0101yid",
    "gn:population":0,
    "gn:timezone":"Africa/Cairo",
    "iso:country":"EG",
    "name:ara_x_preferred":[
        "\u0639\u0632\u0628\u0629 \u0641\u0627\u064a\u062f"
    ],
    "name:und_x_variant":[
        "\u2018Izbat F\u0101yid"
    ],
    "wof:name":"`Izbat Fayid",
    "wof:placetype":"locality"
},
  "geometry": {"coordinates":[30.13878,31.25788],"type":"Point"}
}