{
  "type": "Feature",
  "properties": {
    "gn:admin1_code":"10",
    "gn:asciiname":"Abu `Aziz",
    "gn:country_code":"EG",
    "gn:dem":40,
    "gn:feature_class":"P",
    "gn:feature_code":"PPL",
    "gn:name":"Ab\u016b \u2018Az\u012bz",
    "gn:population":0,
    "gn:timezone":"Africa/Cairo",
    "iso:country":"EG",
    "wof:name":"Abu `Aziz",
    "wof:placetype":"locality"
},
  "geometry": {"coordinates":[30.83114,28.43332],"type":"Point"}
}