{
  "type": "Feature",
  "properties": {
    "gn:admin1_code":"27",
    "gn:asciiname":"Sakan Abu Ragia",
    "gn:country_code":"EG",
    "gn:dem":544,
    "gn:feature_class":"P",
    "gn:feature_code":"PPLL",
    "gn:name":"Sakan Abu Rag\u012ba",
    "gn:population":0,
    "gn:timezone":"Africa/Cairo",
    "iso:country":"EG",
    "name:heb_x_preferred":[
        "Sakan Abu Rag\u012ba"
    ],
    "name:heb_x_variant":[
        "\u05e1\u05db\u05df \u05d0\u05d1\u05d5 \u05e8\u05d2\u05d9\u05d4"
    ],
    "wof:name":"Sakan Abu Ragia",
    "wof:placetype":"locality"
},
  "geometry": {"coordinates":[34.48663,30.62845],"type":"Point"}
}