{
  "type": "Feature",
  "properties": {
    "gn:admin1_code":"10",
    "gn:asciiname":"Naj` Mubarak",
    "gn:country_code":"EG",
    "gn:dem":47,
    "gn:feature_class":"P",
    "gn:feature_code":"PPL",
    "gn:name":"Naj\u2018 Mub\u0101rak",
    "gn:population":0,
    "gn:timezone":"Africa/Cairo",
    "iso:country":"EG",
    "name:und_x_variant":[
        "Nag\u2018 Mub\u00e2rik",
        "Naj\u2018 Mub\u0101rak"
    ],
    "wof:name":"Naj` Mubarak",
    "wof:placetype":"locality"
},
  "geometry": {"coordinates":[30.76667,27.61667000000001],"type":"Point"}
}