{
  "type": "Feature",
  "properties": {
    "gn:admin1_code":"03",
    "gn:asciiname":"`Izbat az Zayyatin",
    "gn:country_code":"EG",
    "gn:dem":-1,
    "gn:feature_class":"P",
    "gn:feature_code":"PPL",
    "gn:name":"\u2018Izbat az Zayy\u0101t\u012bn",
    "gn:population":0,
    "gn:timezone":"Africa/Cairo",
    "iso:country":"EG",
    "name:ara_x_preferred":[
        "\u0639\u0632\u0628\u0629 \u0627\u0644\u0632\u064a\u0627\u062a\u064a\u0646"
    ],
    "name:und_x_variant":[
        "\u2018Izbat az Zayy\u0101t\u012bn"
    ],
    "wof:name":"`Izbat az Zayyatin",
    "wof:placetype":"locality"
},
  "geometry": {"coordinates":[30.36362,31.02435],"type":"Point"}
}