{
  "type": "Feature",
  "properties": {
    "gn:admin1_code":"14",
    "gn:asciiname":"`Izbat Harb",
    "gn:country_code":"EG",
    "gn:dem":9,
    "gn:feature_class":"P",
    "gn:feature_code":"PPL",
    "gn:name":"\u2018Izbat \u1e28arb",
    "gn:population":0,
    "gn:timezone":"Africa/Cairo",
    "iso:country":"EG",
    "name:ara_x_preferred":[
        "\u0639\u0632\u0628\u0629 \u062d\u0631\u0628"
    ],
    "name:und_x_variant":[
        "\u2018Izbat \u1e28arb"
    ],
    "wof:name":"`Izbat Harb",
    "wof:placetype":"locality"
},
  "geometry": {"coordinates":[31.36842,30.70215],"type":"Point"}
}