{
  "type": "Feature",
  "properties": {
    "gn:admin1_code":"08",
    "gn:asciiname":"Al Hayy",
    "gn:cc2":"EG",
    "gn:country_code":"EG",
    "gn:dem":21,
    "gn:feature_class":"P",
    "gn:feature_code":"PPL",
    "gn:name":"Al \u1e28ayy",
    "gn:population":0,
    "gn:timezone":"Africa/Cairo",
    "iso:country":"EG",
    "name:und_x_variant":[
        "El-Hai",
        "Al \u1e28ay",
        "Al \u1e28ayy"
    ],
    "wof:name":"Al Hayy",
    "wof:placetype":"locality"
},
  "geometry": {"coordinates":[31.30778,29.64833],"type":"Point"}
}