{
  "type": "Feature",
  "properties": {
    "gn:admin1_code":"17",
    "gn:asciiname":"Al `Assarah",
    "gn:country_code":"EG",
    "gn:dem":54,
    "gn:feature_class":"P",
    "gn:feature_code":"PPL",
    "gn:name":"Al \u2018A\u015f\u015f\u0101rah",
    "gn:population":0,
    "gn:timezone":"Africa/Cairo",
    "iso:country":"EG",
    "name:und_x_variant":[
        "El Assara",
        "Al \u2018A\u015f\u015f\u0101rah"
    ],
    "wof:name":"Al `Assarah",
    "wof:placetype":"locality"
},
  "geometry": {"coordinates":[31.20698,27.21609],"type":"Point"}
}