{
  "type": "Feature",
  "properties": {
    "gn:admin1_code":"12",
    "gn:asciiname":"Nazlat as Siba`at",
    "gn:country_code":"EG",
    "gn:dem":16,
    "gn:feature_class":"P",
    "gn:feature_code":"PPL",
    "gn:name":"Nazlat as Sib\u0101\u2018\u0101t",
    "gn:population":0,
    "gn:timezone":"Africa/Cairo",
    "iso:country":"EG",
    "name:und_x_variant":[
        "Nazlet el Sib\u00e2\u2018\u00e2t",
        "Nazlat as Sib\u0101\u2018\u0101t"
    ],
    "wof:name":"Nazlat as Siba`at",
    "wof:placetype":"locality"
},
  "geometry": {"coordinates":[31.29324,30.40905],"type":"Point"}
}