{
  "type": "Feature",
  "properties": {
    "gn:admin1_code":"14",
    "gn:asciiname":"`Izbat ash Shabrawi",
    "gn:country_code":"EG",
    "gn:dem":10,
    "gn:feature_class":"P",
    "gn:feature_code":"PPL",
    "gn:name":"\u2018Izbat ash Shabr\u0101w\u012b",
    "gn:population":0,
    "gn:timezone":"Africa/Cairo",
    "iso:country":"EG",
    "name:ara_x_preferred":[
        "\u0639\u0632\u0628\u0629 \u0627\u0644\u0634\u0628\u0631\u0627\u0648\u064a"
    ],
    "name:und_x_variant":[
        "\u2018Izbat ash Shabr\u0101w\u012b"
    ],
    "wof:name":"`Izbat ash Shabrawi",
    "wof:placetype":"locality"
},
  "geometry": {"coordinates":[31.6607,30.57861],"type":"Point"}
}