{
  "type": "Feature",
  "properties": {
    "gn:admin1_code":"04",
    "gn:asciiname":"Dar as Salam",
    "gn:country_code":"EG",
    "gn:dem":-36,
    "gn:feature_class":"P",
    "gn:feature_code":"PPL",
    "gn:name":"D\u0101r as Sal\u0101m",
    "gn:population":0,
    "gn:timezone":"Africa/Cairo",
    "iso:country":"EG",
    "wof:name":"Dar as Salam",
    "wof:placetype":"locality"
},
  "geometry": {"coordinates":[30.38258,29.45622],"type":"Point"}
}