{
  "type": "Feature",
  "properties": {
    "gn:admin1_code":"27",
    "gn:asciiname":"Al Mulayz",
    "gn:country_code":"EG",
    "gn:dem":310,
    "gn:feature_class":"P",
    "gn:feature_code":"PPL",
    "gn:name":"Al Mulayz",
    "gn:population":0,
    "gn:timezone":"Africa/Cairo",
    "iso:country":"EG",
    "wof:name":"Al Mulayz",
    "wof:placetype":"locality"
},
  "geometry": {"coordinates":[33.14865,30.42662],"type":"Point"}
}