{
  "type": "Feature",
  "properties": {
    "gn:admin1_code":"20",
    "gn:asciiname":"`Izbat Abu Jabal",
    "gn:country_code":"EG",
    "gn:dem":4,
    "gn:feature_class":"P",
    "gn:feature_code":"PPL",
    "gn:name":"\u2018Izbat Ab\u016b Jabal",
    "gn:population":0,
    "gn:timezone":"Africa/Cairo",
    "iso:country":"EG",
    "name:ara_x_preferred":[
        "\u0639\u0632\u0628\u0629 \u0623\u0628\u0648 \u062c\u0628\u0644"
    ],
    "name:und_x_variant":[
        "\u2018Izbat Ab\u016b Jabal"
    ],
    "wof:name":"`Izbat Abu Jabal",
    "wof:placetype":"locality"
},
  "geometry": {"coordinates":[31.6509,31.4061],"type":"Point"}
}