{
  "type": "Feature",
  "properties": {
    "gn:admin1_code":"04",
    "gn:asciiname":"Ar Rawdah",
    "gn:country_code":"EG",
    "gn:dem":-5,
    "gn:feature_class":"P",
    "gn:feature_code":"PPL",
    "gn:name":"Ar Raw\u1e11ah",
    "gn:population":0,
    "gn:timezone":"Africa/Cairo",
    "iso:country":"EG",
    "name:und_x_variant":[
        "Er R\u014dda",
        "El-R\u00f4da",
        "Ar Raw\u1e11ah"
    ],
    "wof:name":"Ar Rawdah",
    "wof:placetype":"locality"
},
  "geometry": {"coordinates":[31.00112,29.44554],"type":"Point"}
}