{
  "type": "Feature",
  "properties": {
    "gn:admin1_code":"01",
    "gn:asciiname":"Mit Badr Khamis",
    "gn:country_code":"EG",
    "gn:dem":13,
    "gn:feature_class":"P",
    "gn:feature_code":"PPL",
    "gn:name":"M\u012bt Badr Kham\u012bs",
    "gn:population":0,
    "gn:timezone":"Africa/Cairo",
    "iso:country":"EG",
    "name:ara_x_preferred":[
        "\u0645\u064a\u062a \u0628\u062f\u0631 \u062e\u0645\u064a\u0633"
    ],
    "name:und_x_variant":[
        "M\u012bt Badr Kham\u012bs",
        "M\u00eet Badr Kham\u00ees"
    ],
    "wof:name":"Mit Badr Khamis",
    "wof:placetype":"locality"
},
  "geometry": {"coordinates":[31.33865,31.03527],"type":"Point"}
}