{
  "type": "Feature",
  "properties": {
    "gn:admin1_code":"01",
    "gn:asciiname":"`Izbat Jimyanah",
    "gn:country_code":"EG",
    "gn:dem":9,
    "gn:feature_class":"P",
    "gn:feature_code":"PPL",
    "gn:name":"\u2018Izbat Jimy\u0101nah",
    "gn:population":0,
    "gn:timezone":"Africa/Cairo",
    "iso:country":"EG",
    "name:ara_x_preferred":[
        "\u0639\u0632\u0628\u0629 \u062c\u0645\u064a\u0627\u0646\u0629"
    ],
    "name:und_x_variant":[
        "\u2018Izbat Jimy\u0101nah",
        "Gumy\u00e2na"
    ],
    "wof:name":"`Izbat Jimyanah",
    "wof:placetype":"locality"
},
  "geometry": {"coordinates":[31.39765,31.29408],"type":"Point"}
}