{
  "type": "Feature",
  "properties": {
    "iso:country":"EG",
    "name:unk_x_variant":[
        "Az Zirb\u012b"
    ],
    "qs:gn_country":"EG",
    "qs:gn_fcode":"PPL",
    "qs:gn_pop":0,
    "qs:name":"Dar as Salam",
    "qs:name_adm0":"\u0645\u0635\u0631",
    "qs:name_adm1":"\u0627\u0644\u0642\u0627\u0647\u0631\u0629",
    "qs:photos":602,
    "qs:photos_1k":122,
    "qs:photos_9k":3,
    "qs:photos_9r":5,
    "qs:photos_all":602,
    "qs:photos_sr":8,
    "qs:placetype":"Town",
    "qs:pop_sr":"0",
    "qs:woe_adm0":23424802,
    "wof:name":"Dar as Salam",
    "wof:placetype":"locality"
},
  "geometry": {"coordinates":[30.92677,29.4233],"type":"Point"}
}