{
  "type": "Feature",
  "properties": {
    "gn:admin1_code":"3.0",
    "gn:asciiname":"Sindiyun",
    "gn:country_code":"EG",
    "gn:dem":12,
    "gn:feature_class":"P",
    "gn:feature_code":"PPL",
    "gn:name":"Sindiy\u016bn",
    "gn:population":0,
    "gn:timezone":"Africa/Cairo",
    "iso:country":"EG",
    "name:ara_x_preferred":[
        "\u0633\u0646\u062f\u064a\u0648\u0646"
    ],
    "name:und_x_variant":[
        "Sindiy\u016bn"
    ],
    "wof:name":"Sindiyun",
    "wof:placetype":"locality"
},
  "geometry": {"coordinates":[30.51297000000001,31.22943],"type":"Point"}
}