{
  "type": "Feature",
  "properties": {
    "iso:country":"EG",
    "name:unk_x_variant":[
        "El Kilh Gharb"
    ],
    "qs:gn_country":"EG",
    "qs:gn_fcode":"PPL",
    "qs:gn_pop":0,
    "qs:name":"Al Kilh Gharb",
    "qs:name_adm0":"\u0645\u0635\u0631",
    "qs:name_adm1":"\u0627\u0633\u0648\u0627\u0646",
    "qs:photos":152,
    "qs:photos_1k":31,
    "qs:photos_9k":1,
    "qs:photos_9r":4,
    "qs:photos_all":152,
    "qs:photos_sr":4,
    "qs:placetype":"Town",
    "qs:pop_sr":"0",
    "qs:woe_adm0":23424802,
    "wof:name":"Al Kilh Gharb",
    "wof:placetype":"locality"
},
  "geometry": {"coordinates":[32.8361,25.0637],"type":"Point"}
}