{
  "type": "Feature",
  "properties": {
    "gn:admin1_code":"21",
    "gn:asciiname":"`Izbat Nuwaysh",
    "gn:country_code":"EG",
    "gn:dem":7,
    "gn:feature_class":"P",
    "gn:feature_code":"PPL",
    "gn:name":"\u2018Izbat Nuwaysh",
    "gn:population":0,
    "gn:timezone":"Africa/Cairo",
    "iso:country":"EG",
    "name:ara_x_preferred":[
        "\u0639\u0632\u0628\u0629 \u0646\u0648\u064a\u0634"
    ],
    "name:und_x_variant":[
        "\u2018Izbat Nuwaysh"
    ],
    "wof:name":"`Izbat Nuwaysh",
    "wof:placetype":"locality"
},
  "geometry": {"coordinates":[30.79732000000001,31.17724],"type":"Point"}
}