{
  "type": "Feature",
  "properties": {
    "gn:admin1_code":"04",
    "gn:asciiname":"`Izbat as Sa`ayidah",
    "gn:country_code":"EG",
    "gn:dem":-40,
    "gn:feature_class":"P",
    "gn:feature_code":"PPL",
    "gn:name":"\u2018Izbat a\u015f \u015ea\u2018\u0101yidah",
    "gn:population":0,
    "gn:timezone":"Africa/Cairo",
    "iso:country":"EG",
    "name:und_x_variant":[
        "\u2018Ezbet el-\u1e62a \u2018\u00e2yda el-Ba\u1e25ar\u00eeya",
        "\u2018Izbat a\u015f \u015ea\u2018\u0101yidah"
    ],
    "wof:name":"`Izbat as Sa`ayidah",
    "wof:placetype":"locality"
},
  "geometry": {"coordinates":[30.6555,29.43253],"type":"Point"}
}