{
  "type": "Feature",
  "properties": {
    "gn:admin1_code":"03",
    "gn:asciiname":"Abu al Matamir al Bahri",
    "gn:country_code":"EG",
    "gn:dem":0,
    "gn:feature_class":"P",
    "gn:feature_code":"PPL",
    "gn:name":"Ab\u016b al Ma\u0163\u0101m\u012br al Ba\u1e29r\u012b",
    "gn:population":0,
    "gn:timezone":"Africa/Cairo",
    "iso:country":"EG",
    "name:und_x_variant":[
        "Abu el-Ma\u1e6d\u00e2m\u00eer el-Ba\u1e25ari",
        "Ab\u016b al Ma\u0163\u0101m\u012br al Ba\u1e29r\u012b"
    ],
    "wof:name":"Abu al Matamir al Bahri",
    "wof:placetype":"locality"
},
  "geometry": {"coordinates":[30.13454,30.91899],"type":"Point"}
}