{
  "type": "Feature",
  "properties": {
    "gn:admin1_code":"14",
    "gn:asciiname":"Sinjaha",
    "gn:country_code":"EG",
    "gn:dem":11,
    "gn:feature_class":"P",
    "gn:feature_code":"PPL",
    "gn:name":"Sinjah\u0101",
    "gn:population":0,
    "gn:timezone":"Africa/Cairo",
    "iso:country":"EG",
    "name:ara_x_preferred":[
        "\u0633\u0646\u062c\u0647\u0627"
    ],
    "name:und_x_variant":[
        "Sanjah\u0101",
        "Sangaha",
        "Sinjah\u0101"
    ],
    "wof:name":"Sinjaha",
    "wof:placetype":"locality"
},
  "geometry": {"coordinates":[31.63937,30.84602000000001],"type":"Point"}
}