{
  "type": "Feature",
  "properties": {
    "gn:admin1_code":"22",
    "gn:asciiname":"`Izbat Tanati",
    "gn:country_code":"EG",
    "gn:dem":-12,
    "gn:feature_class":"P",
    "gn:feature_code":"PPL",
    "gn:name":"\u2018Izbat \u0162an\u0101\u0163\u012b",
    "gn:population":0,
    "gn:timezone":"Africa/Cairo",
    "iso:country":"EG",
    "name:und_x_variant":[
        "Ezbet \u1e6can\u00e2tti",
        "\u2018Izbat \u0162an\u0101\u0163\u012b"
    ],
    "wof:name":"`Izbat Tanati",
    "wof:placetype":"locality"
},
  "geometry": {"coordinates":[25.56667,29.18333],"type":"Point"}
}