{
  "type": "Feature",
  "properties": {
    "gn:admin1_code":"21",
    "gn:asciiname":"`Izbat al Hamrah",
    "gn:country_code":"EG",
    "gn:dem":2,
    "gn:feature_class":"P",
    "gn:feature_code":"PPLF",
    "gn:name":"\u2018Izbat al \u1e28amrah",
    "gn:population":0,
    "gn:timezone":"Africa/Cairo",
    "iso:country":"EG",
    "name:ara_x_preferred":[
        "\u0639\u0632\u0628\u0629 \u0627\u0644\u062d\u0645\u0631\u0629"
    ],
    "name:und_x_variant":[
        "\u2018Izbat al \u1e28amrah",
        "\u2018Izbat al-\u1e24amrah"
    ],
    "wof:name":"`Izbat al Hamrah",
    "wof:placetype":"locality"
},
  "geometry": {"coordinates":[31.2548,31.24704],"type":"Point"}
}