{
  "type": "Feature",
  "properties": {
    "gn:admin1_code":"12",
    "gn:asciiname":"Kafr al `Arab",
    "gn:country_code":"EG",
    "gn:dem":18,
    "gn:feature_class":"P",
    "gn:feature_code":"PPL",
    "gn:name":"Kafr al \u2018Arab",
    "gn:population":0,
    "gn:timezone":"Africa/Cairo",
    "iso:country":"EG",
    "name:ara_x_preferred":[
        "\u0643\u0641\u0631 \u0627\u0644\u0639\u0631\u0628"
    ],
    "name:und_x_variant":[
        "Kafr el-\u2018Arab",
        "Kafr al \u2018Arab"
    ],
    "wof:name":"Kafr al `Arab",
    "wof:placetype":"locality"
},
  "geometry": {"coordinates":[31.22677,30.40862000000001],"type":"Point"}
}