{
  "type": "Feature",
  "properties": {
    "gn:admin1_code":"03",
    "gn:asciiname":"Qaryat al Amal",
    "gn:country_code":"EG",
    "gn:dem":-5,
    "gn:feature_class":"P",
    "gn:feature_code":"PPL",
    "gn:name":"Qaryat al Amal",
    "gn:population":0,
    "gn:timezone":"Africa/Cairo",
    "iso:country":"EG",
    "name:ara_x_preferred":[
        "\u0642\u0631\u064a\u0629 \u0627\u0644\u0627\u0645\u0644"
    ],
    "wof:name":"Qaryat al Amal",
    "wof:placetype":"locality"
},
  "geometry": {"coordinates":[29.94255,31.0533],"type":"Point"}
}