{
  "type": "Feature",
  "properties": {
    "gn:admin1_code":"09",
    "gn:asciiname":"Shanawan",
    "gn:country_code":"EG",
    "gn:dem":14,
    "gn:feature_class":"P",
    "gn:feature_code":"PPL",
    "gn:name":"Shanaw\u0101n",
    "gn:population":0,
    "gn:timezone":"Africa/Cairo",
    "iso:country":"EG",
    "name:aka_x_preferred":[
        "Shanawan"
    ],
    "name:ara_x_preferred":[
        "\u0634\u0646\u0648\u0627\u0646"
    ],
    "name:pol_x_preferred":[
        "Szanawan"
    ],
    "name:und_x_variant":[
        "Shanaw\u00e2n",
        "Shanaw\u0101n"
    ],
    "wof:name":"Shanawan",
    "wof:placetype":"locality"
},
  "geometry": {"coordinates":[31.00702,30.50162000000001],"type":"Point"}
}