{
  "type": "Feature",
  "properties": {
    "gn:admin1_code":"12",
    "gn:asciiname":"`Izbat Ibrahim Hassan",
    "gn:country_code":"EG",
    "gn:dem":13,
    "gn:feature_class":"P",
    "gn:feature_code":"PPL",
    "gn:name":"\u2018Izbat Ibr\u0101h\u012bm \u1e28assan",
    "gn:population":0,
    "gn:timezone":"Africa/Cairo",
    "iso:country":"EG",
    "name:ara_x_preferred":[
        "\u0639\u0632\u0628\u0629 \u0627\u0628\u0631\u0627\u0647\u064a\u0645 \u062d\u0633\u0646"
    ],
    "name:und_x_variant":[
        "\u2018Izbat Ibr\u0101h\u012bm \u1e28assan"
    ],
    "wof:name":"`Izbat Ibrahim Hassan",
    "wof:placetype":"locality"
},
  "geometry": {"coordinates":[31.19027,30.52021],"type":"Point"}
}