{
  "type": "Feature",
  "properties": {
    "gn:admin1_code":"14",
    "gn:asciiname":"At Tall al Ahmar",
    "gn:country_code":"EG",
    "gn:dem":11,
    "gn:feature_class":"P",
    "gn:feature_code":"PPL",
    "gn:name":"At Tall al A\u1e29mar",
    "gn:population":0,
    "gn:timezone":"Africa/Cairo",
    "iso:country":"EG",
    "name:ara_x_preferred":[
        "\u0627\u0644\u062a\u0644 \u0627\u0644\u0627\u062d\u0645\u0631"
    ],
    "name:und_x_variant":[
        "At Tall al A\u1e29mar"
    ],
    "wof:name":"At Tall al Ahmar",
    "wof:placetype":"locality"
},
  "geometry": {"coordinates":[31.62148,30.64422],"type":"Point"}
}