{
  "type": "Feature",
  "properties": {
    "gn:admin1_code":"05",
    "gn:asciiname":"Ad Dababishah",
    "gn:country_code":"EG",
    "gn:dem":12,
    "gn:feature_class":"P",
    "gn:feature_code":"PPL",
    "gn:name":"A\u1e11 \u1e10ab\u0101bishah",
    "gn:population":0,
    "gn:timezone":"Africa/Cairo",
    "iso:country":"EG",
    "name:und_x_variant":[
        "El-Dab\u00e2bsha",
        "A\u1e11 \u1e10ab\u0101bishah"
    ],
    "wof:name":"Ad Dababishah",
    "wof:placetype":"locality"
},
  "geometry": {"coordinates":[31.18229,30.69122],"type":"Point"}
}