{
  "type": "Feature",
  "properties": {
    "gn:admin1_code":"21",
    "gn:asciiname":"`Izbat Yusuf Habib",
    "gn:country_code":"EG",
    "gn:dem":3,
    "gn:feature_class":"P",
    "gn:feature_code":"PPL",
    "gn:name":"\u2018Izbat Y\u016bsuf \u1e28ab\u012bb",
    "gn:population":0,
    "gn:timezone":"Africa/Cairo",
    "iso:country":"EG",
    "name:ara_x_preferred":[
        "\u0639\u0632\u0628\u0629 \u064a\u0648\u0633\u0641 \u062d\u0628\u064a\u0628"
    ],
    "name:und_x_variant":[
        "\u2018Izbat Y\u016bsuf \u1e28ab\u012bb"
    ],
    "wof:name":"`Izbat Yusuf Habib",
    "wof:placetype":"locality"
},
  "geometry": {"coordinates":[30.62799,31.20361],"type":"Point"}
}