{
  "type": "Feature",
  "properties": {
    "gn:admin1_code":"03",
    "gn:asciiname":"`Ezbet Shiha",
    "gn:country_code":"EG",
    "gn:dem":3,
    "gn:feature_class":"P",
    "gn:feature_code":"PPL",
    "gn:name":"\u2018Ezbet Sh\u00eeha",
    "gn:population":0,
    "gn:timezone":"Africa/Cairo",
    "iso:country":"EG",
    "wof:name":"`Ezbet Shiha",
    "wof:placetype":"locality"
},
  "geometry": {"coordinates":[30.46028,30.94889],"type":"Point"}
}