{
  "type": "Feature",
  "properties": {
    "gn:admin1_code":"21",
    "gn:asciiname":"`Izbat al Hajj Yusuf",
    "gn:country_code":"EG",
    "gn:dem":3,
    "gn:feature_class":"P",
    "gn:feature_code":"PPL",
    "gn:name":"\u2018Izbat al \u1e28\u0101jj Y\u016bsuf",
    "gn:population":0,
    "gn:timezone":"Africa/Cairo",
    "iso:country":"EG",
    "name:ara_x_preferred":[
        "\u0639\u0632\u0628\u0629 \u0627\u0644\u062d\u0627\u062c \u064a\u0648\u0633\u0641"
    ],
    "name:und_x_variant":[
        "\u2018Izbat al \u1e28\u0101jj Y\u016bsif",
        "\u2018Izbat al \u1e28\u0101jj Y\u016bsuf"
    ],
    "wof:name":"`Izbat al Hajj Yusuf",
    "wof:placetype":"locality"
},
  "geometry": {"coordinates":[31.02818,31.29121],"type":"Point"}
}