{
  "type": "Feature",
  "properties": {
    "gn:admin1_code":"27",
    "gn:asciiname":"Qaryat at Tulul",
    "gn:country_code":"EG",
    "gn:dem":3,
    "gn:feature_class":"P",
    "gn:feature_code":"PPL",
    "gn:name":"Qaryat at Tul\u016bl",
    "gn:population":0,
    "gn:timezone":"Africa/Cairo",
    "iso:country":"EG",
    "name:ara_x_preferred":[
        "\u0642\u0631\u064a\u0629 \u0627\u0644\u062a\u0644\u0648\u0644"
    ],
    "name:und_x_variant":[
        "Qaryat el- Til\u00fbl",
        "Qaryat at Til\u016bl",
        "Qaryat at Tul\u016bl"
    ],
    "wof:name":"Qaryat at Tulul",
    "wof:placetype":"locality"
},
  "geometry": {"coordinates":[33.2281,31.05454000000001],"type":"Point"}
}