{
  "type": "Feature",
  "properties": {
    "gn:admin1_code":"05",
    "gn:asciiname":"Kafr Mit al Harun",
    "gn:country_code":"EG",
    "gn:dem":16,
    "gn:feature_class":"P",
    "gn:feature_code":"PPL",
    "gn:name":"Kafr M\u012bt al \u1e28\u0101r\u016bn",
    "gn:population":0,
    "gn:timezone":"Africa/Cairo",
    "iso:country":"EG",
    "name:ara_x_preferred":[
        "\u0643\u0641\u0631 \u0645\u064a\u062a \u0627\u0644\u062d\u0627\u0631\u0648\u0646"
    ],
    "name:und_x_variant":[
        "Kafr M\u00eet el-\u1e24\u00e2r\u00fbn",
        "Kafr M\u012bt al \u1e28\u0101r\u016bn"
    ],
    "wof:name":"Kafr Mit al Harun",
    "wof:placetype":"locality"
},
  "geometry": {"coordinates":[31.25413,30.61117],"type":"Point"}
}