{
  "type": "Feature",
  "properties": {
    "gn:admin1_code":"01",
    "gn:asciiname":"`Izbat Mustafa Fawdah",
    "gn:country_code":"EG",
    "gn:dem":8,
    "gn:feature_class":"P",
    "gn:feature_code":"PPL",
    "gn:name":"\u2018Izbat Mu\u015f\u0163af\u00e1 Fawdah",
    "gn:population":0,
    "gn:timezone":"Africa/Cairo",
    "iso:country":"EG",
    "name:ara_x_preferred":[
        "\u0639\u0632\u0628\u0629 \u0645\u0635\u0637\u0641\u0649 \u0641\u0648\u062f\u0647"
    ],
    "name:und_x_variant":[
        "\u2018Izbat Mu\u015f\u0163af\u00e1 Fawdah",
        "\u2018Izbat Mu\u015f\u0163af\u00e1 F\u016bdah",
        "\u2018Iz. Mu\u1e63\u1e6dafa\u2019 F\u016bdah"
    ],
    "wof:name":"`Izbat Mustafa Fawdah",
    "wof:placetype":"locality"
},
  "geometry": {"coordinates":[31.4454,30.84168],"type":"Point"}
}