{
  "type": "Feature",
  "properties": {
    "gn:admin1_code":"09",
    "gn:asciiname":"Kafr al Hima",
    "gn:country_code":"EG",
    "gn:dem":21,
    "gn:feature_class":"P",
    "gn:feature_code":"PPL",
    "gn:name":"Kafr al \u1e28im\u0101",
    "gn:population":0,
    "gn:timezone":"Africa/Cairo",
    "iso:country":"EG",
    "name:ara_x_preferred":[
        "\u0643\u0641\u0631 \u0627\u0644\u062d\u0645\u0627"
    ],
    "name:und_x_variant":[
        "Kafr el-Hima",
        "Kafr al \u2019im\u0101\u2019",
        "Kafr al \u1e28im\u0101"
    ],
    "wof:name":"Kafr al Hima",
    "wof:placetype":"locality"
},
  "geometry": {"coordinates":[31.09228,30.29827],"type":"Point"}
}