{
  "type": "Feature",
  "properties": {
    "gn:admin1_code":"04",
    "gn:asciiname":"`Ezbet Kuraiyim",
    "gn:country_code":"EG",
    "gn:dem":9,
    "gn:feature_class":"P",
    "gn:feature_code":"PPL",
    "gn:name":"\u2018Ezbet Kura\u00eeyim",
    "gn:population":0,
    "gn:timezone":"Africa/Cairo",
    "iso:country":"EG",
    "wof:name":"`Ezbet Kuraiyim",
    "wof:placetype":"locality"
},
  "geometry": {"coordinates":[30.63333,29.25],"type":"Point"}
}