{
  "type": "Feature",
  "properties": {
    "gn:admin1_code":"03",
    "gn:asciiname":"`Izbat Dayramis",
    "gn:country_code":"EG",
    "gn:dem":2,
    "gn:feature_class":"P",
    "gn:feature_code":"PPL",
    "gn:name":"\u2018Izbat Dayr\u0101mis",
    "gn:population":0,
    "gn:timezone":"Africa/Cairo",
    "iso:country":"EG",
    "name:ara_x_preferred":[
        "\u0639\u0632\u0628\u0629 \u062f\u064a\u0631\u0627\u0645\u0633"
    ],
    "name:und_x_variant":[
        "Deir Ams",
        "Dayr Ams",
        "\u2018Izbat Dayr\u0101mis"
    ],
    "wof:name":"`Izbat Dayramis",
    "wof:placetype":"locality"
},
  "geometry": {"coordinates":[30.32161,31.03288],"type":"Point"}
}