{
  "type": "Feature",
  "properties": {
    "gn:admin1_code":"10",
    "gn:asciiname":"Bani Ghani",
    "gn:country_code":"EG",
    "gn:dem":38,
    "gn:feature_class":"P",
    "gn:feature_code":"PPL",
    "gn:name":"Ban\u012b Ghan\u012b",
    "gn:population":0,
    "gn:timezone":"Africa/Cairo",
    "iso:country":"EG",
    "name:und_x_variant":[
        "Beni Ghani",
        "Ban\u012b Ghan\u012b"
    ],
    "wof:name":"Bani Ghani",
    "wof:placetype":"locality"
},
  "geometry": {"coordinates":[30.66988,28.24968],"type":"Point"}
}