{
  "type": "Feature",
  "properties": {
    "gn:admin1_code":"01",
    "gn:asciiname":"`Izbat `Asim",
    "gn:country_code":"EG",
    "gn:dem":6,
    "gn:feature_class":"P",
    "gn:feature_code":"PPL",
    "gn:name":"\u2018Izbat \u2018\u0100\u015fim",
    "gn:population":0,
    "gn:timezone":"Africa/Cairo",
    "iso:country":"EG",
    "name:ara_x_preferred":[
        "\u0639\u0632\u0628\u0629 \u0639\u0627\u0635\u0645"
    ],
    "name:und_x_variant":[
        "\u2018Izbat \u2018\u0100\u015fim"
    ],
    "wof:name":"`Izbat `Asim",
    "wof:placetype":"locality"
},
  "geometry": {"coordinates":[31.54132,30.94218],"type":"Point"}
}