{
  "type": "Feature",
  "properties": {
    "gn:admin1_code":"14",
    "gn:asciiname":"Manshiyat al Fuli al Kabirah",
    "gn:country_code":"EG",
    "gn:dem":8,
    "gn:feature_class":"P",
    "gn:feature_code":"PPL",
    "gn:name":"Mansh\u012byat al F\u016bl\u012b al Kab\u012brah",
    "gn:population":0,
    "gn:timezone":"Africa/Cairo",
    "iso:country":"EG",
    "name:und_x_variant":[
        "Minsh\u0101t Mu\u015f\u0163af\u00e1 \u1e28usayn al F\u016bl\u012b",
        "Mansh\u012byat al F\u016bl\u012b al Kab\u012brah"
    ],
    "wof:name":"Manshiyat al Fuli al Kabirah",
    "wof:placetype":"locality"
},
  "geometry": {"coordinates":[31.92979,30.92544],"type":"Point"}
}