{
  "type": "Feature",
  "properties": {
    "gn:admin1_code":"05",
    "gn:asciiname":"`Izbat Manshiyat an Nasr",
    "gn:country_code":"EG",
    "gn:dem":13,
    "gn:feature_class":"P",
    "gn:feature_code":"PPL",
    "gn:name":"\u2018Izbat Mansh\u012byat an Na\u015fr",
    "gn:population":0,
    "gn:timezone":"Africa/Cairo",
    "iso:country":"EG",
    "name:ara_x_preferred":[
        "\u0639\u0632\u0628\u0629 \u0645\u0646\u0634\u064a\u0629 \u0627\u0644\u0646\u0635\u0631"
    ],
    "name:und_x_variant":[
        "\u2018Izbat Mansh\u012byat an Na\u015fr",
        "\u2018Izbat Manshiyyat an-Na\u1e63r"
    ],
    "wof:name":"`Izbat Manshiyat an Nasr",
    "wof:placetype":"locality"
},
  "geometry": {"coordinates":[30.94669,30.75907],"type":"Point"}
}