{
  "type": "Feature",
  "properties": {
    "gn:admin1_code":"01",
    "gn:asciiname":"`Izbat Na`im `Ali Hindi",
    "gn:country_code":"EG",
    "gn:dem":5,
    "gn:feature_class":"P",
    "gn:feature_code":"PPL",
    "gn:name":"\u2018Izbat Na\u2018\u012bm \u2018Al\u012b Hind\u012b",
    "gn:population":0,
    "gn:timezone":"Africa/Cairo",
    "iso:country":"EG",
    "name:ara_x_preferred":[
        "\u0639\u0632\u0628\u0629 \u0646\u0639\u064a\u0645 \u0639\u0644\u064a \u0647\u0646\u062f\u064a"
    ],
    "name:und_x_variant":[
        "\u2018Izbat Na\u2018\u012bm \u2018Al\u012b Hind\u012b",
        "\u2018Iz. Na\u2018\u012bm \u2018Al\u012b Hind\u012b"
    ],
    "wof:name":"`Izbat Na`im `Ali Hindi",
    "wof:placetype":"locality"
},
  "geometry": {"coordinates":[31.71846,31.04129],"type":"Point"}
}