{
  "type": "Feature",
  "properties": {
    "gn:admin1_code":"14",
    "gn:asciiname":"`Izbat al Halayifah",
    "gn:country_code":"EG",
    "gn:dem":8,
    "gn:feature_class":"P",
    "gn:feature_code":"PPL",
    "gn:name":"\u2018Izbat al \u1e28al\u0101yifah",
    "gn:population":0,
    "gn:timezone":"Africa/Cairo",
    "iso:country":"EG",
    "name:ara_x_preferred":[
        "\u0639\u0632\u0628\u0629 \u0627\u0644\u062d\u0644\u0627\u064a\u0641\u0629"
    ],
    "name:und_x_variant":[
        "\u2018Izbat al \u1e28al\u0101yifah",
        "\u2018Izbat al \u1e28al\u0101yfah"
    ],
    "wof:name":"`Izbat al Halayifah",
    "wof:placetype":"locality"
},
  "geometry": {"coordinates":[31.71105,30.64231],"type":"Point"}
}