{
  "type": "Feature",
  "properties": {
    "gn:admin1_code":"03",
    "gn:asciiname":"`Izbat Ahmad Kishk",
    "gn:country_code":"EG",
    "gn:dem":6,
    "gn:feature_class":"P",
    "gn:feature_code":"PPL",
    "gn:name":"\u2018Izbat A\u1e29mad Kishk",
    "gn:population":0,
    "gn:timezone":"Africa/Cairo",
    "iso:country":"EG",
    "name:ara_x_preferred":[
        "\u0639\u0632\u0628\u0629 \u0623\u062d\u0645\u062f \u0643\u0634\u0643"
    ],
    "name:und_x_variant":[
        "\u2018Izbat A\u1e29mad Kishk"
    ],
    "wof:name":"`Izbat Ahmad Kishk",
    "wof:placetype":"locality"
},
  "geometry": {"coordinates":[30.54575,31.16495],"type":"Point"}
}