{
  "type": "Feature",
  "properties": {
    "gn:admin1_code":"14",
    "gn:asciiname":"`Izbat Muhammad al Barad`i al Qibliyah",
    "gn:country_code":"EG",
    "gn:dem":2,
    "gn:feature_class":"P",
    "gn:feature_code":"PPL",
    "gn:name":"\u2018Izbat Mu\u1e29ammad al Bar\u0101d\u2018\u012b al Qibl\u012byah",
    "gn:population":0,
    "gn:timezone":"Africa/Cairo",
    "iso:country":"EG",
    "name:ara_x_preferred":[
        "\u0639\u0632\u0628\u0629 \u0645\u062d\u0645\u062f \u0627\u0644\u0628\u0631\u0627\u062f\u0639\u064a \u0627\u0644\u0642\u0628\u0644\u064a\u0629"
    ],
    "name:und_x_variant":[
        "\u2018Izbat Mu\u1e29ammad al Bar\u0101d\u2018\u012b al Qibl\u012byah",
        "\u2018Izbat Muhammad al-Bar\u0101d\u2018\u012b al-Qibliyyah"
    ],
    "wof:name":"`Izbat Muhammad al Barad`i al Qibliyah",
    "wof:placetype":"locality"
},
  "geometry": {"coordinates":[31.93253,31.02866],"type":"Point"}
}