{
  "type": "Feature",
  "properties": {
    "gn:admin1_code":"01",
    "gn:asciiname":"Ghazalah",
    "gn:country_code":"EG",
    "gn:dem":10,
    "gn:feature_class":"P",
    "gn:feature_code":"PPL",
    "gn:name":"Ghaz\u0101lah",
    "gn:population":0,
    "gn:timezone":"Africa/Cairo",
    "iso:country":"EG",
    "name:ara_x_preferred":[
        "\u063a\u0632\u0627\u0644\u0629"
    ],
    "name:und_x_variant":[
        "Ghaz\u00e2la",
        "Ghaz\u0101lah"
    ],
    "wof:name":"Ghazalah",
    "wof:placetype":"locality"
},
  "geometry": {"coordinates":[31.6023,30.87051],"type":"Point"}
}