{
  "type": "Feature",
  "properties": {
    "gn:admin1_code":"21",
    "gn:asciiname":"`Izbah Raqm Thalathah wa Khamsun",
    "gn:country_code":"EG",
    "gn:dem":3,
    "gn:feature_class":"P",
    "gn:feature_code":"PPL",
    "gn:name":"\u2018Izbah Raqm Thal\u0101thah wa Khams\u016bn",
    "gn:population":0,
    "gn:timezone":"Africa/Cairo",
    "iso:country":"EG",
    "name:ara_x_preferred":[
        "\u0639\u0632\u0628\u0629 \u0631\u0642\u0645 \u0665\u0663"
    ],
    "name:ara_x_variant":[
        "\u0639\u0632\u0628\u0629 \u0631\u0642\u0645 53"
    ],
    "name:und_x_variant":[
        "\u2018Izbah Raqm Thal\u0101thah wa Khams\u016bn",
        "\u2018Izbah Raqm 53"
    ],
    "wof:name":"`Izbah Raqm Thalathah wa Khamsun",
    "wof:placetype":"locality"
},
  "geometry": {"coordinates":[31.05924000000001,31.35034000000001],"type":"Point"}
}