{
  "type": "Feature",
  "properties": {
    "gn:admin1_code":"09",
    "gn:asciiname":"Al `Amirah",
    "gn:country_code":"EG",
    "gn:dem":14,
    "gn:feature_class":"P",
    "gn:feature_code":"PPL",
    "gn:name":"Al \u2018\u0100mirah",
    "gn:population":0,
    "gn:timezone":"Africa/Cairo",
    "iso:country":"EG",
    "name:ara_x_preferred":[
        "\u0627\u0644\u0639\u0627\u0645\u0631\u0629"
    ],
    "name:und_x_variant":[
        "El-\u2018\u00c2mra",
        "Al \u2018\u0100mirah",
        "Al-\u2018\u0100mrah"
    ],
    "wof:name":"Al `Amirah",
    "wof:placetype":"locality"
},
  "geometry": {"coordinates":[30.97957,30.49494],"type":"Point"}
}