{
  "type": "Feature",
  "properties": {
    "gn:admin1_code":"21",
    "gn:asciiname":"Al Khushu`i",
    "gn:country_code":"EG",
    "gn:dem":6,
    "gn:feature_class":"P",
    "gn:feature_code":"PPL",
    "gn:name":"Al Khush\u016b\u2018\u012b",
    "gn:population":0,
    "gn:timezone":"Africa/Cairo",
    "iso:country":"EG",
    "name:und_x_variant":[
        "El-Khush\u00fb\u2018i",
        "Al Khush\u016b\u2018\u012b"
    ],
    "wof:name":"Al Khushu`i",
    "wof:placetype":"locality"
},
  "geometry": {"coordinates":[31.0325,31.59167],"type":"Point"}
}