{
  "type": "Feature",
  "properties": {
    "gn:admin1_code":"21",
    "gn:asciiname":"`Izbat `Abd al Hamid",
    "gn:country_code":"EG",
    "gn:dem":6,
    "gn:feature_class":"P",
    "gn:feature_code":"PPL",
    "gn:name":"\u2018Izbat \u2018Abd al \u1e28am\u012bd",
    "gn:population":0,
    "gn:timezone":"Africa/Cairo",
    "iso:country":"EG",
    "name:ara_x_preferred":[
        "\u0639\u0632\u0628\u0629 \u0639\u0628\u062f \u0627\u0644\u062d\u0645\u064a\u062f"
    ],
    "name:und_x_variant":[
        "\u2018Izbat \u2018Abd al \u1e28am\u012bd",
        "\u2018Izbat \u2018Abd al-\u1e24am\u012bd"
    ],
    "wof:name":"`Izbat `Abd al Hamid",
    "wof:placetype":"locality"
},
  "geometry": {"coordinates":[30.86942,31.07465],"type":"Point"}
}