{
  "type": "Feature",
  "properties": {
    "gn:admin1_code":"04",
    "gn:asciiname":"`Ezbet el-Ra`l el-Kharaba",
    "gn:country_code":"EG",
    "gn:dem":-9,
    "gn:feature_class":"P",
    "gn:feature_code":"PPL",
    "gn:name":"\u2018Ezbet el-R\u00e2\u2018l el-Khar\u00e2ba",
    "gn:population":0,
    "gn:timezone":"Africa/Cairo",
    "iso:country":"EG",
    "wof:name":"`Ezbet el-Ra`l el-Kharaba",
    "wof:placetype":"locality"
},
  "geometry": {"coordinates":[30.46146,29.40698],"type":"Point"}
}