{
  "type": "Feature",
  "properties": {
    "gn:admin1_code":"10",
    "gn:asciiname":"Mawqif al Qays",
    "gn:country_code":"EG",
    "gn:dem":35,
    "gn:feature_class":"P",
    "gn:feature_code":"PPL",
    "gn:name":"Mawqif al Qays",
    "gn:population":0,
    "gn:timezone":"Africa/Cairo",
    "iso:country":"EG",
    "wof:name":"Mawqif al Qays",
    "wof:placetype":"locality"
},
  "geometry": {"coordinates":[30.78333,28.48194],"type":"Point"}
}