{
  "type": "Feature",
  "properties": {
    "gn:admin1_code":"14",
    "gn:asciiname":"`Izbat ash Shawadifi",
    "gn:country_code":"EG",
    "gn:dem":13,
    "gn:feature_class":"P",
    "gn:feature_code":"PPL",
    "gn:name":"\u2018Izbat ash Shaw\u0101dif\u012b",
    "gn:population":0,
    "gn:timezone":"Africa/Cairo",
    "iso:country":"EG",
    "name:ara_x_preferred":[
        "\u0639\u0632\u0628\u0629 \u0627\u0644\u0634\u0648\u0627\u062f\u0641\u064a"
    ],
    "name:und_x_variant":[
        "\u2018Izbat ash Shaw\u0101dif\u012b",
        "\u2018Izbat ash Shaw\u0101df\u012b"
    ],
    "wof:name":"`Izbat ash Shawadifi",
    "wof:placetype":"locality"
},
  "geometry": {"coordinates":[31.59017,30.62547],"type":"Point"}
}