{
  "type": "Feature",
  "properties": {
    "gn:admin1_code":"02",
    "gn:asciiname":"Naj` Kawm Bisaw",
    "gn:country_code":"EG",
    "gn:dem":51,
    "gn:feature_class":"P",
    "gn:feature_code":"PPL",
    "gn:name":"Naj\u2018 Kawm Bis\u0101w",
    "gn:population":0,
    "gn:timezone":"Africa/Cairo",
    "iso:country":"EG",
    "name:und_x_variant":[
        "K\u00f4m Bis\u00e2w",
        "Nag\u2018 K\u00f4m Bis\u00e2w",
        "Naj\u2018 Kawm Bis\u0101w"
    ],
    "wof:name":"Naj` Kawm Bisaw",
    "wof:placetype":"locality"
},
  "geometry": {"coordinates":[31.10502,27.31961],"type":"Point"}
}