{
  "type": "Feature",
  "properties": {
    "gn:admin1_code":"03",
    "gn:asciiname":"`Izbat Muhammad Badwai",
    "gn:country_code":"EG",
    "gn:dem":-1,
    "gn:feature_class":"P",
    "gn:feature_code":"PPL",
    "gn:name":"\u2018Izbat Mu\u1e29ammad Badwa\u012b",
    "gn:population":0,
    "gn:timezone":"Africa/Cairo",
    "iso:country":"EG",
    "name:ara_x_preferred":[
        "\u0639\u0632\u0628\u0629 \u0645\u062d\u0645\u062f \u0628\u062f\u0648\u064a"
    ],
    "name:und_x_variant":[
        "\u2018Izbat Mu\u1e29ammad Badwa\u012b",
        "\u2018Izbat Mu\u1e25ammad Badaw\u012b"
    ],
    "wof:name":"`Izbat Muhammad Badwai",
    "wof:placetype":"locality"
},
  "geometry": {"coordinates":[30.43041,31.10799],"type":"Point"}
}