{
  "type": "Feature",
  "properties": {
    "gn:admin1_code":"01",
    "gn:asciiname":"`Izbat `Ali Zaki",
    "gn:country_code":"EG",
    "gn:dem":3,
    "gn:feature_class":"P",
    "gn:feature_code":"PPL",
    "gn:name":"\u2018Izbat \u2018Al\u012b Zak\u012b",
    "gn:population":0,
    "gn:timezone":"Africa/Cairo",
    "iso:country":"EG",
    "name:ara_x_preferred":[
        "\u0639\u0632\u0628\u0629 \u0639\u0644\u064a \u0632\u0643\u064a"
    ],
    "name:und_x_variant":[
        "\u2018Izbat \u2018Al\u012b Zak\u012b"
    ],
    "wof:name":"`Izbat `Ali Zaki",
    "wof:placetype":"locality"
},
  "geometry": {"coordinates":[31.8915,31.11973],"type":"Point"}
}