{
  "type": "Feature",
  "properties": {
    "gn:admin1_code":"03",
    "gn:asciiname":"`Izbat Kawm al Kalakh",
    "gn:country_code":"EG",
    "gn:dem":3,
    "gn:feature_class":"P",
    "gn:feature_code":"PPL",
    "gn:name":"\u2018Izbat Kawm al Kalakh",
    "gn:population":0,
    "gn:timezone":"Africa/Cairo",
    "iso:country":"EG",
    "name:und_x_variant":[
        "\u2018Ezbet K\u00f4m el-Kalakh",
        "\u2018Izbat Kawm al Kalakh"
    ],
    "wof:name":"`Izbat Kawm al Kalakh",
    "wof:placetype":"locality"
},
  "geometry": {"coordinates":[30.2325,31.28111],"type":"Point"}
}