{
  "type": "Feature",
  "properties": {
    "gn:admin1_code":"21",
    "gn:asciiname":"Al Wayasifah",
    "gn:country_code":"EG",
    "gn:dem":5,
    "gn:feature_class":"P",
    "gn:feature_code":"PPL",
    "gn:name":"Al Way\u0101sifah",
    "gn:population":0,
    "gn:timezone":"Africa/Cairo",
    "iso:country":"EG",
    "name:ara_x_preferred":[
        "\u0627\u0644\u0648\u064a\u0627\u0633\u0641\u0629"
    ],
    "name:und_x_variant":[
        "El-Way\u00e2sfa",
        "Al Way\u0101sifah",
        "Al-Way\u0101sfah"
    ],
    "wof:name":"Al Wayasifah",
    "wof:placetype":"locality"
},
  "geometry": {"coordinates":[31.01242,31.58365],"type":"Point"}
}