{
  "type": "Feature",
  "properties": {
    "gn:admin1_code":"21",
    "gn:asciiname":"`Izbat as Sanayiwah",
    "gn:country_code":"EG",
    "gn:dem":6,
    "gn:feature_class":"P",
    "gn:feature_code":"PPL",
    "gn:name":"\u2018Izbat as San\u0101yiwah",
    "gn:population":0,
    "gn:timezone":"Africa/Cairo",
    "iso:country":"EG",
    "name:ara_x_preferred":[
        "\u0639\u0632\u0628\u0629 \u0627\u0644\u0633\u0646\u0627\u064a\u0648\u0629"
    ],
    "name:und_x_variant":[
        "\u2018Izbat as San\u0101ywah",
        "\u2018Izbat as San\u0101yiwah"
    ],
    "wof:name":"`Izbat as Sanayiwah",
    "wof:placetype":"locality"
},
  "geometry": {"coordinates":[31.23037,31.25366],"type":"Point"}
}