{
  "type": "Feature",
  "properties": {
    "gn:admin1_code":"08",
    "gn:asciiname":"Al Hajir",
    "gn:country_code":"EG",
    "gn:dem":19,
    "gn:feature_class":"P",
    "gn:feature_code":"PPL",
    "gn:name":"Al \u1e28\u0101jir",
    "gn:population":0,
    "gn:timezone":"Africa/Cairo",
    "iso:country":"EG",
    "name:ara_x_preferred":[
        "\u0627\u0644\u062d\u0627\u062c\u0631"
    ],
    "name:und_x_variant":[
        "El-\u1e24\u00e2gir",
        "\u2018Izbat al Am\u012br \u2018Umar B\u0101sh\u0101",
        "Al \u1e28\u0101jir",
        "Al-\u1e24\u0101jir"
    ],
    "wof:name":"Al Hajir",
    "wof:placetype":"locality"
},
  "geometry": {"coordinates":[30.91149,30.28385],"type":"Point"}
}