{
  "type": "Feature",
  "properties": {
    "gn:admin1_code":"14",
    "gn:asciiname":"`Izbat Wasif",
    "gn:country_code":"EG",
    "gn:dem":13,
    "gn:feature_class":"P",
    "gn:feature_code":"PPL",
    "gn:name":"\u2018Izbat W\u0101\u015fif",
    "gn:population":0,
    "gn:timezone":"Africa/Cairo",
    "iso:country":"EG",
    "name:ara_x_preferred":[
        "\u0639\u0632\u0628\u0629 \u0648\u0627\u0635\u0641"
    ],
    "name:und_x_variant":[
        "\u2018Izbat W\u0101\u015fif"
    ],
    "wof:name":"`Izbat Wasif",
    "wof:placetype":"locality"
},
  "geometry": {"coordinates":[31.69876,30.50176],"type":"Point"}
}