{
  "type": "Feature",
  "properties": {
    "gn:admin1_code":"17",
    "gn:asciiname":"Naj` ash Shaykh Hariz",
    "gn:country_code":"EG",
    "gn:dem":47,
    "gn:feature_class":"P",
    "gn:feature_code":"PPL",
    "gn:name":"Naj\u2018 ash Shaykh \u1e28ar\u012bz",
    "gn:population":0,
    "gn:timezone":"Africa/Cairo",
    "iso:country":"EG",
    "name:und_x_variant":[
        "Nag\u2018 el-Sheikh \u1e24ar\u00eez",
        "Nag\u2018 el Sheikh \u1e24ireiz",
        "Naj\u2018 ash Shaykh \u1e28ar\u012bz"
    ],
    "wof:name":"Naj` ash Shaykh Hariz",
    "wof:placetype":"locality"
},
  "geometry": {"coordinates":[30.85,27.36667000000001],"type":"Point"}
}