{
  "type": "Feature",
  "properties": {
    "gn:admin1_code":"14",
    "gn:asciiname":"Kafr ash Shaykh `Ali",
    "gn:country_code":"EG",
    "gn:dem":11,
    "gn:feature_class":"P",
    "gn:feature_code":"PPL",
    "gn:name":"Kafr ash Shaykh \u2018Al\u012b",
    "gn:population":0,
    "gn:timezone":"Africa/Cairo",
    "iso:country":"EG",
    "name:ara_x_preferred":[
        "\u0643\u0641\u0631 \u0627\u0644\u0634\u064a\u062e \u0639\u0644\u064a"
    ],
    "name:und_x_variant":[
        "Kafr el-Sheikh \u2018Ali",
        "Kafr ash Shaykh \u2018Al\u012b"
    ],
    "wof:name":"Kafr ash Shaykh `Ali",
    "wof:placetype":"locality"
},
  "geometry": {"coordinates":[31.5046,30.79899],"type":"Point"}
}