{
  "type": "Feature",
  "properties": {
    "gn:admin1_code":"04",
    "gn:asciiname":"`Ezbet Muhammad `Ali el- Gharbiya",
    "gn:country_code":"EG",
    "gn:dem":0,
    "gn:feature_class":"P",
    "gn:feature_code":"PPL",
    "gn:name":"\u2018Ezbet Mu\u1e25ammad \u2018Al\u00ee el- Gharb\u00eeya",
    "gn:population":0,
    "gn:timezone":"Africa/Cairo",
    "iso:country":"EG",
    "wof:name":"`Ezbet Muhammad `Ali el- Gharbiya",
    "wof:placetype":"locality"
},
  "geometry": {"coordinates":[30.58333,29.16667],"type":"Point"}
}