{
  "type": "Feature",
  "properties": {
    "gn:admin1_code":"03",
    "gn:asciiname":"`Izbat Abu Farraj",
    "gn:country_code":"EG",
    "gn:dem":-1,
    "gn:feature_class":"P",
    "gn:feature_code":"PPL",
    "gn:name":"\u2018Izbat Ab\u016b Farr\u0101j",
    "gn:population":0,
    "gn:timezone":"Africa/Cairo",
    "iso:country":"EG",
    "wof:name":"`Izbat Abu Farraj",
    "wof:placetype":"locality"
},
  "geometry": {"coordinates":[30.23135,30.92264],"type":"Point"}
}