{
  "type": "Feature",
  "properties": {
    "iso:country":"EG",
    "name:ara_x_preferred":[
        "\u0639\u0648\u0641\u064a\u0631\u0627"
    ],
    "name:azb_x_preferred":[
        "\u0639\u0648\u0641\u06cc\u0631\u0627"
    ],
    "name:ces_x_preferred":[
        "Ofira"
    ],
    "name:eng_x_preferred":[
        "Ofira"
    ],
    "name:fas_x_preferred":[
        "\u0639\u0648\u0641\u06cc\u0631\u0627"
    ],
    "name:heb_x_preferred":[
        "\u05d0\u05d5\u05e4\u05d9\u05e8\u05d4"
    ],
    "name:nld_x_preferred":[
        "Ofira"
    ],
    "qs:gn_pop":0,
    "qs:name":"Ofira",
    "qs:name_adm0":"\u0645\u0635\u0631",
    "qs:name_adm1":"\u062c\u0646\u0648\u0628 \u0633\u064a\u0646\u0627\u0621",
    "qs:photos":5000,
    "qs:photos_1k":1000,
    "qs:photos_9k":22,
    "qs:photos_9r":14,
    "qs:photos_all":5000,
    "qs:photos_sr":24,
    "qs:placetype":"Town",
    "qs:pop_sr":"0",
    "qs:woe_adm0":23424802,
    "wd:wordcount":130,
    "wof:name":"Ofira",
    "wof:placetype":"locality"
},
  "geometry": {"coordinates":[34.318027,27.862477],"type":"Point"}
}