{
  "type": "Feature",
  "properties": {
    "gn:admin1_code":"21",
    "gn:asciiname":"Al Manshiyah al Jadidah",
    "gn:country_code":"EG",
    "gn:dem":2,
    "gn:feature_class":"P",
    "gn:feature_code":"PPL",
    "gn:name":"Al Mansh\u012byah al Jad\u012bdah",
    "gn:population":0,
    "gn:timezone":"Africa/Cairo",
    "iso:country":"EG",
    "name:ara_x_preferred":[
        "\u0627\u0644\u0645\u0646\u0634\u064a\u0629 \u0627\u0644\u062c\u062f\u064a\u062f\u0629"
    ],
    "name:und_x_variant":[
        "Al Mansh\u012byah al Jad\u012bdah"
    ],
    "wof:name":"Al Manshiyah al Jadidah",
    "wof:placetype":"locality"
},
  "geometry": {"coordinates":[30.8837,31.30685],"type":"Point"}
}