{
  "type": "Feature",
  "properties": {
    "gn:admin1_code":"16",
    "gn:asciiname":"Kalabishah",
    "gn:cc2":"EG",
    "gn:country_code":"EG",
    "gn:dem":179,
    "gn:feature_class":"P",
    "gn:feature_code":"PPL",
    "gn:name":"Kal\u0101bishah",
    "gn:population":0,
    "gn:timezone":"Africa/Cairo",
    "iso:country":"EG",
    "name:und_x_variant":[
        "Talmis",
        "Kal\u00e2bsha",
        "Kal\u0101bishah"
    ],
    "wof:name":"Kalabishah",
    "wof:placetype":"locality"
},
  "geometry": {"coordinates":[32.86667,23.55],"type":"Point"}
}