{
  "type": "Feature",
  "properties": {
    "gn:admin1_code":"10",
    "gn:asciiname":"Nazlat Hirz",
    "gn:country_code":"EG",
    "gn:dem":47,
    "gn:feature_class":"P",
    "gn:feature_code":"PPL",
    "gn:name":"Nazlat \u1e28irz",
    "gn:population":0,
    "gn:timezone":"Africa/Cairo",
    "iso:country":"EG",
    "name:und_x_variant":[
        "Nazlet \u1e24irz",
        "Nazlat \u1e28irz"
    ],
    "wof:name":"Nazlat Hirz",
    "wof:placetype":"locality"
},
  "geometry": {"coordinates":[30.77828,27.85644000000001],"type":"Point"}
}