{
  "type": "Feature",
  "properties": {
    "gn:admin1_code":"09",
    "gn:asciiname":"`Izbat al Halawani",
    "gn:country_code":"EG",
    "gn:dem":11,
    "gn:feature_class":"P",
    "gn:feature_code":"PPL",
    "gn:name":"\u2018Izbat al \u1e28alaw\u0101n\u012b",
    "gn:population":0,
    "gn:timezone":"Africa/Cairo",
    "iso:country":"EG",
    "name:ara_x_preferred":[
        "\u0639\u0632\u0628\u0629 \u0627\u0644\u062d\u0644\u0648\u0627\u0646\u064a"
    ],
    "name:und_x_variant":[
        "\u2018Izbat al \u1e28alaw\u0101n\u012b",
        "\u2018Izbat al \u1e24alaw\u0101n\u012b"
    ],
    "wof:name":"`Izbat al Halawani",
    "wof:placetype":"locality"
},
  "geometry": {"coordinates":[30.9779,30.34846],"type":"Point"}
}