{
  "type": "Feature",
  "properties": {
    "gn:admin1_code":"09",
    "gn:asciiname":"Kafr Tanbidi",
    "gn:country_code":"EG",
    "gn:dem":14,
    "gn:feature_class":"P",
    "gn:feature_code":"PPL",
    "gn:name":"Kafr \u0162anbid\u012b",
    "gn:population":0,
    "gn:timezone":"Africa/Cairo",
    "iso:country":"EG",
    "name:und_x_variant":[
        "Kafr \u1e6cambidi",
        "Kafr \u0162anbid\u012b"
    ],
    "wof:name":"Kafr Tanbidi",
    "wof:placetype":"locality"
},
  "geometry": {"coordinates":[30.99998,30.59059],"type":"Point"}
}