{
  "type": "Feature",
  "properties": {
    "iso:country":"EG",
    "qs:gn_pop":0,
    "qs:name":"Ad Dabiyah",
    "qs:name_adm0":"\u0645\u0635\u0631",
    "qs:name_adm1":"\u0642\u0646\u0627",
    "qs:photos":385,
    "qs:photos_1k":78,
    "qs:photos_9k":2,
    "qs:photos_9r":5,
    "qs:photos_all":385,
    "qs:photos_sr":6,
    "qs:placetype":"Town",
    "qs:pop_sr":"0",
    "qs:woe_adm0":23424802,
    "wof:name":"Ad Dabiyah",
    "wof:placetype":"locality"
},
  "geometry": {"coordinates":[32.54495,25.610719],"type":"Point"}
}