{
  "type": "Feature",
  "properties": {
    "gn:admin1_code":"09",
    "gn:asciiname":"Kafr Manawahlah",
    "gn:country_code":"EG",
    "gn:dem":19,
    "gn:feature_class":"P",
    "gn:feature_code":"PPL",
    "gn:name":"Kafr Man\u0101wahlah",
    "gn:population":0,
    "gn:timezone":"Africa/Cairo",
    "iso:country":"EG",
    "name:ara_x_preferred":[
        "\u0643\u0641\u0631 \u0645\u0646\u0627\u0648\u0647\u0644\u0629"
    ],
    "name:und_x_variant":[
        "Kafr Man\u00e2wahla",
        "Kafr Man\u0101wahlah"
    ],
    "wof:name":"Kafr Manawahlah",
    "wof:placetype":"locality"
},
  "geometry": {"coordinates":[31.03577,30.47665],"type":"Point"}
}