{
  "type": "Feature",
  "properties": {
    "gn:admin1_code":"21",
    "gn:asciiname":"`Izbat Rashwan Agha",
    "gn:country_code":"EG",
    "gn:dem":5,
    "gn:feature_class":"P",
    "gn:feature_code":"PPL",
    "gn:name":"\u2018Izbat Rashw\u0101n Agh\u0101",
    "gn:population":0,
    "gn:timezone":"Africa/Cairo",
    "iso:country":"EG",
    "name:ara_x_preferred":[
        "\u0639\u0632\u0628\u0629 \u0631\u0634\u0648\u0627\u0646 \u0623\u063a\u0627"
    ],
    "name:und_x_variant":[
        "\u2018Izbat Rashw\u0101n Agh\u0101",
        "\u2018Izbat Rashw\u0101n \u0100gh\u0101"
    ],
    "wof:name":"`Izbat Rashwan Agha",
    "wof:placetype":"locality"
},
  "geometry": {"coordinates":[30.8721,31.12838],"type":"Point"}
}