{
  "type": "Feature",
  "properties": {
    "gn:admin1_code":"23",
    "gn:asciiname":"Naj` Sitayh",
    "gn:country_code":"EG",
    "gn:dem":81,
    "gn:feature_class":"P",
    "gn:feature_code":"PPL",
    "gn:name":"Naj\u2018 Si\u0163ay\u1e29",
    "gn:population":0,
    "gn:timezone":"Africa/Cairo",
    "iso:country":"EG",
    "name:und_x_variant":[
        "Nag\u2018 Si\u1e6dei\u1e25",
        "Naj\u2018 Si\u0163ay\u1e29"
    ],
    "wof:name":"Naj` Sitayh",
    "wof:placetype":"locality"
},
  "geometry": {"coordinates":[32.49167,25.46722],"type":"Point"}
}