{
  "type": "Feature",
  "properties": {
    "gn:country":"EG",
    "gn:fcode":"PPL",
    "gn:population":53851,
    "iso:country":"EG",
    "name:und_x_variant":[
        "Farshuut"
    ],
    "qs:name":"Farsh\u016b\u0163",
    "qs:photos_9r":0,
    "qs:photos_sr":0,
    "qs:pop_sr":"8",
    "wof:name":"Farsh\u016b\u0163",
    "wof:placetype":"locality",
    "wof:population":53851
},
  "geometry": {"coordinates":[32.16329,26.05494],"type":"Point"}
}