{
  "type": "Feature",
  "properties": {
    "gn:admin1_code":"21",
    "gn:asciiname":"`Izbat Labib `Atiyah",
    "gn:country_code":"EG",
    "gn:dem":3,
    "gn:feature_class":"P",
    "gn:feature_code":"PPL",
    "gn:name":"\u2018Izbat Lab\u012bb \u2018A\u0163\u012byah",
    "gn:population":0,
    "gn:timezone":"Africa/Cairo",
    "iso:country":"EG",
    "name:ara_x_preferred":[
        "\u0639\u0632\u0628\u0629 \u0644\u0628\u064a\u0628 \u0639\u0637\u064a\u0629"
    ],
    "name:und_x_variant":[
        "\u2018Izbat Lab\u012bb \u2018A\u0163\u012byah",
        "\u2018Izbat Lab\u012bb \u2018A\u1e6diyyah"
    ],
    "wof:name":"`Izbat Labib `Atiyah",
    "wof:placetype":"locality"
},
  "geometry": {"coordinates":[30.81665,31.17162],"type":"Point"}
}