{
  "type": "Feature",
  "properties": {
    "gn:admin1_code":"15",
    "gn:asciiname":"Muhammad al `Askari",
    "gn:country_code":"EG",
    "gn:dem":18,
    "gn:feature_class":"P",
    "gn:feature_code":"PPL",
    "gn:name":"Mu\u1e29ammad al \u2018Askar\u012b",
    "gn:population":0,
    "gn:timezone":"Africa/Cairo",
    "iso:country":"EG",
    "name:und_x_variant":[
        "Muh el-\u2019Askari",
        "Mu\u1e29ammad al \u2018Askar\u012b",
        "Mu\u1e29ammad el- \u2018Askari"
    ],
    "wof:name":"Muhammad al `Askari",
    "wof:placetype":"locality"
},
  "geometry": {"coordinates":[32.54322,30.04956],"type":"Point"}
}