{
  "type": "Feature",
  "properties": {
    "gn:admin1_code":"16",
    "gn:asciiname":"Al Kilh",
    "gn:country_code":"EG",
    "gn:dem":89,
    "gn:feature_class":"P",
    "gn:feature_code":"PPL",
    "gn:name":"Al Kil\u1e29",
    "gn:population":0,
    "gn:timezone":"Africa/Cairo",
    "iso:country":"EG",
    "name:und_x_variant":[
        "Kil\u1e25 el Gabal",
        "Kil\u1e29 al Jabal",
        "Al Kil\u1e29"
    ],
    "wof:name":"Al Kilh",
    "wof:placetype":"locality"
},
  "geometry": {"coordinates":[32.83013,25.07096],"type":"Point"}
}