{
  "type": "Feature",
  "properties": {
    "gn:admin1_code":"01",
    "gn:asciiname":"Sharqiyat al Ma`sarah",
    "gn:country_code":"EG",
    "gn:dem":5,
    "gn:feature_class":"P",
    "gn:feature_code":"PPL",
    "gn:name":"Sharq\u012byat al Ma\u2018\u015farah",
    "gn:population":0,
    "gn:timezone":"Africa/Cairo",
    "iso:country":"EG",
    "name:ara_x_preferred":[
        "\u0634\u0631\u0642\u064a\u0629 \u0627\u0644\u0645\u0639\u0635\u0631\u0629"
    ],
    "name:und_x_variant":[
        "Sharq\u012byat al Ma\u2018\u015farah"
    ],
    "wof:name":"Sharqiyat al Ma`sarah",
    "wof:placetype":"locality"
},
  "geometry": {"coordinates":[31.27883,31.29918],"type":"Point"}
}