{
  "type": "Feature",
  "properties": {
    "gn:admin1_code":"24",
    "gn:asciiname":"El `Araba bi Sohag",
    "gn:country_code":"EG",
    "gn:dem":67,
    "gn:feature_class":"P",
    "gn:feature_code":"PPL",
    "gn:name":"El \u2018Araba bi Soh\u00e2g",
    "gn:population":0,
    "gn:timezone":"Africa/Cairo",
    "iso:country":"EG",
    "wof:name":"El `Araba bi Sohag",
    "wof:placetype":"locality"
},
  "geometry": {"coordinates":[31.59068,26.59699],"type":"Point"}
}