{
  "type": "Feature",
  "properties": {
    "gn:admin1_code":"02",
    "gn:asciiname":"Salwa Qibli",
    "gn:country_code":"EG",
    "gn:dem":102,
    "gn:feature_class":"P",
    "gn:feature_code":"PPL",
    "gn:name":"Salw\u00e1 Qibl\u012b",
    "gn:population":0,
    "gn:timezone":"Africa/Cairo",
    "iso:country":"EG",
    "name:und_x_variant":[
        "Silw\u00e1 Qibli",
        "Salw\u00e1 Qibl\u012b"
    ],
    "wof:name":"Salwa Qibli",
    "wof:placetype":"locality"
},
  "geometry": {"coordinates":[32.94679,24.70976],"type":"Point"}
}