{
  "type": "Feature",
  "properties": {
    "gn:admin1_code":"03",
    "gn:asciiname":"`Izbat Qutush",
    "gn:country_code":"EG",
    "gn:dem":-3,
    "gn:feature_class":"P",
    "gn:feature_code":"PPL",
    "gn:name":"\u2018Izbat Qu\u0163\u016bsh",
    "gn:population":0,
    "gn:timezone":"Africa/Cairo",
    "iso:country":"EG",
    "name:ara_x_preferred":[
        "\u0639\u0632\u0628\u0629 \u0642\u0637\u0648\u0634"
    ],
    "name:und_x_variant":[
        "\u2018Izbat Qu\u0163\u016bsh"
    ],
    "wof:name":"`Izbat Qutush",
    "wof:placetype":"locality"
},
  "geometry": {"coordinates":[30.15493,31.0338],"type":"Point"}
}