{
  "type": "Feature",
  "properties": {
    "gn:admin1_code":"15",
    "gn:asciiname":"`Izbat Farhan `Id",
    "gn:country_code":"EG",
    "gn:dem":4,
    "gn:feature_class":"P",
    "gn:feature_code":"PPL",
    "gn:name":"\u2018Izbat Far\u1e29\u0101n \u2018\u012ad",
    "gn:population":0,
    "gn:timezone":"Africa/Cairo",
    "iso:country":"EG",
    "name:und_x_variant":[
        "\u2018Ezbet Far\u1e25\u00e2n \u2018E\u00eed",
        "\u2018Izbat Far\u1e29\u0101n \u2018\u012ad"
    ],
    "wof:name":"`Izbat Farhan `Id",
    "wof:placetype":"locality"
},
  "geometry": {"coordinates":[32.43333,30.21667],"type":"Point"}
}