{
  "type": "Feature",
  "properties": {
    "gn:admin1_code":"11",
    "gn:asciiname":"Kafr ash Shara`inah",
    "gn:country_code":"EG",
    "gn:dem":284,
    "gn:feature_class":"P",
    "gn:feature_code":"PPL",
    "gn:name":"Kafr ash Shar\u0101\u2018inah",
    "gn:population":0,
    "gn:timezone":"Africa/Cairo",
    "iso:country":"EG",
    "name:und_x_variant":[
        "Kafr el-Shar\u00e2\u2018na",
        "Kafr ash Shar\u0101\u2018inah"
    ],
    "wof:name":"Kafr ash Shara`inah",
    "wof:placetype":"locality"
},
  "geometry": {"coordinates":[31.76667,30.05],"type":"Point"}
}