{
  "type": "Feature",
  "properties": {
    "gn:admin1_code":"03",
    "gn:asciiname":"`Izbat al Hadidi",
    "gn:country_code":"EG",
    "gn:dem":2,
    "gn:feature_class":"P",
    "gn:feature_code":"PPL",
    "gn:name":"\u2018Izbat al \u1e28ad\u012bd\u012b",
    "gn:population":0,
    "gn:timezone":"Africa/Cairo",
    "iso:country":"EG",
    "name:ara_x_preferred":[
        "\u0639\u0632\u0628\u0629 \u0627\u0644\u062d\u062f\u064a\u062f\u064a"
    ],
    "name:und_x_variant":[
        "\u2018Izbat al \u1e28ad\u012bd\u012b"
    ],
    "wof:name":"`Izbat al Hadidi",
    "wof:placetype":"locality"
},
  "geometry": {"coordinates":[30.34631,31.17271],"type":"Point"}
}