{
  "type": "Feature",
  "properties": {
    "gn:admin1_code":"14",
    "gn:asciiname":"`Izbat al Hajjajiyah al Qadimah",
    "gn:country_code":"EG",
    "gn:dem":6,
    "gn:feature_class":"P",
    "gn:feature_code":"PPL",
    "gn:name":"\u2018Izbat al \u1e28ajj\u0101j\u012byah al Qad\u012bmah",
    "gn:population":0,
    "gn:timezone":"Africa/Cairo",
    "iso:country":"EG",
    "name:ara_x_preferred":[
        "\u0639\u0632\u0628\u0629 \u0627\u0644\u062d\u062c\u0627\u062c\u064a\u0629 \u0627\u0644\u0642\u062f\u064a\u0645\u0629"
    ],
    "name:und_x_variant":[
        "\u2018Izbat al \u1e28ajj\u0101j\u012byah al Qad\u012bmah",
        "\u2018Izbat al-\u1e24ajj\u0101jiyyah al-Qad\u012bmah"
    ],
    "wof:name":"`Izbat al Hajjajiyah al Qadimah",
    "wof:placetype":"locality"
},
  "geometry": {"coordinates":[31.81484,30.70116],"type":"Point"}
}