{
  "type": "Feature",
  "properties": {
    "gn:admin1_code":"23",
    "gn:asciiname":"Naj` Kawm Jabir",
    "gn:country_code":"EG",
    "gn:dem":69,
    "gn:feature_class":"P",
    "gn:feature_code":"PPL",
    "gn:name":"Naj\u2018 Kawm J\u0101bir",
    "gn:population":0,
    "gn:timezone":"Africa/Cairo",
    "iso:country":"EG",
    "wof:name":"Naj` Kawm Jabir",
    "wof:placetype":"locality"
},
  "geometry": {"coordinates":[32.03524,26.12231],"type":"Point"}
}