{
  "type": "Feature",
  "properties": {
    "gn:admin1_code":"10",
    "gn:asciiname":"Jabal at Tayr",
    "gn:country_code":"EG",
    "gn:dem":44,
    "gn:feature_class":"P",
    "gn:feature_code":"PPL",
    "gn:name":"Jabal a\u0163 \u0162ayr",
    "gn:population":0,
    "gn:timezone":"Africa/Cairo",
    "iso:country":"EG",
    "name:und_x_variant":[
        "Al J\u0101mi\u2018",
        "Gebel el-\u1e6ceir",
        "El G\u00e2mi\u2018",
        "Gebel et Teir",
        "Gabal el Teir",
        "Jabal a\u0163 \u0162ayr"
    ],
    "wof:name":"Jabal at Tayr",
    "wof:placetype":"locality"
},
  "geometry": {"coordinates":[30.76052,28.2322],"type":"Point"}
}