{
  "type": "Feature",
  "properties": {
    "gn:admin1_code":"09",
    "gn:asciiname":"Kafr Qarshum",
    "gn:country_code":"EG",
    "gn:dem":11,
    "gn:feature_class":"P",
    "gn:feature_code":"PPL",
    "gn:name":"Kafr Qarsh\u016bm",
    "gn:population":0,
    "gn:timezone":"Africa/Cairo",
    "iso:country":"EG",
    "name:und_x_variant":[
        "Kafr Qursh\u016bm",
        "Kafr Qarsh\u016bm"
    ],
    "wof:name":"Kafr Qarshum",
    "wof:placetype":"locality"
},
  "geometry": {"coordinates":[30.97569,30.67764],"type":"Point"}
}