{
  "type": "Feature",
  "properties": {
    "gn:admin1_code":"10",
    "gn:asciiname":"Bani Khiyar",
    "gn:country_code":"EG",
    "gn:dem":46,
    "gn:feature_class":"P",
    "gn:feature_code":"PPL",
    "gn:name":"Ban\u012b Khiy\u0101r",
    "gn:population":0,
    "gn:timezone":"Africa/Cairo",
    "iso:country":"EG",
    "name:und_x_variant":[
        "Beni Khiy\u00e2r",
        "Ban\u012b Khiy\u0101r"
    ],
    "wof:name":"Bani Khiyar",
    "wof:placetype":"locality"
},
  "geometry": {"coordinates":[30.70608,27.97625],"type":"Point"}
}