{
  "type": "Feature",
  "properties": {
    "gn:admin1_code":"10",
    "gn:asciiname":"Al `Arin al Bahri",
    "gn:country_code":"EG",
    "gn:dem":42,
    "gn:feature_class":"P",
    "gn:feature_code":"PPL",
    "gn:name":"Al \u2018Ar\u012bn al Ba\u1e29r\u012b",
    "gn:population":0,
    "gn:timezone":"Africa/Cairo",
    "iso:country":"EG",
    "name:und_x_variant":[
        "El Ar\u00een Ba\u1e25ari",
        "Al \u2018Ar\u012bn al Ba\u1e29r\u012b"
    ],
    "wof:name":"Al `Arin al Bahri",
    "wof:placetype":"locality"
},
  "geometry": {"coordinates":[30.75,27.78333],"type":"Point"}
}