{
  "type": "Feature",
  "properties": {
    "gn:admin1_code":"21",
    "gn:asciiname":"`Izbat Fawdah",
    "gn:country_code":"EG",
    "gn:dem":8,
    "gn:feature_class":"P",
    "gn:feature_code":"PPL",
    "gn:name":"\u2018Izbat Fawdah",
    "gn:population":0,
    "gn:timezone":"Africa/Cairo",
    "iso:country":"EG",
    "name:ara_x_preferred":[
        "\u0639\u0632\u0628\u0629 \u0641\u0648\u062f\u0629"
    ],
    "name:und_x_variant":[
        "\u2018Izbat Fawdah",
        "\u2018Izbat F\u016bdah"
    ],
    "wof:name":"`Izbat Fawdah",
    "wof:placetype":"locality"
},
  "geometry": {"coordinates":[31.17101,31.17803],"type":"Point"}
}