{
  "type": "Feature",
  "properties": {
    "gn:admin1_code":"04",
    "gn:asciiname":"`Izbat Abu Taha",
    "gn:country_code":"EG",
    "gn:dem":27,
    "gn:feature_class":"P",
    "gn:feature_code":"PPL",
    "gn:name":"\u2018Izbat Ab\u016b \u0162\u0101h\u0101",
    "gn:population":0,
    "gn:timezone":"Africa/Cairo",
    "iso:country":"EG",
    "wof:name":"`Izbat Abu Taha",
    "wof:placetype":"locality"
},
  "geometry": {"coordinates":[30.94678,29.22603],"type":"Point"}
}