{
  "type": "Feature",
  "properties": {
    "gn:admin1_code":"01",
    "gn:asciiname":"`Izbat Abu Ahmad",
    "gn:country_code":"EG",
    "gn:dem":5,
    "gn:feature_class":"P",
    "gn:feature_code":"PPL",
    "gn:name":"\u2018Izbat Ab\u016b A\u1e29mad",
    "gn:population":0,
    "gn:timezone":"Africa/Cairo",
    "iso:country":"EG",
    "name:ara_x_preferred":[
        "\u0639\u0632\u0628\u0629 \u0623\u0628\u0648 \u0623\u062d\u0645\u062f"
    ],
    "name:und_x_variant":[
        "\u2018Izbat Ab\u016b A\u1e29mad",
        "\u2018Izbat Ab\u016b A\u1e25mad"
    ],
    "wof:name":"`Izbat Abu Ahmad",
    "wof:placetype":"locality"
},
  "geometry": {"coordinates":[31.27678,31.1808],"type":"Point"}
}