{
  "type": "Feature",
  "properties": {
    "gn:admin1_code":"14",
    "gn:asciiname":"Kafr Thu`aylib",
    "gn:country_code":"EG",
    "gn:dem":9,
    "gn:feature_class":"P",
    "gn:feature_code":"PPL",
    "gn:name":"Kafr Thu\u2018aylib",
    "gn:population":0,
    "gn:timezone":"Africa/Cairo",
    "iso:country":"EG",
    "name:und_x_variant":[
        "Kafr Ti\u2018eilib",
        "Kafr Thu\u2018aylib"
    ],
    "wof:name":"Kafr Thu`aylib",
    "wof:placetype":"locality"
},
  "geometry": {"coordinates":[31.65,30.48333],"type":"Point"}
}