{
  "type": "Feature",
  "properties": {
    "gn:admin1_code":"10",
    "gn:asciiname":"Ishnin an Nasara",
    "gn:country_code":"EG",
    "gn:dem":39,
    "gn:feature_class":"P",
    "gn:feature_code":"PPL",
    "gn:name":"Ishn\u012bn an Na\u015f\u0101r\u00e1",
    "gn:population":0,
    "gn:timezone":"Africa/Cairo",
    "iso:country":"EG",
    "name:und_x_variant":[
        "Ishn\u00een el Na\u015f\u00e2r\u00e1",
        "Ishn\u012bn an Na\u015f\u0101r\u00e1"
    ],
    "wof:name":"Ishnin an Nasara",
    "wof:placetype":"locality"
},
  "geometry": {"coordinates":[30.77326,28.61373],"type":"Point"}
}