{
  "type": "Feature",
  "properties": {
    "gn:admin1_code":"03",
    "gn:asciiname":"Kafr Musa`id",
    "gn:country_code":"EG",
    "gn:dem":6,
    "gn:feature_class":"P",
    "gn:feature_code":"PPL",
    "gn:name":"Kafr Mus\u0101\u2018id",
    "gn:population":0,
    "gn:timezone":"Africa/Cairo",
    "iso:country":"EG",
    "name:ara_x_preferred":[
        "\u0643\u0641\u0631 \u0645\u0633\u0627\u0639\u062f"
    ],
    "name:und_x_variant":[
        "Kafr Mosaid",
        "Kafr Mes\u00e2\u2018id",
        "Kafr Mus\u0101\u2018id"
    ],
    "wof:name":"Kafr Musa`id",
    "wof:placetype":"locality"
},
  "geometry": {"coordinates":[30.62297,30.91738],"type":"Point"}
}