{
  "type": "Feature",
  "properties": {
    "gn:admin1_code":"18",
    "gn:asciiname":"`Izbat Tis`in",
    "gn:country_code":"EG",
    "gn:dem":-1,
    "gn:feature_class":"P",
    "gn:feature_code":"PPL",
    "gn:name":"\u2018Izbat Tis\u2018\u012bn",
    "gn:population":0,
    "gn:timezone":"Africa/Cairo",
    "iso:country":"EG",
    "name:ara_x_preferred":[
        "\u0639\u0632\u0628\u0629 \u062a\u0633\u0639\u064a\u0646"
    ],
    "name:und_x_variant":[
        "\u2018Izbat Tis\u2018\u012bn"
    ],
    "wof:name":"`Izbat Tis`in",
    "wof:placetype":"locality"
},
  "geometry": {"coordinates":[32.03997,31.04838],"type":"Point"}
}