{
  "type": "Feature",
  "properties": {
    "gn:admin1_code":"08",
    "gn:asciiname":"Atris",
    "gn:country_code":"EG",
    "gn:dem":18,
    "gn:feature_class":"P",
    "gn:feature_code":"PPL",
    "gn:name":"Atr\u012bs",
    "gn:population":0,
    "gn:timezone":"Africa/Cairo",
    "iso:country":"EG",
    "name:ara_x_preferred":[
        "\u0623\u062a\u0631\u064a\u0633"
    ],
    "name:und_x_variant":[
        "Atr\u012bs"
    ],
    "wof:name":"Atris",
    "wof:placetype":"locality"
},
  "geometry": {"coordinates":[30.8839,30.33552],"type":"Point"}
}