{
  "type": "Feature",
  "properties": {
    "gn:admin1_code":"05",
    "gn:asciiname":"`Izbat al Jimmayzah",
    "gn:country_code":"EG",
    "gn:dem":7,
    "gn:feature_class":"P",
    "gn:feature_code":"PPL",
    "gn:name":"\u2018Izbat al Jimmayzah",
    "gn:population":0,
    "gn:timezone":"Africa/Cairo",
    "iso:country":"EG",
    "name:ara_x_preferred":[
        "\u0639\u0632\u0628\u0629 \u0627\u0644\u062c\u0645\u064a\u0632\u0629"
    ],
    "name:und_x_variant":[
        "\u2018Izbat al Jimmayzah",
        "\u2018Izbat al-Jimmayzah"
    ],
    "wof:name":"`Izbat al Jimmayzah",
    "wof:placetype":"locality"
},
  "geometry": {"coordinates":[31.0857,31.06973],"type":"Point"}
}