{
  "type": "Feature",
  "properties": {
    "gn:admin1_code":"13",
    "gn:asciiname":"Abidus",
    "gn:country_code":"EG",
    "gn:dem":79,
    "gn:feature_class":"P",
    "gn:feature_code":"PPL",
    "gn:name":"Ab\u012bd\u016bs",
    "gn:population":0,
    "gn:timezone":"Africa/Cairo",
    "iso:country":"EG",
    "wof:name":"Abidus",
    "wof:placetype":"locality"
},
  "geometry": {"coordinates":[31.92194000000001,26.18449],"type":"Point"}
}