{
  "type": "Feature",
  "properties": {
    "gn:admin1_code":"21",
    "gn:asciiname":"`Izbat al Hakim",
    "gn:country_code":"EG",
    "gn:dem":5,
    "gn:feature_class":"P",
    "gn:feature_code":"PPL",
    "gn:name":"\u2018Izbat al \u1e28ak\u012bm",
    "gn:population":0,
    "gn:timezone":"Africa/Cairo",
    "iso:country":"EG",
    "name:ara_x_preferred":[
        "\u0639\u0632\u0628\u0629 \u0627\u0644\u062d\u0643\u064a\u0645"
    ],
    "name:und_x_variant":[
        "\u2018Izbat al \u1e28ak\u012bm",
        "\u2018Izbat al-\u1e24ak\u012bm"
    ],
    "wof:name":"`Izbat al Hakim",
    "wof:placetype":"locality"
},
  "geometry": {"coordinates":[31.10271,31.14472],"type":"Point"}
}