{
  "type": "Feature",
  "properties": {
    "gn:admin1_code":"10",
    "gn:asciiname":"`Izbat as Sawaytah",
    "gn:country_code":"EG",
    "gn:dem":40,
    "gn:feature_class":"P",
    "gn:feature_code":"PPL",
    "gn:name":"\u2018Izbat as Saw\u0101y\u0163ah",
    "gn:population":0,
    "gn:timezone":"Africa/Cairo",
    "iso:country":"EG",
    "name:und_x_variant":[
        "\u2018Izbat as Saw\u0101y\u0163ah",
        "El Saw\u00e2y\u1e6da",
        "A\u015f \u015eaw\u0101\u2019i\u0163ah"
    ],
    "wof:name":"`Izbat as Sawaytah",
    "wof:placetype":"locality"
},
  "geometry": {"coordinates":[30.80569,28.3951],"type":"Point"}
}