{
  "type": "Feature",
  "properties": {
    "gn:admin1_code":"01",
    "gn:asciiname":"Ash Sha`alah",
    "gn:country_code":"EG",
    "gn:dem":10,
    "gn:feature_class":"P",
    "gn:feature_code":"PPL",
    "gn:name":"Ash Sha\u2018\u0101lah",
    "gn:population":0,
    "gn:timezone":"Africa/Cairo",
    "iso:country":"EG",
    "name:ara_x_preferred":[
        "\u0627\u0644\u0634\u0639\u0627\u0644\u0629"
    ],
    "name:und_x_variant":[
        "Ash Sha\u2018\u0101lah",
        "Ash-Sha\u2018\u0101llah"
    ],
    "wof:name":"Ash Sha`alah",
    "wof:placetype":"locality"
},
  "geometry": {"coordinates":[31.40023,30.84051],"type":"Point"}
}