{
  "type": "Feature",
  "properties": {
    "gn:admin1_code":"14",
    "gn:asciiname":"Naj` `Udah",
    "gn:country_code":"EG",
    "gn:dem":12,
    "gn:feature_class":"P",
    "gn:feature_code":"PPL",
    "gn:name":"Naj\u2018 \u2018\u016adah",
    "gn:population":0,
    "gn:timezone":"Africa/Cairo",
    "iso:country":"EG",
    "name:ara_x_preferred":[
        "\u0646\u062c\u0639 \u0639\u0648\u062f\u0629"
    ],
    "name:und_x_variant":[
        "Naj\u2018 \u2018\u016adah"
    ],
    "wof:name":"Naj` `Udah",
    "wof:placetype":"locality"
},
  "geometry": {"coordinates":[31.76562,30.67396],"type":"Point"}
}