{
  "type": "Feature",
  "properties": {
    "gn:admin1_code":"14",
    "gn:asciiname":"`Izbat Barradah",
    "gn:country_code":"EG",
    "gn:dem":10,
    "gn:feature_class":"P",
    "gn:feature_code":"PPL",
    "gn:name":"\u2018Izbat Barr\u0101dah",
    "gn:population":0,
    "gn:timezone":"Africa/Cairo",
    "iso:country":"EG",
    "name:ara_x_preferred":[
        "\u0639\u0632\u0628\u0629 \u0628\u0631\u0627\u062f\u0629"
    ],
    "name:und_x_variant":[
        "\u2018Izbat Barr\u0101dah"
    ],
    "wof:name":"`Izbat Barradah",
    "wof:placetype":"locality"
},
  "geometry": {"coordinates":[31.70882000000001,30.73662],"type":"Point"}
}