{
  "type": "Feature",
  "properties": {
    "gn:admin1_code":"04",
    "gn:asciiname":"Al A`lam",
    "gn:country_code":"EG",
    "gn:dem":22,
    "gn:feature_class":"P",
    "gn:feature_code":"PPL",
    "gn:name":"Al A\u2018l\u0101m",
    "gn:population":0,
    "gn:timezone":"Africa/Cairo",
    "iso:country":"EG",
    "name:und_x_variant":[
        "El-A\u2018l\u00e2m",
        "Al A\u2018l\u0101m"
    ],
    "wof:name":"Al A`lam",
    "wof:placetype":"locality"
},
  "geometry": {"coordinates":[30.86982,29.34941],"type":"Point"}
}