{
  "type": "Feature",
  "properties": {
    "gn:admin1_code":"02",
    "gn:asciiname":"Ar Ruwayjat",
    "gn:country_code":"EG",
    "gn:dem":59,
    "gn:feature_class":"P",
    "gn:feature_code":"PPL",
    "gn:name":"Ar Ruwayj\u0101t",
    "gn:population":0,
    "gn:timezone":"Africa/Cairo",
    "iso:country":"EG",
    "wof:name":"Ar Ruwayjat",
    "wof:placetype":"locality"
},
  "geometry": {"coordinates":[31.41981,27.05249],"type":"Point"}
}