{
  "type": "Feature",
  "properties": {
    "gn:admin1_code":"02",
    "gn:asciiname":"Al Ma`abidah",
    "gn:country_code":"EG",
    "gn:dem":50,
    "gn:feature_class":"P",
    "gn:feature_code":"PPL",
    "gn:name":"Al Ma\u2018\u0101bidah",
    "gn:population":0,
    "gn:timezone":"Africa/Cairo",
    "iso:country":"EG",
    "name:und_x_variant":[
        "El Ma\u2018\u00e2bda",
        "Al Ma\u2018\u0101bidah"
    ],
    "wof:name":"Al Ma`abidah",
    "wof:placetype":"locality"
},
  "geometry": {"coordinates":[31.02303,27.33743],"type":"Point"}
}