{
  "type": "Feature",
  "properties": {
    "gn:admin1_code":"21",
    "gn:asciiname":"`Izbat al Ghanayimah",
    "gn:country_code":"EG",
    "gn:dem":1,
    "gn:feature_class":"P",
    "gn:feature_code":"PPL",
    "gn:name":"\u2018Izbat al Ghan\u0101yimah",
    "gn:population":0,
    "gn:timezone":"Africa/Cairo",
    "iso:country":"EG",
    "name:ara_x_preferred":[
        "\u0639\u0632\u0628\u0629 \u0627\u0644\u063a\u0646\u0627\u064a\u0645\u0629"
    ],
    "name:und_x_variant":[
        "\u2018Izbat al Ghan\u0101yimah",
        "\u2018Izbat al Ghan\u0101ymah"
    ],
    "wof:name":"`Izbat al Ghanayimah",
    "wof:placetype":"locality"
},
  "geometry": {"coordinates":[30.61786,31.31305],"type":"Point"}
}