{
  "type": "Feature",
  "properties": {
    "gn:admin1_code":"12",
    "gn:asciiname":"Ash Shuqr",
    "gn:country_code":"EG",
    "gn:dem":15,
    "gn:feature_class":"P",
    "gn:feature_code":"PPL",
    "gn:name":"Ash Shuqr",
    "gn:population":0,
    "gn:timezone":"Africa/Cairo",
    "iso:country":"EG",
    "name:ara_x_preferred":[
        "\u0627\u0644\u0634\u0642\u0631"
    ],
    "name:und_x_variant":[
        "El-Shuqr",
        "Ash Shuqr"
    ],
    "wof:name":"Ash Shuqr",
    "wof:placetype":"locality"
},
  "geometry": {"coordinates":[31.27815,30.51032],"type":"Point"}
}