{
  "type": "Feature",
  "properties": {
    "iso:country":"EG",
    "name:ara_x_preferred":[
        "\u0633\u0631\u0633 \u0627\u0644\u0644\u064a\u0627\u0646\u0629"
    ],
    "name:unk_x_variant":[
        "Sers el-liy\u00e2neh"
    ],
    "qs:gn_country":"EG",
    "qs:gn_fcode":"PPL",
    "qs:gn_pop":0,
    "qs:name":"Sirs al Layyanah",
    "qs:name_adm0":"\u0645\u0635\u0631",
    "qs:name_adm1":"\u0627\u0644\u0645\u0646\u0648\u0641\u064a\u0629",
    "qs:photos":0,
    "qs:photos_1k":0,
    "qs:photos_9k":0,
    "qs:photos_9r":0,
    "qs:photos_all":0,
    "qs:photos_sr":0,
    "qs:placetype":"Town",
    "qs:pop_sr":"0",
    "qs:woe_adm0":23424802,
    "wof:name":"Sirs al Layyanah",
    "wof:placetype":"locality"
},
  "geometry": {"coordinates":[30.96667,30.43333],"type":"Point"}
}