{
  "type": "Feature",
  "properties": {
    "gn:admin1_code":"09",
    "gn:asciiname":"Kafr Hilal",
    "gn:country_code":"EG",
    "gn:dem":15,
    "gn:feature_class":"P",
    "gn:feature_code":"PPL",
    "gn:name":"Kafr Hil\u0101l",
    "gn:population":0,
    "gn:timezone":"Africa/Cairo",
    "iso:country":"EG",
    "name:ara_x_preferred":[
        "\u0643\u0641\u0631 \u0647\u0644\u0627\u0644"
    ],
    "name:und_x_variant":[
        "Kafr Hil\u0101l"
    ],
    "wof:name":"Kafr Hilal",
    "wof:placetype":"locality"
},
  "geometry": {"coordinates":[31.17254,30.64451],"type":"Point"}
}