{
  "type": "Feature",
  "properties": {
    "gn:admin1_code":"13.0",
    "gn:asciiname":"Tunaydah",
    "gn:country_code":"EG",
    "gn:dem":128,
    "gn:feature_class":"P",
    "gn:feature_code":"PPL",
    "gn:name":"Tunaydah",
    "gn:population":0,
    "gn:timezone":"Africa/Cairo",
    "iso:country":"EG",
    "name:und_x_variant":[
        "Tineida",
        "Tanaydah",
        "Tenida",
        "Teneida",
        "Tunaydah"
    ],
    "wof:name":"Tunaydah",
    "wof:placetype":"locality"
},
  "geometry": {"coordinates":[29.34039000000001,25.51118],"type":"Point"}
}