{
  "type": "Feature",
  "properties": {
    "gn:admin1_code":"14",
    "gn:asciiname":"Kafr al Wada'i`ah",
    "gn:country_code":"EG",
    "gn:dem":7,
    "gn:feature_class":"P",
    "gn:feature_code":"PPL",
    "gn:name":"Kafr al Wad\u0101\u2019i\u2018ah",
    "gn:population":0,
    "gn:timezone":"Africa/Cairo",
    "iso:country":"EG",
    "name:und_x_variant":[
        "Kafr el-Wad\u00e2y\u2018a",
        "Kafr al Wad\u0101\u2019i\u2018ah"
    ],
    "wof:name":"Kafr al Wada'i`ah",
    "wof:placetype":"locality"
},
  "geometry": {"coordinates":[31.85,30.73333],"type":"Point"}
}