{
  "type": "Feature",
  "properties": {
    "gn:admin1_code":"14",
    "gn:asciiname":"Minsha'at Ahmad `Urabi",
    "gn:country_code":"EG",
    "gn:dem":10,
    "gn:feature_class":"P",
    "gn:feature_code":"PPL",
    "gn:name":"Minsha\u2019\u0101t A\u1e29mad \u2018Ur\u0101b\u012b",
    "gn:population":0,
    "gn:timezone":"Africa/Cairo",
    "iso:country":"EG",
    "name:ara_x_preferred":[
        "\u0645\u0646\u0634\u0623\u0629 \u0623\u062d\u0645\u062f \u0639\u0631\u0627\u0628\u064a"
    ],
    "name:und_x_variant":[
        "Minsha\u2019\u0101t A\u1e29mad \u2018Ur\u0101b\u012b",
        "Minsh\u0101t A\u1e25mad \u2018Ur\u0101b\u012b"
    ],
    "wof:name":"Minsha'at Ahmad `Urabi",
    "wof:placetype":"locality"
},
  "geometry": {"coordinates":[31.78544,30.52578],"type":"Point"}
}