{
  "type": "Feature",
  "properties": {
    "gn:admin1_code":"01",
    "gn:asciiname":"`Izbat Jad",
    "gn:country_code":"EG",
    "gn:dem":4,
    "gn:feature_class":"P",
    "gn:feature_code":"PPL",
    "gn:name":"\u2018Izbat J\u0101d",
    "gn:population":0,
    "gn:timezone":"Africa/Cairo",
    "iso:country":"EG",
    "name:ara_x_preferred":[
        "\u0639\u0632\u0628\u0629 \u062c\u0627\u062f"
    ],
    "name:und_x_variant":[
        "\u2018Izbat J\u0101d"
    ],
    "wof:name":"`Izbat Jad",
    "wof:placetype":"locality"
},
  "geometry": {"coordinates":[31.60417,30.99912],"type":"Point"}
}