{
  "type": "Feature",
  "properties": {
    "gn:admin1_code":"05",
    "gn:asciiname":"Kafr Hasab Allah",
    "gn:cc2":"EG",
    "gn:country_code":"EG",
    "gn:dem":6,
    "gn:feature_class":"P",
    "gn:feature_code":"PPL",
    "gn:name":"Kafr \u1e28asab All\u0101h",
    "gn:population":0,
    "gn:timezone":"Africa/Cairo",
    "iso:country":"EG",
    "name:und_x_variant":[
        "Kafr \u1e24asaballa",
        "Kafr \u1e28asab All\u0101h"
    ],
    "wof:name":"Kafr Hasab Allah",
    "wof:placetype":"locality"
},
  "geometry": {"coordinates":[31.23333,31.03333],"type":"Point"}
}