{
  "type": "Feature",
  "properties": {
    "gn:admin1_code":"14",
    "gn:asciiname":"`Izbat Musa Agha",
    "gn:country_code":"EG",
    "gn:dem":12,
    "gn:feature_class":"P",
    "gn:feature_code":"PPL",
    "gn:name":"\u2018Izbat M\u016bs\u00e1 Agh\u0101",
    "gn:population":0,
    "gn:timezone":"Africa/Cairo",
    "iso:country":"EG",
    "name:ara_x_preferred":[
        "\u0639\u0632\u0628\u0629 \u0645\u0648\u0633\u0649 \u0623\u063a\u0627"
    ],
    "name:und_x_variant":[
        "\u2018Izbat M\u016bs\u00e1 Agh\u0101"
    ],
    "wof:name":"`Izbat Musa Agha",
    "wof:placetype":"locality"
},
  "geometry": {"coordinates":[31.5615,30.72602],"type":"Point"}
}