{
  "type": "Feature",
  "properties": {
    "gn:admin1_code":"03",
    "gn:asciiname":"Al Wafa'iyah",
    "gn:country_code":"EG",
    "gn:dem":3,
    "gn:feature_class":"P",
    "gn:feature_code":"PPL",
    "gn:name":"Al Waf\u0101\u2019\u012byah",
    "gn:population":0,
    "gn:timezone":"Africa/Cairo",
    "iso:country":"EG",
    "name:und_x_variant":[
        "El-Waf\u00e2\u2019\u00eeya",
        "El Waf\u00e2\u2019iya",
        "El Yah\u016bdiya",
        "Al Waf\u0101\u2019\u012byah"
    ],
    "wof:name":"Al Wafa'iyah",
    "wof:placetype":"locality"
},
  "geometry": {"coordinates":[30.59353,30.76725],"type":"Point"}
}