{
  "type": "Feature",
  "properties": {
    "gn:admin1_code":"01",
    "gn:asciiname":"Al Hutah",
    "gn:country_code":"EG",
    "gn:dem":8,
    "gn:feature_class":"P",
    "gn:feature_code":"PPL",
    "gn:name":"Al \u1e28\u016btah",
    "gn:population":0,
    "gn:timezone":"Africa/Cairo",
    "iso:country":"EG",
    "name:ara_x_preferred":[
        "\u0627\u0644\u062d\u0648\u062a\u0629"
    ],
    "name:und_x_variant":[
        "Al \u1e28\u016btah",
        "Al-\u1e24\u016btah"
    ],
    "wof:name":"Al Hutah",
    "wof:placetype":"locality"
},
  "geometry": {"coordinates":[31.97619000000001,31.1706],"type":"Point"}
}