{
  "type": "Feature",
  "properties": {
    "gn:admin1_code":"10",
    "gn:asciiname":"Maghaghah",
    "gn:country_code":"EG",
    "gn:dem":40,
    "gn:feature_class":"P",
    "gn:feature_code":"PPL",
    "gn:name":"Magh\u0101ghah",
    "gn:population":0,
    "gn:timezone":"Africa/Cairo",
    "iso:country":"EG",
    "name:und_x_variant":[
        "Magagha",
        "Magh\u00e2gha",
        "Magh\u0101ghah"
    ],
    "wof:name":"Maghaghah",
    "wof:placetype":"locality"
},
  "geometry": {"coordinates":[30.84234,28.6484],"type":"Point"}
}