{
  "type": "Feature",
  "properties": {
    "gn:admin1_code":"10",
    "gn:asciiname":"Maghaghah",
    "gn:country_code":"EG",
    "gn:dem":40,
    "gn:feature_class":"P",
    "gn:feature_code":"PPL",
    "gn:name":"Magh\u0101ghah",
    "gn:population":0,
    "gn:timezone":"Africa/Cairo",
    "iso:country":"EG",
    "name:ara_x_preferred":[
        "\u0645\u063a\u0627\u063a\u0629"
    ],
    "name:arz_x_preferred":[
        "\u0645\u063a\u0627\u063a\u0647"
    ],
    "name:fas_x_preferred":[
        "\u0645\u063a\u0627\u063a\u0647"
    ],
    "name:kat_x_preferred":[
        "\u10db\u10d0\u10e6\u10d0\u10e6\u10d0"
    ],
    "name:pol_x_preferred":[
        "Maghagha"
    ],
    "name:por_x_preferred":[
        "Maghagha"
    ],
    "name:rus_x_preferred":[
        "\u041c\u0430\u0433\u0430\u0433\u0430"
    ],
    "name:tur_x_preferred":[
        "Maghagha"
    ],
    "name:und_x_variant":[
        "Magagha",
        "Magh\u00e2gha",
        "Magh\u0101ghah"
    ],
    "wof:name":"Maghaghah",
    "wof:placetype":"locality"
},
  "geometry": {"coordinates":[30.84234,28.6484],"type":"Point"}
}