{
  "type": "Feature",
  "properties": {
    "gn:admin1_code":"09",
    "gn:asciiname":"Kafr al Qalashi",
    "gn:country_code":"EG",
    "gn:dem":12,
    "gn:feature_class":"P",
    "gn:feature_code":"PPL",
    "gn:name":"Kafr al Qalash\u012b",
    "gn:population":0,
    "gn:timezone":"Africa/Cairo",
    "iso:country":"EG",
    "name:und_x_variant":[
        "Kafr el-Qalashi",
        "Kafr al Qalash\u012b"
    ],
    "wof:name":"Kafr al Qalashi",
    "wof:placetype":"locality"
},
  "geometry": {"coordinates":[30.98533,30.65624],"type":"Point"}
}