{
  "type": "Feature",
  "properties": {
    "gn:admin1_code":"21",
    "gn:asciiname":"`Izbat al `Umdah al Ghannam",
    "gn:country_code":"EG",
    "gn:dem":2,
    "gn:feature_class":"P",
    "gn:feature_code":"PPL",
    "gn:name":"\u2018Izbat al \u2018Umdah al Ghann\u0101m",
    "gn:population":0,
    "gn:timezone":"Africa/Cairo",
    "iso:country":"EG",
    "name:ara_x_preferred":[
        "\u0639\u0632\u0628\u0629 \u0627\u0644\u0639\u0645\u062f\u0629 \u0627\u0644\u063a\u0646\u0627\u0645"
    ],
    "name:und_x_variant":[
        "\u2018Izbat al \u2018Umdah al Ghann\u0101m"
    ],
    "wof:name":"`Izbat al `Umdah al Ghannam",
    "wof:placetype":"locality"
},
  "geometry": {"coordinates":[30.83883,31.29593],"type":"Point"}
}