{
  "type": "Feature",
  "properties": {
    "gn:admin1_code":"12",
    "gn:asciiname":"Barshum al Kubra",
    "gn:country_code":"EG",
    "gn:dem":19,
    "gn:feature_class":"P",
    "gn:feature_code":"PPL",
    "gn:name":"Barsh\u016bm al Kubr\u00e1",
    "gn:population":0,
    "gn:timezone":"Africa/Cairo",
    "iso:country":"EG",
    "name:ara_x_preferred":[
        "\u0628\u0631\u0634\u0648\u0645 \u0627\u0644\u0643\u0628\u0631\u0649"
    ],
    "name:und_x_variant":[
        "Barsh\u00fbm el-Kubra",
        "Barsh\u016bm al Kubr\u00e1",
        "Kafr Barsh\u016bm al Kubr\u00e1",
        "Kafr Barsh\u00fbm el-Kubra"
    ],
    "wof:name":"Barshum al Kubra",
    "wof:placetype":"locality"
},
  "geometry": {"coordinates":[31.11079,30.32365],"type":"Point"}
}