{
  "type": "Feature",
  "properties": {
    "gn:admin1_code":"17",
    "gn:asciiname":"Mijris",
    "gn:country_code":"EG",
    "gn:dem":58,
    "gn:feature_class":"P",
    "gn:feature_code":"PPL",
    "gn:name":"Mijr\u012bs",
    "gn:population":0,
    "gn:timezone":"Africa/Cairo",
    "iso:country":"EG",
    "name:und_x_variant":[
        "Migr\u00ees",
        "Mijr\u012bs"
    ],
    "wof:name":"Mijris",
    "wof:placetype":"locality"
},
  "geometry": {"coordinates":[31.37855,26.97721],"type":"Point"}
}