{
  "type": "Feature",
  "properties": {
    "gn:admin1_code":"18",
    "gn:asciiname":"Bahnamuh",
    "gn:country_code":"EG",
    "gn:dem":28,
    "gn:feature_class":"P",
    "gn:feature_code":"PPL",
    "gn:name":"Bahnam\u016bh",
    "gn:population":0,
    "gn:timezone":"Africa/Cairo",
    "iso:country":"EG",
    "name:und_x_variant":[
        "Bahnamoh",
        "Bahnam\u016bh"
    ],
    "wof:name":"Bahnamuh",
    "wof:placetype":"locality"
},
  "geometry": {"coordinates":[30.90791,29.05806],"type":"Point"}
}