{
  "type": "Feature",
  "properties": {
    "gn:admin1_code":"21",
    "gn:asciiname":"`Izbat al Ghalayisah",
    "gn:country_code":"EG",
    "gn:dem":2,
    "gn:feature_class":"P",
    "gn:feature_code":"PPL",
    "gn:name":"\u2018Izbat al Ghal\u0101yisah",
    "gn:population":0,
    "gn:timezone":"Africa/Cairo",
    "iso:country":"EG",
    "name:ara_x_preferred":[
        "\u0639\u0632\u0628\u0629 \u0627\u0644\u063a\u0644\u0627\u064a\u0633\u0629"
    ],
    "name:und_x_variant":[
        "\u2018Izbat al Ghal\u0101yisah",
        "\u2018Izbat al Ghal\u0101ysah"
    ],
    "wof:name":"`Izbat al Ghalayisah",
    "wof:placetype":"locality"
},
  "geometry": {"coordinates":[30.45704000000001,31.36271],"type":"Point"}
}