{
  "type": "Feature",
  "properties": {
    "gn:admin1_code":"12",
    "gn:asciiname":"`Izbat Hawd Batatah",
    "gn:country_code":"EG",
    "gn:dem":16,
    "gn:feature_class":"P",
    "gn:feature_code":"PPL",
    "gn:name":"\u2018Izbat \u1e28aw\u1e11 Ba\u0163\u0101\u0163ah",
    "gn:population":0,
    "gn:timezone":"Africa/Cairo",
    "iso:country":"EG",
    "name:ara_x_preferred":[
        "\u0639\u0632\u0628\u0629 \u062d\u0648\u0636 \u0628\u0637\u0627\u0637\u0629"
    ],
    "name:und_x_variant":[
        "\u2018Izbat \u1e28aw\u1e11 Ba\u0163\u0101\u0163ah"
    ],
    "wof:name":"`Izbat Hawd Batatah",
    "wof:placetype":"locality"
},
  "geometry": {"coordinates":[31.228,30.37618],"type":"Point"}
}