{
  "type": "Feature",
  "properties": {
    "gn:admin1_code":"03",
    "gn:asciiname":"Qaryat al Mukhtar",
    "gn:country_code":"EG",
    "gn:dem":-4,
    "gn:feature_class":"P",
    "gn:feature_code":"PPL",
    "gn:name":"Qaryat al Mukht\u0101r",
    "gn:population":0,
    "gn:timezone":"Africa/Cairo",
    "iso:country":"EG",
    "name:ara_x_preferred":[
        "\u0642\u0631\u064a\u0629 \u0627\u0644\u0645\u062e\u062a\u0627\u0631"
    ],
    "name:und_x_variant":[
        "Qaryat al Mukht\u0101r"
    ],
    "wof:name":"Qaryat al Mukhtar",
    "wof:placetype":"locality"
},
  "geometry": {"coordinates":[30.0393,31.02601],"type":"Point"}
}