{
  "type": "Feature",
  "properties": {
    "gn:admin1_code":"03",
    "gn:asciiname":"Dirshabah",
    "gn:country_code":"EG",
    "gn:dem":10,
    "gn:feature_class":"P",
    "gn:feature_code":"PPL",
    "gn:name":"Dirsh\u0101bah",
    "gn:population":0,
    "gn:timezone":"Africa/Cairo",
    "iso:country":"EG",
    "name:ara_x_preferred":[
        "\u062f\u0631\u0634\u0627\u0628\u0629"
    ],
    "name:und_x_variant":[
        "Dirsh\u00e2ba",
        "Dirsh\u0101bah"
    ],
    "wof:name":"Dirshabah",
    "wof:placetype":"locality"
},
  "geometry": {"coordinates":[30.61933,31.13808],"type":"Point"}
}