{
  "type": "Feature",
  "properties": {
    "gn:admin1_code":"01",
    "gn:asciiname":"`Izbat Husayn `Izzat",
    "gn:country_code":"EG",
    "gn:dem":7,
    "gn:feature_class":"P",
    "gn:feature_code":"PPL",
    "gn:name":"\u2018Izbat \u1e28usayn \u2018Izzat",
    "gn:population":0,
    "gn:timezone":"Africa/Cairo",
    "iso:country":"EG",
    "name:ara_x_preferred":[
        "\u0639\u0632\u0628\u0629 \u062d\u0633\u064a\u0646 \u0639\u0632\u062a"
    ],
    "name:ara_x_variant":[
        "\u0639\u0632\u0628\u0629 \u0627\u0644\u0628\u0631\u0627\u0628\u0631\u0629"
    ],
    "name:und_x_variant":[
        "\u2018Izbat \u1e28usayn \u2018Izzat",
        "\u2018Izbat al Bar\u0101birah"
    ],
    "wof:name":"`Izbat Husayn `Izzat",
    "wof:placetype":"locality"
},
  "geometry": {"coordinates":[31.56902,30.85831],"type":"Point"}
}