{
  "type": "Feature",
  "properties": {
    "gn:admin1_code":"14.0",
    "gn:asciiname":"Tall Huwayn",
    "gn:country_code":"EG",
    "gn:dem":13,
    "gn:feature_class":"P",
    "gn:feature_code":"PPL",
    "gn:name":"Tall \u1e28uwayn",
    "gn:population":0,
    "gn:timezone":"Africa/Cairo",
    "iso:country":"EG",
    "name:ara_x_preferred":[
        "\u062a\u0644 \u062d\u0648\u064a\u0646"
    ],
    "name:und_x_variant":[
        "Tall \u1e28aw\u012bn",
        "Tell \u1e24aw\u00een",
        "Tall \u1e28uwayn"
    ],
    "wof:name":"Tall Huwayn",
    "wof:placetype":"locality"
},
  "geometry": {"coordinates":[31.43456,30.59318],"type":"Point"}
}