{
  "type": "Feature",
  "properties": {
    "gn:admin1_code":"03",
    "gn:asciiname":"Ash Shamasimah",
    "gn:country_code":"EG",
    "gn:dem":4,
    "gn:feature_class":"P",
    "gn:feature_code":"PPL",
    "gn:name":"Ash Sham\u0101simah",
    "gn:population":0,
    "gn:timezone":"Africa/Cairo",
    "iso:country":"EG",
    "name:ara_x_preferred":[
        "\u0627\u0644\u0634\u0645\u0627\u0633\u0645\u0629"
    ],
    "name:und_x_variant":[
        "El-Sham\u00e2sma",
        "Ash Sham\u0101simah"
    ],
    "wof:name":"Ash Shamasimah",
    "wof:placetype":"locality"
},
  "geometry": {"coordinates":[30.46056,31.32938],"type":"Point"}
}