{
  "type": "Feature",
  "properties": {
    "gn:admin1_code":"24",
    "gn:asciiname":"Al Hima'",
    "gn:country_code":"EG",
    "gn:dem":58,
    "gn:feature_class":"P",
    "gn:feature_code":"PPL",
    "gn:name":"Al \u1e28im\u0101\u2019",
    "gn:population":0,
    "gn:timezone":"Africa/Cairo",
    "iso:country":"EG",
    "name:und_x_variant":[
        "El \u1e24ima",
        "Al \u1e28im\u0101\u2019"
    ],
    "wof:name":"Al Hima'",
    "wof:placetype":"locality"
},
  "geometry": {"coordinates":[31.45,26.91667],"type":"Point"}
}