{
  "type": "Feature",
  "properties": {
    "gn:admin1_code":"16",
    "gn:asciiname":"Ash Shallal",
    "gn:country_code":"EG",
    "gn:dem":125,
    "gn:feature_class":"P",
    "gn:feature_code":"PPL",
    "gn:name":"Ash Shall\u0101l",
    "gn:population":0,
    "gn:timezone":"Africa/Cairo",
    "iso:country":"EG",
    "name:und_x_variant":[
        "Esh Shall\u0101l",
        "Shellal",
        "El-Shall\u00e2l",
        "Ash Shall\u0101l"
    ],
    "wof:name":"Ash Shallal",
    "wof:placetype":"locality"
},
  "geometry": {"coordinates":[32.91078,24.03685],"type":"Point"}
}