{
  "type": "Feature",
  "properties": {
    "gn:admin1_code":"21",
    "gn:asciiname":"Al `Amriyah",
    "gn:country_code":"EG",
    "gn:dem":3,
    "gn:feature_class":"P",
    "gn:feature_code":"PPL",
    "gn:name":"Al \u2018Amr\u012byah",
    "gn:population":0,
    "gn:timezone":"Africa/Cairo",
    "iso:country":"EG",
    "name:ara_x_preferred":[
        "\u0627\u0644\u0639\u0645\u0631\u064a\u0629"
    ],
    "name:und_x_variant":[
        "El-\u2018Amr\u00eeya",
        "Al \u2018Amr\u012byah",
        "Al-\u2018Amriyyah"
    ],
    "wof:name":"Al `Amriyah",
    "wof:placetype":"locality"
},
  "geometry": {"coordinates":[31.00648,31.58066],"type":"Point"}
}