{
  "type": "Feature",
  "properties": {
    "gn:admin1_code":"21",
    "gn:asciiname":"Kawm ad Dahab",
    "gn:country_code":"EG",
    "gn:dem":5,
    "gn:feature_class":"P",
    "gn:feature_code":"PPL",
    "gn:name":"Kawm ad Dahab",
    "gn:population":0,
    "gn:timezone":"Africa/Cairo",
    "iso:country":"EG",
    "name:ara_x_preferred":[
        "\u0643\u0648\u0645 \u0627\u0644\u062f\u0647\u0628"
    ],
    "name:und_x_variant":[
        "\u2018Ezbet K\u00f4m el-Dahab",
        "Kawm ad Dahab"
    ],
    "wof:name":"Kawm ad Dahab",
    "wof:placetype":"locality"
},
  "geometry": {"coordinates":[30.73829000000001,31.33893],"type":"Point"}
}