{
  "type": "Feature",
  "properties": {
    "gn:admin1_code":"03",
    "gn:asciiname":"`Izbat al Hamra'",
    "gn:country_code":"EG",
    "gn:dem":1,
    "gn:feature_class":"P",
    "gn:feature_code":"PPLF",
    "gn:name":"\u2018Izbat al \u1e28amr\u0101\u2019",
    "gn:population":0,
    "gn:timezone":"Africa/Cairo",
    "iso:country":"EG",
    "name:ara_x_preferred":[
        "\u0639\u0632\u0628\u0629 \u0627\u0644\u062d\u0645\u0631\u0627\u0621"
    ],
    "name:und_x_variant":[
        "\u2018Izbat al \u1e28amr\u0101\u2019",
        "\u2018Izbat al-\u1e24amr\u0101\u2018"
    ],
    "wof:name":"`Izbat al Hamra'",
    "wof:placetype":"locality"
},
  "geometry": {"coordinates":[30.27796,30.43524],"type":"Point"}
}