{
  "type": "Feature",
  "properties": {
    "gn:admin1_code":"03",
    "gn:asciiname":"`Izbat `Awad Shihatah",
    "gn:country_code":"EG",
    "gn:dem":2,
    "gn:feature_class":"P",
    "gn:feature_code":"PPL",
    "gn:name":"\u2018Izbat \u2018Awa\u1e11 Shi\u1e29\u0101tah",
    "gn:population":0,
    "gn:timezone":"Africa/Cairo",
    "iso:country":"EG",
    "name:ara_x_preferred":[
        "\u0639\u0632\u0628\u0629 \u0639\u0648\u0636 \u0634\u062d\u0627\u062a\u0629"
    ],
    "name:und_x_variant":[
        "\u2018Izbat \u2018Awa\u1e11 Shi\u1e29\u0101tah",
        "\u2018Izbat \u2018Awa\u1e0d Shi\u1e25\u0101tah"
    ],
    "wof:name":"`Izbat `Awad Shihatah",
    "wof:placetype":"locality"
},
  "geometry": {"coordinates":[30.45272000000001,31.07914],"type":"Point"}
}