{
  "type": "Feature",
  "properties": {
    "gn:admin1_code":"01",
    "gn:asciiname":"Taranish al Bahr",
    "gn:country_code":"EG",
    "gn:dem":4,
    "gn:feature_class":"P",
    "gn:feature_code":"PPL",
    "gn:name":"\u0162ar\u0101n\u012bsh al Ba\u1e29r",
    "gn:population":0,
    "gn:timezone":"Africa/Cairo",
    "iso:country":"EG",
    "wof:name":"Taranish al Bahr",
    "wof:placetype":"locality"
},
  "geometry": {"coordinates":[31.50694,31.15833],"type":"Point"}
}