{
  "type": "Feature",
  "properties": {
    "gn:admin1_code":"21",
    "gn:asciiname":"`Izbat Hasan al Ibrashi",
    "gn:country_code":"EG",
    "gn:dem":6,
    "gn:feature_class":"P",
    "gn:feature_code":"PPL",
    "gn:name":"\u2018Izbat \u1e28asan al Ibr\u0101sh\u012b",
    "gn:population":0,
    "gn:timezone":"Africa/Cairo",
    "iso:country":"EG",
    "name:ara_x_preferred":[
        "\u0639\u0632\u0628\u0629 \u062d\u0633\u0646 \u0627\u0644\u0625\u0628\u0631\u0627\u0634\u064a"
    ],
    "name:und_x_variant":[
        "\u2018Izbat \u1e28asan al Ibr\u0101sh\u012b",
        "\u2018Izbat \u1e24asan al-Ibr\u0101sh\u012b"
    ],
    "wof:name":"`Izbat Hasan al Ibrashi",
    "wof:placetype":"locality"
},
  "geometry": {"coordinates":[30.91337,31.24392000000001],"type":"Point"}
}