{
  "type": "Feature",
  "properties": {
    "gn:admin1_code":"14",
    "gn:asciiname":"`Izbat Ahmad Husayn",
    "gn:country_code":"EG",
    "gn:dem":10,
    "gn:feature_class":"P",
    "gn:feature_code":"PPL",
    "gn:name":"\u2018Izbat A\u1e29mad \u1e28usayn",
    "gn:population":0,
    "gn:timezone":"Africa/Cairo",
    "iso:country":"EG",
    "name:ara_x_preferred":[
        "\u0639\u0632\u0628\u0629 \u0623\u062d\u0645\u062f \u062d\u0633\u064a\u0646"
    ],
    "name:und_x_variant":[
        "\u2018Izbat A\u1e29mad \u1e28usayn"
    ],
    "wof:name":"`Izbat Ahmad Husayn",
    "wof:placetype":"locality"
},
  "geometry": {"coordinates":[31.57309,30.58065],"type":"Point"}
}