{
  "type": "Feature",
  "properties": {
    "iso:country":"EG",
    "qs:gn_pop":0,
    "qs:name":"Al Nasr City",
    "qs:name_adm0":"\u0645\u0635\u0631",
    "qs:name_adm1":"\u0627\u0644\u0627\u0633\u0643\u0646\u062f\u0631\u064a\u0629",
    "qs:photos":31,
    "qs:photos_1k":6,
    "qs:photos_9k":1,
    "qs:photos_9r":2,
    "qs:photos_all":31,
    "qs:photos_sr":2,
    "qs:placetype":"Suburb",
    "qs:pop_sr":"0",
    "qs:woe_adm0":23424802,
    "wof:name":"Al Nasr City",
    "wof:placetype":"neighbourhood"
},
  "geometry": {"coordinates":[29.988167,31.252393],"type":"Point"}
}