{
  "type": "Feature",
  "properties": {
    "gn:admin1_code":"12",
    "gn:asciiname":"Kafr ash Shurafa' al Qibli",
    "gn:country_code":"EG",
    "gn:dem":18,
    "gn:feature_class":"P",
    "gn:feature_code":"PPL",
    "gn:name":"Kafr ash Shuraf\u0101\u2019 al Qibl\u012b",
    "gn:population":0,
    "gn:timezone":"Africa/Cairo",
    "iso:country":"EG",
    "name:und_x_variant":[
        "Kafr el-Shurafa el-Qibli",
        "Kafr ash Shuraf\u0101\u2019 al Qibl\u012b"
    ],
    "wof:name":"Kafr ash Shurafa' al Qibli",
    "wof:placetype":"locality"
},
  "geometry": {"coordinates":[31.34526,30.36058],"type":"Point"}
}