{
  "type": "Feature",
  "properties": {
    "gn:country":"EG",
    "gn:fcode":"PPL",
    "gn:population":42708,
    "iso:country":"EG",
    "name:ara_x_preferred":[
        "\u0642\u0648\u064a\u0633\u0646\u0627"
    ],
    "name:arz_x_preferred":[
        "\u0642\u0648\u064a\u0633\u0646\u0627"
    ],
    "name:azb_x_preferred":[
        "\u0642\u0648\u06cc\u0633\u0646\u0627"
    ],
    "name:ceb_x_preferred":[
        "Quwaysin\u0101"
    ],
    "name:eng_x_preferred":[
        "Quweisna"
    ],
    "name:fas_x_preferred":[
        "\u0642\u0648\u06cc\u0633\u0646\u0627"
    ],
    "name:heb_x_preferred":[
        "\u05e7\u05d5\u05d9\u05e1\u05e0\u05d4"
    ],
    "name:mlg_x_preferred":[
        "Quwaysin\u0101"
    ],
    "name:nld_x_preferred":[
        "Quweisna"
    ],
    "name:pol_x_preferred":[
        "Kuweisna"
    ],
    "name:rus_x_preferred":[
        "\u041a\u0443\u0432\u0435\u0439\u0441\u0438\u043d\u0430"
    ],
    "name:swe_x_preferred":[
        "Quwaysin\u0101"
    ],
    "name:tha_x_preferred":[
        "\u0e01\u0e38\u0e27\u0e31\u0e22\u0e2a\u0e4c\u0e19\u0e32"
    ],
    "name:und_x_variant":[
        "Kuesnah"
    ],
    "name:zul_x_preferred":[
        "Quesna"
    ],
    "qs_pg:aaroncc":"EG",
    "qs_pg:gn_country":"EG",
    "qs_pg:gn_fcode":"PPL",
    "qs_pg:gn_pop":42708,
    "qs_pg:name":"Quwaysin\u0101",
    "qs_pg:photos_9r":0,
    "qs_pg:photos_sr":0,
    "qs_pg:pop_sr":7,
    "qs_pg:qs_pg_placetype":"locality",
    "wof:name":"Quwaysin\u0101",
    "wof:placetype":"locality",
    "wof:population":42708
},
  "geometry": {"coordinates":[31.15777,30.56482],"type":"Point"}
}