{
  "type": "Feature",
  "properties": {
    "gn:gn_country":"EG",
    "gn:gn_fcode":"PPL",
    "gn:gn_pop":42708,
    "gn:population":42708,
    "iso:country":"EG",
    "name:ara_x_preferred":[
        "\u0642\u0648\u064a\u0633\u0646\u0627"
    ],
    "name:eng_x_preferred":[
        "Quweisna"
    ],
    "name:nld_x_preferred":[
        "Quweisna"
    ],
    "name:pol_x_preferred":[
        "Kuweisna"
    ],
    "name:rus_x_preferred":[
        "\u041a\u0443\u0432\u0435\u0439\u0441\u0438\u043d\u0430"
    ],
    "name:swe_x_preferred":[
        "Quwaysin\u0101"
    ],
    "name:unk_x_variant":[
        "Kuesnah"
    ],
    "qs_pg:aaroncc":"EG",
    "qs_pg:gn_country":"EG",
    "qs_pg:gn_fcode":"PPL",
    "qs_pg:gn_pop":42708,
    "qs_pg:name":"Quwaysin\u0101",
    "qs_pg:photos_9r":0,
    "qs_pg:photos_sr":0,
    "qs_pg:pop_sr":7,
    "qs_pg:qs_pg_placetype":"locality",
    "wof:name":"Quwaysin\u0101",
    "wof:placetype":"locality",
    "wof:population":42708
},
  "geometry": {"coordinates":[31.15777,30.56482],"type":"Point"}
}