{
  "type": "Feature",
  "properties": {
    "gn:admin1_code":"21",
    "gn:asciiname":"`Izbat al Mala`ib",
    "gn:country_code":"EG",
    "gn:dem":4,
    "gn:feature_class":"P",
    "gn:feature_code":"PPL",
    "gn:name":"\u2018Izbat al Mal\u0101\u2018ib",
    "gn:population":0,
    "gn:timezone":"Africa/Cairo",
    "iso:country":"EG",
    "name:ara_x_preferred":[
        "\u0639\u0632\u0628\u0629 \u0627\u0644\u0645\u0644\u0627\u0639\u0628"
    ],
    "name:und_x_variant":[
        "\u2018Izbat al Mal\u0101\u2018ib"
    ],
    "wof:name":"`Izbat al Mala`ib",
    "wof:placetype":"locality"
},
  "geometry": {"coordinates":[30.70044,31.16551],"type":"Point"}
}