{
  "type": "Feature",
  "properties": {
    "gn:admin1_code":"01",
    "gn:asciiname":"`Izbat Turil",
    "gn:country_code":"EG",
    "gn:dem":6,
    "gn:feature_class":"P",
    "gn:feature_code":"PPL",
    "gn:name":"\u2018Izbat \u0162\u016br\u012bl",
    "gn:population":0,
    "gn:timezone":"Africa/Cairo",
    "iso:country":"EG",
    "name:ara_x_preferred":[
        "\u0639\u0632\u0628\u0629 \u0637\u0648\u0631\u064a\u0644"
    ],
    "name:und_x_variant":[
        "\u2018Izbat \u0162\u016br\u012bl"
    ],
    "wof:name":"`Izbat Turil",
    "wof:placetype":"locality"
},
  "geometry": {"coordinates":[31.58071,30.99053],"type":"Point"}
}