{
  "type": "Feature",
  "properties": {
    "gn:admin1_code":"05",
    "gn:asciiname":"`Izbat `Abd al Majid ash Shadhli",
    "gn:country_code":"EG",
    "gn:dem":5,
    "gn:feature_class":"P",
    "gn:feature_code":"PPL",
    "gn:name":"\u2018Izbat \u2018Abd al Maj\u012bd ash Sh\u0101dhl\u012b",
    "gn:population":0,
    "gn:timezone":"Africa/Cairo",
    "iso:country":"EG",
    "name:ara_x_preferred":[
        "\u0639\u0632\u0628\u0629 \u0639\u0628\u062f \u0627\u0644\u0645\u062c\u064a\u062f \u0627\u0644\u0634\u0627\u0630\u0644\u064a"
    ],
    "name:und_x_variant":[
        "\u2018Izbat \u2018Abd al Maj\u012bd ash Sh\u0101dhl\u012b",
        "\u2018Izbat \u2018Abd al-Mij\u012bd ash-Sh\u0101dhl\u012b"
    ],
    "wof:name":"`Izbat `Abd al Majid ash Shadhli",
    "wof:placetype":"locality"
},
  "geometry": {"coordinates":[30.8533,31.00208],"type":"Point"}
}