{
  "type": "Feature",
  "properties": {
    "gn:admin1_code":"10",
    "gn:asciiname":"Saqiyat Musa",
    "gn:country_code":"EG",
    "gn:dem":45,
    "gn:feature_class":"P",
    "gn:feature_code":"PPL",
    "gn:name":"S\u0101qiyat M\u016bs\u00e1",
    "gn:population":0,
    "gn:timezone":"Africa/Cairo",
    "iso:country":"EG",
    "name:und_x_variant":[
        "S\u00e2qyet M\u00fbsa",
        "S\u0101qiyat M\u016bs\u00e1"
    ],
    "wof:name":"Saqiyat Musa",
    "wof:placetype":"locality"
},
  "geometry": {"coordinates":[30.81479,27.86587],"type":"Point"}
}