{
  "type": "Feature",
  "properties": {
    "gn:admin1_code":"21",
    "gn:asciiname":"`Izbat Yahya",
    "gn:country_code":"EG",
    "gn:dem":6,
    "gn:feature_class":"P",
    "gn:feature_code":"PPL",
    "gn:name":"\u2018Izbat Ya\u1e29y\u00e1",
    "gn:population":0,
    "gn:timezone":"Africa/Cairo",
    "iso:country":"EG",
    "name:ara_x_preferred":[
        "\u0639\u0632\u0628\u0629 \u064a\u062d\u064a\u0649"
    ],
    "name:und_x_variant":[
        "\u2018Izbat Ya\u1e29y\u00e1",
        "\u2018Izbat Ya\u1e25y\u00e1"
    ],
    "wof:name":"`Izbat Yahya",
    "wof:placetype":"locality"
},
  "geometry": {"coordinates":[30.77172,31.14901],"type":"Point"}
}