{
  "type": "Feature",
  "properties": {
    "gn:admin1_code":"03",
    "gn:asciiname":"`Izbat Sarhan",
    "gn:country_code":"EG",
    "gn:dem":0,
    "gn:feature_class":"P",
    "gn:feature_code":"PPL",
    "gn:name":"\u2018Izbat Sar\u1e29\u0101n",
    "gn:population":0,
    "gn:timezone":"Africa/Cairo",
    "iso:country":"EG",
    "name:ara_x_preferred":[
        "\u0639\u0632\u0628\u0629 \u0633\u0631\u062d\u0627\u0646"
    ],
    "name:und_x_variant":[
        "\u2018Izbat Sar\u1e29\u0101n",
        "\u2018Izbat Sar\u1e25\u0101n",
        "\u2018Izbat Sir\u1e29\u0101n"
    ],
    "wof:name":"`Izbat Sarhan",
    "wof:placetype":"locality"
},
  "geometry": {"coordinates":[30.46138,31.23989000000001],"type":"Point"}
}