{
  "type": "Feature",
  "properties": {
    "gn:admin1_code":"13",
    "gn:asciiname":"`Ezbet Muhammad Tuleib",
    "gn:country_code":"EG",
    "gn:dem":77,
    "gn:feature_class":"P",
    "gn:feature_code":"PPL",
    "gn:name":"\u2018Ezbet Mu\u1e29ammad Tuleib",
    "gn:population":0,
    "gn:timezone":"Africa/Cairo",
    "iso:country":"EG",
    "wof:name":"`Ezbet Muhammad Tuleib",
    "wof:placetype":"locality"
},
  "geometry": {"coordinates":[30.61667000000001,25.68333],"type":"Point"}
}