{
  "type": "Feature",
  "properties": {
    "gn:admin1_code":"01",
    "gn:asciiname":"`Izbat al Hishah",
    "gn:country_code":"EG",
    "gn:dem":6,
    "gn:feature_class":"P",
    "gn:feature_code":"PPL",
    "gn:name":"\u2018Izbat al H\u012bshah",
    "gn:population":0,
    "gn:timezone":"Africa/Cairo",
    "iso:country":"EG",
    "name:ara_x_preferred":[
        "\u0639\u0632\u0628\u0629 \u0627\u0644\u0647\u064a\u0634\u0629"
    ],
    "name:und_x_variant":[
        "\u2018Izbat al H\u012bshah",
        "\u2018Izbat Al-H\u012bshah"
    ],
    "wof:name":"`Izbat al Hishah",
    "wof:placetype":"locality"
},
  "geometry": {"coordinates":[31.76532000000001,31.09697],"type":"Point"}
}