{
  "type": "Feature",
  "properties": {
    "gn:admin1_code":"18",
    "gn:asciiname":"Minshat Abu Milih",
    "gn:country_code":"EG",
    "gn:dem":31,
    "gn:feature_class":"P",
    "gn:feature_code":"PPL",
    "gn:name":"Minsh\u0101t Ab\u016b Mil\u012b\u1e29",
    "gn:population":0,
    "gn:timezone":"Africa/Cairo",
    "iso:country":"EG",
    "name:und_x_variant":[
        "Minsh\u0101t Ab\u016b Mal\u012b\u1e29",
        "Minsh\u0101t Ab\u016b Mil\u012b\u1e29"
    ],
    "wof:name":"Minshat Abu Milih",
    "wof:placetype":"locality"
},
  "geometry": {"coordinates":[30.90489,28.96323],"type":"Point"}
}