{
  "type": "Feature",
  "properties": {
    "gn:admin1_code":"14",
    "gn:asciiname":"`Izbat `Ilaywah",
    "gn:country_code":"EG",
    "gn:dem":11,
    "gn:feature_class":"P",
    "gn:feature_code":"PPL",
    "gn:name":"\u2018Izbat \u2018Ilaywah",
    "gn:population":0,
    "gn:timezone":"Africa/Cairo",
    "iso:country":"EG",
    "name:ara_x_preferred":[
        "\u0639\u0632\u0628\u0629 \u0639\u0644\u064a\u0648\u0647"
    ],
    "name:und_x_variant":[
        "\u2018Izbat \u2018Ilaywah",
        "\u2018Ezbet \u2018Abd el-Rahm\u00e2n \u2018Ileiwa"
    ],
    "wof:name":"`Izbat `Ilaywah",
    "wof:placetype":"locality"
},
  "geometry": {"coordinates":[31.96207,30.88712],"type":"Point"}
}