{
  "type": "Feature",
  "properties": {
    "gn:admin1_code":"14",
    "gn:asciiname":"`Izbat Ya`qub",
    "gn:country_code":"EG",
    "gn:dem":7,
    "gn:feature_class":"P",
    "gn:feature_code":"PPL",
    "gn:name":"\u2018Izbat Ya\u2018q\u016bb",
    "gn:population":0,
    "gn:timezone":"Africa/Cairo",
    "iso:country":"EG",
    "name:ara_x_preferred":[
        "\u0639\u0632\u0628\u0629 \u064a\u0639\u0642\u0648\u0628"
    ],
    "name:und_x_variant":[
        "\u2018Izbat Ya\u2018q\u016bb"
    ],
    "wof:name":"`Izbat Ya`qub",
    "wof:placetype":"locality"
},
  "geometry": {"coordinates":[31.58848,30.81826],"type":"Point"}
}