{
  "type": "Feature",
  "properties": {
    "gn:admin1_code":"14",
    "gn:asciiname":"`Izbat Ghanim as Salik",
    "gn:country_code":"EG",
    "gn:dem":10,
    "gn:feature_class":"P",
    "gn:feature_code":"PPL",
    "gn:name":"\u2018Izbat Gh\u0101nim as S\u0101lik",
    "gn:population":0,
    "gn:timezone":"Africa/Cairo",
    "iso:country":"EG",
    "name:ara_x_preferred":[
        "\u0639\u0632\u0628\u0629 \u063a\u0627\u0646\u0645 \u0627\u0644\u0633\u0627\u0644\u0643"
    ],
    "name:und_x_variant":[
        "\u2018Izbat Gh\u0101nim as S\u0101lik"
    ],
    "wof:name":"`Izbat Ghanim as Salik",
    "wof:placetype":"locality"
},
  "geometry": {"coordinates":[31.65537,30.56787000000001],"type":"Point"}
}