{
  "type": "Feature",
  "properties": {
    "gn:admin1_code":"12",
    "gn:asciiname":"Mit al Hufiyin",
    "gn:country_code":"EG",
    "gn:dem":17,
    "gn:feature_class":"P",
    "gn:feature_code":"PPL",
    "gn:name":"M\u012bt al \u1e28\u016bfiy\u012bn",
    "gn:population":0,
    "gn:timezone":"Africa/Cairo",
    "iso:country":"EG",
    "name:ara_x_preferred":[
        "\u0645\u064a\u062a \u0627\u0644\u062d\u0648\u0641\u064a\u064a\u0646"
    ],
    "name:und_x_variant":[
        "M\u00eet el-\u1e24\u00fbfiy\u00een",
        "M\u012bt al \u1e28\u016bfiy\u012bn"
    ],
    "wof:name":"Mit al Hufiyin",
    "wof:placetype":"locality"
},
  "geometry": {"coordinates":[31.20935,30.51615],"type":"Point"}
}