{
  "type": "Feature",
  "properties": {
    "gn:admin1_code":"13",
    "gn:asciiname":"Naj` al Ghabat",
    "gn:country_code":"EG",
    "gn:dem":83,
    "gn:feature_class":"P",
    "gn:feature_code":"PPL",
    "gn:name":"Naj\u2018 al Gh\u0101b\u0101t",
    "gn:population":0,
    "gn:timezone":"Africa/Cairo",
    "iso:country":"EG",
    "name:und_x_variant":[
        "Nag\u2019 el-Gh\u00e2b\u00e2t",
        "Naj\u2018 al Gh\u0101b\u0101t"
    ],
    "wof:name":"Naj` al Ghabat",
    "wof:placetype":"locality"
},
  "geometry": {"coordinates":[31.94695,26.16838],"type":"Point"}
}