{
  "type": "Feature",
  "properties": {
    "gn:admin1_code":"10",
    "gn:asciiname":"Abyuha",
    "gn:country_code":"EG",
    "gn:dem":48,
    "gn:feature_class":"P",
    "gn:feature_code":"PPL",
    "gn:name":"Aby\u016bh\u0101",
    "gn:population":0,
    "gn:timezone":"Africa/Cairo",
    "iso:country":"EG",
    "wof:name":"Abyuha",
    "wof:placetype":"locality"
},
  "geometry": {"coordinates":[30.83039,27.96642],"type":"Point"}
}