{
  "type": "Feature",
  "properties": {
    "gn:admin1_code":"14",
    "gn:asciiname":"`Izbat `Abd al Majid Fawzi",
    "gn:country_code":"EG",
    "gn:dem":10,
    "gn:feature_class":"P",
    "gn:feature_code":"PPL",
    "gn:name":"\u2018Izbat \u2018Abd al Maj\u012bd Fawz\u012b",
    "gn:population":0,
    "gn:timezone":"Africa/Cairo",
    "iso:country":"EG",
    "name:ara_x_preferred":[
        "\u0639\u0632\u0628\u0629 \u0639\u0628\u062f \u0627\u0644\u0645\u062c\u064a\u062f \u0641\u0648\u0632\u064a"
    ],
    "name:und_x_variant":[
        "\u2018Izbat \u2018Abd al Maj\u012bd Fawz\u012b"
    ],
    "wof:name":"`Izbat `Abd al Majid Fawzi",
    "wof:placetype":"locality"
},
  "geometry": {"coordinates":[31.52508,30.69244],"type":"Point"}
}