{
  "type": "Feature",
  "properties": {
    "gn:admin1_code":"09",
    "gn:asciiname":"Mit `Afif",
    "gn:country_code":"EG",
    "gn:dem":18,
    "gn:feature_class":"P",
    "gn:feature_code":"PPL",
    "gn:name":"M\u012bt \u2018Af\u012bf",
    "gn:population":0,
    "gn:timezone":"Africa/Cairo",
    "iso:country":"EG",
    "name:ara_x_preferred":[
        "M\u012bt \u2018Af\u012bf"
    ],
    "name:ara_x_variant":[
        "\u0645\u064a\u062a \u0639\u0641\u064a\u0641"
    ],
    "wof:name":"Mit `Afif",
    "wof:placetype":"locality"
},
  "geometry": {"coordinates":[31.09413,30.3886],"type":"Point"}
}