{
  "type": "Feature",
  "properties": {
    "gn:admin1_code":"17",
    "gn:asciiname":"Naj` ash Shaykh Musa`id",
    "gn:country_code":"EG",
    "gn:dem":43,
    "gn:feature_class":"P",
    "gn:feature_code":"PPL",
    "gn:name":"Naj\u2018 ash Shaykh Mus\u0101\u2018id",
    "gn:population":0,
    "gn:timezone":"Africa/Cairo",
    "iso:country":"EG",
    "name:und_x_variant":[
        "Nazlet el Sheikh Mis\u00e2\u2018id",
        "Nag\u2018 el Sheikh Mis\u00e2\u2018id",
        "Naj\u2018 ash Shaykh Mus\u0101\u2018id"
    ],
    "wof:name":"Naj` ash Shaykh Musa`id",
    "wof:placetype":"locality"
},
  "geometry": {"coordinates":[30.76667,27.48333],"type":"Point"}
}