{
  "type": "Feature",
  "properties": {
    "gn:admin1_code":"14",
    "gn:asciiname":"Kafr Hajji",
    "gn:cc2":"EG",
    "gn:country_code":"EG",
    "gn:dem":8,
    "gn:feature_class":"P",
    "gn:feature_code":"PPL",
    "gn:name":"Kafr \u1e28ajj\u012b",
    "gn:population":0,
    "gn:timezone":"Africa/Cairo",
    "iso:country":"EG",
    "name:und_x_variant":[
        "Kafr Higgi",
        "Kafr Haggi",
        "Kafr \u1e28ajj\u012b"
    ],
    "wof:name":"Kafr Hajji",
    "wof:placetype":"locality"
},
  "geometry": {"coordinates":[31.61667000000001,30.76667],"type":"Point"}
}