{
  "type": "Feature",
  "properties": {
    "gn:admin1_code":"01",
    "gn:asciiname":"Mit Faris",
    "gn:country_code":"EG",
    "gn:dem":7,
    "gn:feature_class":"P",
    "gn:feature_code":"PPL",
    "gn:name":"M\u012bt F\u0101ris",
    "gn:population":0,
    "gn:timezone":"Africa/Cairo",
    "iso:country":"EG",
    "name:ara_x_preferred":[
        "M\u012bt F\u0101ris"
    ],
    "name:ara_x_variant":[
        "\u0645\u064a\u062a \u0641\u0627\u0631\u0633"
    ],
    "name:und_x_variant":[
        "M\u012bt F\u0101ris wa Kafrih\u0101",
        "Mit Faras wa Kafraha",
        "M\u00eet F\u00e2ris"
    ],
    "wof:name":"Mit Faris",
    "wof:placetype":"locality"
},
  "geometry": {"coordinates":[31.60645,31.04019000000001],"type":"Point"}
}