{
  "type": "Feature",
  "properties": {
    "gn:admin1_code":"01",
    "gn:asciiname":"`Izbat Ghunaym as Saghirah",
    "gn:country_code":"EG",
    "gn:dem":7,
    "gn:feature_class":"P",
    "gn:feature_code":"PPL",
    "gn:name":"\u2018Izbat Ghunaym a\u015f \u015eagh\u012brah",
    "gn:population":0,
    "gn:timezone":"Africa/Cairo",
    "iso:country":"EG",
    "name:ara_x_preferred":[
        "\u0639\u0632\u0628\u0629 \u063a\u0646\u064a\u0645 \u0627\u0644\u0635\u063a\u064a\u0631\u0629"
    ],
    "name:und_x_variant":[
        "\u2018Izbat Ghunaym a\u015f \u015eagh\u012brah"
    ],
    "wof:name":"`Izbat Ghunaym as Saghirah",
    "wof:placetype":"locality"
},
  "geometry": {"coordinates":[31.5009,31.25472],"type":"Point"}
}