{
  "type": "Feature",
  "properties": {
    "gn:admin1_code":"14",
    "gn:asciiname":"`Izbat Harun",
    "gn:country_code":"EG",
    "gn:dem":11,
    "gn:feature_class":"P",
    "gn:feature_code":"PPL",
    "gn:name":"\u2018Izbat H\u0101r\u016bn",
    "gn:population":0,
    "gn:timezone":"Africa/Cairo",
    "iso:country":"EG",
    "name:ara_x_preferred":[
        "\u0639\u0632\u0628\u0629 \u0647\u0627\u0631\u0648\u0646"
    ],
    "name:und_x_variant":[
        "\u2018Izbat H\u0101r\u016bn"
    ],
    "wof:name":"`Izbat Harun",
    "wof:placetype":"locality"
},
  "geometry": {"coordinates":[31.52185,30.42462],"type":"Point"}
}