{
  "type": "Feature",
  "properties": {
    "gn:admin1_code":"21",
    "gn:asciiname":"`Izbat Khayr Allah",
    "gn:country_code":"EG",
    "gn:dem":6,
    "gn:feature_class":"P",
    "gn:feature_code":"PPL",
    "gn:name":"\u2018Izbat Khayr All\u0101h",
    "gn:population":0,
    "gn:timezone":"Africa/Cairo",
    "iso:country":"EG",
    "name:ara_x_preferred":[
        "\u0639\u0632\u0628\u0629 \u062e\u064a\u0631 \u0627\u0644\u0644\u0647"
    ],
    "name:und_x_variant":[
        "\u2018Izbat Khayr All\u0101h",
        "\u2018Izbat Khayr Allah"
    ],
    "wof:name":"`Izbat Khayr Allah",
    "wof:placetype":"locality"
},
  "geometry": {"coordinates":[30.96748,31.20716],"type":"Point"}
}