{
  "type": "Feature",
  "properties": {
    "gn:admin1_code":"24",
    "gn:asciiname":"Al-Qusah",
    "gn:country_code":"EG",
    "gn:dem":71,
    "gn:feature_class":"P",
    "gn:feature_code":"PPL",
    "gn:name":"Al-Q\u016b\u015fah",
    "gn:population":0,
    "gn:timezone":"Africa/Cairo",
    "iso:country":"EG",
    "name:und_x_variant":[
        "El-Q\u00fbs\u00eeya",
        "Al-Q\u016b\u015fah"
    ],
    "wof:name":"Al-Qusah",
    "wof:placetype":"locality"
},
  "geometry": {"coordinates":[32.15643,26.1703],"type":"Point"}
}