{
  "type": "Feature",
  "properties": {
    "gn:admin1_code":"14",
    "gn:asciiname":"`Izbat al Marazi`ah",
    "gn:country_code":"EG",
    "gn:dem":12,
    "gn:feature_class":"P",
    "gn:feature_code":"PPL",
    "gn:name":"\u2018Izbat al Mar\u0101z\u012b\u2018ah",
    "gn:population":0,
    "gn:timezone":"Africa/Cairo",
    "iso:country":"EG",
    "name:ara_x_preferred":[
        "\u0639\u0632\u0628\u0629 \u0627\u0644\u0645\u0631\u0627\u0632\u064a\u0639\u0629"
    ],
    "name:und_x_variant":[
        "El-Maz\u00e2r\u2018a",
        "Al Maz\u0101ri\u2018ah",
        "\u2018Izbat al Mar\u0101z\u012b\u2018ah"
    ],
    "wof:name":"`Izbat al Marazi`ah",
    "wof:placetype":"locality"
},
  "geometry": {"coordinates":[31.89649,30.55304000000001],"type":"Point"}
}