{
  "type": "Feature",
  "properties": {
    "gn:admin1_code":"01",
    "gn:asciiname":"`Izbat al Hidadah",
    "gn:country_code":"EG",
    "gn:dem":5,
    "gn:feature_class":"P",
    "gn:feature_code":"PPL",
    "gn:name":"\u2018Izbat al Hid\u0101dah",
    "gn:population":0,
    "gn:timezone":"Africa/Cairo",
    "iso:country":"EG",
    "name:ara_x_preferred":[
        "\u0639\u0632\u0628\u0629 \u0627\u0644\u062d\u062f\u0627\u062f\u0629"
    ],
    "name:und_x_variant":[
        "\u2018Izbat al Hid\u0101dah",
        "\u2018Izbat al \u1e28add\u0101dah"
    ],
    "wof:name":"`Izbat al Hidadah",
    "wof:placetype":"locality"
},
  "geometry": {"coordinates":[31.76281,31.04774],"type":"Point"}
}