{
  "type": "Feature",
  "properties": {
    "gn:admin1_code":"09",
    "gn:asciiname":"`Izbat Astasiyah",
    "gn:country_code":"EG",
    "gn:dem":15,
    "gn:feature_class":"P",
    "gn:feature_code":"PPL",
    "gn:name":"\u2018Izbat As\u0163\u0101siyah",
    "gn:population":0,
    "gn:timezone":"Africa/Cairo",
    "iso:country":"EG",
    "name:ara_x_preferred":[
        "\u0639\u0632\u0628\u0629 \u0627\u0633\u0637\u0627\u0633\u064a\u0629"
    ],
    "name:und_x_variant":[
        "\u2018Izbat As\u0163\u0101siyah",
        "\u2018Izbat As\u0163\u0101syah"
    ],
    "wof:name":"`Izbat Astasiyah",
    "wof:placetype":"locality"
},
  "geometry": {"coordinates":[31.02832,30.27612],"type":"Point"}
}