{
  "type": "Feature",
  "properties": {
    "gn:admin1_code":"21",
    "gn:asciiname":"`Izbat Minashshi ash Sharqiyah",
    "gn:country_code":"EG",
    "gn:dem":8,
    "gn:feature_class":"P",
    "gn:feature_code":"PPL",
    "gn:name":"\u2018Izbat Minashsh\u012b ash Sharq\u012byah",
    "gn:population":0,
    "gn:timezone":"Africa/Cairo",
    "iso:country":"EG",
    "name:ara_x_preferred":[
        "\u0639\u0632\u0628\u0629 \u0645\u0646\u0634\u064a \u0627\u0644\u0634\u0631\u0642\u064a\u0629"
    ],
    "name:und_x_variant":[
        "\u2018Izbat Minashsh\u012b ash Sharq\u012byah",
        "\u2018Izbat Minashsh\u012b ash-Sharqiyyah"
    ],
    "wof:name":"`Izbat Minashshi ash Sharqiyah",
    "wof:placetype":"locality"
},
  "geometry": {"coordinates":[31.0663,31.22562000000001],"type":"Point"}
}