{
  "type": "Feature",
  "properties": {
    "gn:admin1_code":"04",
    "gn:asciiname":"`Izbat Anwar `Ali Salih",
    "gn:country_code":"EG",
    "gn:dem":15,
    "gn:feature_class":"P",
    "gn:feature_code":"PPL",
    "gn:name":"\u2018Izbat Anwar \u2018Al\u012b \u015e\u0101li\u1e29",
    "gn:population":0,
    "gn:timezone":"Africa/Cairo",
    "iso:country":"EG",
    "wof:name":"`Izbat Anwar `Ali Salih",
    "wof:placetype":"locality"
},
  "geometry": {"coordinates":[30.82246,29.17855],"type":"Point"}
}