{
  "type": "Feature",
  "properties": {
    "gn:admin1_code":"14",
    "gn:asciiname":"Mubashir",
    "gn:country_code":"EG",
    "gn:dem":12,
    "gn:feature_class":"P",
    "gn:feature_code":"PPL",
    "gn:name":"Mub\u0101shir",
    "gn:population":0,
    "gn:timezone":"Africa/Cairo",
    "iso:country":"EG",
    "name:ara_x_preferred":[
        "Mub\u0101shir"
    ],
    "name:ara_x_variant":[
        "\u0645\u0628\u0627\u0634\u0631"
    ],
    "wof:name":"Mubashir",
    "wof:placetype":"locality"
},
  "geometry": {"coordinates":[31.51254,30.71726],"type":"Point"}
}