{
  "type": "Feature",
  "properties": {
    "gn:admin1_code":"09",
    "gn:asciiname":"Al Hilwasi",
    "gn:country_code":"EG",
    "gn:dem":20,
    "gn:feature_class":"P",
    "gn:feature_code":"PPL",
    "gn:name":"Al \u1e28ilw\u0101\u015f\u012b",
    "gn:population":0,
    "gn:timezone":"Africa/Cairo",
    "iso:country":"EG",
    "name:ara_x_preferred":[
        "Al \u1e28ilw\u0101\u015f\u012b"
    ],
    "name:ara_x_variant":[
        "\u0627\u0644\u062d\u0644\u0648\u0627\u0635\u064a"
    ],
    "name:und_x_variant":[
        "El-Hilw\u00e2\u015fi",
        "Helw\u00e2si",
        "El Helwasi",
        "Al \u2019ilw\u0101\u015f\u012b"
    ],
    "wof:name":"Al Hilwasi",
    "wof:placetype":"locality"
},
  "geometry": {"coordinates":[31.0577,30.24809],"type":"Point"}
}