{
  "type": "Feature",
  "properties": {
    "gn:admin1_code":"21",
    "gn:asciiname":"`Izbat Hasan `Uthman",
    "gn:country_code":"EG",
    "gn:dem":6,
    "gn:feature_class":"P",
    "gn:feature_code":"PPL",
    "gn:name":"\u2018Izbat \u1e28asan \u2018Uthm\u0101n",
    "gn:population":0,
    "gn:timezone":"Africa/Cairo",
    "iso:country":"EG",
    "name:ara_x_preferred":[
        "\u0639\u0632\u0628\u0629 \u062d\u0633\u0646 \u0639\u062b\u0645\u0627\u0646"
    ],
    "name:und_x_variant":[
        "\u2018Izbat \u1e28asan \u2018Uthm\u0101n",
        "\u2018Izbat \u1e24asan \u2018Uthm\u0101n"
    ],
    "wof:name":"`Izbat Hasan `Uthman",
    "wof:placetype":"locality"
},
  "geometry": {"coordinates":[30.86073,31.23369000000001],"type":"Point"}
}