{
  "type": "Feature",
  "properties": {
    "gn:admin1_code":"14",
    "gn:asciiname":"Al Wafayidah",
    "gn:country_code":"EG",
    "gn:dem":7,
    "gn:feature_class":"P",
    "gn:feature_code":"PPL",
    "gn:name":"Al Waf\u0101yidah",
    "gn:population":0,
    "gn:timezone":"Africa/Cairo",
    "iso:country":"EG",
    "name:ara_x_preferred":[
        "\u0627\u0644\u0648\u0641\u0627\u064a\u062f\u0629"
    ],
    "name:und_x_variant":[
        "Al Waf\u0101yidah",
        "Al-Waf\u0101ydah"
    ],
    "wof:name":"Al Wafayidah",
    "wof:placetype":"locality"
},
  "geometry": {"coordinates":[32.02176,30.81639],"type":"Point"}
}