{
  "type": "Feature",
  "properties": {
    "gn:admin1_code":"14",
    "gn:asciiname":"`Izbat Mustafa Hilmi",
    "gn:country_code":"EG",
    "gn:dem":7,
    "gn:feature_class":"P",
    "gn:feature_code":"PPL",
    "gn:name":"\u2018Izbat Mu\u015f\u0163af\u00e1 \u1e28ilm\u012b",
    "gn:population":0,
    "gn:timezone":"Africa/Cairo",
    "iso:country":"EG",
    "name:ara_x_preferred":[
        "\u0639\u0632\u0628\u0629 \u0645\u0635\u0637\u0641\u0649 \u062d\u0644\u0645\u064a"
    ],
    "name:und_x_variant":[
        "\u2018Izbat Mu\u015f\u0163af\u00e1 \u1e28ilm\u012b"
    ],
    "wof:name":"`Izbat Mustafa Hilmi",
    "wof:placetype":"locality"
},
  "geometry": {"coordinates":[31.697,30.74781],"type":"Point"}
}