{
  "type": "Feature",
  "properties": {
    "gn:admin1_code":"23",
    "gn:asciiname":"Faw Qibli",
    "gn:country_code":"EG",
    "gn:dem":76,
    "gn:feature_class":"P",
    "gn:feature_code":"PPL",
    "gn:name":"F\u0101w Qibl\u012b",
    "gn:population":0,
    "gn:timezone":"Africa/Cairo",
    "iso:country":"EG",
    "name:und_x_variant":[
        "F\u0101u Qibli",
        "F\u00e2w",
        "F\u0101w Qibl\u012b"
    ],
    "wof:name":"Faw Qibli",
    "wof:placetype":"locality"
},
  "geometry": {"coordinates":[32.40495,26.11257],"type":"Point"}
}