{
  "type": "Feature",
  "properties": {
    "gn:admin1_code":"02",
    "gn:asciiname":"`Arab Mutayr",
    "gn:country_code":"EG",
    "gn:dem":56,
    "gn:feature_class":"P",
    "gn:feature_code":"PPL",
    "gn:name":"\u2018Arab Mu\u0163ayr",
    "gn:population":0,
    "gn:timezone":"Africa/Cairo",
    "iso:country":"EG",
    "name:und_x_variant":[
        "\u2018Arab Miteir",
        "\u2018Arab Hat\u012bm",
        "\u2018Arab Mu\u0163ayr"
    ],
    "wof:name":"`Arab Mutayr",
    "wof:placetype":"locality"
},
  "geometry": {"coordinates":[31.23841,27.2627],"type":"Point"}
}