{
  "type": "Feature",
  "properties": {
    "gn:admin1_code":"08",
    "gn:asciiname":"Baharmis",
    "gn:country_code":"EG",
    "gn:dem":23,
    "gn:feature_class":"P",
    "gn:feature_code":"PPL",
    "gn:name":"Baharmis",
    "gn:population":0,
    "gn:timezone":"Africa/Cairo",
    "iso:country":"EG",
    "name:ara_x_preferred":[
        "\u0628\u0647\u0631\u0645\u0633"
    ],
    "name:und_x_variant":[
        "Baharmis wa as Sab\u012bl",
        "Baharmis and El-Sib\u00eel",
        "Baharmis"
    ],
    "wof:name":"Baharmis",
    "wof:placetype":"locality"
},
  "geometry": {"coordinates":[31.10731,30.16761],"type":"Point"}
}