{
  "type": "Feature",
  "properties": {
    "gn:admin1_code":"12",
    "gn:asciiname":"Kafr at Turjuman",
    "gn:country_code":"EG",
    "gn:dem":26,
    "gn:feature_class":"P",
    "gn:feature_code":"PPL",
    "gn:name":"Kafr at Turjum\u0101n",
    "gn:population":0,
    "gn:timezone":"Africa/Cairo",
    "iso:country":"EG",
    "name:ara_x_preferred":[
        "\u0643\u0641\u0631 \u0627\u0644\u062a\u0631\u062c\u0645\u0627\u0646"
    ],
    "name:und_x_variant":[
        "Kafr el-Turgum\u00e2n",
        "Kafr at Turjum\u0101n"
    ],
    "wof:name":"Kafr at Turjuman",
    "wof:placetype":"locality"
},
  "geometry": {"coordinates":[31.09557,30.02731],"type":"Point"}
}