{
  "type": "Feature",
  "properties": {
    "gn:admin1_code":"03",
    "gn:asciiname":"Nizarat Buwayt",
    "gn:country_code":"EG",
    "gn:dem":3,
    "gn:feature_class":"P",
    "gn:feature_code":"PPL",
    "gn:name":"Niz\u0327\u0101rat Buway\u0163",
    "gn:population":0,
    "gn:timezone":"Africa/Cairo",
    "iso:country":"EG",
    "name:ara_x_preferred":[
        "\u0646\u0638\u0627\u0631\u0629 \u0628\u0648\u064a\u0637"
    ],
    "name:und_x_variant":[
        "Ni\u1e95aret B\u00fbwei\u1e6d",
        "Niz\u0327\u0101rat Buway\u0163",
        "Ni\u1e93\u0101rat Buwayt"
    ],
    "wof:name":"Nizarat Buwayt",
    "wof:placetype":"locality"
},
  "geometry": {"coordinates":[30.532,31.09027],"type":"Point"}
}