{
  "type": "Feature",
  "properties": {
    "gn:admin1_code":"05",
    "gn:asciiname":"`Izbat Jamilah",
    "gn:country_code":"EG",
    "gn:dem":8,
    "gn:feature_class":"P",
    "gn:feature_code":"PPL",
    "gn:name":"\u2018Izbat Jam\u012blah",
    "gn:population":0,
    "gn:timezone":"Africa/Cairo",
    "iso:country":"EG",
    "name:ara_x_preferred":[
        "\u0639\u0632\u0628\u0629 \u062c\u0645\u064a\u0644\u0629"
    ],
    "name:und_x_variant":[
        "\u2018Izbat Jam\u012blah"
    ],
    "wof:name":"`Izbat Jamilah",
    "wof:placetype":"locality"
},
  "geometry": {"coordinates":[31.06465,31.00617],"type":"Point"}
}