{
  "type": "Feature",
  "properties": {
    "gn:admin1_code":"24",
    "gn:asciiname":"Naj` Hashim",
    "gn:country_code":"EG",
    "gn:dem":66,
    "gn:feature_class":"P",
    "gn:feature_code":"PPL",
    "gn:name":"Naj\u2018 H\u0101shim",
    "gn:population":0,
    "gn:timezone":"Africa/Cairo",
    "iso:country":"EG",
    "wof:name":"Naj` Hashim",
    "wof:placetype":"locality"
},
  "geometry": {"coordinates":[31.91667,26.35],"type":"Point"}
}