{
  "type": "Feature",
  "properties": {
    "gn:admin1_code":"14",
    "gn:asciiname":"Kafr Ikyad",
    "gn:country_code":"EG",
    "gn:dem":13,
    "gn:feature_class":"P",
    "gn:feature_code":"PPL",
    "gn:name":"Kafr Iky\u0101d",
    "gn:population":0,
    "gn:timezone":"Africa/Cairo",
    "iso:country":"EG",
    "name:ara_x_preferred":[
        "\u0643\u0641\u0631 \u0625\u0643\u064a\u0627\u062f"
    ],
    "name:und_x_variant":[
        "Kafr Iky\u0101d"
    ],
    "wof:name":"Kafr Ikyad",
    "wof:placetype":"locality"
},
  "geometry": {"coordinates":[31.50274000000001,30.45436],"type":"Point"}
}