{
  "type": "Feature",
  "properties": {
    "gn:admin1_code":"12",
    "gn:asciiname":"`Izbat `Ali `Atiyah",
    "gn:country_code":"EG",
    "gn:dem":16,
    "gn:feature_class":"P",
    "gn:feature_code":"PPL",
    "gn:name":"\u2018Izbat \u2018Al\u012b \u2018A\u0163\u012byah",
    "gn:population":0,
    "gn:timezone":"Africa/Cairo",
    "iso:country":"EG",
    "name:ara_x_preferred":[
        "\u0639\u0632\u0628\u0629 \u0639\u0644\u064a \u0639\u0637\u0628\u0629"
    ],
    "name:und_x_variant":[
        "\u2018Izbat \u2018Al\u012b \u2018A\u0163\u012byah"
    ],
    "wof:name":"`Izbat `Ali `Atiyah",
    "wof:placetype":"locality"
},
  "geometry": {"coordinates":[31.1814,30.5056],"type":"Point"}
}