{
  "type": "Feature",
  "properties": {
    "gn:gn_country":"EG",
    "gn:gn_fcode":"PPLX",
    "gn:gn_pop":0,
    "iso:country":"EG",
    "name:ara_x_preferred":[
        "B\u016blkil\u012b"
    ],
    "name:ara_x_variant":[
        "\u0628\u0648\u0644\u0643\u0644\u064a"
    ],
    "name:ceb_x_preferred":[
        "Bulkeley"
    ],
    "name:eng_x_preferred":[
        "Bulkeley"
    ],
    "name:fra_x_preferred":[
        "Bulkeley"
    ],
    "name:pol_x_preferred":[
        "Bulkeley"
    ],
    "name:swe_x_preferred":[
        "Bulkeley"
    ],
    "name:unk_x_variant":[
        "Bulkeley"
    ],
    "qs:gn_fcode":"PPLX",
    "qs:gn_local":0,
    "qs:gn_namadm1":"06",
    "qs:gn_name":"Bulkeley",
    "qs:local_max":1580,
    "qs:local_sum":9759,
    "qs:localhoods":18,
    "qs:name":"Bulkeley",
    "qs:name_adm0":"\u0645\u0635\u0631",
    "qs:name_adm1":"\u0627\u0644\u0627\u0633\u0643\u0646\u062f\u0631\u064a\u0629",
    "qs:name_local":"\u0627\u0644\u0627\u0633\u0643\u0646\u062f\u0631\u064a\u0629",
    "qs:photo_max":134,
    "qs:photo_sum":1083,
    "qs:placetype":"Suburb",
    "qs:quad_count":34,
    "qs:woe_adm0":23424802,
    "qs:woe_adm1":2345228,
    "qs:woe_adm2":0,
    "qs:woe_lau":0,
    "qs:woe_local":1522006,
    "qs:woe_ver":"7.10.0",
    "qs_pg:aaroncc":"EG",
    "qs_pg:gn_country":"EG",
    "qs_pg:gn_fcode":"PPLX",
    "qs_pg:gn_pop":0,
    "qs_pg:name":"Bulkeley",
    "qs_pg:name_adm0":"\u0645\u0635\u0631",
    "qs_pg:name_adm1":"\u0627\u0644\u0627\u0633\u0643\u0646\u062f\u0631\u064a\u0629",
    "qs_pg:photos":797,
    "qs_pg:photos_1k":161,
    "qs_pg:photos_9k":4,
    "qs_pg:photos_9r":6,
    "qs_pg:photos_all":797,
    "qs_pg:photos_sr":9,
    "qs_pg:pop_sr":0,
    "qs_pg:qs_pg_placetype":"neighbourhood",
    "qs_pg:qs_pg_placetype_gp":"Suburb",
    "qs_pg:woe_adm0":23424802,
    "wd:wordcount":950,
    "wof:lang":[
        "eng"
    ],
    "wof:name":"Bulkeley",
    "wof:placetype":"neighbourhood"
},
  "geometry": {"coordinates":[29.947181,31.228166],"type":"Point"}
}