{
  "type": "Feature",
  "properties": {
    "gn:admin1_code":"04",
    "gn:asciiname":"`Ezbet Mahmud `Ali `Arafa",
    "gn:country_code":"EG",
    "gn:dem":12,
    "gn:feature_class":"P",
    "gn:feature_code":"PPL",
    "gn:name":"\u2018Ezbet Mahm\u00fbd \u2018Ali \u2018Arafa",
    "gn:population":0,
    "gn:timezone":"Africa/Cairo",
    "iso:country":"EG",
    "wof:name":"`Ezbet Mahmud `Ali `Arafa",
    "wof:placetype":"locality"
},
  "geometry": {"coordinates":[30.96982,29.55163],"type":"Point"}
}