{
  "type": "Feature",
  "properties": {
    "gn:admin1_code":"21",
    "gn:asciiname":"`Izbat al Hawwah",
    "gn:country_code":"EG",
    "gn:dem":5,
    "gn:feature_class":"P",
    "gn:feature_code":"PPL",
    "gn:name":"\u2018Izbat al \u1e28awwah",
    "gn:population":0,
    "gn:timezone":"Africa/Cairo",
    "iso:country":"EG",
    "name:ara_x_preferred":[
        "\u0639\u0632\u0628\u0629 \u0627\u0644\u062d\u0648\u0629"
    ],
    "name:und_x_variant":[
        "\u2018Izbat al \u1e28awwah",
        "\u2018Izbat al-\u1e24awwah"
    ],
    "wof:name":"`Izbat al Hawwah",
    "wof:placetype":"locality"
},
  "geometry": {"coordinates":[31.23212,31.23004],"type":"Point"}
}