{
  "type": "Feature",
  "properties": {
    "gn:admin1_code":"10",
    "gn:asciiname":"Hur",
    "gn:country_code":"EG",
    "gn:dem":48,
    "gn:feature_class":"P",
    "gn:feature_code":"PPL",
    "gn:name":"H\u016br",
    "gn:population":0,
    "gn:timezone":"Africa/Cairo",
    "iso:country":"EG",
    "name:ceb_x_preferred":[
        "Hur"
    ],
    "name:fas_x_preferred":[
        "\u062d\u0648\u0631"
    ],
    "name:slk_x_preferred":[
        "Hur"
    ],
    "name:swe_x_preferred":[
        "Hur"
    ],
    "name:und_x_variant":[
        "Hawr",
        "H\u00f4r",
        "H\u016br"
    ],
    "wof:name":"Hur",
    "wof:placetype":"locality"
},
  "geometry": {"coordinates":[30.73277,27.85966],"type":"Point"}
}