{
  "type": "Feature",
  "properties": {
    "gn:admin1_code":"18",
    "gn:asciiname":"Ihnasya al Madinah",
    "gn:country_code":"EG",
    "gn:dem":30,
    "gn:feature_class":"P",
    "gn:feature_code":"PPL",
    "gn:name":"Ihn\u0101sy\u0101 al Mad\u012bnah",
    "gn:population":0,
    "gn:timezone":"Africa/Cairo",
    "iso:country":"EG",
    "name:und_x_variant":[
        "H\u0113rakleouspolis Megal\u00e9",
        "Ihnasya el Mad\u00eena",
        "Heracleopolis Magna",
        "Ihn\u0101siyat al Mad\u012bnah",
        "Ihn\u0101syat al Mad\u012bnah",
        "Ihn\u0101sy\u0101 al Mad\u012bnah"
    ],
    "wof:name":"Ihnasya al Madinah",
    "wof:placetype":"locality"
},
  "geometry": {"coordinates":[30.94319,29.0895],"type":"Point"}
}