{
  "type": "Feature",
  "properties": {
    "gn:admin1_code":"01",
    "gn:asciiname":"Mit `Abbad",
    "gn:country_code":"EG",
    "gn:dem":9,
    "gn:feature_class":"P",
    "gn:feature_code":"PPL",
    "gn:name":"M\u00eet \u2018Abb\u00e2d",
    "gn:population":0,
    "gn:timezone":"Africa/Cairo",
    "iso:country":"EG",
    "wof:name":"Mit `Abbad",
    "wof:placetype":"locality"
},
  "geometry": {"coordinates":[31.24917,31.06694],"type":"Point"}
}