{
  "type": "Feature",
  "properties": {
    "gn:admin1_code":"17",
    "gn:asciiname":"Al Fayama'",
    "gn:country_code":"EG",
    "gn:dem":56,
    "gn:feature_class":"P",
    "gn:feature_code":"PPL",
    "gn:name":"Al Fayam\u0101\u2019",
    "gn:population":0,
    "gn:timezone":"Africa/Cairo",
    "iso:country":"EG",
    "name:und_x_variant":[
        "El Fayama",
        "Al Fayam\u0101\u2019"
    ],
    "wof:name":"Al Fayama'",
    "wof:placetype":"locality"
},
  "geometry": {"coordinates":[31.23703,27.22266],"type":"Point"}
}