{
  "type": "Feature",
  "properties": {
    "gn:admin1_code":"14",
    "gn:asciiname":"Kafr Sur at Tall",
    "gn:cc2":"EG",
    "gn:country_code":"EG",
    "gn:dem":13,
    "gn:feature_class":"P",
    "gn:feature_code":"PPL",
    "gn:name":"Kafr S\u016br at Tall",
    "gn:population":0,
    "gn:timezone":"Africa/Cairo",
    "iso:country":"EG",
    "name:und_x_variant":[
        "Kafr S\u00fbr el Tall",
        "Kafr S\u016br at Tall"
    ],
    "wof:name":"Kafr Sur at Tall",
    "wof:placetype":"locality"
},
  "geometry": {"coordinates":[31.66667,30.48333],"type":"Point"}
}