{
  "type": "Feature",
  "properties": {
    "gn:admin1_code":"21",
    "gn:asciiname":"`Izbat Abu `Abd Allah",
    "gn:country_code":"EG",
    "gn:dem":5,
    "gn:feature_class":"P",
    "gn:feature_code":"PPL",
    "gn:name":"\u2018Izbat Ab\u016b \u2018Abd All\u0101h",
    "gn:population":0,
    "gn:timezone":"Africa/Cairo",
    "iso:country":"EG",
    "name:ara_x_preferred":[
        "\u0639\u0632\u0628\u0629 \u0623\u0628\u0648 \u0639\u0628\u062f \u0627\u0644\u0644\u0647"
    ],
    "name:und_x_variant":[
        "\u2018Izbat Ab\u016b \u2018Abd All\u0101h"
    ],
    "wof:name":"`Izbat Abu `Abd Allah",
    "wof:placetype":"locality"
},
  "geometry": {"coordinates":[30.87838,31.27475],"type":"Point"}
}