{
  "type": "Feature",
  "properties": {
    "gn:admin1_code":"09",
    "gn:asciiname":"Kafr ash Shaykh Ibrahim",
    "gn:country_code":"EG",
    "gn:dem":16,
    "gn:feature_class":"P",
    "gn:feature_code":"PPL",
    "gn:name":"Kafr ash Shaykh Ibr\u0101h\u012bm",
    "gn:population":0,
    "gn:timezone":"Africa/Cairo",
    "iso:country":"EG",
    "name:ara_x_preferred":[
        "\u0643\u0641\u0631 \u0627\u0644\u0634\u064a\u062e \u0627\u0628\u0631\u0627\u0647\u064a\u0645"
    ],
    "name:und_x_variant":[
        "Kafr el Sheikh Ibr\u00e2h\u00eem",
        "Kafr ash Shaykh Ibr\u0101h\u012bm"
    ],
    "wof:name":"Kafr ash Shaykh Ibrahim",
    "wof:placetype":"locality"
},
  "geometry": {"coordinates":[31.14333,30.5278],"type":"Point"}
}