{
  "type": "Feature",
  "properties": {
    "gn:admin1_code":"08",
    "gn:asciiname":"Nag` `Arab Muhammad Abu Kamil",
    "gn:country_code":"EG",
    "gn:dem":27,
    "gn:feature_class":"P",
    "gn:feature_code":"PPL",
    "gn:name":"Nag\u2018 \u2018Arab Mu\u1e25ammad Abu K\u00e2mil",
    "gn:population":0,
    "gn:timezone":"Africa/Cairo",
    "iso:country":"EG",
    "wof:name":"Nag` `Arab Muhammad Abu Kamil",
    "wof:placetype":"locality"
},
  "geometry": {"coordinates":[31.26667,29.46667],"type":"Point"}
}