{
  "type": "Feature",
  "properties": {
    "gn:admin1_code":"17",
    "gn:asciiname":"Sanabu",
    "gn:country_code":"EG",
    "gn:dem":55,
    "gn:feature_class":"P",
    "gn:feature_code":"PPL",
    "gn:name":"\u015eanab\u016b",
    "gn:population":0,
    "gn:timezone":"Africa/Cairo",
    "iso:country":"EG",
    "name:ara_x_preferred":[
        "\u0635\u0646\u0628\u0648"
    ],
    "name:und_x_variant":[
        "Sanbu",
        "\u015eanab\u016b"
    ],
    "wof:name":"Sanabu",
    "wof:placetype":"locality"
},
  "geometry": {"coordinates":[30.78975,27.49353],"type":"Point"}
}