{
  "type": "Feature",
  "properties": {
    "gn:admin1_code":"17",
    "gn:asciiname":"Dayrut ash Sharif",
    "gn:country_code":"EG",
    "gn:dem":55,
    "gn:feature_class":"P",
    "gn:feature_code":"PPL",
    "gn:name":"Dayr\u016b\u0163 ash Shar\u012bf",
    "gn:population":0,
    "gn:timezone":"Africa/Cairo",
    "iso:country":"EG",
    "name:und_x_variant":[
        "Dair\u016bt esh Shar\u012bf",
        "Dair\u00fb\u1e6d el Shir\u00eef",
        "Dayr\u016b\u0163 ash Shar\u012bf"
    ],
    "wof:name":"Dayrut ash Sharif",
    "wof:placetype":"locality"
},
  "geometry": {"coordinates":[30.81717,27.58357],"type":"Point"}
}