{
  "type": "Feature",
  "properties": {
    "gn:admin1_code":"12.0",
    "gn:asciiname":"Zufaytat Mashtul",
    "gn:country_code":"EG",
    "gn:dem":17,
    "gn:feature_class":"P",
    "gn:feature_code":"PPL",
    "gn:name":"Zufaytat Masht\u016bl",
    "gn:population":0,
    "gn:timezone":"Africa/Cairo",
    "iso:country":"EG",
    "name:und_x_variant":[
        "Masht\u016bl",
        "Zifeitet Masht\u00fbl",
        "Zufaytat Masht\u016bl"
    ],
    "wof:name":"Zufaytat Mashtul",
    "wof:placetype":"locality"
},
  "geometry": {"coordinates":[31.35963,30.32447],"type":"Point"}
}