{
  "type": "Feature",
  "properties": {
    "gn:admin1_code":"05",
    "gn:asciiname":"`Izbat Muhammad wa `Abd al Mun`im Wahbi",
    "gn:country_code":"EG",
    "gn:dem":7,
    "gn:feature_class":"P",
    "gn:feature_code":"PPL",
    "gn:name":"\u2018Izbat Mu\u1e29ammad wa \u2018Abd al Mun\u2018im Wahb\u012b",
    "gn:population":0,
    "gn:timezone":"Africa/Cairo",
    "iso:country":"EG",
    "name:ara_x_preferred":[
        "\u0639\u0632\u0628\u0629 \u0645\u062d\u0645\u062f \u0648 \u0639\u0628\u062f \u0627\u0644\u0645\u0646\u0639\u0645 \u0648\u0647\u0628\u064a"
    ],
    "name:und_x_variant":[
        "\u2018Izbat Mu\u1e29ammad wa \u2018Abd al Mun\u2018im Wahb\u012b",
        "\u2018Ezbet Muhammad",
        "\u2018Izbat Mu\u1e25ammad & \u2018Abd al-Mun\u2018im Wahb\u012b"
    ],
    "wof:name":"`Izbat Muhammad wa `Abd al Mun`im Wahbi",
    "wof:placetype":"locality"
},
  "geometry": {"coordinates":[31.01699,30.98713],"type":"Point"}
}