{
  "type": "Feature",
  "properties": {
    "gn:admin1_code":"17",
    "gn:asciiname":"Kawm Injashah",
    "gn:country_code":"EG",
    "gn:dem":57,
    "gn:feature_class":"P",
    "gn:feature_code":"PPL",
    "gn:name":"Kawm Inj\u0101shah",
    "gn:population":0,
    "gn:timezone":"Africa/Cairo",
    "iso:country":"EG",
    "name:und_x_variant":[
        "K\u00f4m Ing\u00e2sha",
        "Kawm Inj\u0101shah"
    ],
    "wof:name":"Kawm Injashah",
    "wof:placetype":"locality"
},
  "geometry": {"coordinates":[30.74964000000001,27.5514],"type":"Point"}
}