{
  "type": "Feature",
  "properties": {
    "gn:admin1_code":"01",
    "gn:asciiname":"`Izbat Sulayt",
    "gn:country_code":"EG",
    "gn:dem":7,
    "gn:feature_class":"P",
    "gn:feature_code":"PPL",
    "gn:name":"\u2018Izbat Sulay\u0163",
    "gn:population":0,
    "gn:timezone":"Africa/Cairo",
    "iso:country":"EG",
    "name:ara_x_preferred":[
        "\u0639\u0632\u0628\u0629 \u0633\u0644\u064a\u062a"
    ],
    "name:und_x_variant":[
        "\u2018Izbat Sulay\u0163",
        "\u2018Izbat Silay\u0163"
    ],
    "wof:name":"`Izbat Sulayt",
    "wof:placetype":"locality"
},
  "geometry": {"coordinates":[31.56055,30.85458],"type":"Point"}
}