{
  "type": "Feature",
  "properties": {
    "gn:admin1_code":"14",
    "gn:asciiname":"`Izbat ar Raghlah",
    "gn:country_code":"EG",
    "gn:dem":8,
    "gn:feature_class":"P",
    "gn:feature_code":"PPL",
    "gn:name":"\u2018Izbat ar Raghlah",
    "gn:population":0,
    "gn:timezone":"Africa/Cairo",
    "iso:country":"EG",
    "name:ara_x_preferred":[
        "\u0639\u0632\u0628\u0629 \u0627\u0644\u0631\u063a\u0644\u0629"
    ],
    "name:und_x_variant":[
        "\u2018Izbat ar Raghlah"
    ],
    "wof:name":"`Izbat ar Raghlah",
    "wof:placetype":"locality"
},
  "geometry": {"coordinates":[31.7013,30.80199],"type":"Point"}
}