{
  "type": "Feature",
  "properties": {
    "gn:admin1_code":"14",
    "gn:asciiname":"Al Kilaniyah",
    "gn:country_code":"EG",
    "gn:dem":12,
    "gn:feature_class":"P",
    "gn:feature_code":"PPL",
    "gn:name":"Al K\u012bl\u0101n\u012byah",
    "gn:population":0,
    "gn:timezone":"Africa/Cairo",
    "iso:country":"EG",
    "name:ara_x_preferred":[
        "\u0627\u0644\u0643\u064a\u0644\u0627\u0646\u064a\u0629"
    ],
    "name:und_x_variant":[
        "Kafr el-K\u00eel\u00e2n\u00eeya",
        "Al K\u012bl\u0101n\u012byah",
        "Al-K\u012bl\u0101niyyah"
    ],
    "wof:name":"Al Kilaniyah",
    "wof:placetype":"locality"
},
  "geometry": {"coordinates":[31.78558,30.70681],"type":"Point"}
}