{
  "type": "Feature",
  "properties": {
    "gn:admin1_code":"09",
    "gn:asciiname":"Saft Jidam",
    "gn:country_code":"EG",
    "gn:dem":10,
    "gn:feature_class":"P",
    "gn:feature_code":"PPL",
    "gn:name":"\u015eaf\u0163 Jid\u0101m",
    "gn:population":0,
    "gn:timezone":"Africa/Cairo",
    "iso:country":"EG",
    "name:und_x_variant":[
        "\u015eaf\u0163 Judh\u0101m",
        "\u015eaf\u0163 Jid\u0101m"
    ],
    "wof:name":"Saft Jidam",
    "wof:placetype":"locality"
},
  "geometry": {"coordinates":[30.86402,30.69391],"type":"Point"}
}