{
  "type": "Feature",
  "properties": {
    "gn:admin1_code":"09",
    "gn:asciiname":"`Izbat Makhali",
    "gn:country_code":"EG",
    "gn:dem":15,
    "gn:feature_class":"P",
    "gn:feature_code":"PPL",
    "gn:name":"\u2018Izbat Makh\u0101l\u012b",
    "gn:population":0,
    "gn:timezone":"Africa/Cairo",
    "iso:country":"EG",
    "name:ara_x_preferred":[
        "\u0639\u0632\u0628\u0629 \u0645\u062e\u0627\u0644\u064a"
    ],
    "name:und_x_variant":[
        "\u2018Izbat Makh\u0101l\u012b"
    ],
    "wof:name":"`Izbat Makhali",
    "wof:placetype":"locality"
},
  "geometry": {"coordinates":[30.93641,30.39433],"type":"Point"}
}