{
  "type": "Feature",
  "properties": {
    "gn:admin1_code":"14",
    "gn:asciiname":"Bahnabay",
    "gn:country_code":"EG",
    "gn:dem":14,
    "gn:feature_class":"P",
    "gn:feature_code":"PPL",
    "gn:name":"Bahn\u0101b\u0101y",
    "gn:population":0,
    "gn:timezone":"Africa/Cairo",
    "iso:country":"EG",
    "name:ara_x_preferred":[
        "\u0628\u0647\u0646\u0627\u0628\u0627\u064a"
    ],
    "name:und_x_variant":[
        "Bahn\u00e2b\u00e2i",
        "Bahn\u0101b\u0101y"
    ],
    "wof:name":"Bahnabay",
    "wof:placetype":"locality"
},
  "geometry": {"coordinates":[31.47429,30.65437],"type":"Point"}
}