{
  "type": "Feature",
  "properties": {
    "gn:admin1_code":"14",
    "gn:asciiname":"`Izbat Nimr",
    "gn:country_code":"EG",
    "gn:dem":10,
    "gn:feature_class":"P",
    "gn:feature_code":"PPL",
    "gn:name":"\u2018Izbat Nimr",
    "gn:population":0,
    "gn:timezone":"Africa/Cairo",
    "iso:country":"EG",
    "name:ara_x_preferred":[
        "\u0639\u0632\u0628\u0629 \u0646\u0645\u0631"
    ],
    "name:und_x_variant":[
        "\u2018Izbat Nimr"
    ],
    "wof:name":"`Izbat Nimr",
    "wof:placetype":"locality"
},
  "geometry": {"coordinates":[31.69113,30.70314],"type":"Point"}
}