{
  "type": "Feature",
  "properties": {
    "gn:admin1_code":"24",
    "gn:asciiname":"Salim ash Sharqiyah",
    "gn:cc2":"EG",
    "gn:country_code":"EG",
    "gn:dem":58,
    "gn:feature_class":"P",
    "gn:feature_code":"PPL",
    "gn:name":"Sal\u012bm ash Sharq\u012byah",
    "gn:population":0,
    "gn:timezone":"Africa/Cairo",
    "iso:country":"EG",
    "name:und_x_variant":[
        "Sil\u00eem el Sharq\u00eeya",
        "Sal\u012bm ash Sharq\u012byah"
    ],
    "wof:name":"Salim ash Sharqiyah",
    "wof:placetype":"locality"
},
  "geometry": {"coordinates":[31.41667,26.85],"type":"Point"}
}