{
  "type": "Feature",
  "properties": {
    "gn:admin1_code":"01",
    "gn:asciiname":"Kafr `Abd al Mu'min",
    "gn:country_code":"EG",
    "gn:dem":10,
    "gn:feature_class":"P",
    "gn:feature_code":"PPL",
    "gn:name":"Kafr \u2018Abd al Mu\u2019min",
    "gn:population":0,
    "gn:timezone":"Africa/Cairo",
    "iso:country":"EG",
    "name:ara_x_preferred":[
        "\u0643\u0641\u0631 \u0639\u0628\u062f \u0627\u0644\u0645\u0624\u0645\u0646"
    ],
    "name:und_x_variant":[
        "Kafr \u2018Abd el-Mu\u2019min",
        "Kafr \u2018Abd al Mu\u2019min",
        "Kafr \u2018Abd al-Mu\u2019min"
    ],
    "wof:name":"Kafr `Abd al Mu'min",
    "wof:placetype":"locality"
},
  "geometry": {"coordinates":[31.5107,31.08176],"type":"Point"}
}