{
  "type": "Feature",
  "properties": {
    "gn:admin1_code":"21",
    "gn:asciiname":"`Izbat Ahmad al `Isawi",
    "gn:country_code":"EG",
    "gn:dem":6,
    "gn:feature_class":"P",
    "gn:feature_code":"PPL",
    "gn:name":"\u2018Izbat A\u1e29mad al \u2018\u012asaw\u012b",
    "gn:population":0,
    "gn:timezone":"Africa/Cairo",
    "iso:country":"EG",
    "name:ara_x_preferred":[
        "\u0639\u0632\u0628\u0629 \u0623\u062d\u0645\u062f \u0627\u0644\u0639\u064a\u0633\u0648\u0649"
    ],
    "name:und_x_variant":[
        "\u2018Izbat A\u1e29mad al \u2018\u012asaw\u012b",
        "\u2018Izbat A\u1e25mad al-\u2018\u012asaw\u012b"
    ],
    "wof:name":"`Izbat Ahmad al `Isawi",
    "wof:placetype":"locality"
},
  "geometry": {"coordinates":[30.89313,31.12792],"type":"Point"}
}