{
  "type": "Feature",
  "properties": {
    "gn:admin1_code":"14",
    "gn:asciiname":"`Izbat Abu Hajar",
    "gn:country_code":"EG",
    "gn:dem":11,
    "gn:feature_class":"P",
    "gn:feature_code":"PPL",
    "gn:name":"\u2018Izbat Ab\u016b \u1e28ajar",
    "gn:population":0,
    "gn:timezone":"Africa/Cairo",
    "iso:country":"EG",
    "name:ara_x_preferred":[
        "\u0639\u0632\u0628\u0629 \u0623\u0628\u0648 \u062d\u062c\u0631"
    ],
    "name:und_x_variant":[
        "\u2018Izbat Ab\u016b \u1e28ajar"
    ],
    "wof:name":"`Izbat Abu Hajar",
    "wof:placetype":"locality"
},
  "geometry": {"coordinates":[31.68897,30.59577],"type":"Point"}
}