{
  "type": "Feature",
  "properties": {
    "gn:admin1_code":"05",
    "gn:asciiname":"Balkim",
    "gn:country_code":"EG",
    "gn:dem":13,
    "gn:feature_class":"P",
    "gn:feature_code":"PPL",
    "gn:name":"Balk\u012bm",
    "gn:population":0,
    "gn:timezone":"Africa/Cairo",
    "iso:country":"EG",
    "name:ara_x_preferred":[
        "\u0628\u0644\u0643\u064a\u0645"
    ],
    "name:und_x_variant":[
        "Balk\u00eem",
        "Balk\u012bm"
    ],
    "wof:name":"Balkim",
    "wof:placetype":"locality"
},
  "geometry": {"coordinates":[31.10627,30.75191],"type":"Point"}
}