{
  "type": "Feature",
  "properties": {
    "gn:admin1_code":"03",
    "gn:asciiname":"`Izbat al Marsa",
    "gn:country_code":"EG",
    "gn:dem":-2,
    "gn:feature_class":"P",
    "gn:feature_code":"PPL",
    "gn:name":"\u2018Izbat al Mars\u00e1",
    "gn:population":0,
    "gn:timezone":"Africa/Cairo",
    "iso:country":"EG",
    "name:ara_x_preferred":[
        "\u0639\u0632\u0628\u0629 \u0627\u0644\u0645\u0631\u0633\u0649"
    ],
    "name:und_x_variant":[
        "Al Mars\u00e1",
        "\u2018Ezbet Far\u00eed B\u00e2n\u00fbb",
        "\u2018Azbat Far\u012bd B\u0101n\u016bb",
        "\u2018Izbat Far\u012bd B\u0101n\u016bb",
        "\u2018Izbat al Mars\u00e1"
    ],
    "wof:name":"`Izbat al Marsa",
    "wof:placetype":"locality"
},
  "geometry": {"coordinates":[30.08843,31.07933],"type":"Point"}
}