{
  "type": "Feature",
  "properties": {
    "gn:admin1_code":"01",
    "gn:asciiname":"`Izbat Sa`d Butrus",
    "gn:country_code":"EG",
    "gn:dem":8,
    "gn:feature_class":"P",
    "gn:feature_code":"PPL",
    "gn:name":"\u2018Izbat Sa\u2018d Bu\u0163rus",
    "gn:population":0,
    "gn:timezone":"Africa/Cairo",
    "iso:country":"EG",
    "name:und_x_variant":[
        "\u2018Izbat Sa\u2018d Bu\u0163rus",
        "\u0639\u0632\u0628\u0629 \u0633\u0639\u062f \u0628\u0637\u0631\u0633",
        "\u2018Iz. Sa\u2018d Bu\u1e6drus"
    ],
    "wof:name":"`Izbat Sa`d Butrus",
    "wof:placetype":"locality"
},
  "geometry": {"coordinates":[31.44981,30.82266],"type":"Point"}
}