{
  "type": "Feature",
  "properties": {
    "gn:gn_country":"EG",
    "gn:gn_fcode":"PPL",
    "gn:gn_pop":129211,
    "gn:population":129211,
    "iso:country":"EG",
    "name:ara_x_preferred":[
        "\u0628\u0644\u0628\u064a\u0633"
    ],
    "name:bul_x_preferred":[
        "\u0411\u0438\u043b\u0431\u0430\u0439\u0441"
    ],
    "name:cat_x_preferred":[
        "Bilbeis"
    ],
    "name:ces_x_preferred":[
        "Bilbajs"
    ],
    "name:deu_x_preferred":[
        "Bilbeis"
    ],
    "name:ell_x_preferred":[
        "\u039c\u03c0\u03b9\u03bc\u03c0\u03ac\u03b9\u03c2"
    ],
    "name:eng_x_preferred":[
        "Bilbeis"
    ],
    "name:fas_x_preferred":[
        "\u0628\u0644\u0628\u06cc\u0633"
    ],
    "name:fra_x_preferred":[
        "Bilb\u00e9is"
    ],
    "name:heb_x_preferred":[
        "\u05d1\u05d9\u05dc\u05d1\u05d9\u05e1"
    ],
    "name:hye_x_preferred":[
        "\u0532\u056b\u056c\u0562\u0565\u0575\u057d"
    ],
    "name:ita_x_preferred":[
        "Bilbeis"
    ],
    "name:jpn_x_preferred":[
        "\u30d3\u30eb\u30d9\u30fc\u30b9"
    ],
    "name:kaz_x_preferred":[
        "\u0411\u0438\u043b\u044c\u0431\u0435\u0439\u0441"
    ],
    "name:kor_x_preferred":[
        "\ube4c\ubca0\uc774\uc2a4"
    ],
    "name:lav_x_preferred":[
        "Bilbeisa"
    ],
    "name:nld_x_preferred":[
        "Bilbeis"
    ],
    "name:nob_x_preferred":[
        "Bilbays"
    ],
    "name:pol_x_preferred":[
        "Bilbajs"
    ],
    "name:por_x_preferred":[
        "Bilbeis"
    ],
    "name:rus_x_preferred":[
        "\u0411\u0438\u043b\u044c\u0431\u0435\u0439\u0441"
    ],
    "name:sco_x_preferred":[
        "Bilbeis"
    ],
    "name:srp_x_preferred":[
        "\u0411\u0438\u043b\u0431\u0435\u0458\u0441"
    ],
    "name:swe_x_preferred":[
        "Bilbays"
    ],
    "name:tur_x_preferred":[
        "Bilbeys"
    ],
    "name:ukr_x_preferred":[
        "\u0411\u0456\u043b\u044c\u0431\u0435\u0439\u0441"
    ],
    "name:unk_x_variant":[
        "Bilbeis"
    ],
    "name:urd_x_preferred":[
        "\u0628\u0644\u0628\u06cc\u0633"
    ],
    "name:zho_x_preferred":[
        "\u6bd4\u52d2\u62dc\u65af"
    ],
    "qs_pg:aaroncc":"EG",
    "qs_pg:gn_country":"EG",
    "qs_pg:gn_fcode":"PPL",
    "qs_pg:gn_pop":129211,
    "qs_pg:name":"Bilbays",
    "qs_pg:photos_9r":0,
    "qs_pg:photos_sr":0,
    "qs_pg:pop_sr":9,
    "qs_pg:qs_pg_placetype":"locality",
    "wof:name":"Bilbays",
    "wof:placetype":"locality",
    "wof:population":129211
},
  "geometry": {"coordinates":[31.56223,30.42039],"type":"Point"}
}