{
  "type": "Feature",
  "properties": {
    "gn:admin1_code":"18",
    "gn:asciiname":"Sarabu",
    "gn:country_code":"EG",
    "gn:dem":31,
    "gn:feature_class":"P",
    "gn:feature_code":"PPL",
    "gn:name":"Sarab\u016b",
    "gn:population":0,
    "gn:timezone":"Africa/Cairo",
    "iso:country":"EG",
    "wof:name":"Sarabu",
    "wof:placetype":"locality"
},
  "geometry": {"coordinates":[30.8432,28.94633],"type":"Point"}
}