{
  "type": "Feature",
  "properties": {
    "gn:admin1_code":"06",
    "gn:asciiname":"Qaryah Wahid/Sab`ah",
    "gn:country_code":"EG",
    "gn:dem":-2,
    "gn:feature_class":"P",
    "gn:feature_code":"PPL",
    "gn:name":"Qaryah W\u0101hid/Sab\u2018ah",
    "gn:population":0,
    "gn:timezone":"Africa/Cairo",
    "iso:country":"EG",
    "name:ara_x_preferred":[
        "\u0642\u0631\u064a\u0629 \u0667/\u0661"
    ],
    "name:und_x_variant":[
        "Qaryah W\u0101hid/Sab\u2018ah",
        "Qaryah 1/7"
    ],
    "wof:name":"Qaryah Wahid/Sab`ah",
    "wof:placetype":"locality"
},
  "geometry": {"coordinates":[29.97404,31.14685],"type":"Point"}
}