{
  "type": "Feature",
  "properties": {
    "gn:admin1_code":"20",
    "gn:asciiname":"`Izbat al Kashif",
    "gn:country_code":"EG",
    "gn:dem":4,
    "gn:feature_class":"P",
    "gn:feature_code":"PPL",
    "gn:name":"\u2018Izbat al K\u0101shif",
    "gn:population":0,
    "gn:timezone":"Africa/Cairo",
    "iso:country":"EG",
    "name:ara_x_preferred":[
        "\u0639\u0632\u0628\u0629 \u0627\u0644\u0643\u0627\u0634\u0641"
    ],
    "name:und_x_variant":[
        "\u2018Izbat al K\u0101shif",
        "\u2018Iz. al-K\u0101shif"
    ],
    "wof:name":"`Izbat al Kashif",
    "wof:placetype":"locality"
},
  "geometry": {"coordinates":[31.67874,31.24616],"type":"Point"}
}