{
  "type": "Feature",
  "properties": {
    "gn:admin1_code":"14",
    "gn:asciiname":"Kafr an Naja'irah",
    "gn:country_code":"EG",
    "gn:dem":6,
    "gn:feature_class":"P",
    "gn:feature_code":"PPL",
    "gn:name":"Kafr an Naj\u0101\u2019irah",
    "gn:population":0,
    "gn:timezone":"Africa/Cairo",
    "iso:country":"EG",
    "name:und_x_variant":[
        "Kafr el-Nag\u00e2yra",
        "Kafr an Naj\u0101\u2019irah"
    ],
    "wof:name":"Kafr an Naja'irah",
    "wof:placetype":"locality"
},
  "geometry": {"coordinates":[31.83333,30.68333],"type":"Point"}
}