{
  "type": "Feature",
  "properties": {
    "gn:admin1_code":"18",
    "gn:asciiname":"Jazirat al Fuqqa`i",
    "gn:country_code":"EG",
    "gn:dem":34,
    "gn:feature_class":"P",
    "gn:feature_code":"PPL",
    "gn:name":"Jaz\u012brat al Fuqq\u0101\u2018\u012b",
    "gn:population":0,
    "gn:timezone":"Africa/Cairo",
    "iso:country":"EG",
    "name:und_x_variant":[
        "Geziret el Fuqq\u00e2\u2018i",
        "Jaz\u012brat al Fuqq\u0101\u2018\u012b"
    ],
    "wof:name":"Jazirat al Fuqqa`i",
    "wof:placetype":"locality"
},
  "geometry": {"coordinates":[30.94277,28.89396],"type":"Point"}
}