{
  "type": "Feature",
  "properties": {
    "gn:admin1_code":"21",
    "gn:asciiname":"Awlad Salah",
    "gn:cc2":"EG",
    "gn:country_code":"EG",
    "gn:dem":3,
    "gn:feature_class":"P",
    "gn:feature_code":"PPL",
    "gn:name":"Awl\u0101d \u015eal\u0101\u1e29",
    "gn:population":0,
    "gn:timezone":"Africa/Cairo",
    "iso:country":"EG",
    "name:und_x_variant":[
        "Aul\u00e2d \u1e62al\u00e2\u1e25",
        "Awl\u0101d \u015eal\u0101\u1e29"
    ],
    "wof:name":"Awlad Salah",
    "wof:placetype":"locality"
},
  "geometry": {"coordinates":[31.03694,31.58194],"type":"Point"}
}