{
  "type": "Feature",
  "properties": {
    "gn:admin1_code":"03",
    "gn:asciiname":"`Ezbet el-Tawil",
    "gn:country_code":"EG",
    "gn:dem":-1,
    "gn:feature_class":"P",
    "gn:feature_code":"PPL",
    "gn:name":"\u2018Ezbet el-\u1e6caw\u00eel",
    "gn:population":0,
    "gn:timezone":"Africa/Cairo",
    "iso:country":"EG",
    "wof:name":"`Ezbet el-Tawil",
    "wof:placetype":"locality"
},
  "geometry": {"coordinates":[30.46806,31.35139],"type":"Point"}
}