{
  "type": "Feature",
  "properties": {
    "gn:admin1_code":"10",
    "gn:asciiname":"Kafr Khuzam",
    "gn:country_code":"EG",
    "gn:dem":50,
    "gn:feature_class":"P",
    "gn:feature_code":"PPL",
    "gn:name":"Kafr Khuz\u0101m",
    "gn:population":0,
    "gn:timezone":"Africa/Cairo",
    "iso:country":"EG",
    "wof:name":"Kafr Khuzam",
    "wof:placetype":"locality"
},
  "geometry": {"coordinates":[30.87174000000001,27.66498],"type":"Point"}
}