{
  "type": "Feature",
  "properties": {
    "gn:country":"EG",
    "gn:fcode":"PPL",
    "gn:population":45269,
    "iso:country":"EG",
    "qs:name":"I\u0163s\u0101",
    "qs:photos_9r":0,
    "qs:photos_sr":0,
    "qs:pop_sr":"7",
    "wof:name":"I\u0163s\u0101",
    "wof:placetype":"locality",
    "wof:population":45269
},
  "geometry": {"coordinates":[30.78944,29.2376],"type":"Point"}
}