{
  "type": "Feature",
  "properties": {
    "gn:admin1_code":"12",
    "gn:asciiname":"Kafr ash Shahawi Khatir",
    "gn:cc2":"EG",
    "gn:country_code":"EG",
    "gn:dem":15,
    "gn:feature_class":"P",
    "gn:feature_code":"PPL",
    "gn:name":"Kafr ash Shah\u0101w\u012b Kh\u0101\u0163ir",
    "gn:population":0,
    "gn:timezone":"Africa/Cairo",
    "iso:country":"EG",
    "name:und_x_variant":[
        "Kafr el-Shah\u00e2wi Kh\u00e2\u1e6dir",
        "Kafr ash Shah\u0101w\u012b Kh\u0101\u0163ir"
    ],
    "wof:name":"Kafr ash Shahawi Khatir",
    "wof:placetype":"locality"
},
  "geometry": {"coordinates":[31.26667,30.5375],"type":"Point"}
}