{
  "type": "Feature",
  "properties": {
    "gn:admin1_code":"23",
    "gn:asciiname":"Naj` Judah",
    "gn:country_code":"EG",
    "gn:dem":74,
    "gn:feature_class":"P",
    "gn:feature_code":"PPL",
    "gn:name":"Naj\u2018 J\u016bdah",
    "gn:population":0,
    "gn:timezone":"Africa/Cairo",
    "iso:country":"EG",
    "wof:name":"Naj` Judah",
    "wof:placetype":"locality"
},
  "geometry": {"coordinates":[32.79227,26.02176],"type":"Point"}
}